Workbook

Sheet DealScope pricing unit economic
A1: DealScope pricing unit economics
A2: DealScope — Pricing and sensitivity · Growth
A4: Variable / dimension | B4: Customer monthly earned revenue | C4: Customer monthly delivered audits | D4: Revenue per delivered audit | E4: Unit gross profit | F4: Unit gross margin | G4: Unit contribution profit | H4: Unit contribution margin
A5: Annual deal-team | B5: =IF(EXACT("Annual deal-team","Annual deal-team"),('Model inputs'!B45/12+MAX('Model inputs'!B14*'Model inputs'!B7-'Model inputs'!B24/12,0)*'Model inputs'!B32)*(1-'Model inputs'!B37),('Model inputs'!B45/12+'Model inputs'!B9*'Model inputs'!B14)*(1-'Model inputs'!B37)) -> 4000 | C5: ='Model inputs'!B14*IF(IF(EXACT("Annual deal-team","Annual deal-team"),IF('Model inputs'!B7="","",'Model inputs'!B7),1)="",0,IF(EXACT("Annual deal-team","Annual deal-team"),IF('Model inputs'!B7="","",'Model inputs'!B7),1)) -> 4 | D5: =IFERROR('DealScope pricing unit economic'!B5/'DealScope pricing unit economic'!C5,"") -> 1000 | E5: ='DealScope pricing unit economic'!D5-'Model inputs'!B18 -> 905.35 | F5: =IFERROR('DealScope pricing unit economic'!E5/'DealScope pricing unit economic'!D5,"") -> 0.90535 | G5: ='DealScope pricing unit economic'!E5-'DealScope pricing unit economic'!D5*'Model inputs'!B38-IFERROR('Model inputs'!B42*'Model inputs'!B41/'DealScope pricing unit economic'!C5,0) -> 867.85 | H5: =IFERROR('DealScope pricing unit economic'!G5/'DealScope pricing unit economic'!D5,"") -> 0.86785
A6: Hybrid | B6: =IF(EXACT("Hybrid","Annual deal-team"),('Model inputs'!B46/12+MAX('Model inputs'!B14*'Model inputs'!B7-'Model inputs'!B25/12,0)*'Model inputs'!B33)*(1-'Model inputs'!B37),('Model inputs'!B46/12+'Model inputs'!B10*'Model inputs'!B14)*(1-'Model inputs'!B37)) -> 4500 | C6: ='Model inputs'!B14*IF(IF(EXACT("Hybrid","Annual deal-team"),IF('Model inputs'!B7="","",'Model inputs'!B7),1)="",0,IF(EXACT("Hybrid","Annual deal-team"),IF('Model inputs'!B7="","",'Model inputs'!B7),1)) -> 4 | D6: =IFERROR('DealScope pricing unit economic'!B6/'DealScope pricing unit economic'!C6,"") -> 1125 | E6: ='DealScope pricing unit economic'!D6-'Model inputs'!B18 -> 1030.35 | F6: =IFERROR('DealScope pricing unit economic'!E6/'DealScope pricing unit economic'!D6,"") -> 0.91586667 | G6: ='DealScope pricing unit economic'!E6-'DealScope pricing unit economic'!D6*'Model inputs'!B38-IFERROR('Model inputs'!B42*'Model inputs'!B41/'DealScope pricing unit economic'!C6,0) -> 989.1 | H6: =IFERROR('DealScope pricing unit economic'!G6/'DealScope pricing unit economic'!D6,"") -> 0.8792
A7: Per audit — base | B7: =IF(EXACT("Per audit — base","Annual deal-team"),('Model inputs'!B47/12+MAX('Model inputs'!B14*'Model inputs'!B7-'Model inputs'!B26/12,0)*'Model inputs'!B34)*(1-'Model inputs'!B37),('Model inputs'!B47/12+'Model inputs'!B11*'Model inputs'!B14)*(1-'Model inputs'!B37)) -> 6000 | C7: ='Model inputs'!B14*IF(IF(EXACT("Per audit — base","Annual deal-team"),IF('Model inputs'!B7="","",'Model inputs'!B7),1)="",0,IF(EXACT("Per audit — base","Annual deal-team"),IF('Model inputs'!B7="","",'Model inputs'!B7),1)) -> 4 | D7: =IFERROR('DealScope pricing unit economic'!B7/'DealScope pricing unit economic'!C7,"") -> 1500 | E7: ='DealScope pricing unit economic'!D7-'Model inputs'!B18 -> 1405.35 | F7: =IFERROR('DealScope pricing unit economic'!E7/'DealScope pricing unit economic'!D7,"") -> 0.9369 | G7: ='DealScope pricing unit economic'!E7-'DealScope pricing unit economic'!D7*'Model inputs'!B38-IFERROR('Model inputs'!B42*'Model inputs'!B41/'DealScope pricing unit economic'!C7,0) -> 1352.85 | H7: =IFERROR('DealScope pricing unit economic'!G7/'DealScope pricing unit economic'!D7,"") -> 0.9019
A8: Per audit — high | B8: =IF(EXACT("Per audit — high","Annual deal-team"),('Model inputs'!B48/12+MAX('Model inputs'!B14*'Model inputs'!B7-'Model inputs'!B27/12,0)*'Model inputs'!B35)*(1-'Model inputs'!B37),('Model inputs'!B48/12+'Model inputs'!B12*'Model inputs'!B14)*(1-'Model inputs'!B37)) -> 12000 | C8: ='Model inputs'!B14*IF(IF(EXACT("Per audit — high","Annual deal-team"),IF('Model inputs'!B7="","",'Model inputs'!B7),1)="",0,IF(EXACT("Per audit — high","Annual deal-team"),IF('Model inputs'!B7="","",'Model inputs'!B7),1)) -> 4 | D8: =IFERROR('DealScope pricing unit economic'!B8/'DealScope pricing unit economic'!C8,"") -> 3000 | E8: ='DealScope pricing unit economic'!D8-'Model inputs'!B18 -> 2905.35 | F8: =IFERROR('DealScope pricing unit economic'!E8/'DealScope pricing unit economic'!D8,"") -> 0.96845 | G8: ='DealScope pricing unit economic'!E8-'DealScope pricing unit economic'!D8*'Model inputs'!B38-IFERROR('Model inputs'!B42*'Model inputs'!B41/'DealScope pricing unit economic'!C8,0) -> 2807.85 | H8: =IFERROR('DealScope pricing unit economic'!G8/'DealScope pricing unit economic'!D8,"") -> 0.93595
A9: Per audit — low | B9: =IF(EXACT("Per audit — low","Annual deal-team"),('Model inputs'!B49/12+MAX('Model inputs'!B14*'Model inputs'!B7-'Model inputs'!B28/12,0)*'Model inputs'!B36)*(1-'Model inputs'!B37),('Model inputs'!B49/12+'Model inputs'!B13*'Model inputs'!B14)*(1-'Model inputs'!B37)) -> 3000 | C9: ='Model inputs'!B14*IF(IF(EXACT("Per audit — low","Annual deal-team"),IF('Model inputs'!B7="","",'Model inputs'!B7),1)="",0,IF(EXACT("Per audit — low","Annual deal-team"),IF('Model inputs'!B7="","",'Model inputs'!B7),1)) -> 4 | D9: =IFERROR('DealScope pricing unit economic'!B9/'DealScope pricing unit economic'!C9,"") -> 750 | E9: ='DealScope pricing unit economic'!D9-'Model inputs'!B18 -> 655.35 | F9: =IFERROR('DealScope pricing unit economic'!E9/'DealScope pricing unit economic'!D9,"") -> 0.8738 | G9: ='DealScope pricing unit economic'!E9-'DealScope pricing unit economic'!D9*'Model inputs'!B38-IFERROR('Model inputs'!B42*'Model inputs'!B41/'DealScope pricing unit economic'!C9,0) -> 625.35 | H9: =IFERROR('DealScope pricing unit economic'!G9/'DealScope pricing unit economic'!D9,"") -> 0.8338

Sheet DealScope sensitivity controls
A1: DealScope sensitivity controls
A2: DealScope — Pricing and sensitivity · Growth
A4: Variable / dimension | B4: Sensitivity audit frequency | C4: Sensitivity discount | D4: Sensitivity data multiplier | E4: Sensitivity dollars per credit | F4: Sensitivity delay months | G4: Sensitivity allowance utilization | H4: Allowance only switch
A5: Baseline | B5: =IF('Model inputs'!B14="","",'Model inputs'!B14) -> 4 | C5: =IF('Model inputs'!B37="","",'Model inputs'!B37) -> 0 | D5: =1 -> 1 | E5: =IF('Model inputs'!B16="","",'Model inputs'!B16) -> 0.1 | F5: =IF('Model inputs'!B40="","",'Model inputs'!B40) -> 0 | G5: =1 -> 1 | H5: =0 -> 0
A6: Audits 2/month | B6: =2 -> 2 | C6: =IF('Model inputs'!B37="","",'Model inputs'!B37) -> 0 | D6: =1 -> 1 | E6: =IF('Model inputs'!B16="","",'Model inputs'!B16) -> 0.1 | F6: =IF('Model inputs'!B40="","",'Model inputs'!B40) -> 0 | G6: =1 -> 1 | H6: =0 -> 0
A7: Audits 3/month | B7: =3 -> 3 | C7: =IF('Model inputs'!B37="","",'Model inputs'!B37) -> 0 | D7: =1 -> 1 | E7: =IF('Model inputs'!B16="","",'Model inputs'!B16) -> 0.1 | F7: =IF('Model inputs'!B40="","",'Model inputs'!B40) -> 0 | G7: =1 -> 1 | H7: =0 -> 0
A8: Audits 4/month | B8: =4 -> 4 | C8: =IF('Model inputs'!B37="","",'Model inputs'!B37) -> 0 | D8: =1 -> 1 | E8: =IF('Model inputs'!B16="","",'Model inputs'!B16) -> 0.1 | F8: =IF('Model inputs'!B40="","",'Model inputs'!B40) -> 0 | G8: =1 -> 1 | H8: =0 -> 0
A9: Discount 0% | B9: =IF('Model inputs'!B14="","",'Model inputs'!B14) -> 4 | C9: =0 -> 0 | D9: =1 -> 1 | E9: =IF('Model inputs'!B16="","",'Model inputs'!B16) -> 0.1 | F9: =IF('Model inputs'!B40="","",'Model inputs'!B40) -> 0 | G9: =1 -> 1 | H9: =0 -> 0
A10: Discount 20% | B10: =IF('Model inputs'!B14="","",'Model inputs'!B14) -> 4 | C10: =0.2 -> 0.2 | D10: =1 -> 1 | E10: =IF('Model inputs'!B16="","",'Model inputs'!B16) -> 0.1 | F10: =IF('Model inputs'!B40="","",'Model inputs'!B40) -> 0 | G10: =1 -> 1 | H10: =0 -> 0
A11: Discount 40% | B11: =IF('Model inputs'!B14="","",'Model inputs'!B14) -> 4 | C11: =0.4 -> 0.4 | D11: =1 -> 1 | E11: =IF('Model inputs'!B16="","",'Model inputs'!B16) -> 0.1 | F11: =IF('Model inputs'!B40="","",'Model inputs'!B40) -> 0 | G11: =1 -> 1 | H11: =0 -> 0
A12: Data cost x1 | B12: =IF('Model inputs'!B14="","",'Model inputs'!B14) -> 4 | C12: =IF('Model inputs'!B37="","",'Model inputs'!B37) -> 0 | D12: =1 -> 1 | E12: =IF('Model inputs'!B16="","",'Model inputs'!B16) -> 0.1 | F12: =IF('Model inputs'!B40="","",'Model inputs'!B40) -> 0 | G12: =1 -> 1 | H12: =0 -> 0
A13: Data cost x2 | B13: =IF('Model inputs'!B14="","",'Model inputs'!B14) -> 4 | C13: =IF('Model inputs'!B37="","",'Model inputs'!B37) -> 0 | D13: =2 -> 2 | E13: =IF('Model inputs'!B16="","",'Model inputs'!B16) -> 0.1 | F13: =IF('Model inputs'!B40="","",'Model inputs'!B40) -> 0 | G13: =1 -> 1 | H13: =0 -> 0
A14: Data cost x3 | B14: =IF('Model inputs'!B14="","",'Model inputs'!B14) -> 4 | C14: =IF('Model inputs'!B37="","",'Model inputs'!B37) -> 0 | D14: =3 -> 3 | E14: =IF('Model inputs'!B16="","",'Model inputs'!B16) -> 0.1 | F14: =IF('Model inputs'!B40="","",'Model inputs'!B40) -> 0 | G14: =1 -> 1 | H14: =0 -> 0
A15: Credit rate $0.05 | B15: =IF('Model inputs'!B14="","",'Model inputs'!B14) -> 4 | C15: =IF('Model inputs'!B37="","",'Model inputs'!B37) -> 0 | D15: =1 -> 1 | E15: =0.05 -> 0.05 | F15: =IF('Model inputs'!B40="","",'Model inputs'!B40) -> 0 | G15: =1 -> 1 | H15: =0 -> 0
A16: Credit rate $0.10 | B16: =IF('Model inputs'!B14="","",'Model inputs'!B14) -> 4 | C16: =IF('Model inputs'!B37="","",'Model inputs'!B37) -> 0 | D16: =1 -> 1 | E16: =0.1 -> 0.1 | F16: =IF('Model inputs'!B40="","",'Model inputs'!B40) -> 0 | G16: =1 -> 1 | H16: =0 -> 0
A17: Credit rate $0.25 | B17: =IF('Model inputs'!B14="","",'Model inputs'!B14) -> 4 | C17: =IF('Model inputs'!B37="","",'Model inputs'!B37) -> 0 | D17: =1 -> 1 | E17: =0.25 -> 0.25 | F17: =IF('Model inputs'!B40="","",'Model inputs'!B40) -> 0 | G17: =1 -> 1 | H17: =0 -> 0
A18: Sales delay 0 months | B18: =IF('Model inputs'!B14="","",'Model inputs'!B14) -> 4 | C18: =IF('Model inputs'!B37="","",'Model inputs'!B37) -> 0 | D18: =1 -> 1 | E18: =IF('Model inputs'!B16="","",'Model inputs'!B16) -> 0.1 | F18: =0 -> 0 | G18: =1 -> 1 | H18: =0 -> 0
A19: Sales delay 2 months | B19: =IF('Model inputs'!B14="","",'Model inputs'!B14) -> 4 | C19: =IF('Model inputs'!B37="","",'Model inputs'!B37) -> 0 | D19: =1 -> 1 | E19: =IF('Model inputs'!B16="","",'Model inputs'!B16) -> 0.1 | F19: =2 -> 2 | G19: =1 -> 1 | H19: =0 -> 0
A20: Sales delay 4 months | B20: =IF('Model inputs'!B14="","",'Model inputs'!B14) -> 4 | C20: =IF('Model inputs'!B37="","",'Model inputs'!B37) -> 0 | D20: =1 -> 1 | E20: =IF('Model inputs'!B16="","",'Model inputs'!B16) -> 0.1 | F20: =4 -> 4 | G20: =1 -> 1 | H20: =0 -> 0
A21: Annual allowance utilization 50% | B21: =IF('Model inputs'!B14="","",'Model inputs'!B14) -> 4 | C21: =IF('Model inputs'!B37="","",'Model inputs'!B37) -> 0 | D21: =1 -> 1 | E21: =IF('Model inputs'!B16="","",'Model inputs'!B16) -> 0.1 | F21: =IF('Model inputs'!B40="","",'Model inputs'!B40) -> 0 | G21: =0.5 -> 0.5 | H21: =1 -> 1
A22: Annual allowance utilization 75% | B22: =IF('Model inputs'!B14="","",'Model inputs'!B14) -> 4 | C22: =IF('Model inputs'!B37="","",'Model inputs'!B37) -> 0 | D22: =1 -> 1 | E22: =IF('Model inputs'!B16="","",'Model inputs'!B16) -> 0.1 | F22: =IF('Model inputs'!B40="","",'Model inputs'!B40) -> 0 | G22: =0.75 -> 0.75 | H22: =1 -> 1
A23: Annual allowance utilization 100% | B23: =IF('Model inputs'!B14="","",'Model inputs'!B14) -> 4 | C23: =IF('Model inputs'!B37="","",'Model inputs'!B37) -> 0 | D23: =1 -> 1 | E23: =IF('Model inputs'!B16="","",'Model inputs'!B16) -> 0.1 | F23: =IF('Model inputs'!B40="","",'Model inputs'!B40) -> 0 | G23: =1 -> 1 | H23: =1 -> 1

Sheet DealScope sensitivity compariso
A1: DealScope sensitivity comparisons
A2: DealScope — Pricing and sensitivity · Growth
A4: Variable / dimension | B4: Sensitivity delivered frequency | C4: Sensitivity customer monthly revenue | D4: Sensitivity delivery cost per audit | E4: Sensitivity revenue per audit | F4: Sensitivity gross margin | G4: Sensitivity contribution margin | H4: Sensitivity customer months | I4: Sensitivity 12-month earned revenue | J4: Sensitivity 12-month operating profit
A5: Annual deal-team | B5: ="" | C5: ="" | D5: ="" | E5: ="" | F5: ="" | G5: ="" | H5: ="" | I5: ="" | J5: =""
A6: Annual allowance utilization 100% | B6: =IF(IF(IF(ISERROR('DealScope sensitivity controls'!H23=1),'DealScope sensitivity controls'!H23=1,IF('DealScope sensitivity controls'!H23="","",'DealScope sensitivity controls'!H23=1))="",FALSE,IF(ISERROR('DealScope sensitivity controls'!H23=1),'DealScope sensitivity controls'!H23=1,IF('DealScope sensitivity controls'!H23="","",'DealScope sensitivity controls'!H23=1))),'Model inputs'!B6/12*'DealScope sensitivity controls'!G23,IF('DealScope sensitivity controls'!B23="","",'DealScope sensitivity controls'!B23)) -> 2 | C6: =IF(EXACT("Annual deal-team","Annual deal-team"),('Model inputs'!B45/12+MAX('DealScope sensitivity compariso'!B6-'Model inputs'!B24/12,0)*'Model inputs'!B32)*(1-'DealScope sensitivity controls'!C23),('Model inputs'!B45/12+'Model inputs'!B9*'DealScope sensitivity compariso'!B6)*(1-'DealScope sensitivity controls'!C23)) -> 2000 | D6: ='Model inputs'!B15*'DealScope sensitivity controls'!E23*'DealScope sensitivity controls'!D23*'Model inputs'!B17+'Model inputs'!B30+'Model inputs'!B39+'Model inputs'!B19 -> 94.65 | E6: =IFERROR('DealScope sensitivity compariso'!C6/'DealScope sensitivity compariso'!B6,"") -> 1000 | F6: =IFERROR(('DealScope sensitivity compariso'!E6-'DealScope sensitivity compariso'!D6)/'DealScope sensitivity compariso'!E6,"") -> 0.90535 | G6: =IFERROR(('DealScope sensitivity compariso'!C6*(1-'Model inputs'!B38)-'DealScope sensitivity compariso'!B6*'DealScope sensitivity compariso'!D6-'Model inputs'!B42*'Model inputs'!B41)/'DealScope sensitivity compariso'!C6,"") -> 0.86035 | H6: ='Model inputs'!B75+IF(IF(IF(IF(ISERROR('Model inputs'!B29=1),'Model inputs'!B29=1,IF('Model inputs'!B29="","",'Model inputs'!B29=1))="",FALSE,IF(ISERROR('Model inputs'!B29=1),'Model inputs'!B29=1,IF('Model inputs'!B29="","",'Model inputs'!B29=1))),'Model inputs'!B43*MIN(MAX((11-'DealScope sensitivity controls'!F23)/'Model inputs'!B21,0),1),IF(IF(IF(ISERROR(11>'DealScope sensitivity controls'!F23),11>'DealScope sensitivity controls'!F23,IF('DealScope sensitivity controls'!F23="","",11>'DealScope sensitivity controls'!F23))="",FALSE,IF(ISERROR(11>'DealScope sensitivity controls'!F23),11>'DealScope sensitivity controls'!F23,IF('DealScope sensitivity controls'!F23="","",11>'DealScope sensitivity controls'!F23))),IF('Model inputs'!B43="","",'Model inputs'!B43),0))="",0,IF(IF(IF(ISERROR('Model inputs'!B29=1),'Model inputs'!B29=1,IF('Model inputs'!B29="","",'Model inputs'!B29=1))="",FALSE,IF(ISERROR('Model inputs'!B29=1),'Model inputs'!B29=1,IF('Model inputs'!B29="","",'Model inputs'!B29=1))),'Model inputs'!B43*MIN(MAX((11-'DealScope sensitivity controls'!F23)/'Model inputs'!B21,0),1),IF(IF(IF(ISERROR(11>'DealScope sensitivity controls'!F23),11>'DealScope sensitivity controls'!F23,IF('DealScope sensitivity controls'!F23="","",11>'DealScope sensitivity controls'!F23))="",FALSE,IF(ISERROR(11>'DealScope sensitivity controls'!F23),11>'DealScope sensitivity controls'!F23,IF('DealScope sensitivity controls'!F23="","",11>'DealScope sensitivity controls'!F23))),IF('Model inputs'!B43="","",'Model inputs'!B43),0)))+IF(IF(IF(IF(ISERROR('Model inputs'!B29=1),'Model inputs'!B29=1,IF('Model inputs'!B29="","",'Model inputs'!B29=1))="",FALSE,IF(ISERROR('Model inputs'!B29=1),'Model inputs'!B29=1,IF('Model inputs'!B29="","",'Model inputs'!B29=1))),'Model inputs'!B43*MIN(MAX((12-'DealScope sensitivity controls'!F23)/'Model inputs'!B21,0),1),IF(IF(IF(ISERROR(12>'DealScope sensitivity controls'!F23),12>'DealScope sensitivity controls'!F23,IF('DealScope sensitivity controls'!F23="","",12>'DealScope sensitivity controls'!F23))="",FALSE,IF(ISERROR(12>'DealScope sensitivity controls'!F23),12>'DealScope sensitivity controls'!F23,IF('DealScope sensitivity controls'!F23="","",12>'DealScope sensitivity controls'!F23))),IF('Model inputs'!B43="","",'Model inputs'!B43),0))="",0,IF(IF(IF(ISERROR('Model inputs'!B29=1),'Model inputs'!B29=1,IF('Model inputs'!B29="","",'Model inputs'!B29=1))="",FALSE,IF(ISERROR('Model inputs'!B29=1),'Model inputs'!B29=1,IF('Model inputs'!B29="","",'Model inputs'!B29=1))),'Model inputs'!B43*MIN(MAX((12-'DealScope sensitivity controls'!F23)/'Model inputs'!B21,0),1),IF(IF(IF(ISERROR(12>'DealScope sensitivity controls'!F23),12>'DealScope sensitivity controls'!F23,IF('DealScope sensitivity controls'!F23="","",12>'DealScope sensitivity controls'!F23))="",FALSE,IF(ISERROR(12>'DealScope sensitivity controls'!F23),12>'DealScope sensitivity controls'!F23,IF('DealScope sensitivity controls'!F23="","",12>'DealScope sensitivity controls'!F23))),IF('Model inputs'!B43="","",'Model inputs'!B43),0))) -> 97.5 | I6: ='DealScope sensitivity compariso'!H6*'DealScope sensitivity compariso'!C6 -> 195000 | J6: ='DealScope sensitivity compariso'!I6*(1-'Model inputs'!B38)-'DealScope sensitivity compariso'!H6*('DealScope sensitivity compariso'!B6*'DealScope sensitivity compariso'!D6+'Model inputs'!B42*'Model inputs'!B41)-SUM('Model inputs'!B76,'Model inputs'!B77) -> 155268.25
A7: Annual allowance utilization 50% | B7: =IF(IF(IF(ISERROR('DealScope sensitivity controls'!H21=1),'DealScope sensitivity controls'!H21=1,IF('DealScope sensitivity controls'!H21="","",'DealScope sensitivity controls'!H21=1))="",FALSE,IF(ISERROR('DealScope sensitivity controls'!H21=1),'DealScope sensitivity controls'!H21=1,IF('DealScope sensitivity controls'!H21="","",'DealScope sensitivity controls'!H21=1))),'Model inputs'!B6/12*'DealScope sensitivity controls'!G21,IF('DealScope sensitivity controls'!B21="","",'DealScope sensitivity controls'!B21)) -> 1 | C7: =IF(EXACT("Annual deal-team","Annual deal-team"),('Model inputs'!B45/12+MAX('DealScope sensitivity compariso'!B7-'Model inputs'!B24/12,0)*'Model inputs'!B32)*(1-'DealScope sensitivity controls'!C21),('Model inputs'!B45/12+'Model inputs'!B9*'DealScope sensitivity compariso'!B7)*(1-'DealScope sensitivity controls'!C21)) -> 2000 | D7: ='Model inputs'!B15*'DealScope sensitivity controls'!E21*'DealScope sensitivity controls'!D21*'Model inputs'!B17+'Model inputs'!B30+'Model inputs'!B39+'Model inputs'!B19 -> 94.65 | E7: =IFERROR('DealScope sensitivity compariso'!C7/'DealScope sensitivity compariso'!B7,"") -> 2000 | F7: =IFERROR(('DealScope sensitivity compariso'!E7-'DealScope sensitivity compariso'!D7)/'DealScope sensitivity compariso'!E7,"") -> 0.952675 | G7: =IFERROR(('DealScope sensitivity compariso'!C7*(1-'Model inputs'!B38)-'DealScope sensitivity compariso'!B7*'DealScope sensitivity compariso'!D7-'Model inputs'!B42*'Model inputs'!B41)/'DealScope sensitivity compariso'!C7,"") -> 0.907675 | H7: ='Model inputs'!B82+IF(IF(IF(IF(ISERROR('Model inputs'!B29=1),'Model inputs'!B29=1,IF('Model inputs'!B29="","",'Model inputs'!B29=1))="",FALSE,IF(ISERROR('Model inputs'!B29=1),'Model inputs'!B29=1,IF('Model inputs'!B29="","",'Model inputs'!B29=1))),'Model inputs'!B43*MIN(MAX((11-'DealScope sensitivity controls'!F21)/'Model inputs'!B21,0),1),IF(IF(IF(ISERROR(11>'DealScope sensitivity controls'!F21),11>'DealScope sensitivity controls'!F21,IF('DealScope sensitivity controls'!F21="","",11>'DealScope sensitivity controls'!F21))="",FALSE,IF(ISERROR(11>'DealScope sensitivity controls'!F21),11>'DealScope sensitivity controls'!F21,IF('DealScope sensitivity controls'!F21="","",11>'DealScope sensitivity controls'!F21))),IF('Model inputs'!B43="","",'Model inputs'!B43),0))="",0,IF(IF(IF(ISERROR('Model inputs'!B29=1),'Model inputs'!B29=1,IF('Model inputs'!B29="","",'Model inputs'!B29=1))="",FALSE,IF(ISERROR('Model inputs'!B29=1),'Model inputs'!B29=1,IF('Model inputs'!B29="","",'Model inputs'!B29=1))),'Model inputs'!B43*MIN(MAX((11-'DealScope sensitivity controls'!F21)/'Model inputs'!B21,0),1),IF(IF(IF(ISERROR(11>'DealScope sensitivity controls'!F21),11>'DealScope sensitivity controls'!F21,IF('DealScope sensitivity controls'!F21="","",11>'DealScope sensitivity controls'!F21))="",FALSE,IF(ISERROR(11>'DealScope sensitivity controls'!F21),11>'DealScope sensitivity controls'!F21,IF('DealScope sensitivity controls'!F21="","",11>'DealScope sensitivity controls'!F21))),IF('Model inputs'!B43="","",'Model inputs'!B43),0)))+IF(IF(IF(IF(ISERROR('Model inputs'!B29=1),'Model inputs'!B29=1,IF('Model inputs'!B29="","",'Model inputs'!B29=1))="",FALSE,IF(ISERROR('Model inputs'!B29=1),'Model inputs'!B29=1,IF('Model inputs'!B29="","",'Model inputs'!B29=1))),'Model inputs'!B43*MIN(MAX((12-'DealScope sensitivity controls'!F21)/'Model inputs'!B21,0),1),IF(IF(IF(ISERROR(12>'DealScope sensitivity controls'!F21),12>'DealScope sensitivity controls'!F21,IF('DealScope sensitivity controls'!F21="","",12>'DealScope sensitivity controls'!F21))="",FALSE,IF(ISERROR(12>'DealScope sensitivity controls'!F21),12>'DealScope sensitivity controls'!F21,IF('DealScope sensitivity controls'!F21="","",12>'DealScope sensitivity controls'!F21))),IF('Model inputs'!B43="","",'Model inputs'!B43),0))="",0,IF(IF(IF(ISERROR('Model inputs'!B29=1),'Model inputs'!B29=1,IF('Model inputs'!B29="","",'Model inputs'!B29=1))="",FALSE,IF(ISERROR('Model inputs'!B29=1),'Model inputs'!B29=1,IF('Model inputs'!B29="","",'Model inputs'!B29=1))),'Model inputs'!B43*MIN(MAX((12-'DealScope sensitivity controls'!F21)/'Model inputs'!B21,0),1),IF(IF(IF(ISERROR(12>'DealScope sensitivity controls'!F21),12>'DealScope sensitivity controls'!F21,IF('DealScope sensitivity controls'!F21="","",12>'DealScope sensitivity controls'!F21))="",FALSE,IF(ISERROR(12>'DealScope sensitivity controls'!F21),12>'DealScope sensitivity controls'!F21,IF('DealScope sensitivity controls'!F21="","",12>'DealScope sensitivity controls'!F21))),IF('Model inputs'!B43="","",'Model inputs'!B43),0))) -> 97.5 | I7: ='DealScope sensitivity compariso'!H7*'DealScope sensitivity compariso'!C7 -> 195000 | J7: ='DealScope sensitivity compariso'!I7*(1-'Model inputs'!B38)-'DealScope sensitivity compariso'!H7*('DealScope sensitivity compariso'!B7*'DealScope sensitivity compariso'!D7+'Model inputs'!B42*'Model inputs'!B41)-SUM('Model inputs'!B76,'Model inputs'!B77) -> 164496.62
A8: Annual allowance utilization 75% | B8: =IF(IF(IF(ISERROR('DealScope sensitivity controls'!H22=1),'DealScope sensitivity controls'!H22=1,IF('DealScope sensitivity controls'!H22="","",'DealScope sensitivity controls'!H22=1))="",FALSE,IF(ISERROR('DealScope sensitivity controls'!H22=1),'DealScope sensitivity controls'!H22=1,IF('DealScope sensitivity controls'!H22="","",'DealScope sensitivity controls'!H22=1))),'Model inputs'!B6/12*'DealScope sensitivity controls'!G22,IF('DealScope sensitivity controls'!B22="","",'DealScope sensitivity controls'!B22)) -> 1.5 | C8: =IF(EXACT("Annual deal-team","Annual deal-team"),('Model inputs'!B45/12+MAX('DealScope sensitivity compariso'!B8-'Model inputs'!B24/12,0)*'Model inputs'!B32)*(1-'DealScope sensitivity controls'!C22),('Model inputs'!B45/12+'Model inputs'!B9*'DealScope sensitivity compariso'!B8)*(1-'DealScope sensitivity controls'!C22)) -> 2000 | D8: ='Model inputs'!B15*'DealScope sensitivity controls'!E22*'DealScope sensitivity controls'!D22*'Model inputs'!B17+'Model inputs'!B30+'Model inputs'!B39+'Model inputs'!B19 -> 94.65 | E8: =IFERROR('DealScope sensitivity compariso'!C8/'DealScope sensitivity compariso'!B8,"") -> 1333.3333 | F8: =IFERROR(('DealScope sensitivity compariso'!E8-'DealScope sensitivity compariso'!D8)/'DealScope sensitivity compariso'!E8,"") -> 0.9290125 | G8: =IFERROR(('DealScope sensitivity compariso'!C8*(1-'Model inputs'!B38)-'DealScope sensitivity compariso'!B8*'DealScope sensitivity compariso'!D8-'Model inputs'!B42*'Model inputs'!B41)/'DealScope sensitivity compariso'!C8,"") -> 0.8840125 | H8: ='Model inputs'!B87+IF(IF(IF(IF(ISERROR('Model inputs'!B29=1),'Model inputs'!B29=1,IF('Model inputs'!B29="","",'Model inputs'!B29=1))="",FALSE,IF(ISERROR('Model inputs'!B29=1),'Model inputs'!B29=1,IF('Model inputs'!B29="","",'Model inputs'!B29=1))),'Model inputs'!B43*MIN(MAX((11-'DealScope sensitivity controls'!F22)/'Model inputs'!B21,0),1),IF(IF(IF(ISERROR(11>'DealScope sensitivity controls'!F22),11>'DealScope sensitivity controls'!F22,IF('DealScope sensitivity controls'!F22="","",11>'DealScope sensitivity controls'!F22))="",FALSE,IF(ISERROR(11>'DealScope sensitivity controls'!F22),11>'DealScope sensitivity controls'!F22,IF('DealScope sensitivity controls'!F22="","",11>'DealScope sensitivity controls'!F22))),IF('Model inputs'!B43="","",'Model inputs'!B43),0))="",0,IF(IF(IF(ISERROR('Model inputs'!B29=1),'Model inputs'!B29=1,IF('Model inputs'!B29="","",'Model inputs'!B29=1))="",FALSE,IF(ISERROR('Model inputs'!B29=1),'Model inputs'!B29=1,IF('Model inputs'!B29="","",'Model inputs'!B29=1))),'Model inputs'!B43*MIN(MAX((11-'DealScope sensitivity controls'!F22)/'Model inputs'!B21,0),1),IF(IF(IF(ISERROR(11>'DealScope sensitivity controls'!F22),11>'DealScope sensitivity controls'!F22,IF('DealScope sensitivity controls'!F22="","",11>'DealScope sensitivity controls'!F22))="",FALSE,IF(ISERROR(11>'DealScope sensitivity controls'!F22),11>'DealScope sensitivity controls'!F22,IF('DealScope sensitivity controls'!F22="","",11>'DealScope sensitivity controls'!F22))),IF('Model inputs'!B43="","",'Model inputs'!B43),0)))+IF(IF(IF(IF(ISERROR('Model inputs'!B29=1),'Model inputs'!B29=1,IF('Model inputs'!B29="","",'Model inputs'!B29=1))="",FALSE,IF(ISERROR('Model inputs'!B29=1),'Model inputs'!B29=1,IF('Model inputs'!B29="","",'Model inputs'!B29=1))),'Model inputs'!B43*MIN(MAX((12-'DealScope sensitivity controls'!F22)/'Model inputs'!B21,0),1),IF(IF(IF(ISERROR(12>'DealScope sensitivity controls'!F22),12>'DealScope sensitivity controls'!F22,IF('DealScope sensitivity controls'!F22="","",12>'DealScope sensitivity controls'!F22))="",FALSE,IF(ISERROR(12>'DealScope sensitivity controls'!F22),12>'DealScope sensitivity controls'!F22,IF('DealScope sensitivity controls'!F22="","",12>'DealScope sensitivity controls'!F22))),IF('Model inputs'!B43="","",'Model inputs'!B43),0))="",0,IF(IF(IF(ISERROR('Model inputs'!B29=1),'Model inputs'!B29=1,IF('Model inputs'!B29="","",'Model inputs'!B29=1))="",FALSE,IF(ISERROR('Model inputs'!B29=1),'Model inputs'!B29=1,IF('Model inputs'!B29="","",'Model inputs'!B29=1))),'Model inputs'!B43*MIN(MAX((12-'DealScope sensitivity controls'!F22)/'Model inputs'!B21,0),1),IF(IF(IF(ISERROR(12>'DealScope sensitivity controls'!F22),12>'DealScope sensitivity controls'!F22,IF('DealScope sensitivity controls'!F22="","",12>'DealScope sensitivity controls'!F22))="",FALSE,IF(ISERROR(12>'DealScope sensitivity controls'!F22),12>'DealScope sensitivity controls'!F22,IF('DealScope sensitivity controls'!F22="","",12>'DealScope sensitivity controls'!F22))),IF('Model inputs'!B43="","",'Model inputs'!B43),0))) -> 97.5 | I8: ='DealScope sensitivity compariso'!H8*'DealScope sensitivity compariso'!C8 -> 195000 | J8: ='DealScope sensitivity compariso'!I8*(1-'Model inputs'!B38)-'DealScope sensitivity compariso'!H8*('DealScope sensitivity compariso'!B8*'DealScope sensitivity compariso'!D8+'Model inputs'!B42*'Model inputs'!B41)-SUM('Model inputs'!B76,'Model inputs'!B77) -> 159882.44
A9: Audits 2/month | B9: =IF(IF(IF(ISERROR('DealScope sensitivity controls'!H6=1),'DealScope sensitivity controls'!H6=1,IF('DealScope sensitivity controls'!H6="","",'DealScope sensitivity controls'!H6=1))="",FALSE,IF(ISERROR('DealScope sensitivity controls'!H6=1),'DealScope sensitivity controls'!H6=1,IF('DealScope sensitivity controls'!H6="","",'DealScope sensitivity controls'!H6=1))),'Model inputs'!B6/12*'DealScope sensitivity controls'!G6,IF('DealScope sensitivity controls'!B6="","",'DealScope sensitivity controls'!B6)) -> 2 | C9: =IF(EXACT("Annual deal-team","Annual deal-team"),('Model inputs'!B45/12+MAX('DealScope sensitivity compariso'!B9-'Model inputs'!B24/12,0)*'Model inputs'!B32)*(1-'DealScope sensitivity controls'!C6),('Model inputs'!B45/12+'Model inputs'!B9*'DealScope sensitivity compariso'!B9)*(1-'DealScope sensitivity controls'!C6)) -> 2000 | D9: ='Model inputs'!B15*'DealScope sensitivity controls'!E6*'DealScope sensitivity controls'!D6*'Model inputs'!B17+'Model inputs'!B30+'Model inputs'!B39+'Model inputs'!B19 -> 94.65 | E9: =IFERROR('DealScope sensitivity compariso'!C9/'DealScope sensitivity compariso'!B9,"") -> 1000 | F9: =IFERROR(('DealScope sensitivity compariso'!E9-'DealScope sensitivity compariso'!D9)/'DealScope sensitivity compariso'!E9,"") -> 0.90535 | G9: =IFERROR(('DealScope sensitivity compariso'!C9*(1-'Model inputs'!B38)-'DealScope sensitivity compariso'!B9*'DealScope sensitivity compariso'!D9-'Model inputs'!B42*'Model inputs'!B41)/'DealScope sensitivity compariso'!C9,"") -> 0.86035 | H9: ='Model inputs'!B92+IF(IF(IF(IF(ISERROR('Model inputs'!B29=1),'Model inputs'!B29=1,IF('Model inputs'!B29="","",'Model inputs'!B29=1))="",FALSE,IF(ISERROR('Model inputs'!B29=1),'Model inputs'!B29=1,IF('Model inputs'!B29="","",'Model inputs'!B29=1))),'Model inputs'!B43*MIN(MAX((11-'DealScope sensitivity controls'!F6)/'Model inputs'!B21,0),1),IF(IF(IF(ISERROR(11>'DealScope sensitivity controls'!F6),11>'DealScope sensitivity controls'!F6,IF('DealScope sensitivity controls'!F6="","",11>'DealScope sensitivity controls'!F6))="",FALSE,IF(ISERROR(11>'DealScope sensitivity controls'!F6),11>'DealScope sensitivity controls'!F6,IF('DealScope sensitivity controls'!F6="","",11>'DealScope sensitivity controls'!F6))),IF('Model inputs'!B43="","",'Model inputs'!B43),0))="",0,IF(IF(IF(ISERROR('Model inputs'!B29=1),'Model inputs'!B29=1,IF('Model inputs'!B29="","",'Model inputs'!B29=1))="",FALSE,IF(ISERROR('Model inputs'!B29=1),'Model inputs'!B29=1,IF('Model inputs'!B29="","",'Model inputs'!B29=1))),'Model inputs'!B43*MIN(MAX((11-'DealScope sensitivity controls'!F6)/'Model inputs'!B21,0),1),IF(IF(IF(ISERROR(11>'DealScope sensitivity controls'!F6),11>'DealScope sensitivity controls'!F6,IF('DealScope sensitivity controls'!F6="","",11>'DealScope sensitivity controls'!F6))="",FALSE,IF(ISERROR(11>'DealScope sensitivity controls'!F6),11>'DealScope sensitivity controls'!F6,IF('DealScope sensitivity controls'!F6="","",11>'DealScope sensitivity controls'!F6))),IF('Model inputs'!B43="","",'Model inputs'!B43),0)))+IF(IF(IF(IF(ISERROR('Model inputs'!B29=1),'Model inputs'!B29=1,IF('Model inputs'!B29="","",'Model inputs'!B29=1))="",FALSE,IF(ISERROR('Model inputs'!B29=1),'Model inputs'!B29=1,IF('Model inputs'!B29="","",'Model inputs'!B29=1))),'Model inputs'!B43*MIN(MAX((12-'DealScope sensitivity controls'!F6)/'Model inputs'!B21,0),1),IF(IF(IF(ISERROR(12>'DealScope sensitivity controls'!F6),12>'DealScope sensitivity controls'!F6,IF('DealScope sensitivity controls'!F6="","",12>'DealScope sensitivity controls'!F6))="",FALSE,IF(ISERROR(12>'DealScope sensitivity controls'!F6),12>'DealScope sensitivity controls'!F6,IF('DealScope sensitivity controls'!F6="","",12>'DealScope sensitivity controls'!F6))),IF('Model inputs'!B43="","",'Model inputs'!B43),0))="",0,IF(IF(IF(ISERROR('Model inputs'!B29=1),'Model inputs'!B29=1,IF('Model inputs'!B29="","",'Model inputs'!B29=1))="",FALSE,IF(ISERROR('Model inputs'!B29=1),'Model inputs'!B29=1,IF('Model inputs'!B29="","",'Model inputs'!B29=1))),'Model inputs'!B43*MIN(MAX((12-'DealScope sensitivity controls'!F6)/'Model inputs'!B21,0),1),IF(IF(IF(ISERROR(12>'DealScope sensitivity controls'!F6),12>'DealScope sensitivity controls'!F6,IF('DealScope sensitivity controls'!F6="","",12>'DealScope sensitivity controls'!F6))="",FALSE,IF(ISERROR(12>'DealScope sensitivity controls'!F6),12>'DealScope sensitivity controls'!F6,IF('DealScope sensitivity controls'!F6="","",12>'DealScope sensitivity controls'!F6))),IF('Model inputs'!B43="","",'Model inputs'!B43),0))) -> 97.5 | I9: ='DealScope sensitivity compariso'!H9*'DealScope sensitivity compariso'!C9 -> 195000 | J9: ='DealScope sensitivity compariso'!I9*(1-'Model inputs'!B38)-'DealScope sensitivity compariso'!H9*('DealScope sensitivity compariso'!B9*'DealScope sensitivity compariso'!D9+'Model inputs'!B42*'Model inputs'!B41)-SUM('Model inputs'!B76,'Model inputs'!B77) -> 155268.25
A10: Audits 3/month | B10: =IF(IF(IF(ISERROR('DealScope sensitivity controls'!H7=1),'DealScope sensitivity controls'!H7=1,IF('DealScope sensitivity controls'!H7="","",'DealScope sensitivity controls'!H7=1))="",FALSE,IF(ISERROR('DealScope sensitivity controls'!H7=1),'DealScope sensitivity controls'!H7=1,IF('DealScope sensitivity controls'!H7="","",'DealScope sensitivity controls'!H7=1))),'Model inputs'!B6/12*'DealScope sensitivity controls'!G7,IF('DealScope sensitivity controls'!B7="","",'DealScope sensitivity controls'!B7)) -> 3 | C10: =IF(EXACT("Annual deal-team","Annual deal-team"),('Model inputs'!B45/12+MAX('DealScope sensitivity compariso'!B10-'Model inputs'!B24/12,0)*'Model inputs'!B32)*(1-'DealScope sensitivity controls'!C7),('Model inputs'!B45/12+'Model inputs'!B9*'DealScope sensitivity compariso'!B10)*(1-'DealScope sensitivity controls'!C7)) -> 3000 | D10: ='Model inputs'!B15*'DealScope sensitivity controls'!E7*'DealScope sensitivity controls'!D7*'Model inputs'!B17+'Model inputs'!B30+'Model inputs'!B39+'Model inputs'!B19 -> 94.65 | E10: =IFERROR('DealScope sensitivity compariso'!C10/'DealScope sensitivity compariso'!B10,"") -> 1000 | F10: =IFERROR(('DealScope sensitivity compariso'!E10-'DealScope sensitivity compariso'!D10)/'DealScope sensitivity compariso'!E10,"") -> 0.90535 | G10: =IFERROR(('DealScope sensitivity compariso'!C10*(1-'Model inputs'!B38)-'DealScope sensitivity compariso'!B10*'DealScope sensitivity compariso'!D10-'Model inputs'!B42*'Model inputs'!B41)/'DealScope sensitivity compariso'!C10,"") -> 0.86535 | H10: ='Model inputs'!B97+IF(IF(IF(IF(ISERROR('Model inputs'!B29=1),'Model inputs'!B29=1,IF('Model inputs'!B29="","",'Model inputs'!B29=1))="",FALSE,IF(ISERROR('Model inputs'!B29=1),'Model inputs'!B29=1,IF('Model inputs'!B29="","",'Model inputs'!B29=1))),'Model inputs'!B43*MIN(MAX((11-'DealScope sensitivity controls'!F7)/'Model inputs'!B21,0),1),IF(IF(IF(ISERROR(11>'DealScope sensitivity controls'!F7),11>'DealScope sensitivity controls'!F7,IF('DealScope sensitivity controls'!F7="","",11>'DealScope sensitivity controls'!F7))="",FALSE,IF(ISERROR(11>'DealScope sensitivity controls'!F7),11>'DealScope sensitivity controls'!F7,IF('DealScope sensitivity controls'!F7="","",11>'DealScope sensitivity controls'!F7))),IF('Model inputs'!B43="","",'Model inputs'!B43),0))="",0,IF(IF(IF(ISERROR('Model inputs'!B29=1),'Model inputs'!B29=1,IF('Model inputs'!B29="","",'Model inputs'!B29=1))="",FALSE,IF(ISERROR('Model inputs'!B29=1),'Model inputs'!B29=1,IF('Model inputs'!B29="","",'Model inputs'!B29=1))),'Model inputs'!B43*MIN(MAX((11-'DealScope sensitivity controls'!F7)/'Model inputs'!B21,0),1),IF(IF(IF(ISERROR(11>'DealScope sensitivity controls'!F7),11>'DealScope sensitivity controls'!F7,IF('DealScope sensitivity controls'!F7="","",11>'DealScope sensitivity controls'!F7))="",FALSE,IF(ISERROR(11>'DealScope sensitivity controls'!F7),11>'DealScope sensitivity controls'!F7,IF('DealScope sensitivity controls'!F7="","",11>'DealScope sensitivity controls'!F7))),IF('Model inputs'!B43="","",'Model inputs'!B43),0)))+IF(IF(IF(IF(ISERROR('Model inputs'!B29=1),'Model inputs'!B29=1,IF('Model inputs'!B29="","",'Model inputs'!B29=1))="",FALSE,IF(ISERROR('Model inputs'!B29=1),'Model inputs'!B29=1,IF('Model inputs'!B29="","",'Model inputs'!B29=1))),'Model inputs'!B43*MIN(MAX((12-'DealScope sensitivity controls'!F7)/'Model inputs'!B21,0),1),IF(IF(IF(ISERROR(12>'DealScope sensitivity controls'!F7),12>'DealScope sensitivity controls'!F7,IF('DealScope sensitivity controls'!F7="","",12>'DealScope sensitivity controls'!F7))="",FALSE,IF(ISERROR(12>'DealScope sensitivity controls'!F7),12>'DealScope sensitivity controls'!F7,IF('DealScope sensitivity controls'!F7="","",12>'DealScope sensitivity controls'!F7))),IF('Model inputs'!B43="","",'Model inputs'!B43),0))="",0,IF(IF(IF(ISERROR('Model inputs'!B29=1),'Model inputs'!B29=1,IF('Model inputs'!B29="","",'Model inputs'!B29=1))="",FALSE,IF(ISERROR('Model inputs'!B29=1),'Model inputs'!B29=1,IF('Model inputs'!B29="","",'Model inputs'!B29=1))),'Model inputs'!B43*MIN(MAX((12-'DealScope sensitivity controls'!F7)/'Model inputs'!B21,0),1),IF(IF(IF(ISERROR(12>'DealScope sensitivity controls'!F7),12>'DealScope sensitivity controls'!F7,IF('DealScope sensitivity controls'!F7="","",12>'DealScope sensitivity controls'!F7))="",FALSE,IF(ISERROR(12>'DealScope sensitivity controls'!F7),12>'DealScope sensitivity controls'!F7,IF('DealScope sensitivity controls'!F7="","",12>'DealScope sensitivity controls'!F7))),IF('Model inputs'!B43="","",'Model inputs'!B43),0))) -> 97.5 | I10: ='DealScope sensitivity compariso'!H10*'DealScope sensitivity compariso'!C10 -> 292500 | J10: ='DealScope sensitivity compariso'!I10*(1-'Model inputs'!B38)-'DealScope sensitivity compariso'!H10*('DealScope sensitivity compariso'!B10*'DealScope sensitivity compariso'!D10+'Model inputs'!B42*'Model inputs'!B41)-SUM('Model inputs'!B76,'Model inputs'!B77) -> 240614.88
A11: Audits 4/month | B11: =IF(IF(IF(ISERROR('DealScope sensitivity controls'!H8=1),'DealScope sensitivity controls'!H8=1,IF('DealScope sensitivity controls'!H8="","",'DealScope sensitivity controls'!H8=1))="",FALSE,IF(ISERROR('DealScope sensitivity controls'!H8=1),'DealScope sensitivity controls'!H8=1,IF('DealScope sensitivity controls'!H8="","",'DealScope sensitivity controls'!H8=1))),'Model inputs'!B6/12*'DealScope sensitivity controls'!G8,IF('DealScope sensitivity controls'!B8="","",'DealScope sensitivity controls'!B8)) -> 4 | C11: =IF(EXACT("Annual deal-team","Annual deal-team"),('Model inputs'!B45/12+MAX('DealScope sensitivity compariso'!B11-'Model inputs'!B24/12,0)*'Model inputs'!B32)*(1-'DealScope sensitivity controls'!C8),('Model inputs'!B45/12+'Model inputs'!B9*'DealScope sensitivity compariso'!B11)*(1-'DealScope sensitivity controls'!C8)) -> 4000 | D11: ='Model inputs'!B15*'DealScope sensitivity controls'!E8*'DealScope sensitivity controls'!D8*'Model inputs'!B17+'Model inputs'!B30+'Model inputs'!B39+'Model inputs'!B19 -> 94.65 | E11: =IFERROR('DealScope sensitivity compariso'!C11/'DealScope sensitivity compariso'!B11,"") -> 1000 | F11: =IFERROR(('DealScope sensitivity compariso'!E11-'DealScope sensitivity compariso'!D11)/'DealScope sensitivity compariso'!E11,"") -> 0.90535 | G11: =IFERROR(('DealScope sensitivity compariso'!C11*(1-'Model inputs'!B38)-'DealScope sensitivity compariso'!B11*'DealScope sensitivity compariso'!D11-'Model inputs'!B42*'Model inputs'!B41)/'DealScope sensitivity compariso'!C11,"") -> 0.86785 | H11: ='Model inputs'!B102+IF(IF(IF(IF(ISERROR('Model inputs'!B29=1),'Model inputs'!B29=1,IF('Model inputs'!B29="","",'Model inputs'!B29=1))="",FALSE,IF(ISERROR('Model inputs'!B29=1),'Model inputs'!B29=1,IF('Model inputs'!B29="","",'Model inputs'!B29=1))),'Model inputs'!B43*MIN(MAX((11-'DealScope sensitivity controls'!F8)/'Model inputs'!B21,0),1),IF(IF(IF(ISERROR(11>'DealScope sensitivity controls'!F8),11>'DealScope sensitivity controls'!F8,IF('DealScope sensitivity controls'!F8="","",11>'DealScope sensitivity controls'!F8))="",FALSE,IF(ISERROR(11>'DealScope sensitivity controls'!F8),11>'DealScope sensitivity controls'!F8,IF('DealScope sensitivity controls'!F8="","",11>'DealScope sensitivity controls'!F8))),IF('Model inputs'!B43="","",'Model inputs'!B43),0))="",0,IF(IF(IF(ISERROR('Model inputs'!B29=1),'Model inputs'!B29=1,IF('Model inputs'!B29="","",'Model inputs'!B29=1))="",FALSE,IF(ISERROR('Model inputs'!B29=1),'Model inputs'!B29=1,IF('Model inputs'!B29="","",'Model inputs'!B29=1))),'Model inputs'!B43*MIN(MAX((11-'DealScope sensitivity controls'!F8)/'Model inputs'!B21,0),1),IF(IF(IF(ISERROR(11>'DealScope sensitivity controls'!F8),11>'DealScope sensitivity controls'!F8,IF('DealScope sensitivity controls'!F8="","",11>'DealScope sensitivity controls'!F8))="",FALSE,IF(ISERROR(11>'DealScope sensitivity controls'!F8),11>'DealScope sensitivity controls'!F8,IF('DealScope sensitivity controls'!F8="","",11>'DealScope sensitivity controls'!F8))),IF('Model inputs'!B43="","",'Model inputs'!B43),0)))+IF(IF(IF(IF(ISERROR('Model inputs'!B29=1),'Model inputs'!B29=1,IF('Model inputs'!B29="","",'Model inputs'!B29=1))="",FALSE,IF(ISERROR('Model inputs'!B29=1),'Model inputs'!B29=1,IF('Model inputs'!B29="","",'Model inputs'!B29=1))),'Model inputs'!B43*MIN(MAX((12-'DealScope sensitivity controls'!F8)/'Model inputs'!B21,0),1),IF(IF(IF(ISERROR(12>'DealScope sensitivity controls'!F8),12>'DealScope sensitivity controls'!F8,IF('DealScope sensitivity controls'!F8="","",12>'DealScope sensitivity controls'!F8))="",FALSE,IF(ISERROR(12>'DealScope sensitivity controls'!F8),12>'DealScope sensitivity controls'!F8,IF('DealScope sensitivity controls'!F8="","",12>'DealScope sensitivity controls'!F8))),IF('Model inputs'!B43="","",'Model inputs'!B43),0))="",0,IF(IF(IF(ISERROR('Model inputs'!B29=1),'Model inputs'!B29=1,IF('Model inputs'!B29="","",'Model inputs'!B29=1))="",FALSE,IF(ISERROR('Model inputs'!B29=1),'Model inputs'!B29=1,IF('Model inputs'!B29="","",'Model inputs'!B29=1))),'Model inputs'!B43*MIN(MAX((12-'DealScope sensitivity controls'!F8)/'Model inputs'!B21,0),1),IF(IF(IF(ISERROR(12>'DealScope sensitivity controls'!F8),12>'DealScope sensitivity controls'!F8,IF('DealScope sensitivity controls'!F8="","",12>'DealScope sensitivity controls'!F8))="",FALSE,IF(ISERROR(12>'DealScope sensitivity controls'!F8),12>'DealScope sensitivity controls'!F8,IF('DealScope sensitivity controls'!F8="","",12>'DealScope sensitivity controls'!F8))),IF('Model inputs'!B43="","",'Model inputs'!B43),0))) -> 97.5 | I11: ='DealScope sensitivity compariso'!H11*'DealScope sensitivity compariso'!C11 -> 390000 | J11: ='DealScope sensitivity compariso'!I11*(1-'Model inputs'!B38)-'DealScope sensitivity compariso'!H11*('DealScope sensitivity compariso'!B11*'DealScope sensitivity compariso'!D11+'Model inputs'!B42*'Model inputs'!B41)-SUM('Model inputs'!B76,'Model inputs'!B77) -> 325961.5
A12: Baseline | B12: =IF(IF(IF(ISERROR('DealScope sensitivity controls'!H5=1),'DealScope sensitivity controls'!H5=1,IF('DealScope sensitivity controls'!H5="","",'DealScope sensitivity controls'!H5=1))="",FALSE,IF(ISERROR('DealScope sensitivity controls'!H5=1),'DealScope sensitivity controls'!H5=1,IF('DealScope sensitivity controls'!H5="","",'DealScope sensitivity controls'!H5=1))),'Model inputs'!B6/12*'DealScope sensitivity controls'!G5,IF('DealScope sensitivity controls'!B5="","",'DealScope sensitivity controls'!B5)) -> 4 | C12: =IF(EXACT("Annual deal-team","Annual deal-team"),('Model inputs'!B45/12+MAX('DealScope sensitivity compariso'!B12-'Model inputs'!B24/12,0)*'Model inputs'!B32)*(1-'DealScope sensitivity controls'!C5),('Model inputs'!B45/12+'Model inputs'!B9*'DealScope sensitivity compariso'!B12)*(1-'DealScope sensitivity controls'!C5)) -> 4000 | D12: ='Model inputs'!B15*'DealScope sensitivity controls'!E5*'DealScope sensitivity controls'!D5*'Model inputs'!B17+'Model inputs'!B30+'Model inputs'!B39+'Model inputs'!B19 -> 94.65 | E12: =IFERROR('DealScope sensitivity compariso'!C12/'DealScope sensitivity compariso'!B12,"") -> 1000 | F12: =IFERROR(('DealScope sensitivity compariso'!E12-'DealScope sensitivity compariso'!D12)/'DealScope sensitivity compariso'!E12,"") -> 0.90535 | G12: =IFERROR(('DealScope sensitivity compariso'!C12*(1-'Model inputs'!B38)-'DealScope sensitivity compariso'!B12*'DealScope sensitivity compariso'!D12-'Model inputs'!B42*'Model inputs'!B41)/'DealScope sensitivity compariso'!C12,"") -> 0.86785 | H12: ='Model inputs'!B107+IF(IF(IF(IF(ISERROR('Model inputs'!B29=1),'Model inputs'!B29=1,IF('Model inputs'!B29="","",'Model inputs'!B29=1))="",FALSE,IF(ISERROR('Model inputs'!B29=1),'Model inputs'!B29=1,IF('Model inputs'!B29="","",'Model inputs'!B29=1))),'Model inputs'!B43*MIN(MAX((11-'DealScope sensitivity controls'!F5)/'Model inputs'!B21,0),1),IF(IF(IF(ISERROR(11>'DealScope sensitivity controls'!F5),11>'DealScope sensitivity controls'!F5,IF('DealScope sensitivity controls'!F5="","",11>'DealScope sensitivity controls'!F5))="",FALSE,IF(ISERROR(11>'DealScope sensitivity controls'!F5),11>'DealScope sensitivity controls'!F5,IF('DealScope sensitivity controls'!F5="","",11>'DealScope sensitivity controls'!F5))),IF('Model inputs'!B43="","",'Model inputs'!B43),0))="",0,IF(IF(IF(ISERROR('Model inputs'!B29=1),'Model inputs'!B29=1,IF('Model inputs'!B29="","",'Model inputs'!B29=1))="",FALSE,IF(ISERROR('Model inputs'!B29=1),'Model inputs'!B29=1,IF('Model inputs'!B29="","",'Model inputs'!B29=1))),'Model inputs'!B43*MIN(MAX((11-'DealScope sensitivity controls'!F5)/'Model inputs'!B21,0),1),IF(IF(IF(ISERROR(11>'DealScope sensitivity controls'!F5),11>'DealScope sensitivity controls'!F5,IF('DealScope sensitivity controls'!F5="","",11>'DealScope sensitivity controls'!F5))="",FALSE,IF(ISERROR(11>'DealScope sensitivity controls'!F5),11>'DealScope sensitivity controls'!F5,IF('DealScope sensitivity controls'!F5="","",11>'DealScope sensitivity controls'!F5))),IF('Model inputs'!B43="","",'Model inputs'!B43),0)))+IF(IF(IF(IF(ISERROR('Model inputs'!B29=1),'Model inputs'!B29=1,IF('Model inputs'!B29="","",'Model inputs'!B29=1))="",FALSE,IF(ISERROR('Model inputs'!B29=1),'Model inputs'!B29=1,IF('Model inputs'!B29="","",'Model inputs'!B29=1))),'Model inputs'!B43*MIN(MAX((12-'DealScope sensitivity controls'!F5)/'Model inputs'!B21,0),1),IF(IF(IF(ISERROR(12>'DealScope sensitivity controls'!F5),12>'DealScope sensitivity controls'!F5,IF('DealScope sensitivity controls'!F5="","",12>'DealScope sensitivity controls'!F5))="",FALSE,IF(ISERROR(12>'DealScope sensitivity controls'!F5),12>'DealScope sensitivity controls'!F5,IF('DealScope sensitivity controls'!F5="","",12>'DealScope sensitivity controls'!F5))),IF('Model inputs'!B43="","",'Model inputs'!B43),0))="",0,IF(IF(IF(ISERROR('Model inputs'!B29=1),'Model inputs'!B29=1,IF('Model inputs'!B29="","",'Model inputs'!B29=1))="",FALSE,IF(ISERROR('Model inputs'!B29=1),'Model inputs'!B29=1,IF('Model inputs'!B29="","",'Model inputs'!B29=1))),'Model inputs'!B43*MIN(MAX((12-'DealScope sensitivity controls'!F5)/'Model inputs'!B21,0),1),IF(IF(IF(ISERROR(12>'DealScope sensitivity controls'!F5),12>'DealScope sensitivity controls'!F5,IF('DealScope sensitivity controls'!F5="","",12>'DealScope sensitivity controls'!F5))="",FALSE,IF(ISERROR(12>'DealScope sensitivity controls'!F5),12>'DealScope sensitivity controls'!F5,IF('DealScope sensitivity controls'!F5="","",12>'DealScope sensitivity controls'!F5))),IF('Model inputs'!B43="","",'Model inputs'!B43),0))) -> 97.5 | I12: ='DealScope sensitivity compariso'!H12*'DealScope sensitivity compariso'!C12 -> 390000 | J12: ='DealScope sensitivity compariso'!I12*(1-'Model inputs'!B38)-'DealScope sensitivity compariso'!H12*('DealScope sensitivity compariso'!B12*'DealScope sensitivity compariso'!D12+'Model inputs'!B42*'Model inputs'!B41)-SUM('Model inputs'!B76,'Model inputs'!B77) -> 325961.5
A13: Credit rate $0.05 | B13: =IF(IF(IF(ISERROR('DealScope sensitivity controls'!H15=1),'DealScope sensitivity controls'!H15=1,IF('DealScope sensitivity controls'!H15="","",'DealScope sensitivity controls'!H15=1))="",FALSE,IF(ISERROR('DealScope sensitivity controls'!H15=1),'DealScope sensitivity controls'!H15=1,IF('DealScope sensitivity controls'!H15="","",'DealScope sensitivity controls'!H15=1))),'Model inputs'!B6/12*'DealScope sensitivity controls'!G15,IF('DealScope sensitivity controls'!B15="","",'DealScope sensitivity controls'!B15)) -> 4 | C13: =IF(EXACT("Annual deal-team","Annual deal-team"),('Model inputs'!B45/12+MAX('DealScope sensitivity compariso'!B13-'Model inputs'!B24/12,0)*'Model inputs'!B32)*(1-'DealScope sensitivity controls'!C15),('Model inputs'!B45/12+'Model inputs'!B9*'DealScope sensitivity compariso'!B13)*(1-'DealScope sensitivity controls'!C15)) -> 4000 | D13: ='Model inputs'!B15*'DealScope sensitivity controls'!E15*'DealScope sensitivity controls'!D15*'Model inputs'!B17+'Model inputs'!B30+'Model inputs'!B39+'Model inputs'!B19 -> 93.35 | E13: =IFERROR('DealScope sensitivity compariso'!C13/'DealScope sensitivity compariso'!B13,"") -> 1000 | F13: =IFERROR(('DealScope sensitivity compariso'!E13-'DealScope sensitivity compariso'!D13)/'DealScope sensitivity compariso'!E13,"") -> 0.90665 | G13: =IFERROR(('DealScope sensitivity compariso'!C13*(1-'Model inputs'!B38)-'DealScope sensitivity compariso'!B13*'DealScope sensitivity compariso'!D13-'Model inputs'!B42*'Model inputs'!B41)/'DealScope sensitivity compariso'!C13,"") -> 0.86915 | H13: ='Model inputs'!B112+IF(IF(IF(IF(ISERROR('Model inputs'!B29=1),'Model inputs'!B29=1,IF('Model inputs'!B29="","",'Model inputs'!B29=1))="",FALSE,IF(ISERROR('Model inputs'!B29=1),'Model inputs'!B29=1,IF('Model inputs'!B29="","",'Model inputs'!B29=1))),'Model inputs'!B43*MIN(MAX((11-'DealScope sensitivity controls'!F15)/'Model inputs'!B21,0),1),IF(IF(IF(ISERROR(11>'DealScope sensitivity controls'!F15),11>'DealScope sensitivity controls'!F15,IF('DealScope sensitivity controls'!F15="","",11>'DealScope sensitivity controls'!F15))="",FALSE,IF(ISERROR(11>'DealScope sensitivity controls'!F15),11>'DealScope sensitivity controls'!F15,IF('DealScope sensitivity controls'!F15="","",11>'DealScope sensitivity controls'!F15))),IF('Model inputs'!B43="","",'Model inputs'!B43),0))="",0,IF(IF(IF(ISERROR('Model inputs'!B29=1),'Model inputs'!B29=1,IF('Model inputs'!B29="","",'Model inputs'!B29=1))="",FALSE,IF(ISERROR('Model inputs'!B29=1),'Model inputs'!B29=1,IF('Model inputs'!B29="","",'Model inputs'!B29=1))),'Model inputs'!B43*MIN(MAX((11-'DealScope sensitivity controls'!F15)/'Model inputs'!B21,0),1),IF(IF(IF(ISERROR(11>'DealScope sensitivity controls'!F15),11>'DealScope sensitivity controls'!F15,IF('DealScope sensitivity controls'!F15="","",11>'DealScope sensitivity controls'!F15))="",FALSE,IF(ISERROR(11>'DealScope sensitivity controls'!F15),11>'DealScope sensitivity controls'!F15,IF('DealScope sensitivity controls'!F15="","",11>'DealScope sensitivity controls'!F15))),IF('Model inputs'!B43="","",'Model inputs'!B43),0)))+IF(IF(IF(IF(ISERROR('Model inputs'!B29=1),'Model inputs'!B29=1,IF('Model inputs'!B29="","",'Model inputs'!B29=1))="",FALSE,IF(ISERROR('Model inputs'!B29=1),'Model inputs'!B29=1,IF('Model inputs'!B29="","",'Model inputs'!B29=1))),'Model inputs'!B43*MIN(MAX((12-'DealScope sensitivity controls'!F15)/'Model inputs'!B21,0),1),IF(IF(IF(ISERROR(12>'DealScope sensitivity controls'!F15),12>'DealScope sensitivity controls'!F15,IF('DealScope sensitivity controls'!F15="","",12>'DealScope sensitivity controls'!F15))="",FALSE,IF(ISERROR(12>'DealScope sensitivity controls'!F15),12>'DealScope sensitivity controls'!F15,IF('DealScope sensitivity controls'!F15="","",12>'DealScope sensitivity controls'!F15))),IF('Model inputs'!B43="","",'Model inputs'!B43),0))="",0,IF(IF(IF(ISERROR('Model inputs'!B29=1),'Model inputs'!B29=1,IF('Model inputs'!B29="","",'Model inputs'!B29=1))="",FALSE,IF(ISERROR('Model inputs'!B29=1),'Model inputs'!B29=1,IF('Model inputs'!B29="","",'Model inputs'!B29=1))),'Model inputs'!B43*MIN(MAX((12-'DealScope sensitivity controls'!F15)/'Model inputs'!B21,0),1),IF(IF(IF(ISERROR(12>'DealScope sensitivity controls'!F15),12>'DealScope sensitivity controls'!F15,IF('DealScope sensitivity controls'!F15="","",12>'DealScope sensitivity controls'!F15))="",FALSE,IF(ISERROR(12>'DealScope sensitivity controls'!F15),12>'DealScope sensitivity controls'!F15,IF('DealScope sensitivity controls'!F15="","",12>'DealScope sensitivity controls'!F15))),IF('Model inputs'!B43="","",'Model inputs'!B43),0))) -> 97.5 | I13: ='DealScope sensitivity compariso'!H13*'DealScope sensitivity compariso'!C13 -> 390000 | J13: ='DealScope sensitivity compariso'!I13*(1-'Model inputs'!B38)-'DealScope sensitivity compariso'!H13*('DealScope sensitivity compariso'!B13*'DealScope sensitivity compariso'!D13+'Model inputs'!B42*'Model inputs'!B41)-SUM('Model inputs'!B76,'Model inputs'!B77) -> 326468.5
A14: Credit rate $0.10 | B14: =IF(IF(IF(ISERROR('DealScope sensitivity controls'!H16=1),'DealScope sensitivity controls'!H16=1,IF('DealScope sensitivity controls'!H16="","",'DealScope sensitivity controls'!H16=1))="",FALSE,IF(ISERROR('DealScope sensitivity controls'!H16=1),'DealScope sensitivity controls'!H16=1,IF('DealScope sensitivity controls'!H16="","",'DealScope sensitivity controls'!H16=1))),'Model inputs'!B6/12*'DealScope sensitivity controls'!G16,IF('DealScope sensitivity controls'!B16="","",'DealScope sensitivity controls'!B16)) -> 4 | C14: =IF(EXACT("Annual deal-team","Annual deal-team"),('Model inputs'!B45/12+MAX('DealScope sensitivity compariso'!B14-'Model inputs'!B24/12,0)*'Model inputs'!B32)*(1-'DealScope sensitivity controls'!C16),('Model inputs'!B45/12+'Model inputs'!B9*'DealScope sensitivity compariso'!B14)*(1-'DealScope sensitivity controls'!C16)) -> 4000 | D14: ='Model inputs'!B15*'DealScope sensitivity controls'!E16*'DealScope sensitivity controls'!D16*'Model inputs'!B17+'Model inputs'!B30+'Model inputs'!B39+'Model inputs'!B19 -> 94.65 | E14: =IFERROR('DealScope sensitivity compariso'!C14/'DealScope sensitivity compariso'!B14,"") -> 1000 | F14: =IFERROR(('DealScope sensitivity compariso'!E14-'DealScope sensitivity compariso'!D14)/'DealScope sensitivity compariso'!E14,"") -> 0.90535 | G14: =IFERROR(('DealScope sensitivity compariso'!C14*(1-'Model inputs'!B38)-'DealScope sensitivity compariso'!B14*'DealScope sensitivity compariso'!D14-'Model inputs'!B42*'Model inputs'!B41)/'DealScope sensitivity compariso'!C14,"") -> 0.86785 | H14: ='Model inputs'!B117+IF(IF(IF(IF(ISERROR('Model inputs'!B29=1),'Model inputs'!B29=1,IF('Model inputs'!B29="","",'Model inputs'!B29=1))="",FALSE,IF(ISERROR('Model inputs'!B29=1),'Model inputs'!B29=1,IF('Model inputs'!B29="","",'Model inputs'!B29=1))),'Model inputs'!B43*MIN(MAX((11-'DealScope sensitivity controls'!F16)/'Model inputs'!B21,0),1),IF(IF(IF(ISERROR(11>'DealScope sensitivity controls'!F16),11>'DealScope sensitivity controls'!F16,IF('DealScope sensitivity controls'!F16="","",11>'DealScope sensitivity controls'!F16))="",FALSE,IF(ISERROR(11>'DealScope sensitivity controls'!F16),11>'DealScope sensitivity controls'!F16,IF('DealScope sensitivity controls'!F16="","",11>'DealScope sensitivity controls'!F16))),IF('Model inputs'!B43="","",'Model inputs'!B43),0))="",0,IF(IF(IF(ISERROR('Model inputs'!B29=1),'Model inputs'!B29=1,IF('Model inputs'!B29="","",'Model inputs'!B29=1))="",FALSE,IF(ISERROR('Model inputs'!B29=1),'Model inputs'!B29=1,IF('Model inputs'!B29="","",'Model inputs'!B29=1))),'Model inputs'!B43*MIN(MAX((11-'DealScope sensitivity controls'!F16)/'Model inputs'!B21,0),1),IF(IF(IF(ISERROR(11>'DealScope sensitivity controls'!F16),11>'DealScope sensitivity controls'!F16,IF('DealScope sensitivity controls'!F16="","",11>'DealScope sensitivity controls'!F16))="",FALSE,IF(ISERROR(11>'DealScope sensitivity controls'!F16),11>'DealScope sensitivity controls'!F16,IF('DealScope sensitivity controls'!F16="","",11>'DealScope sensitivity controls'!F16))),IF('Model inputs'!B43="","",'Model inputs'!B43),0)))+IF(IF(IF(IF(ISERROR('Model inputs'!B29=1),'Model inputs'!B29=1,IF('Model inputs'!B29="","",'Model inputs'!B29=1))="",FALSE,IF(ISERROR('Model inputs'!B29=1),'Model inputs'!B29=1,IF('Model inputs'!B29="","",'Model inputs'!B29=1))),'Model inputs'!B43*MIN(MAX((12-'DealScope sensitivity controls'!F16)/'Model inputs'!B21,0),1),IF(IF(IF(ISERROR(12>'DealScope sensitivity controls'!F16),12>'DealScope sensitivity controls'!F16,IF('DealScope sensitivity controls'!F16="","",12>'DealScope sensitivity controls'!F16))="",FALSE,IF(ISERROR(12>'DealScope sensitivity controls'!F16),12>'DealScope sensitivity controls'!F16,IF('DealScope sensitivity controls'!F16="","",12>'DealScope sensitivity controls'!F16))),IF('Model inputs'!B43="","",'Model inputs'!B43),0))="",0,IF(IF(IF(ISERROR('Model inputs'!B29=1),'Model inputs'!B29=1,IF('Model inputs'!B29="","",'Model inputs'!B29=1))="",FALSE,IF(ISERROR('Model inputs'!B29=1),'Model inputs'!B29=1,IF('Model inputs'!B29="","",'Model inputs'!B29=1))),'Model inputs'!B43*MIN(MAX((12-'DealScope sensitivity controls'!F16)/'Model inputs'!B21,0),1),IF(IF(IF(ISERROR(12>'DealScope sensitivity controls'!F16),12>'DealScope sensitivity controls'!F16,IF('DealScope sensitivity controls'!F16="","",12>'DealScope sensitivity controls'!F16))="",FALSE,IF(ISERROR(12>'DealScope sensitivity controls'!F16),12>'DealScope sensitivity controls'!F16,IF('DealScope sensitivity controls'!F16="","",12>'DealScope sensitivity controls'!F16))),IF('Model inputs'!B43="","",'Model inputs'!B43),0))) -> 97.5 | I14: ='DealScope sensitivity compariso'!H14*'DealScope sensitivity compariso'!C14 -> 390000 | J14: ='DealScope sensitivity compariso'!I14*(1-'Model inputs'!B38)-'DealScope sensitivity compariso'!H14*('DealScope sensitivity compariso'!B14*'DealScope sensitivity compariso'!D14+'Model inputs'!B42*'Model inputs'!B41)-SUM('Model inputs'!B76,'Model inputs'!B77) -> 325961.5
A15: Credit rate $0.25 | B15: =IF(IF(IF(ISERROR('DealScope sensitivity controls'!H17=1),'DealScope sensitivity controls'!H17=1,IF('DealScope sensitivity controls'!H17="","",'DealScope sensitivity controls'!H17=1))="",FALSE,IF(ISERROR('DealScope sensitivity controls'!H17=1),'DealScope sensitivity controls'!H17=1,IF('DealScope sensitivity controls'!H17="","",'DealScope sensitivity controls'!H17=1))),'Model inputs'!B6/12*'DealScope sensitivity controls'!G17,IF('DealScope sensitivity controls'!B17="","",'DealScope sensitivity controls'!B17)) -> 4 | C15: =IF(EXACT("Annual deal-team","Annual deal-team"),('Model inputs'!B45/12+MAX('DealScope sensitivity compariso'!B15-'Model inputs'!B24/12,0)*'Model inputs'!B32)*(1-'DealScope sensitivity controls'!C17),('Model inputs'!B45/12+'Model inputs'!B9*'DealScope sensitivity compariso'!B15)*(1-'DealScope sensitivity controls'!C17)) -> 4000 | D15: ='Model inputs'!B15*'DealScope sensitivity controls'!E17*'DealScope sensitivity controls'!D17*'Model inputs'!B17+'Model inputs'!B30+'Model inputs'!B39+'Model inputs'!B19 -> 98.55 | E15: =IFERROR('DealScope sensitivity compariso'!C15/'DealScope sensitivity compariso'!B15,"") -> 1000 | F15: =IFERROR(('DealScope sensitivity compariso'!E15-'DealScope sensitivity compariso'!D15)/'DealScope sensitivity compariso'!E15,"") -> 0.90145 | G15: =IFERROR(('DealScope sensitivity compariso'!C15*(1-'Model inputs'!B38)-'DealScope sensitivity compariso'!B15*'DealScope sensitivity compariso'!D15-'Model inputs'!B42*'Model inputs'!B41)/'DealScope sensitivity compariso'!C15,"") -> 0.86395 | H15: ='Model inputs'!B122+IF(IF(IF(IF(ISERROR('Model inputs'!B29=1),'Model inputs'!B29=1,IF('Model inputs'!B29="","",'Model inputs'!B29=1))="",FALSE,IF(ISERROR('Model inputs'!B29=1),'Model inputs'!B29=1,IF('Model inputs'!B29="","",'Model inputs'!B29=1))),'Model inputs'!B43*MIN(MAX((11-'DealScope sensitivity controls'!F17)/'Model inputs'!B21,0),1),IF(IF(IF(ISERROR(11>'DealScope sensitivity controls'!F17),11>'DealScope sensitivity controls'!F17,IF('DealScope sensitivity controls'!F17="","",11>'DealScope sensitivity controls'!F17))="",FALSE,IF(ISERROR(11>'DealScope sensitivity controls'!F17),11>'DealScope sensitivity controls'!F17,IF('DealScope sensitivity controls'!F17="","",11>'DealScope sensitivity controls'!F17))),IF('Model inputs'!B43="","",'Model inputs'!B43),0))="",0,IF(IF(IF(ISERROR('Model inputs'!B29=1),'Model inputs'!B29=1,IF('Model inputs'!B29="","",'Model inputs'!B29=1))="",FALSE,IF(ISERROR('Model inputs'!B29=1),'Model inputs'!B29=1,IF('Model inputs'!B29="","",'Model inputs'!B29=1))),'Model inputs'!B43*MIN(MAX((11-'DealScope sensitivity controls'!F17)/'Model inputs'!B21,0),1),IF(IF(IF(ISERROR(11>'DealScope sensitivity controls'!F17),11>'DealScope sensitivity controls'!F17,IF('DealScope sensitivity controls'!F17="","",11>'DealScope sensitivity controls'!F17))="",FALSE,IF(ISERROR(11>'DealScope sensitivity controls'!F17),11>'DealScope sensitivity controls'!F17,IF('DealScope sensitivity controls'!F17="","",11>'DealScope sensitivity controls'!F17))),IF('Model inputs'!B43="","",'Model inputs'!B43),0)))+IF(IF(IF(IF(ISERROR('Model inputs'!B29=1),'Model inputs'!B29=1,IF('Model inputs'!B29="","",'Model inputs'!B29=1))="",FALSE,IF(ISERROR('Model inputs'!B29=1),'Model inputs'!B29=1,IF('Model inputs'!B29="","",'Model inputs'!B29=1))),'Model inputs'!B43*MIN(MAX((12-'DealScope sensitivity controls'!F17)/'Model inputs'!B21,0),1),IF(IF(IF(ISERROR(12>'DealScope sensitivity controls'!F17),12>'DealScope sensitivity controls'!F17,IF('DealScope sensitivity controls'!F17="","",12>'DealScope sensitivity controls'!F17))="",FALSE,IF(ISERROR(12>'DealScope sensitivity controls'!F17),12>'DealScope sensitivity controls'!F17,IF('DealScope sensitivity controls'!F17="","",12>'DealScope sensitivity controls'!F17))),IF('Model inputs'!B43="","",'Model inputs'!B43),0))="",0,IF(IF(IF(ISERROR('Model inputs'!B29=1),'Model inputs'!B29=1,IF('Model inputs'!B29="","",'Model inputs'!B29=1))="",FALSE,IF(ISERROR('Model inputs'!B29=1),'Model inputs'!B29=1,IF('Model inputs'!B29="","",'Model inputs'!B29=1))),'Model inputs'!B43*MIN(MAX((12-'DealScope sensitivity controls'!F17)/'Model inputs'!B21,0),1),IF(IF(IF(ISERROR(12>'DealScope sensitivity controls'!F17),12>'DealScope sensitivity controls'!F17,IF('DealScope sensitivity controls'!F17="","",12>'DealScope sensitivity controls'!F17))="",FALSE,IF(ISERROR(12>'DealScope sensitivity controls'!F17),12>'DealScope sensitivity controls'!F17,IF('DealScope sensitivity controls'!F17="","",12>'DealScope sensitivity controls'!F17))),IF('Model inputs'!B43="","",'Model inputs'!B43),0))) -> 97.5 | I15: ='DealScope sensitivity compariso'!H15*'DealScope sensitivity compariso'!C15 -> 390000 | J15: ='DealScope sensitivity compariso'!I15*(1-'Model inputs'!B38)-'DealScope sensitivity compariso'!H15*('DealScope sensitivity compariso'!B15*'DealScope sensitivity compariso'!D15+'Model inputs'!B42*'Model inputs'!B41)-SUM('Model inputs'!B76,'Model inputs'!B77) -> 324440.5
A16: Data cost x1 | B16: =IF(IF(IF(ISERROR('DealScope sensitivity controls'!H12=1),'DealScope sensitivity controls'!H12=1,IF('DealScope sensitivity controls'!H12="","",'DealScope sensitivity controls'!H12=1))="",FALSE,IF(ISERROR('DealScope sensitivity controls'!H12=1),'DealScope sensitivity controls'!H12=1,IF('DealScope sensitivity controls'!H12="","",'DealScope sensitivity controls'!H12=1))),'Model inputs'!B6/12*'DealScope sensitivity controls'!G12,IF('DealScope sensitivity controls'!B12="","",'DealScope sensitivity controls'!B12)) -> 4 | C16: =IF(EXACT("Annual deal-team","Annual deal-team"),('Model inputs'!B45/12+MAX('DealScope sensitivity compariso'!B16-'Model inputs'!B24/12,0)*'Model inputs'!B32)*(1-'DealScope sensitivity controls'!C12),('Model inputs'!B45/12+'Model inputs'!B9*'DealScope sensitivity compariso'!B16)*(1-'DealScope sensitivity controls'!C12)) -> 4000 | D16: ='Model inputs'!B15*'DealScope sensitivity controls'!E12*'DealScope sensitivity controls'!D12*'Model inputs'!B17+'Model inputs'!B30+'Model inputs'!B39+'Model inputs'!B19 -> 94.65 | E16: =IFERROR('DealScope sensitivity compariso'!C16/'DealScope sensitivity compariso'!B16,"") -> 1000 | F16: =IFERROR(('DealScope sensitivity compariso'!E16-'DealScope sensitivity compariso'!D16)/'DealScope sensitivity compariso'!E16,"") -> 0.90535 | G16: =IFERROR(('DealScope sensitivity compariso'!C16*(1-'Model inputs'!B38)-'DealScope sensitivity compariso'!B16*'DealScope sensitivity compariso'!D16-'Model inputs'!B42*'Model inputs'!B41)/'DealScope sensitivity compariso'!C16,"") -> 0.86785 | H16: ='Model inputs'!B127+IF(IF(IF(IF(ISERROR('Model inputs'!B29=1),'Model inputs'!B29=1,IF('Model inputs'!B29="","",'Model inputs'!B29=1))="",FALSE,IF(ISERROR('Model inputs'!B29=1),'Model inputs'!B29=1,IF('Model inputs'!B29="","",'Model inputs'!B29=1))),'Model inputs'!B43*MIN(MAX((11-'DealScope sensitivity controls'!F12)/'Model inputs'!B21,0),1),IF(IF(IF(ISERROR(11>'DealScope sensitivity controls'!F12),11>'DealScope sensitivity controls'!F12,IF('DealScope sensitivity controls'!F12="","",11>'DealScope sensitivity controls'!F12))="",FALSE,IF(ISERROR(11>'DealScope sensitivity controls'!F12),11>'DealScope sensitivity controls'!F12,IF('DealScope sensitivity controls'!F12="","",11>'DealScope sensitivity controls'!F12))),IF('Model inputs'!B43="","",'Model inputs'!B43),0))="",0,IF(IF(IF(ISERROR('Model inputs'!B29=1),'Model inputs'!B29=1,IF('Model inputs'!B29="","",'Model inputs'!B29=1))="",FALSE,IF(ISERROR('Model inputs'!B29=1),'Model inputs'!B29=1,IF('Model inputs'!B29="","",'Model inputs'!B29=1))),'Model inputs'!B43*MIN(MAX((11-'DealScope sensitivity controls'!F12)/'Model inputs'!B21,0),1),IF(IF(IF(ISERROR(11>'DealScope sensitivity controls'!F12),11>'DealScope sensitivity controls'!F12,IF('DealScope sensitivity controls'!F12="","",11>'DealScope sensitivity controls'!F12))="",FALSE,IF(ISERROR(11>'DealScope sensitivity controls'!F12),11>'DealScope sensitivity controls'!F12,IF('DealScope sensitivity controls'!F12="","",11>'DealScope sensitivity controls'!F12))),IF('Model inputs'!B43="","",'Model inputs'!B43),0)))+IF(IF(IF(IF(ISERROR('Model inputs'!B29=1),'Model inputs'!B29=1,IF('Model inputs'!B29="","",'Model inputs'!B29=1))="",FALSE,IF(ISERROR('Model inputs'!B29=1),'Model inputs'!B29=1,IF('Model inputs'!B29="","",'Model inputs'!B29=1))),'Model inputs'!B43*MIN(MAX((12-'DealScope sensitivity controls'!F12)/'Model inputs'!B21,0),1),IF(IF(IF(ISERROR(12>'DealScope sensitivity controls'!F12),12>'DealScope sensitivity controls'!F12,IF('DealScope sensitivity controls'!F12="","",12>'DealScope sensitivity controls'!F12))="",FALSE,IF(ISERROR(12>'DealScope sensitivity controls'!F12),12>'DealScope sensitivity controls'!F12,IF('DealScope sensitivity controls'!F12="","",12>'DealScope sensitivity controls'!F12))),IF('Model inputs'!B43="","",'Model inputs'!B43),0))="",0,IF(IF(IF(ISERROR('Model inputs'!B29=1),'Model inputs'!B29=1,IF('Model inputs'!B29="","",'Model inputs'!B29=1))="",FALSE,IF(ISERROR('Model inputs'!B29=1),'Model inputs'!B29=1,IF('Model inputs'!B29="","",'Model inputs'!B29=1))),'Model inputs'!B43*MIN(MAX((12-'DealScope sensitivity controls'!F12)/'Model inputs'!B21,0),1),IF(IF(IF(ISERROR(12>'DealScope sensitivity controls'!F12),12>'DealScope sensitivity controls'!F12,IF('DealScope sensitivity controls'!F12="","",12>'DealScope sensitivity controls'!F12))="",FALSE,IF(ISERROR(12>'DealScope sensitivity controls'!F12),12>'DealScope sensitivity controls'!F12,IF('DealScope sensitivity controls'!F12="","",12>'DealScope sensitivity controls'!F12))),IF('Model inputs'!B43="","",'Model inputs'!B43),0))) -> 97.5 | I16: ='DealScope sensitivity compariso'!H16*'DealScope sensitivity compariso'!C16 -> 390000 | J16: ='DealScope sensitivity compariso'!I16*(1-'Model inputs'!B38)-'DealScope sensitivity compariso'!H16*('DealScope sensitivity compariso'!B16*'DealScope sensitivity compariso'!D16+'Model inputs'!B42*'Model inputs'!B41)-SUM('Model inputs'!B76,'Model inputs'!B77) -> 325961.5
A17: Data cost x2 | B17: =IF(IF(IF(ISERROR('DealScope sensitivity controls'!H13=1),'DealScope sensitivity controls'!H13=1,IF('DealScope sensitivity controls'!H13="","",'DealScope sensitivity controls'!H13=1))="",FALSE,IF(ISERROR('DealScope sensitivity controls'!H13=1),'DealScope sensitivity controls'!H13=1,IF('DealScope sensitivity controls'!H13="","",'DealScope sensitivity controls'!H13=1))),'Model inputs'!B6/12*'DealScope sensitivity controls'!G13,IF('DealScope sensitivity controls'!B13="","",'DealScope sensitivity controls'!B13)) -> 4 | C17: =IF(EXACT("Annual deal-team","Annual deal-team"),('Model inputs'!B45/12+MAX('DealScope sensitivity compariso'!B17-'Model inputs'!B24/12,0)*'Model inputs'!B32)*(1-'DealScope sensitivity controls'!C13),('Model inputs'!B45/12+'Model inputs'!B9*'DealScope sensitivity compariso'!B17)*(1-'DealScope sensitivity controls'!C13)) -> 4000 | D17: ='Model inputs'!B15*'DealScope sensitivity controls'!E13*'DealScope sensitivity controls'!D13*'Model inputs'!B17+'Model inputs'!B30+'Model inputs'!B39+'Model inputs'!B19 -> 97.25 | E17: =IFERROR('DealScope sensitivity compariso'!C17/'DealScope sensitivity compariso'!B17,"") -> 1000 | F17: =IFERROR(('DealScope sensitivity compariso'!E17-'DealScope sensitivity compariso'!D17)/'DealScope sensitivity compariso'!E17,"") -> 0.90275 | G17: =IFERROR(('DealScope sensitivity compariso'!C17*(1-'Model inputs'!B38)-'DealScope sensitivity compariso'!B17*'DealScope sensitivity compariso'!D17-'Model inputs'!B42*'Model inputs'!B41)/'DealScope sensitivity compariso'!C17,"") -> 0.86525 | H17: ='Model inputs'!B132+IF(IF(IF(IF(ISERROR('Model inputs'!B29=1),'Model inputs'!B29=1,IF('Model inputs'!B29="","",'Model inputs'!B29=1))="",FALSE,IF(ISERROR('Model inputs'!B29=1),'Model inputs'!B29=1,IF('Model inputs'!B29="","",'Model inputs'!B29=1))),'Model inputs'!B43*MIN(MAX((11-'DealScope sensitivity controls'!F13)/'Model inputs'!B21,0),1),IF(IF(IF(ISERROR(11>'DealScope sensitivity controls'!F13),11>'DealScope sensitivity controls'!F13,IF('DealScope sensitivity controls'!F13="","",11>'DealScope sensitivity controls'!F13))="",FALSE,IF(ISERROR(11>'DealScope sensitivity controls'!F13),11>'DealScope sensitivity controls'!F13,IF('DealScope sensitivity controls'!F13="","",11>'DealScope sensitivity controls'!F13))),IF('Model inputs'!B43="","",'Model inputs'!B43),0))="",0,IF(IF(IF(ISERROR('Model inputs'!B29=1),'Model inputs'!B29=1,IF('Model inputs'!B29="","",'Model inputs'!B29=1))="",FALSE,IF(ISERROR('Model inputs'!B29=1),'Model inputs'!B29=1,IF('Model inputs'!B29="","",'Model inputs'!B29=1))),'Model inputs'!B43*MIN(MAX((11-'DealScope sensitivity controls'!F13)/'Model inputs'!B21,0),1),IF(IF(IF(ISERROR(11>'DealScope sensitivity controls'!F13),11>'DealScope sensitivity controls'!F13,IF('DealScope sensitivity controls'!F13="","",11>'DealScope sensitivity controls'!F13))="",FALSE,IF(ISERROR(11>'DealScope sensitivity controls'!F13),11>'DealScope sensitivity controls'!F13,IF('DealScope sensitivity controls'!F13="","",11>'DealScope sensitivity controls'!F13))),IF('Model inputs'!B43="","",'Model inputs'!B43),0)))+IF(IF(IF(IF(ISERROR('Model inputs'!B29=1),'Model inputs'!B29=1,IF('Model inputs'!B29="","",'Model inputs'!B29=1))="",FALSE,IF(ISERROR('Model inputs'!B29=1),'Model inputs'!B29=1,IF('Model inputs'!B29="","",'Model inputs'!B29=1))),'Model inputs'!B43*MIN(MAX((12-'DealScope sensitivity controls'!F13)/'Model inputs'!B21,0),1),IF(IF(IF(ISERROR(12>'DealScope sensitivity controls'!F13),12>'DealScope sensitivity controls'!F13,IF('DealScope sensitivity controls'!F13="","",12>'DealScope sensitivity controls'!F13))="",FALSE,IF(ISERROR(12>'DealScope sensitivity controls'!F13),12>'DealScope sensitivity controls'!F13,IF('DealScope sensitivity controls'!F13="","",12>'DealScope sensitivity controls'!F13))),IF('Model inputs'!B43="","",'Model inputs'!B43),0))="",0,IF(IF(IF(ISERROR('Model inputs'!B29=1),'Model inputs'!B29=1,IF('Model inputs'!B29="","",'Model inputs'!B29=1))="",FALSE,IF(ISERROR('Model inputs'!B29=1),'Model inputs'!B29=1,IF('Model inputs'!B29="","",'Model inputs'!B29=1))),'Model inputs'!B43*MIN(MAX((12-'DealScope sensitivity controls'!F13)/'Model inputs'!B21,0),1),IF(IF(IF(ISERROR(12>'DealScope sensitivity controls'!F13),12>'DealScope sensitivity controls'!F13,IF('DealScope sensitivity controls'!F13="","",12>'DealScope sensitivity controls'!F13))="",FALSE,IF(ISERROR(12>'DealScope sensitivity controls'!F13),12>'DealScope sensitivity controls'!F13,IF('DealScope sensitivity controls'!F13="","",12>'DealScope sensitivity controls'!F13))),IF('Model inputs'!B43="","",'Model inputs'!B43),0))) -> 97.5 | I17: ='DealScope sensitivity compariso'!H17*'DealScope sensitivity compariso'!C17 -> 390000 | J17: ='DealScope sensitivity compariso'!I17*(1-'Model inputs'!B38)-'DealScope sensitivity compariso'!H17*('DealScope sensitivity compariso'!B17*'DealScope sensitivity compariso'!D17+'Model inputs'!B42*'Model inputs'!B41)-SUM('Model inputs'!B76,'Model inputs'!B77) -> 324947.5
A18: Data cost x3 | B18: =IF(IF(IF(ISERROR('DealScope sensitivity controls'!H14=1),'DealScope sensitivity controls'!H14=1,IF('DealScope sensitivity controls'!H14="","",'DealScope sensitivity controls'!H14=1))="",FALSE,IF(ISERROR('DealScope sensitivity controls'!H14=1),'DealScope sensitivity controls'!H14=1,IF('DealScope sensitivity controls'!H14="","",'DealScope sensitivity controls'!H14=1))),'Model inputs'!B6/12*'DealScope sensitivity controls'!G14,IF('DealScope sensitivity controls'!B14="","",'DealScope sensitivity controls'!B14)) -> 4 | C18: =IF(EXACT("Annual deal-team","Annual deal-team"),('Model inputs'!B45/12+MAX('DealScope sensitivity compariso'!B18-'Model inputs'!B24/12,0)*'Model inputs'!B32)*(1-'DealScope sensitivity controls'!C14),('Model inputs'!B45/12+'Model inputs'!B9*'DealScope sensitivity compariso'!B18)*(1-'DealScope sensitivity controls'!C14)) -> 4000 | D18: ='Model inputs'!B15*'DealScope sensitivity controls'!E14*'DealScope sensitivity controls'!D14*'Model inputs'!B17+'Model inputs'!B30+'Model inputs'!B39+'Model inputs'!B19 -> 99.85 | E18: =IFERROR('DealScope sensitivity compariso'!C18/'DealScope sensitivity compariso'!B18,"") -> 1000 | F18: =IFERROR(('DealScope sensitivity compariso'!E18-'DealScope sensitivity compariso'!D18)/'DealScope sensitivity compariso'!E18,"") -> 0.90015 | G18: =IFERROR(('DealScope sensitivity compariso'!C18*(1-'Model inputs'!B38)-'DealScope sensitivity compariso'!B18*'DealScope sensitivity compariso'!D18-'Model inputs'!B42*'Model inputs'!B41)/'DealScope sensitivity compariso'!C18,"") -> 0.86265 | H18: ='Model inputs'!B137+IF(IF(IF(IF(ISERROR('Model inputs'!B29=1),'Model inputs'!B29=1,IF('Model inputs'!B29="","",'Model inputs'!B29=1))="",FALSE,IF(ISERROR('Model inputs'!B29=1),'Model inputs'!B29=1,IF('Model inputs'!B29="","",'Model inputs'!B29=1))),'Model inputs'!B43*MIN(MAX((11-'DealScope sensitivity controls'!F14)/'Model inputs'!B21,0),1),IF(IF(IF(ISERROR(11>'DealScope sensitivity controls'!F14),11>'DealScope sensitivity controls'!F14,IF('DealScope sensitivity controls'!F14="","",11>'DealScope sensitivity controls'!F14))="",FALSE,IF(ISERROR(11>'DealScope sensitivity controls'!F14),11>'DealScope sensitivity controls'!F14,IF('DealScope sensitivity controls'!F14="","",11>'DealScope sensitivity controls'!F14))),IF('Model inputs'!B43="","",'Model inputs'!B43),0))="",0,IF(IF(IF(ISERROR('Model inputs'!B29=1),'Model inputs'!B29=1,IF('Model inputs'!B29="","",'Model inputs'!B29=1))="",FALSE,IF(ISERROR('Model inputs'!B29=1),'Model inputs'!B29=1,IF('Model inputs'!B29="","",'Model inputs'!B29=1))),'Model inputs'!B43*MIN(MAX((11-'DealScope sensitivity controls'!F14)/'Model inputs'!B21,0),1),IF(IF(IF(ISERROR(11>'DealScope sensitivity controls'!F14),11>'DealScope sensitivity controls'!F14,IF('DealScope sensitivity controls'!F14="","",11>'DealScope sensitivity controls'!F14))="",FALSE,IF(ISERROR(11>'DealScope sensitivity controls'!F14),11>'DealScope sensitivity controls'!F14,IF('DealScope sensitivity controls'!F14="","",11>'DealScope sensitivity controls'!F14))),IF('Model inputs'!B43="","",'Model inputs'!B43),0)))+IF(IF(IF(IF(ISERROR('Model inputs'!B29=1),'Model inputs'!B29=1,IF('Model inputs'!B29="","",'Model inputs'!B29=1))="",FALSE,IF(ISERROR('Model inputs'!B29=1),'Model inputs'!B29=1,IF('Model inputs'!B29="","",'Model inputs'!B29=1))),'Model inputs'!B43*MIN(MAX((12-'DealScope sensitivity controls'!F14)/'Model inputs'!B21,0),1),IF(IF(IF(ISERROR(12>'DealScope sensitivity controls'!F14),12>'DealScope sensitivity controls'!F14,IF('DealScope sensitivity controls'!F14="","",12>'DealScope sensitivity controls'!F14))="",FALSE,IF(ISERROR(12>'DealScope sensitivity controls'!F14),12>'DealScope sensitivity controls'!F14,IF('DealScope sensitivity controls'!F14="","",12>'DealScope sensitivity controls'!F14))),IF('Model inputs'!B43="","",'Model inputs'!B43),0))="",0,IF(IF(IF(ISERROR('Model inputs'!B29=1),'Model inputs'!B29=1,IF('Model inputs'!B29="","",'Model inputs'!B29=1))="",FALSE,IF(ISERROR('Model inputs'!B29=1),'Model inputs'!B29=1,IF('Model inputs'!B29="","",'Model inputs'!B29=1))),'Model inputs'!B43*MIN(MAX((12-'DealScope sensitivity controls'!F14)/'Model inputs'!B21,0),1),IF(IF(IF(ISERROR(12>'DealScope sensitivity controls'!F14),12>'DealScope sensitivity controls'!F14,IF('DealScope sensitivity controls'!F14="","",12>'DealScope sensitivity controls'!F14))="",FALSE,IF(ISERROR(12>'DealScope sensitivity controls'!F14),12>'DealScope sensitivity controls'!F14,IF('DealScope sensitivity controls'!F14="","",12>'DealScope sensitivity controls'!F14))),IF('Model inputs'!B43="","",'Model inputs'!B43),0))) -> 97.5 | I18: ='DealScope sensitivity compariso'!H18*'DealScope sensitivity compariso'!C18 -> 390000 | J18: ='DealScope sensitivity compariso'!I18*(1-'Model inputs'!B38)-'DealScope sensitivity compariso'!H18*('DealScope sensitivity compariso'!B18*'DealScope sensitivity compariso'!D18+'Model inputs'!B42*'Model inputs'!B41)-SUM('Model inputs'!B76,'Model inputs'!B77) -> 323933.5
A19: Discount 0% | B19: =IF(IF(IF(ISERROR('DealScope sensitivity controls'!H9=1),'DealScope sensitivity controls'!H9=1,IF('DealScope sensitivity controls'!H9="","",'DealScope sensitivity controls'!H9=1))="",FALSE,IF(ISERROR('DealScope sensitivity controls'!H9=1),'DealScope sensitivity controls'!H9=1,IF('DealScope sensitivity controls'!H9="","",'DealScope sensitivity controls'!H9=1))),'Model inputs'!B6/12*'DealScope sensitivity controls'!G9,IF('DealScope sensitivity controls'!B9="","",'DealScope sensitivity controls'!B9)) -> 4 | C19: =IF(EXACT("Annual deal-team","Annual deal-team"),('Model inputs'!B45/12+MAX('DealScope sensitivity compariso'!B19-'Model inputs'!B24/12,0)*'Model inputs'!B32)*(1-'DealScope sensitivity controls'!C9),('Model inputs'!B45/12+'Model inputs'!B9*'DealScope sensitivity compariso'!B19)*(1-'DealScope sensitivity controls'!C9)) -> 4000 | D19: ='Model inputs'!B15*'DealScope sensitivity controls'!E9*'DealScope sensitivity controls'!D9*'Model inputs'!B17+'Model inputs'!B30+'Model inputs'!B39+'Model inputs'!B19 -> 94.65 | E19: =IFERROR('DealScope sensitivity compariso'!C19/'DealScope sensitivity compariso'!B19,"") -> 1000 | F19: =IFERROR(('DealScope sensitivity compariso'!E19-'DealScope sensitivity compariso'!D19)/'DealScope sensitivity compariso'!E19,"") -> 0.90535 | G19: =IFERROR(('DealScope sensitivity compariso'!C19*(1-'Model inputs'!B38)-'DealScope sensitivity compariso'!B19*'DealScope sensitivity compariso'!D19-'Model inputs'!B42*'Model inputs'!B41)/'DealScope sensitivity compariso'!C19,"") -> 0.86785 | H19: ='Model inputs'!B142+IF(IF(IF(IF(ISERROR('Model inputs'!B29=1),'Model inputs'!B29=1,IF('Model inputs'!B29="","",'Model inputs'!B29=1))="",FALSE,IF(ISERROR('Model inputs'!B29=1),'Model inputs'!B29=1,IF('Model inputs'!B29="","",'Model inputs'!B29=1))),'Model inputs'!B43*MIN(MAX((11-'DealScope sensitivity controls'!F9)/'Model inputs'!B21,0),1),IF(IF(IF(ISERROR(11>'DealScope sensitivity controls'!F9),11>'DealScope sensitivity controls'!F9,IF('DealScope sensitivity controls'!F9="","",11>'DealScope sensitivity controls'!F9))="",FALSE,IF(ISERROR(11>'DealScope sensitivity controls'!F9),11>'DealScope sensitivity controls'!F9,IF('DealScope sensitivity controls'!F9="","",11>'DealScope sensitivity controls'!F9))),IF('Model inputs'!B43="","",'Model inputs'!B43),0))="",0,IF(IF(IF(ISERROR('Model inputs'!B29=1),'Model inputs'!B29=1,IF('Model inputs'!B29="","",'Model inputs'!B29=1))="",FALSE,IF(ISERROR('Model inputs'!B29=1),'Model inputs'!B29=1,IF('Model inputs'!B29="","",'Model inputs'!B29=1))),'Model inputs'!B43*MIN(MAX((11-'DealScope sensitivity controls'!F9)/'Model inputs'!B21,0),1),IF(IF(IF(ISERROR(11>'DealScope sensitivity controls'!F9),11>'DealScope sensitivity controls'!F9,IF('DealScope sensitivity controls'!F9="","",11>'DealScope sensitivity controls'!F9))="",FALSE,IF(ISERROR(11>'DealScope sensitivity controls'!F9),11>'DealScope sensitivity controls'!F9,IF('DealScope sensitivity controls'!F9="","",11>'DealScope sensitivity controls'!F9))),IF('Model inputs'!B43="","",'Model inputs'!B43),0)))+IF(IF(IF(IF(ISERROR('Model inputs'!B29=1),'Model inputs'!B29=1,IF('Model inputs'!B29="","",'Model inputs'!B29=1))="",FALSE,IF(ISERROR('Model inputs'!B29=1),'Model inputs'!B29=1,IF('Model inputs'!B29="","",'Model inputs'!B29=1))),'Model inputs'!B43*MIN(MAX((12-'DealScope sensitivity controls'!F9)/'Model inputs'!B21,0),1),IF(IF(IF(ISERROR(12>'DealScope sensitivity controls'!F9),12>'DealScope sensitivity controls'!F9,IF('DealScope sensitivity controls'!F9="","",12>'DealScope sensitivity controls'!F9))="",FALSE,IF(ISERROR(12>'DealScope sensitivity controls'!F9),12>'DealScope sensitivity controls'!F9,IF('DealScope sensitivity controls'!F9="","",12>'DealScope sensitivity controls'!F9))),IF('Model inputs'!B43="","",'Model inputs'!B43),0))="",0,IF(IF(IF(ISERROR('Model inputs'!B29=1),'Model inputs'!B29=1,IF('Model inputs'!B29="","",'Model inputs'!B29=1))="",FALSE,IF(ISERROR('Model inputs'!B29=1),'Model inputs'!B29=1,IF('Model inputs'!B29="","",'Model inputs'!B29=1))),'Model inputs'!B43*MIN(MAX((12-'DealScope sensitivity controls'!F9)/'Model inputs'!B21,0),1),IF(IF(IF(ISERROR(12>'DealScope sensitivity controls'!F9),12>'DealScope sensitivity controls'!F9,IF('DealScope sensitivity controls'!F9="","",12>'DealScope sensitivity controls'!F9))="",FALSE,IF(ISERROR(12>'DealScope sensitivity controls'!F9),12>'DealScope sensitivity controls'!F9,IF('DealScope sensitivity controls'!F9="","",12>'DealScope sensitivity controls'!F9))),IF('Model inputs'!B43="","",'Model inputs'!B43),0))) -> 97.5 | I19: ='DealScope sensitivity compariso'!H19*'DealScope sensitivity compariso'!C19 -> 390000 | J19: ='DealScope sensitivity compariso'!I19*(1-'Model inputs'!B38)-'DealScope sensitivity compariso'!H19*('DealScope sensitivity compariso'!B19*'DealScope sensitivity compariso'!D19+'Model inputs'!B42*'Model inputs'!B41)-SUM('Model inputs'!B76,'Model inputs'!B77) -> 325961.5
A20: Discount 20% | B20: =IF(IF(IF(ISERROR('DealScope sensitivity controls'!H10=1),'DealScope sensitivity controls'!H10=1,IF('DealScope sensitivity controls'!H10="","",'DealScope sensitivity controls'!H10=1))="",FALSE,IF(ISERROR('DealScope sensitivity controls'!H10=1),'DealScope sensitivity controls'!H10=1,IF('DealScope sensitivity controls'!H10="","",'DealScope sensitivity controls'!H10=1))),'Model inputs'!B6/12*'DealScope sensitivity controls'!G10,IF('DealScope sensitivity controls'!B10="","",'DealScope sensitivity controls'!B10)) -> 4 | C20: =IF(EXACT("Annual deal-team","Annual deal-team"),('Model inputs'!B45/12+MAX('DealScope sensitivity compariso'!B20-'Model inputs'!B24/12,0)*'Model inputs'!B32)*(1-'DealScope sensitivity controls'!C10),('Model inputs'!B45/12+'Model inputs'!B9*'DealScope sensitivity compariso'!B20)*(1-'DealScope sensitivity controls'!C10)) -> 3200 | D20: ='Model inputs'!B15*'DealScope sensitivity controls'!E10*'DealScope sensitivity controls'!D10*'Model inputs'!B17+'Model inputs'!B30+'Model inputs'!B39+'Model inputs'!B19 -> 94.65 | E20: =IFERROR('DealScope sensitivity compariso'!C20/'DealScope sensitivity compariso'!B20,"") -> 800 | F20: =IFERROR(('DealScope sensitivity compariso'!E20-'DealScope sensitivity compariso'!D20)/'DealScope sensitivity compariso'!E20,"") -> 0.8816875 | G20: =IFERROR(('DealScope sensitivity compariso'!C20*(1-'Model inputs'!B38)-'DealScope sensitivity compariso'!B20*'DealScope sensitivity compariso'!D20-'Model inputs'!B42*'Model inputs'!B41)/'DealScope sensitivity compariso'!C20,"") -> 0.8423125 | H20: ='Model inputs'!B147+IF(IF(IF(IF(ISERROR('Model inputs'!B29=1),'Model inputs'!B29=1,IF('Model inputs'!B29="","",'Model inputs'!B29=1))="",FALSE,IF(ISERROR('Model inputs'!B29=1),'Model inputs'!B29=1,IF('Model inputs'!B29="","",'Model inputs'!B29=1))),'Model inputs'!B43*MIN(MAX((11-'DealScope sensitivity controls'!F10)/'Model inputs'!B21,0),1),IF(IF(IF(ISERROR(11>'DealScope sensitivity controls'!F10),11>'DealScope sensitivity controls'!F10,IF('DealScope sensitivity controls'!F10="","",11>'DealScope sensitivity controls'!F10))="",FALSE,IF(ISERROR(11>'DealScope sensitivity controls'!F10),11>'DealScope sensitivity controls'!F10,IF('DealScope sensitivity controls'!F10="","",11>'DealScope sensitivity controls'!F10))),IF('Model inputs'!B43="","",'Model inputs'!B43),0))="",0,IF(IF(IF(ISERROR('Model inputs'!B29=1),'Model inputs'!B29=1,IF('Model inputs'!B29="","",'Model inputs'!B29=1))="",FALSE,IF(ISERROR('Model inputs'!B29=1),'Model inputs'!B29=1,IF('Model inputs'!B29="","",'Model inputs'!B29=1))),'Model inputs'!B43*MIN(MAX((11-'DealScope sensitivity controls'!F10)/'Model inputs'!B21,0),1),IF(IF(IF(ISERROR(11>'DealScope sensitivity controls'!F10),11>'DealScope sensitivity controls'!F10,IF('DealScope sensitivity controls'!F10="","",11>'DealScope sensitivity controls'!F10))="",FALSE,IF(ISERROR(11>'DealScope sensitivity controls'!F10),11>'DealScope sensitivity controls'!F10,IF('DealScope sensitivity controls'!F10="","",11>'DealScope sensitivity controls'!F10))),IF('Model inputs'!B43="","",'Model inputs'!B43),0)))+IF(IF(IF(IF(ISERROR('Model inputs'!B29=1),'Model inputs'!B29=1,IF('Model inputs'!B29="","",'Model inputs'!B29=1))="",FALSE,IF(ISERROR('Model inputs'!B29=1),'Model inputs'!B29=1,IF('Model inputs'!B29="","",'Model inputs'!B29=1))),'Model inputs'!B43*MIN(MAX((12-'DealScope sensitivity controls'!F10)/'Model inputs'!B21,0),1),IF(IF(IF(ISERROR(12>'DealScope sensitivity controls'!F10),12>'DealScope sensitivity controls'!F10,IF('DealScope sensitivity controls'!F10="","",12>'DealScope sensitivity controls'!F10))="",FALSE,IF(ISERROR(12>'DealScope sensitivity controls'!F10),12>'DealScope sensitivity controls'!F10,IF('DealScope sensitivity controls'!F10="","",12>'DealScope sensitivity controls'!F10))),IF('Model inputs'!B43="","",'Model inputs'!B43),0))="",0,IF(IF(IF(ISERROR('Model inputs'!B29=1),'Model inputs'!B29=1,IF('Model inputs'!B29="","",'Model inputs'!B29=1))="",FALSE,IF(ISERROR('Model inputs'!B29=1),'Model inputs'!B29=1,IF('Model inputs'!B29="","",'Model inputs'!B29=1))),'Model inputs'!B43*MIN(MAX((12-'DealScope sensitivity controls'!F10)/'Model inputs'!B21,0),1),IF(IF(IF(ISERROR(12>'DealScope sensitivity controls'!F10),12>'DealScope sensitivity controls'!F10,IF('DealScope sensitivity controls'!F10="","",12>'DealScope sensitivity controls'!F10))="",FALSE,IF(ISERROR(12>'DealScope sensitivity controls'!F10),12>'DealScope sensitivity controls'!F10,IF('DealScope sensitivity controls'!F10="","",12>'DealScope sensitivity controls'!F10))),IF('Model inputs'!B43="","",'Model inputs'!B43),0))) -> 97.5 | I20: ='DealScope sensitivity compariso'!H20*'DealScope sensitivity compariso'!C20 -> 312000 | J20: ='DealScope sensitivity compariso'!I20*(1-'Model inputs'!B38)-'DealScope sensitivity compariso'!H20*('DealScope sensitivity compariso'!B20*'DealScope sensitivity compariso'!D20+'Model inputs'!B42*'Model inputs'!B41)-SUM('Model inputs'!B76,'Model inputs'!B77) -> 250301.5
A21: Discount 40% | B21: =IF(IF(IF(ISERROR('DealScope sensitivity controls'!H11=1),'DealScope sensitivity controls'!H11=1,IF('DealScope sensitivity controls'!H11="","",'DealScope sensitivity controls'!H11=1))="",FALSE,IF(ISERROR('DealScope sensitivity controls'!H11=1),'DealScope sensitivity controls'!H11=1,IF('DealScope sensitivity controls'!H11="","",'DealScope sensitivity controls'!H11=1))),'Model inputs'!B6/12*'DealScope sensitivity controls'!G11,IF('DealScope sensitivity controls'!B11="","",'DealScope sensitivity controls'!B11)) -> 4 | C21: =IF(EXACT("Annual deal-team","Annual deal-team"),('Model inputs'!B45/12+MAX('DealScope sensitivity compariso'!B21-'Model inputs'!B24/12,0)*'Model inputs'!B32)*(1-'DealScope sensitivity controls'!C11),('Model inputs'!B45/12+'Model inputs'!B9*'DealScope sensitivity compariso'!B21)*(1-'DealScope sensitivity controls'!C11)) -> 2400 | D21: ='Model inputs'!B15*'DealScope sensitivity controls'!E11*'DealScope sensitivity controls'!D11*'Model inputs'!B17+'Model inputs'!B30+'Model inputs'!B39+'Model inputs'!B19 -> 94.65 | E21: =IFERROR('DealScope sensitivity compariso'!C21/'DealScope sensitivity compariso'!B21,"") -> 600 | F21: =IFERROR(('DealScope sensitivity compariso'!E21-'DealScope sensitivity compariso'!D21)/'DealScope sensitivity compariso'!E21,"") -> 0.84225 | G21: =IFERROR(('DealScope sensitivity compariso'!C21*(1-'Model inputs'!B38)-'DealScope sensitivity compariso'!B21*'DealScope sensitivity compariso'!D21-'Model inputs'!B42*'Model inputs'!B41)/'DealScope sensitivity compariso'!C21,"") -> 0.79975 | H21: ='Model inputs'!B152+IF(IF(IF(IF(ISERROR('Model inputs'!B29=1),'Model inputs'!B29=1,IF('Model inputs'!B29="","",'Model inputs'!B29=1))="",FALSE,IF(ISERROR('Model inputs'!B29=1),'Model inputs'!B29=1,IF('Model inputs'!B29="","",'Model inputs'!B29=1))),'Model inputs'!B43*MIN(MAX((11-'DealScope sensitivity controls'!F11)/'Model inputs'!B21,0),1),IF(IF(IF(ISERROR(11>'DealScope sensitivity controls'!F11),11>'DealScope sensitivity controls'!F11,IF('DealScope sensitivity controls'!F11="","",11>'DealScope sensitivity controls'!F11))="",FALSE,IF(ISERROR(11>'DealScope sensitivity controls'!F11),11>'DealScope sensitivity controls'!F11,IF('DealScope sensitivity controls'!F11="","",11>'DealScope sensitivity controls'!F11))),IF('Model inputs'!B43="","",'Model inputs'!B43),0))="",0,IF(IF(IF(ISERROR('Model inputs'!B29=1),'Model inputs'!B29=1,IF('Model inputs'!B29="","",'Model inputs'!B29=1))="",FALSE,IF(ISERROR('Model inputs'!B29=1),'Model inputs'!B29=1,IF('Model inputs'!B29="","",'Model inputs'!B29=1))),'Model inputs'!B43*MIN(MAX((11-'DealScope sensitivity controls'!F11)/'Model inputs'!B21,0),1),IF(IF(IF(ISERROR(11>'DealScope sensitivity controls'!F11),11>'DealScope sensitivity controls'!F11,IF('DealScope sensitivity controls'!F11="","",11>'DealScope sensitivity controls'!F11))="",FALSE,IF(ISERROR(11>'DealScope sensitivity controls'!F11),11>'DealScope sensitivity controls'!F11,IF('DealScope sensitivity controls'!F11="","",11>'DealScope sensitivity controls'!F11))),IF('Model inputs'!B43="","",'Model inputs'!B43),0)))+IF(IF(IF(IF(ISERROR('Model inputs'!B29=1),'Model inputs'!B29=1,IF('Model inputs'!B29="","",'Model inputs'!B29=1))="",FALSE,IF(ISERROR('Model inputs'!B29=1),'Model inputs'!B29=1,IF('Model inputs'!B29="","",'Model inputs'!B29=1))),'Model inputs'!B43*MIN(MAX((12-'DealScope sensitivity controls'!F11)/'Model inputs'!B21,0),1),IF(IF(IF(ISERROR(12>'DealScope sensitivity controls'!F11),12>'DealScope sensitivity controls'!F11,IF('DealScope sensitivity controls'!F11="","",12>'DealScope sensitivity controls'!F11))="",FALSE,IF(ISERROR(12>'DealScope sensitivity controls'!F11),12>'DealScope sensitivity controls'!F11,IF('DealScope sensitivity controls'!F11="","",12>'DealScope sensitivity controls'!F11))),IF('Model inputs'!B43="","",'Model inputs'!B43),0))="",0,IF(IF(IF(ISERROR('Model inputs'!B29=1),'Model inputs'!B29=1,IF('Model inputs'!B29="","",'Model inputs'!B29=1))="",FALSE,IF(ISERROR('Model inputs'!B29=1),'Model inputs'!B29=1,IF('Model inputs'!B29="","",'Model inputs'!B29=1))),'Model inputs'!B43*MIN(MAX((12-'DealScope sensitivity controls'!F11)/'Model inputs'!B21,0),1),IF(IF(IF(ISERROR(12>'DealScope sensitivity controls'!F11),12>'DealScope sensitivity controls'!F11,IF('DealScope sensitivity controls'!F11="","",12>'DealScope sensitivity controls'!F11))="",FALSE,IF(ISERROR(12>'DealScope sensitivity controls'!F11),12>'DealScope sensitivity controls'!F11,IF('DealScope sensitivity controls'!F11="","",12>'DealScope sensitivity controls'!F11))),IF('Model inputs'!B43="","",'Model inputs'!B43),0))) -> 97.5 | I21: ='DealScope sensitivity compariso'!H21*'DealScope sensitivity compariso'!C21 -> 234000 | J21: ='DealScope sensitivity compariso'!I21*(1-'Model inputs'!B38)-'DealScope sensitivity compariso'!H21*('DealScope sensitivity compariso'!B21*'DealScope sensitivity compariso'!D21+'Model inputs'!B42*'Model inputs'!B41)-SUM('Model inputs'!B76,'Model inputs'!B77) -> 174641.5
A22: Sales delay 0 months | B22: =IF(IF(IF(ISERROR('DealScope sensitivity controls'!H18=1),'DealScope sensitivity controls'!H18=1,IF('DealScope sensitivity controls'!H18="","",'DealScope sensitivity controls'!H18=1))="",FALSE,IF(ISERROR('DealScope sensitivity controls'!H18=1),'DealScope sensitivity controls'!H18=1,IF('DealScope sensitivity controls'!H18="","",'DealScope sensitivity controls'!H18=1))),'Model inputs'!B6/12*'DealScope sensitivity controls'!G18,IF('DealScope sensitivity controls'!B18="","",'DealScope sensitivity controls'!B18)) -> 4 | C22: =IF(EXACT("Annual deal-team","Annual deal-team"),('Model inputs'!B45/12+MAX('DealScope sensitivity compariso'!B22-'Model inputs'!B24/12,0)*'Model inputs'!B32)*(1-'DealScope sensitivity controls'!C18),('Model inputs'!B45/12+'Model inputs'!B9*'DealScope sensitivity compariso'!B22)*(1-'DealScope sensitivity controls'!C18)) -> 4000 | D22: ='Model inputs'!B15*'DealScope sensitivity controls'!E18*'DealScope sensitivity controls'!D18*'Model inputs'!B17+'Model inputs'!B30+'Model inputs'!B39+'Model inputs'!B19 -> 94.65 | E22: =IFERROR('DealScope sensitivity compariso'!C22/'DealScope sensitivity compariso'!B22,"") -> 1000 | F22: =IFERROR(('DealScope sensitivity compariso'!E22-'DealScope sensitivity compariso'!D22)/'DealScope sensitivity compariso'!E22,"") -> 0.90535 | G22: =IFERROR(('DealScope sensitivity compariso'!C22*(1-'Model inputs'!B38)-'DealScope sensitivity compariso'!B22*'DealScope sensitivity compariso'!D22-'Model inputs'!B42*'Model inputs'!B41)/'DealScope sensitivity compariso'!C22,"") -> 0.86785 | H22: ='Model inputs'!B157+IF(IF(IF(IF(ISERROR('Model inputs'!B29=1),'Model inputs'!B29=1,IF('Model inputs'!B29="","",'Model inputs'!B29=1))="",FALSE,IF(ISERROR('Model inputs'!B29=1),'Model inputs'!B29=1,IF('Model inputs'!B29="","",'Model inputs'!B29=1))),'Model inputs'!B43*MIN(MAX((11-'DealScope sensitivity controls'!F18)/'Model inputs'!B21,0),1),IF(IF(IF(ISERROR(11>'DealScope sensitivity controls'!F18),11>'DealScope sensitivity controls'!F18,IF('DealScope sensitivity controls'!F18="","",11>'DealScope sensitivity controls'!F18))="",FALSE,IF(ISERROR(11>'DealScope sensitivity controls'!F18),11>'DealScope sensitivity controls'!F18,IF('DealScope sensitivity controls'!F18="","",11>'DealScope sensitivity controls'!F18))),IF('Model inputs'!B43="","",'Model inputs'!B43),0))="",0,IF(IF(IF(ISERROR('Model inputs'!B29=1),'Model inputs'!B29=1,IF('Model inputs'!B29="","",'Model inputs'!B29=1))="",FALSE,IF(ISERROR('Model inputs'!B29=1),'Model inputs'!B29=1,IF('Model inputs'!B29="","",'Model inputs'!B29=1))),'Model inputs'!B43*MIN(MAX((11-'DealScope sensitivity controls'!F18)/'Model inputs'!B21,0),1),IF(IF(IF(ISERROR(11>'DealScope sensitivity controls'!F18),11>'DealScope sensitivity controls'!F18,IF('DealScope sensitivity controls'!F18="","",11>'DealScope sensitivity controls'!F18))="",FALSE,IF(ISERROR(11>'DealScope sensitivity controls'!F18),11>'DealScope sensitivity controls'!F18,IF('DealScope sensitivity controls'!F18="","",11>'DealScope sensitivity controls'!F18))),IF('Model inputs'!B43="","",'Model inputs'!B43),0)))+IF(IF(IF(IF(ISERROR('Model inputs'!B29=1),'Model inputs'!B29=1,IF('Model inputs'!B29="","",'Model inputs'!B29=1))="",FALSE,IF(ISERROR('Model inputs'!B29=1),'Model inputs'!B29=1,IF('Model inputs'!B29="","",'Model inputs'!B29=1))),'Model inputs'!B43*MIN(MAX((12-'DealScope sensitivity controls'!F18)/'Model inputs'!B21,0),1),IF(IF(IF(ISERROR(12>'DealScope sensitivity controls'!F18),12>'DealScope sensitivity controls'!F18,IF('DealScope sensitivity controls'!F18="","",12>'DealScope sensitivity controls'!F18))="",FALSE,IF(ISERROR(12>'DealScope sensitivity controls'!F18),12>'DealScope sensitivity controls'!F18,IF('DealScope sensitivity controls'!F18="","",12>'DealScope sensitivity controls'!F18))),IF('Model inputs'!B43="","",'Model inputs'!B43),0))="",0,IF(IF(IF(ISERROR('Model inputs'!B29=1),'Model inputs'!B29=1,IF('Model inputs'!B29="","",'Model inputs'!B29=1))="",FALSE,IF(ISERROR('Model inputs'!B29=1),'Model inputs'!B29=1,IF('Model inputs'!B29="","",'Model inputs'!B29=1))),'Model inputs'!B43*MIN(MAX((12-'DealScope sensitivity controls'!F18)/'Model inputs'!B21,0),1),IF(IF(IF(ISERROR(12>'DealScope sensitivity controls'!F18),12>'DealScope sensitivity controls'!F18,IF('DealScope sensitivity controls'!F18="","",12>'DealScope sensitivity controls'!F18))="",FALSE,IF(ISERROR(12>'DealScope sensitivity controls'!F18),12>'DealScope sensitivity controls'!F18,IF('DealScope sensitivity controls'!F18="","",12>'DealScope sensitivity controls'!F18))),IF('Model inputs'!B43="","",'Model inputs'!B43),0))) -> 97.5 | I22: ='DealScope sensitivity compariso'!H22*'DealScope sensitivity compariso'!C22 -> 390000 | J22: ='DealScope sensitivity compariso'!I22*(1-'Model inputs'!B38)-'DealScope sensitivity compariso'!H22*('DealScope sensitivity compariso'!B22*'DealScope sensitivity compariso'!D22+'Model inputs'!B42*'Model inputs'!B41)-SUM('Model inputs'!B76,'Model inputs'!B77) -> 325961.5
A23: Sales delay 2 months | B23: =IF(IF(IF(ISERROR('DealScope sensitivity controls'!H19=1),'DealScope sensitivity controls'!H19=1,IF('DealScope sensitivity controls'!H19="","",'DealScope sensitivity controls'!H19=1))="",FALSE,IF(ISERROR('DealScope sensitivity controls'!H19=1),'DealScope sensitivity controls'!H19=1,IF('DealScope sensitivity controls'!H19="","",'DealScope sensitivity controls'!H19=1))),'Model inputs'!B6/12*'DealScope sensitivity controls'!G19,IF('DealScope sensitivity controls'!B19="","",'DealScope sensitivity controls'!B19)) -> 4 | C23: =IF(EXACT("Annual deal-team","Annual deal-team"),('Model inputs'!B45/12+MAX('DealScope sensitivity compariso'!B23-'Model inputs'!B24/12,0)*'Model inputs'!B32)*(1-'DealScope sensitivity controls'!C19),('Model inputs'!B45/12+'Model inputs'!B9*'DealScope sensitivity compariso'!B23)*(1-'DealScope sensitivity controls'!C19)) -> 4000 | D23: ='Model inputs'!B15*'DealScope sensitivity controls'!E19*'DealScope sensitivity controls'!D19*'Model inputs'!B17+'Model inputs'!B30+'Model inputs'!B39+'Model inputs'!B19 -> 94.65 | E23: =IFERROR('DealScope sensitivity compariso'!C23/'DealScope sensitivity compariso'!B23,"") -> 1000 | F23: =IFERROR(('DealScope sensitivity compariso'!E23-'DealScope sensitivity compariso'!D23)/'DealScope sensitivity compariso'!E23,"") -> 0.90535 | G23: =IFERROR(('DealScope sensitivity compariso'!C23*(1-'Model inputs'!B38)-'DealScope sensitivity compariso'!B23*'DealScope sensitivity compariso'!D23-'Model inputs'!B42*'Model inputs'!B41)/'DealScope sensitivity compariso'!C23,"") -> 0.86785 | H23: ='Model inputs'!B162+IF(IF(IF(IF(ISERROR('Model inputs'!B29=1),'Model inputs'!B29=1,IF('Model inputs'!B29="","",'Model inputs'!B29=1))="",FALSE,IF(ISERROR('Model inputs'!B29=1),'Model inputs'!B29=1,IF('Model inputs'!B29="","",'Model inputs'!B29=1))),'Model inputs'!B43*MIN(MAX((11-'DealScope sensitivity controls'!F19)/'Model inputs'!B21,0),1),IF(IF(IF(ISERROR(11>'DealScope sensitivity controls'!F19),11>'DealScope sensitivity controls'!F19,IF('DealScope sensitivity controls'!F19="","",11>'DealScope sensitivity controls'!F19))="",FALSE,IF(ISERROR(11>'DealScope sensitivity controls'!F19),11>'DealScope sensitivity controls'!F19,IF('DealScope sensitivity controls'!F19="","",11>'DealScope sensitivity controls'!F19))),IF('Model inputs'!B43="","",'Model inputs'!B43),0))="",0,IF(IF(IF(ISERROR('Model inputs'!B29=1),'Model inputs'!B29=1,IF('Model inputs'!B29="","",'Model inputs'!B29=1))="",FALSE,IF(ISERROR('Model inputs'!B29=1),'Model inputs'!B29=1,IF('Model inputs'!B29="","",'Model inputs'!B29=1))),'Model inputs'!B43*MIN(MAX((11-'DealScope sensitivity controls'!F19)/'Model inputs'!B21,0),1),IF(IF(IF(ISERROR(11>'DealScope sensitivity controls'!F19),11>'DealScope sensitivity controls'!F19,IF('DealScope sensitivity controls'!F19="","",11>'DealScope sensitivity controls'!F19))="",FALSE,IF(ISERROR(11>'DealScope sensitivity controls'!F19),11>'DealScope sensitivity controls'!F19,IF('DealScope sensitivity controls'!F19="","",11>'DealScope sensitivity controls'!F19))),IF('Model inputs'!B43="","",'Model inputs'!B43),0)))+IF(IF(IF(IF(ISERROR('Model inputs'!B29=1),'Model inputs'!B29=1,IF('Model inputs'!B29="","",'Model inputs'!B29=1))="",FALSE,IF(ISERROR('Model inputs'!B29=1),'Model inputs'!B29=1,IF('Model inputs'!B29="","",'Model inputs'!B29=1))),'Model inputs'!B43*MIN(MAX((12-'DealScope sensitivity controls'!F19)/'Model inputs'!B21,0),1),IF(IF(IF(ISERROR(12>'DealScope sensitivity controls'!F19),12>'DealScope sensitivity controls'!F19,IF('DealScope sensitivity controls'!F19="","",12>'DealScope sensitivity controls'!F19))="",FALSE,IF(ISERROR(12>'DealScope sensitivity controls'!F19),12>'DealScope sensitivity controls'!F19,IF('DealScope sensitivity controls'!F19="","",12>'DealScope sensitivity controls'!F19))),IF('Model inputs'!B43="","",'Model inputs'!B43),0))="",0,IF(IF(IF(ISERROR('Model inputs'!B29=1),'Model inputs'!B29=1,IF('Model inputs'!B29="","",'Model inputs'!B29=1))="",FALSE,IF(ISERROR('Model inputs'!B29=1),'Model inputs'!B29=1,IF('Model inputs'!B29="","",'Model inputs'!B29=1))),'Model inputs'!B43*MIN(MAX((12-'DealScope sensitivity controls'!F19)/'Model inputs'!B21,0),1),IF(IF(IF(ISERROR(12>'DealScope sensitivity controls'!F19),12>'DealScope sensitivity controls'!F19,IF('DealScope sensitivity controls'!F19="","",12>'DealScope sensitivity controls'!F19))="",FALSE,IF(ISERROR(12>'DealScope sensitivity controls'!F19),12>'DealScope sensitivity controls'!F19,IF('DealScope sensitivity controls'!F19="","",12>'DealScope sensitivity controls'!F19))),IF('Model inputs'!B43="","",'Model inputs'!B43),0))) -> 68.75 | I23: ='DealScope sensitivity compariso'!H23*'DealScope sensitivity compariso'!C23 -> 275000 | J23: ='DealScope sensitivity compariso'!I23*(1-'Model inputs'!B38)-'DealScope sensitivity compariso'!H23*('DealScope sensitivity compariso'!B23*'DealScope sensitivity compariso'!D23+'Model inputs'!B42*'Model inputs'!B41)-SUM('Model inputs'!B76,'Model inputs'!B77) -> 226158.75
A24: Sales delay 4 months | B24: =IF(IF(IF(ISERROR('DealScope sensitivity controls'!H20=1),'DealScope sensitivity controls'!H20=1,IF('DealScope sensitivity controls'!H20="","",'DealScope sensitivity controls'!H20=1))="",FALSE,IF(ISERROR('DealScope sensitivity controls'!H20=1),'DealScope sensitivity controls'!H20=1,IF('DealScope sensitivity controls'!H20="","",'DealScope sensitivity controls'!H20=1))),'Model inputs'!B6/12*'DealScope sensitivity controls'!G20,IF('DealScope sensitivity controls'!B20="","",'DealScope sensitivity controls'!B20)) -> 4 | C24: =IF(EXACT("Annual deal-team","Annual deal-team"),('Model inputs'!B45/12+MAX('DealScope sensitivity compariso'!B24-'Model inputs'!B24/12,0)*'Model inputs'!B32)*(1-'DealScope sensitivity controls'!C20),('Model inputs'!B45/12+'Model inputs'!B9*'DealScope sensitivity compariso'!B24)*(1-'DealScope sensitivity controls'!C20)) -> 4000 | D24: ='Model inputs'!B15*'DealScope sensitivity controls'!E20*'DealScope sensitivity controls'!D20*'Model inputs'!B17+'Model inputs'!B30+'Model inputs'!B39+'Model inputs'!B19 -> 94.65 | E24: =IFERROR('DealScope sensitivity compariso'!C24/'DealScope sensitivity compariso'!B24,"") -> 1000 | F24: =IFERROR(('DealScope sensitivity compariso'!E24-'DealScope sensitivity compariso'!D24)/'DealScope sensitivity compariso'!E24,"") -> 0.90535 | G24: =IFERROR(('DealScope sensitivity compariso'!C24*(1-'Model inputs'!B38)-'DealScope sensitivity compariso'!B24*'DealScope sensitivity compariso'!D24-'Model inputs'!B42*'Model inputs'!B41)/'DealScope sensitivity compariso'!C24,"") -> 0.86785 | H24: ='Model inputs'!B167+IF(IF(IF(IF(ISERROR('Model inputs'!B29=1),'Model inputs'!B29=1,IF('Model inputs'!B29="","",'Model inputs'!B29=1))="",FALSE,IF(ISERROR('Model inputs'!B29=1),'Model inputs'!B29=1,IF('Model inputs'!B29="","",'Model inputs'!B29=1))),'Model inputs'!B43*MIN(MAX((11-'DealScope sensitivity controls'!F20)/'Model inputs'!B21,0),1),IF(IF(IF(ISERROR(11>'DealScope sensitivity controls'!F20),11>'DealScope sensitivity controls'!F20,IF('DealScope sensitivity controls'!F20="","",11>'DealScope sensitivity controls'!F20))="",FALSE,IF(ISERROR(11>'DealScope sensitivity controls'!F20),11>'DealScope sensitivity controls'!F20,IF('DealScope sensitivity controls'!F20="","",11>'DealScope sensitivity controls'!F20))),IF('Model inputs'!B43="","",'Model inputs'!B43),0))="",0,IF(IF(IF(ISERROR('Model inputs'!B29=1),'Model inputs'!B29=1,IF('Model inputs'!B29="","",'Model inputs'!B29=1))="",FALSE,IF(ISERROR('Model inputs'!B29=1),'Model inputs'!B29=1,IF('Model inputs'!B29="","",'Model inputs'!B29=1))),'Model inputs'!B43*MIN(MAX((11-'DealScope sensitivity controls'!F20)/'Model inputs'!B21,0),1),IF(IF(IF(ISERROR(11>'DealScope sensitivity controls'!F20),11>'DealScope sensitivity controls'!F20,IF('DealScope sensitivity controls'!F20="","",11>'DealScope sensitivity controls'!F20))="",FALSE,IF(ISERROR(11>'DealScope sensitivity controls'!F20),11>'DealScope sensitivity controls'!F20,IF('DealScope sensitivity controls'!F20="","",11>'DealScope sensitivity controls'!F20))),IF('Model inputs'!B43="","",'Model inputs'!B43),0)))+IF(IF(IF(IF(ISERROR('Model inputs'!B29=1),'Model inputs'!B29=1,IF('Model inputs'!B29="","",'Model inputs'!B29=1))="",FALSE,IF(ISERROR('Model inputs'!B29=1),'Model inputs'!B29=1,IF('Model inputs'!B29="","",'Model inputs'!B29=1))),'Model inputs'!B43*MIN(MAX((12-'DealScope sensitivity controls'!F20)/'Model inputs'!B21,0),1),IF(IF(IF(ISERROR(12>'DealScope sensitivity controls'!F20),12>'DealScope sensitivity controls'!F20,IF('DealScope sensitivity controls'!F20="","",12>'DealScope sensitivity controls'!F20))="",FALSE,IF(ISERROR(12>'DealScope sensitivity controls'!F20),12>'DealScope sensitivity controls'!F20,IF('DealScope sensitivity controls'!F20="","",12>'DealScope sensitivity controls'!F20))),IF('Model inputs'!B43="","",'Model inputs'!B43),0))="",0,IF(IF(IF(ISERROR('Model inputs'!B29=1),'Model inputs'!B29=1,IF('Model inputs'!B29="","",'Model inputs'!B29=1))="",FALSE,IF(ISERROR('Model inputs'!B29=1),'Model inputs'!B29=1,IF('Model inputs'!B29="","",'Model inputs'!B29=1))),'Model inputs'!B43*MIN(MAX((12-'DealScope sensitivity controls'!F20)/'Model inputs'!B21,0),1),IF(IF(IF(ISERROR(12>'DealScope sensitivity controls'!F20),12>'DealScope sensitivity controls'!F20,IF('DealScope sensitivity controls'!F20="","",12>'DealScope sensitivity controls'!F20))="",FALSE,IF(ISERROR(12>'DealScope sensitivity controls'!F20),12>'DealScope sensitivity controls'!F20,IF('DealScope sensitivity controls'!F20="","",12>'DealScope sensitivity controls'!F20))),IF('Model inputs'!B43="","",'Model inputs'!B43),0))) -> 45 | I24: ='DealScope sensitivity compariso'!H24*'DealScope sensitivity compariso'!C24 -> 180000 | J24: ='DealScope sensitivity compariso'!I24*(1-'Model inputs'!B38)-'DealScope sensitivity compariso'!H24*('DealScope sensitivity compariso'!B24*'DealScope sensitivity compariso'!D24+'Model inputs'!B42*'Model inputs'!B41)-SUM('Model inputs'!B76,'Model inputs'!B77) -> 143713
A25: Hybrid | B25: ="" | C25: ="" | D25: ="" | E25: ="" | F25: ="" | G25: ="" | H25: ="" | I25: ="" | J25: =""
A26: Annual allowance utilization 100% | B26: =IF(IF(IF(ISERROR('DealScope sensitivity controls'!H23=1),'DealScope sensitivity controls'!H23=1,IF('DealScope sensitivity controls'!H23="","",'DealScope sensitivity controls'!H23=1))="",FALSE,IF(ISERROR('DealScope sensitivity controls'!H23=1),'DealScope sensitivity controls'!H23=1,IF('DealScope sensitivity controls'!H23="","",'DealScope sensitivity controls'!H23=1))),'Model inputs'!B6/12*'DealScope sensitivity controls'!G23,IF('DealScope sensitivity controls'!B23="","",'DealScope sensitivity controls'!B23)) -> 2 | C26: =IF(EXACT("Hybrid","Annual deal-team"),('Model inputs'!B46/12+MAX('DealScope sensitivity compariso'!B26-'Model inputs'!B25/12,0)*'Model inputs'!B33)*(1-'DealScope sensitivity controls'!C23),('Model inputs'!B46/12+'Model inputs'!B10*'DealScope sensitivity compariso'!B26)*(1-'DealScope sensitivity controls'!C23)) -> 2500 | D26: ='Model inputs'!B15*'DealScope sensitivity controls'!E23*'DealScope sensitivity controls'!D23*'Model inputs'!B17+'Model inputs'!B30+'Model inputs'!B39+'Model inputs'!B19 -> 94.65 | E26: =IFERROR('DealScope sensitivity compariso'!C26/'DealScope sensitivity compariso'!B26,"") -> 1250 | F26: =IFERROR(('DealScope sensitivity compariso'!E26-'DealScope sensitivity compariso'!D26)/'DealScope sensitivity compariso'!E26,"") -> 0.92428 | G26: =IFERROR(('DealScope sensitivity compariso'!C26*(1-'Model inputs'!B38)-'DealScope sensitivity compariso'!B26*'DealScope sensitivity compariso'!D26-'Model inputs'!B42*'Model inputs'!B41)/'DealScope sensitivity compariso'!C26,"") -> 0.88228 | H26: ='Model inputs'!B75+IF(IF(IF(IF(ISERROR('Model inputs'!B29=1),'Model inputs'!B29=1,IF('Model inputs'!B29="","",'Model inputs'!B29=1))="",FALSE,IF(ISERROR('Model inputs'!B29=1),'Model inputs'!B29=1,IF('Model inputs'!B29="","",'Model inputs'!B29=1))),'Model inputs'!B43*MIN(MAX((11-'DealScope sensitivity controls'!F23)/'Model inputs'!B21,0),1),IF(IF(IF(ISERROR(11>'DealScope sensitivity controls'!F23),11>'DealScope sensitivity controls'!F23,IF('DealScope sensitivity controls'!F23="","",11>'DealScope sensitivity controls'!F23))="",FALSE,IF(ISERROR(11>'DealScope sensitivity controls'!F23),11>'DealScope sensitivity controls'!F23,IF('DealScope sensitivity controls'!F23="","",11>'DealScope sensitivity controls'!F23))),IF('Model inputs'!B43="","",'Model inputs'!B43),0))="",0,IF(IF(IF(ISERROR('Model inputs'!B29=1),'Model inputs'!B29=1,IF('Model inputs'!B29="","",'Model inputs'!B29=1))="",FALSE,IF(ISERROR('Model inputs'!B29=1),'Model inputs'!B29=1,IF('Model inputs'!B29="","",'Model inputs'!B29=1))),'Model inputs'!B43*MIN(MAX((11-'DealScope sensitivity controls'!F23)/'Model inputs'!B21,0),1),IF(IF(IF(ISERROR(11>'DealScope sensitivity controls'!F23),11>'DealScope sensitivity controls'!F23,IF('DealScope sensitivity controls'!F23="","",11>'DealScope sensitivity controls'!F23))="",FALSE,IF(ISERROR(11>'DealScope sensitivity controls'!F23),11>'DealScope sensitivity controls'!F23,IF('DealScope sensitivity controls'!F23="","",11>'DealScope sensitivity controls'!F23))),IF('Model inputs'!B43="","",'Model inputs'!B43),0)))+IF(IF(IF(IF(ISERROR('Model inputs'!B29=1),'Model inputs'!B29=1,IF('Model inputs'!B29="","",'Model inputs'!B29=1))="",FALSE,IF(ISERROR('Model inputs'!B29=1),'Model inputs'!B29=1,IF('Model inputs'!B29="","",'Model inputs'!B29=1))),'Model inputs'!B43*MIN(MAX((12-'DealScope sensitivity controls'!F23)/'Model inputs'!B21,0),1),IF(IF(IF(ISERROR(12>'DealScope sensitivity controls'!F23),12>'DealScope sensitivity controls'!F23,IF('DealScope sensitivity controls'!F23="","",12>'DealScope sensitivity controls'!F23))="",FALSE,IF(ISERROR(12>'DealScope sensitivity controls'!F23),12>'DealScope sensitivity controls'!F23,IF('DealScope sensitivity controls'!F23="","",12>'DealScope sensitivity controls'!F23))),IF('Model inputs'!B43="","",'Model inputs'!B43),0))="",0,IF(IF(IF(ISERROR('Model inputs'!B29=1),'Model inputs'!B29=1,IF('Model inputs'!B29="","",'Model inputs'!B29=1))="",FALSE,IF(ISERROR('Model inputs'!B29=1),'Model inputs'!B29=1,IF('Model inputs'!B29="","",'Model inputs'!B29=1))),'Model inputs'!B43*MIN(MAX((12-'DealScope sensitivity controls'!F23)/'Model inputs'!B21,0),1),IF(IF(IF(ISERROR(12>'DealScope sensitivity controls'!F23),12>'DealScope sensitivity controls'!F23,IF('DealScope sensitivity controls'!F23="","",12>'DealScope sensitivity controls'!F23))="",FALSE,IF(ISERROR(12>'DealScope sensitivity controls'!F23),12>'DealScope sensitivity controls'!F23,IF('DealScope sensitivity controls'!F23="","",12>'DealScope sensitivity controls'!F23))),IF('Model inputs'!B43="","",'Model inputs'!B43),0))) -> 97.5 | I26: ='DealScope sensitivity compariso'!H26*'DealScope sensitivity compariso'!C26 -> 243750 | J26: ='DealScope sensitivity compariso'!I26*(1-'Model inputs'!B38)-'DealScope sensitivity compariso'!H26*('DealScope sensitivity compariso'!B26*'DealScope sensitivity compariso'!D26+'Model inputs'!B42*'Model inputs'!B41)-SUM('Model inputs'!B76,'Model inputs'!B77) -> 202555.75
A27: Annual allowance utilization 50% | B27: =IF(IF(IF(ISERROR('DealScope sensitivity controls'!H21=1),'DealScope sensitivity controls'!H21=1,IF('DealScope sensitivity controls'!H21="","",'DealScope sensitivity controls'!H21=1))="",FALSE,IF(ISERROR('DealScope sensitivity controls'!H21=1),'DealScope sensitivity controls'!H21=1,IF('DealScope sensitivity controls'!H21="","",'DealScope sensitivity controls'!H21=1))),'Model inputs'!B6/12*'DealScope sensitivity controls'!G21,IF('DealScope sensitivity controls'!B21="","",'DealScope sensitivity controls'!B21)) -> 1 | C27: =IF(EXACT("Hybrid","Annual deal-team"),('Model inputs'!B46/12+MAX('DealScope sensitivity compariso'!B27-'Model inputs'!B25/12,0)*'Model inputs'!B33)*(1-'DealScope sensitivity controls'!C21),('Model inputs'!B46/12+'Model inputs'!B10*'DealScope sensitivity compariso'!B27)*(1-'DealScope sensitivity controls'!C21)) -> 1500 | D27: ='Model inputs'!B15*'DealScope sensitivity controls'!E21*'DealScope sensitivity controls'!D21*'Model inputs'!B17+'Model inputs'!B30+'Model inputs'!B39+'Model inputs'!B19 -> 94.65 | E27: =IFERROR('DealScope sensitivity compariso'!C27/'DealScope sensitivity compariso'!B27,"") -> 1500 | F27: =IFERROR(('DealScope sensitivity compariso'!E27-'DealScope sensitivity compariso'!D27)/'DealScope sensitivity compariso'!E27,"") -> 0.9369 | G27: =IFERROR(('DealScope sensitivity compariso'!C27*(1-'Model inputs'!B38)-'DealScope sensitivity compariso'!B27*'DealScope sensitivity compariso'!D27-'Model inputs'!B42*'Model inputs'!B41)/'DealScope sensitivity compariso'!C27,"") -> 0.8869 | H27: ='Model inputs'!B82+IF(IF(IF(IF(ISERROR('Model inputs'!B29=1),'Model inputs'!B29=1,IF('Model inputs'!B29="","",'Model inputs'!B29=1))="",FALSE,IF(ISERROR('Model inputs'!B29=1),'Model inputs'!B29=1,IF('Model inputs'!B29="","",'Model inputs'!B29=1))),'Model inputs'!B43*MIN(MAX((11-'DealScope sensitivity controls'!F21)/'Model inputs'!B21,0),1),IF(IF(IF(ISERROR(11>'DealScope sensitivity controls'!F21),11>'DealScope sensitivity controls'!F21,IF('DealScope sensitivity controls'!F21="","",11>'DealScope sensitivity controls'!F21))="",FALSE,IF(ISERROR(11>'DealScope sensitivity controls'!F21),11>'DealScope sensitivity controls'!F21,IF('DealScope sensitivity controls'!F21="","",11>'DealScope sensitivity controls'!F21))),IF('Model inputs'!B43="","",'Model inputs'!B43),0))="",0,IF(IF(IF(ISERROR('Model inputs'!B29=1),'Model inputs'!B29=1,IF('Model inputs'!B29="","",'Model inputs'!B29=1))="",FALSE,IF(ISERROR('Model inputs'!B29=1),'Model inputs'!B29=1,IF('Model inputs'!B29="","",'Model inputs'!B29=1))),'Model inputs'!B43*MIN(MAX((11-'DealScope sensitivity controls'!F21)/'Model inputs'!B21,0),1),IF(IF(IF(ISERROR(11>'DealScope sensitivity controls'!F21),11>'DealScope sensitivity controls'!F21,IF('DealScope sensitivity controls'!F21="","",11>'DealScope sensitivity controls'!F21))="",FALSE,IF(ISERROR(11>'DealScope sensitivity controls'!F21),11>'DealScope sensitivity controls'!F21,IF('DealScope sensitivity controls'!F21="","",11>'DealScope sensitivity controls'!F21))),IF('Model inputs'!B43="","",'Model inputs'!B43),0)))+IF(IF(IF(IF(ISERROR('Model inputs'!B29=1),'Model inputs'!B29=1,IF('Model inputs'!B29="","",'Model inputs'!B29=1))="",FALSE,IF(ISERROR('Model inputs'!B29=1),'Model inputs'!B29=1,IF('Model inputs'!B29="","",'Model inputs'!B29=1))),'Model inputs'!B43*MIN(MAX((12-'DealScope sensitivity controls'!F21)/'Model inputs'!B21,0),1),IF(IF(IF(ISERROR(12>'DealScope sensitivity controls'!F21),12>'DealScope sensitivity controls'!F21,IF('DealScope sensitivity controls'!F21="","",12>'DealScope sensitivity controls'!F21))="",FALSE,IF(ISERROR(12>'DealScope sensitivity controls'!F21),12>'DealScope sensitivity controls'!F21,IF('DealScope sensitivity controls'!F21="","",12>'DealScope sensitivity controls'!F21))),IF('Model inputs'!B43="","",'Model inputs'!B43),0))="",0,IF(IF(IF(ISERROR('Model inputs'!B29=1),'Model inputs'!B29=1,IF('Model inputs'!B29="","",'Model inputs'!B29=1))="",FALSE,IF(ISERROR('Model inputs'!B29=1),'Model inputs'!B29=1,IF('Model inputs'!B29="","",'Model inputs'!B29=1))),'Model inputs'!B43*MIN(MAX((12-'DealScope sensitivity controls'!F21)/'Model inputs'!B21,0),1),IF(IF(IF(ISERROR(12>'DealScope sensitivity controls'!F21),12>'DealScope sensitivity controls'!F21,IF('DealScope sensitivity controls'!F21="","",12>'DealScope sensitivity controls'!F21))="",FALSE,IF(ISERROR(12>'DealScope sensitivity controls'!F21),12>'DealScope sensitivity controls'!F21,IF('DealScope sensitivity controls'!F21="","",12>'DealScope sensitivity controls'!F21))),IF('Model inputs'!B43="","",'Model inputs'!B43),0))) -> 97.5 | I27: ='DealScope sensitivity compariso'!H27*'DealScope sensitivity compariso'!C27 -> 146250 | J27: ='DealScope sensitivity compariso'!I27*(1-'Model inputs'!B38)-'DealScope sensitivity compariso'!H27*('DealScope sensitivity compariso'!B27*'DealScope sensitivity compariso'!D27+'Model inputs'!B42*'Model inputs'!B41)-SUM('Model inputs'!B76,'Model inputs'!B77) -> 117209.12
A28: Annual allowance utilization 75% | B28: =IF(IF(IF(ISERROR('DealScope sensitivity controls'!H22=1),'DealScope sensitivity controls'!H22=1,IF('DealScope sensitivity controls'!H22="","",'DealScope sensitivity controls'!H22=1))="",FALSE,IF(ISERROR('DealScope sensitivity controls'!H22=1),'DealScope sensitivity controls'!H22=1,IF('DealScope sensitivity controls'!H22="","",'DealScope sensitivity controls'!H22=1))),'Model inputs'!B6/12*'DealScope sensitivity controls'!G22,IF('DealScope sensitivity controls'!B22="","",'DealScope sensitivity controls'!B22)) -> 1.5 | C28: =IF(EXACT("Hybrid","Annual deal-team"),('Model inputs'!B46/12+MAX('DealScope sensitivity compariso'!B28-'Model inputs'!B25/12,0)*'Model inputs'!B33)*(1-'DealScope sensitivity controls'!C22),('Model inputs'!B46/12+'Model inputs'!B10*'DealScope sensitivity compariso'!B28)*(1-'DealScope sensitivity controls'!C22)) -> 2000 | D28: ='Model inputs'!B15*'DealScope sensitivity controls'!E22*'DealScope sensitivity controls'!D22*'Model inputs'!B17+'Model inputs'!B30+'Model inputs'!B39+'Model inputs'!B19 -> 94.65 | E28: =IFERROR('DealScope sensitivity compariso'!C28/'DealScope sensitivity compariso'!B28,"") -> 1333.3333 | F28: =IFERROR(('DealScope sensitivity compariso'!E28-'DealScope sensitivity compariso'!D28)/'DealScope sensitivity compariso'!E28,"") -> 0.9290125 | G28: =IFERROR(('DealScope sensitivity compariso'!C28*(1-'Model inputs'!B38)-'DealScope sensitivity compariso'!B28*'DealScope sensitivity compariso'!D28-'Model inputs'!B42*'Model inputs'!B41)/'DealScope sensitivity compariso'!C28,"") -> 0.8840125 | H28: ='Model inputs'!B87+IF(IF(IF(IF(ISERROR('Model inputs'!B29=1),'Model inputs'!B29=1,IF('Model inputs'!B29="","",'Model inputs'!B29=1))="",FALSE,IF(ISERROR('Model inputs'!B29=1),'Model inputs'!B29=1,IF('Model inputs'!B29="","",'Model inputs'!B29=1))),'Model inputs'!B43*MIN(MAX((11-'DealScope sensitivity controls'!F22)/'Model inputs'!B21,0),1),IF(IF(IF(ISERROR(11>'DealScope sensitivity controls'!F22),11>'DealScope sensitivity controls'!F22,IF('DealScope sensitivity controls'!F22="","",11>'DealScope sensitivity controls'!F22))="",FALSE,IF(ISERROR(11>'DealScope sensitivity controls'!F22),11>'DealScope sensitivity controls'!F22,IF('DealScope sensitivity controls'!F22="","",11>'DealScope sensitivity controls'!F22))),IF('Model inputs'!B43="","",'Model inputs'!B43),0))="",0,IF(IF(IF(ISERROR('Model inputs'!B29=1),'Model inputs'!B29=1,IF('Model inputs'!B29="","",'Model inputs'!B29=1))="",FALSE,IF(ISERROR('Model inputs'!B29=1),'Model inputs'!B29=1,IF('Model inputs'!B29="","",'Model inputs'!B29=1))),'Model inputs'!B43*MIN(MAX((11-'DealScope sensitivity controls'!F22)/'Model inputs'!B21,0),1),IF(IF(IF(ISERROR(11>'DealScope sensitivity controls'!F22),11>'DealScope sensitivity controls'!F22,IF('DealScope sensitivity controls'!F22="","",11>'DealScope sensitivity controls'!F22))="",FALSE,IF(ISERROR(11>'DealScope sensitivity controls'!F22),11>'DealScope sensitivity controls'!F22,IF('DealScope sensitivity controls'!F22="","",11>'DealScope sensitivity controls'!F22))),IF('Model inputs'!B43="","",'Model inputs'!B43),0)))+IF(IF(IF(IF(ISERROR('Model inputs'!B29=1),'Model inputs'!B29=1,IF('Model inputs'!B29="","",'Model inputs'!B29=1))="",FALSE,IF(ISERROR('Model inputs'!B29=1),'Model inputs'!B29=1,IF('Model inputs'!B29="","",'Model inputs'!B29=1))),'Model inputs'!B43*MIN(MAX((12-'DealScope sensitivity controls'!F22)/'Model inputs'!B21,0),1),IF(IF(IF(ISERROR(12>'DealScope sensitivity controls'!F22),12>'DealScope sensitivity controls'!F22,IF('DealScope sensitivity controls'!F22="","",12>'DealScope sensitivity controls'!F22))="",FALSE,IF(ISERROR(12>'DealScope sensitivity controls'!F22),12>'DealScope sensitivity controls'!F22,IF('DealScope sensitivity controls'!F22="","",12>'DealScope sensitivity controls'!F22))),IF('Model inputs'!B43="","",'Model inputs'!B43),0))="",0,IF(IF(IF(ISERROR('Model inputs'!B29=1),'Model inputs'!B29=1,IF('Model inputs'!B29="","",'Model inputs'!B29=1))="",FALSE,IF(ISERROR('Model inputs'!B29=1),'Model inputs'!B29=1,IF('Model inputs'!B29="","",'Model inputs'!B29=1))),'Model inputs'!B43*MIN(MAX((12-'DealScope sensitivity controls'!F22)/'Model inputs'!B21,0),1),IF(IF(IF(ISERROR(12>'DealScope sensitivity controls'!F22),12>'DealScope sensitivity controls'!F22,IF('DealScope sensitivity controls'!F22="","",12>'DealScope sensitivity controls'!F22))="",FALSE,IF(ISERROR(12>'DealScope sensitivity controls'!F22),12>'DealScope sensitivity controls'!F22,IF('DealScope sensitivity controls'!F22="","",12>'DealScope sensitivity controls'!F22))),IF('Model inputs'!B43="","",'Model inputs'!B43),0))) -> 97.5 | I28: ='DealScope sensitivity compariso'!H28*'DealScope sensitivity compariso'!C28 -> 195000 | J28: ='DealScope sensitivity compariso'!I28*(1-'Model inputs'!B38)-'DealScope sensitivity compariso'!H28*('DealScope sensitivity compariso'!B28*'DealScope sensitivity compariso'!D28+'Model inputs'!B42*'Model inputs'!B41)-SUM('Model inputs'!B76,'Model inputs'!B77) -> 159882.44
A29: Audits 2/month | B29: =IF(IF(IF(ISERROR('DealScope sensitivity controls'!H6=1),'DealScope sensitivity controls'!H6=1,IF('DealScope sensitivity controls'!H6="","",'DealScope sensitivity controls'!H6=1))="",FALSE,IF(ISERROR('DealScope sensitivity controls'!H6=1),'DealScope sensitivity controls'!H6=1,IF('DealScope sensitivity controls'!H6="","",'DealScope sensitivity controls'!H6=1))),'Model inputs'!B6/12*'DealScope sensitivity controls'!G6,IF('DealScope sensitivity controls'!B6="","",'DealScope sensitivity controls'!B6)) -> 2 | C29: =IF(EXACT("Hybrid","Annual deal-team"),('Model inputs'!B46/12+MAX('DealScope sensitivity compariso'!B29-'Model inputs'!B25/12,0)*'Model inputs'!B33)*(1-'DealScope sensitivity controls'!C6),('Model inputs'!B46/12+'Model inputs'!B10*'DealScope sensitivity compariso'!B29)*(1-'DealScope sensitivity controls'!C6)) -> 2500 | D29: ='Model inputs'!B15*'DealScope sensitivity controls'!E6*'DealScope sensitivity controls'!D6*'Model inputs'!B17+'Model inputs'!B30+'Model inputs'!B39+'Model inputs'!B19 -> 94.65 | E29: =IFERROR('DealScope sensitivity compariso'!C29/'DealScope sensitivity compariso'!B29,"") -> 1250 | F29: =IFERROR(('DealScope sensitivity compariso'!E29-'DealScope sensitivity compariso'!D29)/'DealScope sensitivity compariso'!E29,"") -> 0.92428 | G29: =IFERROR(('DealScope sensitivity compariso'!C29*(1-'Model inputs'!B38)-'DealScope sensitivity compariso'!B29*'DealScope sensitivity compariso'!D29-'Model inputs'!B42*'Model inputs'!B41)/'DealScope sensitivity compariso'!C29,"") -> 0.88228 | H29: ='Model inputs'!B92+IF(IF(IF(IF(ISERROR('Model inputs'!B29=1),'Model inputs'!B29=1,IF('Model inputs'!B29="","",'Model inputs'!B29=1))="",FALSE,IF(ISERROR('Model inputs'!B29=1),'Model inputs'!B29=1,IF('Model inputs'!B29="","",'Model inputs'!B29=1))),'Model inputs'!B43*MIN(MAX((11-'DealScope sensitivity controls'!F6)/'Model inputs'!B21,0),1),IF(IF(IF(ISERROR(11>'DealScope sensitivity controls'!F6),11>'DealScope sensitivity controls'!F6,IF('DealScope sensitivity controls'!F6="","",11>'DealScope sensitivity controls'!F6))="",FALSE,IF(ISERROR(11>'DealScope sensitivity controls'!F6),11>'DealScope sensitivity controls'!F6,IF('DealScope sensitivity controls'!F6="","",11>'DealScope sensitivity controls'!F6))),IF('Model inputs'!B43="","",'Model inputs'!B43),0))="",0,IF(IF(IF(ISERROR('Model inputs'!B29=1),'Model inputs'!B29=1,IF('Model inputs'!B29="","",'Model inputs'!B29=1))="",FALSE,IF(ISERROR('Model inputs'!B29=1),'Model inputs'!B29=1,IF('Model inputs'!B29="","",'Model inputs'!B29=1))),'Model inputs'!B43*MIN(MAX((11-'DealScope sensitivity controls'!F6)/'Model inputs'!B21,0),1),IF(IF(IF(ISERROR(11>'DealScope sensitivity controls'!F6),11>'DealScope sensitivity controls'!F6,IF('DealScope sensitivity controls'!F6="","",11>'DealScope sensitivity controls'!F6))="",FALSE,IF(ISERROR(11>'DealScope sensitivity controls'!F6),11>'DealScope sensitivity controls'!F6,IF('DealScope sensitivity controls'!F6="","",11>'DealScope sensitivity controls'!F6))),IF('Model inputs'!B43="","",'Model inputs'!B43),0)))+IF(IF(IF(IF(ISERROR('Model inputs'!B29=1),'Model inputs'!B29=1,IF('Model inputs'!B29="","",'Model inputs'!B29=1))="",FALSE,IF(ISERROR('Model inputs'!B29=1),'Model inputs'!B29=1,IF('Model inputs'!B29="","",'Model inputs'!B29=1))),'Model inputs'!B43*MIN(MAX((12-'DealScope sensitivity controls'!F6)/'Model inputs'!B21,0),1),IF(IF(IF(ISERROR(12>'DealScope sensitivity controls'!F6),12>'DealScope sensitivity controls'!F6,IF('DealScope sensitivity controls'!F6="","",12>'DealScope sensitivity controls'!F6))="",FALSE,IF(ISERROR(12>'DealScope sensitivity controls'!F6),12>'DealScope sensitivity controls'!F6,IF('DealScope sensitivity controls'!F6="","",12>'DealScope sensitivity controls'!F6))),IF('Model inputs'!B43="","",'Model inputs'!B43),0))="",0,IF(IF(IF(ISERROR('Model inputs'!B29=1),'Model inputs'!B29=1,IF('Model inputs'!B29="","",'Model inputs'!B29=1))="",FALSE,IF(ISERROR('Model inputs'!B29=1),'Model inputs'!B29=1,IF('Model inputs'!B29="","",'Model inputs'!B29=1))),'Model inputs'!B43*MIN(MAX((12-'DealScope sensitivity controls'!F6)/'Model inputs'!B21,0),1),IF(IF(IF(ISERROR(12>'DealScope sensitivity controls'!F6),12>'DealScope sensitivity controls'!F6,IF('DealScope sensitivity controls'!F6="","",12>'DealScope sensitivity controls'!F6))="",FALSE,IF(ISERROR(12>'DealScope sensitivity controls'!F6),12>'DealScope sensitivity controls'!F6,IF('DealScope sensitivity controls'!F6="","",12>'DealScope sensitivity controls'!F6))),IF('Model inputs'!B43="","",'Model inputs'!B43),0))) -> 97.5 | I29: ='DealScope sensitivity compariso'!H29*'DealScope sensitivity compariso'!C29 -> 243750 | J29: ='DealScope sensitivity compariso'!I29*(1-'Model inputs'!B38)-'DealScope sensitivity compariso'!H29*('DealScope sensitivity compariso'!B29*'DealScope sensitivity compariso'!D29+'Model inputs'!B42*'Model inputs'!B41)-SUM('Model inputs'!B76,'Model inputs'!B77) -> 202555.75
A30: Audits 3/month | B30: =IF(IF(IF(ISERROR('DealScope sensitivity controls'!H7=1),'DealScope sensitivity controls'!H7=1,IF('DealScope sensitivity controls'!H7="","",'DealScope sensitivity controls'!H7=1))="",FALSE,IF(ISERROR('DealScope sensitivity controls'!H7=1),'DealScope sensitivity controls'!H7=1,IF('DealScope sensitivity controls'!H7="","",'DealScope sensitivity controls'!H7=1))),'Model inputs'!B6/12*'DealScope sensitivity controls'!G7,IF('DealScope sensitivity controls'!B7="","",'DealScope sensitivity controls'!B7)) -> 3 | C30: =IF(EXACT("Hybrid","Annual deal-team"),('Model inputs'!B46/12+MAX('DealScope sensitivity compariso'!B30-'Model inputs'!B25/12,0)*'Model inputs'!B33)*(1-'DealScope sensitivity controls'!C7),('Model inputs'!B46/12+'Model inputs'!B10*'DealScope sensitivity compariso'!B30)*(1-'DealScope sensitivity controls'!C7)) -> 3500 | D30: ='Model inputs'!B15*'DealScope sensitivity controls'!E7*'DealScope sensitivity controls'!D7*'Model inputs'!B17+'Model inputs'!B30+'Model inputs'!B39+'Model inputs'!B19 -> 94.65 | E30: =IFERROR('DealScope sensitivity compariso'!C30/'DealScope sensitivity compariso'!B30,"") -> 1166.6667 | F30: =IFERROR(('DealScope sensitivity compariso'!E30-'DealScope sensitivity compariso'!D30)/'DealScope sensitivity compariso'!E30,"") -> 0.91887143 | G30: =IFERROR(('DealScope sensitivity compariso'!C30*(1-'Model inputs'!B38)-'DealScope sensitivity compariso'!B30*'DealScope sensitivity compariso'!D30-'Model inputs'!B42*'Model inputs'!B41)/'DealScope sensitivity compariso'!C30,"") -> 0.8803 | H30: ='Model inputs'!B97+IF(IF(IF(IF(ISERROR('Model inputs'!B29=1),'Model inputs'!B29=1,IF('Model inputs'!B29="","",'Model inputs'!B29=1))="",FALSE,IF(ISERROR('Model inputs'!B29=1),'Model inputs'!B29=1,IF('Model inputs'!B29="","",'Model inputs'!B29=1))),'Model inputs'!B43*MIN(MAX((11-'DealScope sensitivity controls'!F7)/'Model inputs'!B21,0),1),IF(IF(IF(ISERROR(11>'DealScope sensitivity controls'!F7),11>'DealScope sensitivity controls'!F7,IF('DealScope sensitivity controls'!F7="","",11>'DealScope sensitivity controls'!F7))="",FALSE,IF(ISERROR(11>'DealScope sensitivity controls'!F7),11>'DealScope sensitivity controls'!F7,IF('DealScope sensitivity controls'!F7="","",11>'DealScope sensitivity controls'!F7))),IF('Model inputs'!B43="","",'Model inputs'!B43),0))="",0,IF(IF(IF(ISERROR('Model inputs'!B29=1),'Model inputs'!B29=1,IF('Model inputs'!B29="","",'Model inputs'!B29=1))="",FALSE,IF(ISERROR('Model inputs'!B29=1),'Model inputs'!B29=1,IF('Model inputs'!B29="","",'Model inputs'!B29=1))),'Model inputs'!B43*MIN(MAX((11-'DealScope sensitivity controls'!F7)/'Model inputs'!B21,0),1),IF(IF(IF(ISERROR(11>'DealScope sensitivity controls'!F7),11>'DealScope sensitivity controls'!F7,IF('DealScope sensitivity controls'!F7="","",11>'DealScope sensitivity controls'!F7))="",FALSE,IF(ISERROR(11>'DealScope sensitivity controls'!F7),11>'DealScope sensitivity controls'!F7,IF('DealScope sensitivity controls'!F7="","",11>'DealScope sensitivity controls'!F7))),IF('Model inputs'!B43="","",'Model inputs'!B43),0)))+IF(IF(IF(IF(ISERROR('Model inputs'!B29=1),'Model inputs'!B29=1,IF('Model inputs'!B29="","",'Model inputs'!B29=1))="",FALSE,IF(ISERROR('Model inputs'!B29=1),'Model inputs'!B29=1,IF('Model inputs'!B29="","",'Model inputs'!B29=1))),'Model inputs'!B43*MIN(MAX((12-'DealScope sensitivity controls'!F7)/'Model inputs'!B21,0),1),IF(IF(IF(ISERROR(12>'DealScope sensitivity controls'!F7),12>'DealScope sensitivity controls'!F7,IF('DealScope sensitivity controls'!F7="","",12>'DealScope sensitivity controls'!F7))="",FALSE,IF(ISERROR(12>'DealScope sensitivity controls'!F7),12>'DealScope sensitivity controls'!F7,IF('DealScope sensitivity controls'!F7="","",12>'DealScope sensitivity controls'!F7))),IF('Model inputs'!B43="","",'Model inputs'!B43),0))="",0,IF(IF(IF(ISERROR('Model inputs'!B29=1),'Model inputs'!B29=1,IF('Model inputs'!B29="","",'Model inputs'!B29=1))="",FALSE,IF(ISERROR('Model inputs'!B29=1),'Model inputs'!B29=1,IF('Model inputs'!B29="","",'Model inputs'!B29=1))),'Model inputs'!B43*MIN(MAX((12-'DealScope sensitivity controls'!F7)/'Model inputs'!B21,0),1),IF(IF(IF(ISERROR(12>'DealScope sensitivity controls'!F7),12>'DealScope sensitivity controls'!F7,IF('DealScope sensitivity controls'!F7="","",12>'DealScope sensitivity controls'!F7))="",FALSE,IF(ISERROR(12>'DealScope sensitivity controls'!F7),12>'DealScope sensitivity controls'!F7,IF('DealScope sensitivity controls'!F7="","",12>'DealScope sensitivity controls'!F7))),IF('Model inputs'!B43="","",'Model inputs'!B43),0))) -> 97.5 | I30: ='DealScope sensitivity compariso'!H30*'DealScope sensitivity compariso'!C30 -> 341250 | J30: ='DealScope sensitivity compariso'!I30*(1-'Model inputs'!B38)-'DealScope sensitivity compariso'!H30*('DealScope sensitivity compariso'!B30*'DealScope sensitivity compariso'!D30+'Model inputs'!B42*'Model inputs'!B41)-SUM('Model inputs'!B76,'Model inputs'!B77) -> 287902.38
A31: Audits 4/month | B31: =IF(IF(IF(ISERROR('DealScope sensitivity controls'!H8=1),'DealScope sensitivity controls'!H8=1,IF('DealScope sensitivity controls'!H8="","",'DealScope sensitivity controls'!H8=1))="",FALSE,IF(ISERROR('DealScope sensitivity controls'!H8=1),'DealScope sensitivity controls'!H8=1,IF('DealScope sensitivity controls'!H8="","",'DealScope sensitivity controls'!H8=1))),'Model inputs'!B6/12*'DealScope sensitivity controls'!G8,IF('DealScope sensitivity controls'!B8="","",'DealScope sensitivity controls'!B8)) -> 4 | C31: =IF(EXACT("Hybrid","Annual deal-team"),('Model inputs'!B46/12+MAX('DealScope sensitivity compariso'!B31-'Model inputs'!B25/12,0)*'Model inputs'!B33)*(1-'DealScope sensitivity controls'!C8),('Model inputs'!B46/12+'Model inputs'!B10*'DealScope sensitivity compariso'!B31)*(1-'DealScope sensitivity controls'!C8)) -> 4500 | D31: ='Model inputs'!B15*'DealScope sensitivity controls'!E8*'DealScope sensitivity controls'!D8*'Model inputs'!B17+'Model inputs'!B30+'Model inputs'!B39+'Model inputs'!B19 -> 94.65 | E31: =IFERROR('DealScope sensitivity compariso'!C31/'DealScope sensitivity compariso'!B31,"") -> 1125 | F31: =IFERROR(('DealScope sensitivity compariso'!E31-'DealScope sensitivity compariso'!D31)/'DealScope sensitivity compariso'!E31,"") -> 0.91586667 | G31: =IFERROR(('DealScope sensitivity compariso'!C31*(1-'Model inputs'!B38)-'DealScope sensitivity compariso'!B31*'DealScope sensitivity compariso'!D31-'Model inputs'!B42*'Model inputs'!B41)/'DealScope sensitivity compariso'!C31,"") -> 0.8792 | H31: ='Model inputs'!B102+IF(IF(IF(IF(ISERROR('Model inputs'!B29=1),'Model inputs'!B29=1,IF('Model inputs'!B29="","",'Model inputs'!B29=1))="",FALSE,IF(ISERROR('Model inputs'!B29=1),'Model inputs'!B29=1,IF('Model inputs'!B29="","",'Model inputs'!B29=1))),'Model inputs'!B43*MIN(MAX((11-'DealScope sensitivity controls'!F8)/'Model inputs'!B21,0),1),IF(IF(IF(ISERROR(11>'DealScope sensitivity controls'!F8),11>'DealScope sensitivity controls'!F8,IF('DealScope sensitivity controls'!F8="","",11>'DealScope sensitivity controls'!F8))="",FALSE,IF(ISERROR(11>'DealScope sensitivity controls'!F8),11>'DealScope sensitivity controls'!F8,IF('DealScope sensitivity controls'!F8="","",11>'DealScope sensitivity controls'!F8))),IF('Model inputs'!B43="","",'Model inputs'!B43),0))="",0,IF(IF(IF(ISERROR('Model inputs'!B29=1),'Model inputs'!B29=1,IF('Model inputs'!B29="","",'Model inputs'!B29=1))="",FALSE,IF(ISERROR('Model inputs'!B29=1),'Model inputs'!B29=1,IF('Model inputs'!B29="","",'Model inputs'!B29=1))),'Model inputs'!B43*MIN(MAX((11-'DealScope sensitivity controls'!F8)/'Model inputs'!B21,0),1),IF(IF(IF(ISERROR(11>'DealScope sensitivity controls'!F8),11>'DealScope sensitivity controls'!F8,IF('DealScope sensitivity controls'!F8="","",11>'DealScope sensitivity controls'!F8))="",FALSE,IF(ISERROR(11>'DealScope sensitivity controls'!F8),11>'DealScope sensitivity controls'!F8,IF('DealScope sensitivity controls'!F8="","",11>'DealScope sensitivity controls'!F8))),IF('Model inputs'!B43="","",'Model inputs'!B43),0)))+IF(IF(IF(IF(ISERROR('Model inputs'!B29=1),'Model inputs'!B29=1,IF('Model inputs'!B29="","",'Model inputs'!B29=1))="",FALSE,IF(ISERROR('Model inputs'!B29=1),'Model inputs'!B29=1,IF('Model inputs'!B29="","",'Model inputs'!B29=1))),'Model inputs'!B43*MIN(MAX((12-'DealScope sensitivity controls'!F8)/'Model inputs'!B21,0),1),IF(IF(IF(ISERROR(12>'DealScope sensitivity controls'!F8),12>'DealScope sensitivity controls'!F8,IF('DealScope sensitivity controls'!F8="","",12>'DealScope sensitivity controls'!F8))="",FALSE,IF(ISERROR(12>'DealScope sensitivity controls'!F8),12>'DealScope sensitivity controls'!F8,IF('DealScope sensitivity controls'!F8="","",12>'DealScope sensitivity controls'!F8))),IF('Model inputs'!B43="","",'Model inputs'!B43),0))="",0,IF(IF(IF(ISERROR('Model inputs'!B29=1),'Model inputs'!B29=1,IF('Model inputs'!B29="","",'Model inputs'!B29=1))="",FALSE,IF(ISERROR('Model inputs'!B29=1),'Model inputs'!B29=1,IF('Model inputs'!B29="","",'Model inputs'!B29=1))),'Model inputs'!B43*MIN(MAX((12-'DealScope sensitivity controls'!F8)/'Model inputs'!B21,0),1),IF(IF(IF(ISERROR(12>'DealScope sensitivity controls'!F8),12>'DealScope sensitivity controls'!F8,IF('DealScope sensitivity controls'!F8="","",12>'DealScope sensitivity controls'!F8))="",FALSE,IF(ISERROR(12>'DealScope sensitivity controls'!F8),12>'DealScope sensitivity controls'!F8,IF('DealScope sensitivity controls'!F8="","",12>'DealScope sensitivity controls'!F8))),IF('Model inputs'!B43="","",'Model inputs'!B43),0))) -> 97.5 | I31: ='DealScope sensitivity compariso'!H31*'DealScope sensitivity compariso'!C31 -> 438750 | J31: ='DealScope sensitivity compariso'!I31*(1-'Model inputs'!B38)-'DealScope sensitivity compariso'!H31*('DealScope sensitivity compariso'!B31*'DealScope sensitivity compariso'!D31+'Model inputs'!B42*'Model inputs'!B41)-SUM('Model inputs'!B76,'Model inputs'!B77) -> 373249
A32: Baseline | B32: =IF(IF(IF(ISERROR('DealScope sensitivity controls'!H5=1),'DealScope sensitivity controls'!H5=1,IF('DealScope sensitivity controls'!H5="","",'DealScope sensitivity controls'!H5=1))="",FALSE,IF(ISERROR('DealScope sensitivity controls'!H5=1),'DealScope sensitivity controls'!H5=1,IF('DealScope sensitivity controls'!H5="","",'DealScope sensitivity controls'!H5=1))),'Model inputs'!B6/12*'DealScope sensitivity controls'!G5,IF('DealScope sensitivity controls'!B5="","",'DealScope sensitivity controls'!B5)) -> 4 | C32: =IF(EXACT("Hybrid","Annual deal-team"),('Model inputs'!B46/12+MAX('DealScope sensitivity compariso'!B32-'Model inputs'!B25/12,0)*'Model inputs'!B33)*(1-'DealScope sensitivity controls'!C5),('Model inputs'!B46/12+'Model inputs'!B10*'DealScope sensitivity compariso'!B32)*(1-'DealScope sensitivity controls'!C5)) -> 4500 | D32: ='Model inputs'!B15*'DealScope sensitivity controls'!E5*'DealScope sensitivity controls'!D5*'Model inputs'!B17+'Model inputs'!B30+'Model inputs'!B39+'Model inputs'!B19 -> 94.65 | E32: =IFERROR('DealScope sensitivity compariso'!C32/'DealScope sensitivity compariso'!B32,"") -> 1125 | F32: =IFERROR(('DealScope sensitivity compariso'!E32-'DealScope sensitivity compariso'!D32)/'DealScope sensitivity compariso'!E32,"") -> 0.91586667 | G32: =IFERROR(('DealScope sensitivity compariso'!C32*(1-'Model inputs'!B38)-'DealScope sensitivity compariso'!B32*'DealScope sensitivity compariso'!D32-'Model inputs'!B42*'Model inputs'!B41)/'DealScope sensitivity compariso'!C32,"") -> 0.8792 | H32: ='Model inputs'!B107+IF(IF(IF(IF(ISERROR('Model inputs'!B29=1),'Model inputs'!B29=1,IF('Model inputs'!B29="","",'Model inputs'!B29=1))="",FALSE,IF(ISERROR('Model inputs'!B29=1),'Model inputs'!B29=1,IF('Model inputs'!B29="","",'Model inputs'!B29=1))),'Model inputs'!B43*MIN(MAX((11-'DealScope sensitivity controls'!F5)/'Model inputs'!B21,0),1),IF(IF(IF(ISERROR(11>'DealScope sensitivity controls'!F5),11>'DealScope sensitivity controls'!F5,IF('DealScope sensitivity controls'!F5="","",11>'DealScope sensitivity controls'!F5))="",FALSE,IF(ISERROR(11>'DealScope sensitivity controls'!F5),11>'DealScope sensitivity controls'!F5,IF('DealScope sensitivity controls'!F5="","",11>'DealScope sensitivity controls'!F5))),IF('Model inputs'!B43="","",'Model inputs'!B43),0))="",0,IF(IF(IF(ISERROR('Model inputs'!B29=1),'Model inputs'!B29=1,IF('Model inputs'!B29="","",'Model inputs'!B29=1))="",FALSE,IF(ISERROR('Model inputs'!B29=1),'Model inputs'!B29=1,IF('Model inputs'!B29="","",'Model inputs'!B29=1))),'Model inputs'!B43*MIN(MAX((11-'DealScope sensitivity controls'!F5)/'Model inputs'!B21,0),1),IF(IF(IF(ISERROR(11>'DealScope sensitivity controls'!F5),11>'DealScope sensitivity controls'!F5,IF('DealScope sensitivity controls'!F5="","",11>'DealScope sensitivity controls'!F5))="",FALSE,IF(ISERROR(11>'DealScope sensitivity controls'!F5),11>'DealScope sensitivity controls'!F5,IF('DealScope sensitivity controls'!F5="","",11>'DealScope sensitivity controls'!F5))),IF('Model inputs'!B43="","",'Model inputs'!B43),0)))+IF(IF(IF(IF(ISERROR('Model inputs'!B29=1),'Model inputs'!B29=1,IF('Model inputs'!B29="","",'Model inputs'!B29=1))="",FALSE,IF(ISERROR('Model inputs'!B29=1),'Model inputs'!B29=1,IF('Model inputs'!B29="","",'Model inputs'!B29=1))),'Model inputs'!B43*MIN(MAX((12-'DealScope sensitivity controls'!F5)/'Model inputs'!B21,0),1),IF(IF(IF(ISERROR(12>'DealScope sensitivity controls'!F5),12>'DealScope sensitivity controls'!F5,IF('DealScope sensitivity controls'!F5="","",12>'DealScope sensitivity controls'!F5))="",FALSE,IF(ISERROR(12>'DealScope sensitivity controls'!F5),12>'DealScope sensitivity controls'!F5,IF('DealScope sensitivity controls'!F5="","",12>'DealScope sensitivity controls'!F5))),IF('Model inputs'!B43="","",'Model inputs'!B43),0))="",0,IF(IF(IF(ISERROR('Model inputs'!B29=1),'Model inputs'!B29=1,IF('Model inputs'!B29="","",'Model inputs'!B29=1))="",FALSE,IF(ISERROR('Model inputs'!B29=1),'Model inputs'!B29=1,IF('Model inputs'!B29="","",'Model inputs'!B29=1))),'Model inputs'!B43*MIN(MAX((12-'DealScope sensitivity controls'!F5)/'Model inputs'!B21,0),1),IF(IF(IF(ISERROR(12>'DealScope sensitivity controls'!F5),12>'DealScope sensitivity controls'!F5,IF('DealScope sensitivity controls'!F5="","",12>'DealScope sensitivity controls'!F5))="",FALSE,IF(ISERROR(12>'DealScope sensitivity controls'!F5),12>'DealScope sensitivity controls'!F5,IF('DealScope sensitivity controls'!F5="","",12>'DealScope sensitivity controls'!F5))),IF('Model inputs'!B43="","",'Model inputs'!B43),0))) -> 97.5 | I32: ='DealScope sensitivity compariso'!H32*'DealScope sensitivity compariso'!C32 -> 438750 | J32: ='DealScope sensitivity compariso'!I32*(1-'Model inputs'!B38)-'DealScope sensitivity compariso'!H32*('DealScope sensitivity compariso'!B32*'DealScope sensitivity compariso'!D32+'Model inputs'!B42*'Model inputs'!B41)-SUM('Model inputs'!B76,'Model inputs'!B77) -> 373249
A33: Credit rate $0.05 | B33: =IF(IF(IF(ISERROR('DealScope sensitivity controls'!H15=1),'DealScope sensitivity controls'!H15=1,IF('DealScope sensitivity controls'!H15="","",'DealScope sensitivity controls'!H15=1))="",FALSE,IF(ISERROR('DealScope sensitivity controls'!H15=1),'DealScope sensitivity controls'!H15=1,IF('DealScope sensitivity controls'!H15="","",'DealScope sensitivity controls'!H15=1))),'Model inputs'!B6/12*'DealScope sensitivity controls'!G15,IF('DealScope sensitivity controls'!B15="","",'DealScope sensitivity controls'!B15)) -> 4 | C33: =IF(EXACT("Hybrid","Annual deal-team"),('Model inputs'!B46/12+MAX('DealScope sensitivity compariso'!B33-'Model inputs'!B25/12,0)*'Model inputs'!B33)*(1-'DealScope sensitivity controls'!C15),('Model inputs'!B46/12+'Model inputs'!B10*'DealScope sensitivity compariso'!B33)*(1-'DealScope sensitivity controls'!C15)) -> 4500 | D33: ='Model inputs'!B15*'DealScope sensitivity controls'!E15*'DealScope sensitivity controls'!D15*'Model inputs'!B17+'Model inputs'!B30+'Model inputs'!B39+'Model inputs'!B19 -> 93.35 | E33: =IFERROR('DealScope sensitivity compariso'!C33/'DealScope sensitivity compariso'!B33,"") -> 1125 | F33: =IFERROR(('DealScope sensitivity compariso'!E33-'DealScope sensitivity compariso'!D33)/'DealScope sensitivity compariso'!E33,"") -> 0.91702222 | G33: =IFERROR(('DealScope sensitivity compariso'!C33*(1-'Model inputs'!B38)-'DealScope sensitivity compariso'!B33*'DealScope sensitivity compariso'!D33-'Model inputs'!B42*'Model inputs'!B41)/'DealScope sensitivity compariso'!C33,"") -> 0.88035556 | H33: ='Model inputs'!B112+IF(IF(IF(IF(ISERROR('Model inputs'!B29=1),'Model inputs'!B29=1,IF('Model inputs'!B29="","",'Model inputs'!B29=1))="",FALSE,IF(ISERROR('Model inputs'!B29=1),'Model inputs'!B29=1,IF('Model inputs'!B29="","",'Model inputs'!B29=1))),'Model inputs'!B43*MIN(MAX((11-'DealScope sensitivity controls'!F15)/'Model inputs'!B21,0),1),IF(IF(IF(ISERROR(11>'DealScope sensitivity controls'!F15),11>'DealScope sensitivity controls'!F15,IF('DealScope sensitivity controls'!F15="","",11>'DealScope sensitivity controls'!F15))="",FALSE,IF(ISERROR(11>'DealScope sensitivity controls'!F15),11>'DealScope sensitivity controls'!F15,IF('DealScope sensitivity controls'!F15="","",11>'DealScope sensitivity controls'!F15))),IF('Model inputs'!B43="","",'Model inputs'!B43),0))="",0,IF(IF(IF(ISERROR('Model inputs'!B29=1),'Model inputs'!B29=1,IF('Model inputs'!B29="","",'Model inputs'!B29=1))="",FALSE,IF(ISERROR('Model inputs'!B29=1),'Model inputs'!B29=1,IF('Model inputs'!B29="","",'Model inputs'!B29=1))),'Model inputs'!B43*MIN(MAX((11-'DealScope sensitivity controls'!F15)/'Model inputs'!B21,0),1),IF(IF(IF(ISERROR(11>'DealScope sensitivity controls'!F15),11>'DealScope sensitivity controls'!F15,IF('DealScope sensitivity controls'!F15="","",11>'DealScope sensitivity controls'!F15))="",FALSE,IF(ISERROR(11>'DealScope sensitivity controls'!F15),11>'DealScope sensitivity controls'!F15,IF('DealScope sensitivity controls'!F15="","",11>'DealScope sensitivity controls'!F15))),IF('Model inputs'!B43="","",'Model inputs'!B43),0)))+IF(IF(IF(IF(ISERROR('Model inputs'!B29=1),'Model inputs'!B29=1,IF('Model inputs'!B29="","",'Model inputs'!B29=1))="",FALSE,IF(ISERROR('Model inputs'!B29=1),'Model inputs'!B29=1,IF('Model inputs'!B29="","",'Model inputs'!B29=1))),'Model inputs'!B43*MIN(MAX((12-'DealScope sensitivity controls'!F15)/'Model inputs'!B21,0),1),IF(IF(IF(ISERROR(12>'DealScope sensitivity controls'!F15),12>'DealScope sensitivity controls'!F15,IF('DealScope sensitivity controls'!F15="","",12>'DealScope sensitivity controls'!F15))="",FALSE,IF(ISERROR(12>'DealScope sensitivity controls'!F15),12>'DealScope sensitivity controls'!F15,IF('DealScope sensitivity controls'!F15="","",12>'DealScope sensitivity controls'!F15))),IF('Model inputs'!B43="","",'Model inputs'!B43),0))="",0,IF(IF(IF(ISERROR('Model inputs'!B29=1),'Model inputs'!B29=1,IF('Model inputs'!B29="","",'Model inputs'!B29=1))="",FALSE,IF(ISERROR('Model inputs'!B29=1),'Model inputs'!B29=1,IF('Model inputs'!B29="","",'Model inputs'!B29=1))),'Model inputs'!B43*MIN(MAX((12-'DealScope sensitivity controls'!F15)/'Model inputs'!B21,0),1),IF(IF(IF(ISERROR(12>'DealScope sensitivity controls'!F15),12>'DealScope sensitivity controls'!F15,IF('DealScope sensitivity controls'!F15="","",12>'DealScope sensitivity controls'!F15))="",FALSE,IF(ISERROR(12>'DealScope sensitivity controls'!F15),12>'DealScope sensitivity controls'!F15,IF('DealScope sensitivity controls'!F15="","",12>'DealScope sensitivity controls'!F15))),IF('Model inputs'!B43="","",'Model inputs'!B43),0))) -> 97.5 | I33: ='DealScope sensitivity compariso'!H33*'DealScope sensitivity compariso'!C33 -> 438750 | J33: ='DealScope sensitivity compariso'!I33*(1-'Model inputs'!B38)-'DealScope sensitivity compariso'!H33*('DealScope sensitivity compariso'!B33*'DealScope sensitivity compariso'!D33+'Model inputs'!B42*'Model inputs'!B41)-SUM('Model inputs'!B76,'Model inputs'!B77) -> 373756
A34: Credit rate $0.10 | B34: =IF(IF(IF(ISERROR('DealScope sensitivity controls'!H16=1),'DealScope sensitivity controls'!H16=1,IF('DealScope sensitivity controls'!H16="","",'DealScope sensitivity controls'!H16=1))="",FALSE,IF(ISERROR('DealScope sensitivity controls'!H16=1),'DealScope sensitivity controls'!H16=1,IF('DealScope sensitivity controls'!H16="","",'DealScope sensitivity controls'!H16=1))),'Model inputs'!B6/12*'DealScope sensitivity controls'!G16,IF('DealScope sensitivity controls'!B16="","",'DealScope sensitivity controls'!B16)) -> 4 | C34: =IF(EXACT("Hybrid","Annual deal-team"),('Model inputs'!B46/12+MAX('DealScope sensitivity compariso'!B34-'Model inputs'!B25/12,0)*'Model inputs'!B33)*(1-'DealScope sensitivity controls'!C16),('Model inputs'!B46/12+'Model inputs'!B10*'DealScope sensitivity compariso'!B34)*(1-'DealScope sensitivity controls'!C16)) -> 4500 | D34: ='Model inputs'!B15*'DealScope sensitivity controls'!E16*'DealScope sensitivity controls'!D16*'Model inputs'!B17+'Model inputs'!B30+'Model inputs'!B39+'Model inputs'!B19 -> 94.65 | E34: =IFERROR('DealScope sensitivity compariso'!C34/'DealScope sensitivity compariso'!B34,"") -> 1125 | F34: =IFERROR(('DealScope sensitivity compariso'!E34-'DealScope sensitivity compariso'!D34)/'DealScope sensitivity compariso'!E34,"") -> 0.91586667 | G34: =IFERROR(('DealScope sensitivity compariso'!C34*(1-'Model inputs'!B38)-'DealScope sensitivity compariso'!B34*'DealScope sensitivity compariso'!D34-'Model inputs'!B42*'Model inputs'!B41)/'DealScope sensitivity compariso'!C34,"") -> 0.8792 | H34: ='Model inputs'!B117+IF(IF(IF(IF(ISERROR('Model inputs'!B29=1),'Model inputs'!B29=1,IF('Model inputs'!B29="","",'Model inputs'!B29=1))="",FALSE,IF(ISERROR('Model inputs'!B29=1),'Model inputs'!B29=1,IF('Model inputs'!B29="","",'Model inputs'!B29=1))),'Model inputs'!B43*MIN(MAX((11-'DealScope sensitivity controls'!F16)/'Model inputs'!B21,0),1),IF(IF(IF(ISERROR(11>'DealScope sensitivity controls'!F16),11>'DealScope sensitivity controls'!F16,IF('DealScope sensitivity controls'!F16="","",11>'DealScope sensitivity controls'!F16))="",FALSE,IF(ISERROR(11>'DealScope sensitivity controls'!F16),11>'DealScope sensitivity controls'!F16,IF('DealScope sensitivity controls'!F16="","",11>'DealScope sensitivity controls'!F16))),IF('Model inputs'!B43="","",'Model inputs'!B43),0))="",0,IF(IF(IF(ISERROR('Model inputs'!B29=1),'Model inputs'!B29=1,IF('Model inputs'!B29="","",'Model inputs'!B29=1))="",FALSE,IF(ISERROR('Model inputs'!B29=1),'Model inputs'!B29=1,IF('Model inputs'!B29="","",'Model inputs'!B29=1))),'Model inputs'!B43*MIN(MAX((11-'DealScope sensitivity controls'!F16)/'Model inputs'!B21,0),1),IF(IF(IF(ISERROR(11>'DealScope sensitivity controls'!F16),11>'DealScope sensitivity controls'!F16,IF('DealScope sensitivity controls'!F16="","",11>'DealScope sensitivity controls'!F16))="",FALSE,IF(ISERROR(11>'DealScope sensitivity controls'!F16),11>'DealScope sensitivity controls'!F16,IF('DealScope sensitivity controls'!F16="","",11>'DealScope sensitivity controls'!F16))),IF('Model inputs'!B43="","",'Model inputs'!B43),0)))+IF(IF(IF(IF(ISERROR('Model inputs'!B29=1),'Model inputs'!B29=1,IF('Model inputs'!B29="","",'Model inputs'!B29=1))="",FALSE,IF(ISERROR('Model inputs'!B29=1),'Model inputs'!B29=1,IF('Model inputs'!B29="","",'Model inputs'!B29=1))),'Model inputs'!B43*MIN(MAX((12-'DealScope sensitivity controls'!F16)/'Model inputs'!B21,0),1),IF(IF(IF(ISERROR(12>'DealScope sensitivity controls'!F16),12>'DealScope sensitivity controls'!F16,IF('DealScope sensitivity controls'!F16="","",12>'DealScope sensitivity controls'!F16))="",FALSE,IF(ISERROR(12>'DealScope sensitivity controls'!F16),12>'DealScope sensitivity controls'!F16,IF('DealScope sensitivity controls'!F16="","",12>'DealScope sensitivity controls'!F16))),IF('Model inputs'!B43="","",'Model inputs'!B43),0))="",0,IF(IF(IF(ISERROR('Model inputs'!B29=1),'Model inputs'!B29=1,IF('Model inputs'!B29="","",'Model inputs'!B29=1))="",FALSE,IF(ISERROR('Model inputs'!B29=1),'Model inputs'!B29=1,IF('Model inputs'!B29="","",'Model inputs'!B29=1))),'Model inputs'!B43*MIN(MAX((12-'DealScope sensitivity controls'!F16)/'Model inputs'!B21,0),1),IF(IF(IF(ISERROR(12>'DealScope sensitivity controls'!F16),12>'DealScope sensitivity controls'!F16,IF('DealScope sensitivity controls'!F16="","",12>'DealScope sensitivity controls'!F16))="",FALSE,IF(ISERROR(12>'DealScope sensitivity controls'!F16),12>'DealScope sensitivity controls'!F16,IF('DealScope sensitivity controls'!F16="","",12>'DealScope sensitivity controls'!F16))),IF('Model inputs'!B43="","",'Model inputs'!B43),0))) -> 97.5 | I34: ='DealScope sensitivity compariso'!H34*'DealScope sensitivity compariso'!C34 -> 438750 | J34: ='DealScope sensitivity compariso'!I34*(1-'Model inputs'!B38)-'DealScope sensitivity compariso'!H34*('DealScope sensitivity compariso'!B34*'DealScope sensitivity compariso'!D34+'Model inputs'!B42*'Model inputs'!B41)-SUM('Model inputs'!B76,'Model inputs'!B77) -> 373249
A35: Credit rate $0.25 | B35: =IF(IF(IF(ISERROR('DealScope sensitivity controls'!H17=1),'DealScope sensitivity controls'!H17=1,IF('DealScope sensitivity controls'!H17="","",'DealScope sensitivity controls'!H17=1))="",FALSE,IF(ISERROR('DealScope sensitivity controls'!H17=1),'DealScope sensitivity controls'!H17=1,IF('DealScope sensitivity controls'!H17="","",'DealScope sensitivity controls'!H17=1))),'Model inputs'!B6/12*'DealScope sensitivity controls'!G17,IF('DealScope sensitivity controls'!B17="","",'DealScope sensitivity controls'!B17)) -> 4 | C35: =IF(EXACT("Hybrid","Annual deal-team"),('Model inputs'!B46/12+MAX('DealScope sensitivity compariso'!B35-'Model inputs'!B25/12,0)*'Model inputs'!B33)*(1-'DealScope sensitivity controls'!C17),('Model inputs'!B46/12+'Model inputs'!B10*'DealScope sensitivity compariso'!B35)*(1-'DealScope sensitivity controls'!C17)) -> 4500 | D35: ='Model inputs'!B15*'DealScope sensitivity controls'!E17*'DealScope sensitivity controls'!D17*'Model inputs'!B17+'Model inputs'!B30+'Model inputs'!B39+'Model inputs'!B19 -> 98.55 | E35: =IFERROR('DealScope sensitivity compariso'!C35/'DealScope sensitivity compariso'!B35,"") -> 1125 | F35: =IFERROR(('DealScope sensitivity compariso'!E35-'DealScope sensitivity compariso'!D35)/'DealScope sensitivity compariso'!E35,"") -> 0.9124 | G35: =IFERROR(('DealScope sensitivity compariso'!C35*(1-'Model inputs'!B38)-'DealScope sensitivity compariso'!B35*'DealScope sensitivity compariso'!D35-'Model inputs'!B42*'Model inputs'!B41)/'DealScope sensitivity compariso'!C35,"") -> 0.87573333 | H35: ='Model inputs'!B122+IF(IF(IF(IF(ISERROR('Model inputs'!B29=1),'Model inputs'!B29=1,IF('Model inputs'!B29="","",'Model inputs'!B29=1))="",FALSE,IF(ISERROR('Model inputs'!B29=1),'Model inputs'!B29=1,IF('Model inputs'!B29="","",'Model inputs'!B29=1))),'Model inputs'!B43*MIN(MAX((11-'DealScope sensitivity controls'!F17)/'Model inputs'!B21,0),1),IF(IF(IF(ISERROR(11>'DealScope sensitivity controls'!F17),11>'DealScope sensitivity controls'!F17,IF('DealScope sensitivity controls'!F17="","",11>'DealScope sensitivity controls'!F17))="",FALSE,IF(ISERROR(11>'DealScope sensitivity controls'!F17),11>'DealScope sensitivity controls'!F17,IF('DealScope sensitivity controls'!F17="","",11>'DealScope sensitivity controls'!F17))),IF('Model inputs'!B43="","",'Model inputs'!B43),0))="",0,IF(IF(IF(ISERROR('Model inputs'!B29=1),'Model inputs'!B29=1,IF('Model inputs'!B29="","",'Model inputs'!B29=1))="",FALSE,IF(ISERROR('Model inputs'!B29=1),'Model inputs'!B29=1,IF('Model inputs'!B29="","",'Model inputs'!B29=1))),'Model inputs'!B43*MIN(MAX((11-'DealScope sensitivity controls'!F17)/'Model inputs'!B21,0),1),IF(IF(IF(ISERROR(11>'DealScope sensitivity controls'!F17),11>'DealScope sensitivity controls'!F17,IF('DealScope sensitivity controls'!F17="","",11>'DealScope sensitivity controls'!F17))="",FALSE,IF(ISERROR(11>'DealScope sensitivity controls'!F17),11>'DealScope sensitivity controls'!F17,IF('DealScope sensitivity controls'!F17="","",11>'DealScope sensitivity controls'!F17))),IF('Model inputs'!B43="","",'Model inputs'!B43),0)))+IF(IF(IF(IF(ISERROR('Model inputs'!B29=1),'Model inputs'!B29=1,IF('Model inputs'!B29="","",'Model inputs'!B29=1))="",FALSE,IF(ISERROR('Model inputs'!B29=1),'Model inputs'!B29=1,IF('Model inputs'!B29="","",'Model inputs'!B29=1))),'Model inputs'!B43*MIN(MAX((12-'DealScope sensitivity controls'!F17)/'Model inputs'!B21,0),1),IF(IF(IF(ISERROR(12>'DealScope sensitivity controls'!F17),12>'DealScope sensitivity controls'!F17,IF('DealScope sensitivity controls'!F17="","",12>'DealScope sensitivity controls'!F17))="",FALSE,IF(ISERROR(12>'DealScope sensitivity controls'!F17),12>'DealScope sensitivity controls'!F17,IF('DealScope sensitivity controls'!F17="","",12>'DealScope sensitivity controls'!F17))),IF('Model inputs'!B43="","",'Model inputs'!B43),0))="",0,IF(IF(IF(ISERROR('Model inputs'!B29=1),'Model inputs'!B29=1,IF('Model inputs'!B29="","",'Model inputs'!B29=1))="",FALSE,IF(ISERROR('Model inputs'!B29=1),'Model inputs'!B29=1,IF('Model inputs'!B29="","",'Model inputs'!B29=1))),'Model inputs'!B43*MIN(MAX((12-'DealScope sensitivity controls'!F17)/'Model inputs'!B21,0),1),IF(IF(IF(ISERROR(12>'DealScope sensitivity controls'!F17),12>'DealScope sensitivity controls'!F17,IF('DealScope sensitivity controls'!F17="","",12>'DealScope sensitivity controls'!F17))="",FALSE,IF(ISERROR(12>'DealScope sensitivity controls'!F17),12>'DealScope sensitivity controls'!F17,IF('DealScope sensitivity controls'!F17="","",12>'DealScope sensitivity controls'!F17))),IF('Model inputs'!B43="","",'Model inputs'!B43),0))) -> 97.5 | I35: ='DealScope sensitivity compariso'!H35*'DealScope sensitivity compariso'!C35 -> 438750 | J35: ='DealScope sensitivity compariso'!I35*(1-'Model inputs'!B38)-'DealScope sensitivity compariso'!H35*('DealScope sensitivity compariso'!B35*'DealScope sensitivity compariso'!D35+'Model inputs'!B42*'Model inputs'!B41)-SUM('Model inputs'!B76,'Model inputs'!B77) -> 371728
A36: Data cost x1 | B36: =IF(IF(IF(ISERROR('DealScope sensitivity controls'!H12=1),'DealScope sensitivity controls'!H12=1,IF('DealScope sensitivity controls'!H12="","",'DealScope sensitivity controls'!H12=1))="",FALSE,IF(ISERROR('DealScope sensitivity controls'!H12=1),'DealScope sensitivity controls'!H12=1,IF('DealScope sensitivity controls'!H12="","",'DealScope sensitivity controls'!H12=1))),'Model inputs'!B6/12*'DealScope sensitivity controls'!G12,IF('DealScope sensitivity controls'!B12="","",'DealScope sensitivity controls'!B12)) -> 4 | C36: =IF(EXACT("Hybrid","Annual deal-team"),('Model inputs'!B46/12+MAX('DealScope sensitivity compariso'!B36-'Model inputs'!B25/12,0)*'Model inputs'!B33)*(1-'DealScope sensitivity controls'!C12),('Model inputs'!B46/12+'Model inputs'!B10*'DealScope sensitivity compariso'!B36)*(1-'DealScope sensitivity controls'!C12)) -> 4500 | D36: ='Model inputs'!B15*'DealScope sensitivity controls'!E12*'DealScope sensitivity controls'!D12*'Model inputs'!B17+'Model inputs'!B30+'Model inputs'!B39+'Model inputs'!B19 -> 94.65 | E36: =IFERROR('DealScope sensitivity compariso'!C36/'DealScope sensitivity compariso'!B36,"") -> 1125 | F36: =IFERROR(('DealScope sensitivity compariso'!E36-'DealScope sensitivity compariso'!D36)/'DealScope sensitivity compariso'!E36,"") -> 0.91586667 | G36: =IFERROR(('DealScope sensitivity compariso'!C36*(1-'Model inputs'!B38)-'DealScope sensitivity compariso'!B36*'DealScope sensitivity compariso'!D36-'Model inputs'!B42*'Model inputs'!B41)/'DealScope sensitivity compariso'!C36,"") -> 0.8792 | H36: ='Model inputs'!B127+IF(IF(IF(IF(ISERROR('Model inputs'!B29=1),'Model inputs'!B29=1,IF('Model inputs'!B29="","",'Model inputs'!B29=1))="",FALSE,IF(ISERROR('Model inputs'!B29=1),'Model inputs'!B29=1,IF('Model inputs'!B29="","",'Model inputs'!B29=1))),'Model inputs'!B43*MIN(MAX((11-'DealScope sensitivity controls'!F12)/'Model inputs'!B21,0),1),IF(IF(IF(ISERROR(11>'DealScope sensitivity controls'!F12),11>'DealScope sensitivity controls'!F12,IF('DealScope sensitivity controls'!F12="","",11>'DealScope sensitivity controls'!F12))="",FALSE,IF(ISERROR(11>'DealScope sensitivity controls'!F12),11>'DealScope sensitivity controls'!F12,IF('DealScope sensitivity controls'!F12="","",11>'DealScope sensitivity controls'!F12))),IF('Model inputs'!B43="","",'Model inputs'!B43),0))="",0,IF(IF(IF(ISERROR('Model inputs'!B29=1),'Model inputs'!B29=1,IF('Model inputs'!B29="","",'Model inputs'!B29=1))="",FALSE,IF(ISERROR('Model inputs'!B29=1),'Model inputs'!B29=1,IF('Model inputs'!B29="","",'Model inputs'!B29=1))),'Model inputs'!B43*MIN(MAX((11-'DealScope sensitivity controls'!F12)/'Model inputs'!B21,0),1),IF(IF(IF(ISERROR(11>'DealScope sensitivity controls'!F12),11>'DealScope sensitivity controls'!F12,IF('DealScope sensitivity controls'!F12="","",11>'DealScope sensitivity controls'!F12))="",FALSE,IF(ISERROR(11>'DealScope sensitivity controls'!F12),11>'DealScope sensitivity controls'!F12,IF('DealScope sensitivity controls'!F12="","",11>'DealScope sensitivity controls'!F12))),IF('Model inputs'!B43="","",'Model inputs'!B43),0)))+IF(IF(IF(IF(ISERROR('Model inputs'!B29=1),'Model inputs'!B29=1,IF('Model inputs'!B29="","",'Model inputs'!B29=1))="",FALSE,IF(ISERROR('Model inputs'!B29=1),'Model inputs'!B29=1,IF('Model inputs'!B29="","",'Model inputs'!B29=1))),'Model inputs'!B43*MIN(MAX((12-'DealScope sensitivity controls'!F12)/'Model inputs'!B21,0),1),IF(IF(IF(ISERROR(12>'DealScope sensitivity controls'!F12),12>'DealScope sensitivity controls'!F12,IF('DealScope sensitivity controls'!F12="","",12>'DealScope sensitivity controls'!F12))="",FALSE,IF(ISERROR(12>'DealScope sensitivity controls'!F12),12>'DealScope sensitivity controls'!F12,IF('DealScope sensitivity controls'!F12="","",12>'DealScope sensitivity controls'!F12))),IF('Model inputs'!B43="","",'Model inputs'!B43),0))="",0,IF(IF(IF(ISERROR('Model inputs'!B29=1),'Model inputs'!B29=1,IF('Model inputs'!B29="","",'Model inputs'!B29=1))="",FALSE,IF(ISERROR('Model inputs'!B29=1),'Model inputs'!B29=1,IF('Model inputs'!B29="","",'Model inputs'!B29=1))),'Model inputs'!B43*MIN(MAX((12-'DealScope sensitivity controls'!F12)/'Model inputs'!B21,0),1),IF(IF(IF(ISERROR(12>'DealScope sensitivity controls'!F12),12>'DealScope sensitivity controls'!F12,IF('DealScope sensitivity controls'!F12="","",12>'DealScope sensitivity controls'!F12))="",FALSE,IF(ISERROR(12>'DealScope sensitivity controls'!F12),12>'DealScope sensitivity controls'!F12,IF('DealScope sensitivity controls'!F12="","",12>'DealScope sensitivity controls'!F12))),IF('Model inputs'!B43="","",'Model inputs'!B43),0))) -> 97.5 | I36: ='DealScope sensitivity compariso'!H36*'DealScope sensitivity compariso'!C36 -> 438750 | J36: ='DealScope sensitivity compariso'!I36*(1-'Model inputs'!B38)-'DealScope sensitivity compariso'!H36*('DealScope sensitivity compariso'!B36*'DealScope sensitivity compariso'!D36+'Model inputs'!B42*'Model inputs'!B41)-SUM('Model inputs'!B76,'Model inputs'!B77) -> 373249
A37: Data cost x2 | B37: =IF(IF(IF(ISERROR('DealScope sensitivity controls'!H13=1),'DealScope sensitivity controls'!H13=1,IF('DealScope sensitivity controls'!H13="","",'DealScope sensitivity controls'!H13=1))="",FALSE,IF(ISERROR('DealScope sensitivity controls'!H13=1),'DealScope sensitivity controls'!H13=1,IF('DealScope sensitivity controls'!H13="","",'DealScope sensitivity controls'!H13=1))),'Model inputs'!B6/12*'DealScope sensitivity controls'!G13,IF('DealScope sensitivity controls'!B13="","",'DealScope sensitivity controls'!B13)) -> 4 | C37: =IF(EXACT("Hybrid","Annual deal-team"),('Model inputs'!B46/12+MAX('DealScope sensitivity compariso'!B37-'Model inputs'!B25/12,0)*'Model inputs'!B33)*(1-'DealScope sensitivity controls'!C13),('Model inputs'!B46/12+'Model inputs'!B10*'DealScope sensitivity compariso'!B37)*(1-'DealScope sensitivity controls'!C13)) -> 4500 | D37: ='Model inputs'!B15*'DealScope sensitivity controls'!E13*'DealScope sensitivity controls'!D13*'Model inputs'!B17+'Model inputs'!B30+'Model inputs'!B39+'Model inputs'!B19 -> 97.25 | E37: =IFERROR('DealScope sensitivity compariso'!C37/'DealScope sensitivity compariso'!B37,"") -> 1125 | F37: =IFERROR(('DealScope sensitivity compariso'!E37-'DealScope sensitivity compariso'!D37)/'DealScope sensitivity compariso'!E37,"") -> 0.91355556 | G37: =IFERROR(('DealScope sensitivity compariso'!C37*(1-'Model inputs'!B38)-'DealScope sensitivity compariso'!B37*'DealScope sensitivity compariso'!D37-'Model inputs'!B42*'Model inputs'!B41)/'DealScope sensitivity compariso'!C37,"") -> 0.87688889 | H37: ='Model inputs'!B132+IF(IF(IF(IF(ISERROR('Model inputs'!B29=1),'Model inputs'!B29=1,IF('Model inputs'!B29="","",'Model inputs'!B29=1))="",FALSE,IF(ISERROR('Model inputs'!B29=1),'Model inputs'!B29=1,IF('Model inputs'!B29="","",'Model inputs'!B29=1))),'Model inputs'!B43*MIN(MAX((11-'DealScope sensitivity controls'!F13)/'Model inputs'!B21,0),1),IF(IF(IF(ISERROR(11>'DealScope sensitivity controls'!F13),11>'DealScope sensitivity controls'!F13,IF('DealScope sensitivity controls'!F13="","",11>'DealScope sensitivity controls'!F13))="",FALSE,IF(ISERROR(11>'DealScope sensitivity controls'!F13),11>'DealScope sensitivity controls'!F13,IF('DealScope sensitivity controls'!F13="","",11>'DealScope sensitivity controls'!F13))),IF('Model inputs'!B43="","",'Model inputs'!B43),0))="",0,IF(IF(IF(ISERROR('Model inputs'!B29=1),'Model inputs'!B29=1,IF('Model inputs'!B29="","",'Model inputs'!B29=1))="",FALSE,IF(ISERROR('Model inputs'!B29=1),'Model inputs'!B29=1,IF('Model inputs'!B29="","",'Model inputs'!B29=1))),'Model inputs'!B43*MIN(MAX((11-'DealScope sensitivity controls'!F13)/'Model inputs'!B21,0),1),IF(IF(IF(ISERROR(11>'DealScope sensitivity controls'!F13),11>'DealScope sensitivity controls'!F13,IF('DealScope sensitivity controls'!F13="","",11>'DealScope sensitivity controls'!F13))="",FALSE,IF(ISERROR(11>'DealScope sensitivity controls'!F13),11>'DealScope sensitivity controls'!F13,IF('DealScope sensitivity controls'!F13="","",11>'DealScope sensitivity controls'!F13))),IF('Model inputs'!B43="","",'Model inputs'!B43),0)))+IF(IF(IF(IF(ISERROR('Model inputs'!B29=1),'Model inputs'!B29=1,IF('Model inputs'!B29="","",'Model inputs'!B29=1))="",FALSE,IF(ISERROR('Model inputs'!B29=1),'Model inputs'!B29=1,IF('Model inputs'!B29="","",'Model inputs'!B29=1))),'Model inputs'!B43*MIN(MAX((12-'DealScope sensitivity controls'!F13)/'Model inputs'!B21,0),1),IF(IF(IF(ISERROR(12>'DealScope sensitivity controls'!F13),12>'DealScope sensitivity controls'!F13,IF('DealScope sensitivity controls'!F13="","",12>'DealScope sensitivity controls'!F13))="",FALSE,IF(ISERROR(12>'DealScope sensitivity controls'!F13),12>'DealScope sensitivity controls'!F13,IF('DealScope sensitivity controls'!F13="","",12>'DealScope sensitivity controls'!F13))),IF('Model inputs'!B43="","",'Model inputs'!B43),0))="",0,IF(IF(IF(ISERROR('Model inputs'!B29=1),'Model inputs'!B29=1,IF('Model inputs'!B29="","",'Model inputs'!B29=1))="",FALSE,IF(ISERROR('Model inputs'!B29=1),'Model inputs'!B29=1,IF('Model inputs'!B29="","",'Model inputs'!B29=1))),'Model inputs'!B43*MIN(MAX((12-'DealScope sensitivity controls'!F13)/'Model inputs'!B21,0),1),IF(IF(IF(ISERROR(12>'DealScope sensitivity controls'!F13),12>'DealScope sensitivity controls'!F13,IF('DealScope sensitivity controls'!F13="","",12>'DealScope sensitivity controls'!F13))="",FALSE,IF(ISERROR(12>'DealScope sensitivity controls'!F13),12>'DealScope sensitivity controls'!F13,IF('DealScope sensitivity controls'!F13="","",12>'DealScope sensitivity controls'!F13))),IF('Model inputs'!B43="","",'Model inputs'!B43),0))) -> 97.5 | I37: ='DealScope sensitivity compariso'!H37*'DealScope sensitivity compariso'!C37 -> 438750 | J37: ='DealScope sensitivity compariso'!I37*(1-'Model inputs'!B38)-'DealScope sensitivity compariso'!H37*('DealScope sensitivity compariso'!B37*'DealScope sensitivity compariso'!D37+'Model inputs'!B42*'Model inputs'!B41)-SUM('Model inputs'!B76,'Model inputs'!B77) -> 372235
A38: Data cost x3 | B38: =IF(IF(IF(ISERROR('DealScope sensitivity controls'!H14=1),'DealScope sensitivity controls'!H14=1,IF('DealScope sensitivity controls'!H14="","",'DealScope sensitivity controls'!H14=1))="",FALSE,IF(ISERROR('DealScope sensitivity controls'!H14=1),'DealScope sensitivity controls'!H14=1,IF('DealScope sensitivity controls'!H14="","",'DealScope sensitivity controls'!H14=1))),'Model inputs'!B6/12*'DealScope sensitivity controls'!G14,IF('DealScope sensitivity controls'!B14="","",'DealScope sensitivity controls'!B14)) -> 4 | C38: =IF(EXACT("Hybrid","Annual deal-team"),('Model inputs'!B46/12+MAX('DealScope sensitivity compariso'!B38-'Model inputs'!B25/12,0)*'Model inputs'!B33)*(1-'DealScope sensitivity controls'!C14),('Model inputs'!B46/12+'Model inputs'!B10*'DealScope sensitivity compariso'!B38)*(1-'DealScope sensitivity controls'!C14)) -> 4500 | D38: ='Model inputs'!B15*'DealScope sensitivity controls'!E14*'DealScope sensitivity controls'!D14*'Model inputs'!B17+'Model inputs'!B30+'Model inputs'!B39+'Model inputs'!B19 -> 99.85 | E38: =IFERROR('DealScope sensitivity compariso'!C38/'DealScope sensitivity compariso'!B38,"") -> 1125 | F38: =IFERROR(('DealScope sensitivity compariso'!E38-'DealScope sensitivity compariso'!D38)/'DealScope sensitivity compariso'!E38,"") -> 0.91124444 | G38: =IFERROR(('DealScope sensitivity compariso'!C38*(1-'Model inputs'!B38)-'DealScope sensitivity compariso'!B38*'DealScope sensitivity compariso'!D38-'Model inputs'!B42*'Model inputs'!B41)/'DealScope sensitivity compariso'!C38,"") -> 0.87457778 | H38: ='Model inputs'!B137+IF(IF(IF(IF(ISERROR('Model inputs'!B29=1),'Model inputs'!B29=1,IF('Model inputs'!B29="","",'Model inputs'!B29=1))="",FALSE,IF(ISERROR('Model inputs'!B29=1),'Model inputs'!B29=1,IF('Model inputs'!B29="","",'Model inputs'!B29=1))),'Model inputs'!B43*MIN(MAX((11-'DealScope sensitivity controls'!F14)/'Model inputs'!B21,0),1),IF(IF(IF(ISERROR(11>'DealScope sensitivity controls'!F14),11>'DealScope sensitivity controls'!F14,IF('DealScope sensitivity controls'!F14="","",11>'DealScope sensitivity controls'!F14))="",FALSE,IF(ISERROR(11>'DealScope sensitivity controls'!F14),11>'DealScope sensitivity controls'!F14,IF('DealScope sensitivity controls'!F14="","",11>'DealScope sensitivity controls'!F14))),IF('Model inputs'!B43="","",'Model inputs'!B43),0))="",0,IF(IF(IF(ISERROR('Model inputs'!B29=1),'Model inputs'!B29=1,IF('Model inputs'!B29="","",'Model inputs'!B29=1))="",FALSE,IF(ISERROR('Model inputs'!B29=1),'Model inputs'!B29=1,IF('Model inputs'!B29="","",'Model inputs'!B29=1))),'Model inputs'!B43*MIN(MAX((11-'DealScope sensitivity controls'!F14)/'Model inputs'!B21,0),1),IF(IF(IF(ISERROR(11>'DealScope sensitivity controls'!F14),11>'DealScope sensitivity controls'!F14,IF('DealScope sensitivity controls'!F14="","",11>'DealScope sensitivity controls'!F14))="",FALSE,IF(ISERROR(11>'DealScope sensitivity controls'!F14),11>'DealScope sensitivity controls'!F14,IF('DealScope sensitivity controls'!F14="","",11>'DealScope sensitivity controls'!F14))),IF('Model inputs'!B43="","",'Model inputs'!B43),0)))+IF(IF(IF(IF(ISERROR('Model inputs'!B29=1),'Model inputs'!B29=1,IF('Model inputs'!B29="","",'Model inputs'!B29=1))="",FALSE,IF(ISERROR('Model inputs'!B29=1),'Model inputs'!B29=1,IF('Model inputs'!B29="","",'Model inputs'!B29=1))),'Model inputs'!B43*MIN(MAX((12-'DealScope sensitivity controls'!F14)/'Model inputs'!B21,0),1),IF(IF(IF(ISERROR(12>'DealScope sensitivity controls'!F14),12>'DealScope sensitivity controls'!F14,IF('DealScope sensitivity controls'!F14="","",12>'DealScope sensitivity controls'!F14))="",FALSE,IF(ISERROR(12>'DealScope sensitivity controls'!F14),12>'DealScope sensitivity controls'!F14,IF('DealScope sensitivity controls'!F14="","",12>'DealScope sensitivity controls'!F14))),IF('Model inputs'!B43="","",'Model inputs'!B43),0))="",0,IF(IF(IF(ISERROR('Model inputs'!B29=1),'Model inputs'!B29=1,IF('Model inputs'!B29="","",'Model inputs'!B29=1))="",FALSE,IF(ISERROR('Model inputs'!B29=1),'Model inputs'!B29=1,IF('Model inputs'!B29="","",'Model inputs'!B29=1))),'Model inputs'!B43*MIN(MAX((12-'DealScope sensitivity controls'!F14)/'Model inputs'!B21,0),1),IF(IF(IF(ISERROR(12>'DealScope sensitivity controls'!F14),12>'DealScope sensitivity controls'!F14,IF('DealScope sensitivity controls'!F14="","",12>'DealScope sensitivity controls'!F14))="",FALSE,IF(ISERROR(12>'DealScope sensitivity controls'!F14),12>'DealScope sensitivity controls'!F14,IF('DealScope sensitivity controls'!F14="","",12>'DealScope sensitivity controls'!F14))),IF('Model inputs'!B43="","",'Model inputs'!B43),0))) -> 97.5 | I38: ='DealScope sensitivity compariso'!H38*'DealScope sensitivity compariso'!C38 -> 438750 | J38: ='DealScope sensitivity compariso'!I38*(1-'Model inputs'!B38)-'DealScope sensitivity compariso'!H38*('DealScope sensitivity compariso'!B38*'DealScope sensitivity compariso'!D38+'Model inputs'!B42*'Model inputs'!B41)-SUM('Model inputs'!B76,'Model inputs'!B77) -> 371221
A39: Discount 0% | B39: =IF(IF(IF(ISERROR('DealScope sensitivity controls'!H9=1),'DealScope sensitivity controls'!H9=1,IF('DealScope sensitivity controls'!H9="","",'DealScope sensitivity controls'!H9=1))="",FALSE,IF(ISERROR('DealScope sensitivity controls'!H9=1),'DealScope sensitivity controls'!H9=1,IF('DealScope sensitivity controls'!H9="","",'DealScope sensitivity controls'!H9=1))),'Model inputs'!B6/12*'DealScope sensitivity controls'!G9,IF('DealScope sensitivity controls'!B9="","",'DealScope sensitivity controls'!B9)) -> 4 | C39: =IF(EXACT("Hybrid","Annual deal-team"),('Model inputs'!B46/12+MAX('DealScope sensitivity compariso'!B39-'Model inputs'!B25/12,0)*'Model inputs'!B33)*(1-'DealScope sensitivity controls'!C9),('Model inputs'!B46/12+'Model inputs'!B10*'DealScope sensitivity compariso'!B39)*(1-'DealScope sensitivity controls'!C9)) -> 4500 | D39: ='Model inputs'!B15*'DealScope sensitivity controls'!E9*'DealScope sensitivity controls'!D9*'Model inputs'!B17+'Model inputs'!B30+'Model inputs'!B39+'Model inputs'!B19 -> 94.65 | E39: =IFERROR('DealScope sensitivity compariso'!C39/'DealScope sensitivity compariso'!B39,"") -> 1125 | F39: =IFERROR(('DealScope sensitivity compariso'!E39-'DealScope sensitivity compariso'!D39)/'DealScope sensitivity compariso'!E39,"") -> 0.91586667 | G39: =IFERROR(('DealScope sensitivity compariso'!C39*(1-'Model inputs'!B38)-'DealScope sensitivity compariso'!B39*'DealScope sensitivity compariso'!D39-'Model inputs'!B42*'Model inputs'!B41)/'DealScope sensitivity compariso'!C39,"") -> 0.8792 | H39: ='Model inputs'!B142+IF(IF(IF(IF(ISERROR('Model inputs'!B29=1),'Model inputs'!B29=1,IF('Model inputs'!B29="","",'Model inputs'!B29=1))="",FALSE,IF(ISERROR('Model inputs'!B29=1),'Model inputs'!B29=1,IF('Model inputs'!B29="","",'Model inputs'!B29=1))),'Model inputs'!B43*MIN(MAX((11-'DealScope sensitivity controls'!F9)/'Model inputs'!B21,0),1),IF(IF(IF(ISERROR(11>'DealScope sensitivity controls'!F9),11>'DealScope sensitivity controls'!F9,IF('DealScope sensitivity controls'!F9="","",11>'DealScope sensitivity controls'!F9))="",FALSE,IF(ISERROR(11>'DealScope sensitivity controls'!F9),11>'DealScope sensitivity controls'!F9,IF('DealScope sensitivity controls'!F9="","",11>'DealScope sensitivity controls'!F9))),IF('Model inputs'!B43="","",'Model inputs'!B43),0))="",0,IF(IF(IF(ISERROR('Model inputs'!B29=1),'Model inputs'!B29=1,IF('Model inputs'!B29="","",'Model inputs'!B29=1))="",FALSE,IF(ISERROR('Model inputs'!B29=1),'Model inputs'!B29=1,IF('Model inputs'!B29="","",'Model inputs'!B29=1))),'Model inputs'!B43*MIN(MAX((11-'DealScope sensitivity controls'!F9)/'Model inputs'!B21,0),1),IF(IF(IF(ISERROR(11>'DealScope sensitivity controls'!F9),11>'DealScope sensitivity controls'!F9,IF('DealScope sensitivity controls'!F9="","",11>'DealScope sensitivity controls'!F9))="",FALSE,IF(ISERROR(11>'DealScope sensitivity controls'!F9),11>'DealScope sensitivity controls'!F9,IF('DealScope sensitivity controls'!F9="","",11>'DealScope sensitivity controls'!F9))),IF('Model inputs'!B43="","",'Model inputs'!B43),0)))+IF(IF(IF(IF(ISERROR('Model inputs'!B29=1),'Model inputs'!B29=1,IF('Model inputs'!B29="","",'Model inputs'!B29=1))="",FALSE,IF(ISERROR('Model inputs'!B29=1),'Model inputs'!B29=1,IF('Model inputs'!B29="","",'Model inputs'!B29=1))),'Model inputs'!B43*MIN(MAX((12-'DealScope sensitivity controls'!F9)/'Model inputs'!B21,0),1),IF(IF(IF(ISERROR(12>'DealScope sensitivity controls'!F9),12>'DealScope sensitivity controls'!F9,IF('DealScope sensitivity controls'!F9="","",12>'DealScope sensitivity controls'!F9))="",FALSE,IF(ISERROR(12>'DealScope sensitivity controls'!F9),12>'DealScope sensitivity controls'!F9,IF('DealScope sensitivity controls'!F9="","",12>'DealScope sensitivity controls'!F9))),IF('Model inputs'!B43="","",'Model inputs'!B43),0))="",0,IF(IF(IF(ISERROR('Model inputs'!B29=1),'Model inputs'!B29=1,IF('Model inputs'!B29="","",'Model inputs'!B29=1))="",FALSE,IF(ISERROR('Model inputs'!B29=1),'Model inputs'!B29=1,IF('Model inputs'!B29="","",'Model inputs'!B29=1))),'Model inputs'!B43*MIN(MAX((12-'DealScope sensitivity controls'!F9)/'Model inputs'!B21,0),1),IF(IF(IF(ISERROR(12>'DealScope sensitivity controls'!F9),12>'DealScope sensitivity controls'!F9,IF('DealScope sensitivity controls'!F9="","",12>'DealScope sensitivity controls'!F9))="",FALSE,IF(ISERROR(12>'DealScope sensitivity controls'!F9),12>'DealScope sensitivity controls'!F9,IF('DealScope sensitivity controls'!F9="","",12>'DealScope sensitivity controls'!F9))),IF('Model inputs'!B43="","",'Model inputs'!B43),0))) -> 97.5 | I39: ='DealScope sensitivity compariso'!H39*'DealScope sensitivity compariso'!C39 -> 438750 | J39: ='DealScope sensitivity compariso'!I39*(1-'Model inputs'!B38)-'DealScope sensitivity compariso'!H39*('DealScope sensitivity compariso'!B39*'DealScope sensitivity compariso'!D39+'Model inputs'!B42*'Model inputs'!B41)-SUM('Model inputs'!B76,'Model inputs'!B77) -> 373249
A40: Discount 20% | B40: =IF(IF(IF(ISERROR('DealScope sensitivity controls'!H10=1),'DealScope sensitivity controls'!H10=1,IF('DealScope sensitivity controls'!H10="","",'DealScope sensitivity controls'!H10=1))="",FALSE,IF(ISERROR('DealScope sensitivity controls'!H10=1),'DealScope sensitivity controls'!H10=1,IF('DealScope sensitivity controls'!H10="","",'DealScope sensitivity controls'!H10=1))),'Model inputs'!B6/12*'DealScope sensitivity controls'!G10,IF('DealScope sensitivity controls'!B10="","",'DealScope sensitivity controls'!B10)) -> 4 | C40: =IF(EXACT("Hybrid","Annual deal-team"),('Model inputs'!B46/12+MAX('DealScope sensitivity compariso'!B40-'Model inputs'!B25/12,0)*'Model inputs'!B33)*(1-'DealScope sensitivity controls'!C10),('Model inputs'!B46/12+'Model inputs'!B10*'DealScope sensitivity compariso'!B40)*(1-'DealScope sensitivity controls'!C10)) -> 3600 | D40: ='Model inputs'!B15*'DealScope sensitivity controls'!E10*'DealScope sensitivity controls'!D10*'Model inputs'!B17+'Model inputs'!B30+'Model inputs'!B39+'Model inputs'!B19 -> 94.65 | E40: =IFERROR('DealScope sensitivity compariso'!C40/'DealScope sensitivity compariso'!B40,"") -> 900 | F40: =IFERROR(('DealScope sensitivity compariso'!E40-'DealScope sensitivity compariso'!D40)/'DealScope sensitivity compariso'!E40,"") -> 0.89483333 | G40: =IFERROR(('DealScope sensitivity compariso'!C40*(1-'Model inputs'!B38)-'DealScope sensitivity compariso'!B40*'DealScope sensitivity compariso'!D40-'Model inputs'!B42*'Model inputs'!B41)/'DealScope sensitivity compariso'!C40,"") -> 0.8565 | H40: ='Model inputs'!B147+IF(IF(IF(IF(ISERROR('Model inputs'!B29=1),'Model inputs'!B29=1,IF('Model inputs'!B29="","",'Model inputs'!B29=1))="",FALSE,IF(ISERROR('Model inputs'!B29=1),'Model inputs'!B29=1,IF('Model inputs'!B29="","",'Model inputs'!B29=1))),'Model inputs'!B43*MIN(MAX((11-'DealScope sensitivity controls'!F10)/'Model inputs'!B21,0),1),IF(IF(IF(ISERROR(11>'DealScope sensitivity controls'!F10),11>'DealScope sensitivity controls'!F10,IF('DealScope sensitivity controls'!F10="","",11>'DealScope sensitivity controls'!F10))="",FALSE,IF(ISERROR(11>'DealScope sensitivity controls'!F10),11>'DealScope sensitivity controls'!F10,IF('DealScope sensitivity controls'!F10="","",11>'DealScope sensitivity controls'!F10))),IF('Model inputs'!B43="","",'Model inputs'!B43),0))="",0,IF(IF(IF(ISERROR('Model inputs'!B29=1),'Model inputs'!B29=1,IF('Model inputs'!B29="","",'Model inputs'!B29=1))="",FALSE,IF(ISERROR('Model inputs'!B29=1),'Model inputs'!B29=1,IF('Model inputs'!B29="","",'Model inputs'!B29=1))),'Model inputs'!B43*MIN(MAX((11-'DealScope sensitivity controls'!F10)/'Model inputs'!B21,0),1),IF(IF(IF(ISERROR(11>'DealScope sensitivity controls'!F10),11>'DealScope sensitivity controls'!F10,IF('DealScope sensitivity controls'!F10="","",11>'DealScope sensitivity controls'!F10))="",FALSE,IF(ISERROR(11>'DealScope sensitivity controls'!F10),11>'DealScope sensitivity controls'!F10,IF('DealScope sensitivity controls'!F10="","",11>'DealScope sensitivity controls'!F10))),IF('Model inputs'!B43="","",'Model inputs'!B43),0)))+IF(IF(IF(IF(ISERROR('Model inputs'!B29=1),'Model inputs'!B29=1,IF('Model inputs'!B29="","",'Model inputs'!B29=1))="",FALSE,IF(ISERROR('Model inputs'!B29=1),'Model inputs'!B29=1,IF('Model inputs'!B29="","",'Model inputs'!B29=1))),'Model inputs'!B43*MIN(MAX((12-'DealScope sensitivity controls'!F10)/'Model inputs'!B21,0),1),IF(IF(IF(ISERROR(12>'DealScope sensitivity controls'!F10),12>'DealScope sensitivity controls'!F10,IF('DealScope sensitivity controls'!F10="","",12>'DealScope sensitivity controls'!F10))="",FALSE,IF(ISERROR(12>'DealScope sensitivity controls'!F10),12>'DealScope sensitivity controls'!F10,IF('DealScope sensitivity controls'!F10="","",12>'DealScope sensitivity controls'!F10))),IF('Model inputs'!B43="","",'Model inputs'!B43),0))="",0,IF(IF(IF(ISERROR('Model inputs'!B29=1),'Model inputs'!B29=1,IF('Model inputs'!B29="","",'Model inputs'!B29=1))="",FALSE,IF(ISERROR('Model inputs'!B29=1),'Model inputs'!B29=1,IF('Model inputs'!B29="","",'Model inputs'!B29=1))),'Model inputs'!B43*MIN(MAX((12-'DealScope sensitivity controls'!F10)/'Model inputs'!B21,0),1),IF(IF(IF(ISERROR(12>'DealScope sensitivity controls'!F10),12>'DealScope sensitivity controls'!F10,IF('DealScope sensitivity controls'!F10="","",12>'DealScope sensitivity controls'!F10))="",FALSE,IF(ISERROR(12>'DealScope sensitivity controls'!F10),12>'DealScope sensitivity controls'!F10,IF('DealScope sensitivity controls'!F10="","",12>'DealScope sensitivity controls'!F10))),IF('Model inputs'!B43="","",'Model inputs'!B43),0))) -> 97.5 | I40: ='DealScope sensitivity compariso'!H40*'DealScope sensitivity compariso'!C40 -> 351000 | J40: ='DealScope sensitivity compariso'!I40*(1-'Model inputs'!B38)-'DealScope sensitivity compariso'!H40*('DealScope sensitivity compariso'!B40*'DealScope sensitivity compariso'!D40+'Model inputs'!B42*'Model inputs'!B41)-SUM('Model inputs'!B76,'Model inputs'!B77) -> 288131.5
A41: Discount 40% | B41: =IF(IF(IF(ISERROR('DealScope sensitivity controls'!H11=1),'DealScope sensitivity controls'!H11=1,IF('DealScope sensitivity controls'!H11="","",'DealScope sensitivity controls'!H11=1))="",FALSE,IF(ISERROR('DealScope sensitivity controls'!H11=1),'DealScope sensitivity controls'!H11=1,IF('DealScope sensitivity controls'!H11="","",'DealScope sensitivity controls'!H11=1))),'Model inputs'!B6/12*'DealScope sensitivity controls'!G11,IF('DealScope sensitivity controls'!B11="","",'DealScope sensitivity controls'!B11)) -> 4 | C41: =IF(EXACT("Hybrid","Annual deal-team"),('Model inputs'!B46/12+MAX('DealScope sensitivity compariso'!B41-'Model inputs'!B25/12,0)*'Model inputs'!B33)*(1-'DealScope sensitivity controls'!C11),('Model inputs'!B46/12+'Model inputs'!B10*'DealScope sensitivity compariso'!B41)*(1-'DealScope sensitivity controls'!C11)) -> 2700 | D41: ='Model inputs'!B15*'DealScope sensitivity controls'!E11*'DealScope sensitivity controls'!D11*'Model inputs'!B17+'Model inputs'!B30+'Model inputs'!B39+'Model inputs'!B19 -> 94.65 | E41: =IFERROR('DealScope sensitivity compariso'!C41/'DealScope sensitivity compariso'!B41,"") -> 675 | F41: =IFERROR(('DealScope sensitivity compariso'!E41-'DealScope sensitivity compariso'!D41)/'DealScope sensitivity compariso'!E41,"") -> 0.85977778 | G41: =IFERROR(('DealScope sensitivity compariso'!C41*(1-'Model inputs'!B38)-'DealScope sensitivity compariso'!B41*'DealScope sensitivity compariso'!D41-'Model inputs'!B42*'Model inputs'!B41)/'DealScope sensitivity compariso'!C41,"") -> 0.81866667 | H41: ='Model inputs'!B152+IF(IF(IF(IF(ISERROR('Model inputs'!B29=1),'Model inputs'!B29=1,IF('Model inputs'!B29="","",'Model inputs'!B29=1))="",FALSE,IF(ISERROR('Model inputs'!B29=1),'Model inputs'!B29=1,IF('Model inputs'!B29="","",'Model inputs'!B29=1))),'Model inputs'!B43*MIN(MAX((11-'DealScope sensitivity controls'!F11)/'Model inputs'!B21,0),1),IF(IF(IF(ISERROR(11>'DealScope sensitivity controls'!F11),11>'DealScope sensitivity controls'!F11,IF('DealScope sensitivity controls'!F11="","",11>'DealScope sensitivity controls'!F11))="",FALSE,IF(ISERROR(11>'DealScope sensitivity controls'!F11),11>'DealScope sensitivity controls'!F11,IF('DealScope sensitivity controls'!F11="","",11>'DealScope sensitivity controls'!F11))),IF('Model inputs'!B43="","",'Model inputs'!B43),0))="",0,IF(IF(IF(ISERROR('Model inputs'!B29=1),'Model inputs'!B29=1,IF('Model inputs'!B29="","",'Model inputs'!B29=1))="",FALSE,IF(ISERROR('Model inputs'!B29=1),'Model inputs'!B29=1,IF('Model inputs'!B29="","",'Model inputs'!B29=1))),'Model inputs'!B43*MIN(MAX((11-'DealScope sensitivity controls'!F11)/'Model inputs'!B21,0),1),IF(IF(IF(ISERROR(11>'DealScope sensitivity controls'!F11),11>'DealScope sensitivity controls'!F11,IF('DealScope sensitivity controls'!F11="","",11>'DealScope sensitivity controls'!F11))="",FALSE,IF(ISERROR(11>'DealScope sensitivity controls'!F11),11>'DealScope sensitivity controls'!F11,IF('DealScope sensitivity controls'!F11="","",11>'DealScope sensitivity controls'!F11))),IF('Model inputs'!B43="","",'Model inputs'!B43),0)))+IF(IF(IF(IF(ISERROR('Model inputs'!B29=1),'Model inputs'!B29=1,IF('Model inputs'!B29="","",'Model inputs'!B29=1))="",FALSE,IF(ISERROR('Model inputs'!B29=1),'Model inputs'!B29=1,IF('Model inputs'!B29="","",'Model inputs'!B29=1))),'Model inputs'!B43*MIN(MAX((12-'DealScope sensitivity controls'!F11)/'Model inputs'!B21,0),1),IF(IF(IF(ISERROR(12>'DealScope sensitivity controls'!F11),12>'DealScope sensitivity controls'!F11,IF('DealScope sensitivity controls'!F11="","",12>'DealScope sensitivity controls'!F11))="",FALSE,IF(ISERROR(12>'DealScope sensitivity controls'!F11),12>'DealScope sensitivity controls'!F11,IF('DealScope sensitivity controls'!F11="","",12>'DealScope sensitivity controls'!F11))),IF('Model inputs'!B43="","",'Model inputs'!B43),0))="",0,IF(IF(IF(ISERROR('Model inputs'!B29=1),'Model inputs'!B29=1,IF('Model inputs'!B29="","",'Model inputs'!B29=1))="",FALSE,IF(ISERROR('Model inputs'!B29=1),'Model inputs'!B29=1,IF('Model inputs'!B29="","",'Model inputs'!B29=1))),'Model inputs'!B43*MIN(MAX((12-'DealScope sensitivity controls'!F11)/'Model inputs'!B21,0),1),IF(IF(IF(ISERROR(12>'DealScope sensitivity controls'!F11),12>'DealScope sensitivity controls'!F11,IF('DealScope sensitivity controls'!F11="","",12>'DealScope sensitivity controls'!F11))="",FALSE,IF(ISERROR(12>'DealScope sensitivity controls'!F11),12>'DealScope sensitivity controls'!F11,IF('DealScope sensitivity controls'!F11="","",12>'DealScope sensitivity controls'!F11))),IF('Model inputs'!B43="","",'Model inputs'!B43),0))) -> 97.5 | I41: ='DealScope sensitivity compariso'!H41*'DealScope sensitivity compariso'!C41 -> 263250 | J41: ='DealScope sensitivity compariso'!I41*(1-'Model inputs'!B38)-'DealScope sensitivity compariso'!H41*('DealScope sensitivity compariso'!B41*'DealScope sensitivity compariso'!D41+'Model inputs'!B42*'Model inputs'!B41)-SUM('Model inputs'!B76,'Model inputs'!B77) -> 203014
A42: Sales delay 0 months | B42: =IF(IF(IF(ISERROR('DealScope sensitivity controls'!H18=1),'DealScope sensitivity controls'!H18=1,IF('DealScope sensitivity controls'!H18="","",'DealScope sensitivity controls'!H18=1))="",FALSE,IF(ISERROR('DealScope sensitivity controls'!H18=1),'DealScope sensitivity controls'!H18=1,IF('DealScope sensitivity controls'!H18="","",'DealScope sensitivity controls'!H18=1))),'Model inputs'!B6/12*'DealScope sensitivity controls'!G18,IF('DealScope sensitivity controls'!B18="","",'DealScope sensitivity controls'!B18)) -> 4 | C42: =IF(EXACT("Hybrid","Annual deal-team"),('Model inputs'!B46/12+MAX('DealScope sensitivity compariso'!B42-'Model inputs'!B25/12,0)*'Model inputs'!B33)*(1-'DealScope sensitivity controls'!C18),('Model inputs'!B46/12+'Model inputs'!B10*'DealScope sensitivity compariso'!B42)*(1-'DealScope sensitivity controls'!C18)) -> 4500 | D42: ='Model inputs'!B15*'DealScope sensitivity controls'!E18*'DealScope sensitivity controls'!D18*'Model inputs'!B17+'Model inputs'!B30+'Model inputs'!B39+'Model inputs'!B19 -> 94.65 | E42: =IFERROR('DealScope sensitivity compariso'!C42/'DealScope sensitivity compariso'!B42,"") -> 1125 | F42: =IFERROR(('DealScope sensitivity compariso'!E42-'DealScope sensitivity compariso'!D42)/'DealScope sensitivity compariso'!E42,"") -> 0.91586667 | G42: =IFERROR(('DealScope sensitivity compariso'!C42*(1-'Model inputs'!B38)-'DealScope sensitivity compariso'!B42*'DealScope sensitivity compariso'!D42-'Model inputs'!B42*'Model inputs'!B41)/'DealScope sensitivity compariso'!C42,"") -> 0.8792 | H42: ='Model inputs'!B157+IF(IF(IF(IF(ISERROR('Model inputs'!B29=1),'Model inputs'!B29=1,IF('Model inputs'!B29="","",'Model inputs'!B29=1))="",FALSE,IF(ISERROR('Model inputs'!B29=1),'Model inputs'!B29=1,IF('Model inputs'!B29="","",'Model inputs'!B29=1))),'Model inputs'!B43*MIN(MAX((11-'DealScope sensitivity controls'!F18)/'Model inputs'!B21,0),1),IF(IF(IF(ISERROR(11>'DealScope sensitivity controls'!F18),11>'DealScope sensitivity controls'!F18,IF('DealScope sensitivity controls'!F18="","",11>'DealScope sensitivity controls'!F18))="",FALSE,IF(ISERROR(11>'DealScope sensitivity controls'!F18),11>'DealScope sensitivity controls'!F18,IF('DealScope sensitivity controls'!F18="","",11>'DealScope sensitivity controls'!F18))),IF('Model inputs'!B43="","",'Model inputs'!B43),0))="",0,IF(IF(IF(ISERROR('Model inputs'!B29=1),'Model inputs'!B29=1,IF('Model inputs'!B29="","",'Model inputs'!B29=1))="",FALSE,IF(ISERROR('Model inputs'!B29=1),'Model inputs'!B29=1,IF('Model inputs'!B29="","",'Model inputs'!B29=1))),'Model inputs'!B43*MIN(MAX((11-'DealScope sensitivity controls'!F18)/'Model inputs'!B21,0),1),IF(IF(IF(ISERROR(11>'DealScope sensitivity controls'!F18),11>'DealScope sensitivity controls'!F18,IF('DealScope sensitivity controls'!F18="","",11>'DealScope sensitivity controls'!F18))="",FALSE,IF(ISERROR(11>'DealScope sensitivity controls'!F18),11>'DealScope sensitivity controls'!F18,IF('DealScope sensitivity controls'!F18="","",11>'DealScope sensitivity controls'!F18))),IF('Model inputs'!B43="","",'Model inputs'!B43),0)))+IF(IF(IF(IF(ISERROR('Model inputs'!B29=1),'Model inputs'!B29=1,IF('Model inputs'!B29="","",'Model inputs'!B29=1))="",FALSE,IF(ISERROR('Model inputs'!B29=1),'Model inputs'!B29=1,IF('Model inputs'!B29="","",'Model inputs'!B29=1))),'Model inputs'!B43*MIN(MAX((12-'DealScope sensitivity controls'!F18)/'Model inputs'!B21,0),1),IF(IF(IF(ISERROR(12>'DealScope sensitivity controls'!F18),12>'DealScope sensitivity controls'!F18,IF('DealScope sensitivity controls'!F18="","",12>'DealScope sensitivity controls'!F18))="",FALSE,IF(ISERROR(12>'DealScope sensitivity controls'!F18),12>'DealScope sensitivity controls'!F18,IF('DealScope sensitivity controls'!F18="","",12>'DealScope sensitivity controls'!F18))),IF('Model inputs'!B43="","",'Model inputs'!B43),0))="",0,IF(IF(IF(ISERROR('Model inputs'!B29=1),'Model inputs'!B29=1,IF('Model inputs'!B29="","",'Model inputs'!B29=1))="",FALSE,IF(ISERROR('Model inputs'!B29=1),'Model inputs'!B29=1,IF('Model inputs'!B29="","",'Model inputs'!B29=1))),'Model inputs'!B43*MIN(MAX((12-'DealScope sensitivity controls'!F18)/'Model inputs'!B21,0),1),IF(IF(IF(ISERROR(12>'DealScope sensitivity controls'!F18),12>'DealScope sensitivity controls'!F18,IF('DealScope sensitivity controls'!F18="","",12>'DealScope sensitivity controls'!F18))="",FALSE,IF(ISERROR(12>'DealScope sensitivity controls'!F18),12>'DealScope sensitivity controls'!F18,IF('DealScope sensitivity controls'!F18="","",12>'DealScope sensitivity controls'!F18))),IF('Model inputs'!B43="","",'Model inputs'!B43),0))) -> 97.5 | I42: ='DealScope sensitivity compariso'!H42*'DealScope sensitivity compariso'!C42 -> 438750 | J42: ='DealScope sensitivity compariso'!I42*(1-'Model inputs'!B38)-'DealScope sensitivity compariso'!H42*('DealScope sensitivity compariso'!B42*'DealScope sensitivity compariso'!D42+'Model inputs'!B42*'Model inputs'!B41)-SUM('Model inputs'!B76,'Model inputs'!B77) -> 373249
A43: Sales delay 2 months | B43: =IF(IF(IF(ISERROR('DealScope sensitivity controls'!H19=1),'DealScope sensitivity controls'!H19=1,IF('DealScope sensitivity controls'!H19="","",'DealScope sensitivity controls'!H19=1))="",FALSE,IF(ISERROR('DealScope sensitivity controls'!H19=1),'DealScope sensitivity controls'!H19=1,IF('DealScope sensitivity controls'!H19="","",'DealScope sensitivity controls'!H19=1))),'Model inputs'!B6/12*'DealScope sensitivity controls'!G19,IF('DealScope sensitivity controls'!B19="","",'DealScope sensitivity controls'!B19)) -> 4 | C43: =IF(EXACT("Hybrid","Annual deal-team"),('Model inputs'!B46/12+MAX('DealScope sensitivity compariso'!B43-'Model inputs'!B25/12,0)*'Model inputs'!B33)*(1-'DealScope sensitivity controls'!C19),('Model inputs'!B46/12+'Model inputs'!B10*'DealScope sensitivity compariso'!B43)*(1-'DealScope sensitivity controls'!C19)) -> 4500 | D43: ='Model inputs'!B15*'DealScope sensitivity controls'!E19*'DealScope sensitivity controls'!D19*'Model inputs'!B17+'Model inputs'!B30+'Model inputs'!B39+'Model inputs'!B19 -> 94.65 | E43: =IFERROR('DealScope sensitivity compariso'!C43/'DealScope sensitivity compariso'!B43,"") -> 1125 | F43: =IFERROR(('DealScope sensitivity compariso'!E43-'DealScope sensitivity compariso'!D43)/'DealScope sensitivity compariso'!E43,"") -> 0.91586667 | G43: =IFERROR(('DealScope sensitivity compariso'!C43*(1-'Model inputs'!B38)-'DealScope sensitivity compariso'!B43*'DealScope sensitivity compariso'!D43-'Model inputs'!B42*'Model inputs'!B41)/'DealScope sensitivity compariso'!C43,"") -> 0.8792 | H43: ='Model inputs'!B162+IF(IF(IF(IF(ISERROR('Model inputs'!B29=1),'Model inputs'!B29=1,IF('Model inputs'!B29="","",'Model inputs'!B29=1))="",FALSE,IF(ISERROR('Model inputs'!B29=1),'Model inputs'!B29=1,IF('Model inputs'!B29="","",'Model inputs'!B29=1))),'Model inputs'!B43*MIN(MAX((11-'DealScope sensitivity controls'!F19)/'Model inputs'!B21,0),1),IF(IF(IF(ISERROR(11>'DealScope sensitivity controls'!F19),11>'DealScope sensitivity controls'!F19,IF('DealScope sensitivity controls'!F19="","",11>'DealScope sensitivity controls'!F19))="",FALSE,IF(ISERROR(11>'DealScope sensitivity controls'!F19),11>'DealScope sensitivity controls'!F19,IF('DealScope sensitivity controls'!F19="","",11>'DealScope sensitivity controls'!F19))),IF('Model inputs'!B43="","",'Model inputs'!B43),0))="",0,IF(IF(IF(ISERROR('Model inputs'!B29=1),'Model inputs'!B29=1,IF('Model inputs'!B29="","",'Model inputs'!B29=1))="",FALSE,IF(ISERROR('Model inputs'!B29=1),'Model inputs'!B29=1,IF('Model inputs'!B29="","",'Model inputs'!B29=1))),'Model inputs'!B43*MIN(MAX((11-'DealScope sensitivity controls'!F19)/'Model inputs'!B21,0),1),IF(IF(IF(ISERROR(11>'DealScope sensitivity controls'!F19),11>'DealScope sensitivity controls'!F19,IF('DealScope sensitivity controls'!F19="","",11>'DealScope sensitivity controls'!F19))="",FALSE,IF(ISERROR(11>'DealScope sensitivity controls'!F19),11>'DealScope sensitivity controls'!F19,IF('DealScope sensitivity controls'!F19="","",11>'DealScope sensitivity controls'!F19))),IF('Model inputs'!B43="","",'Model inputs'!B43),0)))+IF(IF(IF(IF(ISERROR('Model inputs'!B29=1),'Model inputs'!B29=1,IF('Model inputs'!B29="","",'Model inputs'!B29=1))="",FALSE,IF(ISERROR('Model inputs'!B29=1),'Model inputs'!B29=1,IF('Model inputs'!B29="","",'Model inputs'!B29=1))),'Model inputs'!B43*MIN(MAX((12-'DealScope sensitivity controls'!F19)/'Model inputs'!B21,0),1),IF(IF(IF(ISERROR(12>'DealScope sensitivity controls'!F19),12>'DealScope sensitivity controls'!F19,IF('DealScope sensitivity controls'!F19="","",12>'DealScope sensitivity controls'!F19))="",FALSE,IF(ISERROR(12>'DealScope sensitivity controls'!F19),12>'DealScope sensitivity controls'!F19,IF('DealScope sensitivity controls'!F19="","",12>'DealScope sensitivity controls'!F19))),IF('Model inputs'!B43="","",'Model inputs'!B43),0))="",0,IF(IF(IF(ISERROR('Model inputs'!B29=1),'Model inputs'!B29=1,IF('Model inputs'!B29="","",'Model inputs'!B29=1))="",FALSE,IF(ISERROR('Model inputs'!B29=1),'Model inputs'!B29=1,IF('Model inputs'!B29="","",'Model inputs'!B29=1))),'Model inputs'!B43*MIN(MAX((12-'DealScope sensitivity controls'!F19)/'Model inputs'!B21,0),1),IF(IF(IF(ISERROR(12>'DealScope sensitivity controls'!F19),12>'DealScope sensitivity controls'!F19,IF('DealScope sensitivity controls'!F19="","",12>'DealScope sensitivity controls'!F19))="",FALSE,IF(ISERROR(12>'DealScope sensitivity controls'!F19),12>'DealScope sensitivity controls'!F19,IF('DealScope sensitivity controls'!F19="","",12>'DealScope sensitivity controls'!F19))),IF('Model inputs'!B43="","",'Model inputs'!B43),0))) -> 68.75 | I43: ='DealScope sensitivity compariso'!H43*'DealScope sensitivity compariso'!C43 -> 309375 | J43: ='DealScope sensitivity compariso'!I43*(1-'Model inputs'!B38)-'DealScope sensitivity compariso'!H43*('DealScope sensitivity compariso'!B43*'DealScope sensitivity compariso'!D43+'Model inputs'!B42*'Model inputs'!B41)-SUM('Model inputs'!B76,'Model inputs'!B77) -> 259502.5
