Workbook

Sheet DealScope 12-month financial pr
A1: DealScope 12-month financial projection
A2: DealScope — Financial projection · Growth
A4: Variable / dimension | B4: 2026-10 | C4: 2026-11 | D4: 2026-12 | E4: 2027-01 | F4: 2027-02 | G4: 2027-03 | H4: 2027-04 | I4: 2027-05 | J4: 2027-06 | K4: 2027-07 | L4: 2027-08 | M4: 2027-09
A5: Paying customer equivalents | B5: =IF(IF(IF(ISERROR('Model inputs'!O80=1),'Model inputs'!O80=1,IF('Model inputs'!O80="","",'Model inputs'!O80=1))="",FALSE,IF(ISERROR('Model inputs'!O80=1),'Model inputs'!O80=1,IF('Model inputs'!O80="","",'Model inputs'!O80=1))),'Model inputs'!O114*MIN(MAX(('Model inputs'!C105-'Model inputs'!O109)/'Model inputs'!O63,0),1),IF(IF(IF(ISERROR('Model inputs'!C105>'Model inputs'!O109),'Model inputs'!C105>'Model inputs'!O109,IF(OR('Model inputs'!C105="",'Model inputs'!O109=""),"",'Model inputs'!C105>'Model inputs'!O109))="",FALSE,IF(ISERROR('Model inputs'!C105>'Model inputs'!O109),'Model inputs'!C105>'Model inputs'!O109,IF(OR('Model inputs'!C105="",'Model inputs'!O109=""),"",'Model inputs'!C105>'Model inputs'!O109))),IF('Model inputs'!O114="","",'Model inputs'!O114),0)) -> 1.25 | C5: =IF(IF(IF(ISERROR('Model inputs'!O80=1),'Model inputs'!O80=1,IF('Model inputs'!O80="","",'Model inputs'!O80=1))="",FALSE,IF(ISERROR('Model inputs'!O80=1),'Model inputs'!O80=1,IF('Model inputs'!O80="","",'Model inputs'!O80=1))),'Model inputs'!O114*MIN(MAX(('Model inputs'!D105-'Model inputs'!O109)/'Model inputs'!O63,0),1),IF(IF(IF(ISERROR('Model inputs'!D105>'Model inputs'!O109),'Model inputs'!D105>'Model inputs'!O109,IF(OR('Model inputs'!D105="",'Model inputs'!O109=""),"",'Model inputs'!D105>'Model inputs'!O109))="",FALSE,IF(ISERROR('Model inputs'!D105>'Model inputs'!O109),'Model inputs'!D105>'Model inputs'!O109,IF(OR('Model inputs'!D105="",'Model inputs'!O109=""),"",'Model inputs'!D105>'Model inputs'!O109))),IF('Model inputs'!O114="","",'Model inputs'!O114),0)) -> 2.5 | D5: =IF(IF(IF(ISERROR('Model inputs'!O80=1),'Model inputs'!O80=1,IF('Model inputs'!O80="","",'Model inputs'!O80=1))="",FALSE,IF(ISERROR('Model inputs'!O80=1),'Model inputs'!O80=1,IF('Model inputs'!O80="","",'Model inputs'!O80=1))),'Model inputs'!O114*MIN(MAX(('Model inputs'!E105-'Model inputs'!O109)/'Model inputs'!O63,0),1),IF(IF(IF(ISERROR('Model inputs'!E105>'Model inputs'!O109),'Model inputs'!E105>'Model inputs'!O109,IF(OR('Model inputs'!E105="",'Model inputs'!O109=""),"",'Model inputs'!E105>'Model inputs'!O109))="",FALSE,IF(ISERROR('Model inputs'!E105>'Model inputs'!O109),'Model inputs'!E105>'Model inputs'!O109,IF(OR('Model inputs'!E105="",'Model inputs'!O109=""),"",'Model inputs'!E105>'Model inputs'!O109))),IF('Model inputs'!O114="","",'Model inputs'!O114),0)) -> 3.75 | E5: =IF(IF(IF(ISERROR('Model inputs'!O80=1),'Model inputs'!O80=1,IF('Model inputs'!O80="","",'Model inputs'!O80=1))="",FALSE,IF(ISERROR('Model inputs'!O80=1),'Model inputs'!O80=1,IF('Model inputs'!O80="","",'Model inputs'!O80=1))),'Model inputs'!O114*MIN(MAX(('Model inputs'!F105-'Model inputs'!O109)/'Model inputs'!O63,0),1),IF(IF(IF(ISERROR('Model inputs'!F105>'Model inputs'!O109),'Model inputs'!F105>'Model inputs'!O109,IF(OR('Model inputs'!F105="",'Model inputs'!O109=""),"",'Model inputs'!F105>'Model inputs'!O109))="",FALSE,IF(ISERROR('Model inputs'!F105>'Model inputs'!O109),'Model inputs'!F105>'Model inputs'!O109,IF(OR('Model inputs'!F105="",'Model inputs'!O109=""),"",'Model inputs'!F105>'Model inputs'!O109))),IF('Model inputs'!O114="","",'Model inputs'!O114),0)) -> 5 | F5: =IF(IF(IF(ISERROR('Model inputs'!O80=1),'Model inputs'!O80=1,IF('Model inputs'!O80="","",'Model inputs'!O80=1))="",FALSE,IF(ISERROR('Model inputs'!O80=1),'Model inputs'!O80=1,IF('Model inputs'!O80="","",'Model inputs'!O80=1))),'Model inputs'!O114*MIN(MAX(('Model inputs'!G105-'Model inputs'!O109)/'Model inputs'!O63,0),1),IF(IF(IF(ISERROR('Model inputs'!G105>'Model inputs'!O109),'Model inputs'!G105>'Model inputs'!O109,IF(OR('Model inputs'!G105="",'Model inputs'!O109=""),"",'Model inputs'!G105>'Model inputs'!O109))="",FALSE,IF(ISERROR('Model inputs'!G105>'Model inputs'!O109),'Model inputs'!G105>'Model inputs'!O109,IF(OR('Model inputs'!G105="",'Model inputs'!O109=""),"",'Model inputs'!G105>'Model inputs'!O109))),IF('Model inputs'!O114="","",'Model inputs'!O114),0)) -> 6.25 | G5: =IF(IF(IF(ISERROR('Model inputs'!O80=1),'Model inputs'!O80=1,IF('Model inputs'!O80="","",'Model inputs'!O80=1))="",FALSE,IF(ISERROR('Model inputs'!O80=1),'Model inputs'!O80=1,IF('Model inputs'!O80="","",'Model inputs'!O80=1))),'Model inputs'!O114*MIN(MAX(('Model inputs'!H105-'Model inputs'!O109)/'Model inputs'!O63,0),1),IF(IF(IF(ISERROR('Model inputs'!H105>'Model inputs'!O109),'Model inputs'!H105>'Model inputs'!O109,IF(OR('Model inputs'!H105="",'Model inputs'!O109=""),"",'Model inputs'!H105>'Model inputs'!O109))="",FALSE,IF(ISERROR('Model inputs'!H105>'Model inputs'!O109),'Model inputs'!H105>'Model inputs'!O109,IF(OR('Model inputs'!H105="",'Model inputs'!O109=""),"",'Model inputs'!H105>'Model inputs'!O109))),IF('Model inputs'!O114="","",'Model inputs'!O114),0)) -> 7.5 | H5: =IF(IF(IF(ISERROR('Model inputs'!O80=1),'Model inputs'!O80=1,IF('Model inputs'!O80="","",'Model inputs'!O80=1))="",FALSE,IF(ISERROR('Model inputs'!O80=1),'Model inputs'!O80=1,IF('Model inputs'!O80="","",'Model inputs'!O80=1))),'Model inputs'!O114*MIN(MAX(('Model inputs'!I105-'Model inputs'!O109)/'Model inputs'!O63,0),1),IF(IF(IF(ISERROR('Model inputs'!I105>'Model inputs'!O109),'Model inputs'!I105>'Model inputs'!O109,IF(OR('Model inputs'!I105="",'Model inputs'!O109=""),"",'Model inputs'!I105>'Model inputs'!O109))="",FALSE,IF(ISERROR('Model inputs'!I105>'Model inputs'!O109),'Model inputs'!I105>'Model inputs'!O109,IF(OR('Model inputs'!I105="",'Model inputs'!O109=""),"",'Model inputs'!I105>'Model inputs'!O109))),IF('Model inputs'!O114="","",'Model inputs'!O114),0)) -> 8.75 | I5: =IF(IF(IF(ISERROR('Model inputs'!O80=1),'Model inputs'!O80=1,IF('Model inputs'!O80="","",'Model inputs'!O80=1))="",FALSE,IF(ISERROR('Model inputs'!O80=1),'Model inputs'!O80=1,IF('Model inputs'!O80="","",'Model inputs'!O80=1))),'Model inputs'!O114*MIN(MAX(('Model inputs'!J105-'Model inputs'!O109)/'Model inputs'!O63,0),1),IF(IF(IF(ISERROR('Model inputs'!J105>'Model inputs'!O109),'Model inputs'!J105>'Model inputs'!O109,IF(OR('Model inputs'!J105="",'Model inputs'!O109=""),"",'Model inputs'!J105>'Model inputs'!O109))="",FALSE,IF(ISERROR('Model inputs'!J105>'Model inputs'!O109),'Model inputs'!J105>'Model inputs'!O109,IF(OR('Model inputs'!J105="",'Model inputs'!O109=""),"",'Model inputs'!J105>'Model inputs'!O109))),IF('Model inputs'!O114="","",'Model inputs'!O114),0)) -> 10 | J5: =IF(IF(IF(ISERROR('Model inputs'!O80=1),'Model inputs'!O80=1,IF('Model inputs'!O80="","",'Model inputs'!O80=1))="",FALSE,IF(ISERROR('Model inputs'!O80=1),'Model inputs'!O80=1,IF('Model inputs'!O80="","",'Model inputs'!O80=1))),'Model inputs'!O114*MIN(MAX(('Model inputs'!K105-'Model inputs'!O109)/'Model inputs'!O63,0),1),IF(IF(IF(ISERROR('Model inputs'!K105>'Model inputs'!O109),'Model inputs'!K105>'Model inputs'!O109,IF(OR('Model inputs'!K105="",'Model inputs'!O109=""),"",'Model inputs'!K105>'Model inputs'!O109))="",FALSE,IF(ISERROR('Model inputs'!K105>'Model inputs'!O109),'Model inputs'!K105>'Model inputs'!O109,IF(OR('Model inputs'!K105="",'Model inputs'!O109=""),"",'Model inputs'!K105>'Model inputs'!O109))),IF('Model inputs'!O114="","",'Model inputs'!O114),0)) -> 11.25 | K5: =IF(IF(IF(ISERROR('Model inputs'!O80=1),'Model inputs'!O80=1,IF('Model inputs'!O80="","",'Model inputs'!O80=1))="",FALSE,IF(ISERROR('Model inputs'!O80=1),'Model inputs'!O80=1,IF('Model inputs'!O80="","",'Model inputs'!O80=1))),'Model inputs'!O114*MIN(MAX(('Model inputs'!L105-'Model inputs'!O109)/'Model inputs'!O63,0),1),IF(IF(IF(ISERROR('Model inputs'!L105>'Model inputs'!O109),'Model inputs'!L105>'Model inputs'!O109,IF(OR('Model inputs'!L105="",'Model inputs'!O109=""),"",'Model inputs'!L105>'Model inputs'!O109))="",FALSE,IF(ISERROR('Model inputs'!L105>'Model inputs'!O109),'Model inputs'!L105>'Model inputs'!O109,IF(OR('Model inputs'!L105="",'Model inputs'!O109=""),"",'Model inputs'!L105>'Model inputs'!O109))),IF('Model inputs'!O114="","",'Model inputs'!O114),0)) -> 12.5 | L5: =IF(IF(IF(ISERROR('Model inputs'!O80=1),'Model inputs'!O80=1,IF('Model inputs'!O80="","",'Model inputs'!O80=1))="",FALSE,IF(ISERROR('Model inputs'!O80=1),'Model inputs'!O80=1,IF('Model inputs'!O80="","",'Model inputs'!O80=1))),'Model inputs'!O114*MIN(MAX(('Model inputs'!M105-'Model inputs'!O109)/'Model inputs'!O63,0),1),IF(IF(IF(ISERROR('Model inputs'!M105>'Model inputs'!O109),'Model inputs'!M105>'Model inputs'!O109,IF(OR('Model inputs'!M105="",'Model inputs'!O109=""),"",'Model inputs'!M105>'Model inputs'!O109))="",FALSE,IF(ISERROR('Model inputs'!M105>'Model inputs'!O109),'Model inputs'!M105>'Model inputs'!O109,IF(OR('Model inputs'!M105="",'Model inputs'!O109=""),"",'Model inputs'!M105>'Model inputs'!O109))),IF('Model inputs'!O114="","",'Model inputs'!O114),0)) -> 13.75 | M5: =IF(IF(IF(ISERROR('Model inputs'!O80=1),'Model inputs'!O80=1,IF('Model inputs'!O80="","",'Model inputs'!O80=1))="",FALSE,IF(ISERROR('Model inputs'!O80=1),'Model inputs'!O80=1,IF('Model inputs'!O80="","",'Model inputs'!O80=1))),'Model inputs'!O114*MIN(MAX(('Model inputs'!N105-'Model inputs'!O109)/'Model inputs'!O63,0),1),IF(IF(IF(ISERROR('Model inputs'!N105>'Model inputs'!O109),'Model inputs'!N105>'Model inputs'!O109,IF(OR('Model inputs'!N105="",'Model inputs'!O109=""),"",'Model inputs'!N105>'Model inputs'!O109))="",FALSE,IF(ISERROR('Model inputs'!N105>'Model inputs'!O109),'Model inputs'!N105>'Model inputs'!O109,IF(OR('Model inputs'!N105="",'Model inputs'!O109=""),"",'Model inputs'!N105>'Model inputs'!O109))),IF('Model inputs'!O114="","",'Model inputs'!O114),0)) -> 15
A6: Plan Audits delivered | B6: =IF(SUM(IF(IF('Model inputs'!B274="",0,1)="",0,IF('Model inputs'!B274="",0,1)),IF(IF('Model inputs'!B275="",0,1)="",0,IF('Model inputs'!B275="",0,1)),IF(IF('Model inputs'!B276="",0,1)="",0,IF('Model inputs'!B276="",0,1)),IF(IF('Model inputs'!B277="",0,1)="",0,IF('Model inputs'!B277="",0,1)),IF(IF('Model inputs'!B278="",0,1)="",0,IF('Model inputs'!B278="",0,1)))=0,"",SUM('Model inputs'!B274,'Model inputs'!B275,'Model inputs'!B276,'Model inputs'!B277,'Model inputs'!B278)) -> 5 | C6: =IF(SUM(IF(IF('Model inputs'!B279="",0,1)="",0,IF('Model inputs'!B279="",0,1)),IF(IF('Model inputs'!B280="",0,1)="",0,IF('Model inputs'!B280="",0,1)),IF(IF('Model inputs'!B281="",0,1)="",0,IF('Model inputs'!B281="",0,1)),IF(IF('Model inputs'!B282="",0,1)="",0,IF('Model inputs'!B282="",0,1)),IF(IF('Model inputs'!B283="",0,1)="",0,IF('Model inputs'!B283="",0,1)))=0,"",SUM('Model inputs'!B279,'Model inputs'!B280,'Model inputs'!B281,'Model inputs'!B282,'Model inputs'!B283)) -> 10 | D6: =IF(SUM(IF(IF('Model inputs'!B284="",0,1)="",0,IF('Model inputs'!B284="",0,1)),IF(IF('Model inputs'!B285="",0,1)="",0,IF('Model inputs'!B285="",0,1)),IF(IF('Model inputs'!B286="",0,1)="",0,IF('Model inputs'!B286="",0,1)),IF(IF('Model inputs'!B287="",0,1)="",0,IF('Model inputs'!B287="",0,1)),IF(IF('Model inputs'!B288="",0,1)="",0,IF('Model inputs'!B288="",0,1)))=0,"",SUM('Model inputs'!B284,'Model inputs'!B285,'Model inputs'!B286,'Model inputs'!B287,'Model inputs'!B288)) -> 15 | E6: =IF(SUM(IF(IF('Model inputs'!B289="",0,1)="",0,IF('Model inputs'!B289="",0,1)),IF(IF('Model inputs'!B290="",0,1)="",0,IF('Model inputs'!B290="",0,1)),IF(IF('Model inputs'!B291="",0,1)="",0,IF('Model inputs'!B291="",0,1)),IF(IF('Model inputs'!B292="",0,1)="",0,IF('Model inputs'!B292="",0,1)),IF(IF('Model inputs'!B293="",0,1)="",0,IF('Model inputs'!B293="",0,1)))=0,"",SUM('Model inputs'!B289,'Model inputs'!B290,'Model inputs'!B291,'Model inputs'!B292,'Model inputs'!B293)) -> 20 | F6: =IF(SUM(IF(IF('Model inputs'!B294="",0,1)="",0,IF('Model inputs'!B294="",0,1)),IF(IF('Model inputs'!B295="",0,1)="",0,IF('Model inputs'!B295="",0,1)),IF(IF('Model inputs'!B296="",0,1)="",0,IF('Model inputs'!B296="",0,1)),IF(IF('Model inputs'!B297="",0,1)="",0,IF('Model inputs'!B297="",0,1)),IF(IF('Model inputs'!B298="",0,1)="",0,IF('Model inputs'!B298="",0,1)))=0,"",SUM('Model inputs'!B294,'Model inputs'!B295,'Model inputs'!B296,'Model inputs'!B297,'Model inputs'!B298)) -> 25 | G6: =IF(SUM(IF(IF('Model inputs'!B299="",0,1)="",0,IF('Model inputs'!B299="",0,1)),IF(IF('Model inputs'!B300="",0,1)="",0,IF('Model inputs'!B300="",0,1)),IF(IF('Model inputs'!B301="",0,1)="",0,IF('Model inputs'!B301="",0,1)),IF(IF('Model inputs'!B302="",0,1)="",0,IF('Model inputs'!B302="",0,1)),IF(IF('Model inputs'!B303="",0,1)="",0,IF('Model inputs'!B303="",0,1)))=0,"",SUM('Model inputs'!B299,'Model inputs'!B300,'Model inputs'!B301,'Model inputs'!B302,'Model inputs'!B303)) -> 30 | H6: =IF(SUM(IF(IF('Model inputs'!B304="",0,1)="",0,IF('Model inputs'!B304="",0,1)),IF(IF('Model inputs'!B305="",0,1)="",0,IF('Model inputs'!B305="",0,1)),IF(IF('Model inputs'!B306="",0,1)="",0,IF('Model inputs'!B306="",0,1)),IF(IF('Model inputs'!B307="",0,1)="",0,IF('Model inputs'!B307="",0,1)),IF(IF('Model inputs'!B308="",0,1)="",0,IF('Model inputs'!B308="",0,1)))=0,"",SUM('Model inputs'!B304,'Model inputs'!B305,'Model inputs'!B306,'Model inputs'!B307,'Model inputs'!B308)) -> 35 | I6: =IF(SUM(IF(IF('Model inputs'!B309="",0,1)="",0,IF('Model inputs'!B309="",0,1)),IF(IF('Model inputs'!B310="",0,1)="",0,IF('Model inputs'!B310="",0,1)),IF(IF('Model inputs'!B311="",0,1)="",0,IF('Model inputs'!B311="",0,1)),IF(IF('Model inputs'!B312="",0,1)="",0,IF('Model inputs'!B312="",0,1)),IF(IF('Model inputs'!B313="",0,1)="",0,IF('Model inputs'!B313="",0,1)))=0,"",SUM('Model inputs'!B309,'Model inputs'!B310,'Model inputs'!B311,'Model inputs'!B312,'Model inputs'!B313)) -> 40 | J6: =IF(SUM(IF(IF('Model inputs'!B314="",0,1)="",0,IF('Model inputs'!B314="",0,1)),IF(IF('Model inputs'!B315="",0,1)="",0,IF('Model inputs'!B315="",0,1)),IF(IF('Model inputs'!B316="",0,1)="",0,IF('Model inputs'!B316="",0,1)),IF(IF('Model inputs'!B317="",0,1)="",0,IF('Model inputs'!B317="",0,1)),IF(IF('Model inputs'!B318="",0,1)="",0,IF('Model inputs'!B318="",0,1)))=0,"",SUM('Model inputs'!B314,'Model inputs'!B315,'Model inputs'!B316,'Model inputs'!B317,'Model inputs'!B318)) -> 45 | K6: =IF(SUM(IF(IF('Model inputs'!B319="",0,1)="",0,IF('Model inputs'!B319="",0,1)),IF(IF('Model inputs'!B320="",0,1)="",0,IF('Model inputs'!B320="",0,1)),IF(IF('Model inputs'!B321="",0,1)="",0,IF('Model inputs'!B321="",0,1)),IF(IF('Model inputs'!B322="",0,1)="",0,IF('Model inputs'!B322="",0,1)),IF(IF('Model inputs'!B323="",0,1)="",0,IF('Model inputs'!B323="",0,1)))=0,"",SUM('Model inputs'!B319,'Model inputs'!B320,'Model inputs'!B321,'Model inputs'!B322,'Model inputs'!B323)) -> 50 | L6: =IF(SUM(IF(IF('Model inputs'!B324="",0,1)="",0,IF('Model inputs'!B324="",0,1)),IF(IF('Model inputs'!B325="",0,1)="",0,IF('Model inputs'!B325="",0,1)),IF(IF('Model inputs'!B326="",0,1)="",0,IF('Model inputs'!B326="",0,1)),IF(IF('Model inputs'!B327="",0,1)="",0,IF('Model inputs'!B327="",0,1)),IF(IF('Model inputs'!B328="",0,1)="",0,IF('Model inputs'!B328="",0,1)))=0,"",SUM('Model inputs'!B324,'Model inputs'!B325,'Model inputs'!B326,'Model inputs'!B327,'Model inputs'!B328)) -> 55 | M6: =IF(SUM(IF(IF('Model inputs'!B329="",0,1)="",0,IF('Model inputs'!B329="",0,1)),IF(IF('Model inputs'!B330="",0,1)="",0,IF('Model inputs'!B330="",0,1)),IF(IF('Model inputs'!B331="",0,1)="",0,IF('Model inputs'!B331="",0,1)),IF(IF('Model inputs'!B332="",0,1)="",0,IF('Model inputs'!B332="",0,1)),IF(IF('Model inputs'!B333="",0,1)="",0,IF('Model inputs'!B333="",0,1)))=0,"",SUM('Model inputs'!B329,'Model inputs'!B330,'Model inputs'!B331,'Model inputs'!B332,'Model inputs'!B333)) -> 60
A7: Plan Earned revenue | B7: =IF(SUM(IF(IF('Model inputs'!B334="",0,1)="",0,IF('Model inputs'!B334="",0,1)),IF(IF('Model inputs'!B335="",0,1)="",0,IF('Model inputs'!B335="",0,1)),IF(IF('Model inputs'!B336="",0,1)="",0,IF('Model inputs'!B336="",0,1)),IF(IF('Model inputs'!B337="",0,1)="",0,IF('Model inputs'!B337="",0,1)),IF(IF('Model inputs'!B338="",0,1)="",0,IF('Model inputs'!B338="",0,1)))=0,"",SUM('Model inputs'!B334,'Model inputs'!B335,'Model inputs'!B336,'Model inputs'!B337,'Model inputs'!B338)) -> 5000 | C7: =IF(SUM(IF(IF('Model inputs'!B339="",0,1)="",0,IF('Model inputs'!B339="",0,1)),IF(IF('Model inputs'!B340="",0,1)="",0,IF('Model inputs'!B340="",0,1)),IF(IF('Model inputs'!B341="",0,1)="",0,IF('Model inputs'!B341="",0,1)),IF(IF('Model inputs'!B342="",0,1)="",0,IF('Model inputs'!B342="",0,1)),IF(IF('Model inputs'!B343="",0,1)="",0,IF('Model inputs'!B343="",0,1)))=0,"",SUM('Model inputs'!B339,'Model inputs'!B340,'Model inputs'!B341,'Model inputs'!B342,'Model inputs'!B343)) -> 10000 | D7: =IF(SUM(IF(IF('Model inputs'!B344="",0,1)="",0,IF('Model inputs'!B344="",0,1)),IF(IF('Model inputs'!B345="",0,1)="",0,IF('Model inputs'!B345="",0,1)),IF(IF('Model inputs'!B346="",0,1)="",0,IF('Model inputs'!B346="",0,1)),IF(IF('Model inputs'!B347="",0,1)="",0,IF('Model inputs'!B347="",0,1)),IF(IF('Model inputs'!B348="",0,1)="",0,IF('Model inputs'!B348="",0,1)))=0,"",SUM('Model inputs'!B344,'Model inputs'!B345,'Model inputs'!B346,'Model inputs'!B347,'Model inputs'!B348)) -> 15000 | E7: =IF(SUM(IF(IF('Model inputs'!B349="",0,1)="",0,IF('Model inputs'!B349="",0,1)),IF(IF('Model inputs'!B350="",0,1)="",0,IF('Model inputs'!B350="",0,1)),IF(IF('Model inputs'!B351="",0,1)="",0,IF('Model inputs'!B351="",0,1)),IF(IF('Model inputs'!B352="",0,1)="",0,IF('Model inputs'!B352="",0,1)),IF(IF('Model inputs'!B353="",0,1)="",0,IF('Model inputs'!B353="",0,1)))=0,"",SUM('Model inputs'!B349,'Model inputs'!B350,'Model inputs'!B351,'Model inputs'!B352,'Model inputs'!B353)) -> 20000 | F7: =IF(SUM(IF(IF('Model inputs'!B354="",0,1)="",0,IF('Model inputs'!B354="",0,1)),IF(IF('Model inputs'!B355="",0,1)="",0,IF('Model inputs'!B355="",0,1)),IF(IF('Model inputs'!B356="",0,1)="",0,IF('Model inputs'!B356="",0,1)),IF(IF('Model inputs'!B357="",0,1)="",0,IF('Model inputs'!B357="",0,1)),IF(IF('Model inputs'!B358="",0,1)="",0,IF('Model inputs'!B358="",0,1)))=0,"",SUM('Model inputs'!B354,'Model inputs'!B355,'Model inputs'!B356,'Model inputs'!B357,'Model inputs'!B358)) -> 25000 | G7: =IF(SUM(IF(IF('Model inputs'!B359="",0,1)="",0,IF('Model inputs'!B359="",0,1)),IF(IF('Model inputs'!B360="",0,1)="",0,IF('Model inputs'!B360="",0,1)),IF(IF('Model inputs'!B361="",0,1)="",0,IF('Model inputs'!B361="",0,1)),IF(IF('Model inputs'!B362="",0,1)="",0,IF('Model inputs'!B362="",0,1)),IF(IF('Model inputs'!B363="",0,1)="",0,IF('Model inputs'!B363="",0,1)))=0,"",SUM('Model inputs'!B359,'Model inputs'!B360,'Model inputs'!B361,'Model inputs'!B362,'Model inputs'!B363)) -> 30000 | H7: =IF(SUM(IF(IF('Model inputs'!B364="",0,1)="",0,IF('Model inputs'!B364="",0,1)),IF(IF('Model inputs'!B365="",0,1)="",0,IF('Model inputs'!B365="",0,1)),IF(IF('Model inputs'!B366="",0,1)="",0,IF('Model inputs'!B366="",0,1)),IF(IF('Model inputs'!B367="",0,1)="",0,IF('Model inputs'!B367="",0,1)),IF(IF('Model inputs'!B368="",0,1)="",0,IF('Model inputs'!B368="",0,1)))=0,"",SUM('Model inputs'!B364,'Model inputs'!B365,'Model inputs'!B366,'Model inputs'!B367,'Model inputs'!B368)) -> 35000 | I7: =IF(SUM(IF(IF('Model inputs'!B369="",0,1)="",0,IF('Model inputs'!B369="",0,1)),IF(IF('Model inputs'!B370="",0,1)="",0,IF('Model inputs'!B370="",0,1)),IF(IF('Model inputs'!B371="",0,1)="",0,IF('Model inputs'!B371="",0,1)),IF(IF('Model inputs'!B372="",0,1)="",0,IF('Model inputs'!B372="",0,1)),IF(IF('Model inputs'!B373="",0,1)="",0,IF('Model inputs'!B373="",0,1)))=0,"",SUM('Model inputs'!B369,'Model inputs'!B370,'Model inputs'!B371,'Model inputs'!B372,'Model inputs'!B373)) -> 40000 | J7: =IF(SUM(IF(IF('Model inputs'!B374="",0,1)="",0,IF('Model inputs'!B374="",0,1)),IF(IF('Model inputs'!B375="",0,1)="",0,IF('Model inputs'!B375="",0,1)),IF(IF('Model inputs'!B376="",0,1)="",0,IF('Model inputs'!B376="",0,1)),IF(IF('Model inputs'!B377="",0,1)="",0,IF('Model inputs'!B377="",0,1)),IF(IF('Model inputs'!B378="",0,1)="",0,IF('Model inputs'!B378="",0,1)))=0,"",SUM('Model inputs'!B374,'Model inputs'!B375,'Model inputs'!B376,'Model inputs'!B377,'Model inputs'!B378)) -> 45000 | K7: =IF(SUM(IF(IF('Model inputs'!B379="",0,1)="",0,IF('Model inputs'!B379="",0,1)),IF(IF('Model inputs'!B380="",0,1)="",0,IF('Model inputs'!B380="",0,1)),IF(IF('Model inputs'!B381="",0,1)="",0,IF('Model inputs'!B381="",0,1)),IF(IF('Model inputs'!B382="",0,1)="",0,IF('Model inputs'!B382="",0,1)),IF(IF('Model inputs'!B383="",0,1)="",0,IF('Model inputs'!B383="",0,1)))=0,"",SUM('Model inputs'!B379,'Model inputs'!B380,'Model inputs'!B381,'Model inputs'!B382,'Model inputs'!B383)) -> 50000 | L7: =IF(SUM(IF(IF('Model inputs'!B384="",0,1)="",0,IF('Model inputs'!B384="",0,1)),IF(IF('Model inputs'!B385="",0,1)="",0,IF('Model inputs'!B385="",0,1)),IF(IF('Model inputs'!B386="",0,1)="",0,IF('Model inputs'!B386="",0,1)),IF(IF('Model inputs'!B387="",0,1)="",0,IF('Model inputs'!B387="",0,1)),IF(IF('Model inputs'!B388="",0,1)="",0,IF('Model inputs'!B388="",0,1)))=0,"",SUM('Model inputs'!B384,'Model inputs'!B385,'Model inputs'!B386,'Model inputs'!B387,'Model inputs'!B388)) -> 55000 | M7: =IF(SUM(IF(IF('Model inputs'!B389="",0,1)="",0,IF('Model inputs'!B389="",0,1)),IF(IF('Model inputs'!B390="",0,1)="",0,IF('Model inputs'!B390="",0,1)),IF(IF('Model inputs'!B391="",0,1)="",0,IF('Model inputs'!B391="",0,1)),IF(IF('Model inputs'!B392="",0,1)="",0,IF('Model inputs'!B392="",0,1)),IF(IF('Model inputs'!B393="",0,1)="",0,IF('Model inputs'!B393="",0,1)))=0,"",SUM('Model inputs'!B389,'Model inputs'!B390,'Model inputs'!B391,'Model inputs'!B392,'Model inputs'!B393)) -> 60000
A8: Plan Delivery COGS | B8: =IF(SUM(IF(IF('Model inputs'!B394="",0,1)="",0,IF('Model inputs'!B394="",0,1)),IF(IF('Model inputs'!B395="",0,1)="",0,IF('Model inputs'!B395="",0,1)),IF(IF('Model inputs'!B396="",0,1)="",0,IF('Model inputs'!B396="",0,1)),IF(IF('Model inputs'!B397="",0,1)="",0,IF('Model inputs'!B397="",0,1)),IF(IF('Model inputs'!B398="",0,1)="",0,IF('Model inputs'!B398="",0,1)))=0,"",SUM('Model inputs'!B394,'Model inputs'!B395,'Model inputs'!B396,'Model inputs'!B397,'Model inputs'!B398)) -> 473.25 | C8: =IF(SUM(IF(IF('Model inputs'!B399="",0,1)="",0,IF('Model inputs'!B399="",0,1)),IF(IF('Model inputs'!B400="",0,1)="",0,IF('Model inputs'!B400="",0,1)),IF(IF('Model inputs'!B401="",0,1)="",0,IF('Model inputs'!B401="",0,1)),IF(IF('Model inputs'!B402="",0,1)="",0,IF('Model inputs'!B402="",0,1)),IF(IF('Model inputs'!B403="",0,1)="",0,IF('Model inputs'!B403="",0,1)))=0,"",SUM('Model inputs'!B399,'Model inputs'!B400,'Model inputs'!B401,'Model inputs'!B402,'Model inputs'!B403)) -> 946.5 | D8: =IF(SUM(IF(IF('Model inputs'!B404="",0,1)="",0,IF('Model inputs'!B404="",0,1)),IF(IF('Model inputs'!B405="",0,1)="",0,IF('Model inputs'!B405="",0,1)),IF(IF('Model inputs'!B406="",0,1)="",0,IF('Model inputs'!B406="",0,1)),IF(IF('Model inputs'!B407="",0,1)="",0,IF('Model inputs'!B407="",0,1)),IF(IF('Model inputs'!B408="",0,1)="",0,IF('Model inputs'!B408="",0,1)))=0,"",SUM('Model inputs'!B404,'Model inputs'!B405,'Model inputs'!B406,'Model inputs'!B407,'Model inputs'!B408)) -> 1419.75 | E8: =IF(SUM(IF(IF('Model inputs'!B409="",0,1)="",0,IF('Model inputs'!B409="",0,1)),IF(IF('Model inputs'!B410="",0,1)="",0,IF('Model inputs'!B410="",0,1)),IF(IF('Model inputs'!B411="",0,1)="",0,IF('Model inputs'!B411="",0,1)),IF(IF('Model inputs'!B412="",0,1)="",0,IF('Model inputs'!B412="",0,1)),IF(IF('Model inputs'!B413="",0,1)="",0,IF('Model inputs'!B413="",0,1)))=0,"",SUM('Model inputs'!B409,'Model inputs'!B410,'Model inputs'!B411,'Model inputs'!B412,'Model inputs'!B413)) -> 1893 | F8: =IF(SUM(IF(IF('Model inputs'!B414="",0,1)="",0,IF('Model inputs'!B414="",0,1)),IF(IF('Model inputs'!B415="",0,1)="",0,IF('Model inputs'!B415="",0,1)),IF(IF('Model inputs'!B416="",0,1)="",0,IF('Model inputs'!B416="",0,1)),IF(IF('Model inputs'!B417="",0,1)="",0,IF('Model inputs'!B417="",0,1)),IF(IF('Model inputs'!B418="",0,1)="",0,IF('Model inputs'!B418="",0,1)))=0,"",SUM('Model inputs'!B414,'Model inputs'!B415,'Model inputs'!B416,'Model inputs'!B417,'Model inputs'!B418)) -> 2366.25 | G8: =IF(SUM(IF(IF('Model inputs'!B419="",0,1)="",0,IF('Model inputs'!B419="",0,1)),IF(IF('Model inputs'!B420="",0,1)="",0,IF('Model inputs'!B420="",0,1)),IF(IF('Model inputs'!B421="",0,1)="",0,IF('Model inputs'!B421="",0,1)),IF(IF('Model inputs'!B422="",0,1)="",0,IF('Model inputs'!B422="",0,1)),IF(IF('Model inputs'!B423="",0,1)="",0,IF('Model inputs'!B423="",0,1)))=0,"",SUM('Model inputs'!B419,'Model inputs'!B420,'Model inputs'!B421,'Model inputs'!B422,'Model inputs'!B423)) -> 2839.5 | H8: =IF(SUM(IF(IF('Model inputs'!B424="",0,1)="",0,IF('Model inputs'!B424="",0,1)),IF(IF('Model inputs'!B425="",0,1)="",0,IF('Model inputs'!B425="",0,1)),IF(IF('Model inputs'!B426="",0,1)="",0,IF('Model inputs'!B426="",0,1)),IF(IF('Model inputs'!B427="",0,1)="",0,IF('Model inputs'!B427="",0,1)),IF(IF('Model inputs'!B428="",0,1)="",0,IF('Model inputs'!B428="",0,1)))=0,"",SUM('Model inputs'!B424,'Model inputs'!B425,'Model inputs'!B426,'Model inputs'!B427,'Model inputs'!B428)) -> 3312.75 | I8: =IF(SUM(IF(IF('Model inputs'!B429="",0,1)="",0,IF('Model inputs'!B429="",0,1)),IF(IF('Model inputs'!B430="",0,1)="",0,IF('Model inputs'!B430="",0,1)),IF(IF('Model inputs'!B431="",0,1)="",0,IF('Model inputs'!B431="",0,1)),IF(IF('Model inputs'!B432="",0,1)="",0,IF('Model inputs'!B432="",0,1)),IF(IF('Model inputs'!B433="",0,1)="",0,IF('Model inputs'!B433="",0,1)))=0,"",SUM('Model inputs'!B429,'Model inputs'!B430,'Model inputs'!B431,'Model inputs'!B432,'Model inputs'!B433)) -> 3786 | J8: =IF(SUM(IF(IF('Model inputs'!B434="",0,1)="",0,IF('Model inputs'!B434="",0,1)),IF(IF('Model inputs'!B435="",0,1)="",0,IF('Model inputs'!B435="",0,1)),IF(IF('Model inputs'!B436="",0,1)="",0,IF('Model inputs'!B436="",0,1)),IF(IF('Model inputs'!B437="",0,1)="",0,IF('Model inputs'!B437="",0,1)),IF(IF('Model inputs'!B438="",0,1)="",0,IF('Model inputs'!B438="",0,1)))=0,"",SUM('Model inputs'!B434,'Model inputs'!B435,'Model inputs'!B436,'Model inputs'!B437,'Model inputs'!B438)) -> 4259.25 | K8: =IF(SUM(IF(IF('Model inputs'!B439="",0,1)="",0,IF('Model inputs'!B439="",0,1)),IF(IF('Model inputs'!B440="",0,1)="",0,IF('Model inputs'!B440="",0,1)),IF(IF('Model inputs'!B441="",0,1)="",0,IF('Model inputs'!B441="",0,1)),IF(IF('Model inputs'!B442="",0,1)="",0,IF('Model inputs'!B442="",0,1)),IF(IF('Model inputs'!B443="",0,1)="",0,IF('Model inputs'!B443="",0,1)))=0,"",SUM('Model inputs'!B439,'Model inputs'!B440,'Model inputs'!B441,'Model inputs'!B442,'Model inputs'!B443)) -> 4732.5 | L8: =IF(SUM(IF(IF('Model inputs'!B444="",0,1)="",0,IF('Model inputs'!B444="",0,1)),IF(IF('Model inputs'!B445="",0,1)="",0,IF('Model inputs'!B445="",0,1)),IF(IF('Model inputs'!B446="",0,1)="",0,IF('Model inputs'!B446="",0,1)),IF(IF('Model inputs'!B447="",0,1)="",0,IF('Model inputs'!B447="",0,1)),IF(IF('Model inputs'!B448="",0,1)="",0,IF('Model inputs'!B448="",0,1)))=0,"",SUM('Model inputs'!B444,'Model inputs'!B445,'Model inputs'!B446,'Model inputs'!B447,'Model inputs'!B448)) -> 5205.75 | M8: =IF(SUM(IF(IF('Model inputs'!B449="",0,1)="",0,IF('Model inputs'!B449="",0,1)),IF(IF('Model inputs'!B450="",0,1)="",0,IF('Model inputs'!B450="",0,1)),IF(IF('Model inputs'!B451="",0,1)="",0,IF('Model inputs'!B451="",0,1)),IF(IF('Model inputs'!B452="",0,1)="",0,IF('Model inputs'!B452="",0,1)),IF(IF('Model inputs'!B453="",0,1)="",0,IF('Model inputs'!B453="",0,1)))=0,"",SUM('Model inputs'!B449,'Model inputs'!B450,'Model inputs'!B451,'Model inputs'!B452,'Model inputs'!B453)) -> 5679
A9: Plan Gross profit | B9: =IF(SUM(IF(IF('Model inputs'!B454="",0,1)="",0,IF('Model inputs'!B454="",0,1)),IF(IF('Model inputs'!B455="",0,1)="",0,IF('Model inputs'!B455="",0,1)),IF(IF('Model inputs'!B456="",0,1)="",0,IF('Model inputs'!B456="",0,1)),IF(IF('Model inputs'!B457="",0,1)="",0,IF('Model inputs'!B457="",0,1)),IF(IF('Model inputs'!B458="",0,1)="",0,IF('Model inputs'!B458="",0,1)))=0,"",SUM('Model inputs'!B454,'Model inputs'!B455,'Model inputs'!B456,'Model inputs'!B457,'Model inputs'!B458)) -> 4526.75 | C9: =IF(SUM(IF(IF('Model inputs'!B459="",0,1)="",0,IF('Model inputs'!B459="",0,1)),IF(IF('Model inputs'!B460="",0,1)="",0,IF('Model inputs'!B460="",0,1)),IF(IF('Model inputs'!B461="",0,1)="",0,IF('Model inputs'!B461="",0,1)),IF(IF('Model inputs'!B462="",0,1)="",0,IF('Model inputs'!B462="",0,1)),IF(IF('Model inputs'!B463="",0,1)="",0,IF('Model inputs'!B463="",0,1)))=0,"",SUM('Model inputs'!B459,'Model inputs'!B460,'Model inputs'!B461,'Model inputs'!B462,'Model inputs'!B463)) -> 9053.5 | D9: =IF(SUM(IF(IF('Model inputs'!B464="",0,1)="",0,IF('Model inputs'!B464="",0,1)),IF(IF('Model inputs'!B465="",0,1)="",0,IF('Model inputs'!B465="",0,1)),IF(IF('Model inputs'!B466="",0,1)="",0,IF('Model inputs'!B466="",0,1)),IF(IF('Model inputs'!B467="",0,1)="",0,IF('Model inputs'!B467="",0,1)),IF(IF('Model inputs'!B468="",0,1)="",0,IF('Model inputs'!B468="",0,1)))=0,"",SUM('Model inputs'!B464,'Model inputs'!B465,'Model inputs'!B466,'Model inputs'!B467,'Model inputs'!B468)) -> 13580.25 | E9: =IF(SUM(IF(IF('Model inputs'!B469="",0,1)="",0,IF('Model inputs'!B469="",0,1)),IF(IF('Model inputs'!B470="",0,1)="",0,IF('Model inputs'!B470="",0,1)),IF(IF('Model inputs'!B471="",0,1)="",0,IF('Model inputs'!B471="",0,1)),IF(IF('Model inputs'!B472="",0,1)="",0,IF('Model inputs'!B472="",0,1)),IF(IF('Model inputs'!B473="",0,1)="",0,IF('Model inputs'!B473="",0,1)))=0,"",SUM('Model inputs'!B469,'Model inputs'!B470,'Model inputs'!B471,'Model inputs'!B472,'Model inputs'!B473)) -> 18107 | F9: =IF(SUM(IF(IF('Model inputs'!B474="",0,1)="",0,IF('Model inputs'!B474="",0,1)),IF(IF('Model inputs'!B475="",0,1)="",0,IF('Model inputs'!B475="",0,1)),IF(IF('Model inputs'!B476="",0,1)="",0,IF('Model inputs'!B476="",0,1)),IF(IF('Model inputs'!B477="",0,1)="",0,IF('Model inputs'!B477="",0,1)),IF(IF('Model inputs'!B478="",0,1)="",0,IF('Model inputs'!B478="",0,1)))=0,"",SUM('Model inputs'!B474,'Model inputs'!B475,'Model inputs'!B476,'Model inputs'!B477,'Model inputs'!B478)) -> 22633.75 | G9: =IF(SUM(IF(IF('Model inputs'!B479="",0,1)="",0,IF('Model inputs'!B479="",0,1)),IF(IF('Model inputs'!B480="",0,1)="",0,IF('Model inputs'!B480="",0,1)),IF(IF('Model inputs'!B481="",0,1)="",0,IF('Model inputs'!B481="",0,1)),IF(IF('Model inputs'!B482="",0,1)="",0,IF('Model inputs'!B482="",0,1)),IF(IF('Model inputs'!B483="",0,1)="",0,IF('Model inputs'!B483="",0,1)))=0,"",SUM('Model inputs'!B479,'Model inputs'!B480,'Model inputs'!B481,'Model inputs'!B482,'Model inputs'!B483)) -> 27160.5 | H9: =IF(SUM(IF(IF('Model inputs'!B484="",0,1)="",0,IF('Model inputs'!B484="",0,1)),IF(IF('Model inputs'!B485="",0,1)="",0,IF('Model inputs'!B485="",0,1)),IF(IF('Model inputs'!B486="",0,1)="",0,IF('Model inputs'!B486="",0,1)),IF(IF('Model inputs'!B487="",0,1)="",0,IF('Model inputs'!B487="",0,1)),IF(IF('Model inputs'!B488="",0,1)="",0,IF('Model inputs'!B488="",0,1)))=0,"",SUM('Model inputs'!B484,'Model inputs'!B485,'Model inputs'!B486,'Model inputs'!B487,'Model inputs'!B488)) -> 31687.25 | I9: =IF(SUM(IF(IF('Model inputs'!B489="",0,1)="",0,IF('Model inputs'!B489="",0,1)),IF(IF('Model inputs'!B490="",0,1)="",0,IF('Model inputs'!B490="",0,1)),IF(IF('Model inputs'!B491="",0,1)="",0,IF('Model inputs'!B491="",0,1)),IF(IF('Model inputs'!B492="",0,1)="",0,IF('Model inputs'!B492="",0,1)),IF(IF('Model inputs'!B493="",0,1)="",0,IF('Model inputs'!B493="",0,1)))=0,"",SUM('Model inputs'!B489,'Model inputs'!B490,'Model inputs'!B491,'Model inputs'!B492,'Model inputs'!B493)) -> 36214 | J9: =IF(SUM(IF(IF('Model inputs'!B494="",0,1)="",0,IF('Model inputs'!B494="",0,1)),IF(IF('Model inputs'!B495="",0,1)="",0,IF('Model inputs'!B495="",0,1)),IF(IF('Model inputs'!B496="",0,1)="",0,IF('Model inputs'!B496="",0,1)),IF(IF('Model inputs'!B497="",0,1)="",0,IF('Model inputs'!B497="",0,1)),IF(IF('Model inputs'!B498="",0,1)="",0,IF('Model inputs'!B498="",0,1)))=0,"",SUM('Model inputs'!B494,'Model inputs'!B495,'Model inputs'!B496,'Model inputs'!B497,'Model inputs'!B498)) -> 40740.75 | K9: =IF(SUM(IF(IF('Model inputs'!B499="",0,1)="",0,IF('Model inputs'!B499="",0,1)),IF(IF('Model inputs'!B500="",0,1)="",0,IF('Model inputs'!B500="",0,1)),IF(IF('Model inputs'!B501="",0,1)="",0,IF('Model inputs'!B501="",0,1)),IF(IF('Model inputs'!B502="",0,1)="",0,IF('Model inputs'!B502="",0,1)),IF(IF('Model inputs'!B503="",0,1)="",0,IF('Model inputs'!B503="",0,1)))=0,"",SUM('Model inputs'!B499,'Model inputs'!B500,'Model inputs'!B501,'Model inputs'!B502,'Model inputs'!B503)) -> 45267.5 | L9: =IF(SUM(IF(IF('Model inputs'!B504="",0,1)="",0,IF('Model inputs'!B504="",0,1)),IF(IF('Model inputs'!B505="",0,1)="",0,IF('Model inputs'!B505="",0,1)),IF(IF('Model inputs'!B506="",0,1)="",0,IF('Model inputs'!B506="",0,1)),IF(IF('Model inputs'!B507="",0,1)="",0,IF('Model inputs'!B507="",0,1)),IF(IF('Model inputs'!B508="",0,1)="",0,IF('Model inputs'!B508="",0,1)))=0,"",SUM('Model inputs'!B504,'Model inputs'!B505,'Model inputs'!B506,'Model inputs'!B507,'Model inputs'!B508)) -> 49794.25 | M9: =IF(SUM(IF(IF('Model inputs'!B509="",0,1)="",0,IF('Model inputs'!B509="",0,1)),IF(IF('Model inputs'!B510="",0,1)="",0,IF('Model inputs'!B510="",0,1)),IF(IF('Model inputs'!B511="",0,1)="",0,IF('Model inputs'!B511="",0,1)),IF(IF('Model inputs'!B512="",0,1)="",0,IF('Model inputs'!B512="",0,1)),IF(IF('Model inputs'!B513="",0,1)="",0,IF('Model inputs'!B513="",0,1)))=0,"",SUM('Model inputs'!B509,'Model inputs'!B510,'Model inputs'!B511,'Model inputs'!B512,'Model inputs'!B513)) -> 54321
A10: Plan Gross margin by pricing | B10: =IF(SUM(IF(IF('Model inputs'!B514="",0,1)="",0,IF('Model inputs'!B514="",0,1)),IF(IF('Model inputs'!B515="",0,1)="",0,IF('Model inputs'!B515="",0,1)),IF(IF('Model inputs'!B516="",0,1)="",0,IF('Model inputs'!B516="",0,1)),IF(IF('Model inputs'!B517="",0,1)="",0,IF('Model inputs'!B517="",0,1)),IF(IF('Model inputs'!B518="",0,1)="",0,IF('Model inputs'!B518="",0,1)))=0,"",SUM('Model inputs'!B514,'Model inputs'!B515,'Model inputs'!B516,'Model inputs'!B517,'Model inputs'!B518)) -> 0.90535 | C10: =IF(SUM(IF(IF('Model inputs'!B519="",0,1)="",0,IF('Model inputs'!B519="",0,1)),IF(IF('Model inputs'!B520="",0,1)="",0,IF('Model inputs'!B520="",0,1)),IF(IF('Model inputs'!B521="",0,1)="",0,IF('Model inputs'!B521="",0,1)),IF(IF('Model inputs'!B522="",0,1)="",0,IF('Model inputs'!B522="",0,1)),IF(IF('Model inputs'!B523="",0,1)="",0,IF('Model inputs'!B523="",0,1)))=0,"",SUM('Model inputs'!B519,'Model inputs'!B520,'Model inputs'!B521,'Model inputs'!B522,'Model inputs'!B523)) -> 0.90535 | D10: =IF(SUM(IF(IF('Model inputs'!B524="",0,1)="",0,IF('Model inputs'!B524="",0,1)),IF(IF('Model inputs'!B525="",0,1)="",0,IF('Model inputs'!B525="",0,1)),IF(IF('Model inputs'!B526="",0,1)="",0,IF('Model inputs'!B526="",0,1)),IF(IF('Model inputs'!B527="",0,1)="",0,IF('Model inputs'!B527="",0,1)),IF(IF('Model inputs'!B528="",0,1)="",0,IF('Model inputs'!B528="",0,1)))=0,"",SUM('Model inputs'!B524,'Model inputs'!B525,'Model inputs'!B526,'Model inputs'!B527,'Model inputs'!B528)) -> 0.90535 | E10: =IF(SUM(IF(IF('Model inputs'!B529="",0,1)="",0,IF('Model inputs'!B529="",0,1)),IF(IF('Model inputs'!B530="",0,1)="",0,IF('Model inputs'!B530="",0,1)),IF(IF('Model inputs'!B531="",0,1)="",0,IF('Model inputs'!B531="",0,1)),IF(IF('Model inputs'!B532="",0,1)="",0,IF('Model inputs'!B532="",0,1)),IF(IF('Model inputs'!B533="",0,1)="",0,IF('Model inputs'!B533="",0,1)))=0,"",SUM('Model inputs'!B529,'Model inputs'!B530,'Model inputs'!B531,'Model inputs'!B532,'Model inputs'!B533)) -> 0.90535 | F10: =IF(SUM(IF(IF('Model inputs'!B534="",0,1)="",0,IF('Model inputs'!B534="",0,1)),IF(IF('Model inputs'!B535="",0,1)="",0,IF('Model inputs'!B535="",0,1)),IF(IF('Model inputs'!B536="",0,1)="",0,IF('Model inputs'!B536="",0,1)),IF(IF('Model inputs'!B537="",0,1)="",0,IF('Model inputs'!B537="",0,1)),IF(IF('Model inputs'!B538="",0,1)="",0,IF('Model inputs'!B538="",0,1)))=0,"",SUM('Model inputs'!B534,'Model inputs'!B535,'Model inputs'!B536,'Model inputs'!B537,'Model inputs'!B538)) -> 0.90535 | G10: =IF(SUM(IF(IF('Model inputs'!B539="",0,1)="",0,IF('Model inputs'!B539="",0,1)),IF(IF('Model inputs'!B540="",0,1)="",0,IF('Model inputs'!B540="",0,1)),IF(IF('Model inputs'!B541="",0,1)="",0,IF('Model inputs'!B541="",0,1)),IF(IF('Model inputs'!B542="",0,1)="",0,IF('Model inputs'!B542="",0,1)),IF(IF('Model inputs'!B543="",0,1)="",0,IF('Model inputs'!B543="",0,1)))=0,"",SUM('Model inputs'!B539,'Model inputs'!B540,'Model inputs'!B541,'Model inputs'!B542,'Model inputs'!B543)) -> 0.90535 | H10: =IF(SUM(IF(IF('Model inputs'!B544="",0,1)="",0,IF('Model inputs'!B544="",0,1)),IF(IF('Model inputs'!B545="",0,1)="",0,IF('Model inputs'!B545="",0,1)),IF(IF('Model inputs'!B546="",0,1)="",0,IF('Model inputs'!B546="",0,1)),IF(IF('Model inputs'!B547="",0,1)="",0,IF('Model inputs'!B547="",0,1)),IF(IF('Model inputs'!B548="",0,1)="",0,IF('Model inputs'!B548="",0,1)))=0,"",SUM('Model inputs'!B544,'Model inputs'!B545,'Model inputs'!B546,'Model inputs'!B547,'Model inputs'!B548)) -> 0.90535 | I10: =IF(SUM(IF(IF('Model inputs'!B549="",0,1)="",0,IF('Model inputs'!B549="",0,1)),IF(IF('Model inputs'!B550="",0,1)="",0,IF('Model inputs'!B550="",0,1)),IF(IF('Model inputs'!B551="",0,1)="",0,IF('Model inputs'!B551="",0,1)),IF(IF('Model inputs'!B552="",0,1)="",0,IF('Model inputs'!B552="",0,1)),IF(IF('Model inputs'!B553="",0,1)="",0,IF('Model inputs'!B553="",0,1)))=0,"",SUM('Model inputs'!B549,'Model inputs'!B550,'Model inputs'!B551,'Model inputs'!B552,'Model inputs'!B553)) -> 0.90535 | J10: =IF(SUM(IF(IF('Model inputs'!B554="",0,1)="",0,IF('Model inputs'!B554="",0,1)),IF(IF('Model inputs'!B555="",0,1)="",0,IF('Model inputs'!B555="",0,1)),IF(IF('Model inputs'!B556="",0,1)="",0,IF('Model inputs'!B556="",0,1)),IF(IF('Model inputs'!B557="",0,1)="",0,IF('Model inputs'!B557="",0,1)),IF(IF('Model inputs'!B558="",0,1)="",0,IF('Model inputs'!B558="",0,1)))=0,"",SUM('Model inputs'!B554,'Model inputs'!B555,'Model inputs'!B556,'Model inputs'!B557,'Model inputs'!B558)) -> 0.90535 | K10: =IF(SUM(IF(IF('Model inputs'!B559="",0,1)="",0,IF('Model inputs'!B559="",0,1)),IF(IF('Model inputs'!B560="",0,1)="",0,IF('Model inputs'!B560="",0,1)),IF(IF('Model inputs'!B561="",0,1)="",0,IF('Model inputs'!B561="",0,1)),IF(IF('Model inputs'!B562="",0,1)="",0,IF('Model inputs'!B562="",0,1)),IF(IF('Model inputs'!B563="",0,1)="",0,IF('Model inputs'!B563="",0,1)))=0,"",SUM('Model inputs'!B559,'Model inputs'!B560,'Model inputs'!B561,'Model inputs'!B562,'Model inputs'!B563)) -> 0.90535 | L10: =IF(SUM(IF(IF('Model inputs'!B564="",0,1)="",0,IF('Model inputs'!B564="",0,1)),IF(IF('Model inputs'!B565="",0,1)="",0,IF('Model inputs'!B565="",0,1)),IF(IF('Model inputs'!B566="",0,1)="",0,IF('Model inputs'!B566="",0,1)),IF(IF('Model inputs'!B567="",0,1)="",0,IF('Model inputs'!B567="",0,1)),IF(IF('Model inputs'!B568="",0,1)="",0,IF('Model inputs'!B568="",0,1)))=0,"",SUM('Model inputs'!B564,'Model inputs'!B565,'Model inputs'!B566,'Model inputs'!B567,'Model inputs'!B568)) -> 0.90535 | M10: =IF(SUM(IF(IF('Model inputs'!B569="",0,1)="",0,IF('Model inputs'!B569="",0,1)),IF(IF('Model inputs'!B570="",0,1)="",0,IF('Model inputs'!B570="",0,1)),IF(IF('Model inputs'!B571="",0,1)="",0,IF('Model inputs'!B571="",0,1)),IF(IF('Model inputs'!B572="",0,1)="",0,IF('Model inputs'!B572="",0,1)),IF(IF('Model inputs'!B573="",0,1)="",0,IF('Model inputs'!B573="",0,1)))=0,"",SUM('Model inputs'!B569,'Model inputs'!B570,'Model inputs'!B571,'Model inputs'!B572,'Model inputs'!B573)) -> 0.90535
A11: Plan Account support cost | B11: =IF(SUM(IF(IF('Model inputs'!B574="",0,1)="",0,IF('Model inputs'!B574="",0,1)),IF(IF('Model inputs'!B575="",0,1)="",0,IF('Model inputs'!B575="",0,1)),IF(IF('Model inputs'!B576="",0,1)="",0,IF('Model inputs'!B576="",0,1)),IF(IF('Model inputs'!B577="",0,1)="",0,IF('Model inputs'!B577="",0,1)),IF(IF('Model inputs'!B578="",0,1)="",0,IF('Model inputs'!B578="",0,1)))=0,"",SUM('Model inputs'!B574,'Model inputs'!B575,'Model inputs'!B576,'Model inputs'!B577,'Model inputs'!B578)) -> 37.5 | C11: =IF(SUM(IF(IF('Model inputs'!B579="",0,1)="",0,IF('Model inputs'!B579="",0,1)),IF(IF('Model inputs'!B580="",0,1)="",0,IF('Model inputs'!B580="",0,1)),IF(IF('Model inputs'!B581="",0,1)="",0,IF('Model inputs'!B581="",0,1)),IF(IF('Model inputs'!B582="",0,1)="",0,IF('Model inputs'!B582="",0,1)),IF(IF('Model inputs'!B583="",0,1)="",0,IF('Model inputs'!B583="",0,1)))=0,"",SUM('Model inputs'!B579,'Model inputs'!B580,'Model inputs'!B581,'Model inputs'!B582,'Model inputs'!B583)) -> 75 | D11: =IF(SUM(IF(IF('Model inputs'!B584="",0,1)="",0,IF('Model inputs'!B584="",0,1)),IF(IF('Model inputs'!B585="",0,1)="",0,IF('Model inputs'!B585="",0,1)),IF(IF('Model inputs'!B586="",0,1)="",0,IF('Model inputs'!B586="",0,1)),IF(IF('Model inputs'!B587="",0,1)="",0,IF('Model inputs'!B587="",0,1)),IF(IF('Model inputs'!B588="",0,1)="",0,IF('Model inputs'!B588="",0,1)))=0,"",SUM('Model inputs'!B584,'Model inputs'!B585,'Model inputs'!B586,'Model inputs'!B587,'Model inputs'!B588)) -> 112.5 | E11: =IF(SUM(IF(IF('Model inputs'!B589="",0,1)="",0,IF('Model inputs'!B589="",0,1)),IF(IF('Model inputs'!B590="",0,1)="",0,IF('Model inputs'!B590="",0,1)),IF(IF('Model inputs'!B591="",0,1)="",0,IF('Model inputs'!B591="",0,1)),IF(IF('Model inputs'!B592="",0,1)="",0,IF('Model inputs'!B592="",0,1)),IF(IF('Model inputs'!B593="",0,1)="",0,IF('Model inputs'!B593="",0,1)))=0,"",SUM('Model inputs'!B589,'Model inputs'!B590,'Model inputs'!B591,'Model inputs'!B592,'Model inputs'!B593)) -> 150 | F11: =IF(SUM(IF(IF('Model inputs'!B594="",0,1)="",0,IF('Model inputs'!B594="",0,1)),IF(IF('Model inputs'!B595="",0,1)="",0,IF('Model inputs'!B595="",0,1)),IF(IF('Model inputs'!B596="",0,1)="",0,IF('Model inputs'!B596="",0,1)),IF(IF('Model inputs'!B597="",0,1)="",0,IF('Model inputs'!B597="",0,1)),IF(IF('Model inputs'!B598="",0,1)="",0,IF('Model inputs'!B598="",0,1)))=0,"",SUM('Model inputs'!B594,'Model inputs'!B595,'Model inputs'!B596,'Model inputs'!B597,'Model inputs'!B598)) -> 187.5 | G11: =IF(SUM(IF(IF('Model inputs'!B599="",0,1)="",0,IF('Model inputs'!B599="",0,1)),IF(IF('Model inputs'!B600="",0,1)="",0,IF('Model inputs'!B600="",0,1)),IF(IF('Model inputs'!B601="",0,1)="",0,IF('Model inputs'!B601="",0,1)),IF(IF('Model inputs'!B602="",0,1)="",0,IF('Model inputs'!B602="",0,1)),IF(IF('Model inputs'!B603="",0,1)="",0,IF('Model inputs'!B603="",0,1)))=0,"",SUM('Model inputs'!B599,'Model inputs'!B600,'Model inputs'!B601,'Model inputs'!B602,'Model inputs'!B603)) -> 225 | H11: =IF(SUM(IF(IF('Model inputs'!B604="",0,1)="",0,IF('Model inputs'!B604="",0,1)),IF(IF('Model inputs'!B605="",0,1)="",0,IF('Model inputs'!B605="",0,1)),IF(IF('Model inputs'!B606="",0,1)="",0,IF('Model inputs'!B606="",0,1)),IF(IF('Model inputs'!B607="",0,1)="",0,IF('Model inputs'!B607="",0,1)),IF(IF('Model inputs'!B608="",0,1)="",0,IF('Model inputs'!B608="",0,1)))=0,"",SUM('Model inputs'!B604,'Model inputs'!B605,'Model inputs'!B606,'Model inputs'!B607,'Model inputs'!B608)) -> 262.5 | I11: =IF(SUM(IF(IF('Model inputs'!B609="",0,1)="",0,IF('Model inputs'!B609="",0,1)),IF(IF('Model inputs'!B610="",0,1)="",0,IF('Model inputs'!B610="",0,1)),IF(IF('Model inputs'!B611="",0,1)="",0,IF('Model inputs'!B611="",0,1)),IF(IF('Model inputs'!B612="",0,1)="",0,IF('Model inputs'!B612="",0,1)),IF(IF('Model inputs'!B613="",0,1)="",0,IF('Model inputs'!B613="",0,1)))=0,"",SUM('Model inputs'!B609,'Model inputs'!B610,'Model inputs'!B611,'Model inputs'!B612,'Model inputs'!B613)) -> 300 | J11: =IF(SUM(IF(IF('Model inputs'!B614="",0,1)="",0,IF('Model inputs'!B614="",0,1)),IF(IF('Model inputs'!B615="",0,1)="",0,IF('Model inputs'!B615="",0,1)),IF(IF('Model inputs'!B616="",0,1)="",0,IF('Model inputs'!B616="",0,1)),IF(IF('Model inputs'!B617="",0,1)="",0,IF('Model inputs'!B617="",0,1)),IF(IF('Model inputs'!B618="",0,1)="",0,IF('Model inputs'!B618="",0,1)))=0,"",SUM('Model inputs'!B614,'Model inputs'!B615,'Model inputs'!B616,'Model inputs'!B617,'Model inputs'!B618)) -> 337.5 | K11: =IF(SUM(IF(IF('Model inputs'!B619="",0,1)="",0,IF('Model inputs'!B619="",0,1)),IF(IF('Model inputs'!B620="",0,1)="",0,IF('Model inputs'!B620="",0,1)),IF(IF('Model inputs'!B621="",0,1)="",0,IF('Model inputs'!B621="",0,1)),IF(IF('Model inputs'!B622="",0,1)="",0,IF('Model inputs'!B622="",0,1)),IF(IF('Model inputs'!B623="",0,1)="",0,IF('Model inputs'!B623="",0,1)))=0,"",SUM('Model inputs'!B619,'Model inputs'!B620,'Model inputs'!B621,'Model inputs'!B622,'Model inputs'!B623)) -> 375 | L11: =IF(SUM(IF(IF('Model inputs'!B624="",0,1)="",0,IF('Model inputs'!B624="",0,1)),IF(IF('Model inputs'!B625="",0,1)="",0,IF('Model inputs'!B625="",0,1)),IF(IF('Model inputs'!B626="",0,1)="",0,IF('Model inputs'!B626="",0,1)),IF(IF('Model inputs'!B627="",0,1)="",0,IF('Model inputs'!B627="",0,1)),IF(IF('Model inputs'!B628="",0,1)="",0,IF('Model inputs'!B628="",0,1)))=0,"",SUM('Model inputs'!B624,'Model inputs'!B625,'Model inputs'!B626,'Model inputs'!B627,'Model inputs'!B628)) -> 412.5 | M11: =IF(SUM(IF(IF('Model inputs'!B629="",0,1)="",0,IF('Model inputs'!B629="",0,1)),IF(IF('Model inputs'!B630="",0,1)="",0,IF('Model inputs'!B630="",0,1)),IF(IF('Model inputs'!B631="",0,1)="",0,IF('Model inputs'!B631="",0,1)),IF(IF('Model inputs'!B632="",0,1)="",0,IF('Model inputs'!B632="",0,1)),IF(IF('Model inputs'!B633="",0,1)="",0,IF('Model inputs'!B633="",0,1)))=0,"",SUM('Model inputs'!B629,'Model inputs'!B630,'Model inputs'!B631,'Model inputs'!B632,'Model inputs'!B633)) -> 450
A12: Plan Contribution profit | B12: =IF(SUM(IF(IF('Model inputs'!B634="",0,1)="",0,IF('Model inputs'!B634="",0,1)),IF(IF('Model inputs'!B635="",0,1)="",0,IF('Model inputs'!B635="",0,1)),IF(IF('Model inputs'!B636="",0,1)="",0,IF('Model inputs'!B636="",0,1)),IF(IF('Model inputs'!B637="",0,1)="",0,IF('Model inputs'!B637="",0,1)),IF(IF('Model inputs'!B638="",0,1)="",0,IF('Model inputs'!B638="",0,1)))=0,"",SUM('Model inputs'!B634,'Model inputs'!B635,'Model inputs'!B636,'Model inputs'!B637,'Model inputs'!B638)) -> 4339.25 | C12: =IF(SUM(IF(IF('Model inputs'!B639="",0,1)="",0,IF('Model inputs'!B639="",0,1)),IF(IF('Model inputs'!B640="",0,1)="",0,IF('Model inputs'!B640="",0,1)),IF(IF('Model inputs'!B641="",0,1)="",0,IF('Model inputs'!B641="",0,1)),IF(IF('Model inputs'!B642="",0,1)="",0,IF('Model inputs'!B642="",0,1)),IF(IF('Model inputs'!B643="",0,1)="",0,IF('Model inputs'!B643="",0,1)))=0,"",SUM('Model inputs'!B639,'Model inputs'!B640,'Model inputs'!B641,'Model inputs'!B642,'Model inputs'!B643)) -> 8678.5 | D12: =IF(SUM(IF(IF('Model inputs'!B644="",0,1)="",0,IF('Model inputs'!B644="",0,1)),IF(IF('Model inputs'!B645="",0,1)="",0,IF('Model inputs'!B645="",0,1)),IF(IF('Model inputs'!B646="",0,1)="",0,IF('Model inputs'!B646="",0,1)),IF(IF('Model inputs'!B647="",0,1)="",0,IF('Model inputs'!B647="",0,1)),IF(IF('Model inputs'!B648="",0,1)="",0,IF('Model inputs'!B648="",0,1)))=0,"",SUM('Model inputs'!B644,'Model inputs'!B645,'Model inputs'!B646,'Model inputs'!B647,'Model inputs'!B648)) -> 13017.75 | E12: =IF(SUM(IF(IF('Model inputs'!B649="",0,1)="",0,IF('Model inputs'!B649="",0,1)),IF(IF('Model inputs'!B650="",0,1)="",0,IF('Model inputs'!B650="",0,1)),IF(IF('Model inputs'!B651="",0,1)="",0,IF('Model inputs'!B651="",0,1)),IF(IF('Model inputs'!B652="",0,1)="",0,IF('Model inputs'!B652="",0,1)),IF(IF('Model inputs'!B653="",0,1)="",0,IF('Model inputs'!B653="",0,1)))=0,"",SUM('Model inputs'!B649,'Model inputs'!B650,'Model inputs'!B651,'Model inputs'!B652,'Model inputs'!B653)) -> 17357 | F12: =IF(SUM(IF(IF('Model inputs'!B654="",0,1)="",0,IF('Model inputs'!B654="",0,1)),IF(IF('Model inputs'!B655="",0,1)="",0,IF('Model inputs'!B655="",0,1)),IF(IF('Model inputs'!B656="",0,1)="",0,IF('Model inputs'!B656="",0,1)),IF(IF('Model inputs'!B657="",0,1)="",0,IF('Model inputs'!B657="",0,1)),IF(IF('Model inputs'!B658="",0,1)="",0,IF('Model inputs'!B658="",0,1)))=0,"",SUM('Model inputs'!B654,'Model inputs'!B655,'Model inputs'!B656,'Model inputs'!B657,'Model inputs'!B658)) -> 21696.25 | G12: =IF(SUM(IF(IF('Model inputs'!B659="",0,1)="",0,IF('Model inputs'!B659="",0,1)),IF(IF('Model inputs'!B660="",0,1)="",0,IF('Model inputs'!B660="",0,1)),IF(IF('Model inputs'!B661="",0,1)="",0,IF('Model inputs'!B661="",0,1)),IF(IF('Model inputs'!B662="",0,1)="",0,IF('Model inputs'!B662="",0,1)),IF(IF('Model inputs'!B663="",0,1)="",0,IF('Model inputs'!B663="",0,1)))=0,"",SUM('Model inputs'!B659,'Model inputs'!B660,'Model inputs'!B661,'Model inputs'!B662,'Model inputs'!B663)) -> 26035.5 | H12: =IF(SUM(IF(IF('Model inputs'!B664="",0,1)="",0,IF('Model inputs'!B664="",0,1)),IF(IF('Model inputs'!B665="",0,1)="",0,IF('Model inputs'!B665="",0,1)),IF(IF('Model inputs'!B666="",0,1)="",0,IF('Model inputs'!B666="",0,1)),IF(IF('Model inputs'!B667="",0,1)="",0,IF('Model inputs'!B667="",0,1)),IF(IF('Model inputs'!B668="",0,1)="",0,IF('Model inputs'!B668="",0,1)))=0,"",SUM('Model inputs'!B664,'Model inputs'!B665,'Model inputs'!B666,'Model inputs'!B667,'Model inputs'!B668)) -> 30374.75 | I12: =IF(SUM(IF(IF('Model inputs'!B669="",0,1)="",0,IF('Model inputs'!B669="",0,1)),IF(IF('Model inputs'!B670="",0,1)="",0,IF('Model inputs'!B670="",0,1)),IF(IF('Model inputs'!B671="",0,1)="",0,IF('Model inputs'!B671="",0,1)),IF(IF('Model inputs'!B672="",0,1)="",0,IF('Model inputs'!B672="",0,1)),IF(IF('Model inputs'!B673="",0,1)="",0,IF('Model inputs'!B673="",0,1)))=0,"",SUM('Model inputs'!B669,'Model inputs'!B670,'Model inputs'!B671,'Model inputs'!B672,'Model inputs'!B673)) -> 34714 | J12: =IF(SUM(IF(IF('Model inputs'!B674="",0,1)="",0,IF('Model inputs'!B674="",0,1)),IF(IF('Model inputs'!B675="",0,1)="",0,IF('Model inputs'!B675="",0,1)),IF(IF('Model inputs'!B676="",0,1)="",0,IF('Model inputs'!B676="",0,1)),IF(IF('Model inputs'!B677="",0,1)="",0,IF('Model inputs'!B677="",0,1)),IF(IF('Model inputs'!B678="",0,1)="",0,IF('Model inputs'!B678="",0,1)))=0,"",SUM('Model inputs'!B674,'Model inputs'!B675,'Model inputs'!B676,'Model inputs'!B677,'Model inputs'!B678)) -> 39053.25 | K12: =IF(SUM(IF(IF('Model inputs'!B679="",0,1)="",0,IF('Model inputs'!B679="",0,1)),IF(IF('Model inputs'!B680="",0,1)="",0,IF('Model inputs'!B680="",0,1)),IF(IF('Model inputs'!B681="",0,1)="",0,IF('Model inputs'!B681="",0,1)),IF(IF('Model inputs'!B682="",0,1)="",0,IF('Model inputs'!B682="",0,1)),IF(IF('Model inputs'!B683="",0,1)="",0,IF('Model inputs'!B683="",0,1)))=0,"",SUM('Model inputs'!B679,'Model inputs'!B680,'Model inputs'!B681,'Model inputs'!B682,'Model inputs'!B683)) -> 43392.5 | L12: =IF(SUM(IF(IF('Model inputs'!B684="",0,1)="",0,IF('Model inputs'!B684="",0,1)),IF(IF('Model inputs'!B685="",0,1)="",0,IF('Model inputs'!B685="",0,1)),IF(IF('Model inputs'!B686="",0,1)="",0,IF('Model inputs'!B686="",0,1)),IF(IF('Model inputs'!B687="",0,1)="",0,IF('Model inputs'!B687="",0,1)),IF(IF('Model inputs'!B688="",0,1)="",0,IF('Model inputs'!B688="",0,1)))=0,"",SUM('Model inputs'!B684,'Model inputs'!B685,'Model inputs'!B686,'Model inputs'!B687,'Model inputs'!B688)) -> 47731.75 | M12: =IF(SUM(IF(IF('Model inputs'!B689="",0,1)="",0,IF('Model inputs'!B689="",0,1)),IF(IF('Model inputs'!B690="",0,1)="",0,IF('Model inputs'!B690="",0,1)),IF(IF('Model inputs'!B691="",0,1)="",0,IF('Model inputs'!B691="",0,1)),IF(IF('Model inputs'!B692="",0,1)="",0,IF('Model inputs'!B692="",0,1)),IF(IF('Model inputs'!B693="",0,1)="",0,IF('Model inputs'!B693="",0,1)))=0,"",SUM('Model inputs'!B689,'Model inputs'!B690,'Model inputs'!B691,'Model inputs'!B692,'Model inputs'!B693)) -> 52071
A13: Plan Contribution margin by pricing | B13: =IF(SUM(IF(IF('Model inputs'!B694="",0,1)="",0,IF('Model inputs'!B694="",0,1)),IF(IF('Model inputs'!B695="",0,1)="",0,IF('Model inputs'!B695="",0,1)),IF(IF('Model inputs'!B696="",0,1)="",0,IF('Model inputs'!B696="",0,1)),IF(IF('Model inputs'!B697="",0,1)="",0,IF('Model inputs'!B697="",0,1)),IF(IF('Model inputs'!B698="",0,1)="",0,IF('Model inputs'!B698="",0,1)))=0,"",SUM('Model inputs'!B694,'Model inputs'!B695,'Model inputs'!B696,'Model inputs'!B697,'Model inputs'!B698)) -> 0.86785 | C13: =IF(SUM(IF(IF('Model inputs'!B699="",0,1)="",0,IF('Model inputs'!B699="",0,1)),IF(IF('Model inputs'!B700="",0,1)="",0,IF('Model inputs'!B700="",0,1)),IF(IF('Model inputs'!B701="",0,1)="",0,IF('Model inputs'!B701="",0,1)),IF(IF('Model inputs'!B702="",0,1)="",0,IF('Model inputs'!B702="",0,1)),IF(IF('Model inputs'!B703="",0,1)="",0,IF('Model inputs'!B703="",0,1)))=0,"",SUM('Model inputs'!B699,'Model inputs'!B700,'Model inputs'!B701,'Model inputs'!B702,'Model inputs'!B703)) -> 0.86785 | D13: =IF(SUM(IF(IF('Model inputs'!B704="",0,1)="",0,IF('Model inputs'!B704="",0,1)),IF(IF('Model inputs'!B705="",0,1)="",0,IF('Model inputs'!B705="",0,1)),IF(IF('Model inputs'!B706="",0,1)="",0,IF('Model inputs'!B706="",0,1)),IF(IF('Model inputs'!B707="",0,1)="",0,IF('Model inputs'!B707="",0,1)),IF(IF('Model inputs'!B708="",0,1)="",0,IF('Model inputs'!B708="",0,1)))=0,"",SUM('Model inputs'!B704,'Model inputs'!B705,'Model inputs'!B706,'Model inputs'!B707,'Model inputs'!B708)) -> 0.86785 | E13: =IF(SUM(IF(IF('Model inputs'!B709="",0,1)="",0,IF('Model inputs'!B709="",0,1)),IF(IF('Model inputs'!B710="",0,1)="",0,IF('Model inputs'!B710="",0,1)),IF(IF('Model inputs'!B711="",0,1)="",0,IF('Model inputs'!B711="",0,1)),IF(IF('Model inputs'!B712="",0,1)="",0,IF('Model inputs'!B712="",0,1)),IF(IF('Model inputs'!B713="",0,1)="",0,IF('Model inputs'!B713="",0,1)))=0,"",SUM('Model inputs'!B709,'Model inputs'!B710,'Model inputs'!B711,'Model inputs'!B712,'Model inputs'!B713)) -> 0.86785 | F13: =IF(SUM(IF(IF('Model inputs'!B714="",0,1)="",0,IF('Model inputs'!B714="",0,1)),IF(IF('Model inputs'!B715="",0,1)="",0,IF('Model inputs'!B715="",0,1)),IF(IF('Model inputs'!B716="",0,1)="",0,IF('Model inputs'!B716="",0,1)),IF(IF('Model inputs'!B717="",0,1)="",0,IF('Model inputs'!B717="",0,1)),IF(IF('Model inputs'!B718="",0,1)="",0,IF('Model inputs'!B718="",0,1)))=0,"",SUM('Model inputs'!B714,'Model inputs'!B715,'Model inputs'!B716,'Model inputs'!B717,'Model inputs'!B718)) -> 0.86785 | G13: =IF(SUM(IF(IF('Model inputs'!B719="",0,1)="",0,IF('Model inputs'!B719="",0,1)),IF(IF('Model inputs'!B720="",0,1)="",0,IF('Model inputs'!B720="",0,1)),IF(IF('Model inputs'!B721="",0,1)="",0,IF('Model inputs'!B721="",0,1)),IF(IF('Model inputs'!B722="",0,1)="",0,IF('Model inputs'!B722="",0,1)),IF(IF('Model inputs'!B723="",0,1)="",0,IF('Model inputs'!B723="",0,1)))=0,"",SUM('Model inputs'!B719,'Model inputs'!B720,'Model inputs'!B721,'Model inputs'!B722,'Model inputs'!B723)) -> 0.86785 | H13: =IF(SUM(IF(IF('Model inputs'!B724="",0,1)="",0,IF('Model inputs'!B724="",0,1)),IF(IF('Model inputs'!B725="",0,1)="",0,IF('Model inputs'!B725="",0,1)),IF(IF('Model inputs'!B726="",0,1)="",0,IF('Model inputs'!B726="",0,1)),IF(IF('Model inputs'!B727="",0,1)="",0,IF('Model inputs'!B727="",0,1)),IF(IF('Model inputs'!B728="",0,1)="",0,IF('Model inputs'!B728="",0,1)))=0,"",SUM('Model inputs'!B724,'Model inputs'!B725,'Model inputs'!B726,'Model inputs'!B727,'Model inputs'!B728)) -> 0.86785 | I13: =IF(SUM(IF(IF('Model inputs'!B729="",0,1)="",0,IF('Model inputs'!B729="",0,1)),IF(IF('Model inputs'!B730="",0,1)="",0,IF('Model inputs'!B730="",0,1)),IF(IF('Model inputs'!B731="",0,1)="",0,IF('Model inputs'!B731="",0,1)),IF(IF('Model inputs'!B732="",0,1)="",0,IF('Model inputs'!B732="",0,1)),IF(IF('Model inputs'!B733="",0,1)="",0,IF('Model inputs'!B733="",0,1)))=0,"",SUM('Model inputs'!B729,'Model inputs'!B730,'Model inputs'!B731,'Model inputs'!B732,'Model inputs'!B733)) -> 0.86785 | J13: =IF(SUM(IF(IF('Model inputs'!B734="",0,1)="",0,IF('Model inputs'!B734="",0,1)),IF(IF('Model inputs'!B735="",0,1)="",0,IF('Model inputs'!B735="",0,1)),IF(IF('Model inputs'!B736="",0,1)="",0,IF('Model inputs'!B736="",0,1)),IF(IF('Model inputs'!B737="",0,1)="",0,IF('Model inputs'!B737="",0,1)),IF(IF('Model inputs'!B738="",0,1)="",0,IF('Model inputs'!B738="",0,1)))=0,"",SUM('Model inputs'!B734,'Model inputs'!B735,'Model inputs'!B736,'Model inputs'!B737,'Model inputs'!B738)) -> 0.86785 | K13: =IF(SUM(IF(IF('Model inputs'!B739="",0,1)="",0,IF('Model inputs'!B739="",0,1)),IF(IF('Model inputs'!B740="",0,1)="",0,IF('Model inputs'!B740="",0,1)),IF(IF('Model inputs'!B741="",0,1)="",0,IF('Model inputs'!B741="",0,1)),IF(IF('Model inputs'!B742="",0,1)="",0,IF('Model inputs'!B742="",0,1)),IF(IF('Model inputs'!B743="",0,1)="",0,IF('Model inputs'!B743="",0,1)))=0,"",SUM('Model inputs'!B739,'Model inputs'!B740,'Model inputs'!B741,'Model inputs'!B742,'Model inputs'!B743)) -> 0.86785 | L13: =IF(SUM(IF(IF('Model inputs'!B744="",0,1)="",0,IF('Model inputs'!B744="",0,1)),IF(IF('Model inputs'!B745="",0,1)="",0,IF('Model inputs'!B745="",0,1)),IF(IF('Model inputs'!B746="",0,1)="",0,IF('Model inputs'!B746="",0,1)),IF(IF('Model inputs'!B747="",0,1)="",0,IF('Model inputs'!B747="",0,1)),IF(IF('Model inputs'!B748="",0,1)="",0,IF('Model inputs'!B748="",0,1)))=0,"",SUM('Model inputs'!B744,'Model inputs'!B745,'Model inputs'!B746,'Model inputs'!B747,'Model inputs'!B748)) -> 0.86785 | M13: =IF(SUM(IF(IF('Model inputs'!B749="",0,1)="",0,IF('Model inputs'!B749="",0,1)),IF(IF('Model inputs'!B750="",0,1)="",0,IF('Model inputs'!B750="",0,1)),IF(IF('Model inputs'!B751="",0,1)="",0,IF('Model inputs'!B751="",0,1)),IF(IF('Model inputs'!B752="",0,1)="",0,IF('Model inputs'!B752="",0,1)),IF(IF('Model inputs'!B753="",0,1)="",0,IF('Model inputs'!B753="",0,1)))=0,"",SUM('Model inputs'!B749,'Model inputs'!B750,'Model inputs'!B751,'Model inputs'!B752,'Model inputs'!B753)) -> 0.86785
A14: Fixed costs | B14: ='Model inputs'!O79+'Model inputs'!O112+'Model inputs'!O48+'Model inputs'!O66+'Model inputs'!O110+IF(IF(IF(IF(ISERROR('Model inputs'!C105>='Model inputs'!O31),'Model inputs'!C105>='Model inputs'!O31,IF(OR('Model inputs'!C105="",'Model inputs'!O31=""),"",'Model inputs'!C105>='Model inputs'!O31))="",FALSE,IF(ISERROR('Model inputs'!C105>='Model inputs'!O31),'Model inputs'!C105>='Model inputs'!O31,IF(OR('Model inputs'!C105="",'Model inputs'!O31=""),"",'Model inputs'!C105>='Model inputs'!O31))),IF('Model inputs'!O30="","",'Model inputs'!O30),0)="",0,IF(IF(IF(ISERROR('Model inputs'!C105>='Model inputs'!O31),'Model inputs'!C105>='Model inputs'!O31,IF(OR('Model inputs'!C105="",'Model inputs'!O31=""),"",'Model inputs'!C105>='Model inputs'!O31))="",FALSE,IF(ISERROR('Model inputs'!C105>='Model inputs'!O31),'Model inputs'!C105>='Model inputs'!O31,IF(OR('Model inputs'!C105="",'Model inputs'!O31=""),"",'Model inputs'!C105>='Model inputs'!O31))),IF('Model inputs'!O30="","",'Model inputs'!O30),0)) -> 750 | C14: ='Model inputs'!O79+'Model inputs'!O112+'Model inputs'!O48+'Model inputs'!O66+'Model inputs'!O110+IF(IF(IF(IF(ISERROR('Model inputs'!D105>='Model inputs'!O31),'Model inputs'!D105>='Model inputs'!O31,IF(OR('Model inputs'!D105="",'Model inputs'!O31=""),"",'Model inputs'!D105>='Model inputs'!O31))="",FALSE,IF(ISERROR('Model inputs'!D105>='Model inputs'!O31),'Model inputs'!D105>='Model inputs'!O31,IF(OR('Model inputs'!D105="",'Model inputs'!O31=""),"",'Model inputs'!D105>='Model inputs'!O31))),IF('Model inputs'!O30="","",'Model inputs'!O30),0)="",0,IF(IF(IF(ISERROR('Model inputs'!D105>='Model inputs'!O31),'Model inputs'!D105>='Model inputs'!O31,IF(OR('Model inputs'!D105="",'Model inputs'!O31=""),"",'Model inputs'!D105>='Model inputs'!O31))="",FALSE,IF(ISERROR('Model inputs'!D105>='Model inputs'!O31),'Model inputs'!D105>='Model inputs'!O31,IF(OR('Model inputs'!D105="",'Model inputs'!O31=""),"",'Model inputs'!D105>='Model inputs'!O31))),IF('Model inputs'!O30="","",'Model inputs'!O30),0)) -> 750 | D14: ='Model inputs'!O79+'Model inputs'!O112+'Model inputs'!O48+'Model inputs'!O66+'Model inputs'!O110+IF(IF(IF(IF(ISERROR('Model inputs'!E105>='Model inputs'!O31),'Model inputs'!E105>='Model inputs'!O31,IF(OR('Model inputs'!E105="",'Model inputs'!O31=""),"",'Model inputs'!E105>='Model inputs'!O31))="",FALSE,IF(ISERROR('Model inputs'!E105>='Model inputs'!O31),'Model inputs'!E105>='Model inputs'!O31,IF(OR('Model inputs'!E105="",'Model inputs'!O31=""),"",'Model inputs'!E105>='Model inputs'!O31))),IF('Model inputs'!O30="","",'Model inputs'!O30),0)="",0,IF(IF(IF(ISERROR('Model inputs'!E105>='Model inputs'!O31),'Model inputs'!E105>='Model inputs'!O31,IF(OR('Model inputs'!E105="",'Model inputs'!O31=""),"",'Model inputs'!E105>='Model inputs'!O31))="",FALSE,IF(ISERROR('Model inputs'!E105>='Model inputs'!O31),'Model inputs'!E105>='Model inputs'!O31,IF(OR('Model inputs'!E105="",'Model inputs'!O31=""),"",'Model inputs'!E105>='Model inputs'!O31))),IF('Model inputs'!O30="","",'Model inputs'!O30),0)) -> 750 | E14: ='Model inputs'!O79+'Model inputs'!O112+'Model inputs'!O48+'Model inputs'!O66+'Model inputs'!O110+IF(IF(IF(IF(ISERROR('Model inputs'!F105>='Model inputs'!O31),'Model inputs'!F105>='Model inputs'!O31,IF(OR('Model inputs'!F105="",'Model inputs'!O31=""),"",'Model inputs'!F105>='Model inputs'!O31))="",FALSE,IF(ISERROR('Model inputs'!F105>='Model inputs'!O31),'Model inputs'!F105>='Model inputs'!O31,IF(OR('Model inputs'!F105="",'Model inputs'!O31=""),"",'Model inputs'!F105>='Model inputs'!O31))),IF('Model inputs'!O30="","",'Model inputs'!O30),0)="",0,IF(IF(IF(ISERROR('Model inputs'!F105>='Model inputs'!O31),'Model inputs'!F105>='Model inputs'!O31,IF(OR('Model inputs'!F105="",'Model inputs'!O31=""),"",'Model inputs'!F105>='Model inputs'!O31))="",FALSE,IF(ISERROR('Model inputs'!F105>='Model inputs'!O31),'Model inputs'!F105>='Model inputs'!O31,IF(OR('Model inputs'!F105="",'Model inputs'!O31=""),"",'Model inputs'!F105>='Model inputs'!O31))),IF('Model inputs'!O30="","",'Model inputs'!O30),0)) -> 750 | F14: ='Model inputs'!O79+'Model inputs'!O112+'Model inputs'!O48+'Model inputs'!O66+'Model inputs'!O110+IF(IF(IF(IF(ISERROR('Model inputs'!G105>='Model inputs'!O31),'Model inputs'!G105>='Model inputs'!O31,IF(OR('Model inputs'!G105="",'Model inputs'!O31=""),"",'Model inputs'!G105>='Model inputs'!O31))="",FALSE,IF(ISERROR('Model inputs'!G105>='Model inputs'!O31),'Model inputs'!G105>='Model inputs'!O31,IF(OR('Model inputs'!G105="",'Model inputs'!O31=""),"",'Model inputs'!G105>='Model inputs'!O31))),IF('Model inputs'!O30="","",'Model inputs'!O30),0)="",0,IF(IF(IF(ISERROR('Model inputs'!G105>='Model inputs'!O31),'Model inputs'!G105>='Model inputs'!O31,IF(OR('Model inputs'!G105="",'Model inputs'!O31=""),"",'Model inputs'!G105>='Model inputs'!O31))="",FALSE,IF(ISERROR('Model inputs'!G105>='Model inputs'!O31),'Model inputs'!G105>='Model inputs'!O31,IF(OR('Model inputs'!G105="",'Model inputs'!O31=""),"",'Model inputs'!G105>='Model inputs'!O31))),IF('Model inputs'!O30="","",'Model inputs'!O30),0)) -> 750 | G14: ='Model inputs'!O79+'Model inputs'!O112+'Model inputs'!O48+'Model inputs'!O66+'Model inputs'!O110+IF(IF(IF(IF(ISERROR('Model inputs'!H105>='Model inputs'!O31),'Model inputs'!H105>='Model inputs'!O31,IF(OR('Model inputs'!H105="",'Model inputs'!O31=""),"",'Model inputs'!H105>='Model inputs'!O31))="",FALSE,IF(ISERROR('Model inputs'!H105>='Model inputs'!O31),'Model inputs'!H105>='Model inputs'!O31,IF(OR('Model inputs'!H105="",'Model inputs'!O31=""),"",'Model inputs'!H105>='Model inputs'!O31))),IF('Model inputs'!O30="","",'Model inputs'!O30),0)="",0,IF(IF(IF(ISERROR('Model inputs'!H105>='Model inputs'!O31),'Model inputs'!H105>='Model inputs'!O31,IF(OR('Model inputs'!H105="",'Model inputs'!O31=""),"",'Model inputs'!H105>='Model inputs'!O31))="",FALSE,IF(ISERROR('Model inputs'!H105>='Model inputs'!O31),'Model inputs'!H105>='Model inputs'!O31,IF(OR('Model inputs'!H105="",'Model inputs'!O31=""),"",'Model inputs'!H105>='Model inputs'!O31))),IF('Model inputs'!O30="","",'Model inputs'!O30),0)) -> 1250 | H14: ='Model inputs'!O79+'Model inputs'!O112+'Model inputs'!O48+'Model inputs'!O66+'Model inputs'!O110+IF(IF(IF(IF(ISERROR('Model inputs'!I105>='Model inputs'!O31),'Model inputs'!I105>='Model inputs'!O31,IF(OR('Model inputs'!I105="",'Model inputs'!O31=""),"",'Model inputs'!I105>='Model inputs'!O31))="",FALSE,IF(ISERROR('Model inputs'!I105>='Model inputs'!O31),'Model inputs'!I105>='Model inputs'!O31,IF(OR('Model inputs'!I105="",'Model inputs'!O31=""),"",'Model inputs'!I105>='Model inputs'!O31))),IF('Model inputs'!O30="","",'Model inputs'!O30),0)="",0,IF(IF(IF(ISERROR('Model inputs'!I105>='Model inputs'!O31),'Model inputs'!I105>='Model inputs'!O31,IF(OR('Model inputs'!I105="",'Model inputs'!O31=""),"",'Model inputs'!I105>='Model inputs'!O31))="",FALSE,IF(ISERROR('Model inputs'!I105>='Model inputs'!O31),'Model inputs'!I105>='Model inputs'!O31,IF(OR('Model inputs'!I105="",'Model inputs'!O31=""),"",'Model inputs'!I105>='Model inputs'!O31))),IF('Model inputs'!O30="","",'Model inputs'!O30),0)) -> 1250 | I14: ='Model inputs'!O79+'Model inputs'!O112+'Model inputs'!O48+'Model inputs'!O66+'Model inputs'!O110+IF(IF(IF(IF(ISERROR('Model inputs'!J105>='Model inputs'!O31),'Model inputs'!J105>='Model inputs'!O31,IF(OR('Model inputs'!J105="",'Model inputs'!O31=""),"",'Model inputs'!J105>='Model inputs'!O31))="",FALSE,IF(ISERROR('Model inputs'!J105>='Model inputs'!O31),'Model inputs'!J105>='Model inputs'!O31,IF(OR('Model inputs'!J105="",'Model inputs'!O31=""),"",'Model inputs'!J105>='Model inputs'!O31))),IF('Model inputs'!O30="","",'Model inputs'!O30),0)="",0,IF(IF(IF(ISERROR('Model inputs'!J105>='Model inputs'!O31),'Model inputs'!J105>='Model inputs'!O31,IF(OR('Model inputs'!J105="",'Model inputs'!O31=""),"",'Model inputs'!J105>='Model inputs'!O31))="",FALSE,IF(ISERROR('Model inputs'!J105>='Model inputs'!O31),'Model inputs'!J105>='Model inputs'!O31,IF(OR('Model inputs'!J105="",'Model inputs'!O31=""),"",'Model inputs'!J105>='Model inputs'!O31))),IF('Model inputs'!O30="","",'Model inputs'!O30),0)) -> 1250 | J14: ='Model inputs'!O79+'Model inputs'!O112+'Model inputs'!O48+'Model inputs'!O66+'Model inputs'!O110+IF(IF(IF(IF(ISERROR('Model inputs'!K105>='Model inputs'!O31),'Model inputs'!K105>='Model inputs'!O31,IF(OR('Model inputs'!K105="",'Model inputs'!O31=""),"",'Model inputs'!K105>='Model inputs'!O31))="",FALSE,IF(ISERROR('Model inputs'!K105>='Model inputs'!O31),'Model inputs'!K105>='Model inputs'!O31,IF(OR('Model inputs'!K105="",'Model inputs'!O31=""),"",'Model inputs'!K105>='Model inputs'!O31))),IF('Model inputs'!O30="","",'Model inputs'!O30),0)="",0,IF(IF(IF(ISERROR('Model inputs'!K105>='Model inputs'!O31),'Model inputs'!K105>='Model inputs'!O31,IF(OR('Model inputs'!K105="",'Model inputs'!O31=""),"",'Model inputs'!K105>='Model inputs'!O31))="",FALSE,IF(ISERROR('Model inputs'!K105>='Model inputs'!O31),'Model inputs'!K105>='Model inputs'!O31,IF(OR('Model inputs'!K105="",'Model inputs'!O31=""),"",'Model inputs'!K105>='Model inputs'!O31))),IF('Model inputs'!O30="","",'Model inputs'!O30),0)) -> 1250 | K14: ='Model inputs'!O79+'Model inputs'!O112+'Model inputs'!O48+'Model inputs'!O66+'Model inputs'!O110+IF(IF(IF(IF(ISERROR('Model inputs'!L105>='Model inputs'!O31),'Model inputs'!L105>='Model inputs'!O31,IF(OR('Model inputs'!L105="",'Model inputs'!O31=""),"",'Model inputs'!L105>='Model inputs'!O31))="",FALSE,IF(ISERROR('Model inputs'!L105>='Model inputs'!O31),'Model inputs'!L105>='Model inputs'!O31,IF(OR('Model inputs'!L105="",'Model inputs'!O31=""),"",'Model inputs'!L105>='Model inputs'!O31))),IF('Model inputs'!O30="","",'Model inputs'!O30),0)="",0,IF(IF(IF(ISERROR('Model inputs'!L105>='Model inputs'!O31),'Model inputs'!L105>='Model inputs'!O31,IF(OR('Model inputs'!L105="",'Model inputs'!O31=""),"",'Model inputs'!L105>='Model inputs'!O31))="",FALSE,IF(ISERROR('Model inputs'!L105>='Model inputs'!O31),'Model inputs'!L105>='Model inputs'!O31,IF(OR('Model inputs'!L105="",'Model inputs'!O31=""),"",'Model inputs'!L105>='Model inputs'!O31))),IF('Model inputs'!O30="","",'Model inputs'!O30),0)) -> 1250 | L14: ='Model inputs'!O79+'Model inputs'!O112+'Model inputs'!O48+'Model inputs'!O66+'Model inputs'!O110+IF(IF(IF(IF(ISERROR('Model inputs'!M105>='Model inputs'!O31),'Model inputs'!M105>='Model inputs'!O31,IF(OR('Model inputs'!M105="",'Model inputs'!O31=""),"",'Model inputs'!M105>='Model inputs'!O31))="",FALSE,IF(ISERROR('Model inputs'!M105>='Model inputs'!O31),'Model inputs'!M105>='Model inputs'!O31,IF(OR('Model inputs'!M105="",'Model inputs'!O31=""),"",'Model inputs'!M105>='Model inputs'!O31))),IF('Model inputs'!O30="","",'Model inputs'!O30),0)="",0,IF(IF(IF(ISERROR('Model inputs'!M105>='Model inputs'!O31),'Model inputs'!M105>='Model inputs'!O31,IF(OR('Model inputs'!M105="",'Model inputs'!O31=""),"",'Model inputs'!M105>='Model inputs'!O31))="",FALSE,IF(ISERROR('Model inputs'!M105>='Model inputs'!O31),'Model inputs'!M105>='Model inputs'!O31,IF(OR('Model inputs'!M105="",'Model inputs'!O31=""),"",'Model inputs'!M105>='Model inputs'!O31))),IF('Model inputs'!O30="","",'Model inputs'!O30),0)) -> 1250 | M14: ='Model inputs'!O79+'Model inputs'!O112+'Model inputs'!O48+'Model inputs'!O66+'Model inputs'!O110+IF(IF(IF(IF(ISERROR('Model inputs'!N105>='Model inputs'!O31),'Model inputs'!N105>='Model inputs'!O31,IF(OR('Model inputs'!N105="",'Model inputs'!O31=""),"",'Model inputs'!N105>='Model inputs'!O31))="",FALSE,IF(ISERROR('Model inputs'!N105>='Model inputs'!O31),'Model inputs'!N105>='Model inputs'!O31,IF(OR('Model inputs'!N105="",'Model inputs'!O31=""),"",'Model inputs'!N105>='Model inputs'!O31))),IF('Model inputs'!O30="","",'Model inputs'!O30),0)="",0,IF(IF(IF(ISERROR('Model inputs'!N105>='Model inputs'!O31),'Model inputs'!N105>='Model inputs'!O31,IF(OR('Model inputs'!N105="",'Model inputs'!O31=""),"",'Model inputs'!N105>='Model inputs'!O31))="",FALSE,IF(ISERROR('Model inputs'!N105>='Model inputs'!O31),'Model inputs'!N105>='Model inputs'!O31,IF(OR('Model inputs'!N105="",'Model inputs'!O31=""),"",'Model inputs'!N105>='Model inputs'!O31))),IF('Model inputs'!O30="","",'Model inputs'!O30),0)) -> 1250
A15: Monthly operating burn | B15: =-'Model inputs'!C104 -> -3589.25 | C15: =-'Model inputs'!D104 -> -7928.5 | D15: =-'Model inputs'!E104 -> -12267.75 | E15: =-'Model inputs'!F104 -> -16607 | F15: =-'Model inputs'!G104 -> -20946.25 | G15: =-'Model inputs'!H104 -> -24785.5 | H15: =-'Model inputs'!I104 -> -29124.75 | I15: =-'Model inputs'!J104 -> -33464 | ... M15: =-'Model inputs'!N104 -> -50821
A16: Plan Cash collections | B16: =IF(SUM(IF(IF('Model inputs'!B754="",0,1)="",0,IF('Model inputs'!B754="",0,1)),IF(IF('Model inputs'!B755="",0,1)="",0,IF('Model inputs'!B755="",0,1)),IF(IF('Model inputs'!B756="",0,1)="",0,IF('Model inputs'!B756="",0,1)),IF(IF('Model inputs'!B757="",0,1)="",0,IF('Model inputs'!B757="",0,1)),IF(IF('Model inputs'!B758="",0,1)="",0,IF('Model inputs'!B758="",0,1)))=0,"",SUM('Model inputs'!B754,'Model inputs'!B755,'Model inputs'!B756,'Model inputs'!B757,'Model inputs'!B758)) -> 32500 | C16: =IF(SUM(IF(IF('Model inputs'!B759="",0,1)="",0,IF('Model inputs'!B759="",0,1)),IF(IF('Model inputs'!B760="",0,1)="",0,IF('Model inputs'!B760="",0,1)),IF(IF('Model inputs'!B761="",0,1)="",0,IF('Model inputs'!B761="",0,1)),IF(IF('Model inputs'!B762="",0,1)="",0,IF('Model inputs'!B762="",0,1)),IF(IF('Model inputs'!B763="",0,1)="",0,IF('Model inputs'!B763="",0,1)))=0,"",SUM('Model inputs'!B759,'Model inputs'!B760,'Model inputs'!B761,'Model inputs'!B762,'Model inputs'!B763)) -> 35000 | D16: =IF(SUM(IF(IF('Model inputs'!B764="",0,1)="",0,IF('Model inputs'!B764="",0,1)),IF(IF('Model inputs'!B765="",0,1)="",0,IF('Model inputs'!B765="",0,1)),IF(IF('Model inputs'!B766="",0,1)="",0,IF('Model inputs'!B766="",0,1)),IF(IF('Model inputs'!B767="",0,1)="",0,IF('Model inputs'!B767="",0,1)),IF(IF('Model inputs'!B768="",0,1)="",0,IF('Model inputs'!B768="",0,1)))=0,"",SUM('Model inputs'!B764,'Model inputs'!B765,'Model inputs'!B766,'Model inputs'!B767,'Model inputs'!B768)) -> 37500 | E16: =IF(SUM(IF(IF('Model inputs'!B769="",0,1)="",0,IF('Model inputs'!B769="",0,1)),IF(IF('Model inputs'!B770="",0,1)="",0,IF('Model inputs'!B770="",0,1)),IF(IF('Model inputs'!B771="",0,1)="",0,IF('Model inputs'!B771="",0,1)),IF(IF('Model inputs'!B772="",0,1)="",0,IF('Model inputs'!B772="",0,1)),IF(IF('Model inputs'!B773="",0,1)="",0,IF('Model inputs'!B773="",0,1)))=0,"",SUM('Model inputs'!B769,'Model inputs'!B770,'Model inputs'!B771,'Model inputs'!B772,'Model inputs'!B773)) -> 40000 | F16: =IF(SUM(IF(IF('Model inputs'!B774="",0,1)="",0,IF('Model inputs'!B774="",0,1)),IF(IF('Model inputs'!B775="",0,1)="",0,IF('Model inputs'!B775="",0,1)),IF(IF('Model inputs'!B776="",0,1)="",0,IF('Model inputs'!B776="",0,1)),IF(IF('Model inputs'!B777="",0,1)="",0,IF('Model inputs'!B777="",0,1)),IF(IF('Model inputs'!B778="",0,1)="",0,IF('Model inputs'!B778="",0,1)))=0,"",SUM('Model inputs'!B774,'Model inputs'!B775,'Model inputs'!B776,'Model inputs'!B777,'Model inputs'!B778)) -> 42500 | G16: =IF(SUM(IF(IF('Model inputs'!B779="",0,1)="",0,IF('Model inputs'!B779="",0,1)),IF(IF('Model inputs'!B780="",0,1)="",0,IF('Model inputs'!B780="",0,1)),IF(IF('Model inputs'!B781="",0,1)="",0,IF('Model inputs'!B781="",0,1)),IF(IF('Model inputs'!B782="",0,1)="",0,IF('Model inputs'!B782="",0,1)),IF(IF('Model inputs'!B783="",0,1)="",0,IF('Model inputs'!B783="",0,1)))=0,"",SUM('Model inputs'!B779,'Model inputs'!B780,'Model inputs'!B781,'Model inputs'!B782,'Model inputs'!B783)) -> 45000 | H16: =IF(SUM(IF(IF('Model inputs'!B784="",0,1)="",0,IF('Model inputs'!B784="",0,1)),IF(IF('Model inputs'!B785="",0,1)="",0,IF('Model inputs'!B785="",0,1)),IF(IF('Model inputs'!B786="",0,1)="",0,IF('Model inputs'!B786="",0,1)),IF(IF('Model inputs'!B787="",0,1)="",0,IF('Model inputs'!B787="",0,1)),IF(IF('Model inputs'!B788="",0,1)="",0,IF('Model inputs'!B788="",0,1)))=0,"",SUM('Model inputs'!B784,'Model inputs'!B785,'Model inputs'!B786,'Model inputs'!B787,'Model inputs'!B788)) -> 47500 | I16: =IF(SUM(IF(IF('Model inputs'!B789="",0,1)="",0,IF('Model inputs'!B789="",0,1)),IF(IF('Model inputs'!B790="",0,1)="",0,IF('Model inputs'!B790="",0,1)),IF(IF('Model inputs'!B791="",0,1)="",0,IF('Model inputs'!B791="",0,1)),IF(IF('Model inputs'!B792="",0,1)="",0,IF('Model inputs'!B792="",0,1)),IF(IF('Model inputs'!B793="",0,1)="",0,IF('Model inputs'!B793="",0,1)))=0,"",SUM('Model inputs'!B789,'Model inputs'!B790,'Model inputs'!B791,'Model inputs'!B792,'Model inputs'!B793)) -> 50000 | J16: =IF(SUM(IF(IF('Model inputs'!B794="",0,1)="",0,IF('Model inputs'!B794="",0,1)),IF(IF('Model inputs'!B795="",0,1)="",0,IF('Model inputs'!B795="",0,1)),IF(IF('Model inputs'!B796="",0,1)="",0,IF('Model inputs'!B796="",0,1)),IF(IF('Model inputs'!B797="",0,1)="",0,IF('Model inputs'!B797="",0,1)),IF(IF('Model inputs'!B798="",0,1)="",0,IF('Model inputs'!B798="",0,1)))=0,"",SUM('Model inputs'!B794,'Model inputs'!B795,'Model inputs'!B796,'Model inputs'!B797,'Model inputs'!B798)) -> 52500 | K16: =IF(SUM(IF(IF('Model inputs'!B799="",0,1)="",0,IF('Model inputs'!B799="",0,1)),IF(IF('Model inputs'!B800="",0,1)="",0,IF('Model inputs'!B800="",0,1)),IF(IF('Model inputs'!B801="",0,1)="",0,IF('Model inputs'!B801="",0,1)),IF(IF('Model inputs'!B802="",0,1)="",0,IF('Model inputs'!B802="",0,1)),IF(IF('Model inputs'!B803="",0,1)="",0,IF('Model inputs'!B803="",0,1)))=0,"",SUM('Model inputs'!B799,'Model inputs'!B800,'Model inputs'!B801,'Model inputs'!B802,'Model inputs'!B803)) -> 55000 | L16: =IF(SUM(IF(IF('Model inputs'!B804="",0,1)="",0,IF('Model inputs'!B804="",0,1)),IF(IF('Model inputs'!B805="",0,1)="",0,IF('Model inputs'!B805="",0,1)),IF(IF('Model inputs'!B806="",0,1)="",0,IF('Model inputs'!B806="",0,1)),IF(IF('Model inputs'!B807="",0,1)="",0,IF('Model inputs'!B807="",0,1)),IF(IF('Model inputs'!B808="",0,1)="",0,IF('Model inputs'!B808="",0,1)))=0,"",SUM('Model inputs'!B804,'Model inputs'!B805,'Model inputs'!B806,'Model inputs'!B807,'Model inputs'!B808)) -> 57500 | M16: =IF(SUM(IF(IF('Model inputs'!B809="",0,1)="",0,IF('Model inputs'!B809="",0,1)),IF(IF('Model inputs'!B810="",0,1)="",0,IF('Model inputs'!B810="",0,1)),IF(IF('Model inputs'!B811="",0,1)="",0,IF('Model inputs'!B811="",0,1)),IF(IF('Model inputs'!B812="",0,1)="",0,IF('Model inputs'!B812="",0,1)),IF(IF('Model inputs'!B813="",0,1)="",0,IF('Model inputs'!B813="",0,1)))=0,"",SUM('Model inputs'!B809,'Model inputs'!B810,'Model inputs'!B811,'Model inputs'!B812,'Model inputs'!B813)) -> 60000
A17: Plan Payment fees | B17: =IF(SUM(IF(IF('Model inputs'!B814="",0,1)="",0,IF('Model inputs'!B814="",0,1)),IF(IF('Model inputs'!B815="",0,1)="",0,IF('Model inputs'!B815="",0,1)),IF(IF('Model inputs'!B816="",0,1)="",0,IF('Model inputs'!B816="",0,1)),IF(IF('Model inputs'!B817="",0,1)="",0,IF('Model inputs'!B817="",0,1)),IF(IF('Model inputs'!B818="",0,1)="",0,IF('Model inputs'!B818="",0,1)))=0,"",SUM('Model inputs'!B814,'Model inputs'!B815,'Model inputs'!B816,'Model inputs'!B817,'Model inputs'!B818)) -> 975 | C17: =IF(SUM(IF(IF('Model inputs'!B819="",0,1)="",0,IF('Model inputs'!B819="",0,1)),IF(IF('Model inputs'!B820="",0,1)="",0,IF('Model inputs'!B820="",0,1)),IF(IF('Model inputs'!B821="",0,1)="",0,IF('Model inputs'!B821="",0,1)),IF(IF('Model inputs'!B822="",0,1)="",0,IF('Model inputs'!B822="",0,1)),IF(IF('Model inputs'!B823="",0,1)="",0,IF('Model inputs'!B823="",0,1)))=0,"",SUM('Model inputs'!B819,'Model inputs'!B820,'Model inputs'!B821,'Model inputs'!B822,'Model inputs'!B823)) -> 1050 | D17: =IF(SUM(IF(IF('Model inputs'!B824="",0,1)="",0,IF('Model inputs'!B824="",0,1)),IF(IF('Model inputs'!B825="",0,1)="",0,IF('Model inputs'!B825="",0,1)),IF(IF('Model inputs'!B826="",0,1)="",0,IF('Model inputs'!B826="",0,1)),IF(IF('Model inputs'!B827="",0,1)="",0,IF('Model inputs'!B827="",0,1)),IF(IF('Model inputs'!B828="",0,1)="",0,IF('Model inputs'!B828="",0,1)))=0,"",SUM('Model inputs'!B824,'Model inputs'!B825,'Model inputs'!B826,'Model inputs'!B827,'Model inputs'!B828)) -> 1125 | E17: =IF(SUM(IF(IF('Model inputs'!B829="",0,1)="",0,IF('Model inputs'!B829="",0,1)),IF(IF('Model inputs'!B830="",0,1)="",0,IF('Model inputs'!B830="",0,1)),IF(IF('Model inputs'!B831="",0,1)="",0,IF('Model inputs'!B831="",0,1)),IF(IF('Model inputs'!B832="",0,1)="",0,IF('Model inputs'!B832="",0,1)),IF(IF('Model inputs'!B833="",0,1)="",0,IF('Model inputs'!B833="",0,1)))=0,"",SUM('Model inputs'!B829,'Model inputs'!B830,'Model inputs'!B831,'Model inputs'!B832,'Model inputs'!B833)) -> 1200 | F17: =IF(SUM(IF(IF('Model inputs'!B834="",0,1)="",0,IF('Model inputs'!B834="",0,1)),IF(IF('Model inputs'!B835="",0,1)="",0,IF('Model inputs'!B835="",0,1)),IF(IF('Model inputs'!B836="",0,1)="",0,IF('Model inputs'!B836="",0,1)),IF(IF('Model inputs'!B837="",0,1)="",0,IF('Model inputs'!B837="",0,1)),IF(IF('Model inputs'!B838="",0,1)="",0,IF('Model inputs'!B838="",0,1)))=0,"",SUM('Model inputs'!B834,'Model inputs'!B835,'Model inputs'!B836,'Model inputs'!B837,'Model inputs'!B838)) -> 1275 | G17: =IF(SUM(IF(IF('Model inputs'!B839="",0,1)="",0,IF('Model inputs'!B839="",0,1)),IF(IF('Model inputs'!B840="",0,1)="",0,IF('Model inputs'!B840="",0,1)),IF(IF('Model inputs'!B841="",0,1)="",0,IF('Model inputs'!B841="",0,1)),IF(IF('Model inputs'!B842="",0,1)="",0,IF('Model inputs'!B842="",0,1)),IF(IF('Model inputs'!B843="",0,1)="",0,IF('Model inputs'!B843="",0,1)))=0,"",SUM('Model inputs'!B839,'Model inputs'!B840,'Model inputs'!B841,'Model inputs'!B842,'Model inputs'!B843)) -> 1350 | H17: =IF(SUM(IF(IF('Model inputs'!B844="",0,1)="",0,IF('Model inputs'!B844="",0,1)),IF(IF('Model inputs'!B845="",0,1)="",0,IF('Model inputs'!B845="",0,1)),IF(IF('Model inputs'!B846="",0,1)="",0,IF('Model inputs'!B846="",0,1)),IF(IF('Model inputs'!B847="",0,1)="",0,IF('Model inputs'!B847="",0,1)),IF(IF('Model inputs'!B848="",0,1)="",0,IF('Model inputs'!B848="",0,1)))=0,"",SUM('Model inputs'!B844,'Model inputs'!B845,'Model inputs'!B846,'Model inputs'!B847,'Model inputs'!B848)) -> 1425 | I17: =IF(SUM(IF(IF('Model inputs'!B849="",0,1)="",0,IF('Model inputs'!B849="",0,1)),IF(IF('Model inputs'!B850="",0,1)="",0,IF('Model inputs'!B850="",0,1)),IF(IF('Model inputs'!B851="",0,1)="",0,IF('Model inputs'!B851="",0,1)),IF(IF('Model inputs'!B852="",0,1)="",0,IF('Model inputs'!B852="",0,1)),IF(IF('Model inputs'!B853="",0,1)="",0,IF('Model inputs'!B853="",0,1)))=0,"",SUM('Model inputs'!B849,'Model inputs'!B850,'Model inputs'!B851,'Model inputs'!B852,'Model inputs'!B853)) -> 1500 | J17: =IF(SUM(IF(IF('Model inputs'!B854="",0,1)="",0,IF('Model inputs'!B854="",0,1)),IF(IF('Model inputs'!B855="",0,1)="",0,IF('Model inputs'!B855="",0,1)),IF(IF('Model inputs'!B856="",0,1)="",0,IF('Model inputs'!B856="",0,1)),IF(IF('Model inputs'!B857="",0,1)="",0,IF('Model inputs'!B857="",0,1)),IF(IF('Model inputs'!B858="",0,1)="",0,IF('Model inputs'!B858="",0,1)))=0,"",SUM('Model inputs'!B854,'Model inputs'!B855,'Model inputs'!B856,'Model inputs'!B857,'Model inputs'!B858)) -> 1575 | K17: =IF(SUM(IF(IF('Model inputs'!B859="",0,1)="",0,IF('Model inputs'!B859="",0,1)),IF(IF('Model inputs'!B860="",0,1)="",0,IF('Model inputs'!B860="",0,1)),IF(IF('Model inputs'!B861="",0,1)="",0,IF('Model inputs'!B861="",0,1)),IF(IF('Model inputs'!B862="",0,1)="",0,IF('Model inputs'!B862="",0,1)),IF(IF('Model inputs'!B863="",0,1)="",0,IF('Model inputs'!B863="",0,1)))=0,"",SUM('Model inputs'!B859,'Model inputs'!B860,'Model inputs'!B861,'Model inputs'!B862,'Model inputs'!B863)) -> 1650 | L17: =IF(SUM(IF(IF('Model inputs'!B864="",0,1)="",0,IF('Model inputs'!B864="",0,1)),IF(IF('Model inputs'!B865="",0,1)="",0,IF('Model inputs'!B865="",0,1)),IF(IF('Model inputs'!B866="",0,1)="",0,IF('Model inputs'!B866="",0,1)),IF(IF('Model inputs'!B867="",0,1)="",0,IF('Model inputs'!B867="",0,1)),IF(IF('Model inputs'!B868="",0,1)="",0,IF('Model inputs'!B868="",0,1)))=0,"",SUM('Model inputs'!B864,'Model inputs'!B865,'Model inputs'!B866,'Model inputs'!B867,'Model inputs'!B868)) -> 1725 | M17: =IF(SUM(IF(IF('Model inputs'!B869="",0,1)="",0,IF('Model inputs'!B869="",0,1)),IF(IF('Model inputs'!B870="",0,1)="",0,IF('Model inputs'!B870="",0,1)),IF(IF('Model inputs'!B871="",0,1)="",0,IF('Model inputs'!B871="",0,1)),IF(IF('Model inputs'!B872="",0,1)="",0,IF('Model inputs'!B872="",0,1)),IF(IF('Model inputs'!B873="",0,1)="",0,IF('Model inputs'!B873="",0,1)))=0,"",SUM('Model inputs'!B869,'Model inputs'!B870,'Model inputs'!B871,'Model inputs'!B872,'Model inputs'!B873)) -> 1800
A18: Plan Net cash burn | B18: =IF(SUM(IF(IF('Model inputs'!B874="",0,1)="",0,IF('Model inputs'!B874="",0,1)),IF(IF('Model inputs'!B875="",0,1)="",0,IF('Model inputs'!B875="",0,1)),IF(IF('Model inputs'!B876="",0,1)="",0,IF('Model inputs'!B876="",0,1)),IF(IF('Model inputs'!B877="",0,1)="",0,IF('Model inputs'!B877="",0,1)),IF(IF('Model inputs'!B878="",0,1)="",0,IF('Model inputs'!B878="",0,1)))=0,"",SUM('Model inputs'!B874,'Model inputs'!B875,'Model inputs'!B876,'Model inputs'!B877,'Model inputs'!B878)) -> -30264.25 | C18: =IF(SUM(IF(IF('Model inputs'!B879="",0,1)="",0,IF('Model inputs'!B879="",0,1)),IF(IF('Model inputs'!B880="",0,1)="",0,IF('Model inputs'!B880="",0,1)),IF(IF('Model inputs'!B881="",0,1)="",0,IF('Model inputs'!B881="",0,1)),IF(IF('Model inputs'!B882="",0,1)="",0,IF('Model inputs'!B882="",0,1)),IF(IF('Model inputs'!B883="",0,1)="",0,IF('Model inputs'!B883="",0,1)))=0,"",SUM('Model inputs'!B879,'Model inputs'!B880,'Model inputs'!B881,'Model inputs'!B882,'Model inputs'!B883)) -> -32178.5 | D18: =IF(SUM(IF(IF('Model inputs'!B884="",0,1)="",0,IF('Model inputs'!B884="",0,1)),IF(IF('Model inputs'!B885="",0,1)="",0,IF('Model inputs'!B885="",0,1)),IF(IF('Model inputs'!B886="",0,1)="",0,IF('Model inputs'!B886="",0,1)),IF(IF('Model inputs'!B887="",0,1)="",0,IF('Model inputs'!B887="",0,1)),IF(IF('Model inputs'!B888="",0,1)="",0,IF('Model inputs'!B888="",0,1)))=0,"",SUM('Model inputs'!B884,'Model inputs'!B885,'Model inputs'!B886,'Model inputs'!B887,'Model inputs'!B888)) -> -34092.75 | E18: =IF(SUM(IF(IF('Model inputs'!B889="",0,1)="",0,IF('Model inputs'!B889="",0,1)),IF(IF('Model inputs'!B890="",0,1)="",0,IF('Model inputs'!B890="",0,1)),IF(IF('Model inputs'!B891="",0,1)="",0,IF('Model inputs'!B891="",0,1)),IF(IF('Model inputs'!B892="",0,1)="",0,IF('Model inputs'!B892="",0,1)),IF(IF('Model inputs'!B893="",0,1)="",0,IF('Model inputs'!B893="",0,1)))=0,"",SUM('Model inputs'!B889,'Model inputs'!B890,'Model inputs'!B891,'Model inputs'!B892,'Model inputs'!B893)) -> -36007 | F18: =IF(SUM(IF(IF('Model inputs'!B894="",0,1)="",0,IF('Model inputs'!B894="",0,1)),IF(IF('Model inputs'!B895="",0,1)="",0,IF('Model inputs'!B895="",0,1)),IF(IF('Model inputs'!B896="",0,1)="",0,IF('Model inputs'!B896="",0,1)),IF(IF('Model inputs'!B897="",0,1)="",0,IF('Model inputs'!B897="",0,1)),IF(IF('Model inputs'!B898="",0,1)="",0,IF('Model inputs'!B898="",0,1)))=0,"",SUM('Model inputs'!B894,'Model inputs'!B895,'Model inputs'!B896,'Model inputs'!B897,'Model inputs'!B898)) -> -37921.25 | G18: =IF(SUM(IF(IF('Model inputs'!B899="",0,1)="",0,IF('Model inputs'!B899="",0,1)),IF(IF('Model inputs'!B900="",0,1)="",0,IF('Model inputs'!B900="",0,1)),IF(IF('Model inputs'!B901="",0,1)="",0,IF('Model inputs'!B901="",0,1)),IF(IF('Model inputs'!B902="",0,1)="",0,IF('Model inputs'!B902="",0,1)),IF(IF('Model inputs'!B903="",0,1)="",0,IF('Model inputs'!B903="",0,1)))=0,"",SUM('Model inputs'!B899,'Model inputs'!B900,'Model inputs'!B901,'Model inputs'!B902,'Model inputs'!B903)) -> -39335.5 | H18: =IF(SUM(IF(IF('Model inputs'!B904="",0,1)="",0,IF('Model inputs'!B904="",0,1)),IF(IF('Model inputs'!B905="",0,1)="",0,IF('Model inputs'!B905="",0,1)),IF(IF('Model inputs'!B906="",0,1)="",0,IF('Model inputs'!B906="",0,1)),IF(IF('Model inputs'!B907="",0,1)="",0,IF('Model inputs'!B907="",0,1)),IF(IF('Model inputs'!B908="",0,1)="",0,IF('Model inputs'!B908="",0,1)))=0,"",SUM('Model inputs'!B904,'Model inputs'!B905,'Model inputs'!B906,'Model inputs'!B907,'Model inputs'!B908)) -> -41249.75 | I18: =IF(SUM(IF(IF('Model inputs'!B909="",0,1)="",0,IF('Model inputs'!B909="",0,1)),IF(IF('Model inputs'!B910="",0,1)="",0,IF('Model inputs'!B910="",0,1)),IF(IF('Model inputs'!B911="",0,1)="",0,IF('Model inputs'!B911="",0,1)),IF(IF('Model inputs'!B912="",0,1)="",0,IF('Model inputs'!B912="",0,1)),IF(IF('Model inputs'!B913="",0,1)="",0,IF('Model inputs'!B913="",0,1)))=0,"",SUM('Model inputs'!B909,'Model inputs'!B910,'Model inputs'!B911,'Model inputs'!B912,'Model inputs'!B913)) -> -43164 | J18: =IF(SUM(IF(IF('Model inputs'!B914="",0,1)="",0,IF('Model inputs'!B914="",0,1)),IF(IF('Model inputs'!B915="",0,1)="",0,IF('Model inputs'!B915="",0,1)),IF(IF('Model inputs'!B916="",0,1)="",0,IF('Model inputs'!B916="",0,1)),IF(IF('Model inputs'!B917="",0,1)="",0,IF('Model inputs'!B917="",0,1)),IF(IF('Model inputs'!B918="",0,1)="",0,IF('Model inputs'!B918="",0,1)))=0,"",SUM('Model inputs'!B914,'Model inputs'!B915,'Model inputs'!B916,'Model inputs'!B917,'Model inputs'!B918)) -> -45078.25 | K18: =IF(SUM(IF(IF('Model inputs'!B919="",0,1)="",0,IF('Model inputs'!B919="",0,1)),IF(IF('Model inputs'!B920="",0,1)="",0,IF('Model inputs'!B920="",0,1)),IF(IF('Model inputs'!B921="",0,1)="",0,IF('Model inputs'!B921="",0,1)),IF(IF('Model inputs'!B922="",0,1)="",0,IF('Model inputs'!B922="",0,1)),IF(IF('Model inputs'!B923="",0,1)="",0,IF('Model inputs'!B923="",0,1)))=0,"",SUM('Model inputs'!B919,'Model inputs'!B920,'Model inputs'!B921,'Model inputs'!B922,'Model inputs'!B923)) -> -46992.5 | L18: =IF(SUM(IF(IF('Model inputs'!B924="",0,1)="",0,IF('Model inputs'!B924="",0,1)),IF(IF('Model inputs'!B925="",0,1)="",0,IF('Model inputs'!B925="",0,1)),IF(IF('Model inputs'!B926="",0,1)="",0,IF('Model inputs'!B926="",0,1)),IF(IF('Model inputs'!B927="",0,1)="",0,IF('Model inputs'!B927="",0,1)),IF(IF('Model inputs'!B928="",0,1)="",0,IF('Model inputs'!B928="",0,1)))=0,"",SUM('Model inputs'!B924,'Model inputs'!B925,'Model inputs'!B926,'Model inputs'!B927,'Model inputs'!B928)) -> -48906.75 | M18: =IF(SUM(IF(IF('Model inputs'!B929="",0,1)="",0,IF('Model inputs'!B929="",0,1)),IF(IF('Model inputs'!B930="",0,1)="",0,IF('Model inputs'!B930="",0,1)),IF(IF('Model inputs'!B931="",0,1)="",0,IF('Model inputs'!B931="",0,1)),IF(IF('Model inputs'!B932="",0,1)="",0,IF('Model inputs'!B932="",0,1)),IF(IF('Model inputs'!B933="",0,1)="",0,IF('Model inputs'!B933="",0,1)))=0,"",SUM('Model inputs'!B929,'Model inputs'!B930,'Model inputs'!B931,'Model inputs'!B932,'Model inputs'!B933)) -> -50821
A19: Cumulative net cash burn | B19: =IF(IF(IF(IF(ISERROR('Model inputs'!C105=1),'Model inputs'!C105=1,IF('Model inputs'!C105="","",'Model inputs'!C105=1))="",FALSE,IF(ISERROR('Model inputs'!C105=1),'Model inputs'!C105=1,IF('Model inputs'!C105="","",'Model inputs'!C105=1))),0,IF('Model inputs'!B47="","",'Model inputs'!B47))="",0,IF(IF(IF(ISERROR('Model inputs'!C105=1),'Model inputs'!C105=1,IF('Model inputs'!C105="","",'Model inputs'!C105=1))="",FALSE,IF(ISERROR('Model inputs'!C105=1),'Model inputs'!C105=1,IF('Model inputs'!C105="","",'Model inputs'!C105=1))),0,IF('Model inputs'!B47="","",'Model inputs'!B47)))+'DealScope 12-month financial pr'!B18 -> -30264.25 | C19: =IF(IF(IF(IF(ISERROR('Model inputs'!D105=1),'Model inputs'!D105=1,IF('Model inputs'!D105="","",'Model inputs'!D105=1))="",FALSE,IF(ISERROR('Model inputs'!D105=1),'Model inputs'!D105=1,IF('Model inputs'!D105="","",'Model inputs'!D105=1))),0,IF('DealScope 12-month financial pr'!B19="","",'DealScope 12-month financial pr'!B19))="",0,IF(IF(IF(ISERROR('Model inputs'!D105=1),'Model inputs'!D105=1,IF('Model inputs'!D105="","",'Model inputs'!D105=1))="",FALSE,IF(ISERROR('Model inputs'!D105=1),'Model inputs'!D105=1,IF('Model inputs'!D105="","",'Model inputs'!D105=1))),0,IF('DealScope 12-month financial pr'!B19="","",'DealScope 12-month financial pr'!B19)))+'DealScope 12-month financial pr'!C18 -> -62442.75 | D19: =IF(IF(IF(IF(ISERROR('Model inputs'!E105=1),'Model inputs'!E105=1,IF('Model inputs'!E105="","",'Model inputs'!E105=1))="",FALSE,IF(ISERROR('Model inputs'!E105=1),'Model inputs'!E105=1,IF('Model inputs'!E105="","",'Model inputs'!E105=1))),0,IF('DealScope 12-month financial pr'!C19="","",'DealScope 12-month financial pr'!C19))="",0,IF(IF(IF(ISERROR('Model inputs'!E105=1),'Model inputs'!E105=1,IF('Model inputs'!E105="","",'Model inputs'!E105=1))="",FALSE,IF(ISERROR('Model inputs'!E105=1),'Model inputs'!E105=1,IF('Model inputs'!E105="","",'Model inputs'!E105=1))),0,IF('DealScope 12-month financial pr'!C19="","",'DealScope 12-month financial pr'!C19)))+'DealScope 12-month financial pr'!D18 -> -96535.5 | E19: =IF(IF(IF(IF(ISERROR('Model inputs'!F105=1),'Model inputs'!F105=1,IF('Model inputs'!F105="","",'Model inputs'!F105=1))="",FALSE,IF(ISERROR('Model inputs'!F105=1),'Model inputs'!F105=1,IF('Model inputs'!F105="","",'Model inputs'!F105=1))),0,IF('DealScope 12-month financial pr'!D19="","",'DealScope 12-month financial pr'!D19))="",0,IF(IF(IF(ISERROR('Model inputs'!F105=1),'Model inputs'!F105=1,IF('Model inputs'!F105="","",'Model inputs'!F105=1))="",FALSE,IF(ISERROR('Model inputs'!F105=1),'Model inputs'!F105=1,IF('Model inputs'!F105="","",'Model inputs'!F105=1))),0,IF('DealScope 12-month financial pr'!D19="","",'DealScope 12-month financial pr'!D19)))+'DealScope 12-month financial pr'!E18 -> -132542.5 | F19: =IF(IF(IF(IF(ISERROR('Model inputs'!G105=1),'Model inputs'!G105=1,IF('Model inputs'!G105="","",'Model inputs'!G105=1))="",FALSE,IF(ISERROR('Model inputs'!G105=1),'Model inputs'!G105=1,IF('Model inputs'!G105="","",'Model inputs'!G105=1))),0,IF('DealScope 12-month financial pr'!E19="","",'DealScope 12-month financial pr'!E19))="",0,IF(IF(IF(ISERROR('Model inputs'!G105=1),'Model inputs'!G105=1,IF('Model inputs'!G105="","",'Model inputs'!G105=1))="",FALSE,IF(ISERROR('Model inputs'!G105=1),'Model inputs'!G105=1,IF('Model inputs'!G105="","",'Model inputs'!G105=1))),0,IF('DealScope 12-month financial pr'!E19="","",'DealScope 12-month financial pr'!E19)))+'DealScope 12-month financial pr'!F18 -> -170463.75 | G19: =IF(IF(IF(IF(ISERROR('Model inputs'!H105=1),'Model inputs'!H105=1,IF('Model inputs'!H105="","",'Model inputs'!H105=1))="",FALSE,IF(ISERROR('Model inputs'!H105=1),'Model inputs'!H105=1,IF('Model inputs'!H105="","",'Model inputs'!H105=1))),0,IF('DealScope 12-month financial pr'!F19="","",'DealScope 12-month financial pr'!F19))="",0,IF(IF(IF(ISERROR('Model inputs'!H105=1),'Model inputs'!H105=1,IF('Model inputs'!H105="","",'Model inputs'!H105=1))="",FALSE,IF(ISERROR('Model inputs'!H105=1),'Model inputs'!H105=1,IF('Model inputs'!H105="","",'Model inputs'!H105=1))),0,IF('DealScope 12-month financial pr'!F19="","",'DealScope 12-month financial pr'!F19)))+'DealScope 12-month financial pr'!G18 -> -209799.25 | H19: =IF(IF(IF(IF(ISERROR('Model inputs'!I105=1),'Model inputs'!I105=1,IF('Model inputs'!I105="","",'Model inputs'!I105=1))="",FALSE,IF(ISERROR('Model inputs'!I105=1),'Model inputs'!I105=1,IF('Model inputs'!I105="","",'Model inputs'!I105=1))),0,IF('DealScope 12-month financial pr'!G19="","",'DealScope 12-month financial pr'!G19))="",0,IF(IF(IF(ISERROR('Model inputs'!I105=1),'Model inputs'!I105=1,IF('Model inputs'!I105="","",'Model inputs'!I105=1))="",FALSE,IF(ISERROR('Model inputs'!I105=1),'Model inputs'!I105=1,IF('Model inputs'!I105="","",'Model inputs'!I105=1))),0,IF('DealScope 12-month financial pr'!G19="","",'DealScope 12-month financial pr'!G19)))+'DealScope 12-month financial pr'!H18 -> -251049 | I19: =IF(IF(IF(IF(ISERROR('Model inputs'!J105=1),'Model inputs'!J105=1,IF('Model inputs'!J105="","",'Model inputs'!J105=1))="",FALSE,IF(ISERROR('Model inputs'!J105=1),'Model inputs'!J105=1,IF('Model inputs'!J105="","",'Model inputs'!J105=1))),0,IF('DealScope 12-month financial pr'!H19="","",'DealScope 12-month financial pr'!H19))="",0,IF(IF(IF(ISERROR('Model inputs'!J105=1),'Model inputs'!J105=1,IF('Model inputs'!J105="","",'Model inputs'!J105=1))="",FALSE,IF(ISERROR('Model inputs'!J105=1),'Model inputs'!J105=1,IF('Model inputs'!J105="","",'Model inputs'!J105=1))),0,IF('DealScope 12-month financial pr'!H19="","",'DealScope 12-month financial pr'!H19)))+'DealScope 12-month financial pr'!I18 -> -294213 | J19: =IF(IF(IF(IF(ISERROR('Model inputs'!K105=1),'Model inputs'!K105=1,IF('Model inputs'!K105="","",'Model inputs'!K105=1))="",FALSE,IF(ISERROR('Model inputs'!K105=1),'Model inputs'!K105=1,IF('Model inputs'!K105="","",'Model inputs'!K105=1))),0,IF('DealScope 12-month financial pr'!I19="","",'DealScope 12-month financial pr'!I19))="",0,IF(IF(IF(ISERROR('Model inputs'!K105=1),'Model inputs'!K105=1,IF('Model inputs'!K105="","",'Model inputs'!K105=1))="",FALSE,IF(ISERROR('Model inputs'!K105=1),'Model inputs'!K105=1,IF('Model inputs'!K105="","",'Model inputs'!K105=1))),0,IF('DealScope 12-month financial pr'!I19="","",'DealScope 12-month financial pr'!I19)))+'DealScope 12-month financial pr'!J18 -> -339291.25 | ... M19: =IF(IF(IF(IF(ISERROR('Model inputs'!N105=1),'Model inputs'!N105=1,IF('Model inputs'!N105="","",'Model inputs'!N105=1))="",FALSE,IF(ISERROR('Model inputs'!N105=1),'Model inputs'!N105=1,IF('Model inputs'!N105="","",'Model inputs'!N105=1))),0,IF('DealScope 12-month financial pr'!L19="","",'DealScope 12-month financial pr'!L19))="",0,IF(IF(IF(ISERROR('Model inputs'!N105=1),'Model inputs'!N105=1,IF('Model inputs'!N105="","",'Model inputs'!N105=1))="",FALSE,IF(ISERROR('Model inputs'!N105=1),'Model inputs'!N105=1,IF('Model inputs'!N105="","",'Model inputs'!N105=1))),0,IF('DealScope 12-month financial pr'!L19="","",'DealScope 12-month financial pr'!L19)))+'DealScope 12-month financial pr'!M18 -> -486011.5
A20: Cumulative funding gap | B20: =MAX(IF(IF(IF(IF(ISERROR('Model inputs'!C105=1),'Model inputs'!C105=1,IF('Model inputs'!C105="","",'Model inputs'!C105=1))="",FALSE,IF(ISERROR('Model inputs'!C105=1),'Model inputs'!C105=1,IF('Model inputs'!C105="","",'Model inputs'!C105=1))),0,IF('Model inputs'!B47="","",'Model inputs'!B47))="",0,IF(IF(IF(ISERROR('Model inputs'!C105=1),'Model inputs'!C105=1,IF('Model inputs'!C105="","",'Model inputs'!C105=1))="",FALSE,IF(ISERROR('Model inputs'!C105=1),'Model inputs'!C105=1,IF('Model inputs'!C105="","",'Model inputs'!C105=1))),0,IF('Model inputs'!B47="","",'Model inputs'!B47)))+'DealScope 12-month financial pr'!B18,0) -> 0 | C20: =MAX(IF(IF(IF(IF(ISERROR('Model inputs'!D105=1),'Model inputs'!D105=1,IF('Model inputs'!D105="","",'Model inputs'!D105=1))="",FALSE,IF(ISERROR('Model inputs'!D105=1),'Model inputs'!D105=1,IF('Model inputs'!D105="","",'Model inputs'!D105=1))),0,IF('DealScope 12-month financial pr'!B19="","",'DealScope 12-month financial pr'!B19))="",0,IF(IF(IF(ISERROR('Model inputs'!D105=1),'Model inputs'!D105=1,IF('Model inputs'!D105="","",'Model inputs'!D105=1))="",FALSE,IF(ISERROR('Model inputs'!D105=1),'Model inputs'!D105=1,IF('Model inputs'!D105="","",'Model inputs'!D105=1))),0,IF('DealScope 12-month financial pr'!B19="","",'DealScope 12-month financial pr'!B19)))+'DealScope 12-month financial pr'!C18,0) -> 0 | D20: =MAX(IF(IF(IF(IF(ISERROR('Model inputs'!E105=1),'Model inputs'!E105=1,IF('Model inputs'!E105="","",'Model inputs'!E105=1))="",FALSE,IF(ISERROR('Model inputs'!E105=1),'Model inputs'!E105=1,IF('Model inputs'!E105="","",'Model inputs'!E105=1))),0,IF('DealScope 12-month financial pr'!C19="","",'DealScope 12-month financial pr'!C19))="",0,IF(IF(IF(ISERROR('Model inputs'!E105=1),'Model inputs'!E105=1,IF('Model inputs'!E105="","",'Model inputs'!E105=1))="",FALSE,IF(ISERROR('Model inputs'!E105=1),'Model inputs'!E105=1,IF('Model inputs'!E105="","",'Model inputs'!E105=1))),0,IF('DealScope 12-month financial pr'!C19="","",'DealScope 12-month financial pr'!C19)))+'DealScope 12-month financial pr'!D18,0) -> 0 | E20: =MAX(IF(IF(IF(IF(ISERROR('Model inputs'!F105=1),'Model inputs'!F105=1,IF('Model inputs'!F105="","",'Model inputs'!F105=1))="",FALSE,IF(ISERROR('Model inputs'!F105=1),'Model inputs'!F105=1,IF('Model inputs'!F105="","",'Model inputs'!F105=1))),0,IF('DealScope 12-month financial pr'!D19="","",'DealScope 12-month financial pr'!D19))="",0,IF(IF(IF(ISERROR('Model inputs'!F105=1),'Model inputs'!F105=1,IF('Model inputs'!F105="","",'Model inputs'!F105=1))="",FALSE,IF(ISERROR('Model inputs'!F105=1),'Model inputs'!F105=1,IF('Model inputs'!F105="","",'Model inputs'!F105=1))),0,IF('DealScope 12-month financial pr'!D19="","",'DealScope 12-month financial pr'!D19)))+'DealScope 12-month financial pr'!E18,0) -> 0 | F20: =MAX(IF(IF(IF(IF(ISERROR('Model inputs'!G105=1),'Model inputs'!G105=1,IF('Model inputs'!G105="","",'Model inputs'!G105=1))="",FALSE,IF(ISERROR('Model inputs'!G105=1),'Model inputs'!G105=1,IF('Model inputs'!G105="","",'Model inputs'!G105=1))),0,IF('DealScope 12-month financial pr'!E19="","",'DealScope 12-month financial pr'!E19))="",0,IF(IF(IF(ISERROR('Model inputs'!G105=1),'Model inputs'!G105=1,IF('Model inputs'!G105="","",'Model inputs'!G105=1))="",FALSE,IF(ISERROR('Model inputs'!G105=1),'Model inputs'!G105=1,IF('Model inputs'!G105="","",'Model inputs'!G105=1))),0,IF('DealScope 12-month financial pr'!E19="","",'DealScope 12-month financial pr'!E19)))+'DealScope 12-month financial pr'!F18,0) -> 0 | G20: =MAX(IF(IF(IF(IF(ISERROR('Model inputs'!H105=1),'Model inputs'!H105=1,IF('Model inputs'!H105="","",'Model inputs'!H105=1))="",FALSE,IF(ISERROR('Model inputs'!H105=1),'Model inputs'!H105=1,IF('Model inputs'!H105="","",'Model inputs'!H105=1))),0,IF('DealScope 12-month financial pr'!F19="","",'DealScope 12-month financial pr'!F19))="",0,IF(IF(IF(ISERROR('Model inputs'!H105=1),'Model inputs'!H105=1,IF('Model inputs'!H105="","",'Model inputs'!H105=1))="",FALSE,IF(ISERROR('Model inputs'!H105=1),'Model inputs'!H105=1,IF('Model inputs'!H105="","",'Model inputs'!H105=1))),0,IF('DealScope 12-month financial pr'!F19="","",'DealScope 12-month financial pr'!F19)))+'DealScope 12-month financial pr'!G18,0) -> 0 | H20: =MAX(IF(IF(IF(IF(ISERROR('Model inputs'!I105=1),'Model inputs'!I105=1,IF('Model inputs'!I105="","",'Model inputs'!I105=1))="",FALSE,IF(ISERROR('Model inputs'!I105=1),'Model inputs'!I105=1,IF('Model inputs'!I105="","",'Model inputs'!I105=1))),0,IF('DealScope 12-month financial pr'!G19="","",'DealScope 12-month financial pr'!G19))="",0,IF(IF(IF(ISERROR('Model inputs'!I105=1),'Model inputs'!I105=1,IF('Model inputs'!I105="","",'Model inputs'!I105=1))="",FALSE,IF(ISERROR('Model inputs'!I105=1),'Model inputs'!I105=1,IF('Model inputs'!I105="","",'Model inputs'!I105=1))),0,IF('DealScope 12-month financial pr'!G19="","",'DealScope 12-month financial pr'!G19)))+'DealScope 12-month financial pr'!H18,0) -> 0 | I20: =MAX(IF(IF(IF(IF(ISERROR('Model inputs'!J105=1),'Model inputs'!J105=1,IF('Model inputs'!J105="","",'Model inputs'!J105=1))="",FALSE,IF(ISERROR('Model inputs'!J105=1),'Model inputs'!J105=1,IF('Model inputs'!J105="","",'Model inputs'!J105=1))),0,IF('DealScope 12-month financial pr'!H19="","",'DealScope 12-month financial pr'!H19))="",0,IF(IF(IF(ISERROR('Model inputs'!J105=1),'Model inputs'!J105=1,IF('Model inputs'!J105="","",'Model inputs'!J105=1))="",FALSE,IF(ISERROR('Model inputs'!J105=1),'Model inputs'!J105=1,IF('Model inputs'!J105="","",'Model inputs'!J105=1))),0,IF('DealScope 12-month financial pr'!H19="","",'DealScope 12-month financial pr'!H19)))+'DealScope 12-month financial pr'!I18,0) -> 0 | J20: =MAX(IF(IF(IF(IF(ISERROR('Model inputs'!K105=1),'Model inputs'!K105=1,IF('Model inputs'!K105="","",'Model inputs'!K105=1))="",FALSE,IF(ISERROR('Model inputs'!K105=1),'Model inputs'!K105=1,IF('Model inputs'!K105="","",'Model inputs'!K105=1))),0,IF('DealScope 12-month financial pr'!I19="","",'DealScope 12-month financial pr'!I19))="",0,IF(IF(IF(ISERROR('Model inputs'!K105=1),'Model inputs'!K105=1,IF('Model inputs'!K105="","",'Model inputs'!K105=1))="",FALSE,IF(ISERROR('Model inputs'!K105=1),'Model inputs'!K105=1,IF('Model inputs'!K105="","",'Model inputs'!K105=1))),0,IF('DealScope 12-month financial pr'!I19="","",'DealScope 12-month financial pr'!I19)))+'DealScope 12-month financial pr'!J18,0) -> 0 | ... M20: =MAX(IF(IF(IF(IF(ISERROR('Model inputs'!N105=1),'Model inputs'!N105=1,IF('Model inputs'!N105="","",'Model inputs'!N105=1))="",FALSE,IF(ISERROR('Model inputs'!N105=1),'Model inputs'!N105=1,IF('Model inputs'!N105="","",'Model inputs'!N105=1))),0,IF('DealScope 12-month financial pr'!L19="","",'DealScope 12-month financial pr'!L19))="",0,IF(IF(IF(ISERROR('Model inputs'!N105=1),'Model inputs'!N105=1,IF('Model inputs'!N105="","",'Model inputs'!N105=1))="",FALSE,IF(ISERROR('Model inputs'!N105=1),'Model inputs'!N105=1,IF('Model inputs'!N105="","",'Model inputs'!N105=1))),0,IF('DealScope 12-month financial pr'!L19="","",'DealScope 12-month financial pr'!L19)))+'DealScope 12-month financial pr'!M18,0) -> 0
A21: Conditional cash balance | B21: =IF(IF(IF(ISERROR('Model inputs'!O28=1),'Model inputs'!O28=1,IF('Model inputs'!O28="","",'Model inputs'!O28=1))="",FALSE,IF(ISERROR('Model inputs'!O28=1),'Model inputs'!O28=1,IF('Model inputs'!O28="","",'Model inputs'!O28=1))),IF('Model inputs'!O18="",0,'Model inputs'!O18)-'DealScope 12-month financial pr'!B19,"") | C21: =IF(IF(IF(ISERROR('Model inputs'!O28=1),'Model inputs'!O28=1,IF('Model inputs'!O28="","",'Model inputs'!O28=1))="",FALSE,IF(ISERROR('Model inputs'!O28=1),'Model inputs'!O28=1,IF('Model inputs'!O28="","",'Model inputs'!O28=1))),IF('Model inputs'!O18="",0,'Model inputs'!O18)-'DealScope 12-month financial pr'!C19,"") | D21: =IF(IF(IF(ISERROR('Model inputs'!O28=1),'Model inputs'!O28=1,IF('Model inputs'!O28="","",'Model inputs'!O28=1))="",FALSE,IF(ISERROR('Model inputs'!O28=1),'Model inputs'!O28=1,IF('Model inputs'!O28="","",'Model inputs'!O28=1))),IF('Model inputs'!O18="",0,'Model inputs'!O18)-'DealScope 12-month financial pr'!D19,"") | E21: =IF(IF(IF(ISERROR('Model inputs'!O28=1),'Model inputs'!O28=1,IF('Model inputs'!O28="","",'Model inputs'!O28=1))="",FALSE,IF(ISERROR('Model inputs'!O28=1),'Model inputs'!O28=1,IF('Model inputs'!O28="","",'Model inputs'!O28=1))),IF('Model inputs'!O18="",0,'Model inputs'!O18)-'DealScope 12-month financial pr'!E19,"") | F21: =IF(IF(IF(ISERROR('Model inputs'!O28=1),'Model inputs'!O28=1,IF('Model inputs'!O28="","",'Model inputs'!O28=1))="",FALSE,IF(ISERROR('Model inputs'!O28=1),'Model inputs'!O28=1,IF('Model inputs'!O28="","",'Model inputs'!O28=1))),IF('Model inputs'!O18="",0,'Model inputs'!O18)-'DealScope 12-month financial pr'!F19,"") | G21: =IF(IF(IF(ISERROR('Model inputs'!O28=1),'Model inputs'!O28=1,IF('Model inputs'!O28="","",'Model inputs'!O28=1))="",FALSE,IF(ISERROR('Model inputs'!O28=1),'Model inputs'!O28=1,IF('Model inputs'!O28="","",'Model inputs'!O28=1))),IF('Model inputs'!O18="",0,'Model inputs'!O18)-'DealScope 12-month financial pr'!G19,"") | H21: =IF(IF(IF(ISERROR('Model inputs'!O28=1),'Model inputs'!O28=1,IF('Model inputs'!O28="","",'Model inputs'!O28=1))="",FALSE,IF(ISERROR('Model inputs'!O28=1),'Model inputs'!O28=1,IF('Model inputs'!O28="","",'Model inputs'!O28=1))),IF('Model inputs'!O18="",0,'Model inputs'!O18)-'DealScope 12-month financial pr'!H19,"") | I21: =IF(IF(IF(ISERROR('Model inputs'!O28=1),'Model inputs'!O28=1,IF('Model inputs'!O28="","",'Model inputs'!O28=1))="",FALSE,IF(ISERROR('Model inputs'!O28=1),'Model inputs'!O28=1,IF('Model inputs'!O28="","",'Model inputs'!O28=1))),IF('Model inputs'!O18="",0,'Model inputs'!O18)-'DealScope 12-month financial pr'!I19,"") | J21: =IF(IF(IF(ISERROR('Model inputs'!O28=1),'Model inputs'!O28=1,IF('Model inputs'!O28="","",'Model inputs'!O28=1))="",FALSE,IF(ISERROR('Model inputs'!O28=1),'Model inputs'!O28=1,IF('Model inputs'!O28="","",'Model inputs'!O28=1))),IF('Model inputs'!O18="",0,'Model inputs'!O18)-'DealScope 12-month financial pr'!J19,"") | K21: =IF(IF(IF(ISERROR('Model inputs'!O28=1),'Model inputs'!O28=1,IF('Model inputs'!O28="","",'Model inputs'!O28=1))="",FALSE,IF(ISERROR('Model inputs'!O28=1),'Model inputs'!O28=1,IF('Model inputs'!O28="","",'Model inputs'!O28=1))),IF('Model inputs'!O18="",0,'Model inputs'!O18)-'DealScope 12-month financial pr'!K19,"") | L21: =IF(IF(IF(ISERROR('Model inputs'!O28=1),'Model inputs'!O28=1,IF('Model inputs'!O28="","",'Model inputs'!O28=1))="",FALSE,IF(ISERROR('Model inputs'!O28=1),'Model inputs'!O28=1,IF('Model inputs'!O28="","",'Model inputs'!O28=1))),IF('Model inputs'!O18="",0,'Model inputs'!O18)-'DealScope 12-month financial pr'!L19,"") | M21: =IF(IF(IF(ISERROR('Model inputs'!O28=1),'Model inputs'!O28=1,IF('Model inputs'!O28="","",'Model inputs'!O28=1))="",FALSE,IF(ISERROR('Model inputs'!O28=1),'Model inputs'!O28=1,IF('Model inputs'!O28="","",'Model inputs'!O28=1))),IF('Model inputs'!O18="",0,'Model inputs'!O18)-'DealScope 12-month financial pr'!M19,"")
A22: Deferred subscription revenue | B22: =IF(IF(IF(IF(ISERROR('Model inputs'!C105=1),'Model inputs'!C105=1,IF('Model inputs'!C105="","",'Model inputs'!C105=1))="",FALSE,IF(ISERROR('Model inputs'!C105=1),'Model inputs'!C105=1,IF('Model inputs'!C105="","",'Model inputs'!C105=1))),0,IF('Model inputs'!B49="","",'Model inputs'!B49))="",0,IF(IF(IF(ISERROR('Model inputs'!C105=1),'Model inputs'!C105=1,IF('Model inputs'!C105="","",'Model inputs'!C105=1))="",FALSE,IF(ISERROR('Model inputs'!C105=1),'Model inputs'!C105=1,IF('Model inputs'!C105="","",'Model inputs'!C105=1))),0,IF('Model inputs'!B49="","",'Model inputs'!B49)))+'DealScope 12-month financial pr'!B16-'DealScope 12-month financial pr'!B7 -> 27500 | C22: =IF(IF(IF(IF(ISERROR('Model inputs'!D105=1),'Model inputs'!D105=1,IF('Model inputs'!D105="","",'Model inputs'!D105=1))="",FALSE,IF(ISERROR('Model inputs'!D105=1),'Model inputs'!D105=1,IF('Model inputs'!D105="","",'Model inputs'!D105=1))),0,IF('DealScope 12-month financial pr'!B22="","",'DealScope 12-month financial pr'!B22))="",0,IF(IF(IF(ISERROR('Model inputs'!D105=1),'Model inputs'!D105=1,IF('Model inputs'!D105="","",'Model inputs'!D105=1))="",FALSE,IF(ISERROR('Model inputs'!D105=1),'Model inputs'!D105=1,IF('Model inputs'!D105="","",'Model inputs'!D105=1))),0,IF('DealScope 12-month financial pr'!B22="","",'DealScope 12-month financial pr'!B22)))+'DealScope 12-month financial pr'!C16-'DealScope 12-month financial pr'!C7 -> 52500 | D22: =IF(IF(IF(IF(ISERROR('Model inputs'!E105=1),'Model inputs'!E105=1,IF('Model inputs'!E105="","",'Model inputs'!E105=1))="",FALSE,IF(ISERROR('Model inputs'!E105=1),'Model inputs'!E105=1,IF('Model inputs'!E105="","",'Model inputs'!E105=1))),0,IF('DealScope 12-month financial pr'!C22="","",'DealScope 12-month financial pr'!C22))="",0,IF(IF(IF(ISERROR('Model inputs'!E105=1),'Model inputs'!E105=1,IF('Model inputs'!E105="","",'Model inputs'!E105=1))="",FALSE,IF(ISERROR('Model inputs'!E105=1),'Model inputs'!E105=1,IF('Model inputs'!E105="","",'Model inputs'!E105=1))),0,IF('DealScope 12-month financial pr'!C22="","",'DealScope 12-month financial pr'!C22)))+'DealScope 12-month financial pr'!D16-'DealScope 12-month financial pr'!D7 -> 75000 | E22: =IF(IF(IF(IF(ISERROR('Model inputs'!F105=1),'Model inputs'!F105=1,IF('Model inputs'!F105="","",'Model inputs'!F105=1))="",FALSE,IF(ISERROR('Model inputs'!F105=1),'Model inputs'!F105=1,IF('Model inputs'!F105="","",'Model inputs'!F105=1))),0,IF('DealScope 12-month financial pr'!D22="","",'DealScope 12-month financial pr'!D22))="",0,IF(IF(IF(ISERROR('Model inputs'!F105=1),'Model inputs'!F105=1,IF('Model inputs'!F105="","",'Model inputs'!F105=1))="",FALSE,IF(ISERROR('Model inputs'!F105=1),'Model inputs'!F105=1,IF('Model inputs'!F105="","",'Model inputs'!F105=1))),0,IF('DealScope 12-month financial pr'!D22="","",'DealScope 12-month financial pr'!D22)))+'DealScope 12-month financial pr'!E16-'DealScope 12-month financial pr'!E7 -> 95000 | F22: =IF(IF(IF(IF(ISERROR('Model inputs'!G105=1),'Model inputs'!G105=1,IF('Model inputs'!G105="","",'Model inputs'!G105=1))="",FALSE,IF(ISERROR('Model inputs'!G105=1),'Model inputs'!G105=1,IF('Model inputs'!G105="","",'Model inputs'!G105=1))),0,IF('DealScope 12-month financial pr'!E22="","",'DealScope 12-month financial pr'!E22))="",0,IF(IF(IF(ISERROR('Model inputs'!G105=1),'Model inputs'!G105=1,IF('Model inputs'!G105="","",'Model inputs'!G105=1))="",FALSE,IF(ISERROR('Model inputs'!G105=1),'Model inputs'!G105=1,IF('Model inputs'!G105="","",'Model inputs'!G105=1))),0,IF('DealScope 12-month financial pr'!E22="","",'DealScope 12-month financial pr'!E22)))+'DealScope 12-month financial pr'!F16-'DealScope 12-month financial pr'!F7 -> 112500 | G22: =IF(IF(IF(IF(ISERROR('Model inputs'!H105=1),'Model inputs'!H105=1,IF('Model inputs'!H105="","",'Model inputs'!H105=1))="",FALSE,IF(ISERROR('Model inputs'!H105=1),'Model inputs'!H105=1,IF('Model inputs'!H105="","",'Model inputs'!H105=1))),0,IF('DealScope 12-month financial pr'!F22="","",'DealScope 12-month financial pr'!F22))="",0,IF(IF(IF(ISERROR('Model inputs'!H105=1),'Model inputs'!H105=1,IF('Model inputs'!H105="","",'Model inputs'!H105=1))="",FALSE,IF(ISERROR('Model inputs'!H105=1),'Model inputs'!H105=1,IF('Model inputs'!H105="","",'Model inputs'!H105=1))),0,IF('DealScope 12-month financial pr'!F22="","",'DealScope 12-month financial pr'!F22)))+'DealScope 12-month financial pr'!G16-'DealScope 12-month financial pr'!G7 -> 127500 | H22: =IF(IF(IF(IF(ISERROR('Model inputs'!I105=1),'Model inputs'!I105=1,IF('Model inputs'!I105="","",'Model inputs'!I105=1))="",FALSE,IF(ISERROR('Model inputs'!I105=1),'Model inputs'!I105=1,IF('Model inputs'!I105="","",'Model inputs'!I105=1))),0,IF('DealScope 12-month financial pr'!G22="","",'DealScope 12-month financial pr'!G22))="",0,IF(IF(IF(ISERROR('Model inputs'!I105=1),'Model inputs'!I105=1,IF('Model inputs'!I105="","",'Model inputs'!I105=1))="",FALSE,IF(ISERROR('Model inputs'!I105=1),'Model inputs'!I105=1,IF('Model inputs'!I105="","",'Model inputs'!I105=1))),0,IF('DealScope 12-month financial pr'!G22="","",'DealScope 12-month financial pr'!G22)))+'DealScope 12-month financial pr'!H16-'DealScope 12-month financial pr'!H7 -> 140000 | I22: =IF(IF(IF(IF(ISERROR('Model inputs'!J105=1),'Model inputs'!J105=1,IF('Model inputs'!J105="","",'Model inputs'!J105=1))="",FALSE,IF(ISERROR('Model inputs'!J105=1),'Model inputs'!J105=1,IF('Model inputs'!J105="","",'Model inputs'!J105=1))),0,IF('DealScope 12-month financial pr'!H22="","",'DealScope 12-month financial pr'!H22))="",0,IF(IF(IF(ISERROR('Model inputs'!J105=1),'Model inputs'!J105=1,IF('Model inputs'!J105="","",'Model inputs'!J105=1))="",FALSE,IF(ISERROR('Model inputs'!J105=1),'Model inputs'!J105=1,IF('Model inputs'!J105="","",'Model inputs'!J105=1))),0,IF('DealScope 12-month financial pr'!H22="","",'DealScope 12-month financial pr'!H22)))+'DealScope 12-month financial pr'!I16-'DealScope 12-month financial pr'!I7 -> 150000 | J22: =IF(IF(IF(IF(ISERROR('Model inputs'!K105=1),'Model inputs'!K105=1,IF('Model inputs'!K105="","",'Model inputs'!K105=1))="",FALSE,IF(ISERROR('Model inputs'!K105=1),'Model inputs'!K105=1,IF('Model inputs'!K105="","",'Model inputs'!K105=1))),0,IF('DealScope 12-month financial pr'!I22="","",'DealScope 12-month financial pr'!I22))="",0,IF(IF(IF(ISERROR('Model inputs'!K105=1),'Model inputs'!K105=1,IF('Model inputs'!K105="","",'Model inputs'!K105=1))="",FALSE,IF(ISERROR('Model inputs'!K105=1),'Model inputs'!K105=1,IF('Model inputs'!K105="","",'Model inputs'!K105=1))),0,IF('DealScope 12-month financial pr'!I22="","",'DealScope 12-month financial pr'!I22)))+'DealScope 12-month financial pr'!J16-'DealScope 12-month financial pr'!J7 -> 157500 | ... M22: =IF(IF(IF(IF(ISERROR('Model inputs'!N105=1),'Model inputs'!N105=1,IF('Model inputs'!N105="","",'Model inputs'!N105=1))="",FALSE,IF(ISERROR('Model inputs'!N105=1),'Model inputs'!N105=1,IF('Model inputs'!N105="","",'Model inputs'!N105=1))),0,IF('DealScope 12-month financial pr'!L22="","",'DealScope 12-month financial pr'!L22))="",0,IF(IF(IF(ISERROR('Model inputs'!N105=1),'Model inputs'!N105=1,IF('Model inputs'!N105="","",'Model inputs'!N105=1))="",FALSE,IF(ISERROR('Model inputs'!N105=1),'Model inputs'!N105=1,IF('Model inputs'!N105="","",'Model inputs'!N105=1))),0,IF('DealScope 12-month financial pr'!L22="","",'DealScope 12-month financial pr'!L22)))+'DealScope 12-month financial pr'!M16-'DealScope 12-month financial pr'!M7 -> 165000
A23: QA hours required | B23: ='DealScope 12-month financial pr'!B6*'Model inputs'!O107 -> 7.5 | C23: ='DealScope 12-month financial pr'!C6*'Model inputs'!O107 -> 15 | D23: ='DealScope 12-month financial pr'!D6*'Model inputs'!O107 -> 22.5 | E23: ='DealScope 12-month financial pr'!E6*'Model inputs'!O107 -> 30 | F23: ='DealScope 12-month financial pr'!F6*'Model inputs'!O107 -> 37.5 | G23: ='DealScope 12-month financial pr'!G6*'Model inputs'!O107 -> 45 | H23: ='DealScope 12-month financial pr'!H6*'Model inputs'!O107 -> 52.5 | I23: ='DealScope 12-month financial pr'!I6*'Model inputs'!O107 -> 60 | J23: ='DealScope 12-month financial pr'!J6*'Model inputs'!O107 -> 67.5 | K23: ='DealScope 12-month financial pr'!K6*'Model inputs'!O107 -> 75 | L23: ='DealScope 12-month financial pr'!L6*'Model inputs'!O107 -> 82.5 | M23: ='DealScope 12-month financial pr'!M6*'Model inputs'!O107 -> 90
A24: Support hours required | B24: ='DealScope 12-month financial pr'!B5*'Model inputs'!O113 -> 0.625 | C24: ='DealScope 12-month financial pr'!C5*'Model inputs'!O113 -> 1.25 | D24: ='DealScope 12-month financial pr'!D5*'Model inputs'!O113 -> 1.875 | E24: ='DealScope 12-month financial pr'!E5*'Model inputs'!O113 -> 2.5 | F24: ='DealScope 12-month financial pr'!F5*'Model inputs'!O113 -> 3.125 | G24: ='DealScope 12-month financial pr'!G5*'Model inputs'!O113 -> 3.75 | H24: ='DealScope 12-month financial pr'!H5*'Model inputs'!O113 -> 4.375 | I24: ='DealScope 12-month financial pr'!I5*'Model inputs'!O113 -> 5 | J24: ='DealScope 12-month financial pr'!J5*'Model inputs'!O113 -> 5.625 | K24: ='DealScope 12-month financial pr'!K5*'Model inputs'!O113 -> 6.25 | L24: ='DealScope 12-month financial pr'!L5*'Model inputs'!O113 -> 6.875 | M24: ='DealScope 12-month financial pr'!M5*'Model inputs'!O113 -> 7.5
A25: Credits required | B25: ='DealScope 12-month financial pr'!B6*'Model inputs'!O45 -> 130 | C25: ='DealScope 12-month financial pr'!C6*'Model inputs'!O45 -> 260 | D25: ='DealScope 12-month financial pr'!D6*'Model inputs'!O45 -> 390 | E25: ='DealScope 12-month financial pr'!E6*'Model inputs'!O45 -> 520 | F25: ='DealScope 12-month financial pr'!F6*'Model inputs'!O45 -> 650 | G25: ='DealScope 12-month financial pr'!G6*'Model inputs'!O45 -> 780 | H25: ='DealScope 12-month financial pr'!H6*'Model inputs'!O45 -> 910 | I25: ='DealScope 12-month financial pr'!I6*'Model inputs'!O45 -> 1040 | J25: ='DealScope 12-month financial pr'!J6*'Model inputs'!O45 -> 1170 | K25: ='DealScope 12-month financial pr'!K6*'Model inputs'!O45 -> 1300 | L25: ='DealScope 12-month financial pr'!L6*'Model inputs'!O45 -> 1430 | M25: ='DealScope 12-month financial pr'!M6*'Model inputs'!O45 -> 1560

Sheet DealScope variable cost detail
A1: DealScope variable cost detail
A2: DealScope — Financial projection · Growth
A4: Variable / dimension | B4: 2026-10 | C4: 2026-11 | D4: 2026-12 | E4: 2027-01 | F4: 2027-02 | G4: 2027-03 | H4: 2027-04 | I4: 2027-05 | J4: 2027-06 | K4: 2027-07 | L4: 2027-08 | M4: 2027-09
A5: Monthly Crustdata cost | B5: ='DealScope 12-month financial pr'!B6*'Model inputs'!O44 -> 13 | C5: ='DealScope 12-month financial pr'!C6*'Model inputs'!O44 -> 26 | D5: ='DealScope 12-month financial pr'!D6*'Model inputs'!O44 -> 39 | E5: ='DealScope 12-month financial pr'!E6*'Model inputs'!O44 -> 52 | F5: ='DealScope 12-month financial pr'!F6*'Model inputs'!O44 -> 65 | G5: ='DealScope 12-month financial pr'!G6*'Model inputs'!O44 -> 78 | H5: ='DealScope 12-month financial pr'!H6*'Model inputs'!O44 -> 91 | I5: ='DealScope 12-month financial pr'!I6*'Model inputs'!O44 -> 104 | J5: ='DealScope 12-month financial pr'!J6*'Model inputs'!O44 -> 117 | K5: ='DealScope 12-month financial pr'!K6*'Model inputs'!O44 -> 130 | L5: ='DealScope 12-month financial pr'!L6*'Model inputs'!O44 -> 143 | M5: ='DealScope 12-month financial pr'!M6*'Model inputs'!O44 -> 156
A6: Monthly LLM inference | B6: ='DealScope 12-month financial pr'!B6*'Model inputs'!O81 -> 0.25 | C6: ='DealScope 12-month financial pr'!C6*'Model inputs'!O81 -> 0.5 | D6: ='DealScope 12-month financial pr'!D6*'Model inputs'!O81 -> 0.75 | E6: ='DealScope 12-month financial pr'!E6*'Model inputs'!O81 -> 1 | F6: ='DealScope 12-month financial pr'!F6*'Model inputs'!O81 -> 1.25 | G6: ='DealScope 12-month financial pr'!G6*'Model inputs'!O81 -> 1.5 | H6: ='DealScope 12-month financial pr'!H6*'Model inputs'!O81 -> 1.75 | I6: ='DealScope 12-month financial pr'!I6*'Model inputs'!O81 -> 2 | J6: ='DealScope 12-month financial pr'!J6*'Model inputs'!O81 -> 2.25 | K6: ='DealScope 12-month financial pr'!K6*'Model inputs'!O81 -> 2.5 | L6: ='DealScope 12-month financial pr'!L6*'Model inputs'!O81 -> 2.75 | M6: ='DealScope 12-month financial pr'!M6*'Model inputs'!O81 -> 3
A7: Monthly analyst QA cost | B7: ='DealScope 12-month financial pr'!B6*'Model inputs'!O106 -> 450 | C7: ='DealScope 12-month financial pr'!C6*'Model inputs'!O106 -> 900 | D7: ='DealScope 12-month financial pr'!D6*'Model inputs'!O106 -> 1350 | E7: ='DealScope 12-month financial pr'!E6*'Model inputs'!O106 -> 1800 | F7: ='DealScope 12-month financial pr'!F6*'Model inputs'!O106 -> 2250 | G7: ='DealScope 12-month financial pr'!G6*'Model inputs'!O106 -> 2700 | H7: ='DealScope 12-month financial pr'!H6*'Model inputs'!O106 -> 3150 | I7: ='DealScope 12-month financial pr'!I6*'Model inputs'!O106 -> 3600 | J7: ='DealScope 12-month financial pr'!J6*'Model inputs'!O106 -> 4050 | K7: ='DealScope 12-month financial pr'!K6*'Model inputs'!O106 -> 4500 | L7: ='DealScope 12-month financial pr'!L6*'Model inputs'!O106 -> 4950 | M7: ='DealScope 12-month financial pr'!M6*'Model inputs'!O106 -> 5400
A8: Monthly delivery tooling | B8: ='DealScope 12-month financial pr'!B6*'Model inputs'!O56 -> 10 | C8: ='DealScope 12-month financial pr'!C6*'Model inputs'!O56 -> 20 | D8: ='DealScope 12-month financial pr'!D6*'Model inputs'!O56 -> 30 | E8: ='DealScope 12-month financial pr'!E6*'Model inputs'!O56 -> 40 | F8: ='DealScope 12-month financial pr'!F6*'Model inputs'!O56 -> 50 | G8: ='DealScope 12-month financial pr'!G6*'Model inputs'!O56 -> 60 | H8: ='DealScope 12-month financial pr'!H6*'Model inputs'!O56 -> 70 | I8: ='DealScope 12-month financial pr'!I6*'Model inputs'!O56 -> 80 | J8: ='DealScope 12-month financial pr'!J6*'Model inputs'!O56 -> 90 | K8: ='DealScope 12-month financial pr'!K6*'Model inputs'!O56 -> 100 | L8: ='DealScope 12-month financial pr'!L6*'Model inputs'!O56 -> 110 | M8: ='DealScope 12-month financial pr'!M6*'Model inputs'!O56 -> 120
A9: Plan Account support cost | B9: =IF(SUM(IF(IF('Model inputs'!B574="",0,1)="",0,IF('Model inputs'!B574="",0,1)),IF(IF('Model inputs'!B575="",0,1)="",0,IF('Model inputs'!B575="",0,1)),IF(IF('Model inputs'!B576="",0,1)="",0,IF('Model inputs'!B576="",0,1)),IF(IF('Model inputs'!B577="",0,1)="",0,IF('Model inputs'!B577="",0,1)),IF(IF('Model inputs'!B578="",0,1)="",0,IF('Model inputs'!B578="",0,1)))=0,"",SUM('Model inputs'!B574,'Model inputs'!B575,'Model inputs'!B576,'Model inputs'!B577,'Model inputs'!B578)) -> 37.5 | C9: =IF(SUM(IF(IF('Model inputs'!B579="",0,1)="",0,IF('Model inputs'!B579="",0,1)),IF(IF('Model inputs'!B580="",0,1)="",0,IF('Model inputs'!B580="",0,1)),IF(IF('Model inputs'!B581="",0,1)="",0,IF('Model inputs'!B581="",0,1)),IF(IF('Model inputs'!B582="",0,1)="",0,IF('Model inputs'!B582="",0,1)),IF(IF('Model inputs'!B583="",0,1)="",0,IF('Model inputs'!B583="",0,1)))=0,"",SUM('Model inputs'!B579,'Model inputs'!B580,'Model inputs'!B581,'Model inputs'!B582,'Model inputs'!B583)) -> 75 | D9: =IF(SUM(IF(IF('Model inputs'!B584="",0,1)="",0,IF('Model inputs'!B584="",0,1)),IF(IF('Model inputs'!B585="",0,1)="",0,IF('Model inputs'!B585="",0,1)),IF(IF('Model inputs'!B586="",0,1)="",0,IF('Model inputs'!B586="",0,1)),IF(IF('Model inputs'!B587="",0,1)="",0,IF('Model inputs'!B587="",0,1)),IF(IF('Model inputs'!B588="",0,1)="",0,IF('Model inputs'!B588="",0,1)))=0,"",SUM('Model inputs'!B584,'Model inputs'!B585,'Model inputs'!B586,'Model inputs'!B587,'Model inputs'!B588)) -> 112.5 | E9: =IF(SUM(IF(IF('Model inputs'!B589="",0,1)="",0,IF('Model inputs'!B589="",0,1)),IF(IF('Model inputs'!B590="",0,1)="",0,IF('Model inputs'!B590="",0,1)),IF(IF('Model inputs'!B591="",0,1)="",0,IF('Model inputs'!B591="",0,1)),IF(IF('Model inputs'!B592="",0,1)="",0,IF('Model inputs'!B592="",0,1)),IF(IF('Model inputs'!B593="",0,1)="",0,IF('Model inputs'!B593="",0,1)))=0,"",SUM('Model inputs'!B589,'Model inputs'!B590,'Model inputs'!B591,'Model inputs'!B592,'Model inputs'!B593)) -> 150 | F9: =IF(SUM(IF(IF('Model inputs'!B594="",0,1)="",0,IF('Model inputs'!B594="",0,1)),IF(IF('Model inputs'!B595="",0,1)="",0,IF('Model inputs'!B595="",0,1)),IF(IF('Model inputs'!B596="",0,1)="",0,IF('Model inputs'!B596="",0,1)),IF(IF('Model inputs'!B597="",0,1)="",0,IF('Model inputs'!B597="",0,1)),IF(IF('Model inputs'!B598="",0,1)="",0,IF('Model inputs'!B598="",0,1)))=0,"",SUM('Model inputs'!B594,'Model inputs'!B595,'Model inputs'!B596,'Model inputs'!B597,'Model inputs'!B598)) -> 187.5 | G9: =IF(SUM(IF(IF('Model inputs'!B599="",0,1)="",0,IF('Model inputs'!B599="",0,1)),IF(IF('Model inputs'!B600="",0,1)="",0,IF('Model inputs'!B600="",0,1)),IF(IF('Model inputs'!B601="",0,1)="",0,IF('Model inputs'!B601="",0,1)),IF(IF('Model inputs'!B602="",0,1)="",0,IF('Model inputs'!B602="",0,1)),IF(IF('Model inputs'!B603="",0,1)="",0,IF('Model inputs'!B603="",0,1)))=0,"",SUM('Model inputs'!B599,'Model inputs'!B600,'Model inputs'!B601,'Model inputs'!B602,'Model inputs'!B603)) -> 225 | H9: =IF(SUM(IF(IF('Model inputs'!B604="",0,1)="",0,IF('Model inputs'!B604="",0,1)),IF(IF('Model inputs'!B605="",0,1)="",0,IF('Model inputs'!B605="",0,1)),IF(IF('Model inputs'!B606="",0,1)="",0,IF('Model inputs'!B606="",0,1)),IF(IF('Model inputs'!B607="",0,1)="",0,IF('Model inputs'!B607="",0,1)),IF(IF('Model inputs'!B608="",0,1)="",0,IF('Model inputs'!B608="",0,1)))=0,"",SUM('Model inputs'!B604,'Model inputs'!B605,'Model inputs'!B606,'Model inputs'!B607,'Model inputs'!B608)) -> 262.5 | I9: =IF(SUM(IF(IF('Model inputs'!B609="",0,1)="",0,IF('Model inputs'!B609="",0,1)),IF(IF('Model inputs'!B610="",0,1)="",0,IF('Model inputs'!B610="",0,1)),IF(IF('Model inputs'!B611="",0,1)="",0,IF('Model inputs'!B611="",0,1)),IF(IF('Model inputs'!B612="",0,1)="",0,IF('Model inputs'!B612="",0,1)),IF(IF('Model inputs'!B613="",0,1)="",0,IF('Model inputs'!B613="",0,1)))=0,"",SUM('Model inputs'!B609,'Model inputs'!B610,'Model inputs'!B611,'Model inputs'!B612,'Model inputs'!B613)) -> 300 | J9: =IF(SUM(IF(IF('Model inputs'!B614="",0,1)="",0,IF('Model inputs'!B614="",0,1)),IF(IF('Model inputs'!B615="",0,1)="",0,IF('Model inputs'!B615="",0,1)),IF(IF('Model inputs'!B616="",0,1)="",0,IF('Model inputs'!B616="",0,1)),IF(IF('Model inputs'!B617="",0,1)="",0,IF('Model inputs'!B617="",0,1)),IF(IF('Model inputs'!B618="",0,1)="",0,IF('Model inputs'!B618="",0,1)))=0,"",SUM('Model inputs'!B614,'Model inputs'!B615,'Model inputs'!B616,'Model inputs'!B617,'Model inputs'!B618)) -> 337.5 | K9: =IF(SUM(IF(IF('Model inputs'!B619="",0,1)="",0,IF('Model inputs'!B619="",0,1)),IF(IF('Model inputs'!B620="",0,1)="",0,IF('Model inputs'!B620="",0,1)),IF(IF('Model inputs'!B621="",0,1)="",0,IF('Model inputs'!B621="",0,1)),IF(IF('Model inputs'!B622="",0,1)="",0,IF('Model inputs'!B622="",0,1)),IF(IF('Model inputs'!B623="",0,1)="",0,IF('Model inputs'!B623="",0,1)))=0,"",SUM('Model inputs'!B619,'Model inputs'!B620,'Model inputs'!B621,'Model inputs'!B622,'Model inputs'!B623)) -> 375 | L9: =IF(SUM(IF(IF('Model inputs'!B624="",0,1)="",0,IF('Model inputs'!B624="",0,1)),IF(IF('Model inputs'!B625="",0,1)="",0,IF('Model inputs'!B625="",0,1)),IF(IF('Model inputs'!B626="",0,1)="",0,IF('Model inputs'!B626="",0,1)),IF(IF('Model inputs'!B627="",0,1)="",0,IF('Model inputs'!B627="",0,1)),IF(IF('Model inputs'!B628="",0,1)="",0,IF('Model inputs'!B628="",0,1)))=0,"",SUM('Model inputs'!B624,'Model inputs'!B625,'Model inputs'!B626,'Model inputs'!B627,'Model inputs'!B628)) -> 412.5 | M9: =IF(SUM(IF(IF('Model inputs'!B629="",0,1)="",0,IF('Model inputs'!B629="",0,1)),IF(IF('Model inputs'!B630="",0,1)="",0,IF('Model inputs'!B630="",0,1)),IF(IF('Model inputs'!B631="",0,1)="",0,IF('Model inputs'!B631="",0,1)),IF(IF('Model inputs'!B632="",0,1)="",0,IF('Model inputs'!B632="",0,1)),IF(IF('Model inputs'!B633="",0,1)="",0,IF('Model inputs'!B633="",0,1)))=0,"",SUM('Model inputs'!B629,'Model inputs'!B630,'Model inputs'!B631,'Model inputs'!B632,'Model inputs'!B633)) -> 450
A10: Plan Payment fees | B10: =IF(SUM(IF(IF('Model inputs'!B814="",0,1)="",0,IF('Model inputs'!B814="",0,1)),IF(IF('Model inputs'!B815="",0,1)="",0,IF('Model inputs'!B815="",0,1)),IF(IF('Model inputs'!B816="",0,1)="",0,IF('Model inputs'!B816="",0,1)),IF(IF('Model inputs'!B817="",0,1)="",0,IF('Model inputs'!B817="",0,1)),IF(IF('Model inputs'!B818="",0,1)="",0,IF('Model inputs'!B818="",0,1)))=0,"",SUM('Model inputs'!B814,'Model inputs'!B815,'Model inputs'!B816,'Model inputs'!B817,'Model inputs'!B818)) -> 975 | C10: =IF(SUM(IF(IF('Model inputs'!B819="",0,1)="",0,IF('Model inputs'!B819="",0,1)),IF(IF('Model inputs'!B820="",0,1)="",0,IF('Model inputs'!B820="",0,1)),IF(IF('Model inputs'!B821="",0,1)="",0,IF('Model inputs'!B821="",0,1)),IF(IF('Model inputs'!B822="",0,1)="",0,IF('Model inputs'!B822="",0,1)),IF(IF('Model inputs'!B823="",0,1)="",0,IF('Model inputs'!B823="",0,1)))=0,"",SUM('Model inputs'!B819,'Model inputs'!B820,'Model inputs'!B821,'Model inputs'!B822,'Model inputs'!B823)) -> 1050 | D10: =IF(SUM(IF(IF('Model inputs'!B824="",0,1)="",0,IF('Model inputs'!B824="",0,1)),IF(IF('Model inputs'!B825="",0,1)="",0,IF('Model inputs'!B825="",0,1)),IF(IF('Model inputs'!B826="",0,1)="",0,IF('Model inputs'!B826="",0,1)),IF(IF('Model inputs'!B827="",0,1)="",0,IF('Model inputs'!B827="",0,1)),IF(IF('Model inputs'!B828="",0,1)="",0,IF('Model inputs'!B828="",0,1)))=0,"",SUM('Model inputs'!B824,'Model inputs'!B825,'Model inputs'!B826,'Model inputs'!B827,'Model inputs'!B828)) -> 1125 | E10: =IF(SUM(IF(IF('Model inputs'!B829="",0,1)="",0,IF('Model inputs'!B829="",0,1)),IF(IF('Model inputs'!B830="",0,1)="",0,IF('Model inputs'!B830="",0,1)),IF(IF('Model inputs'!B831="",0,1)="",0,IF('Model inputs'!B831="",0,1)),IF(IF('Model inputs'!B832="",0,1)="",0,IF('Model inputs'!B832="",0,1)),IF(IF('Model inputs'!B833="",0,1)="",0,IF('Model inputs'!B833="",0,1)))=0,"",SUM('Model inputs'!B829,'Model inputs'!B830,'Model inputs'!B831,'Model inputs'!B832,'Model inputs'!B833)) -> 1200 | F10: =IF(SUM(IF(IF('Model inputs'!B834="",0,1)="",0,IF('Model inputs'!B834="",0,1)),IF(IF('Model inputs'!B835="",0,1)="",0,IF('Model inputs'!B835="",0,1)),IF(IF('Model inputs'!B836="",0,1)="",0,IF('Model inputs'!B836="",0,1)),IF(IF('Model inputs'!B837="",0,1)="",0,IF('Model inputs'!B837="",0,1)),IF(IF('Model inputs'!B838="",0,1)="",0,IF('Model inputs'!B838="",0,1)))=0,"",SUM('Model inputs'!B834,'Model inputs'!B835,'Model inputs'!B836,'Model inputs'!B837,'Model inputs'!B838)) -> 1275 | G10: =IF(SUM(IF(IF('Model inputs'!B839="",0,1)="",0,IF('Model inputs'!B839="",0,1)),IF(IF('Model inputs'!B840="",0,1)="",0,IF('Model inputs'!B840="",0,1)),IF(IF('Model inputs'!B841="",0,1)="",0,IF('Model inputs'!B841="",0,1)),IF(IF('Model inputs'!B842="",0,1)="",0,IF('Model inputs'!B842="",0,1)),IF(IF('Model inputs'!B843="",0,1)="",0,IF('Model inputs'!B843="",0,1)))=0,"",SUM('Model inputs'!B839,'Model inputs'!B840,'Model inputs'!B841,'Model inputs'!B842,'Model inputs'!B843)) -> 1350 | H10: =IF(SUM(IF(IF('Model inputs'!B844="",0,1)="",0,IF('Model inputs'!B844="",0,1)),IF(IF('Model inputs'!B845="",0,1)="",0,IF('Model inputs'!B845="",0,1)),IF(IF('Model inputs'!B846="",0,1)="",0,IF('Model inputs'!B846="",0,1)),IF(IF('Model inputs'!B847="",0,1)="",0,IF('Model inputs'!B847="",0,1)),IF(IF('Model inputs'!B848="",0,1)="",0,IF('Model inputs'!B848="",0,1)))=0,"",SUM('Model inputs'!B844,'Model inputs'!B845,'Model inputs'!B846,'Model inputs'!B847,'Model inputs'!B848)) -> 1425 | I10: =IF(SUM(IF(IF('Model inputs'!B849="",0,1)="",0,IF('Model inputs'!B849="",0,1)),IF(IF('Model inputs'!B850="",0,1)="",0,IF('Model inputs'!B850="",0,1)),IF(IF('Model inputs'!B851="",0,1)="",0,IF('Model inputs'!B851="",0,1)),IF(IF('Model inputs'!B852="",0,1)="",0,IF('Model inputs'!B852="",0,1)),IF(IF('Model inputs'!B853="",0,1)="",0,IF('Model inputs'!B853="",0,1)))=0,"",SUM('Model inputs'!B849,'Model inputs'!B850,'Model inputs'!B851,'Model inputs'!B852,'Model inputs'!B853)) -> 1500 | J10: =IF(SUM(IF(IF('Model inputs'!B854="",0,1)="",0,IF('Model inputs'!B854="",0,1)),IF(IF('Model inputs'!B855="",0,1)="",0,IF('Model inputs'!B855="",0,1)),IF(IF('Model inputs'!B856="",0,1)="",0,IF('Model inputs'!B856="",0,1)),IF(IF('Model inputs'!B857="",0,1)="",0,IF('Model inputs'!B857="",0,1)),IF(IF('Model inputs'!B858="",0,1)="",0,IF('Model inputs'!B858="",0,1)))=0,"",SUM('Model inputs'!B854,'Model inputs'!B855,'Model inputs'!B856,'Model inputs'!B857,'Model inputs'!B858)) -> 1575 | K10: =IF(SUM(IF(IF('Model inputs'!B859="",0,1)="",0,IF('Model inputs'!B859="",0,1)),IF(IF('Model inputs'!B860="",0,1)="",0,IF('Model inputs'!B860="",0,1)),IF(IF('Model inputs'!B861="",0,1)="",0,IF('Model inputs'!B861="",0,1)),IF(IF('Model inputs'!B862="",0,1)="",0,IF('Model inputs'!B862="",0,1)),IF(IF('Model inputs'!B863="",0,1)="",0,IF('Model inputs'!B863="",0,1)))=0,"",SUM('Model inputs'!B859,'Model inputs'!B860,'Model inputs'!B861,'Model inputs'!B862,'Model inputs'!B863)) -> 1650 | L10: =IF(SUM(IF(IF('Model inputs'!B864="",0,1)="",0,IF('Model inputs'!B864="",0,1)),IF(IF('Model inputs'!B865="",0,1)="",0,IF('Model inputs'!B865="",0,1)),IF(IF('Model inputs'!B866="",0,1)="",0,IF('Model inputs'!B866="",0,1)),IF(IF('Model inputs'!B867="",0,1)="",0,IF('Model inputs'!B867="",0,1)),IF(IF('Model inputs'!B868="",0,1)="",0,IF('Model inputs'!B868="",0,1)))=0,"",SUM('Model inputs'!B864,'Model inputs'!B865,'Model inputs'!B866,'Model inputs'!B867,'Model inputs'!B868)) -> 1725 | M10: =IF(SUM(IF(IF('Model inputs'!B869="",0,1)="",0,IF('Model inputs'!B869="",0,1)),IF(IF('Model inputs'!B870="",0,1)="",0,IF('Model inputs'!B870="",0,1)),IF(IF('Model inputs'!B871="",0,1)="",0,IF('Model inputs'!B871="",0,1)),IF(IF('Model inputs'!B872="",0,1)="",0,IF('Model inputs'!B872="",0,1)),IF(IF('Model inputs'!B873="",0,1)="",0,IF('Model inputs'!B873="",0,1)))=0,"",SUM('Model inputs'!B869,'Model inputs'!B870,'Model inputs'!B871,'Model inputs'!B872,'Model inputs'!B873)) -> 1800
A11: QA hours required | B11: ='DealScope 12-month financial pr'!B6*'Model inputs'!O107 -> 7.5 | C11: ='DealScope 12-month financial pr'!C6*'Model inputs'!O107 -> 15 | D11: ='DealScope 12-month financial pr'!D6*'Model inputs'!O107 -> 22.5 | E11: ='DealScope 12-month financial pr'!E6*'Model inputs'!O107 -> 30 | F11: ='DealScope 12-month financial pr'!F6*'Model inputs'!O107 -> 37.5 | G11: ='DealScope 12-month financial pr'!G6*'Model inputs'!O107 -> 45 | H11: ='DealScope 12-month financial pr'!H6*'Model inputs'!O107 -> 52.5 | I11: ='DealScope 12-month financial pr'!I6*'Model inputs'!O107 -> 60 | J11: ='DealScope 12-month financial pr'!J6*'Model inputs'!O107 -> 67.5 | K11: ='DealScope 12-month financial pr'!K6*'Model inputs'!O107 -> 75 | L11: ='DealScope 12-month financial pr'!L6*'Model inputs'!O107 -> 82.5 | M11: ='DealScope 12-month financial pr'!M6*'Model inputs'!O107 -> 90
A12: Support hours required | B12: ='DealScope 12-month financial pr'!B5*'Model inputs'!O113 -> 0.625 | C12: ='DealScope 12-month financial pr'!C5*'Model inputs'!O113 -> 1.25 | D12: ='DealScope 12-month financial pr'!D5*'Model inputs'!O113 -> 1.875 | E12: ='DealScope 12-month financial pr'!E5*'Model inputs'!O113 -> 2.5 | F12: ='DealScope 12-month financial pr'!F5*'Model inputs'!O113 -> 3.125 | G12: ='DealScope 12-month financial pr'!G5*'Model inputs'!O113 -> 3.75 | H12: ='DealScope 12-month financial pr'!H5*'Model inputs'!O113 -> 4.375 | I12: ='DealScope 12-month financial pr'!I5*'Model inputs'!O113 -> 5 | J12: ='DealScope 12-month financial pr'!J5*'Model inputs'!O113 -> 5.625 | K12: ='DealScope 12-month financial pr'!K5*'Model inputs'!O113 -> 6.25 | L12: ='DealScope 12-month financial pr'!L5*'Model inputs'!O113 -> 6.875 | M12: ='DealScope 12-month financial pr'!M5*'Model inputs'!O113 -> 7.5

Sheet DealScope conditional cash and
A1: DealScope conditional cash and runway
A2: DealScope — Financial projection · Growth
A4: Variable / dimension | B4: 2026-10 | C4: 2026-11 | D4: 2026-12 | E4: 2027-01 | F4: 2027-02 | G4: 2027-03 | H4: 2027-04 | I4: 2027-05 | J4: 2027-06 | K4: 2027-07 | L4: 2027-08 | M4: 2027-09
A5: Conditional cash balance | B5: =IF(IF(IF(ISERROR('Model inputs'!O28=1),'Model inputs'!O28=1,IF('Model inputs'!O28="","",'Model inputs'!O28=1))="",FALSE,IF(ISERROR('Model inputs'!O28=1),'Model inputs'!O28=1,IF('Model inputs'!O28="","",'Model inputs'!O28=1))),IF('Model inputs'!O18="",0,'Model inputs'!O18)-'DealScope 12-month financial pr'!B19,"") | C5: =IF(IF(IF(ISERROR('Model inputs'!O28=1),'Model inputs'!O28=1,IF('Model inputs'!O28="","",'Model inputs'!O28=1))="",FALSE,IF(ISERROR('Model inputs'!O28=1),'Model inputs'!O28=1,IF('Model inputs'!O28="","",'Model inputs'!O28=1))),IF('Model inputs'!O18="",0,'Model inputs'!O18)-'DealScope 12-month financial pr'!C19,"") | D5: =IF(IF(IF(ISERROR('Model inputs'!O28=1),'Model inputs'!O28=1,IF('Model inputs'!O28="","",'Model inputs'!O28=1))="",FALSE,IF(ISERROR('Model inputs'!O28=1),'Model inputs'!O28=1,IF('Model inputs'!O28="","",'Model inputs'!O28=1))),IF('Model inputs'!O18="",0,'Model inputs'!O18)-'DealScope 12-month financial pr'!D19,"") | E5: =IF(IF(IF(ISERROR('Model inputs'!O28=1),'Model inputs'!O28=1,IF('Model inputs'!O28="","",'Model inputs'!O28=1))="",FALSE,IF(ISERROR('Model inputs'!O28=1),'Model inputs'!O28=1,IF('Model inputs'!O28="","",'Model inputs'!O28=1))),IF('Model inputs'!O18="",0,'Model inputs'!O18)-'DealScope 12-month financial pr'!E19,"") | F5: =IF(IF(IF(ISERROR('Model inputs'!O28=1),'Model inputs'!O28=1,IF('Model inputs'!O28="","",'Model inputs'!O28=1))="",FALSE,IF(ISERROR('Model inputs'!O28=1),'Model inputs'!O28=1,IF('Model inputs'!O28="","",'Model inputs'!O28=1))),IF('Model inputs'!O18="",0,'Model inputs'!O18)-'DealScope 12-month financial pr'!F19,"") | G5: =IF(IF(IF(ISERROR('Model inputs'!O28=1),'Model inputs'!O28=1,IF('Model inputs'!O28="","",'Model inputs'!O28=1))="",FALSE,IF(ISERROR('Model inputs'!O28=1),'Model inputs'!O28=1,IF('Model inputs'!O28="","",'Model inputs'!O28=1))),IF('Model inputs'!O18="",0,'Model inputs'!O18)-'DealScope 12-month financial pr'!G19,"") | H5: =IF(IF(IF(ISERROR('Model inputs'!O28=1),'Model inputs'!O28=1,IF('Model inputs'!O28="","",'Model inputs'!O28=1))="",FALSE,IF(ISERROR('Model inputs'!O28=1),'Model inputs'!O28=1,IF('Model inputs'!O28="","",'Model inputs'!O28=1))),IF('Model inputs'!O18="",0,'Model inputs'!O18)-'DealScope 12-month financial pr'!H19,"") | I5: =IF(IF(IF(ISERROR('Model inputs'!O28=1),'Model inputs'!O28=1,IF('Model inputs'!O28="","",'Model inputs'!O28=1))="",FALSE,IF(ISERROR('Model inputs'!O28=1),'Model inputs'!O28=1,IF('Model inputs'!O28="","",'Model inputs'!O28=1))),IF('Model inputs'!O18="",0,'Model inputs'!O18)-'DealScope 12-month financial pr'!I19,"") | J5: =IF(IF(IF(ISERROR('Model inputs'!O28=1),'Model inputs'!O28=1,IF('Model inputs'!O28="","",'Model inputs'!O28=1))="",FALSE,IF(ISERROR('Model inputs'!O28=1),'Model inputs'!O28=1,IF('Model inputs'!O28="","",'Model inputs'!O28=1))),IF('Model inputs'!O18="",0,'Model inputs'!O18)-'DealScope 12-month financial pr'!J19,"") | K5: =IF(IF(IF(ISERROR('Model inputs'!O28=1),'Model inputs'!O28=1,IF('Model inputs'!O28="","",'Model inputs'!O28=1))="",FALSE,IF(ISERROR('Model inputs'!O28=1),'Model inputs'!O28=1,IF('Model inputs'!O28="","",'Model inputs'!O28=1))),IF('Model inputs'!O18="",0,'Model inputs'!O18)-'DealScope 12-month financial pr'!K19,"") | L5: =IF(IF(IF(ISERROR('Model inputs'!O28=1),'Model inputs'!O28=1,IF('Model inputs'!O28="","",'Model inputs'!O28=1))="",FALSE,IF(ISERROR('Model inputs'!O28=1),'Model inputs'!O28=1,IF('Model inputs'!O28="","",'Model inputs'!O28=1))),IF('Model inputs'!O18="",0,'Model inputs'!O18)-'DealScope 12-month financial pr'!L19,"") | M5: =IF(IF(IF(ISERROR('Model inputs'!O28=1),'Model inputs'!O28=1,IF('Model inputs'!O28="","",'Model inputs'!O28=1))="",FALSE,IF(ISERROR('Model inputs'!O28=1),'Model inputs'!O28=1,IF('Model inputs'!O28="","",'Model inputs'!O28=1))),IF('Model inputs'!O18="",0,'Model inputs'!O18)-'DealScope 12-month financial pr'!M19,"")
A6: Conditional remaining runway months | B6: =IF(IF(IF(IFERROR(IF(ISERROR('Model inputs'!O28=1),'Model inputs'!O28=1,IF('Model inputs'!O28="","",'Model inputs'!O28=1))=FALSE,FALSE),FALSE,IF(IFERROR('Model inputs'!B934=FALSE,FALSE),FALSE,IF(IFERROR('Model inputs'!B935=FALSE,FALSE),FALSE,IF(OR(IF(ISERROR('Model inputs'!O28=1),'Model inputs'!O28=1,IF('Model inputs'!O28="","",'Model inputs'!O28=1))="",'Model inputs'!B934="",'Model inputs'!B935=""),"",AND(IF(ISERROR('Model inputs'!O28=1),'Model inputs'!O28=1,IF('Model inputs'!O28="","",'Model inputs'!O28=1)),'Model inputs'!B934,'Model inputs'!B935)))))="",FALSE,IF(IFERROR(IF(ISERROR('Model inputs'!O28=1),'Model inputs'!O28=1,IF('Model inputs'!O28="","",'Model inputs'!O28=1))=FALSE,FALSE),FALSE,IF(IFERROR('Model inputs'!B934=FALSE,FALSE),FALSE,IF(IFERROR('Model inputs'!B935=FALSE,FALSE),FALSE,IF(OR(IF(ISERROR('Model inputs'!O28=1),'Model inputs'!O28=1,IF('Model inputs'!O28="","",'Model inputs'!O28=1))="",'Model inputs'!B934="",'Model inputs'!B935=""),"",AND(IF(ISERROR('Model inputs'!O28=1),'Model inputs'!O28=1,IF('Model inputs'!O28="","",'Model inputs'!O28=1)),'Model inputs'!B934,'Model inputs'!B935)))))),IF('DealScope conditional cash and'!B5="",0,'DealScope conditional cash and'!B5)/'DealScope forecast overview'!B14,"") | C6: =IF(IF(IF(IFERROR(IF(ISERROR('Model inputs'!O28=1),'Model inputs'!O28=1,IF('Model inputs'!O28="","",'Model inputs'!O28=1))=FALSE,FALSE),FALSE,IF(IFERROR('Model inputs'!B934=FALSE,FALSE),FALSE,IF(IFERROR('Model inputs'!B936=FALSE,FALSE),FALSE,IF(OR(IF(ISERROR('Model inputs'!O28=1),'Model inputs'!O28=1,IF('Model inputs'!O28="","",'Model inputs'!O28=1))="",'Model inputs'!B934="",'Model inputs'!B936=""),"",AND(IF(ISERROR('Model inputs'!O28=1),'Model inputs'!O28=1,IF('Model inputs'!O28="","",'Model inputs'!O28=1)),'Model inputs'!B934,'Model inputs'!B936)))))="",FALSE,IF(IFERROR(IF(ISERROR('Model inputs'!O28=1),'Model inputs'!O28=1,IF('Model inputs'!O28="","",'Model inputs'!O28=1))=FALSE,FALSE),FALSE,IF(IFERROR('Model inputs'!B934=FALSE,FALSE),FALSE,IF(IFERROR('Model inputs'!B936=FALSE,FALSE),FALSE,IF(OR(IF(ISERROR('Model inputs'!O28=1),'Model inputs'!O28=1,IF('Model inputs'!O28="","",'Model inputs'!O28=1))="",'Model inputs'!B934="",'Model inputs'!B936=""),"",AND(IF(ISERROR('Model inputs'!O28=1),'Model inputs'!O28=1,IF('Model inputs'!O28="","",'Model inputs'!O28=1)),'Model inputs'!B934,'Model inputs'!B936)))))),IF('DealScope conditional cash and'!C5="",0,'DealScope conditional cash and'!C5)/'DealScope forecast overview'!B14,"") | D6: =IF(IF(IF(IFERROR(IF(ISERROR('Model inputs'!O28=1),'Model inputs'!O28=1,IF('Model inputs'!O28="","",'Model inputs'!O28=1))=FALSE,FALSE),FALSE,IF(IFERROR('Model inputs'!B934=FALSE,FALSE),FALSE,IF(IFERROR('Model inputs'!B937=FALSE,FALSE),FALSE,IF(OR(IF(ISERROR('Model inputs'!O28=1),'Model inputs'!O28=1,IF('Model inputs'!O28="","",'Model inputs'!O28=1))="",'Model inputs'!B934="",'Model inputs'!B937=""),"",AND(IF(ISERROR('Model inputs'!O28=1),'Model inputs'!O28=1,IF('Model inputs'!O28="","",'Model inputs'!O28=1)),'Model inputs'!B934,'Model inputs'!B937)))))="",FALSE,IF(IFERROR(IF(ISERROR('Model inputs'!O28=1),'Model inputs'!O28=1,IF('Model inputs'!O28="","",'Model inputs'!O28=1))=FALSE,FALSE),FALSE,IF(IFERROR('Model inputs'!B934=FALSE,FALSE),FALSE,IF(IFERROR('Model inputs'!B937=FALSE,FALSE),FALSE,IF(OR(IF(ISERROR('Model inputs'!O28=1),'Model inputs'!O28=1,IF('Model inputs'!O28="","",'Model inputs'!O28=1))="",'Model inputs'!B934="",'Model inputs'!B937=""),"",AND(IF(ISERROR('Model inputs'!O28=1),'Model inputs'!O28=1,IF('Model inputs'!O28="","",'Model inputs'!O28=1)),'Model inputs'!B934,'Model inputs'!B937)))))),IF('DealScope conditional cash and'!D5="",0,'DealScope conditional cash and'!D5)/'DealScope forecast overview'!B14,"") | E6: =IF(IF(IF(IFERROR(IF(ISERROR('Model inputs'!O28=1),'Model inputs'!O28=1,IF('Model inputs'!O28="","",'Model inputs'!O28=1))=FALSE,FALSE),FALSE,IF(IFERROR('Model inputs'!B934=FALSE,FALSE),FALSE,IF(IFERROR('Model inputs'!B938=FALSE,FALSE),FALSE,IF(OR(IF(ISERROR('Model inputs'!O28=1),'Model inputs'!O28=1,IF('Model inputs'!O28="","",'Model inputs'!O28=1))="",'Model inputs'!B934="",'Model inputs'!B938=""),"",AND(IF(ISERROR('Model inputs'!O28=1),'Model inputs'!O28=1,IF('Model inputs'!O28="","",'Model inputs'!O28=1)),'Model inputs'!B934,'Model inputs'!B938)))))="",FALSE,IF(IFERROR(IF(ISERROR('Model inputs'!O28=1),'Model inputs'!O28=1,IF('Model inputs'!O28="","",'Model inputs'!O28=1))=FALSE,FALSE),FALSE,IF(IFERROR('Model inputs'!B934=FALSE,FALSE),FALSE,IF(IFERROR('Model inputs'!B938=FALSE,FALSE),FALSE,IF(OR(IF(ISERROR('Model inputs'!O28=1),'Model inputs'!O28=1,IF('Model inputs'!O28="","",'Model inputs'!O28=1))="",'Model inputs'!B934="",'Model inputs'!B938=""),"",AND(IF(ISERROR('Model inputs'!O28=1),'Model inputs'!O28=1,IF('Model inputs'!O28="","",'Model inputs'!O28=1)),'Model inputs'!B934,'Model inputs'!B938)))))),IF('DealScope conditional cash and'!E5="",0,'DealScope conditional cash and'!E5)/'DealScope forecast overview'!B14,"") | F6: =IF(IF(IF(IFERROR(IF(ISERROR('Model inputs'!O28=1),'Model inputs'!O28=1,IF('Model inputs'!O28="","",'Model inputs'!O28=1))=FALSE,FALSE),FALSE,IF(IFERROR('Model inputs'!B934=FALSE,FALSE),FALSE,IF(IFERROR('Model inputs'!B939=FALSE,FALSE),FALSE,IF(OR(IF(ISERROR('Model inputs'!O28=1),'Model inputs'!O28=1,IF('Model inputs'!O28="","",'Model inputs'!O28=1))="",'Model inputs'!B934="",'Model inputs'!B939=""),"",AND(IF(ISERROR('Model inputs'!O28=1),'Model inputs'!O28=1,IF('Model inputs'!O28="","",'Model inputs'!O28=1)),'Model inputs'!B934,'Model inputs'!B939)))))="",FALSE,IF(IFERROR(IF(ISERROR('Model inputs'!O28=1),'Model inputs'!O28=1,IF('Model inputs'!O28="","",'Model inputs'!O28=1))=FALSE,FALSE),FALSE,IF(IFERROR('Model inputs'!B934=FALSE,FALSE),FALSE,IF(IFERROR('Model inputs'!B939=FALSE,FALSE),FALSE,IF(OR(IF(ISERROR('Model inputs'!O28=1),'Model inputs'!O28=1,IF('Model inputs'!O28="","",'Model inputs'!O28=1))="",'Model inputs'!B934="",'Model inputs'!B939=""),"",AND(IF(ISERROR('Model inputs'!O28=1),'Model inputs'!O28=1,IF('Model inputs'!O28="","",'Model inputs'!O28=1)),'Model inputs'!B934,'Model inputs'!B939)))))),IF('DealScope conditional cash and'!F5="",0,'DealScope conditional cash and'!F5)/'DealScope forecast overview'!B14,"") | G6: =IF(IF(IF(IFERROR(IF(ISERROR('Model inputs'!O28=1),'Model inputs'!O28=1,IF('Model inputs'!O28="","",'Model inputs'!O28=1))=FALSE,FALSE),FALSE,IF(IFERROR('Model inputs'!B934=FALSE,FALSE),FALSE,IF(IFERROR('Model inputs'!B940=FALSE,FALSE),FALSE,IF(OR(IF(ISERROR('Model inputs'!O28=1),'Model inputs'!O28=1,IF('Model inputs'!O28="","",'Model inputs'!O28=1))="",'Model inputs'!B934="",'Model inputs'!B940=""),"",AND(IF(ISERROR('Model inputs'!O28=1),'Model inputs'!O28=1,IF('Model inputs'!O28="","",'Model inputs'!O28=1)),'Model inputs'!B934,'Model inputs'!B940)))))="",FALSE,IF(IFERROR(IF(ISERROR('Model inputs'!O28=1),'Model inputs'!O28=1,IF('Model inputs'!O28="","",'Model inputs'!O28=1))=FALSE,FALSE),FALSE,IF(IFERROR('Model inputs'!B934=FALSE,FALSE),FALSE,IF(IFERROR('Model inputs'!B940=FALSE,FALSE),FALSE,IF(OR(IF(ISERROR('Model inputs'!O28=1),'Model inputs'!O28=1,IF('Model inputs'!O28="","",'Model inputs'!O28=1))="",'Model inputs'!B934="",'Model inputs'!B940=""),"",AND(IF(ISERROR('Model inputs'!O28=1),'Model inputs'!O28=1,IF('Model inputs'!O28="","",'Model inputs'!O28=1)),'Model inputs'!B934,'Model inputs'!B940)))))),IF('DealScope conditional cash and'!G5="",0,'DealScope conditional cash and'!G5)/'DealScope forecast overview'!B14,"") | H6: =IF(IF(IF(IFERROR(IF(ISERROR('Model inputs'!O28=1),'Model inputs'!O28=1,IF('Model inputs'!O28="","",'Model inputs'!O28=1))=FALSE,FALSE),FALSE,IF(IFERROR('Model inputs'!B934=FALSE,FALSE),FALSE,IF(IFERROR('Model inputs'!B941=FALSE,FALSE),FALSE,IF(OR(IF(ISERROR('Model inputs'!O28=1),'Model inputs'!O28=1,IF('Model inputs'!O28="","",'Model inputs'!O28=1))="",'Model inputs'!B934="",'Model inputs'!B941=""),"",AND(IF(ISERROR('Model inputs'!O28=1),'Model inputs'!O28=1,IF('Model inputs'!O28="","",'Model inputs'!O28=1)),'Model inputs'!B934,'Model inputs'!B941)))))="",FALSE,IF(IFERROR(IF(ISERROR('Model inputs'!O28=1),'Model inputs'!O28=1,IF('Model inputs'!O28="","",'Model inputs'!O28=1))=FALSE,FALSE),FALSE,IF(IFERROR('Model inputs'!B934=FALSE,FALSE),FALSE,IF(IFERROR('Model inputs'!B941=FALSE,FALSE),FALSE,IF(OR(IF(ISERROR('Model inputs'!O28=1),'Model inputs'!O28=1,IF('Model inputs'!O28="","",'Model inputs'!O28=1))="",'Model inputs'!B934="",'Model inputs'!B941=""),"",AND(IF(ISERROR('Model inputs'!O28=1),'Model inputs'!O28=1,IF('Model inputs'!O28="","",'Model inputs'!O28=1)),'Model inputs'!B934,'Model inputs'!B941)))))),IF('DealScope conditional cash and'!H5="",0,'DealScope conditional cash and'!H5)/'DealScope forecast overview'!B14,"") | I6: =IF(IF(IF(IFERROR(IF(ISERROR('Model inputs'!O28=1),'Model inputs'!O28=1,IF('Model inputs'!O28="","",'Model inputs'!O28=1))=FALSE,FALSE),FALSE,IF(IFERROR('Model inputs'!B934=FALSE,FALSE),FALSE,IF(IFERROR('Model inputs'!B942=FALSE,FALSE),FALSE,IF(OR(IF(ISERROR('Model inputs'!O28=1),'Model inputs'!O28=1,IF('Model inputs'!O28="","",'Model inputs'!O28=1))="",'Model inputs'!B934="",'Model inputs'!B942=""),"",AND(IF(ISERROR('Model inputs'!O28=1),'Model inputs'!O28=1,IF('Model inputs'!O28="","",'Model inputs'!O28=1)),'Model inputs'!B934,'Model inputs'!B942)))))="",FALSE,IF(IFERROR(IF(ISERROR('Model inputs'!O28=1),'Model inputs'!O28=1,IF('Model inputs'!O28="","",'Model inputs'!O28=1))=FALSE,FALSE),FALSE,IF(IFERROR('Model inputs'!B934=FALSE,FALSE),FALSE,IF(IFERROR('Model inputs'!B942=FALSE,FALSE),FALSE,IF(OR(IF(ISERROR('Model inputs'!O28=1),'Model inputs'!O28=1,IF('Model inputs'!O28="","",'Model inputs'!O28=1))="",'Model inputs'!B934="",'Model inputs'!B942=""),"",AND(IF(ISERROR('Model inputs'!O28=1),'Model inputs'!O28=1,IF('Model inputs'!O28="","",'Model inputs'!O28=1)),'Model inputs'!B934,'Model inputs'!B942)))))),IF('DealScope conditional cash and'!I5="",0,'DealScope conditional cash and'!I5)/'DealScope forecast overview'!B14,"") | J6: =IF(IF(IF(IFERROR(IF(ISERROR('Model inputs'!O28=1),'Model inputs'!O28=1,IF('Model inputs'!O28="","",'Model inputs'!O28=1))=FALSE,FALSE),FALSE,IF(IFERROR('Model inputs'!B934=FALSE,FALSE),FALSE,IF(IFERROR('Model inputs'!B943=FALSE,FALSE),FALSE,IF(OR(IF(ISERROR('Model inputs'!O28=1),'Model inputs'!O28=1,IF('Model inputs'!O28="","",'Model inputs'!O28=1))="",'Model inputs'!B934="",'Model inputs'!B943=""),"",AND(IF(ISERROR('Model inputs'!O28=1),'Model inputs'!O28=1,IF('Model inputs'!O28="","",'Model inputs'!O28=1)),'Model inputs'!B934,'Model inputs'!B943)))))="",FALSE,IF(IFERROR(IF(ISERROR('Model inputs'!O28=1),'Model inputs'!O28=1,IF('Model inputs'!O28="","",'Model inputs'!O28=1))=FALSE,FALSE),FALSE,IF(IFERROR('Model inputs'!B934=FALSE,FALSE),FALSE,IF(IFERROR('Model inputs'!B943=FALSE,FALSE),FALSE,IF(OR(IF(ISERROR('Model inputs'!O28=1),'Model inputs'!O28=1,IF('Model inputs'!O28="","",'Model inputs'!O28=1))="",'Model inputs'!B934="",'Model inputs'!B943=""),"",AND(IF(ISERROR('Model inputs'!O28=1),'Model inputs'!O28=1,IF('Model inputs'!O28="","",'Model inputs'!O28=1)),'Model inputs'!B934,'Model inputs'!B943)))))),IF('DealScope conditional cash and'!J5="",0,'DealScope conditional cash and'!J5)/'DealScope forecast overview'!B14,"") | K6: =IF(IF(IF(IFERROR(IF(ISERROR('Model inputs'!O28=1),'Model inputs'!O28=1,IF('Model inputs'!O28="","",'Model inputs'!O28=1))=FALSE,FALSE),FALSE,IF(IFERROR('Model inputs'!B934=FALSE,FALSE),FALSE,IF(IFERROR('Model inputs'!B944=FALSE,FALSE),FALSE,IF(OR(IF(ISERROR('Model inputs'!O28=1),'Model inputs'!O28=1,IF('Model inputs'!O28="","",'Model inputs'!O28=1))="",'Model inputs'!B934="",'Model inputs'!B944=""),"",AND(IF(ISERROR('Model inputs'!O28=1),'Model inputs'!O28=1,IF('Model inputs'!O28="","",'Model inputs'!O28=1)),'Model inputs'!B934,'Model inputs'!B944)))))="",FALSE,IF(IFERROR(IF(ISERROR('Model inputs'!O28=1),'Model inputs'!O28=1,IF('Model inputs'!O28="","",'Model inputs'!O28=1))=FALSE,FALSE),FALSE,IF(IFERROR('Model inputs'!B934=FALSE,FALSE),FALSE,IF(IFERROR('Model inputs'!B944=FALSE,FALSE),FALSE,IF(OR(IF(ISERROR('Model inputs'!O28=1),'Model inputs'!O28=1,IF('Model inputs'!O28="","",'Model inputs'!O28=1))="",'Model inputs'!B934="",'Model inputs'!B944=""),"",AND(IF(ISERROR('Model inputs'!O28=1),'Model inputs'!O28=1,IF('Model inputs'!O28="","",'Model inputs'!O28=1)),'Model inputs'!B934,'Model inputs'!B944)))))),IF('DealScope conditional cash and'!K5="",0,'DealScope conditional cash and'!K5)/'DealScope forecast overview'!B14,"") | L6: =IF(IF(IF(IFERROR(IF(ISERROR('Model inputs'!O28=1),'Model inputs'!O28=1,IF('Model inputs'!O28="","",'Model inputs'!O28=1))=FALSE,FALSE),FALSE,IF(IFERROR('Model inputs'!B934=FALSE,FALSE),FALSE,IF(IFERROR('Model inputs'!B945=FALSE,FALSE),FALSE,IF(OR(IF(ISERROR('Model inputs'!O28=1),'Model inputs'!O28=1,IF('Model inputs'!O28="","",'Model inputs'!O28=1))="",'Model inputs'!B934="",'Model inputs'!B945=""),"",AND(IF(ISERROR('Model inputs'!O28=1),'Model inputs'!O28=1,IF('Model inputs'!O28="","",'Model inputs'!O28=1)),'Model inputs'!B934,'Model inputs'!B945)))))="",FALSE,IF(IFERROR(IF(ISERROR('Model inputs'!O28=1),'Model inputs'!O28=1,IF('Model inputs'!O28="","",'Model inputs'!O28=1))=FALSE,FALSE),FALSE,IF(IFERROR('Model inputs'!B934=FALSE,FALSE),FALSE,IF(IFERROR('Model inputs'!B945=FALSE,FALSE),FALSE,IF(OR(IF(ISERROR('Model inputs'!O28=1),'Model inputs'!O28=1,IF('Model inputs'!O28="","",'Model inputs'!O28=1))="",'Model inputs'!B934="",'Model inputs'!B945=""),"",AND(IF(ISERROR('Model inputs'!O28=1),'Model inputs'!O28=1,IF('Model inputs'!O28="","",'Model inputs'!O28=1)),'Model inputs'!B934,'Model inputs'!B945)))))),IF('DealScope conditional cash and'!L5="",0,'DealScope conditional cash and'!L5)/'DealScope forecast overview'!B14,"") | M6: =IF(IF(IF(IFERROR(IF(ISERROR('Model inputs'!O28=1),'Model inputs'!O28=1,IF('Model inputs'!O28="","",'Model inputs'!O28=1))=FALSE,FALSE),FALSE,IF(IFERROR('Model inputs'!B934=FALSE,FALSE),FALSE,IF(IFERROR('Model inputs'!B946=FALSE,FALSE),FALSE,IF(OR(IF(ISERROR('Model inputs'!O28=1),'Model inputs'!O28=1,IF('Model inputs'!O28="","",'Model inputs'!O28=1))="",'Model inputs'!B934="",'Model inputs'!B946=""),"",AND(IF(ISERROR('Model inputs'!O28=1),'Model inputs'!O28=1,IF('Model inputs'!O28="","",'Model inputs'!O28=1)),'Model inputs'!B934,'Model inputs'!B946)))))="",FALSE,IF(IFERROR(IF(ISERROR('Model inputs'!O28=1),'Model inputs'!O28=1,IF('Model inputs'!O28="","",'Model inputs'!O28=1))=FALSE,FALSE),FALSE,IF(IFERROR('Model inputs'!B934=FALSE,FALSE),FALSE,IF(IFERROR('Model inputs'!B946=FALSE,FALSE),FALSE,IF(OR(IF(ISERROR('Model inputs'!O28=1),'Model inputs'!O28=1,IF('Model inputs'!O28="","",'Model inputs'!O28=1))="",'Model inputs'!B934="",'Model inputs'!B946=""),"",AND(IF(ISERROR('Model inputs'!O28=1),'Model inputs'!O28=1,IF('Model inputs'!O28="","",'Model inputs'!O28=1)),'Model inputs'!B934,'Model inputs'!B946)))))),IF('DealScope conditional cash and'!M5="",0,'DealScope conditional cash and'!M5)/'DealScope forecast overview'!B14,"")
A7: Cumulative funding gap | B7: =MAX(IF(IF(IF(IF(ISERROR('Model inputs'!C105=1),'Model inputs'!C105=1,IF('Model inputs'!C105="","",'Model inputs'!C105=1))="",FALSE,IF(ISERROR('Model inputs'!C105=1),'Model inputs'!C105=1,IF('Model inputs'!C105="","",'Model inputs'!C105=1))),0,IF('Model inputs'!B47="","",'Model inputs'!B47))="",0,IF(IF(IF(ISERROR('Model inputs'!C105=1),'Model inputs'!C105=1,IF('Model inputs'!C105="","",'Model inputs'!C105=1))="",FALSE,IF(ISERROR('Model inputs'!C105=1),'Model inputs'!C105=1,IF('Model inputs'!C105="","",'Model inputs'!C105=1))),0,IF('Model inputs'!B47="","",'Model inputs'!B47)))+'DealScope 12-month financial pr'!B18,0) -> 0 | C7: =MAX(IF(IF(IF(IF(ISERROR('Model inputs'!D105=1),'Model inputs'!D105=1,IF('Model inputs'!D105="","",'Model inputs'!D105=1))="",FALSE,IF(ISERROR('Model inputs'!D105=1),'Model inputs'!D105=1,IF('Model inputs'!D105="","",'Model inputs'!D105=1))),0,IF('DealScope 12-month financial pr'!B19="","",'DealScope 12-month financial pr'!B19))="",0,IF(IF(IF(ISERROR('Model inputs'!D105=1),'Model inputs'!D105=1,IF('Model inputs'!D105="","",'Model inputs'!D105=1))="",FALSE,IF(ISERROR('Model inputs'!D105=1),'Model inputs'!D105=1,IF('Model inputs'!D105="","",'Model inputs'!D105=1))),0,IF('DealScope 12-month financial pr'!B19="","",'DealScope 12-month financial pr'!B19)))+'DealScope 12-month financial pr'!C18,0) -> 0 | D7: =MAX(IF(IF(IF(IF(ISERROR('Model inputs'!E105=1),'Model inputs'!E105=1,IF('Model inputs'!E105="","",'Model inputs'!E105=1))="",FALSE,IF(ISERROR('Model inputs'!E105=1),'Model inputs'!E105=1,IF('Model inputs'!E105="","",'Model inputs'!E105=1))),0,IF('DealScope 12-month financial pr'!C19="","",'DealScope 12-month financial pr'!C19))="",0,IF(IF(IF(ISERROR('Model inputs'!E105=1),'Model inputs'!E105=1,IF('Model inputs'!E105="","",'Model inputs'!E105=1))="",FALSE,IF(ISERROR('Model inputs'!E105=1),'Model inputs'!E105=1,IF('Model inputs'!E105="","",'Model inputs'!E105=1))),0,IF('DealScope 12-month financial pr'!C19="","",'DealScope 12-month financial pr'!C19)))+'DealScope 12-month financial pr'!D18,0) -> 0 | E7: =MAX(IF(IF(IF(IF(ISERROR('Model inputs'!F105=1),'Model inputs'!F105=1,IF('Model inputs'!F105="","",'Model inputs'!F105=1))="",FALSE,IF(ISERROR('Model inputs'!F105=1),'Model inputs'!F105=1,IF('Model inputs'!F105="","",'Model inputs'!F105=1))),0,IF('DealScope 12-month financial pr'!D19="","",'DealScope 12-month financial pr'!D19))="",0,IF(IF(IF(ISERROR('Model inputs'!F105=1),'Model inputs'!F105=1,IF('Model inputs'!F105="","",'Model inputs'!F105=1))="",FALSE,IF(ISERROR('Model inputs'!F105=1),'Model inputs'!F105=1,IF('Model inputs'!F105="","",'Model inputs'!F105=1))),0,IF('DealScope 12-month financial pr'!D19="","",'DealScope 12-month financial pr'!D19)))+'DealScope 12-month financial pr'!E18,0) -> 0 | F7: =MAX(IF(IF(IF(IF(ISERROR('Model inputs'!G105=1),'Model inputs'!G105=1,IF('Model inputs'!G105="","",'Model inputs'!G105=1))="",FALSE,IF(ISERROR('Model inputs'!G105=1),'Model inputs'!G105=1,IF('Model inputs'!G105="","",'Model inputs'!G105=1))),0,IF('DealScope 12-month financial pr'!E19="","",'DealScope 12-month financial pr'!E19))="",0,IF(IF(IF(ISERROR('Model inputs'!G105=1),'Model inputs'!G105=1,IF('Model inputs'!G105="","",'Model inputs'!G105=1))="",FALSE,IF(ISERROR('Model inputs'!G105=1),'Model inputs'!G105=1,IF('Model inputs'!G105="","",'Model inputs'!G105=1))),0,IF('DealScope 12-month financial pr'!E19="","",'DealScope 12-month financial pr'!E19)))+'DealScope 12-month financial pr'!F18,0) -> 0 | G7: =MAX(IF(IF(IF(IF(ISERROR('Model inputs'!H105=1),'Model inputs'!H105=1,IF('Model inputs'!H105="","",'Model inputs'!H105=1))="",FALSE,IF(ISERROR('Model inputs'!H105=1),'Model inputs'!H105=1,IF('Model inputs'!H105="","",'Model inputs'!H105=1))),0,IF('DealScope 12-month financial pr'!F19="","",'DealScope 12-month financial pr'!F19))="",0,IF(IF(IF(ISERROR('Model inputs'!H105=1),'Model inputs'!H105=1,IF('Model inputs'!H105="","",'Model inputs'!H105=1))="",FALSE,IF(ISERROR('Model inputs'!H105=1),'Model inputs'!H105=1,IF('Model inputs'!H105="","",'Model inputs'!H105=1))),0,IF('DealScope 12-month financial pr'!F19="","",'DealScope 12-month financial pr'!F19)))+'DealScope 12-month financial pr'!G18,0) -> 0 | H7: =MAX(IF(IF(IF(IF(ISERROR('Model inputs'!I105=1),'Model inputs'!I105=1,IF('Model inputs'!I105="","",'Model inputs'!I105=1))="",FALSE,IF(ISERROR('Model inputs'!I105=1),'Model inputs'!I105=1,IF('Model inputs'!I105="","",'Model inputs'!I105=1))),0,IF('DealScope 12-month financial pr'!G19="","",'DealScope 12-month financial pr'!G19))="",0,IF(IF(IF(ISERROR('Model inputs'!I105=1),'Model inputs'!I105=1,IF('Model inputs'!I105="","",'Model inputs'!I105=1))="",FALSE,IF(ISERROR('Model inputs'!I105=1),'Model inputs'!I105=1,IF('Model inputs'!I105="","",'Model inputs'!I105=1))),0,IF('DealScope 12-month financial pr'!G19="","",'DealScope 12-month financial pr'!G19)))+'DealScope 12-month financial pr'!H18,0) -> 0 | I7: =MAX(IF(IF(IF(IF(ISERROR('Model inputs'!J105=1),'Model inputs'!J105=1,IF('Model inputs'!J105="","",'Model inputs'!J105=1))="",FALSE,IF(ISERROR('Model inputs'!J105=1),'Model inputs'!J105=1,IF('Model inputs'!J105="","",'Model inputs'!J105=1))),0,IF('DealScope 12-month financial pr'!H19="","",'DealScope 12-month financial pr'!H19))="",0,IF(IF(IF(ISERROR('Model inputs'!J105=1),'Model inputs'!J105=1,IF('Model inputs'!J105="","",'Model inputs'!J105=1))="",FALSE,IF(ISERROR('Model inputs'!J105=1),'Model inputs'!J105=1,IF('Model inputs'!J105="","",'Model inputs'!J105=1))),0,IF('DealScope 12-month financial pr'!H19="","",'DealScope 12-month financial pr'!H19)))+'DealScope 12-month financial pr'!I18,0) -> 0 | J7: =MAX(IF(IF(IF(IF(ISERROR('Model inputs'!K105=1),'Model inputs'!K105=1,IF('Model inputs'!K105="","",'Model inputs'!K105=1))="",FALSE,IF(ISERROR('Model inputs'!K105=1),'Model inputs'!K105=1,IF('Model inputs'!K105="","",'Model inputs'!K105=1))),0,IF('DealScope 12-month financial pr'!I19="","",'DealScope 12-month financial pr'!I19))="",0,IF(IF(IF(ISERROR('Model inputs'!K105=1),'Model inputs'!K105=1,IF('Model inputs'!K105="","",'Model inputs'!K105=1))="",FALSE,IF(ISERROR('Model inputs'!K105=1),'Model inputs'!K105=1,IF('Model inputs'!K105="","",'Model inputs'!K105=1))),0,IF('DealScope 12-month financial pr'!I19="","",'DealScope 12-month financial pr'!I19)))+'DealScope 12-month financial pr'!J18,0) -> 0 | ... M7: =MAX(IF(IF(IF(IF(ISERROR('Model inputs'!N105=1),'Model inputs'!N105=1,IF('Model inputs'!N105="","",'Model inputs'!N105=1))="",FALSE,IF(ISERROR('Model inputs'!N105=1),'Model inputs'!N105=1,IF('Model inputs'!N105="","",'Model inputs'!N105=1))),0,IF('DealScope 12-month financial pr'!L19="","",'DealScope 12-month financial pr'!L19))="",0,IF(IF(IF(ISERROR('Model inputs'!N105=1),'Model inputs'!N105=1,IF('Model inputs'!N105="","",'Model inputs'!N105=1))="",FALSE,IF(ISERROR('Model inputs'!N105=1),'Model inputs'!N105=1,IF('Model inputs'!N105="","",'Model inputs'!N105=1))),0,IF('DealScope 12-month financial pr'!L19="","",'DealScope 12-month financial pr'!L19)))+'DealScope 12-month financial pr'!M18,0) -> 0
A8: Deferred subscription revenue | B8: =IF(IF(IF(IF(ISERROR('Model inputs'!C105=1),'Model inputs'!C105=1,IF('Model inputs'!C105="","",'Model inputs'!C105=1))="",FALSE,IF(ISERROR('Model inputs'!C105=1),'Model inputs'!C105=1,IF('Model inputs'!C105="","",'Model inputs'!C105=1))),0,IF('Model inputs'!B49="","",'Model inputs'!B49))="",0,IF(IF(IF(ISERROR('Model inputs'!C105=1),'Model inputs'!C105=1,IF('Model inputs'!C105="","",'Model inputs'!C105=1))="",FALSE,IF(ISERROR('Model inputs'!C105=1),'Model inputs'!C105=1,IF('Model inputs'!C105="","",'Model inputs'!C105=1))),0,IF('Model inputs'!B49="","",'Model inputs'!B49)))+'DealScope 12-month financial pr'!B16-'DealScope 12-month financial pr'!B7 -> 27500 | C8: =IF(IF(IF(IF(ISERROR('Model inputs'!D105=1),'Model inputs'!D105=1,IF('Model inputs'!D105="","",'Model inputs'!D105=1))="",FALSE,IF(ISERROR('Model inputs'!D105=1),'Model inputs'!D105=1,IF('Model inputs'!D105="","",'Model inputs'!D105=1))),0,IF('DealScope conditional cash and'!B8="","",'DealScope conditional cash and'!B8))="",0,IF(IF(IF(ISERROR('Model inputs'!D105=1),'Model inputs'!D105=1,IF('Model inputs'!D105="","",'Model inputs'!D105=1))="",FALSE,IF(ISERROR('Model inputs'!D105=1),'Model inputs'!D105=1,IF('Model inputs'!D105="","",'Model inputs'!D105=1))),0,IF('DealScope conditional cash and'!B8="","",'DealScope conditional cash and'!B8)))+'DealScope 12-month financial pr'!C16-'DealScope 12-month financial pr'!C7 -> 52500 | D8: =IF(IF(IF(IF(ISERROR('Model inputs'!E105=1),'Model inputs'!E105=1,IF('Model inputs'!E105="","",'Model inputs'!E105=1))="",FALSE,IF(ISERROR('Model inputs'!E105=1),'Model inputs'!E105=1,IF('Model inputs'!E105="","",'Model inputs'!E105=1))),0,IF('DealScope conditional cash and'!C8="","",'DealScope conditional cash and'!C8))="",0,IF(IF(IF(ISERROR('Model inputs'!E105=1),'Model inputs'!E105=1,IF('Model inputs'!E105="","",'Model inputs'!E105=1))="",FALSE,IF(ISERROR('Model inputs'!E105=1),'Model inputs'!E105=1,IF('Model inputs'!E105="","",'Model inputs'!E105=1))),0,IF('DealScope conditional cash and'!C8="","",'DealScope conditional cash and'!C8)))+'DealScope 12-month financial pr'!D16-'DealScope 12-month financial pr'!D7 -> 75000 | E8: =IF(IF(IF(IF(ISERROR('Model inputs'!F105=1),'Model inputs'!F105=1,IF('Model inputs'!F105="","",'Model inputs'!F105=1))="",FALSE,IF(ISERROR('Model inputs'!F105=1),'Model inputs'!F105=1,IF('Model inputs'!F105="","",'Model inputs'!F105=1))),0,IF('DealScope conditional cash and'!D8="","",'DealScope conditional cash and'!D8))="",0,IF(IF(IF(ISERROR('Model inputs'!F105=1),'Model inputs'!F105=1,IF('Model inputs'!F105="","",'Model inputs'!F105=1))="",FALSE,IF(ISERROR('Model inputs'!F105=1),'Model inputs'!F105=1,IF('Model inputs'!F105="","",'Model inputs'!F105=1))),0,IF('DealScope conditional cash and'!D8="","",'DealScope conditional cash and'!D8)))+'DealScope 12-month financial pr'!E16-'DealScope 12-month financial pr'!E7 -> 95000 | F8: =IF(IF(IF(IF(ISERROR('Model inputs'!G105=1),'Model inputs'!G105=1,IF('Model inputs'!G105="","",'Model inputs'!G105=1))="",FALSE,IF(ISERROR('Model inputs'!G105=1),'Model inputs'!G105=1,IF('Model inputs'!G105="","",'Model inputs'!G105=1))),0,IF('DealScope conditional cash and'!E8="","",'DealScope conditional cash and'!E8))="",0,IF(IF(IF(ISERROR('Model inputs'!G105=1),'Model inputs'!G105=1,IF('Model inputs'!G105="","",'Model inputs'!G105=1))="",FALSE,IF(ISERROR('Model inputs'!G105=1),'Model inputs'!G105=1,IF('Model inputs'!G105="","",'Model inputs'!G105=1))),0,IF('DealScope conditional cash and'!E8="","",'DealScope conditional cash and'!E8)))+'DealScope 12-month financial pr'!F16-'DealScope 12-month financial pr'!F7 -> 112500 | G8: =IF(IF(IF(IF(ISERROR('Model inputs'!H105=1),'Model inputs'!H105=1,IF('Model inputs'!H105="","",'Model inputs'!H105=1))="",FALSE,IF(ISERROR('Model inputs'!H105=1),'Model inputs'!H105=1,IF('Model inputs'!H105="","",'Model inputs'!H105=1))),0,IF('DealScope conditional cash and'!F8="","",'DealScope conditional cash and'!F8))="",0,IF(IF(IF(ISERROR('Model inputs'!H105=1),'Model inputs'!H105=1,IF('Model inputs'!H105="","",'Model inputs'!H105=1))="",FALSE,IF(ISERROR('Model inputs'!H105=1),'Model inputs'!H105=1,IF('Model inputs'!H105="","",'Model inputs'!H105=1))),0,IF('DealScope conditional cash and'!F8="","",'DealScope conditional cash and'!F8)))+'DealScope 12-month financial pr'!G16-'DealScope 12-month financial pr'!G7 -> 127500 | H8: =IF(IF(IF(IF(ISERROR('Model inputs'!I105=1),'Model inputs'!I105=1,IF('Model inputs'!I105="","",'Model inputs'!I105=1))="",FALSE,IF(ISERROR('Model inputs'!I105=1),'Model inputs'!I105=1,IF('Model inputs'!I105="","",'Model inputs'!I105=1))),0,IF('DealScope conditional cash and'!G8="","",'DealScope conditional cash and'!G8))="",0,IF(IF(IF(ISERROR('Model inputs'!I105=1),'Model inputs'!I105=1,IF('Model inputs'!I105="","",'Model inputs'!I105=1))="",FALSE,IF(ISERROR('Model inputs'!I105=1),'Model inputs'!I105=1,IF('Model inputs'!I105="","",'Model inputs'!I105=1))),0,IF('DealScope conditional cash and'!G8="","",'DealScope conditional cash and'!G8)))+'DealScope 12-month financial pr'!H16-'DealScope 12-month financial pr'!H7 -> 140000 | I8: =IF(IF(IF(IF(ISERROR('Model inputs'!J105=1),'Model inputs'!J105=1,IF('Model inputs'!J105="","",'Model inputs'!J105=1))="",FALSE,IF(ISERROR('Model inputs'!J105=1),'Model inputs'!J105=1,IF('Model inputs'!J105="","",'Model inputs'!J105=1))),0,IF('DealScope conditional cash and'!H8="","",'DealScope conditional cash and'!H8))="",0,IF(IF(IF(ISERROR('Model inputs'!J105=1),'Model inputs'!J105=1,IF('Model inputs'!J105="","",'Model inputs'!J105=1))="",FALSE,IF(ISERROR('Model inputs'!J105=1),'Model inputs'!J105=1,IF('Model inputs'!J105="","",'Model inputs'!J105=1))),0,IF('DealScope conditional cash and'!H8="","",'DealScope conditional cash and'!H8)))+'DealScope 12-month financial pr'!I16-'DealScope 12-month financial pr'!I7 -> 150000 | J8: =IF(IF(IF(IF(ISERROR('Model inputs'!K105=1),'Model inputs'!K105=1,IF('Model inputs'!K105="","",'Model inputs'!K105=1))="",FALSE,IF(ISERROR('Model inputs'!K105=1),'Model inputs'!K105=1,IF('Model inputs'!K105="","",'Model inputs'!K105=1))),0,IF('DealScope conditional cash and'!I8="","",'DealScope conditional cash and'!I8))="",0,IF(IF(IF(ISERROR('Model inputs'!K105=1),'Model inputs'!K105=1,IF('Model inputs'!K105="","",'Model inputs'!K105=1))="",FALSE,IF(ISERROR('Model inputs'!K105=1),'Model inputs'!K105=1,IF('Model inputs'!K105="","",'Model inputs'!K105=1))),0,IF('DealScope conditional cash and'!I8="","",'DealScope conditional cash and'!I8)))+'DealScope 12-month financial pr'!J16-'DealScope 12-month financial pr'!J7 -> 157500 | ... M8: =IF(IF(IF(IF(ISERROR('Model inputs'!N105=1),'Model inputs'!N105=1,IF('Model inputs'!N105="","",'Model inputs'!N105=1))="",FALSE,IF(ISERROR('Model inputs'!N105=1),'Model inputs'!N105=1,IF('Model inputs'!N105="","",'Model inputs'!N105=1))),0,IF('DealScope conditional cash and'!L8="","",'DealScope conditional cash and'!L8))="",0,IF(IF(IF(ISERROR('Model inputs'!N105=1),'Model inputs'!N105=1,IF('Model inputs'!N105="","",'Model inputs'!N105=1))="",FALSE,IF(ISERROR('Model inputs'!N105=1),'Model inputs'!N105=1,IF('Model inputs'!N105="","",'Model inputs'!N105=1))),0,IF('DealScope conditional cash and'!L8="","",'DealScope conditional cash and'!L8)))+'DealScope 12-month financial pr'!M16-'DealScope 12-month financial pr'!M7 -> 165000

Sheet DealScope forecast overview
A1: DealScope forecast overview
A2: DealScope — Financial projection · Growth
A4: Variable / dimension | B4: Value
A5: Forecast earned revenue | B5: =SUM('Model inputs'!B947,'Model inputs'!B948) -> 390000
A6: Forecast cash collections | B6: =SUM('Model inputs'!B949,'Model inputs'!B950) -> 555000
A7: Forecast audits | B7: =SUM('Model inputs'!B951,'Model inputs'!B952) -> 390
A8: Forecast delivery cost | B8: =SUM('Model inputs'!B953,'Model inputs'!B954) -> 36913.5
A9: Forecast gross profit | B9: ='DealScope forecast overview'!B5-'DealScope forecast overview'!B8 -> 353086.5
A10: Forecast gross margin | B10: =IFERROR('DealScope forecast overview'!B9/'DealScope forecast overview'!B5,"") -> 0.90535
A11: Forecast contribution profit | B11: =SUM('Model inputs'!B955,'Model inputs'!B956) -> 338461.5
A12: Forecast contribution margin | B12: =IFERROR('DealScope forecast overview'!B11/'DealScope forecast overview'!B5,"") -> 0.86785
A13: Forecast net cash burn | B13: =SUM('Model inputs'!B957,'Model inputs'!B958) -> -486011.5
A14: Average monthly net cash burn | B14: ='DealScope forecast overview'!B13/'Model inputs'!O63 -> -40500.958
A15: Conditional runway months | B15: =IF(IF(IF(IFERROR(IF(ISERROR('Model inputs'!O28=1),'Model inputs'!O28=1,IF('Model inputs'!O28="","",'Model inputs'!O28=1))=FALSE,FALSE),FALSE,IF(IFERROR('Model inputs'!B934=FALSE,FALSE),FALSE,IF(OR(IF(ISERROR('Model inputs'!O28=1),'Model inputs'!O28=1,IF('Model inputs'!O28="","",'Model inputs'!O28=1))="",'Model inputs'!B934=""),"",AND(IF(ISERROR('Model inputs'!O28=1),'Model inputs'!O28=1,IF('Model inputs'!O28="","",'Model inputs'!O28=1)),'Model inputs'!B934))))="",FALSE,IF(IFERROR(IF(ISERROR('Model inputs'!O28=1),'Model inputs'!O28=1,IF('Model inputs'!O28="","",'Model inputs'!O28=1))=FALSE,FALSE),FALSE,IF(IFERROR('Model inputs'!B934=FALSE,FALSE),FALSE,IF(OR(IF(ISERROR('Model inputs'!O28=1),'Model inputs'!O28=1,IF('Model inputs'!O28="","",'Model inputs'!O28=1))="",'Model inputs'!B934=""),"",AND(IF(ISERROR('Model inputs'!O28=1),'Model inputs'!O28=1,IF('Model inputs'!O28="","",'Model inputs'!O28=1)),'Model inputs'!B934))))),IF('Model inputs'!O18="",0,'Model inputs'!O18)/'DealScope forecast overview'!B14,"")
A16: Peak modeled funding need | B16: =MAX(IF(IF(AND('Model inputs'!P65<=DATE(2026,10,1),DATE(2026,10,1)<=EDATE('Model inputs'!P65,'Model inputs'!O63-1*1))="",FALSE,AND('Model inputs'!P65<=DATE(2026,10,1),DATE(2026,10,1)<=EDATE('Model inputs'!P65,'Model inputs'!O63-1*1))),'DealScope 12-month financial pr'!B20,""),IF(IF(AND('Model inputs'!P65<=DATE(2026,11,1),DATE(2026,11,1)<=EDATE('Model inputs'!P65,'Model inputs'!O63-1*1))="",FALSE,AND('Model inputs'!P65<=DATE(2026,11,1),DATE(2026,11,1)<=EDATE('Model inputs'!P65,'Model inputs'!O63-1*1))),'DealScope 12-month financial pr'!C20,""),IF(IF(AND('Model inputs'!P65<=DATE(2026,12,1),DATE(2026,12,1)<=EDATE('Model inputs'!P65,'Model inputs'!O63-1*1))="",FALSE,AND('Model inputs'!P65<=DATE(2026,12,1),DATE(2026,12,1)<=EDATE('Model inputs'!P65,'Model inputs'!O63-1*1))),'DealScope 12-month financial pr'!D20,""),IF(IF(AND('Model inputs'!P65<=DATE(2027,1,1),DATE(2027,1,1)<=EDATE('Model inputs'!P65,'Model inputs'!O63-1*1))="",FALSE,AND('Model inputs'!P65<=DATE(2027,1,1),DATE(2027,1,1)<=EDATE('Model inputs'!P65,'Model inputs'!O63-1*1))),'DealScope 12-month financial pr'!E20,""),IF(IF(AND('Model inputs'!P65<=DATE(2027,2,1),DATE(2027,2,1)<=EDATE('Model inputs'!P65,'Model inputs'!O63-1*1))="",FALSE,AND('Model inputs'!P65<=DATE(2027,2,1),DATE(2027,2,1)<=EDATE('Model inputs'!P65,'Model inputs'!O63-1*1))),'DealScope 12-month financial pr'!F20,""),IF(IF(AND('Model inputs'!P65<=DATE(2027,3,1),DATE(2027,3,1)<=EDATE('Model inputs'!P65,'Model inputs'!O63-1*1))="",FALSE,AND('Model inputs'!P65<=DATE(2027,3,1),DATE(2027,3,1)<=EDATE('Model inputs'!P65,'Model inputs'!O63-1*1))),'DealScope 12-month financial pr'!G20,""),IF(IF(AND('Model inputs'!P65<=DATE(2027,4,1),DATE(2027,4,1)<=EDATE('Model inputs'!P65,'Model inputs'!O63-1*1))="",FALSE,AND('Model inputs'!P65<=DATE(2027,4,1),DATE(2027,4,1)<=EDATE('Model inputs'!P65,'Model inputs'!O63-1*1))),'DealScope 12-month financial pr'!H20,""),IF(IF(AND('Model inputs'!P65<=DATE(2027,5,1),DATE(2027,5,1)<=EDATE('Model inputs'!P65,'Model inputs'!O63-1*1))="",FALSE,AND('Model inputs'!P65<=DATE(2027,5,1),DATE(2027,5,1)<=EDATE('Model inputs'!P65,'Model inputs'!O63-1*1))),'DealScope 12-month financial pr'!I20,""),IF(IF(AND('Model inputs'!P65<=DATE(2027,6,1),DATE(2027,6,1)<=EDATE('Model inputs'!P65,'Model inputs'!O63-1*1))="",FALSE,AND('Model inputs'!P65<=DATE(2027,6,1),DATE(2027,6,1)<=EDATE('Model inputs'!P65,'Model inputs'!O63-1*1))),'DealScope 12-month financial pr'!J20,""),IF(IF(AND('Model inputs'!P65<=DATE(2027,7,1),DATE(2027,7,1)<=EDATE('Model inputs'!P65,'Model inputs'!O63-1*1))="",FALSE,AND('Model inputs'!P65<=DATE(2027,7,1),DATE(2027,7,1)<=EDATE('Model inputs'!P65,'Model inputs'!O63-1*1))),'DealScope 12-month financial pr'!K20,""),IF(IF(AND('Model inputs'!P65<=DATE(2027,8,1),DATE(2027,8,1)<=EDATE('Model inputs'!P65,'Model inputs'!O63-1*1))="",FALSE,AND('Model inputs'!P65<=DATE(2027,8,1),DATE(2027,8,1)<=EDATE('Model inputs'!P65,'Model inputs'!O63-1*1))),'DealScope 12-month financial pr'!L20,""),IF(IF(AND('Model inputs'!P65<=DATE(2027,9,1),DATE(2027,9,1)<=EDATE('Model inputs'!P65,'Model inputs'!O63-1*1))="",FALSE,AND('Model inputs'!P65<=DATE(2027,9,1),DATE(2027,9,1)<=EDATE('Model inputs'!P65,'Model inputs'!O63-1*1))),'DealScope 12-month financial pr'!M20,""),IF(IF(AND('Model inputs'!P65<=DATE(2026,1,1),DATE(2026,1,1)<=EDATE('Model inputs'!P65,'Model inputs'!O63-1*1))="",FALSE,AND('Model inputs'!P65<=DATE(2026,1,1),DATE(2026,1,1)<=EDATE('Model inputs'!P65,'Model inputs'!O63-1*1))),'Model inputs'!Q46,""),IF(IF(AND('Model inputs'!P65<=DATE(2026,2,1),DATE(2026,2,1)<=EDATE('Model inputs'!P65,'Model inputs'!O63-1*1))="",FALSE,AND('Model inputs'!P65<=DATE(2026,2,1),DATE(2026,2,1)<=EDATE('Model inputs'!P65,'Model inputs'!O63-1*1))),'Model inputs'!R46,""),IF(IF(AND('Model inputs'!P65<=DATE(2026,3,1),DATE(2026,3,1)<=EDATE('Model inputs'!P65,'Model inputs'!O63-1*1))="",FALSE,AND('Model inputs'!P65<=DATE(2026,3,1),DATE(2026,3,1)<=EDATE('Model inputs'!P65,'Model inputs'!O63-1*1))),'Model inputs'!S46,""),IF(IF(AND('Model inputs'!P65<=DATE(2026,4,1),DATE(2026,4,1)<=EDATE('Model inputs'!P65,'Model inputs'!O63-1*1))="",FALSE,AND('Model inputs'!P65<=DATE(2026,4,1),DATE(2026,4,1)<=EDATE('Model inputs'!P65,'Model inputs'!O63-1*1))),'Model inputs'!T46,""),IF(IF(AND('Model inputs'!P65<=DATE(2026,5,1),DATE(2026,5,1)<=EDATE('Model inputs'!P65,'Model inputs'!O63-1*1))="",FALSE,AND('Model inputs'!P65<=DATE(2026,5,1),DATE(2026,5,1)<=EDATE('Model inputs'!P65,'Model inputs'!O63-1*1))),'Model inputs'!U46,""),IF(IF(AND('Model inputs'!P65<=DATE(2026,6,1),DATE(2026,6,1)<=EDATE('Model inputs'!P65,'Model inputs'!O63-1*1))="",FALSE,AND('Model inputs'!P65<=DATE(2026,6,1),DATE(2026,6,1)<=EDATE('Model inputs'!P65,'Model inputs'!O63-1*1))),'Model inputs'!V46,""),IF(IF(AND('Model inputs'!P65<=DATE(2026,7,1),DATE(2026,7,1)<=EDATE('Model inputs'!P65,'Model inputs'!O63-1*1))="",FALSE,AND('Model inputs'!P65<=DATE(2026,7,1),DATE(2026,7,1)<=EDATE('Model inputs'!P65,'Model inputs'!O63-1*1))),'Model inputs'!W46,""),IF(IF(AND('Model inputs'!P65<=DATE(2026,8,1),DATE(2026,8,1)<=EDATE('Model inputs'!P65,'Model inputs'!O63-1*1))="",FALSE,AND('Model inputs'!P65<=DATE(2026,8,1),DATE(2026,8,1)<=EDATE('Model inputs'!P65,'Model inputs'!O63-1*1))),'Model inputs'!X46,""),IF(IF(AND('Model inputs'!P65<=DATE(2026,9,1),DATE(2026,9,1)<=EDATE('Model inputs'!P65,'Model inputs'!O63-1*1))="",FALSE,AND('Model inputs'!P65<=DATE(2026,9,1),DATE(2026,9,1)<=EDATE('Model inputs'!P65,'Model inputs'!O63-1*1))),'Model inputs'!B46,""),IF(IF(AND('Model inputs'!P65<=DATE(2027,10,1),DATE(2027,10,1)<=EDATE('Model inputs'!P65,'Model inputs'!O63-1*1))="",FALSE,AND('Model inputs'!P65<=DATE(2027,10,1),DATE(2027,10,1)<=EDATE('Model inputs'!P65,'Model inputs'!O63-1*1))),'Model inputs'!Y46,""),IF(IF(AND('Model inputs'!P65<=DATE(2027,11,1),DATE(2027,11,1)<=EDATE('Model inputs'!P65,'Model inputs'!O63-1*1))="",FALSE,AND('Model inputs'!P65<=DATE(2027,11,1),DATE(2027,11,1)<=EDATE('Model inputs'!P65,'Model inputs'!O63-1*1))),'Model inputs'!Z46,""),IF(IF(AND('Model inputs'!P65<=DATE(2027,12,1),DATE(2027,12,1)<=EDATE('Model inputs'!P65,'Model inputs'!O63-1*1))="",FALSE,AND('Model inputs'!P65<=DATE(2027,12,1),DATE(2027,12,1)<=EDATE('Model inputs'!P65,'Model inputs'!O63-1*1))),'Model inputs'!AA46,"")) -> 0
A17: Total reviewer hours | B17: =SUM('Model inputs'!B959,'Model inputs'!B960) -> 585

Sheet Model inputs
A1: Model inputs
A2: Integration values are aggregated snapshots; raw source records are not included.
A4: Variables
A5: Variable / segment | B5: 2026-09 | C5: 2026-10 | D5: 2026-11 | E5: 2026-12 | F5: 2027-01 | G5: 2027-02 | H5: 2027-03 | I5: 2027-04 | J5: 2027-05 | K5: 2027-06 | L5: 2027-07 | M5: 2027-08 | N5: 2027-09 | O5: Value | P5: Value | Q5: 2026-01 | R5: 2026-02 | S5: 2026-03 | T5: 2026-04 | U5: 2026-05 | V5: 2026-06 | W5: 2026-07 | X5: 2026-08 | Y5: 2027-10 | Z5: 2027-11 | AA5: 2027-12
A6: Account support cost | B6: =SUM('Model inputs'!B7,'Model inputs'!B8,'Model inputs'!B9,'Model inputs'!B10,'Model inputs'!B11) -> 0 | C6: ="" | D6: ="" | E6: ="" | F6: ="" | G6: ="" | H6: ="" | I6: ="" | J6: ="" | ... N6: =""
A7: Account support cost > Annual deal-team | B7: =0 -> 0 | C7: ='Model inputs'!C143*'Model inputs'!O113*'Model inputs'!O148 -> 37.5 | D7: ='Model inputs'!D143*'Model inputs'!O113*'Model inputs'!O148 -> 75 | E7: ='Model inputs'!E143*'Model inputs'!O113*'Model inputs'!O148 -> 112.5 | F7: ='Model inputs'!F143*'Model inputs'!O113*'Model inputs'!O148 -> 150 | G7: ='Model inputs'!G143*'Model inputs'!O113*'Model inputs'!O148 -> 187.5 | H7: ='Model inputs'!H143*'Model inputs'!O113*'Model inputs'!O148 -> 225 | I7: ='Model inputs'!I143*'Model inputs'!O113*'Model inputs'!O148 -> 262.5 | J7: ='Model inputs'!J143*'Model inputs'!O113*'Model inputs'!O148 -> 300 | K7: ='Model inputs'!K143*'Model inputs'!O113*'Model inputs'!O148 -> 337.5 | L7: ='Model inputs'!L143*'Model inputs'!O113*'Model inputs'!O148 -> 375 | M7: ='Model inputs'!M143*'Model inputs'!O113*'Model inputs'!O148 -> 412.5 | N7: ='Model inputs'!N143*'Model inputs'!O113*'Model inputs'!O148 -> 450
A8: Account support cost > Hybrid | B8: =0 -> 0 | C8: ='Model inputs'!C143*'Model inputs'!O113*'Model inputs'!O148 -> 37.5 | D8: ='Model inputs'!D143*'Model inputs'!O113*'Model inputs'!O148 -> 75 | E8: ='Model inputs'!E143*'Model inputs'!O113*'Model inputs'!O148 -> 112.5 | F8: ='Model inputs'!F143*'Model inputs'!O113*'Model inputs'!O148 -> 150 | G8: ='Model inputs'!G143*'Model inputs'!O113*'Model inputs'!O148 -> 187.5 | H8: ='Model inputs'!H143*'Model inputs'!O113*'Model inputs'!O148 -> 225 | I8: ='Model inputs'!I143*'Model inputs'!O113*'Model inputs'!O148 -> 262.5 | J8: ='Model inputs'!J143*'Model inputs'!O113*'Model inputs'!O148 -> 300 | K8: ='Model inputs'!K143*'Model inputs'!O113*'Model inputs'!O148 -> 337.5 | L8: ='Model inputs'!L143*'Model inputs'!O113*'Model inputs'!O148 -> 375 | M8: ='Model inputs'!M143*'Model inputs'!O113*'Model inputs'!O148 -> 412.5 | N8: ='Model inputs'!N143*'Model inputs'!O113*'Model inputs'!O148 -> 450
A9: Account support cost > Per audit — base | B9: =0 -> 0 | C9: ='Model inputs'!C143*'Model inputs'!O113*'Model inputs'!O148 -> 37.5 | D9: ='Model inputs'!D143*'Model inputs'!O113*'Model inputs'!O148 -> 75 | E9: ='Model inputs'!E143*'Model inputs'!O113*'Model inputs'!O148 -> 112.5 | F9: ='Model inputs'!F143*'Model inputs'!O113*'Model inputs'!O148 -> 150 | G9: ='Model inputs'!G143*'Model inputs'!O113*'Model inputs'!O148 -> 187.5 | H9: ='Model inputs'!H143*'Model inputs'!O113*'Model inputs'!O148 -> 225 | I9: ='Model inputs'!I143*'Model inputs'!O113*'Model inputs'!O148 -> 262.5 | J9: ='Model inputs'!J143*'Model inputs'!O113*'Model inputs'!O148 -> 300 | K9: ='Model inputs'!K143*'Model inputs'!O113*'Model inputs'!O148 -> 337.5 | L9: ='Model inputs'!L143*'Model inputs'!O113*'Model inputs'!O148 -> 375 | M9: ='Model inputs'!M143*'Model inputs'!O113*'Model inputs'!O148 -> 412.5 | N9: ='Model inputs'!N143*'Model inputs'!O113*'Model inputs'!O148 -> 450
A10: Account support cost > Per audit — high | B10: =0 -> 0 | C10: ='Model inputs'!C143*'Model inputs'!O113*'Model inputs'!O148 -> 37.5 | D10: ='Model inputs'!D143*'Model inputs'!O113*'Model inputs'!O148 -> 75 | E10: ='Model inputs'!E143*'Model inputs'!O113*'Model inputs'!O148 -> 112.5 | F10: ='Model inputs'!F143*'Model inputs'!O113*'Model inputs'!O148 -> 150 | G10: ='Model inputs'!G143*'Model inputs'!O113*'Model inputs'!O148 -> 187.5 | H10: ='Model inputs'!H143*'Model inputs'!O113*'Model inputs'!O148 -> 225 | I10: ='Model inputs'!I143*'Model inputs'!O113*'Model inputs'!O148 -> 262.5 | J10: ='Model inputs'!J143*'Model inputs'!O113*'Model inputs'!O148 -> 300 | K10: ='Model inputs'!K143*'Model inputs'!O113*'Model inputs'!O148 -> 337.5 | L10: ='Model inputs'!L143*'Model inputs'!O113*'Model inputs'!O148 -> 375 | M10: ='Model inputs'!M143*'Model inputs'!O113*'Model inputs'!O148 -> 412.5 | N10: ='Model inputs'!N143*'Model inputs'!O113*'Model inputs'!O148 -> 450
A11: Account support cost > Per audit — low | B11: =0 -> 0 | C11: ='Model inputs'!C143*'Model inputs'!O113*'Model inputs'!O148 -> 37.5 | D11: ='Model inputs'!D143*'Model inputs'!O113*'Model inputs'!O148 -> 75 | E11: ='Model inputs'!E143*'Model inputs'!O113*'Model inputs'!O148 -> 112.5 | F11: ='Model inputs'!F143*'Model inputs'!O113*'Model inputs'!O148 -> 150 | G11: ='Model inputs'!G143*'Model inputs'!O113*'Model inputs'!O148 -> 187.5 | H11: ='Model inputs'!H143*'Model inputs'!O113*'Model inputs'!O148 -> 225 | I11: ='Model inputs'!I143*'Model inputs'!O113*'Model inputs'!O148 -> 262.5 | J11: ='Model inputs'!J143*'Model inputs'!O113*'Model inputs'!O148 -> 300 | K11: ='Model inputs'!K143*'Model inputs'!O113*'Model inputs'!O148 -> 337.5 | L11: ='Model inputs'!L143*'Model inputs'!O113*'Model inputs'!O148 -> 375 | M11: ='Model inputs'!M143*'Model inputs'!O113*'Model inputs'!O148 -> 412.5 | N11: ='Model inputs'!N143*'Model inputs'!O113*'Model inputs'!O148 -> 450
A12: Audits delivered | B12: =SUM('Model inputs'!B13,'Model inputs'!B14,'Model inputs'!B15,'Model inputs'!B16,'Model inputs'!B17) -> 0 | C12: ="" | D12: ="" | E12: ="" | F12: ="" | G12: ="" | H12: ="" | I12: ="" | J12: ="" | ... N12: =""
A13: Audits delivered > Annual deal-team | B13: =0 -> 0 | C13: ='Model inputs'!C143*'Model inputs'!O119 -> 5 | D13: ='Model inputs'!D143*'Model inputs'!O119 -> 10 | E13: ='Model inputs'!E143*'Model inputs'!O119 -> 15 | F13: ='Model inputs'!F143*'Model inputs'!O119 -> 20 | G13: ='Model inputs'!G143*'Model inputs'!O119 -> 25 | H13: ='Model inputs'!H143*'Model inputs'!O119 -> 30 | I13: ='Model inputs'!I143*'Model inputs'!O119 -> 35 | J13: ='Model inputs'!J143*'Model inputs'!O119 -> 40 | K13: ='Model inputs'!K143*'Model inputs'!O119 -> 45 | L13: ='Model inputs'!L143*'Model inputs'!O119 -> 50 | M13: ='Model inputs'!M143*'Model inputs'!O119 -> 55 | N13: ='Model inputs'!N143*'Model inputs'!O119 -> 60
A14: Audits delivered > Hybrid | B14: =0 -> 0 | C14: ='Model inputs'!C143*'Model inputs'!O120 -> 5 | D14: ='Model inputs'!D143*'Model inputs'!O120 -> 10 | E14: ='Model inputs'!E143*'Model inputs'!O120 -> 15 | F14: ='Model inputs'!F143*'Model inputs'!O120 -> 20 | G14: ='Model inputs'!G143*'Model inputs'!O120 -> 25 | H14: ='Model inputs'!H143*'Model inputs'!O120 -> 30 | I14: ='Model inputs'!I143*'Model inputs'!O120 -> 35 | J14: ='Model inputs'!J143*'Model inputs'!O120 -> 40 | K14: ='Model inputs'!K143*'Model inputs'!O120 -> 45 | L14: ='Model inputs'!L143*'Model inputs'!O120 -> 50 | M14: ='Model inputs'!M143*'Model inputs'!O120 -> 55 | N14: ='Model inputs'!N143*'Model inputs'!O120 -> 60
A15: Audits delivered > Per audit — base | B15: =0 -> 0 | C15: ='Model inputs'!C143*'Model inputs'!O121 -> 5 | D15: ='Model inputs'!D143*'Model inputs'!O121 -> 10 | E15: ='Model inputs'!E143*'Model inputs'!O121 -> 15 | F15: ='Model inputs'!F143*'Model inputs'!O121 -> 20 | G15: ='Model inputs'!G143*'Model inputs'!O121 -> 25 | H15: ='Model inputs'!H143*'Model inputs'!O121 -> 30 | I15: ='Model inputs'!I143*'Model inputs'!O121 -> 35 | J15: ='Model inputs'!J143*'Model inputs'!O121 -> 40 | K15: ='Model inputs'!K143*'Model inputs'!O121 -> 45 | L15: ='Model inputs'!L143*'Model inputs'!O121 -> 50 | M15: ='Model inputs'!M143*'Model inputs'!O121 -> 55 | N15: ='Model inputs'!N143*'Model inputs'!O121 -> 60
A16: Audits delivered > Per audit — high | B16: =0 -> 0 | C16: ='Model inputs'!C143*'Model inputs'!O122 -> 5 | D16: ='Model inputs'!D143*'Model inputs'!O122 -> 10 | E16: ='Model inputs'!E143*'Model inputs'!O122 -> 15 | F16: ='Model inputs'!F143*'Model inputs'!O122 -> 20 | G16: ='Model inputs'!G143*'Model inputs'!O122 -> 25 | H16: ='Model inputs'!H143*'Model inputs'!O122 -> 30 | I16: ='Model inputs'!I143*'Model inputs'!O122 -> 35 | J16: ='Model inputs'!J143*'Model inputs'!O122 -> 40 | K16: ='Model inputs'!K143*'Model inputs'!O122 -> 45 | L16: ='Model inputs'!L143*'Model inputs'!O122 -> 50 | M16: ='Model inputs'!M143*'Model inputs'!O122 -> 55 | N16: ='Model inputs'!N143*'Model inputs'!O122 -> 60
A17: Audits delivered > Per audit — low | B17: =0 -> 0 | C17: ='Model inputs'!C143*'Model inputs'!O123 -> 5 | D17: ='Model inputs'!D143*'Model inputs'!O123 -> 10 | E17: ='Model inputs'!E143*'Model inputs'!O123 -> 15 | F17: ='Model inputs'!F143*'Model inputs'!O123 -> 20 | G17: ='Model inputs'!G143*'Model inputs'!O123 -> 25 | H17: ='Model inputs'!H143*'Model inputs'!O123 -> 30 | I17: ='Model inputs'!I143*'Model inputs'!O123 -> 35 | J17: ='Model inputs'!J143*'Model inputs'!O123 -> 40 | K17: ='Model inputs'!K143*'Model inputs'!O123 -> 45 | L17: ='Model inputs'!L143*'Model inputs'!O123 -> 50 | M17: ='Model inputs'!M143*'Model inputs'!O123 -> 55 | N17: ='Model inputs'!N143*'Model inputs'!O123 -> 60
A18: Available opening cash · DealScope 12-month financial projection | O18: =""
A19: Available opening cash · DealScope forecast overview | P19: =""
A20: Average monthly net cash burn · DealScope conditional cash and runway | O20: ='Model inputs'!P115/'Model inputs'!O63 -> -40500.958
A21: Average monthly net cash burn · DealScope forecast overview | P21: ='Model inputs'!P115/'Model inputs'!O63 -> -40500.958
A22: Cash collections | B22: =SUM('Model inputs'!B23,'Model inputs'!B24,'Model inputs'!B25,'Model inputs'!B26,'Model inputs'!B27) -> 0 | C22: ="" | D22: ="" | E22: ="" | F22: ="" | G22: ="" | H22: ="" | I22: ="" | J22: ="" | ... N22: =""
A23: Cash collections > Annual deal-team | B23: =0 -> 0 | C23: ='Model inputs'!C136*'Model inputs'!O150*(1-'Model inputs'!O144)+'Model inputs'!C58-'Model inputs'!C143*'Model inputs'!O150/12*(1-'Model inputs'!O144) -> 32500 | D23: ='Model inputs'!D136*'Model inputs'!O150*(1-'Model inputs'!O144)+'Model inputs'!D58-'Model inputs'!D143*'Model inputs'!O150/12*(1-'Model inputs'!O144) -> 35000 | E23: ='Model inputs'!E136*'Model inputs'!O150*(1-'Model inputs'!O144)+'Model inputs'!E58-'Model inputs'!E143*'Model inputs'!O150/12*(1-'Model inputs'!O144) -> 37500 | F23: ='Model inputs'!F136*'Model inputs'!O150*(1-'Model inputs'!O144)+'Model inputs'!F58-'Model inputs'!F143*'Model inputs'!O150/12*(1-'Model inputs'!O144) -> 40000 | G23: ='Model inputs'!G136*'Model inputs'!O150*(1-'Model inputs'!O144)+'Model inputs'!G58-'Model inputs'!G143*'Model inputs'!O150/12*(1-'Model inputs'!O144) -> 42500 | H23: ='Model inputs'!H136*'Model inputs'!O150*(1-'Model inputs'!O144)+'Model inputs'!H58-'Model inputs'!H143*'Model inputs'!O150/12*(1-'Model inputs'!O144) -> 45000 | I23: ='Model inputs'!I136*'Model inputs'!O150*(1-'Model inputs'!O144)+'Model inputs'!I58-'Model inputs'!I143*'Model inputs'!O150/12*(1-'Model inputs'!O144) -> 47500 | J23: ='Model inputs'!J136*'Model inputs'!O150*(1-'Model inputs'!O144)+'Model inputs'!J58-'Model inputs'!J143*'Model inputs'!O150/12*(1-'Model inputs'!O144) -> 50000 | K23: ='Model inputs'!K136*'Model inputs'!O150*(1-'Model inputs'!O144)+'Model inputs'!K58-'Model inputs'!K143*'Model inputs'!O150/12*(1-'Model inputs'!O144) -> 52500 | L23: ='Model inputs'!L136*'Model inputs'!O150*(1-'Model inputs'!O144)+'Model inputs'!L58-'Model inputs'!L143*'Model inputs'!O150/12*(1-'Model inputs'!O144) -> 55000 | M23: ='Model inputs'!M136*'Model inputs'!O150*(1-'Model inputs'!O144)+'Model inputs'!M58-'Model inputs'!M143*'Model inputs'!O150/12*(1-'Model inputs'!O144) -> 57500 | N23: ='Model inputs'!N136*'Model inputs'!O150*(1-'Model inputs'!O144)+'Model inputs'!N58-'Model inputs'!N143*'Model inputs'!O150/12*(1-'Model inputs'!O144) -> 60000
A24: Cash collections > Hybrid | B24: =0 -> 0 | C24: ='Model inputs'!C136*'Model inputs'!O151*(1-'Model inputs'!O144)+'Model inputs'!C59-'Model inputs'!C143*'Model inputs'!O151/12*(1-'Model inputs'!O144) -> 12500 | D24: ='Model inputs'!D136*'Model inputs'!O151*(1-'Model inputs'!O144)+'Model inputs'!D59-'Model inputs'!D143*'Model inputs'!O151/12*(1-'Model inputs'!O144) -> 17500 | E24: ='Model inputs'!E136*'Model inputs'!O151*(1-'Model inputs'!O144)+'Model inputs'!E59-'Model inputs'!E143*'Model inputs'!O151/12*(1-'Model inputs'!O144) -> 22500 | F24: ='Model inputs'!F136*'Model inputs'!O151*(1-'Model inputs'!O144)+'Model inputs'!F59-'Model inputs'!F143*'Model inputs'!O151/12*(1-'Model inputs'!O144) -> 27500 | G24: ='Model inputs'!G136*'Model inputs'!O151*(1-'Model inputs'!O144)+'Model inputs'!G59-'Model inputs'!G143*'Model inputs'!O151/12*(1-'Model inputs'!O144) -> 32500 | H24: ='Model inputs'!H136*'Model inputs'!O151*(1-'Model inputs'!O144)+'Model inputs'!H59-'Model inputs'!H143*'Model inputs'!O151/12*(1-'Model inputs'!O144) -> 37500 | I24: ='Model inputs'!I136*'Model inputs'!O151*(1-'Model inputs'!O144)+'Model inputs'!I59-'Model inputs'!I143*'Model inputs'!O151/12*(1-'Model inputs'!O144) -> 42500 | J24: ='Model inputs'!J136*'Model inputs'!O151*(1-'Model inputs'!O144)+'Model inputs'!J59-'Model inputs'!J143*'Model inputs'!O151/12*(1-'Model inputs'!O144) -> 47500 | K24: ='Model inputs'!K136*'Model inputs'!O151*(1-'Model inputs'!O144)+'Model inputs'!K59-'Model inputs'!K143*'Model inputs'!O151/12*(1-'Model inputs'!O144) -> 52500 | L24: ='Model inputs'!L136*'Model inputs'!O151*(1-'Model inputs'!O144)+'Model inputs'!L59-'Model inputs'!L143*'Model inputs'!O151/12*(1-'Model inputs'!O144) -> 57500 | M24: ='Model inputs'!M136*'Model inputs'!O151*(1-'Model inputs'!O144)+'Model inputs'!M59-'Model inputs'!M143*'Model inputs'!O151/12*(1-'Model inputs'!O144) -> 62500 | N24: ='Model inputs'!N136*'Model inputs'!O151*(1-'Model inputs'!O144)+'Model inputs'!N59-'Model inputs'!N143*'Model inputs'!O151/12*(1-'Model inputs'!O144) -> 67500
A25: Cash collections > Per audit — base | B25: =0 -> 0 | C25: ='Model inputs'!C136*'Model inputs'!O152*(1-'Model inputs'!O144)+'Model inputs'!C60-'Model inputs'!C143*'Model inputs'!O152/12*(1-'Model inputs'!O144) -> 7500 | D25: ='Model inputs'!D136*'Model inputs'!O152*(1-'Model inputs'!O144)+'Model inputs'!D60-'Model inputs'!D143*'Model inputs'!O152/12*(1-'Model inputs'!O144) -> 15000 | E25: ='Model inputs'!E136*'Model inputs'!O152*(1-'Model inputs'!O144)+'Model inputs'!E60-'Model inputs'!E143*'Model inputs'!O152/12*(1-'Model inputs'!O144) -> 22500 | F25: ='Model inputs'!F136*'Model inputs'!O152*(1-'Model inputs'!O144)+'Model inputs'!F60-'Model inputs'!F143*'Model inputs'!O152/12*(1-'Model inputs'!O144) -> 30000 | G25: ='Model inputs'!G136*'Model inputs'!O152*(1-'Model inputs'!O144)+'Model inputs'!G60-'Model inputs'!G143*'Model inputs'!O152/12*(1-'Model inputs'!O144) -> 37500 | H25: ='Model inputs'!H136*'Model inputs'!O152*(1-'Model inputs'!O144)+'Model inputs'!H60-'Model inputs'!H143*'Model inputs'!O152/12*(1-'Model inputs'!O144) -> 45000 | I25: ='Model inputs'!I136*'Model inputs'!O152*(1-'Model inputs'!O144)+'Model inputs'!I60-'Model inputs'!I143*'Model inputs'!O152/12*(1-'Model inputs'!O144) -> 52500 | J25: ='Model inputs'!J136*'Model inputs'!O152*(1-'Model inputs'!O144)+'Model inputs'!J60-'Model inputs'!J143*'Model inputs'!O152/12*(1-'Model inputs'!O144) -> 60000 | K25: ='Model inputs'!K136*'Model inputs'!O152*(1-'Model inputs'!O144)+'Model inputs'!K60-'Model inputs'!K143*'Model inputs'!O152/12*(1-'Model inputs'!O144) -> 67500 | L25: ='Model inputs'!L136*'Model inputs'!O152*(1-'Model inputs'!O144)+'Model inputs'!L60-'Model inputs'!L143*'Model inputs'!O152/12*(1-'Model inputs'!O144) -> 75000 | M25: ='Model inputs'!M136*'Model inputs'!O152*(1-'Model inputs'!O144)+'Model inputs'!M60-'Model inputs'!M143*'Model inputs'!O152/12*(1-'Model inputs'!O144) -> 82500 | N25: ='Model inputs'!N136*'Model inputs'!O152*(1-'Model inputs'!O144)+'Model inputs'!N60-'Model inputs'!N143*'Model inputs'!O152/12*(1-'Model inputs'!O144) -> 90000
A26: Cash collections > Per audit — high | B26: =0 -> 0 | C26: ='Model inputs'!C136*'Model inputs'!O153*(1-'Model inputs'!O144)+'Model inputs'!C61-'Model inputs'!C143*'Model inputs'!O153/12*(1-'Model inputs'!O144) -> 15000 | D26: ='Model inputs'!D136*'Model inputs'!O153*(1-'Model inputs'!O144)+'Model inputs'!D61-'Model inputs'!D143*'Model inputs'!O153/12*(1-'Model inputs'!O144) -> 30000 | E26: ='Model inputs'!E136*'Model inputs'!O153*(1-'Model inputs'!O144)+'Model inputs'!E61-'Model inputs'!E143*'Model inputs'!O153/12*(1-'Model inputs'!O144) -> 45000 | F26: ='Model inputs'!F136*'Model inputs'!O153*(1-'Model inputs'!O144)+'Model inputs'!F61-'Model inputs'!F143*'Model inputs'!O153/12*(1-'Model inputs'!O144) -> 60000 | G26: ='Model inputs'!G136*'Model inputs'!O153*(1-'Model inputs'!O144)+'Model inputs'!G61-'Model inputs'!G143*'Model inputs'!O153/12*(1-'Model inputs'!O144) -> 75000 | H26: ='Model inputs'!H136*'Model inputs'!O153*(1-'Model inputs'!O144)+'Model inputs'!H61-'Model inputs'!H143*'Model inputs'!O153/12*(1-'Model inputs'!O144) -> 90000 | I26: ='Model inputs'!I136*'Model inputs'!O153*(1-'Model inputs'!O144)+'Model inputs'!I61-'Model inputs'!I143*'Model inputs'!O153/12*(1-'Model inputs'!O144) -> 105000 | J26: ='Model inputs'!J136*'Model inputs'!O153*(1-'Model inputs'!O144)+'Model inputs'!J61-'Model inputs'!J143*'Model inputs'!O153/12*(1-'Model inputs'!O144) -> 120000 | K26: ='Model inputs'!K136*'Model inputs'!O153*(1-'Model inputs'!O144)+'Model inputs'!K61-'Model inputs'!K143*'Model inputs'!O153/12*(1-'Model inputs'!O144) -> 135000 | L26: ='Model inputs'!L136*'Model inputs'!O153*(1-'Model inputs'!O144)+'Model inputs'!L61-'Model inputs'!L143*'Model inputs'!O153/12*(1-'Model inputs'!O144) -> 150000 | M26: ='Model inputs'!M136*'Model inputs'!O153*(1-'Model inputs'!O144)+'Model inputs'!M61-'Model inputs'!M143*'Model inputs'!O153/12*(1-'Model inputs'!O144) -> 165000 | N26: ='Model inputs'!N136*'Model inputs'!O153*(1-'Model inputs'!O144)+'Model inputs'!N61-'Model inputs'!N143*'Model inputs'!O153/12*(1-'Model inputs'!O144) -> 180000
A27: Cash collections > Per audit — low | B27: =0 -> 0 | C27: ='Model inputs'!C136*'Model inputs'!O154*(1-'Model inputs'!O144)+'Model inputs'!C62-'Model inputs'!C143*'Model inputs'!O154/12*(1-'Model inputs'!O144) -> 3750 | D27: ='Model inputs'!D136*'Model inputs'!O154*(1-'Model inputs'!O144)+'Model inputs'!D62-'Model inputs'!D143*'Model inputs'!O154/12*(1-'Model inputs'!O144) -> 7500 | E27: ='Model inputs'!E136*'Model inputs'!O154*(1-'Model inputs'!O144)+'Model inputs'!E62-'Model inputs'!E143*'Model inputs'!O154/12*(1-'Model inputs'!O144) -> 11250 | F27: ='Model inputs'!F136*'Model inputs'!O154*(1-'Model inputs'!O144)+'Model inputs'!F62-'Model inputs'!F143*'Model inputs'!O154/12*(1-'Model inputs'!O144) -> 15000 | G27: ='Model inputs'!G136*'Model inputs'!O154*(1-'Model inputs'!O144)+'Model inputs'!G62-'Model inputs'!G143*'Model inputs'!O154/12*(1-'Model inputs'!O144) -> 18750 | H27: ='Model inputs'!H136*'Model inputs'!O154*(1-'Model inputs'!O144)+'Model inputs'!H62-'Model inputs'!H143*'Model inputs'!O154/12*(1-'Model inputs'!O144) -> 22500 | I27: ='Model inputs'!I136*'Model inputs'!O154*(1-'Model inputs'!O144)+'Model inputs'!I62-'Model inputs'!I143*'Model inputs'!O154/12*(1-'Model inputs'!O144) -> 26250 | J27: ='Model inputs'!J136*'Model inputs'!O154*(1-'Model inputs'!O144)+'Model inputs'!J62-'Model inputs'!J143*'Model inputs'!O154/12*(1-'Model inputs'!O144) -> 30000 | K27: ='Model inputs'!K136*'Model inputs'!O154*(1-'Model inputs'!O144)+'Model inputs'!K62-'Model inputs'!K143*'Model inputs'!O154/12*(1-'Model inputs'!O144) -> 33750 | L27: ='Model inputs'!L136*'Model inputs'!O154*(1-'Model inputs'!O144)+'Model inputs'!L62-'Model inputs'!L143*'Model inputs'!O154/12*(1-'Model inputs'!O144) -> 37500 | M27: ='Model inputs'!M136*'Model inputs'!O154*(1-'Model inputs'!O144)+'Model inputs'!M62-'Model inputs'!M143*'Model inputs'!O154/12*(1-'Model inputs'!O144) -> 41250 | N27: ='Model inputs'!N136*'Model inputs'!O154*(1-'Model inputs'!O144)+'Model inputs'!N62-'Model inputs'!N143*'Model inputs'!O154/12*(1-'Model inputs'!O144) -> 45000
A28: Cash supplied switch · DealScope 12-month financial projection | O28: =0 -> 0
A29: Cash supplied switch · DealScope forecast overview | P29: =0 -> 0
A30: Compliance monthly | O30: =500 -> 500
A31: Compliance start month | O31: =6 -> 6
A32: Contribution margin by pricing | C32: =IFERROR(IF('Model inputs'!C38="",0,'Model inputs'!C38)/IF('Model inputs'!C57="",0,'Model inputs'!C57),"") | D32: =IFERROR(IF('Model inputs'!D38="",0,'Model inputs'!D38)/IF('Model inputs'!D57="",0,'Model inputs'!D57),"") | E32: =IFERROR(IF('Model inputs'!E38="",0,'Model inputs'!E38)/IF('Model inputs'!E57="",0,'Model inputs'!E57),"") | F32: =IFERROR(IF('Model inputs'!F38="",0,'Model inputs'!F38)/IF('Model inputs'!F57="",0,'Model inputs'!F57),"") | G32: =IFERROR(IF('Model inputs'!G38="",0,'Model inputs'!G38)/IF('Model inputs'!G57="",0,'Model inputs'!G57),"") | H32: =IFERROR(IF('Model inputs'!H38="",0,'Model inputs'!H38)/IF('Model inputs'!H57="",0,'Model inputs'!H57),"") | I32: =IFERROR(IF('Model inputs'!I38="",0,'Model inputs'!I38)/IF('Model inputs'!I57="",0,'Model inputs'!I57),"") | J32: =IFERROR(IF('Model inputs'!J38="",0,'Model inputs'!J38)/IF('Model inputs'!J57="",0,'Model inputs'!J57),"") | ... N32: =IFERROR(IF('Model inputs'!N38="",0,'Model inputs'!N38)/IF('Model inputs'!N57="",0,'Model inputs'!N57),"")
A33: Contribution margin by pricing > Annual deal-team | C33: =IFERROR('Model inputs'!C39/'Model inputs'!C58,"") -> 0.86785 | D33: =IFERROR('Model inputs'!D39/'Model inputs'!D58,"") -> 0.86785 | E33: =IFERROR('Model inputs'!E39/'Model inputs'!E58,"") -> 0.86785 | F33: =IFERROR('Model inputs'!F39/'Model inputs'!F58,"") -> 0.86785 | G33: =IFERROR('Model inputs'!G39/'Model inputs'!G58,"") -> 0.86785 | H33: =IFERROR('Model inputs'!H39/'Model inputs'!H58,"") -> 0.86785 | I33: =IFERROR('Model inputs'!I39/'Model inputs'!I58,"") -> 0.86785 | J33: =IFERROR('Model inputs'!J39/'Model inputs'!J58,"") -> 0.86785 | ... N33: =IFERROR('Model inputs'!N39/'Model inputs'!N58,"") -> 0.86785
A34: Contribution margin by pricing > Hybrid | C34: =IFERROR('Model inputs'!C40/'Model inputs'!C59,"") -> 0.8792 | D34: =IFERROR('Model inputs'!D40/'Model inputs'!D59,"") -> 0.8792 | E34: =IFERROR('Model inputs'!E40/'Model inputs'!E59,"") -> 0.8792 | F34: =IFERROR('Model inputs'!F40/'Model inputs'!F59,"") -> 0.8792 | G34: =IFERROR('Model inputs'!G40/'Model inputs'!G59,"") -> 0.8792 | H34: =IFERROR('Model inputs'!H40/'Model inputs'!H59,"") -> 0.8792 | I34: =IFERROR('Model inputs'!I40/'Model inputs'!I59,"") -> 0.8792 | J34: =IFERROR('Model inputs'!J40/'Model inputs'!J59,"") -> 0.8792 | ... N34: =IFERROR('Model inputs'!N40/'Model inputs'!N59,"") -> 0.8792
A35: Contribution margin by pricing > Per audit — base | C35: =IFERROR('Model inputs'!C41/'Model inputs'!C60,"") -> 0.9019 | D35: =IFERROR('Model inputs'!D41/'Model inputs'!D60,"") -> 0.9019 | E35: =IFERROR('Model inputs'!E41/'Model inputs'!E60,"") -> 0.9019 | F35: =IFERROR('Model inputs'!F41/'Model inputs'!F60,"") -> 0.9019 | G35: =IFERROR('Model inputs'!G41/'Model inputs'!G60,"") -> 0.9019 | H35: =IFERROR('Model inputs'!H41/'Model inputs'!H60,"") -> 0.9019 | I35: =IFERROR('Model inputs'!I41/'Model inputs'!I60,"") -> 0.9019 | J35: =IFERROR('Model inputs'!J41/'Model inputs'!J60,"") -> 0.9019 | ... N35: =IFERROR('Model inputs'!N41/'Model inputs'!N60,"") -> 0.9019
A36: Contribution margin by pricing > Per audit — high | C36: =IFERROR('Model inputs'!C42/'Model inputs'!C61,"") -> 0.93595 | D36: =IFERROR('Model inputs'!D42/'Model inputs'!D61,"") -> 0.93595 | E36: =IFERROR('Model inputs'!E42/'Model inputs'!E61,"") -> 0.93595 | F36: =IFERROR('Model inputs'!F42/'Model inputs'!F61,"") -> 0.93595 | G36: =IFERROR('Model inputs'!G42/'Model inputs'!G61,"") -> 0.93595 | H36: =IFERROR('Model inputs'!H42/'Model inputs'!H61,"") -> 0.93595 | I36: =IFERROR('Model inputs'!I42/'Model inputs'!I61,"") -> 0.93595 | J36: =IFERROR('Model inputs'!J42/'Model inputs'!J61,"") -> 0.93595 | ... N36: =IFERROR('Model inputs'!N42/'Model inputs'!N61,"") -> 0.93595
