Workbook

Sheet DealScope scenario comparison
A1: DealScope scenario comparison
A2: DealScope — Business summary · Growth
A4: Variable / dimension | B4: Value | C4: Value > Conservative
A5: Forecast earned revenue | B5: =SUM('Model inputs'!B305,'Model inputs'!B306) -> 390000 | C5: =SUM('Model inputs'!B307,'Model inputs'!B308) -> 30000
A6: Forecast cash collections | B6: =SUM('Model inputs'!B309,'Model inputs'!B310) -> 555000 | C6: =SUM('Model inputs'!B311,'Model inputs'!B312) -> 30000
A7: Forecast audits | B7: =SUM('Model inputs'!B313,'Model inputs'!B314) -> 390 | C7: =SUM('Model inputs'!B315,'Model inputs'!B316) -> 40
A8: Forecast gross margin | B8: =IFERROR('Model inputs'!B16/'DealScope scenario comparison'!B5,"") -> 0.90535 | C8: =IFERROR('Model inputs'!B17/'DealScope scenario comparison'!C5,"") -> 0.87203333
A9: Forecast contribution margin | B9: =IFERROR('Model inputs'!B14/'DealScope scenario comparison'!B5,"") -> 0.86785 | C9: =IFERROR('Model inputs'!B15/'DealScope scenario comparison'!C5,"") -> 0.82203333
A10: Forecast net cash burn | B10: =SUM('Model inputs'!B317,'Model inputs'!B318) -> -486011.5 | C10: =SUM('Model inputs'!B319,'Model inputs'!B320) -> -12161
A11: Peak modeled funding need | B11: =MAX(IF(IF(AND('Model inputs'!B20<=DATE(2026,1,1),DATE(2026,1,1)<=EDATE('Model inputs'!B20,'Model inputs'!B18-1*1))="",FALSE,AND('Model inputs'!B20<=DATE(2026,1,1),DATE(2026,1,1)<=EDATE('Model inputs'!B20,'Model inputs'!B18-1*1))),'Model inputs'!C12,""),IF(IF(AND('Model inputs'!B20<=DATE(2026,2,1),DATE(2026,2,1)<=EDATE('Model inputs'!B20,'Model inputs'!B18-1*1))="",FALSE,AND('Model inputs'!B20<=DATE(2026,2,1),DATE(2026,2,1)<=EDATE('Model inputs'!B20,'Model inputs'!B18-1*1))),'Model inputs'!D12,""),IF(IF(AND('Model inputs'!B20<=DATE(2026,3,1),DATE(2026,3,1)<=EDATE('Model inputs'!B20,'Model inputs'!B18-1*1))="",FALSE,AND('Model inputs'!B20<=DATE(2026,3,1),DATE(2026,3,1)<=EDATE('Model inputs'!B20,'Model inputs'!B18-1*1))),'Model inputs'!E12,""),IF(IF(AND('Model inputs'!B20<=DATE(2026,4,1),DATE(2026,4,1)<=EDATE('Model inputs'!B20,'Model inputs'!B18-1*1))="",FALSE,AND('Model inputs'!B20<=DATE(2026,4,1),DATE(2026,4,1)<=EDATE('Model inputs'!B20,'Model inputs'!B18-1*1))),'Model inputs'!F12,""),IF(IF(AND('Model inputs'!B20<=DATE(2026,5,1),DATE(2026,5,1)<=EDATE('Model inputs'!B20,'Model inputs'!B18-1*1))="",FALSE,AND('Model inputs'!B20<=DATE(2026,5,1),DATE(2026,5,1)<=EDATE('Model inputs'!B20,'Model inputs'!B18-1*1))),'Model inputs'!G12,""),IF(IF(AND('Model inputs'!B20<=DATE(2026,6,1),DATE(2026,6,1)<=EDATE('Model inputs'!B20,'Model inputs'!B18-1*1))="",FALSE,AND('Model inputs'!B20<=DATE(2026,6,1),DATE(2026,6,1)<=EDATE('Model inputs'!B20,'Model inputs'!B18-1*1))),'Model inputs'!H12,""),IF(IF(AND('Model inputs'!B20<=DATE(2026,7,1),DATE(2026,7,1)<=EDATE('Model inputs'!B20,'Model inputs'!B18-1*1))="",FALSE,AND('Model inputs'!B20<=DATE(2026,7,1),DATE(2026,7,1)<=EDATE('Model inputs'!B20,'Model inputs'!B18-1*1))),'Model inputs'!I12,""),IF(IF(AND('Model inputs'!B20<=DATE(2026,8,1),DATE(2026,8,1)<=EDATE('Model inputs'!B20,'Model inputs'!B18-1*1))="",FALSE,AND('Model inputs'!B20<=DATE(2026,8,1),DATE(2026,8,1)<=EDATE('Model inputs'!B20,'Model inputs'!B18-1*1))),'Model inputs'!J12,""),IF(IF(AND('Model inputs'!B20<=DATE(2026,9,1),DATE(2026,9,1)<=EDATE('Model inputs'!B20,'Model inputs'!B18-1*1))="",FALSE,AND('Model inputs'!B20<=DATE(2026,9,1),DATE(2026,9,1)<=EDATE('Model inputs'!B20,'Model inputs'!B18-1*1))),'Model inputs'!K12,""),IF(IF(AND('Model inputs'!B20<=DATE(2026,10,1),DATE(2026,10,1)<=EDATE('Model inputs'!B20,'Model inputs'!B18-1*1))="",FALSE,AND('Model inputs'!B20<=DATE(2026,10,1),DATE(2026,10,1)<=EDATE('Model inputs'!B20,'Model inputs'!B18-1*1))),'Model inputs'!L12,""),IF(IF(AND('Model inputs'!B20<=DATE(2026,11,1),DATE(2026,11,1)<=EDATE('Model inputs'!B20,'Model inputs'!B18-1*1))="",FALSE,AND('Model inputs'!B20<=DATE(2026,11,1),DATE(2026,11,1)<=EDATE('Model inputs'!B20,'Model inputs'!B18-1*1))),'Model inputs'!M12,""),IF(IF(AND('Model inputs'!B20<=DATE(2026,12,1),DATE(2026,12,1)<=EDATE('Model inputs'!B20,'Model inputs'!B18-1*1))="",FALSE,AND('Model inputs'!B20<=DATE(2026,12,1),DATE(2026,12,1)<=EDATE('Model inputs'!B20,'Model inputs'!B18-1*1))),'Model inputs'!N12,""),IF(IF(AND('Model inputs'!B20<=DATE(2027,1,1),DATE(2027,1,1)<=EDATE('Model inputs'!B20,'Model inputs'!B18-1*1))="",FALSE,AND('Model inputs'!B20<=DATE(2027,1,1),DATE(2027,1,1)<=EDATE('Model inputs'!B20,'Model inputs'!B18-1*1))),'Model inputs'!O12,""),IF(IF(AND('Model inputs'!B20<=DATE(2027,2,1),DATE(2027,2,1)<=EDATE('Model inputs'!B20,'Model inputs'!B18-1*1))="",FALSE,AND('Model inputs'!B20<=DATE(2027,2,1),DATE(2027,2,1)<=EDATE('Model inputs'!B20,'Model inputs'!B18-1*1))),'Model inputs'!P12,""),IF(IF(AND('Model inputs'!B20<=DATE(2027,3,1),DATE(2027,3,1)<=EDATE('Model inputs'!B20,'Model inputs'!B18-1*1))="",FALSE,AND('Model inputs'!B20<=DATE(2027,3,1),DATE(2027,3,1)<=EDATE('Model inputs'!B20,'Model inputs'!B18-1*1))),'Model inputs'!Q12,""),IF(IF(AND('Model inputs'!B20<=DATE(2027,4,1),DATE(2027,4,1)<=EDATE('Model inputs'!B20,'Model inputs'!B18-1*1))="",FALSE,AND('Model inputs'!B20<=DATE(2027,4,1),DATE(2027,4,1)<=EDATE('Model inputs'!B20,'Model inputs'!B18-1*1))),'Model inputs'!R12,""),IF(IF(AND('Model inputs'!B20<=DATE(2027,5,1),DATE(2027,5,1)<=EDATE('Model inputs'!B20,'Model inputs'!B18-1*1))="",FALSE,AND('Model inputs'!B20<=DATE(2027,5,1),DATE(2027,5,1)<=EDATE('Model inputs'!B20,'Model inputs'!B18-1*1))),'Model inputs'!S12,""),IF(IF(AND('Model inputs'!B20<=DATE(2027,6,1),DATE(2027,6,1)<=EDATE('Model inputs'!B20,'Model inputs'!B18-1*1))="",FALSE,AND('Model inputs'!B20<=DATE(2027,6,1),DATE(2027,6,1)<=EDATE('Model inputs'!B20,'Model inputs'!B18-1*1))),'Model inputs'!T12,""),IF(IF(AND('Model inputs'!B20<=DATE(2027,7,1),DATE(2027,7,1)<=EDATE('Model inputs'!B20,'Model inputs'!B18-1*1))="",FALSE,AND('Model inputs'!B20<=DATE(2027,7,1),DATE(2027,7,1)<=EDATE('Model inputs'!B20,'Model inputs'!B18-1*1))),'Model inputs'!U12,""),IF(IF(AND('Model inputs'!B20<=DATE(2027,8,1),DATE(2027,8,1)<=EDATE('Model inputs'!B20,'Model inputs'!B18-1*1))="",FALSE,AND('Model inputs'!B20<=DATE(2027,8,1),DATE(2027,8,1)<=EDATE('Model inputs'!B20,'Model inputs'!B18-1*1))),'Model inputs'!V12,""),IF(IF(AND('Model inputs'!B20<=DATE(2027,9,1),DATE(2027,9,1)<=EDATE('Model inputs'!B20,'Model inputs'!B18-1*1))="",FALSE,AND('Model inputs'!B20<=DATE(2027,9,1),DATE(2027,9,1)<=EDATE('Model inputs'!B20,'Model inputs'!B18-1*1))),'Model inputs'!W12,""),IF(IF(AND('Model inputs'!B20<=DATE(2027,10,1),DATE(2027,10,1)<=EDATE('Model inputs'!B20,'Model inputs'!B18-1*1))="",FALSE,AND('Model inputs'!B20<=DATE(2027,10,1),DATE(2027,10,1)<=EDATE('Model inputs'!B20,'Model inputs'!B18-1*1))),'Model inputs'!X12,""),IF(IF(AND('Model inputs'!B20<=DATE(2027,11,1),DATE(2027,11,1)<=EDATE('Model inputs'!B20,'Model inputs'!B18-1*1))="",FALSE,AND('Model inputs'!B20<=DATE(2027,11,1),DATE(2027,11,1)<=EDATE('Model inputs'!B20,'Model inputs'!B18-1*1))),'Model inputs'!Y12,""),IF(IF(AND('Model inputs'!B20<=DATE(2027,12,1),DATE(2027,12,1)<=EDATE('Model inputs'!B20,'Model inputs'!B18-1*1))="",FALSE,AND('Model inputs'!B20<=DATE(2027,12,1),DATE(2027,12,1)<=EDATE('Model inputs'!B20,'Model inputs'!B18-1*1))),'Model inputs'!Z12,"")) -> 0 | C11: =MAX(IF(IF(AND('Model inputs'!B21<=DATE(2026,1,1),DATE(2026,1,1)<=EDATE('Model inputs'!B21,'Model inputs'!B19-1*1))="",FALSE,AND('Model inputs'!B21<=DATE(2026,1,1),DATE(2026,1,1)<=EDATE('Model inputs'!B21,'Model inputs'!B19-1*1))),'Model inputs'!C13,""),IF(IF(AND('Model inputs'!B21<=DATE(2026,2,1),DATE(2026,2,1)<=EDATE('Model inputs'!B21,'Model inputs'!B19-1*1))="",FALSE,AND('Model inputs'!B21<=DATE(2026,2,1),DATE(2026,2,1)<=EDATE('Model inputs'!B21,'Model inputs'!B19-1*1))),'Model inputs'!D13,""),IF(IF(AND('Model inputs'!B21<=DATE(2026,3,1),DATE(2026,3,1)<=EDATE('Model inputs'!B21,'Model inputs'!B19-1*1))="",FALSE,AND('Model inputs'!B21<=DATE(2026,3,1),DATE(2026,3,1)<=EDATE('Model inputs'!B21,'Model inputs'!B19-1*1))),'Model inputs'!E13,""),IF(IF(AND('Model inputs'!B21<=DATE(2026,4,1),DATE(2026,4,1)<=EDATE('Model inputs'!B21,'Model inputs'!B19-1*1))="",FALSE,AND('Model inputs'!B21<=DATE(2026,4,1),DATE(2026,4,1)<=EDATE('Model inputs'!B21,'Model inputs'!B19-1*1))),'Model inputs'!F13,""),IF(IF(AND('Model inputs'!B21<=DATE(2026,5,1),DATE(2026,5,1)<=EDATE('Model inputs'!B21,'Model inputs'!B19-1*1))="",FALSE,AND('Model inputs'!B21<=DATE(2026,5,1),DATE(2026,5,1)<=EDATE('Model inputs'!B21,'Model inputs'!B19-1*1))),'Model inputs'!G13,""),IF(IF(AND('Model inputs'!B21<=DATE(2026,6,1),DATE(2026,6,1)<=EDATE('Model inputs'!B21,'Model inputs'!B19-1*1))="",FALSE,AND('Model inputs'!B21<=DATE(2026,6,1),DATE(2026,6,1)<=EDATE('Model inputs'!B21,'Model inputs'!B19-1*1))),'Model inputs'!H13,""),IF(IF(AND('Model inputs'!B21<=DATE(2026,7,1),DATE(2026,7,1)<=EDATE('Model inputs'!B21,'Model inputs'!B19-1*1))="",FALSE,AND('Model inputs'!B21<=DATE(2026,7,1),DATE(2026,7,1)<=EDATE('Model inputs'!B21,'Model inputs'!B19-1*1))),'Model inputs'!I13,""),IF(IF(AND('Model inputs'!B21<=DATE(2026,8,1),DATE(2026,8,1)<=EDATE('Model inputs'!B21,'Model inputs'!B19-1*1))="",FALSE,AND('Model inputs'!B21<=DATE(2026,8,1),DATE(2026,8,1)<=EDATE('Model inputs'!B21,'Model inputs'!B19-1*1))),'Model inputs'!J13,""),IF(IF(AND('Model inputs'!B21<=DATE(2026,9,1),DATE(2026,9,1)<=EDATE('Model inputs'!B21,'Model inputs'!B19-1*1))="",FALSE,AND('Model inputs'!B21<=DATE(2026,9,1),DATE(2026,9,1)<=EDATE('Model inputs'!B21,'Model inputs'!B19-1*1))),'Model inputs'!K13,""),IF(IF(AND('Model inputs'!B21<=DATE(2026,10,1),DATE(2026,10,1)<=EDATE('Model inputs'!B21,'Model inputs'!B19-1*1))="",FALSE,AND('Model inputs'!B21<=DATE(2026,10,1),DATE(2026,10,1)<=EDATE('Model inputs'!B21,'Model inputs'!B19-1*1))),'Model inputs'!L13,""),IF(IF(AND('Model inputs'!B21<=DATE(2026,11,1),DATE(2026,11,1)<=EDATE('Model inputs'!B21,'Model inputs'!B19-1*1))="",FALSE,AND('Model inputs'!B21<=DATE(2026,11,1),DATE(2026,11,1)<=EDATE('Model inputs'!B21,'Model inputs'!B19-1*1))),'Model inputs'!M13,""),IF(IF(AND('Model inputs'!B21<=DATE(2026,12,1),DATE(2026,12,1)<=EDATE('Model inputs'!B21,'Model inputs'!B19-1*1))="",FALSE,AND('Model inputs'!B21<=DATE(2026,12,1),DATE(2026,12,1)<=EDATE('Model inputs'!B21,'Model inputs'!B19-1*1))),'Model inputs'!N13,""),IF(IF(AND('Model inputs'!B21<=DATE(2027,1,1),DATE(2027,1,1)<=EDATE('Model inputs'!B21,'Model inputs'!B19-1*1))="",FALSE,AND('Model inputs'!B21<=DATE(2027,1,1),DATE(2027,1,1)<=EDATE('Model inputs'!B21,'Model inputs'!B19-1*1))),'Model inputs'!O13,""),IF(IF(AND('Model inputs'!B21<=DATE(2027,2,1),DATE(2027,2,1)<=EDATE('Model inputs'!B21,'Model inputs'!B19-1*1))="",FALSE,AND('Model inputs'!B21<=DATE(2027,2,1),DATE(2027,2,1)<=EDATE('Model inputs'!B21,'Model inputs'!B19-1*1))),'Model inputs'!P13,""),IF(IF(AND('Model inputs'!B21<=DATE(2027,3,1),DATE(2027,3,1)<=EDATE('Model inputs'!B21,'Model inputs'!B19-1*1))="",FALSE,AND('Model inputs'!B21<=DATE(2027,3,1),DATE(2027,3,1)<=EDATE('Model inputs'!B21,'Model inputs'!B19-1*1))),'Model inputs'!Q13,""),IF(IF(AND('Model inputs'!B21<=DATE(2027,4,1),DATE(2027,4,1)<=EDATE('Model inputs'!B21,'Model inputs'!B19-1*1))="",FALSE,AND('Model inputs'!B21<=DATE(2027,4,1),DATE(2027,4,1)<=EDATE('Model inputs'!B21,'Model inputs'!B19-1*1))),'Model inputs'!R13,""),IF(IF(AND('Model inputs'!B21<=DATE(2027,5,1),DATE(2027,5,1)<=EDATE('Model inputs'!B21,'Model inputs'!B19-1*1))="",FALSE,AND('Model inputs'!B21<=DATE(2027,5,1),DATE(2027,5,1)<=EDATE('Model inputs'!B21,'Model inputs'!B19-1*1))),'Model inputs'!S13,""),IF(IF(AND('Model inputs'!B21<=DATE(2027,6,1),DATE(2027,6,1)<=EDATE('Model inputs'!B21,'Model inputs'!B19-1*1))="",FALSE,AND('Model inputs'!B21<=DATE(2027,6,1),DATE(2027,6,1)<=EDATE('Model inputs'!B21,'Model inputs'!B19-1*1))),'Model inputs'!T13,""),IF(IF(AND('Model inputs'!B21<=DATE(2027,7,1),DATE(2027,7,1)<=EDATE('Model inputs'!B21,'Model inputs'!B19-1*1))="",FALSE,AND('Model inputs'!B21<=DATE(2027,7,1),DATE(2027,7,1)<=EDATE('Model inputs'!B21,'Model inputs'!B19-1*1))),'Model inputs'!U13,""),IF(IF(AND('Model inputs'!B21<=DATE(2027,8,1),DATE(2027,8,1)<=EDATE('Model inputs'!B21,'Model inputs'!B19-1*1))="",FALSE,AND('Model inputs'!B21<=DATE(2027,8,1),DATE(2027,8,1)<=EDATE('Model inputs'!B21,'Model inputs'!B19-1*1))),'Model inputs'!V13,""),IF(IF(AND('Model inputs'!B21<=DATE(2027,9,1),DATE(2027,9,1)<=EDATE('Model inputs'!B21,'Model inputs'!B19-1*1))="",FALSE,AND('Model inputs'!B21<=DATE(2027,9,1),DATE(2027,9,1)<=EDATE('Model inputs'!B21,'Model inputs'!B19-1*1))),'Model inputs'!W13,""),IF(IF(AND('Model inputs'!B21<=DATE(2027,10,1),DATE(2027,10,1)<=EDATE('Model inputs'!B21,'Model inputs'!B19-1*1))="",FALSE,AND('Model inputs'!B21<=DATE(2027,10,1),DATE(2027,10,1)<=EDATE('Model inputs'!B21,'Model inputs'!B19-1*1))),'Model inputs'!X13,""),IF(IF(AND('Model inputs'!B21<=DATE(2027,11,1),DATE(2027,11,1)<=EDATE('Model inputs'!B21,'Model inputs'!B19-1*1))="",FALSE,AND('Model inputs'!B21<=DATE(2027,11,1),DATE(2027,11,1)<=EDATE('Model inputs'!B21,'Model inputs'!B19-1*1))),'Model inputs'!Y13,""),IF(IF(AND('Model inputs'!B21<=DATE(2027,12,1),DATE(2027,12,1)<=EDATE('Model inputs'!B21,'Model inputs'!B19-1*1))="",FALSE,AND('Model inputs'!B21<=DATE(2027,12,1),DATE(2027,12,1)<=EDATE('Model inputs'!B21,'Model inputs'!B19-1*1))),'Model inputs'!Z13,"")) -> 1500
A12: Conditional runway months | B12: =IF(IF(IF(IFERROR(IF(ISERROR('Model inputs'!B10=1),'Model inputs'!B10=1,IF('Model inputs'!B10="","",'Model inputs'!B10=1))=FALSE,FALSE),FALSE,IF(IFERROR(IF(ISERROR('Model inputs'!B8>0),'Model inputs'!B8>0,IF('Model inputs'!B8="","",'Model inputs'!B8>0))=FALSE,FALSE),FALSE,IF(OR(IF(ISERROR('Model inputs'!B10=1),'Model inputs'!B10=1,IF('Model inputs'!B10="","",'Model inputs'!B10=1))="",IF(ISERROR('Model inputs'!B8>0),'Model inputs'!B8>0,IF('Model inputs'!B8="","",'Model inputs'!B8>0))=""),"",AND(IF(ISERROR('Model inputs'!B10=1),'Model inputs'!B10=1,IF('Model inputs'!B10="","",'Model inputs'!B10=1)),IF(ISERROR('Model inputs'!B8>0),'Model inputs'!B8>0,IF('Model inputs'!B8="","",'Model inputs'!B8>0))))))="",FALSE,IF(IFERROR(IF(ISERROR('Model inputs'!B10=1),'Model inputs'!B10=1,IF('Model inputs'!B10="","",'Model inputs'!B10=1))=FALSE,FALSE),FALSE,IF(IFERROR(IF(ISERROR('Model inputs'!B8>0),'Model inputs'!B8>0,IF('Model inputs'!B8="","",'Model inputs'!B8>0))=FALSE,FALSE),FALSE,IF(OR(IF(ISERROR('Model inputs'!B10=1),'Model inputs'!B10=1,IF('Model inputs'!B10="","",'Model inputs'!B10=1))="",IF(ISERROR('Model inputs'!B8>0),'Model inputs'!B8>0,IF('Model inputs'!B8="","",'Model inputs'!B8>0))=""),"",AND(IF(ISERROR('Model inputs'!B10=1),'Model inputs'!B10=1,IF('Model inputs'!B10="","",'Model inputs'!B10=1)),IF(ISERROR('Model inputs'!B8>0),'Model inputs'!B8>0,IF('Model inputs'!B8="","",'Model inputs'!B8>0))))))),IF('Model inputs'!B6="",0,'Model inputs'!B6)/'Model inputs'!B8,"") | C12: =IF(IF(IF(IFERROR(IF(ISERROR('Model inputs'!B11=1),'Model inputs'!B11=1,IF('Model inputs'!B11="","",'Model inputs'!B11=1))=FALSE,FALSE),FALSE,IF(IFERROR(IF(ISERROR('Model inputs'!B9>0),'Model inputs'!B9>0,IF('Model inputs'!B9="","",'Model inputs'!B9>0))=FALSE,FALSE),FALSE,IF(OR(IF(ISERROR('Model inputs'!B11=1),'Model inputs'!B11=1,IF('Model inputs'!B11="","",'Model inputs'!B11=1))="",IF(ISERROR('Model inputs'!B9>0),'Model inputs'!B9>0,IF('Model inputs'!B9="","",'Model inputs'!B9>0))=""),"",AND(IF(ISERROR('Model inputs'!B11=1),'Model inputs'!B11=1,IF('Model inputs'!B11="","",'Model inputs'!B11=1)),IF(ISERROR('Model inputs'!B9>0),'Model inputs'!B9>0,IF('Model inputs'!B9="","",'Model inputs'!B9>0))))))="",FALSE,IF(IFERROR(IF(ISERROR('Model inputs'!B11=1),'Model inputs'!B11=1,IF('Model inputs'!B11="","",'Model inputs'!B11=1))=FALSE,FALSE),FALSE,IF(IFERROR(IF(ISERROR('Model inputs'!B9>0),'Model inputs'!B9>0,IF('Model inputs'!B9="","",'Model inputs'!B9>0))=FALSE,FALSE),FALSE,IF(OR(IF(ISERROR('Model inputs'!B11=1),'Model inputs'!B11=1,IF('Model inputs'!B11="","",'Model inputs'!B11=1))="",IF(ISERROR('Model inputs'!B9>0),'Model inputs'!B9>0,IF('Model inputs'!B9="","",'Model inputs'!B9>0))=""),"",AND(IF(ISERROR('Model inputs'!B11=1),'Model inputs'!B11=1,IF('Model inputs'!B11="","",'Model inputs'!B11=1)),IF(ISERROR('Model inputs'!B9>0),'Model inputs'!B9>0,IF('Model inputs'!B9="","",'Model inputs'!B9>0))))))),IF('Model inputs'!B7="",0,'Model inputs'!B7)/'Model inputs'!B9,"")

Sheet Model inputs
A1: Model inputs
A2: Integration values are aggregated snapshots; raw source records are not included.
A4: Variables
A5: Variable / segment | B5: Value | C5: 2026-01 | D5: 2026-02 | E5: 2026-03 | F5: 2026-04 | G5: 2026-05 | H5: 2026-06 | I5: 2026-07 | J5: 2026-08 | K5: 2026-09 | L5: 2026-10 | M5: 2026-11 | N5: 2026-12 | O5: 2027-01 | P5: 2027-02 | Q5: 2027-03 | R5: 2027-04 | S5: 2027-05 | T5: 2027-06 | U5: 2027-07 | V5: 2027-08 | W5: 2027-09 | X5: 2027-10 | Y5: 2027-11 | Z5: 2027-12 | AA5: Value
A6: Available opening cash · Growth | B6: =""
A7: Available opening cash · Conservative | B7: =""
A8: Average monthly net cash burn · Growth | B8: ='DealScope scenario comparison'!B10/'Model inputs'!B18 -> -40500.958
A9: Average monthly net cash burn · Conservative | B9: ='DealScope scenario comparison'!C10/'Model inputs'!B19 -> -1013.4167
A10: Cash supplied switch · Growth | B10: =0 -> 0
A11: Cash supplied switch · Conservative | B11: =0 -> 0
A12: Cumulative funding gap · Growth | C12: 0 | D12: 0 | E12: 0 | F12: 0 | G12: 0 | H12: 0 | I12: 0 | J12: 0 | K12: 0 | L12: =MAX(IF(IF(IF(IF(ISERROR('Model inputs'!L84=1),'Model inputs'!L84=1,IF('Model inputs'!L84="","",'Model inputs'!L84=1))="",FALSE,IF(ISERROR('Model inputs'!L84=1),'Model inputs'!L84=1,IF('Model inputs'!L84="","",'Model inputs'!L84=1))),0,IF('Model inputs'!K54="","",'Model inputs'!K54))="",0,IF(IF(IF(ISERROR('Model inputs'!L84=1),'Model inputs'!L84=1,IF('Model inputs'!L84="","",'Model inputs'!L84=1))="",FALSE,IF(ISERROR('Model inputs'!L84=1),'Model inputs'!L84=1,IF('Model inputs'!L84="","",'Model inputs'!L84=1))),0,IF('Model inputs'!K54="","",'Model inputs'!K54)))+'Model inputs'!L28,0) -> 0 | M12: =MAX(IF(IF(IF(IF(ISERROR('Model inputs'!M84=1),'Model inputs'!M84=1,IF('Model inputs'!M84="","",'Model inputs'!M84=1))="",FALSE,IF(ISERROR('Model inputs'!M84=1),'Model inputs'!M84=1,IF('Model inputs'!M84="","",'Model inputs'!M84=1))),0,IF('Model inputs'!L54="","",'Model inputs'!L54))="",0,IF(IF(IF(ISERROR('Model inputs'!M84=1),'Model inputs'!M84=1,IF('Model inputs'!M84="","",'Model inputs'!M84=1))="",FALSE,IF(ISERROR('Model inputs'!M84=1),'Model inputs'!M84=1,IF('Model inputs'!M84="","",'Model inputs'!M84=1))),0,IF('Model inputs'!L54="","",'Model inputs'!L54)))+'Model inputs'!M28,0) -> 0 | N12: =MAX(IF(IF(IF(IF(ISERROR('Model inputs'!N84=1),'Model inputs'!N84=1,IF('Model inputs'!N84="","",'Model inputs'!N84=1))="",FALSE,IF(ISERROR('Model inputs'!N84=1),'Model inputs'!N84=1,IF('Model inputs'!N84="","",'Model inputs'!N84=1))),0,IF('Model inputs'!M54="","",'Model inputs'!M54))="",0,IF(IF(IF(ISERROR('Model inputs'!N84=1),'Model inputs'!N84=1,IF('Model inputs'!N84="","",'Model inputs'!N84=1))="",FALSE,IF(ISERROR('Model inputs'!N84=1),'Model inputs'!N84=1,IF('Model inputs'!N84="","",'Model inputs'!N84=1))),0,IF('Model inputs'!M54="","",'Model inputs'!M54)))+'Model inputs'!N28,0) -> 0 | O12: =MAX(IF(IF(IF(IF(ISERROR('Model inputs'!O84=1),'Model inputs'!O84=1,IF('Model inputs'!O84="","",'Model inputs'!O84=1))="",FALSE,IF(ISERROR('Model inputs'!O84=1),'Model inputs'!O84=1,IF('Model inputs'!O84="","",'Model inputs'!O84=1))),0,IF('Model inputs'!N54="","",'Model inputs'!N54))="",0,IF(IF(IF(ISERROR('Model inputs'!O84=1),'Model inputs'!O84=1,IF('Model inputs'!O84="","",'Model inputs'!O84=1))="",FALSE,IF(ISERROR('Model inputs'!O84=1),'Model inputs'!O84=1,IF('Model inputs'!O84="","",'Model inputs'!O84=1))),0,IF('Model inputs'!N54="","",'Model inputs'!N54)))+'Model inputs'!O28,0) -> 0 | P12: =MAX(IF(IF(IF(IF(ISERROR('Model inputs'!P84=1),'Model inputs'!P84=1,IF('Model inputs'!P84="","",'Model inputs'!P84=1))="",FALSE,IF(ISERROR('Model inputs'!P84=1),'Model inputs'!P84=1,IF('Model inputs'!P84="","",'Model inputs'!P84=1))),0,IF('Model inputs'!O54="","",'Model inputs'!O54))="",0,IF(IF(IF(ISERROR('Model inputs'!P84=1),'Model inputs'!P84=1,IF('Model inputs'!P84="","",'Model inputs'!P84=1))="",FALSE,IF(ISERROR('Model inputs'!P84=1),'Model inputs'!P84=1,IF('Model inputs'!P84="","",'Model inputs'!P84=1))),0,IF('Model inputs'!O54="","",'Model inputs'!O54)))+'Model inputs'!P28,0) -> 0 | Q12: =MAX(IF(IF(IF(IF(ISERROR('Model inputs'!Q84=1),'Model inputs'!Q84=1,IF('Model inputs'!Q84="","",'Model inputs'!Q84=1))="",FALSE,IF(ISERROR('Model inputs'!Q84=1),'Model inputs'!Q84=1,IF('Model inputs'!Q84="","",'Model inputs'!Q84=1))),0,IF('Model inputs'!P54="","",'Model inputs'!P54))="",0,IF(IF(IF(ISERROR('Model inputs'!Q84=1),'Model inputs'!Q84=1,IF('Model inputs'!Q84="","",'Model inputs'!Q84=1))="",FALSE,IF(ISERROR('Model inputs'!Q84=1),'Model inputs'!Q84=1,IF('Model inputs'!Q84="","",'Model inputs'!Q84=1))),0,IF('Model inputs'!P54="","",'Model inputs'!P54)))+'Model inputs'!Q28,0) -> 0 | R12: =MAX(IF(IF(IF(IF(ISERROR('Model inputs'!R84=1),'Model inputs'!R84=1,IF('Model inputs'!R84="","",'Model inputs'!R84=1))="",FALSE,IF(ISERROR('Model inputs'!R84=1),'Model inputs'!R84=1,IF('Model inputs'!R84="","",'Model inputs'!R84=1))),0,IF('Model inputs'!Q54="","",'Model inputs'!Q54))="",0,IF(IF(IF(ISERROR('Model inputs'!R84=1),'Model inputs'!R84=1,IF('Model inputs'!R84="","",'Model inputs'!R84=1))="",FALSE,IF(ISERROR('Model inputs'!R84=1),'Model inputs'!R84=1,IF('Model inputs'!R84="","",'Model inputs'!R84=1))),0,IF('Model inputs'!Q54="","",'Model inputs'!Q54)))+'Model inputs'!R28,0) -> 0 | S12: =MAX(IF(IF(IF(IF(ISERROR('Model inputs'!S84=1),'Model inputs'!S84=1,IF('Model inputs'!S84="","",'Model inputs'!S84=1))="",FALSE,IF(ISERROR('Model inputs'!S84=1),'Model inputs'!S84=1,IF('Model inputs'!S84="","",'Model inputs'!S84=1))),0,IF('Model inputs'!R54="","",'Model inputs'!R54))="",0,IF(IF(IF(ISERROR('Model inputs'!S84=1),'Model inputs'!S84=1,IF('Model inputs'!S84="","",'Model inputs'!S84=1))="",FALSE,IF(ISERROR('Model inputs'!S84=1),'Model inputs'!S84=1,IF('Model inputs'!S84="","",'Model inputs'!S84=1))),0,IF('Model inputs'!R54="","",'Model inputs'!R54)))+'Model inputs'!S28,0) -> 0 | ... Z12: =MAX(IF(IF(IF(IF(ISERROR('Model inputs'!Z84=1),'Model inputs'!Z84=1,IF('Model inputs'!Z84="","",'Model inputs'!Z84=1))="",FALSE,IF(ISERROR('Model inputs'!Z84=1),'Model inputs'!Z84=1,IF('Model inputs'!Z84="","",'Model inputs'!Z84=1))),0,IF('Model inputs'!Y54="","",'Model inputs'!Y54))="",0,IF(IF(IF(ISERROR('Model inputs'!Z84=1),'Model inputs'!Z84=1,IF('Model inputs'!Z84="","",'Model inputs'!Z84=1))="",FALSE,IF(ISERROR('Model inputs'!Z84=1),'Model inputs'!Z84=1,IF('Model inputs'!Z84="","",'Model inputs'!Z84=1))),0,IF('Model inputs'!Y54="","",'Model inputs'!Y54)))+'Model inputs'!Z28,0) -> 0
A13: Cumulative funding gap · Conservative | C13: 0 | D13: 0 | E13: 0 | F13: 0 | G13: 0 | H13: 0 | I13: 0 | J13: 0 | K13: 0 | L13: =MAX(IF(IF(IF(IF(ISERROR('Model inputs'!L85=1),'Model inputs'!L85=1,IF('Model inputs'!L85="","",'Model inputs'!L85=1))="",FALSE,IF(ISERROR('Model inputs'!L85=1),'Model inputs'!L85=1,IF('Model inputs'!L85="","",'Model inputs'!L85=1))),0,IF('Model inputs'!K55="","",'Model inputs'!K55))="",0,IF(IF(IF(ISERROR('Model inputs'!L85=1),'Model inputs'!L85=1,IF('Model inputs'!L85="","",'Model inputs'!L85=1))="",FALSE,IF(ISERROR('Model inputs'!L85=1),'Model inputs'!L85=1,IF('Model inputs'!L85="","",'Model inputs'!L85=1))),0,IF('Model inputs'!K55="","",'Model inputs'!K55)))+'Model inputs'!L29,0) -> 750 | M13: =MAX(IF(IF(IF(IF(ISERROR('Model inputs'!M85=1),'Model inputs'!M85=1,IF('Model inputs'!M85="","",'Model inputs'!M85=1))="",FALSE,IF(ISERROR('Model inputs'!M85=1),'Model inputs'!M85=1,IF('Model inputs'!M85="","",'Model inputs'!M85=1))),0,IF('Model inputs'!L55="","",'Model inputs'!L55))="",0,IF(IF(IF(ISERROR('Model inputs'!M85=1),'Model inputs'!M85=1,IF('Model inputs'!M85="","",'Model inputs'!M85=1))="",FALSE,IF(ISERROR('Model inputs'!M85=1),'Model inputs'!M85=1,IF('Model inputs'!M85="","",'Model inputs'!M85=1))),0,IF('Model inputs'!L55="","",'Model inputs'!L55)))+'Model inputs'!M29,0) -> 1500 | N13: =MAX(IF(IF(IF(IF(ISERROR('Model inputs'!N85=1),'Model inputs'!N85=1,IF('Model inputs'!N85="","",'Model inputs'!N85=1))="",FALSE,IF(ISERROR('Model inputs'!N85=1),'Model inputs'!N85=1,IF('Model inputs'!N85="","",'Model inputs'!N85=1))),0,IF('Model inputs'!M55="","",'Model inputs'!M55))="",0,IF(IF(IF(ISERROR('Model inputs'!N85=1),'Model inputs'!N85=1,IF('Model inputs'!N85="","",'Model inputs'!N85=1))="",FALSE,IF(ISERROR('Model inputs'!N85=1),'Model inputs'!N85=1,IF('Model inputs'!N85="","",'Model inputs'!N85=1))),0,IF('Model inputs'!M55="","",'Model inputs'!M55)))+'Model inputs'!N29,0) -> 0 | O13: =MAX(IF(IF(IF(IF(ISERROR('Model inputs'!O85=1),'Model inputs'!O85=1,IF('Model inputs'!O85="","",'Model inputs'!O85=1))="",FALSE,IF(ISERROR('Model inputs'!O85=1),'Model inputs'!O85=1,IF('Model inputs'!O85="","",'Model inputs'!O85=1))),0,IF('Model inputs'!N55="","",'Model inputs'!N55))="",0,IF(IF(IF(ISERROR('Model inputs'!O85=1),'Model inputs'!O85=1,IF('Model inputs'!O85="","",'Model inputs'!O85=1))="",FALSE,IF(ISERROR('Model inputs'!O85=1),'Model inputs'!O85=1,IF('Model inputs'!O85="","",'Model inputs'!O85=1))),0,IF('Model inputs'!N55="","",'Model inputs'!N55)))+'Model inputs'!O29,0) -> 0 | P13: =MAX(IF(IF(IF(IF(ISERROR('Model inputs'!P85=1),'Model inputs'!P85=1,IF('Model inputs'!P85="","",'Model inputs'!P85=1))="",FALSE,IF(ISERROR('Model inputs'!P85=1),'Model inputs'!P85=1,IF('Model inputs'!P85="","",'Model inputs'!P85=1))),0,IF('Model inputs'!O55="","",'Model inputs'!O55))="",0,IF(IF(IF(ISERROR('Model inputs'!P85=1),'Model inputs'!P85=1,IF('Model inputs'!P85="","",'Model inputs'!P85=1))="",FALSE,IF(ISERROR('Model inputs'!P85=1),'Model inputs'!P85=1,IF('Model inputs'!P85="","",'Model inputs'!P85=1))),0,IF('Model inputs'!O55="","",'Model inputs'!O55)))+'Model inputs'!P29,0) -> 0 | Q13: =MAX(IF(IF(IF(IF(ISERROR('Model inputs'!Q85=1),'Model inputs'!Q85=1,IF('Model inputs'!Q85="","",'Model inputs'!Q85=1))="",FALSE,IF(ISERROR('Model inputs'!Q85=1),'Model inputs'!Q85=1,IF('Model inputs'!Q85="","",'Model inputs'!Q85=1))),0,IF('Model inputs'!P55="","",'Model inputs'!P55))="",0,IF(IF(IF(ISERROR('Model inputs'!Q85=1),'Model inputs'!Q85=1,IF('Model inputs'!Q85="","",'Model inputs'!Q85=1))="",FALSE,IF(ISERROR('Model inputs'!Q85=1),'Model inputs'!Q85=1,IF('Model inputs'!Q85="","",'Model inputs'!Q85=1))),0,IF('Model inputs'!P55="","",'Model inputs'!P55)))+'Model inputs'!Q29,0) -> 0 | R13: =MAX(IF(IF(IF(IF(ISERROR('Model inputs'!R85=1),'Model inputs'!R85=1,IF('Model inputs'!R85="","",'Model inputs'!R85=1))="",FALSE,IF(ISERROR('Model inputs'!R85=1),'Model inputs'!R85=1,IF('Model inputs'!R85="","",'Model inputs'!R85=1))),0,IF('Model inputs'!Q55="","",'Model inputs'!Q55))="",0,IF(IF(IF(ISERROR('Model inputs'!R85=1),'Model inputs'!R85=1,IF('Model inputs'!R85="","",'Model inputs'!R85=1))="",FALSE,IF(ISERROR('Model inputs'!R85=1),'Model inputs'!R85=1,IF('Model inputs'!R85="","",'Model inputs'!R85=1))),0,IF('Model inputs'!Q55="","",'Model inputs'!Q55)))+'Model inputs'!R29,0) -> 0 | S13: =MAX(IF(IF(IF(IF(ISERROR('Model inputs'!S85=1),'Model inputs'!S85=1,IF('Model inputs'!S85="","",'Model inputs'!S85=1))="",FALSE,IF(ISERROR('Model inputs'!S85=1),'Model inputs'!S85=1,IF('Model inputs'!S85="","",'Model inputs'!S85=1))),0,IF('Model inputs'!R55="","",'Model inputs'!R55))="",0,IF(IF(IF(ISERROR('Model inputs'!S85=1),'Model inputs'!S85=1,IF('Model inputs'!S85="","",'Model inputs'!S85=1))="",FALSE,IF(ISERROR('Model inputs'!S85=1),'Model inputs'!S85=1,IF('Model inputs'!S85="","",'Model inputs'!S85=1))),0,IF('Model inputs'!R55="","",'Model inputs'!R55)))+'Model inputs'!S29,0) -> 0 | ... Z13: =MAX(IF(IF(IF(IF(ISERROR('Model inputs'!Z85=1),'Model inputs'!Z85=1,IF('Model inputs'!Z85="","",'Model inputs'!Z85=1))="",FALSE,IF(ISERROR('Model inputs'!Z85=1),'Model inputs'!Z85=1,IF('Model inputs'!Z85="","",'Model inputs'!Z85=1))),0,IF('Model inputs'!Y55="","",'Model inputs'!Y55))="",0,IF(IF(IF(ISERROR('Model inputs'!Z85=1),'Model inputs'!Z85=1,IF('Model inputs'!Z85="","",'Model inputs'!Z85=1))="",FALSE,IF(ISERROR('Model inputs'!Z85=1),'Model inputs'!Z85=1,IF('Model inputs'!Z85="","",'Model inputs'!Z85=1))),0,IF('Model inputs'!Y55="","",'Model inputs'!Y55)))+'Model inputs'!Z29,0) -> 0
A14: Forecast contribution profit · Growth | B14: =SUM('Model inputs'!B321,'Model inputs'!B322) -> 338461.5
A15: Forecast contribution profit · Conservative | B15: =SUM('Model inputs'!B323,'Model inputs'!B324) -> 24661
A16: Forecast gross profit · Growth | B16: ='DealScope scenario comparison'!B5-'Model inputs'!B68 -> 353086.5
A17: Forecast gross profit · Conservative | B17: ='DealScope scenario comparison'!C5-'Model inputs'!B69 -> 26161
A18: Forecast months · Growth | B18: =12 -> 12
A19: Forecast months · Conservative | B19: =12 -> 12
A20: Forecast start date · Growth | B20: =DATE(2026,10,1) -> 46296
A21: Forecast start date · Conservative | B21: =DATE(2026,10,1) -> 46296
A22: Plan Audits delivered · Growth | C22: 0 | D22: 0 | E22: 0 | F22: 0 | G22: 0 | H22: 0 | I22: 0 | J22: 0 | K22: 0 | L22: =IF(SUM(IF(IF('Model inputs'!B325="",0,1)="",0,IF('Model inputs'!B325="",0,1)),IF(IF('Model inputs'!B326="",0,1)="",0,IF('Model inputs'!B326="",0,1)),IF(IF('Model inputs'!B327="",0,1)="",0,IF('Model inputs'!B327="",0,1)),IF(IF('Model inputs'!B328="",0,1)="",0,IF('Model inputs'!B328="",0,1)),IF(IF('Model inputs'!B329="",0,1)="",0,IF('Model inputs'!B329="",0,1)))=0,"",SUM('Model inputs'!B325,'Model inputs'!B326,'Model inputs'!B327,'Model inputs'!B328,'Model inputs'!B329)) -> 5 | M22: =IF(SUM(IF(IF('Model inputs'!B330="",0,1)="",0,IF('Model inputs'!B330="",0,1)),IF(IF('Model inputs'!B331="",0,1)="",0,IF('Model inputs'!B331="",0,1)),IF(IF('Model inputs'!B332="",0,1)="",0,IF('Model inputs'!B332="",0,1)),IF(IF('Model inputs'!B333="",0,1)="",0,IF('Model inputs'!B333="",0,1)),IF(IF('Model inputs'!B334="",0,1)="",0,IF('Model inputs'!B334="",0,1)))=0,"",SUM('Model inputs'!B330,'Model inputs'!B331,'Model inputs'!B332,'Model inputs'!B333,'Model inputs'!B334)) -> 10 | N22: =IF(SUM(IF(IF('Model inputs'!B335="",0,1)="",0,IF('Model inputs'!B335="",0,1)),IF(IF('Model inputs'!B336="",0,1)="",0,IF('Model inputs'!B336="",0,1)),IF(IF('Model inputs'!B337="",0,1)="",0,IF('Model inputs'!B337="",0,1)),IF(IF('Model inputs'!B338="",0,1)="",0,IF('Model inputs'!B338="",0,1)),IF(IF('Model inputs'!B339="",0,1)="",0,IF('Model inputs'!B339="",0,1)))=0,"",SUM('Model inputs'!B335,'Model inputs'!B336,'Model inputs'!B337,'Model inputs'!B338,'Model inputs'!B339)) -> 15 | O22: =IF(SUM(IF(IF('Model inputs'!B340="",0,1)="",0,IF('Model inputs'!B340="",0,1)),IF(IF('Model inputs'!B341="",0,1)="",0,IF('Model inputs'!B341="",0,1)),IF(IF('Model inputs'!B342="",0,1)="",0,IF('Model inputs'!B342="",0,1)),IF(IF('Model inputs'!B343="",0,1)="",0,IF('Model inputs'!B343="",0,1)),IF(IF('Model inputs'!B344="",0,1)="",0,IF('Model inputs'!B344="",0,1)))=0,"",SUM('Model inputs'!B340,'Model inputs'!B341,'Model inputs'!B342,'Model inputs'!B343,'Model inputs'!B344)) -> 20 | P22: =IF(SUM(IF(IF('Model inputs'!B345="",0,1)="",0,IF('Model inputs'!B345="",0,1)),IF(IF('Model inputs'!B346="",0,1)="",0,IF('Model inputs'!B346="",0,1)),IF(IF('Model inputs'!B347="",0,1)="",0,IF('Model inputs'!B347="",0,1)),IF(IF('Model inputs'!B348="",0,1)="",0,IF('Model inputs'!B348="",0,1)),IF(IF('Model inputs'!B349="",0,1)="",0,IF('Model inputs'!B349="",0,1)))=0,"",SUM('Model inputs'!B345,'Model inputs'!B346,'Model inputs'!B347,'Model inputs'!B348,'Model inputs'!B349)) -> 25 | Q22: =IF(SUM(IF(IF('Model inputs'!B350="",0,1)="",0,IF('Model inputs'!B350="",0,1)),IF(IF('Model inputs'!B351="",0,1)="",0,IF('Model inputs'!B351="",0,1)),IF(IF('Model inputs'!B352="",0,1)="",0,IF('Model inputs'!B352="",0,1)),IF(IF('Model inputs'!B353="",0,1)="",0,IF('Model inputs'!B353="",0,1)),IF(IF('Model inputs'!B354="",0,1)="",0,IF('Model inputs'!B354="",0,1)))=0,"",SUM('Model inputs'!B350,'Model inputs'!B351,'Model inputs'!B352,'Model inputs'!B353,'Model inputs'!B354)) -> 30 | R22: =IF(SUM(IF(IF('Model inputs'!B355="",0,1)="",0,IF('Model inputs'!B355="",0,1)),IF(IF('Model inputs'!B356="",0,1)="",0,IF('Model inputs'!B356="",0,1)),IF(IF('Model inputs'!B357="",0,1)="",0,IF('Model inputs'!B357="",0,1)),IF(IF('Model inputs'!B358="",0,1)="",0,IF('Model inputs'!B358="",0,1)),IF(IF('Model inputs'!B359="",0,1)="",0,IF('Model inputs'!B359="",0,1)))=0,"",SUM('Model inputs'!B355,'Model inputs'!B356,'Model inputs'!B357,'Model inputs'!B358,'Model inputs'!B359)) -> 35 | S22: =IF(SUM(IF(IF('Model inputs'!B360="",0,1)="",0,IF('Model inputs'!B360="",0,1)),IF(IF('Model inputs'!B361="",0,1)="",0,IF('Model inputs'!B361="",0,1)),IF(IF('Model inputs'!B362="",0,1)="",0,IF('Model inputs'!B362="",0,1)),IF(IF('Model inputs'!B363="",0,1)="",0,IF('Model inputs'!B363="",0,1)),IF(IF('Model inputs'!B364="",0,1)="",0,IF('Model inputs'!B364="",0,1)))=0,"",SUM('Model inputs'!B360,'Model inputs'!B361,'Model inputs'!B362,'Model inputs'!B363,'Model inputs'!B364)) -> 40 | T22: =IF(SUM(IF(IF('Model inputs'!B365="",0,1)="",0,IF('Model inputs'!B365="",0,1)),IF(IF('Model inputs'!B366="",0,1)="",0,IF('Model inputs'!B366="",0,1)),IF(IF('Model inputs'!B367="",0,1)="",0,IF('Model inputs'!B367="",0,1)),IF(IF('Model inputs'!B368="",0,1)="",0,IF('Model inputs'!B368="",0,1)),IF(IF('Model inputs'!B369="",0,1)="",0,IF('Model inputs'!B369="",0,1)))=0,"",SUM('Model inputs'!B365,'Model inputs'!B366,'Model inputs'!B367,'Model inputs'!B368,'Model inputs'!B369)) -> 45 | U22: =IF(SUM(IF(IF('Model inputs'!B370="",0,1)="",0,IF('Model inputs'!B370="",0,1)),IF(IF('Model inputs'!B371="",0,1)="",0,IF('Model inputs'!B371="",0,1)),IF(IF('Model inputs'!B372="",0,1)="",0,IF('Model inputs'!B372="",0,1)),IF(IF('Model inputs'!B373="",0,1)="",0,IF('Model inputs'!B373="",0,1)),IF(IF('Model inputs'!B374="",0,1)="",0,IF('Model inputs'!B374="",0,1)))=0,"",SUM('Model inputs'!B370,'Model inputs'!B371,'Model inputs'!B372,'Model inputs'!B373,'Model inputs'!B374)) -> 50 | V22: =IF(SUM(IF(IF('Model inputs'!B375="",0,1)="",0,IF('Model inputs'!B375="",0,1)),IF(IF('Model inputs'!B376="",0,1)="",0,IF('Model inputs'!B376="",0,1)),IF(IF('Model inputs'!B377="",0,1)="",0,IF('Model inputs'!B377="",0,1)),IF(IF('Model inputs'!B378="",0,1)="",0,IF('Model inputs'!B378="",0,1)),IF(IF('Model inputs'!B379="",0,1)="",0,IF('Model inputs'!B379="",0,1)))=0,"",SUM('Model inputs'!B375,'Model inputs'!B376,'Model inputs'!B377,'Model inputs'!B378,'Model inputs'!B379)) -> 55 | W22: =IF(SUM(IF(IF('Model inputs'!B380="",0,1)="",0,IF('Model inputs'!B380="",0,1)),IF(IF('Model inputs'!B381="",0,1)="",0,IF('Model inputs'!B381="",0,1)),IF(IF('Model inputs'!B382="",0,1)="",0,IF('Model inputs'!B382="",0,1)),IF(IF('Model inputs'!B383="",0,1)="",0,IF('Model inputs'!B383="",0,1)),IF(IF('Model inputs'!B384="",0,1)="",0,IF('Model inputs'!B384="",0,1)))=0,"",SUM('Model inputs'!B380,'Model inputs'!B381,'Model inputs'!B382,'Model inputs'!B383,'Model inputs'!B384)) -> 60 | X22: =IF(SUM(IF(IF('Model inputs'!B385="",0,1)="",0,IF('Model inputs'!B385="",0,1)),IF(IF('Model inputs'!B386="",0,1)="",0,IF('Model inputs'!B386="",0,1)),IF(IF('Model inputs'!B387="",0,1)="",0,IF('Model inputs'!B387="",0,1)),IF(IF('Model inputs'!B388="",0,1)="",0,IF('Model inputs'!B388="",0,1)),IF(IF('Model inputs'!B389="",0,1)="",0,IF('Model inputs'!B389="",0,1)))=0,"",SUM('Model inputs'!B385,'Model inputs'!B386,'Model inputs'!B387,'Model inputs'!B388,'Model inputs'!B389)) -> 60 | Y22: =IF(SUM(IF(IF('Model inputs'!B390="",0,1)="",0,IF('Model inputs'!B390="",0,1)),IF(IF('Model inputs'!B391="",0,1)="",0,IF('Model inputs'!B391="",0,1)),IF(IF('Model inputs'!B392="",0,1)="",0,IF('Model inputs'!B392="",0,1)),IF(IF('Model inputs'!B393="",0,1)="",0,IF('Model inputs'!B393="",0,1)),IF(IF('Model inputs'!B394="",0,1)="",0,IF('Model inputs'!B394="",0,1)))=0,"",SUM('Model inputs'!B390,'Model inputs'!B391,'Model inputs'!B392,'Model inputs'!B393,'Model inputs'!B394)) -> 60 | Z22: =IF(SUM(IF(IF('Model inputs'!B395="",0,1)="",0,IF('Model inputs'!B395="",0,1)),IF(IF('Model inputs'!B396="",0,1)="",0,IF('Model inputs'!B396="",0,1)),IF(IF('Model inputs'!B397="",0,1)="",0,IF('Model inputs'!B397="",0,1)),IF(IF('Model inputs'!B398="",0,1)="",0,IF('Model inputs'!B398="",0,1)),IF(IF('Model inputs'!B399="",0,1)="",0,IF('Model inputs'!B399="",0,1)))=0,"",SUM('Model inputs'!B395,'Model inputs'!B396,'Model inputs'!B397,'Model inputs'!B398,'Model inputs'!B399)) -> 60
A23: Plan Audits delivered · Conservative | C23: 0 | D23: 0 | E23: 0 | F23: 0 | G23: 0 | H23: 0 | I23: 0 | J23: 0 | K23: 0 | L23: =IF(SUM(IF(IF('Model inputs'!B400="",0,1)="",0,IF('Model inputs'!B400="",0,1)),IF(IF('Model inputs'!B401="",0,1)="",0,IF('Model inputs'!B401="",0,1)),IF(IF('Model inputs'!B402="",0,1)="",0,IF('Model inputs'!B402="",0,1)),IF(IF('Model inputs'!B403="",0,1)="",0,IF('Model inputs'!B403="",0,1)),IF(IF('Model inputs'!B404="",0,1)="",0,IF('Model inputs'!B404="",0,1)))=0,"",SUM('Model inputs'!B400,'Model inputs'!B401,'Model inputs'!B402,'Model inputs'!B403,'Model inputs'!B404)) -> 0 | M23: =IF(SUM(IF(IF('Model inputs'!B405="",0,1)="",0,IF('Model inputs'!B405="",0,1)),IF(IF('Model inputs'!B406="",0,1)="",0,IF('Model inputs'!B406="",0,1)),IF(IF('Model inputs'!B407="",0,1)="",0,IF('Model inputs'!B407="",0,1)),IF(IF('Model inputs'!B408="",0,1)="",0,IF('Model inputs'!B408="",0,1)),IF(IF('Model inputs'!B409="",0,1)="",0,IF('Model inputs'!B409="",0,1)))=0,"",SUM('Model inputs'!B405,'Model inputs'!B406,'Model inputs'!B407,'Model inputs'!B408,'Model inputs'!B409)) -> 0 | N23: =IF(SUM(IF(IF('Model inputs'!B410="",0,1)="",0,IF('Model inputs'!B410="",0,1)),IF(IF('Model inputs'!B411="",0,1)="",0,IF('Model inputs'!B411="",0,1)),IF(IF('Model inputs'!B412="",0,1)="",0,IF('Model inputs'!B412="",0,1)),IF(IF('Model inputs'!B413="",0,1)="",0,IF('Model inputs'!B413="",0,1)),IF(IF('Model inputs'!B414="",0,1)="",0,IF('Model inputs'!B414="",0,1)))=0,"",SUM('Model inputs'!B410,'Model inputs'!B411,'Model inputs'!B412,'Model inputs'!B413,'Model inputs'!B414)) -> 4 | O23: =IF(SUM(IF(IF('Model inputs'!B415="",0,1)="",0,IF('Model inputs'!B415="",0,1)),IF(IF('Model inputs'!B416="",0,1)="",0,IF('Model inputs'!B416="",0,1)),IF(IF('Model inputs'!B417="",0,1)="",0,IF('Model inputs'!B417="",0,1)),IF(IF('Model inputs'!B418="",0,1)="",0,IF('Model inputs'!B418="",0,1)),IF(IF('Model inputs'!B419="",0,1)="",0,IF('Model inputs'!B419="",0,1)))=0,"",SUM('Model inputs'!B415,'Model inputs'!B416,'Model inputs'!B417,'Model inputs'!B418,'Model inputs'!B419)) -> 4 | P23: =IF(SUM(IF(IF('Model inputs'!B420="",0,1)="",0,IF('Model inputs'!B420="",0,1)),IF(IF('Model inputs'!B421="",0,1)="",0,IF('Model inputs'!B421="",0,1)),IF(IF('Model inputs'!B422="",0,1)="",0,IF('Model inputs'!B422="",0,1)),IF(IF('Model inputs'!B423="",0,1)="",0,IF('Model inputs'!B423="",0,1)),IF(IF('Model inputs'!B424="",0,1)="",0,IF('Model inputs'!B424="",0,1)))=0,"",SUM('Model inputs'!B420,'Model inputs'!B421,'Model inputs'!B422,'Model inputs'!B423,'Model inputs'!B424)) -> 4 | Q23: =IF(SUM(IF(IF('Model inputs'!B425="",0,1)="",0,IF('Model inputs'!B425="",0,1)),IF(IF('Model inputs'!B426="",0,1)="",0,IF('Model inputs'!B426="",0,1)),IF(IF('Model inputs'!B427="",0,1)="",0,IF('Model inputs'!B427="",0,1)),IF(IF('Model inputs'!B428="",0,1)="",0,IF('Model inputs'!B428="",0,1)),IF(IF('Model inputs'!B429="",0,1)="",0,IF('Model inputs'!B429="",0,1)))=0,"",SUM('Model inputs'!B425,'Model inputs'!B426,'Model inputs'!B427,'Model inputs'!B428,'Model inputs'!B429)) -> 4 | R23: =IF(SUM(IF(IF('Model inputs'!B430="",0,1)="",0,IF('Model inputs'!B430="",0,1)),IF(IF('Model inputs'!B431="",0,1)="",0,IF('Model inputs'!B431="",0,1)),IF(IF('Model inputs'!B432="",0,1)="",0,IF('Model inputs'!B432="",0,1)),IF(IF('Model inputs'!B433="",0,1)="",0,IF('Model inputs'!B433="",0,1)),IF(IF('Model inputs'!B434="",0,1)="",0,IF('Model inputs'!B434="",0,1)))=0,"",SUM('Model inputs'!B430,'Model inputs'!B431,'Model inputs'!B432,'Model inputs'!B433,'Model inputs'!B434)) -> 4 | S23: =IF(SUM(IF(IF('Model inputs'!B435="",0,1)="",0,IF('Model inputs'!B435="",0,1)),IF(IF('Model inputs'!B436="",0,1)="",0,IF('Model inputs'!B436="",0,1)),IF(IF('Model inputs'!B437="",0,1)="",0,IF('Model inputs'!B437="",0,1)),IF(IF('Model inputs'!B438="",0,1)="",0,IF('Model inputs'!B438="",0,1)),IF(IF('Model inputs'!B439="",0,1)="",0,IF('Model inputs'!B439="",0,1)))=0,"",SUM('Model inputs'!B435,'Model inputs'!B436,'Model inputs'!B437,'Model inputs'!B438,'Model inputs'!B439)) -> 4 | T23: =IF(SUM(IF(IF('Model inputs'!B440="",0,1)="",0,IF('Model inputs'!B440="",0,1)),IF(IF('Model inputs'!B441="",0,1)="",0,IF('Model inputs'!B441="",0,1)),IF(IF('Model inputs'!B442="",0,1)="",0,IF('Model inputs'!B442="",0,1)),IF(IF('Model inputs'!B443="",0,1)="",0,IF('Model inputs'!B443="",0,1)),IF(IF('Model inputs'!B444="",0,1)="",0,IF('Model inputs'!B444="",0,1)))=0,"",SUM('Model inputs'!B440,'Model inputs'!B441,'Model inputs'!B442,'Model inputs'!B443,'Model inputs'!B444)) -> 4 | U23: =IF(SUM(IF(IF('Model inputs'!B445="",0,1)="",0,IF('Model inputs'!B445="",0,1)),IF(IF('Model inputs'!B446="",0,1)="",0,IF('Model inputs'!B446="",0,1)),IF(IF('Model inputs'!B447="",0,1)="",0,IF('Model inputs'!B447="",0,1)),IF(IF('Model inputs'!B448="",0,1)="",0,IF('Model inputs'!B448="",0,1)),IF(IF('Model inputs'!B449="",0,1)="",0,IF('Model inputs'!B449="",0,1)))=0,"",SUM('Model inputs'!B445,'Model inputs'!B446,'Model inputs'!B447,'Model inputs'!B448,'Model inputs'!B449)) -> 4 | V23: =IF(SUM(IF(IF('Model inputs'!B450="",0,1)="",0,IF('Model inputs'!B450="",0,1)),IF(IF('Model inputs'!B451="",0,1)="",0,IF('Model inputs'!B451="",0,1)),IF(IF('Model inputs'!B452="",0,1)="",0,IF('Model inputs'!B452="",0,1)),IF(IF('Model inputs'!B453="",0,1)="",0,IF('Model inputs'!B453="",0,1)),IF(IF('Model inputs'!B454="",0,1)="",0,IF('Model inputs'!B454="",0,1)))=0,"",SUM('Model inputs'!B450,'Model inputs'!B451,'Model inputs'!B452,'Model inputs'!B453,'Model inputs'!B454)) -> 4 | W23: =IF(SUM(IF(IF('Model inputs'!B455="",0,1)="",0,IF('Model inputs'!B455="",0,1)),IF(IF('Model inputs'!B456="",0,1)="",0,IF('Model inputs'!B456="",0,1)),IF(IF('Model inputs'!B457="",0,1)="",0,IF('Model inputs'!B457="",0,1)),IF(IF('Model inputs'!B458="",0,1)="",0,IF('Model inputs'!B458="",0,1)),IF(IF('Model inputs'!B459="",0,1)="",0,IF('Model inputs'!B459="",0,1)))=0,"",SUM('Model inputs'!B455,'Model inputs'!B456,'Model inputs'!B457,'Model inputs'!B458,'Model inputs'!B459)) -> 4 | X23: =IF(SUM(IF(IF('Model inputs'!B460="",0,1)="",0,IF('Model inputs'!B460="",0,1)),IF(IF('Model inputs'!B461="",0,1)="",0,IF('Model inputs'!B461="",0,1)),IF(IF('Model inputs'!B462="",0,1)="",0,IF('Model inputs'!B462="",0,1)),IF(IF('Model inputs'!B463="",0,1)="",0,IF('Model inputs'!B463="",0,1)),IF(IF('Model inputs'!B464="",0,1)="",0,IF('Model inputs'!B464="",0,1)))=0,"",SUM('Model inputs'!B460,'Model inputs'!B461,'Model inputs'!B462,'Model inputs'!B463,'Model inputs'!B464)) -> 4 | Y23: =IF(SUM(IF(IF('Model inputs'!B465="",0,1)="",0,IF('Model inputs'!B465="",0,1)),IF(IF('Model inputs'!B466="",0,1)="",0,IF('Model inputs'!B466="",0,1)),IF(IF('Model inputs'!B467="",0,1)="",0,IF('Model inputs'!B467="",0,1)),IF(IF('Model inputs'!B468="",0,1)="",0,IF('Model inputs'!B468="",0,1)),IF(IF('Model inputs'!B469="",0,1)="",0,IF('Model inputs'!B469="",0,1)))=0,"",SUM('Model inputs'!B465,'Model inputs'!B466,'Model inputs'!B467,'Model inputs'!B468,'Model inputs'!B469)) -> 4 | Z23: =IF(SUM(IF(IF('Model inputs'!B470="",0,1)="",0,IF('Model inputs'!B470="",0,1)),IF(IF('Model inputs'!B471="",0,1)="",0,IF('Model inputs'!B471="",0,1)),IF(IF('Model inputs'!B472="",0,1)="",0,IF('Model inputs'!B472="",0,1)),IF(IF('Model inputs'!B473="",0,1)="",0,IF('Model inputs'!B473="",0,1)),IF(IF('Model inputs'!B474="",0,1)="",0,IF('Model inputs'!B474="",0,1)))=0,"",SUM('Model inputs'!B470,'Model inputs'!B471,'Model inputs'!B472,'Model inputs'!B473,'Model inputs'!B474)) -> 4
A24: Plan Cash collections · Growth | C24: 0 | D24: 0 | E24: 0 | F24: 0 | G24: 0 | H24: 0 | I24: 0 | J24: 0 | K24: 0 | L24: =IF(SUM(IF(IF('Model inputs'!B475="",0,1)="",0,IF('Model inputs'!B475="",0,1)),IF(IF('Model inputs'!B476="",0,1)="",0,IF('Model inputs'!B476="",0,1)),IF(IF('Model inputs'!B477="",0,1)="",0,IF('Model inputs'!B477="",0,1)),IF(IF('Model inputs'!B478="",0,1)="",0,IF('Model inputs'!B478="",0,1)),IF(IF('Model inputs'!B479="",0,1)="",0,IF('Model inputs'!B479="",0,1)))=0,"",SUM('Model inputs'!B475,'Model inputs'!B476,'Model inputs'!B477,'Model inputs'!B478,'Model inputs'!B479)) -> 32500 | M24: =IF(SUM(IF(IF('Model inputs'!B480="",0,1)="",0,IF('Model inputs'!B480="",0,1)),IF(IF('Model inputs'!B481="",0,1)="",0,IF('Model inputs'!B481="",0,1)),IF(IF('Model inputs'!B482="",0,1)="",0,IF('Model inputs'!B482="",0,1)),IF(IF('Model inputs'!B483="",0,1)="",0,IF('Model inputs'!B483="",0,1)),IF(IF('Model inputs'!B484="",0,1)="",0,IF('Model inputs'!B484="",0,1)))=0,"",SUM('Model inputs'!B480,'Model inputs'!B481,'Model inputs'!B482,'Model inputs'!B483,'Model inputs'!B484)) -> 35000 | N24: =IF(SUM(IF(IF('Model inputs'!B485="",0,1)="",0,IF('Model inputs'!B485="",0,1)),IF(IF('Model inputs'!B486="",0,1)="",0,IF('Model inputs'!B486="",0,1)),IF(IF('Model inputs'!B487="",0,1)="",0,IF('Model inputs'!B487="",0,1)),IF(IF('Model inputs'!B488="",0,1)="",0,IF('Model inputs'!B488="",0,1)),IF(IF('Model inputs'!B489="",0,1)="",0,IF('Model inputs'!B489="",0,1)))=0,"",SUM('Model inputs'!B485,'Model inputs'!B486,'Model inputs'!B487,'Model inputs'!B488,'Model inputs'!B489)) -> 37500 | O24: =IF(SUM(IF(IF('Model inputs'!B490="",0,1)="",0,IF('Model inputs'!B490="",0,1)),IF(IF('Model inputs'!B491="",0,1)="",0,IF('Model inputs'!B491="",0,1)),IF(IF('Model inputs'!B492="",0,1)="",0,IF('Model inputs'!B492="",0,1)),IF(IF('Model inputs'!B493="",0,1)="",0,IF('Model inputs'!B493="",0,1)),IF(IF('Model inputs'!B494="",0,1)="",0,IF('Model inputs'!B494="",0,1)))=0,"",SUM('Model inputs'!B490,'Model inputs'!B491,'Model inputs'!B492,'Model inputs'!B493,'Model inputs'!B494)) -> 40000 | P24: =IF(SUM(IF(IF('Model inputs'!B495="",0,1)="",0,IF('Model inputs'!B495="",0,1)),IF(IF('Model inputs'!B496="",0,1)="",0,IF('Model inputs'!B496="",0,1)),IF(IF('Model inputs'!B497="",0,1)="",0,IF('Model inputs'!B497="",0,1)),IF(IF('Model inputs'!B498="",0,1)="",0,IF('Model inputs'!B498="",0,1)),IF(IF('Model inputs'!B499="",0,1)="",0,IF('Model inputs'!B499="",0,1)))=0,"",SUM('Model inputs'!B495,'Model inputs'!B496,'Model inputs'!B497,'Model inputs'!B498,'Model inputs'!B499)) -> 42500 | Q24: =IF(SUM(IF(IF('Model inputs'!B500="",0,1)="",0,IF('Model inputs'!B500="",0,1)),IF(IF('Model inputs'!B501="",0,1)="",0,IF('Model inputs'!B501="",0,1)),IF(IF('Model inputs'!B502="",0,1)="",0,IF('Model inputs'!B502="",0,1)),IF(IF('Model inputs'!B503="",0,1)="",0,IF('Model inputs'!B503="",0,1)),IF(IF('Model inputs'!B504="",0,1)="",0,IF('Model inputs'!B504="",0,1)))=0,"",SUM('Model inputs'!B500,'Model inputs'!B501,'Model inputs'!B502,'Model inputs'!B503,'Model inputs'!B504)) -> 45000 | R24: =IF(SUM(IF(IF('Model inputs'!B505="",0,1)="",0,IF('Model inputs'!B505="",0,1)),IF(IF('Model inputs'!B506="",0,1)="",0,IF('Model inputs'!B506="",0,1)),IF(IF('Model inputs'!B507="",0,1)="",0,IF('Model inputs'!B507="",0,1)),IF(IF('Model inputs'!B508="",0,1)="",0,IF('Model inputs'!B508="",0,1)),IF(IF('Model inputs'!B509="",0,1)="",0,IF('Model inputs'!B509="",0,1)))=0,"",SUM('Model inputs'!B505,'Model inputs'!B506,'Model inputs'!B507,'Model inputs'!B508,'Model inputs'!B509)) -> 47500 | S24: =IF(SUM(IF(IF('Model inputs'!B510="",0,1)="",0,IF('Model inputs'!B510="",0,1)),IF(IF('Model inputs'!B511="",0,1)="",0,IF('Model inputs'!B511="",0,1)),IF(IF('Model inputs'!B512="",0,1)="",0,IF('Model inputs'!B512="",0,1)),IF(IF('Model inputs'!B513="",0,1)="",0,IF('Model inputs'!B513="",0,1)),IF(IF('Model inputs'!B514="",0,1)="",0,IF('Model inputs'!B514="",0,1)))=0,"",SUM('Model inputs'!B510,'Model inputs'!B511,'Model inputs'!B512,'Model inputs'!B513,'Model inputs'!B514)) -> 50000 | T24: =IF(SUM(IF(IF('Model inputs'!B515="",0,1)="",0,IF('Model inputs'!B515="",0,1)),IF(IF('Model inputs'!B516="",0,1)="",0,IF('Model inputs'!B516="",0,1)),IF(IF('Model inputs'!B517="",0,1)="",0,IF('Model inputs'!B517="",0,1)),IF(IF('Model inputs'!B518="",0,1)="",0,IF('Model inputs'!B518="",0,1)),IF(IF('Model inputs'!B519="",0,1)="",0,IF('Model inputs'!B519="",0,1)))=0,"",SUM('Model inputs'!B515,'Model inputs'!B516,'Model inputs'!B517,'Model inputs'!B518,'Model inputs'!B519)) -> 52500 | U24: =IF(SUM(IF(IF('Model inputs'!B520="",0,1)="",0,IF('Model inputs'!B520="",0,1)),IF(IF('Model inputs'!B521="",0,1)="",0,IF('Model inputs'!B521="",0,1)),IF(IF('Model inputs'!B522="",0,1)="",0,IF('Model inputs'!B522="",0,1)),IF(IF('Model inputs'!B523="",0,1)="",0,IF('Model inputs'!B523="",0,1)),IF(IF('Model inputs'!B524="",0,1)="",0,IF('Model inputs'!B524="",0,1)))=0,"",SUM('Model inputs'!B520,'Model inputs'!B521,'Model inputs'!B522,'Model inputs'!B523,'Model inputs'!B524)) -> 55000 | V24: =IF(SUM(IF(IF('Model inputs'!B525="",0,1)="",0,IF('Model inputs'!B525="",0,1)),IF(IF('Model inputs'!B526="",0,1)="",0,IF('Model inputs'!B526="",0,1)),IF(IF('Model inputs'!B527="",0,1)="",0,IF('Model inputs'!B527="",0,1)),IF(IF('Model inputs'!B528="",0,1)="",0,IF('Model inputs'!B528="",0,1)),IF(IF('Model inputs'!B529="",0,1)="",0,IF('Model inputs'!B529="",0,1)))=0,"",SUM('Model inputs'!B525,'Model inputs'!B526,'Model inputs'!B527,'Model inputs'!B528,'Model inputs'!B529)) -> 57500 | W24: =IF(SUM(IF(IF('Model inputs'!B530="",0,1)="",0,IF('Model inputs'!B530="",0,1)),IF(IF('Model inputs'!B531="",0,1)="",0,IF('Model inputs'!B531="",0,1)),IF(IF('Model inputs'!B532="",0,1)="",0,IF('Model inputs'!B532="",0,1)),IF(IF('Model inputs'!B533="",0,1)="",0,IF('Model inputs'!B533="",0,1)),IF(IF('Model inputs'!B534="",0,1)="",0,IF('Model inputs'!B534="",0,1)))=0,"",SUM('Model inputs'!B530,'Model inputs'!B531,'Model inputs'!B532,'Model inputs'!B533,'Model inputs'!B534)) -> 60000 | X24: =IF(SUM(IF(IF('Model inputs'!B535="",0,1)="",0,IF('Model inputs'!B535="",0,1)),IF(IF('Model inputs'!B536="",0,1)="",0,IF('Model inputs'!B536="",0,1)),IF(IF('Model inputs'!B537="",0,1)="",0,IF('Model inputs'!B537="",0,1)),IF(IF('Model inputs'!B538="",0,1)="",0,IF('Model inputs'!B538="",0,1)),IF(IF('Model inputs'!B539="",0,1)="",0,IF('Model inputs'!B539="",0,1)))=0,"",SUM('Model inputs'!B535,'Model inputs'!B536,'Model inputs'!B537,'Model inputs'!B538,'Model inputs'!B539)) -> 30000 | Y24: =IF(SUM(IF(IF('Model inputs'!B540="",0,1)="",0,IF('Model inputs'!B540="",0,1)),IF(IF('Model inputs'!B541="",0,1)="",0,IF('Model inputs'!B541="",0,1)),IF(IF('Model inputs'!B542="",0,1)="",0,IF('Model inputs'!B542="",0,1)),IF(IF('Model inputs'!B543="",0,1)="",0,IF('Model inputs'!B543="",0,1)),IF(IF('Model inputs'!B544="",0,1)="",0,IF('Model inputs'!B544="",0,1)))=0,"",SUM('Model inputs'!B540,'Model inputs'!B541,'Model inputs'!B542,'Model inputs'!B543,'Model inputs'!B544)) -> 30000 | Z24: =IF(SUM(IF(IF('Model inputs'!B545="",0,1)="",0,IF('Model inputs'!B545="",0,1)),IF(IF('Model inputs'!B546="",0,1)="",0,IF('Model inputs'!B546="",0,1)),IF(IF('Model inputs'!B547="",0,1)="",0,IF('Model inputs'!B547="",0,1)),IF(IF('Model inputs'!B548="",0,1)="",0,IF('Model inputs'!B548="",0,1)),IF(IF('Model inputs'!B549="",0,1)="",0,IF('Model inputs'!B549="",0,1)))=0,"",SUM('Model inputs'!B545,'Model inputs'!B546,'Model inputs'!B547,'Model inputs'!B548,'Model inputs'!B549)) -> 30000
A25: Plan Cash collections · Conservative | C25: 0 | D25: 0 | E25: 0 | F25: 0 | G25: 0 | H25: 0 | I25: 0 | J25: 0 | K25: 0 | L25: =IF(SUM(IF(IF('Model inputs'!B550="",0,1)="",0,IF('Model inputs'!B550="",0,1)),IF(IF('Model inputs'!B551="",0,1)="",0,IF('Model inputs'!B551="",0,1)),IF(IF('Model inputs'!B552="",0,1)="",0,IF('Model inputs'!B552="",0,1)),IF(IF('Model inputs'!B553="",0,1)="",0,IF('Model inputs'!B553="",0,1)),IF(IF('Model inputs'!B554="",0,1)="",0,IF('Model inputs'!B554="",0,1)))=0,"",SUM('Model inputs'!B550,'Model inputs'!B551,'Model inputs'!B552,'Model inputs'!B553,'Model inputs'!B554)) -> 0 | M25: =IF(SUM(IF(IF('Model inputs'!B555="",0,1)="",0,IF('Model inputs'!B555="",0,1)),IF(IF('Model inputs'!B556="",0,1)="",0,IF('Model inputs'!B556="",0,1)),IF(IF('Model inputs'!B557="",0,1)="",0,IF('Model inputs'!B557="",0,1)),IF(IF('Model inputs'!B558="",0,1)="",0,IF('Model inputs'!B558="",0,1)),IF(IF('Model inputs'!B559="",0,1)="",0,IF('Model inputs'!B559="",0,1)))=0,"",SUM('Model inputs'!B555,'Model inputs'!B556,'Model inputs'!B557,'Model inputs'!B558,'Model inputs'!B559)) -> 0 | N25: =IF(SUM(IF(IF('Model inputs'!B560="",0,1)="",0,IF('Model inputs'!B560="",0,1)),IF(IF('Model inputs'!B561="",0,1)="",0,IF('Model inputs'!B561="",0,1)),IF(IF('Model inputs'!B562="",0,1)="",0,IF('Model inputs'!B562="",0,1)),IF(IF('Model inputs'!B563="",0,1)="",0,IF('Model inputs'!B563="",0,1)),IF(IF('Model inputs'!B564="",0,1)="",0,IF('Model inputs'!B564="",0,1)))=0,"",SUM('Model inputs'!B560,'Model inputs'!B561,'Model inputs'!B562,'Model inputs'!B563,'Model inputs'!B564)) -> 3000 | O25: =IF(SUM(IF(IF('Model inputs'!B565="",0,1)="",0,IF('Model inputs'!B565="",0,1)),IF(IF('Model inputs'!B566="",0,1)="",0,IF('Model inputs'!B566="",0,1)),IF(IF('Model inputs'!B567="",0,1)="",0,IF('Model inputs'!B567="",0,1)),IF(IF('Model inputs'!B568="",0,1)="",0,IF('Model inputs'!B568="",0,1)),IF(IF('Model inputs'!B569="",0,1)="",0,IF('Model inputs'!B569="",0,1)))=0,"",SUM('Model inputs'!B565,'Model inputs'!B566,'Model inputs'!B567,'Model inputs'!B568,'Model inputs'!B569)) -> 3000 | P25: =IF(SUM(IF(IF('Model inputs'!B570="",0,1)="",0,IF('Model inputs'!B570="",0,1)),IF(IF('Model inputs'!B571="",0,1)="",0,IF('Model inputs'!B571="",0,1)),IF(IF('Model inputs'!B572="",0,1)="",0,IF('Model inputs'!B572="",0,1)),IF(IF('Model inputs'!B573="",0,1)="",0,IF('Model inputs'!B573="",0,1)),IF(IF('Model inputs'!B574="",0,1)="",0,IF('Model inputs'!B574="",0,1)))=0,"",SUM('Model inputs'!B570,'Model inputs'!B571,'Model inputs'!B572,'Model inputs'!B573,'Model inputs'!B574)) -> 3000 | Q25: =IF(SUM(IF(IF('Model inputs'!B575="",0,1)="",0,IF('Model inputs'!B575="",0,1)),IF(IF('Model inputs'!B576="",0,1)="",0,IF('Model inputs'!B576="",0,1)),IF(IF('Model inputs'!B577="",0,1)="",0,IF('Model inputs'!B577="",0,1)),IF(IF('Model inputs'!B578="",0,1)="",0,IF('Model inputs'!B578="",0,1)),IF(IF('Model inputs'!B579="",0,1)="",0,IF('Model inputs'!B579="",0,1)))=0,"",SUM('Model inputs'!B575,'Model inputs'!B576,'Model inputs'!B577,'Model inputs'!B578,'Model inputs'!B579)) -> 3000 | R25: =IF(SUM(IF(IF('Model inputs'!B580="",0,1)="",0,IF('Model inputs'!B580="",0,1)),IF(IF('Model inputs'!B581="",0,1)="",0,IF('Model inputs'!B581="",0,1)),IF(IF('Model inputs'!B582="",0,1)="",0,IF('Model inputs'!B582="",0,1)),IF(IF('Model inputs'!B583="",0,1)="",0,IF('Model inputs'!B583="",0,1)),IF(IF('Model inputs'!B584="",0,1)="",0,IF('Model inputs'!B584="",0,1)))=0,"",SUM('Model inputs'!B580,'Model inputs'!B581,'Model inputs'!B582,'Model inputs'!B583,'Model inputs'!B584)) -> 3000 | S25: =IF(SUM(IF(IF('Model inputs'!B585="",0,1)="",0,IF('Model inputs'!B585="",0,1)),IF(IF('Model inputs'!B586="",0,1)="",0,IF('Model inputs'!B586="",0,1)),IF(IF('Model inputs'!B587="",0,1)="",0,IF('Model inputs'!B587="",0,1)),IF(IF('Model inputs'!B588="",0,1)="",0,IF('Model inputs'!B588="",0,1)),IF(IF('Model inputs'!B589="",0,1)="",0,IF('Model inputs'!B589="",0,1)))=0,"",SUM('Model inputs'!B585,'Model inputs'!B586,'Model inputs'!B587,'Model inputs'!B588,'Model inputs'!B589)) -> 3000 | T25: =IF(SUM(IF(IF('Model inputs'!B590="",0,1)="",0,IF('Model inputs'!B590="",0,1)),IF(IF('Model inputs'!B591="",0,1)="",0,IF('Model inputs'!B591="",0,1)),IF(IF('Model inputs'!B592="",0,1)="",0,IF('Model inputs'!B592="",0,1)),IF(IF('Model inputs'!B593="",0,1)="",0,IF('Model inputs'!B593="",0,1)),IF(IF('Model inputs'!B594="",0,1)="",0,IF('Model inputs'!B594="",0,1)))=0,"",SUM('Model inputs'!B590,'Model inputs'!B591,'Model inputs'!B592,'Model inputs'!B593,'Model inputs'!B594)) -> 3000 | U25: =IF(SUM(IF(IF('Model inputs'!B595="",0,1)="",0,IF('Model inputs'!B595="",0,1)),IF(IF('Model inputs'!B596="",0,1)="",0,IF('Model inputs'!B596="",0,1)),IF(IF('Model inputs'!B597="",0,1)="",0,IF('Model inputs'!B597="",0,1)),IF(IF('Model inputs'!B598="",0,1)="",0,IF('Model inputs'!B598="",0,1)),IF(IF('Model inputs'!B599="",0,1)="",0,IF('Model inputs'!B599="",0,1)))=0,"",SUM('Model inputs'!B595,'Model inputs'!B596,'Model inputs'!B597,'Model inputs'!B598,'Model inputs'!B599)) -> 3000 | V25: =IF(SUM(IF(IF('Model inputs'!B600="",0,1)="",0,IF('Model inputs'!B600="",0,1)),IF(IF('Model inputs'!B601="",0,1)="",0,IF('Model inputs'!B601="",0,1)),IF(IF('Model inputs'!B602="",0,1)="",0,IF('Model inputs'!B602="",0,1)),IF(IF('Model inputs'!B603="",0,1)="",0,IF('Model inputs'!B603="",0,1)),IF(IF('Model inputs'!B604="",0,1)="",0,IF('Model inputs'!B604="",0,1)))=0,"",SUM('Model inputs'!B600,'Model inputs'!B601,'Model inputs'!B602,'Model inputs'!B603,'Model inputs'!B604)) -> 3000 | W25: =IF(SUM(IF(IF('Model inputs'!B605="",0,1)="",0,IF('Model inputs'!B605="",0,1)),IF(IF('Model inputs'!B606="",0,1)="",0,IF('Model inputs'!B606="",0,1)),IF(IF('Model inputs'!B607="",0,1)="",0,IF('Model inputs'!B607="",0,1)),IF(IF('Model inputs'!B608="",0,1)="",0,IF('Model inputs'!B608="",0,1)),IF(IF('Model inputs'!B609="",0,1)="",0,IF('Model inputs'!B609="",0,1)))=0,"",SUM('Model inputs'!B605,'Model inputs'!B606,'Model inputs'!B607,'Model inputs'!B608,'Model inputs'!B609)) -> 3000 | X25: =IF(SUM(IF(IF('Model inputs'!B610="",0,1)="",0,IF('Model inputs'!B610="",0,1)),IF(IF('Model inputs'!B611="",0,1)="",0,IF('Model inputs'!B611="",0,1)),IF(IF('Model inputs'!B612="",0,1)="",0,IF('Model inputs'!B612="",0,1)),IF(IF('Model inputs'!B613="",0,1)="",0,IF('Model inputs'!B613="",0,1)),IF(IF('Model inputs'!B614="",0,1)="",0,IF('Model inputs'!B614="",0,1)))=0,"",SUM('Model inputs'!B610,'Model inputs'!B611,'Model inputs'!B612,'Model inputs'!B613,'Model inputs'!B614)) -> 3000 | Y25: =IF(SUM(IF(IF('Model inputs'!B615="",0,1)="",0,IF('Model inputs'!B615="",0,1)),IF(IF('Model inputs'!B616="",0,1)="",0,IF('Model inputs'!B616="",0,1)),IF(IF('Model inputs'!B617="",0,1)="",0,IF('Model inputs'!B617="",0,1)),IF(IF('Model inputs'!B618="",0,1)="",0,IF('Model inputs'!B618="",0,1)),IF(IF('Model inputs'!B619="",0,1)="",0,IF('Model inputs'!B619="",0,1)))=0,"",SUM('Model inputs'!B615,'Model inputs'!B616,'Model inputs'!B617,'Model inputs'!B618,'Model inputs'!B619)) -> 3000 | Z25: =IF(SUM(IF(IF('Model inputs'!B620="",0,1)="",0,IF('Model inputs'!B620="",0,1)),IF(IF('Model inputs'!B621="",0,1)="",0,IF('Model inputs'!B621="",0,1)),IF(IF('Model inputs'!B622="",0,1)="",0,IF('Model inputs'!B622="",0,1)),IF(IF('Model inputs'!B623="",0,1)="",0,IF('Model inputs'!B623="",0,1)),IF(IF('Model inputs'!B624="",0,1)="",0,IF('Model inputs'!B624="",0,1)))=0,"",SUM('Model inputs'!B620,'Model inputs'!B621,'Model inputs'!B622,'Model inputs'!B623,'Model inputs'!B624)) -> 3000
A26: Plan Earned revenue · Growth | C26: 0 | D26: 0 | E26: 0 | F26: 0 | G26: 0 | H26: 0 | I26: 0 | J26: 0 | K26: 0 | L26: =IF(SUM(IF(IF('Model inputs'!B625="",0,1)="",0,IF('Model inputs'!B625="",0,1)),IF(IF('Model inputs'!B626="",0,1)="",0,IF('Model inputs'!B626="",0,1)),IF(IF('Model inputs'!B627="",0,1)="",0,IF('Model inputs'!B627="",0,1)),IF(IF('Model inputs'!B628="",0,1)="",0,IF('Model inputs'!B628="",0,1)),IF(IF('Model inputs'!B629="",0,1)="",0,IF('Model inputs'!B629="",0,1)))=0,"",SUM('Model inputs'!B625,'Model inputs'!B626,'Model inputs'!B627,'Model inputs'!B628,'Model inputs'!B629)) -> 5000 | M26: =IF(SUM(IF(IF('Model inputs'!B630="",0,1)="",0,IF('Model inputs'!B630="",0,1)),IF(IF('Model inputs'!B631="",0,1)="",0,IF('Model inputs'!B631="",0,1)),IF(IF('Model inputs'!B632="",0,1)="",0,IF('Model inputs'!B632="",0,1)),IF(IF('Model inputs'!B633="",0,1)="",0,IF('Model inputs'!B633="",0,1)),IF(IF('Model inputs'!B634="",0,1)="",0,IF('Model inputs'!B634="",0,1)))=0,"",SUM('Model inputs'!B630,'Model inputs'!B631,'Model inputs'!B632,'Model inputs'!B633,'Model inputs'!B634)) -> 10000 | N26: =IF(SUM(IF(IF('Model inputs'!B635="",0,1)="",0,IF('Model inputs'!B635="",0,1)),IF(IF('Model inputs'!B636="",0,1)="",0,IF('Model inputs'!B636="",0,1)),IF(IF('Model inputs'!B637="",0,1)="",0,IF('Model inputs'!B637="",0,1)),IF(IF('Model inputs'!B638="",0,1)="",0,IF('Model inputs'!B638="",0,1)),IF(IF('Model inputs'!B639="",0,1)="",0,IF('Model inputs'!B639="",0,1)))=0,"",SUM('Model inputs'!B635,'Model inputs'!B636,'Model inputs'!B637,'Model inputs'!B638,'Model inputs'!B639)) -> 15000 | O26: =IF(SUM(IF(IF('Model inputs'!B640="",0,1)="",0,IF('Model inputs'!B640="",0,1)),IF(IF('Model inputs'!B641="",0,1)="",0,IF('Model inputs'!B641="",0,1)),IF(IF('Model inputs'!B642="",0,1)="",0,IF('Model inputs'!B642="",0,1)),IF(IF('Model inputs'!B643="",0,1)="",0,IF('Model inputs'!B643="",0,1)),IF(IF('Model inputs'!B644="",0,1)="",0,IF('Model inputs'!B644="",0,1)))=0,"",SUM('Model inputs'!B640,'Model inputs'!B641,'Model inputs'!B642,'Model inputs'!B643,'Model inputs'!B644)) -> 20000 | P26: =IF(SUM(IF(IF('Model inputs'!B645="",0,1)="",0,IF('Model inputs'!B645="",0,1)),IF(IF('Model inputs'!B646="",0,1)="",0,IF('Model inputs'!B646="",0,1)),IF(IF('Model inputs'!B647="",0,1)="",0,IF('Model inputs'!B647="",0,1)),IF(IF('Model inputs'!B648="",0,1)="",0,IF('Model inputs'!B648="",0,1)),IF(IF('Model inputs'!B649="",0,1)="",0,IF('Model inputs'!B649="",0,1)))=0,"",SUM('Model inputs'!B645,'Model inputs'!B646,'Model inputs'!B647,'Model inputs'!B648,'Model inputs'!B649)) -> 25000 | Q26: =IF(SUM(IF(IF('Model inputs'!B650="",0,1)="",0,IF('Model inputs'!B650="",0,1)),IF(IF('Model inputs'!B651="",0,1)="",0,IF('Model inputs'!B651="",0,1)),IF(IF('Model inputs'!B652="",0,1)="",0,IF('Model inputs'!B652="",0,1)),IF(IF('Model inputs'!B653="",0,1)="",0,IF('Model inputs'!B653="",0,1)),IF(IF('Model inputs'!B654="",0,1)="",0,IF('Model inputs'!B654="",0,1)))=0,"",SUM('Model inputs'!B650,'Model inputs'!B651,'Model inputs'!B652,'Model inputs'!B653,'Model inputs'!B654)) -> 30000 | R26: =IF(SUM(IF(IF('Model inputs'!B655="",0,1)="",0,IF('Model inputs'!B655="",0,1)),IF(IF('Model inputs'!B656="",0,1)="",0,IF('Model inputs'!B656="",0,1)),IF(IF('Model inputs'!B657="",0,1)="",0,IF('Model inputs'!B657="",0,1)),IF(IF('Model inputs'!B658="",0,1)="",0,IF('Model inputs'!B658="",0,1)),IF(IF('Model inputs'!B659="",0,1)="",0,IF('Model inputs'!B659="",0,1)))=0,"",SUM('Model inputs'!B655,'Model inputs'!B656,'Model inputs'!B657,'Model inputs'!B658,'Model inputs'!B659)) -> 35000 | S26: =IF(SUM(IF(IF('Model inputs'!B660="",0,1)="",0,IF('Model inputs'!B660="",0,1)),IF(IF('Model inputs'!B661="",0,1)="",0,IF('Model inputs'!B661="",0,1)),IF(IF('Model inputs'!B662="",0,1)="",0,IF('Model inputs'!B662="",0,1)),IF(IF('Model inputs'!B663="",0,1)="",0,IF('Model inputs'!B663="",0,1)),IF(IF('Model inputs'!B664="",0,1)="",0,IF('Model inputs'!B664="",0,1)))=0,"",SUM('Model inputs'!B660,'Model inputs'!B661,'Model inputs'!B662,'Model inputs'!B663,'Model inputs'!B664)) -> 40000 | T26: =IF(SUM(IF(IF('Model inputs'!B665="",0,1)="",0,IF('Model inputs'!B665="",0,1)),IF(IF('Model inputs'!B666="",0,1)="",0,IF('Model inputs'!B666="",0,1)),IF(IF('Model inputs'!B667="",0,1)="",0,IF('Model inputs'!B667="",0,1)),IF(IF('Model inputs'!B668="",0,1)="",0,IF('Model inputs'!B668="",0,1)),IF(IF('Model inputs'!B669="",0,1)="",0,IF('Model inputs'!B669="",0,1)))=0,"",SUM('Model inputs'!B665,'Model inputs'!B666,'Model inputs'!B667,'Model inputs'!B668,'Model inputs'!B669)) -> 45000 | U26: =IF(SUM(IF(IF('Model inputs'!B670="",0,1)="",0,IF('Model inputs'!B670="",0,1)),IF(IF('Model inputs'!B671="",0,1)="",0,IF('Model inputs'!B671="",0,1)),IF(IF('Model inputs'!B672="",0,1)="",0,IF('Model inputs'!B672="",0,1)),IF(IF('Model inputs'!B673="",0,1)="",0,IF('Model inputs'!B673="",0,1)),IF(IF('Model inputs'!B674="",0,1)="",0,IF('Model inputs'!B674="",0,1)))=0,"",SUM('Model inputs'!B670,'Model inputs'!B671,'Model inputs'!B672,'Model inputs'!B673,'Model inputs'!B674)) -> 50000 | V26: =IF(SUM(IF(IF('Model inputs'!B675="",0,1)="",0,IF('Model inputs'!B675="",0,1)),IF(IF('Model inputs'!B676="",0,1)="",0,IF('Model inputs'!B676="",0,1)),IF(IF('Model inputs'!B677="",0,1)="",0,IF('Model inputs'!B677="",0,1)),IF(IF('Model inputs'!B678="",0,1)="",0,IF('Model inputs'!B678="",0,1)),IF(IF('Model inputs'!B679="",0,1)="",0,IF('Model inputs'!B679="",0,1)))=0,"",SUM('Model inputs'!B675,'Model inputs'!B676,'Model inputs'!B677,'Model inputs'!B678,'Model inputs'!B679)) -> 55000 | W26: =IF(SUM(IF(IF('Model inputs'!B680="",0,1)="",0,IF('Model inputs'!B680="",0,1)),IF(IF('Model inputs'!B681="",0,1)="",0,IF('Model inputs'!B681="",0,1)),IF(IF('Model inputs'!B682="",0,1)="",0,IF('Model inputs'!B682="",0,1)),IF(IF('Model inputs'!B683="",0,1)="",0,IF('Model inputs'!B683="",0,1)),IF(IF('Model inputs'!B684="",0,1)="",0,IF('Model inputs'!B684="",0,1)))=0,"",SUM('Model inputs'!B680,'Model inputs'!B681,'Model inputs'!B682,'Model inputs'!B683,'Model inputs'!B684)) -> 60000 | X26: =IF(SUM(IF(IF('Model inputs'!B685="",0,1)="",0,IF('Model inputs'!B685="",0,1)),IF(IF('Model inputs'!B686="",0,1)="",0,IF('Model inputs'!B686="",0,1)),IF(IF('Model inputs'!B687="",0,1)="",0,IF('Model inputs'!B687="",0,1)),IF(IF('Model inputs'!B688="",0,1)="",0,IF('Model inputs'!B688="",0,1)),IF(IF('Model inputs'!B689="",0,1)="",0,IF('Model inputs'!B689="",0,1)))=0,"",SUM('Model inputs'!B685,'Model inputs'!B686,'Model inputs'!B687,'Model inputs'!B688,'Model inputs'!B689)) -> 60000 | Y26: =IF(SUM(IF(IF('Model inputs'!B690="",0,1)="",0,IF('Model inputs'!B690="",0,1)),IF(IF('Model inputs'!B691="",0,1)="",0,IF('Model inputs'!B691="",0,1)),IF(IF('Model inputs'!B692="",0,1)="",0,IF('Model inputs'!B692="",0,1)),IF(IF('Model inputs'!B693="",0,1)="",0,IF('Model inputs'!B693="",0,1)),IF(IF('Model inputs'!B694="",0,1)="",0,IF('Model inputs'!B694="",0,1)))=0,"",SUM('Model inputs'!B690,'Model inputs'!B691,'Model inputs'!B692,'Model inputs'!B693,'Model inputs'!B694)) -> 60000 | Z26: =IF(SUM(IF(IF('Model inputs'!B695="",0,1)="",0,IF('Model inputs'!B695="",0,1)),IF(IF('Model inputs'!B696="",0,1)="",0,IF('Model inputs'!B696="",0,1)),IF(IF('Model inputs'!B697="",0,1)="",0,IF('Model inputs'!B697="",0,1)),IF(IF('Model inputs'!B698="",0,1)="",0,IF('Model inputs'!B698="",0,1)),IF(IF('Model inputs'!B699="",0,1)="",0,IF('Model inputs'!B699="",0,1)))=0,"",SUM('Model inputs'!B695,'Model inputs'!B696,'Model inputs'!B697,'Model inputs'!B698,'Model inputs'!B699)) -> 60000
A27: Plan Earned revenue · Conservative | C27: 0 | D27: 0 | E27: 0 | F27: 0 | G27: 0 | H27: 0 | I27: 0 | J27: 0 | K27: 0 | L27: =IF(SUM(IF(IF('Model inputs'!B700="",0,1)="",0,IF('Model inputs'!B700="",0,1)),IF(IF('Model inputs'!B701="",0,1)="",0,IF('Model inputs'!B701="",0,1)),IF(IF('Model inputs'!B702="",0,1)="",0,IF('Model inputs'!B702="",0,1)),IF(IF('Model inputs'!B703="",0,1)="",0,IF('Model inputs'!B703="",0,1)),IF(IF('Model inputs'!B704="",0,1)="",0,IF('Model inputs'!B704="",0,1)))=0,"",SUM('Model inputs'!B700,'Model inputs'!B701,'Model inputs'!B702,'Model inputs'!B703,'Model inputs'!B704)) -> 0 | M27: =IF(SUM(IF(IF('Model inputs'!B705="",0,1)="",0,IF('Model inputs'!B705="",0,1)),IF(IF('Model inputs'!B706="",0,1)="",0,IF('Model inputs'!B706="",0,1)),IF(IF('Model inputs'!B707="",0,1)="",0,IF('Model inputs'!B707="",0,1)),IF(IF('Model inputs'!B708="",0,1)="",0,IF('Model inputs'!B708="",0,1)),IF(IF('Model inputs'!B709="",0,1)="",0,IF('Model inputs'!B709="",0,1)))=0,"",SUM('Model inputs'!B705,'Model inputs'!B706,'Model inputs'!B707,'Model inputs'!B708,'Model inputs'!B709)) -> 0 | N27: =IF(SUM(IF(IF('Model inputs'!B710="",0,1)="",0,IF('Model inputs'!B710="",0,1)),IF(IF('Model inputs'!B711="",0,1)="",0,IF('Model inputs'!B711="",0,1)),IF(IF('Model inputs'!B712="",0,1)="",0,IF('Model inputs'!B712="",0,1)),IF(IF('Model inputs'!B713="",0,1)="",0,IF('Model inputs'!B713="",0,1)),IF(IF('Model inputs'!B714="",0,1)="",0,IF('Model inputs'!B714="",0,1)))=0,"",SUM('Model inputs'!B710,'Model inputs'!B711,'Model inputs'!B712,'Model inputs'!B713,'Model inputs'!B714)) -> 3000 | O27: =IF(SUM(IF(IF('Model inputs'!B715="",0,1)="",0,IF('Model inputs'!B715="",0,1)),IF(IF('Model inputs'!B716="",0,1)="",0,IF('Model inputs'!B716="",0,1)),IF(IF('Model inputs'!B717="",0,1)="",0,IF('Model inputs'!B717="",0,1)),IF(IF('Model inputs'!B718="",0,1)="",0,IF('Model inputs'!B718="",0,1)),IF(IF('Model inputs'!B719="",0,1)="",0,IF('Model inputs'!B719="",0,1)))=0,"",SUM('Model inputs'!B715,'Model inputs'!B716,'Model inputs'!B717,'Model inputs'!B718,'Model inputs'!B719)) -> 3000 | P27: =IF(SUM(IF(IF('Model inputs'!B720="",0,1)="",0,IF('Model inputs'!B720="",0,1)),IF(IF('Model inputs'!B721="",0,1)="",0,IF('Model inputs'!B721="",0,1)),IF(IF('Model inputs'!B722="",0,1)="",0,IF('Model inputs'!B722="",0,1)),IF(IF('Model inputs'!B723="",0,1)="",0,IF('Model inputs'!B723="",0,1)),IF(IF('Model inputs'!B724="",0,1)="",0,IF('Model inputs'!B724="",0,1)))=0,"",SUM('Model inputs'!B720,'Model inputs'!B721,'Model inputs'!B722,'Model inputs'!B723,'Model inputs'!B724)) -> 3000 | Q27: =IF(SUM(IF(IF('Model inputs'!B725="",0,1)="",0,IF('Model inputs'!B725="",0,1)),IF(IF('Model inputs'!B726="",0,1)="",0,IF('Model inputs'!B726="",0,1)),IF(IF('Model inputs'!B727="",0,1)="",0,IF('Model inputs'!B727="",0,1)),IF(IF('Model inputs'!B728="",0,1)="",0,IF('Model inputs'!B728="",0,1)),IF(IF('Model inputs'!B729="",0,1)="",0,IF('Model inputs'!B729="",0,1)))=0,"",SUM('Model inputs'!B725,'Model inputs'!B726,'Model inputs'!B727,'Model inputs'!B728,'Model inputs'!B729)) -> 3000 | R27: =IF(SUM(IF(IF('Model inputs'!B730="",0,1)="",0,IF('Model inputs'!B730="",0,1)),IF(IF('Model inputs'!B731="",0,1)="",0,IF('Model inputs'!B731="",0,1)),IF(IF('Model inputs'!B732="",0,1)="",0,IF('Model inputs'!B732="",0,1)),IF(IF('Model inputs'!B733="",0,1)="",0,IF('Model inputs'!B733="",0,1)),IF(IF('Model inputs'!B734="",0,1)="",0,IF('Model inputs'!B734="",0,1)))=0,"",SUM('Model inputs'!B730,'Model inputs'!B731,'Model inputs'!B732,'Model inputs'!B733,'Model inputs'!B734)) -> 3000 | S27: =IF(SUM(IF(IF('Model inputs'!B735="",0,1)="",0,IF('Model inputs'!B735="",0,1)),IF(IF('Model inputs'!B736="",0,1)="",0,IF('Model inputs'!B736="",0,1)),IF(IF('Model inputs'!B737="",0,1)="",0,IF('Model inputs'!B737="",0,1)),IF(IF('Model inputs'!B738="",0,1)="",0,IF('Model inputs'!B738="",0,1)),IF(IF('Model inputs'!B739="",0,1)="",0,IF('Model inputs'!B739="",0,1)))=0,"",SUM('Model inputs'!B735,'Model inputs'!B736,'Model inputs'!B737,'Model inputs'!B738,'Model inputs'!B739)) -> 3000 | T27: =IF(SUM(IF(IF('Model inputs'!B740="",0,1)="",0,IF('Model inputs'!B740="",0,1)),IF(IF('Model inputs'!B741="",0,1)="",0,IF('Model inputs'!B741="",0,1)),IF(IF('Model inputs'!B742="",0,1)="",0,IF('Model inputs'!B742="",0,1)),IF(IF('Model inputs'!B743="",0,1)="",0,IF('Model inputs'!B743="",0,1)),IF(IF('Model inputs'!B744="",0,1)="",0,IF('Model inputs'!B744="",0,1)))=0,"",SUM('Model inputs'!B740,'Model inputs'!B741,'Model inputs'!B742,'Model inputs'!B743,'Model inputs'!B744)) -> 3000 | U27: =IF(SUM(IF(IF('Model inputs'!B745="",0,1)="",0,IF('Model inputs'!B745="",0,1)),IF(IF('Model inputs'!B746="",0,1)="",0,IF('Model inputs'!B746="",0,1)),IF(IF('Model inputs'!B747="",0,1)="",0,IF('Model inputs'!B747="",0,1)),IF(IF('Model inputs'!B748="",0,1)="",0,IF('Model inputs'!B748="",0,1)),IF(IF('Model inputs'!B749="",0,1)="",0,IF('Model inputs'!B749="",0,1)))=0,"",SUM('Model inputs'!B745,'Model inputs'!B746,'Model inputs'!B747,'Model inputs'!B748,'Model inputs'!B749)) -> 3000 | V27: =IF(SUM(IF(IF('Model inputs'!B750="",0,1)="",0,IF('Model inputs'!B750="",0,1)),IF(IF('Model inputs'!B751="",0,1)="",0,IF('Model inputs'!B751="",0,1)),IF(IF('Model inputs'!B752="",0,1)="",0,IF('Model inputs'!B752="",0,1)),IF(IF('Model inputs'!B753="",0,1)="",0,IF('Model inputs'!B753="",0,1)),IF(IF('Model inputs'!B754="",0,1)="",0,IF('Model inputs'!B754="",0,1)))=0,"",SUM('Model inputs'!B750,'Model inputs'!B751,'Model inputs'!B752,'Model inputs'!B753,'Model inputs'!B754)) -> 3000 | W27: =IF(SUM(IF(IF('Model inputs'!B755="",0,1)="",0,IF('Model inputs'!B755="",0,1)),IF(IF('Model inputs'!B756="",0,1)="",0,IF('Model inputs'!B756="",0,1)),IF(IF('Model inputs'!B757="",0,1)="",0,IF('Model inputs'!B757="",0,1)),IF(IF('Model inputs'!B758="",0,1)="",0,IF('Model inputs'!B758="",0,1)),IF(IF('Model inputs'!B759="",0,1)="",0,IF('Model inputs'!B759="",0,1)))=0,"",SUM('Model inputs'!B755,'Model inputs'!B756,'Model inputs'!B757,'Model inputs'!B758,'Model inputs'!B759)) -> 3000 | X27: =IF(SUM(IF(IF('Model inputs'!B760="",0,1)="",0,IF('Model inputs'!B760="",0,1)),IF(IF('Model inputs'!B761="",0,1)="",0,IF('Model inputs'!B761="",0,1)),IF(IF('Model inputs'!B762="",0,1)="",0,IF('Model inputs'!B762="",0,1)),IF(IF('Model inputs'!B763="",0,1)="",0,IF('Model inputs'!B763="",0,1)),IF(IF('Model inputs'!B764="",0,1)="",0,IF('Model inputs'!B764="",0,1)))=0,"",SUM('Model inputs'!B760,'Model inputs'!B761,'Model inputs'!B762,'Model inputs'!B763,'Model inputs'!B764)) -> 3000 | Y27: =IF(SUM(IF(IF('Model inputs'!B765="",0,1)="",0,IF('Model inputs'!B765="",0,1)),IF(IF('Model inputs'!B766="",0,1)="",0,IF('Model inputs'!B766="",0,1)),IF(IF('Model inputs'!B767="",0,1)="",0,IF('Model inputs'!B767="",0,1)),IF(IF('Model inputs'!B768="",0,1)="",0,IF('Model inputs'!B768="",0,1)),IF(IF('Model inputs'!B769="",0,1)="",0,IF('Model inputs'!B769="",0,1)))=0,"",SUM('Model inputs'!B765,'Model inputs'!B766,'Model inputs'!B767,'Model inputs'!B768,'Model inputs'!B769)) -> 3000 | Z27: =IF(SUM(IF(IF('Model inputs'!B770="",0,1)="",0,IF('Model inputs'!B770="",0,1)),IF(IF('Model inputs'!B771="",0,1)="",0,IF('Model inputs'!B771="",0,1)),IF(IF('Model inputs'!B772="",0,1)="",0,IF('Model inputs'!B772="",0,1)),IF(IF('Model inputs'!B773="",0,1)="",0,IF('Model inputs'!B773="",0,1)),IF(IF('Model inputs'!B774="",0,1)="",0,IF('Model inputs'!B774="",0,1)))=0,"",SUM('Model inputs'!B770,'Model inputs'!B771,'Model inputs'!B772,'Model inputs'!B773,'Model inputs'!B774)) -> 3000
A28: Plan Net cash burn · Growth | C28: 0 | D28: 0 | E28: 0 | F28: 0 | G28: 0 | H28: 0 | I28: 0 | J28: 0 | K28: 0 | L28: =IF(SUM(IF(IF('Model inputs'!B775="",0,1)="",0,IF('Model inputs'!B775="",0,1)),IF(IF('Model inputs'!B776="",0,1)="",0,IF('Model inputs'!B776="",0,1)),IF(IF('Model inputs'!B777="",0,1)="",0,IF('Model inputs'!B777="",0,1)),IF(IF('Model inputs'!B778="",0,1)="",0,IF('Model inputs'!B778="",0,1)),IF(IF('Model inputs'!B779="",0,1)="",0,IF('Model inputs'!B779="",0,1)))=0,"",SUM('Model inputs'!B775,'Model inputs'!B776,'Model inputs'!B777,'Model inputs'!B778,'Model inputs'!B779)) -> -30264.25 | M28: =IF(SUM(IF(IF('Model inputs'!B780="",0,1)="",0,IF('Model inputs'!B780="",0,1)),IF(IF('Model inputs'!B781="",0,1)="",0,IF('Model inputs'!B781="",0,1)),IF(IF('Model inputs'!B782="",0,1)="",0,IF('Model inputs'!B782="",0,1)),IF(IF('Model inputs'!B783="",0,1)="",0,IF('Model inputs'!B783="",0,1)),IF(IF('Model inputs'!B784="",0,1)="",0,IF('Model inputs'!B784="",0,1)))=0,"",SUM('Model inputs'!B780,'Model inputs'!B781,'Model inputs'!B782,'Model inputs'!B783,'Model inputs'!B784)) -> -32178.5 | N28: =IF(SUM(IF(IF('Model inputs'!B785="",0,1)="",0,IF('Model inputs'!B785="",0,1)),IF(IF('Model inputs'!B786="",0,1)="",0,IF('Model inputs'!B786="",0,1)),IF(IF('Model inputs'!B787="",0,1)="",0,IF('Model inputs'!B787="",0,1)),IF(IF('Model inputs'!B788="",0,1)="",0,IF('Model inputs'!B788="",0,1)),IF(IF('Model inputs'!B789="",0,1)="",0,IF('Model inputs'!B789="",0,1)))=0,"",SUM('Model inputs'!B785,'Model inputs'!B786,'Model inputs'!B787,'Model inputs'!B788,'Model inputs'!B789)) -> -34092.75 | O28: =IF(SUM(IF(IF('Model inputs'!B790="",0,1)="",0,IF('Model inputs'!B790="",0,1)),IF(IF('Model inputs'!B791="",0,1)="",0,IF('Model inputs'!B791="",0,1)),IF(IF('Model inputs'!B792="",0,1)="",0,IF('Model inputs'!B792="",0,1)),IF(IF('Model inputs'!B793="",0,1)="",0,IF('Model inputs'!B793="",0,1)),IF(IF('Model inputs'!B794="",0,1)="",0,IF('Model inputs'!B794="",0,1)))=0,"",SUM('Model inputs'!B790,'Model inputs'!B791,'Model inputs'!B792,'Model inputs'!B793,'Model inputs'!B794)) -> -36007 | P28: =IF(SUM(IF(IF('Model inputs'!B795="",0,1)="",0,IF('Model inputs'!B795="",0,1)),IF(IF('Model inputs'!B796="",0,1)="",0,IF('Model inputs'!B796="",0,1)),IF(IF('Model inputs'!B797="",0,1)="",0,IF('Model inputs'!B797="",0,1)),IF(IF('Model inputs'!B798="",0,1)="",0,IF('Model inputs'!B798="",0,1)),IF(IF('Model inputs'!B799="",0,1)="",0,IF('Model inputs'!B799="",0,1)))=0,"",SUM('Model inputs'!B795,'Model inputs'!B796,'Model inputs'!B797,'Model inputs'!B798,'Model inputs'!B799)) -> -37921.25 | Q28: =IF(SUM(IF(IF('Model inputs'!B800="",0,1)="",0,IF('Model inputs'!B800="",0,1)),IF(IF('Model inputs'!B801="",0,1)="",0,IF('Model inputs'!B801="",0,1)),IF(IF('Model inputs'!B802="",0,1)="",0,IF('Model inputs'!B802="",0,1)),IF(IF('Model inputs'!B803="",0,1)="",0,IF('Model inputs'!B803="",0,1)),IF(IF('Model inputs'!B804="",0,1)="",0,IF('Model inputs'!B804="",0,1)))=0,"",SUM('Model inputs'!B800,'Model inputs'!B801,'Model inputs'!B802,'Model inputs'!B803,'Model inputs'!B804)) -> -39335.5 | R28: =IF(SUM(IF(IF('Model inputs'!B805="",0,1)="",0,IF('Model inputs'!B805="",0,1)),IF(IF('Model inputs'!B806="",0,1)="",0,IF('Model inputs'!B806="",0,1)),IF(IF('Model inputs'!B807="",0,1)="",0,IF('Model inputs'!B807="",0,1)),IF(IF('Model inputs'!B808="",0,1)="",0,IF('Model inputs'!B808="",0,1)),IF(IF('Model inputs'!B809="",0,1)="",0,IF('Model inputs'!B809="",0,1)))=0,"",SUM('Model inputs'!B805,'Model inputs'!B806,'Model inputs'!B807,'Model inputs'!B808,'Model inputs'!B809)) -> -41249.75 | S28: =IF(SUM(IF(IF('Model inputs'!B810="",0,1)="",0,IF('Model inputs'!B810="",0,1)),IF(IF('Model inputs'!B811="",0,1)="",0,IF('Model inputs'!B811="",0,1)),IF(IF('Model inputs'!B812="",0,1)="",0,IF('Model inputs'!B812="",0,1)),IF(IF('Model inputs'!B813="",0,1)="",0,IF('Model inputs'!B813="",0,1)),IF(IF('Model inputs'!B814="",0,1)="",0,IF('Model inputs'!B814="",0,1)))=0,"",SUM('Model inputs'!B810,'Model inputs'!B811,'Model inputs'!B812,'Model inputs'!B813,'Model inputs'!B814)) -> -43164 | T28: =IF(SUM(IF(IF('Model inputs'!B815="",0,1)="",0,IF('Model inputs'!B815="",0,1)),IF(IF('Model inputs'!B816="",0,1)="",0,IF('Model inputs'!B816="",0,1)),IF(IF('Model inputs'!B817="",0,1)="",0,IF('Model inputs'!B817="",0,1)),IF(IF('Model inputs'!B818="",0,1)="",0,IF('Model inputs'!B818="",0,1)),IF(IF('Model inputs'!B819="",0,1)="",0,IF('Model inputs'!B819="",0,1)))=0,"",SUM('Model inputs'!B815,'Model inputs'!B816,'Model inputs'!B817,'Model inputs'!B818,'Model inputs'!B819)) -> -45078.25 | U28: =IF(SUM(IF(IF('Model inputs'!B820="",0,1)="",0,IF('Model inputs'!B820="",0,1)),IF(IF('Model inputs'!B821="",0,1)="",0,IF('Model inputs'!B821="",0,1)),IF(IF('Model inputs'!B822="",0,1)="",0,IF('Model inputs'!B822="",0,1)),IF(IF('Model inputs'!B823="",0,1)="",0,IF('Model inputs'!B823="",0,1)),IF(IF('Model inputs'!B824="",0,1)="",0,IF('Model inputs'!B824="",0,1)))=0,"",SUM('Model inputs'!B820,'Model inputs'!B821,'Model inputs'!B822,'Model inputs'!B823,'Model inputs'!B824)) -> -46992.5 | V28: =IF(SUM(IF(IF('Model inputs'!B825="",0,1)="",0,IF('Model inputs'!B825="",0,1)),IF(IF('Model inputs'!B826="",0,1)="",0,IF('Model inputs'!B826="",0,1)),IF(IF('Model inputs'!B827="",0,1)="",0,IF('Model inputs'!B827="",0,1)),IF(IF('Model inputs'!B828="",0,1)="",0,IF('Model inputs'!B828="",0,1)),IF(IF('Model inputs'!B829="",0,1)="",0,IF('Model inputs'!B829="",0,1)))=0,"",SUM('Model inputs'!B825,'Model inputs'!B826,'Model inputs'!B827,'Model inputs'!B828,'Model inputs'!B829)) -> -48906.75 | W28: =IF(SUM(IF(IF('Model inputs'!B830="",0,1)="",0,IF('Model inputs'!B830="",0,1)),IF(IF('Model inputs'!B831="",0,1)="",0,IF('Model inputs'!B831="",0,1)),IF(IF('Model inputs'!B832="",0,1)="",0,IF('Model inputs'!B832="",0,1)),IF(IF('Model inputs'!B833="",0,1)="",0,IF('Model inputs'!B833="",0,1)),IF(IF('Model inputs'!B834="",0,1)="",0,IF('Model inputs'!B834="",0,1)))=0,"",SUM('Model inputs'!B830,'Model inputs'!B831,'Model inputs'!B832,'Model inputs'!B833,'Model inputs'!B834)) -> -50821 | X28: =IF(SUM(IF(IF('Model inputs'!B835="",0,1)="",0,IF('Model inputs'!B835="",0,1)),IF(IF('Model inputs'!B836="",0,1)="",0,IF('Model inputs'!B836="",0,1)),IF(IF('Model inputs'!B837="",0,1)="",0,IF('Model inputs'!B837="",0,1)),IF(IF('Model inputs'!B838="",0,1)="",0,IF('Model inputs'!B838="",0,1)),IF(IF('Model inputs'!B839="",0,1)="",0,IF('Model inputs'!B839="",0,1)))=0,"",SUM('Model inputs'!B835,'Model inputs'!B836,'Model inputs'!B837,'Model inputs'!B838,'Model inputs'!B839)) -> -21721 | Y28: =IF(SUM(IF(IF('Model inputs'!B840="",0,1)="",0,IF('Model inputs'!B840="",0,1)),IF(IF('Model inputs'!B841="",0,1)="",0,IF('Model inputs'!B841="",0,1)),IF(IF('Model inputs'!B842="",0,1)="",0,IF('Model inputs'!B842="",0,1)),IF(IF('Model inputs'!B843="",0,1)="",0,IF('Model inputs'!B843="",0,1)),IF(IF('Model inputs'!B844="",0,1)="",0,IF('Model inputs'!B844="",0,1)))=0,"",SUM('Model inputs'!B840,'Model inputs'!B841,'Model inputs'!B842,'Model inputs'!B843,'Model inputs'!B844)) -> -21721 | Z28: =IF(SUM(IF(IF('Model inputs'!B845="",0,1)="",0,IF('Model inputs'!B845="",0,1)),IF(IF('Model inputs'!B846="",0,1)="",0,IF('Model inputs'!B846="",0,1)),IF(IF('Model inputs'!B847="",0,1)="",0,IF('Model inputs'!B847="",0,1)),IF(IF('Model inputs'!B848="",0,1)="",0,IF('Model inputs'!B848="",0,1)),IF(IF('Model inputs'!B849="",0,1)="",0,IF('Model inputs'!B849="",0,1)))=0,"",SUM('Model inputs'!B845,'Model inputs'!B846,'Model inputs'!B847,'Model inputs'!B848,'Model inputs'!B849)) -> -21721
A29: Plan Net cash burn · Conservative | C29: 0 | D29: 0 | E29: 0 | F29: 0 | G29: 0 | H29: 0 | I29: 0 | J29: 0 | K29: 0 | L29: =IF(SUM(IF(IF('Model inputs'!B850="",0,1)="",0,IF('Model inputs'!B850="",0,1)),IF(IF('Model inputs'!B851="",0,1)="",0,IF('Model inputs'!B851="",0,1)),IF(IF('Model inputs'!B852="",0,1)="",0,IF('Model inputs'!B852="",0,1)),IF(IF('Model inputs'!B853="",0,1)="",0,IF('Model inputs'!B853="",0,1)),IF(IF('Model inputs'!B854="",0,1)="",0,IF('Model inputs'!B854="",0,1)))=0,"",SUM('Model inputs'!B850,'Model inputs'!B851,'Model inputs'!B852,'Model inputs'!B853,'Model inputs'!B854)) -> 750 | M29: =IF(SUM(IF(IF('Model inputs'!B855="",0,1)="",0,IF('Model inputs'!B855="",0,1)),IF(IF('Model inputs'!B856="",0,1)="",0,IF('Model inputs'!B856="",0,1)),IF(IF('Model inputs'!B857="",0,1)="",0,IF('Model inputs'!B857="",0,1)),IF(IF('Model inputs'!B858="",0,1)="",0,IF('Model inputs'!B858="",0,1)),IF(IF('Model inputs'!B859="",0,1)="",0,IF('Model inputs'!B859="",0,1)))=0,"",SUM('Model inputs'!B855,'Model inputs'!B856,'Model inputs'!B857,'Model inputs'!B858,'Model inputs'!B859)) -> 750 | N29: =IF(SUM(IF(IF('Model inputs'!B860="",0,1)="",0,IF('Model inputs'!B860="",0,1)),IF(IF('Model inputs'!B861="",0,1)="",0,IF('Model inputs'!B861="",0,1)),IF(IF('Model inputs'!B862="",0,1)="",0,IF('Model inputs'!B862="",0,1)),IF(IF('Model inputs'!B863="",0,1)="",0,IF('Model inputs'!B863="",0,1)),IF(IF('Model inputs'!B864="",0,1)="",0,IF('Model inputs'!B864="",0,1)))=0,"",SUM('Model inputs'!B860,'Model inputs'!B861,'Model inputs'!B862,'Model inputs'!B863,'Model inputs'!B864)) -> -1716.1 | O29: =IF(SUM(IF(IF('Model inputs'!B865="",0,1)="",0,IF('Model inputs'!B865="",0,1)),IF(IF('Model inputs'!B866="",0,1)="",0,IF('Model inputs'!B866="",0,1)),IF(IF('Model inputs'!B867="",0,1)="",0,IF('Model inputs'!B867="",0,1)),IF(IF('Model inputs'!B868="",0,1)="",0,IF('Model inputs'!B868="",0,1)),IF(IF('Model inputs'!B869="",0,1)="",0,IF('Model inputs'!B869="",0,1)))=0,"",SUM('Model inputs'!B865,'Model inputs'!B866,'Model inputs'!B867,'Model inputs'!B868,'Model inputs'!B869)) -> -1716.1 | P29: =IF(SUM(IF(IF('Model inputs'!B870="",0,1)="",0,IF('Model inputs'!B870="",0,1)),IF(IF('Model inputs'!B871="",0,1)="",0,IF('Model inputs'!B871="",0,1)),IF(IF('Model inputs'!B872="",0,1)="",0,IF('Model inputs'!B872="",0,1)),IF(IF('Model inputs'!B873="",0,1)="",0,IF('Model inputs'!B873="",0,1)),IF(IF('Model inputs'!B874="",0,1)="",0,IF('Model inputs'!B874="",0,1)))=0,"",SUM('Model inputs'!B870,'Model inputs'!B871,'Model inputs'!B872,'Model inputs'!B873,'Model inputs'!B874)) -> -1716.1 | Q29: =IF(SUM(IF(IF('Model inputs'!B875="",0,1)="",0,IF('Model inputs'!B875="",0,1)),IF(IF('Model inputs'!B876="",0,1)="",0,IF('Model inputs'!B876="",0,1)),IF(IF('Model inputs'!B877="",0,1)="",0,IF('Model inputs'!B877="",0,1)),IF(IF('Model inputs'!B878="",0,1)="",0,IF('Model inputs'!B878="",0,1)),IF(IF('Model inputs'!B879="",0,1)="",0,IF('Model inputs'!B879="",0,1)))=0,"",SUM('Model inputs'!B875,'Model inputs'!B876,'Model inputs'!B877,'Model inputs'!B878,'Model inputs'!B879)) -> -1216.1 | R29: =IF(SUM(IF(IF('Model inputs'!B880="",0,1)="",0,IF('Model inputs'!B880="",0,1)),IF(IF('Model inputs'!B881="",0,1)="",0,IF('Model inputs'!B881="",0,1)),IF(IF('Model inputs'!B882="",0,1)="",0,IF('Model inputs'!B882="",0,1)),IF(IF('Model inputs'!B883="",0,1)="",0,IF('Model inputs'!B883="",0,1)),IF(IF('Model inputs'!B884="",0,1)="",0,IF('Model inputs'!B884="",0,1)))=0,"",SUM('Model inputs'!B880,'Model inputs'!B881,'Model inputs'!B882,'Model inputs'!B883,'Model inputs'!B884)) -> -1216.1 | S29: =IF(SUM(IF(IF('Model inputs'!B885="",0,1)="",0,IF('Model inputs'!B885="",0,1)),IF(IF('Model inputs'!B886="",0,1)="",0,IF('Model inputs'!B886="",0,1)),IF(IF('Model inputs'!B887="",0,1)="",0,IF('Model inputs'!B887="",0,1)),IF(IF('Model inputs'!B888="",0,1)="",0,IF('Model inputs'!B888="",0,1)),IF(IF('Model inputs'!B889="",0,1)="",0,IF('Model inputs'!B889="",0,1)))=0,"",SUM('Model inputs'!B885,'Model inputs'!B886,'Model inputs'!B887,'Model inputs'!B888,'Model inputs'!B889)) -> -1216.1 | T29: =IF(SUM(IF(IF('Model inputs'!B890="",0,1)="",0,IF('Model inputs'!B890="",0,1)),IF(IF('Model inputs'!B891="",0,1)="",0,IF('Model inputs'!B891="",0,1)),IF(IF('Model inputs'!B892="",0,1)="",0,IF('Model inputs'!B892="",0,1)),IF(IF('Model inputs'!B893="",0,1)="",0,IF('Model inputs'!B893="",0,1)),IF(IF('Model inputs'!B894="",0,1)="",0,IF('Model inputs'!B894="",0,1)))=0,"",SUM('Model inputs'!B890,'Model inputs'!B891,'Model inputs'!B892,'Model inputs'!B893,'Model inputs'!B894)) -> -1216.1 | U29: =IF(SUM(IF(IF('Model inputs'!B895="",0,1)="",0,IF('Model inputs'!B895="",0,1)),IF(IF('Model inputs'!B896="",0,1)="",0,IF('Model inputs'!B896="",0,1)),IF(IF('Model inputs'!B897="",0,1)="",0,IF('Model inputs'!B897="",0,1)),IF(IF('Model inputs'!B898="",0,1)="",0,IF('Model inputs'!B898="",0,1)),IF(IF('Model inputs'!B899="",0,1)="",0,IF('Model inputs'!B899="",0,1)))=0,"",SUM('Model inputs'!B895,'Model inputs'!B896,'Model inputs'!B897,'Model inputs'!B898,'Model inputs'!B899)) -> -1216.1 | V29: =IF(SUM(IF(IF('Model inputs'!B900="",0,1)="",0,IF('Model inputs'!B900="",0,1)),IF(IF('Model inputs'!B901="",0,1)="",0,IF('Model inputs'!B901="",0,1)),IF(IF('Model inputs'!B902="",0,1)="",0,IF('Model inputs'!B902="",0,1)),IF(IF('Model inputs'!B903="",0,1)="",0,IF('Model inputs'!B903="",0,1)),IF(IF('Model inputs'!B904="",0,1)="",0,IF('Model inputs'!B904="",0,1)))=0,"",SUM('Model inputs'!B900,'Model inputs'!B901,'Model inputs'!B902,'Model inputs'!B903,'Model inputs'!B904)) -> -1216.1 | W29: =IF(SUM(IF(IF('Model inputs'!B905="",0,1)="",0,IF('Model inputs'!B905="",0,1)),IF(IF('Model inputs'!B906="",0,1)="",0,IF('Model inputs'!B906="",0,1)),IF(IF('Model inputs'!B907="",0,1)="",0,IF('Model inputs'!B907="",0,1)),IF(IF('Model inputs'!B908="",0,1)="",0,IF('Model inputs'!B908="",0,1)),IF(IF('Model inputs'!B909="",0,1)="",0,IF('Model inputs'!B909="",0,1)))=0,"",SUM('Model inputs'!B905,'Model inputs'!B906,'Model inputs'!B907,'Model inputs'!B908,'Model inputs'!B909)) -> -1216.1 | X29: =IF(SUM(IF(IF('Model inputs'!B910="",0,1)="",0,IF('Model inputs'!B910="",0,1)),IF(IF('Model inputs'!B911="",0,1)="",0,IF('Model inputs'!B911="",0,1)),IF(IF('Model inputs'!B912="",0,1)="",0,IF('Model inputs'!B912="",0,1)),IF(IF('Model inputs'!B913="",0,1)="",0,IF('Model inputs'!B913="",0,1)),IF(IF('Model inputs'!B914="",0,1)="",0,IF('Model inputs'!B914="",0,1)))=0,"",SUM('Model inputs'!B910,'Model inputs'!B911,'Model inputs'!B912,'Model inputs'!B913,'Model inputs'!B914)) -> -1216.1 | Y29: =IF(SUM(IF(IF('Model inputs'!B915="",0,1)="",0,IF('Model inputs'!B915="",0,1)),IF(IF('Model inputs'!B916="",0,1)="",0,IF('Model inputs'!B916="",0,1)),IF(IF('Model inputs'!B917="",0,1)="",0,IF('Model inputs'!B917="",0,1)),IF(IF('Model inputs'!B918="",0,1)="",0,IF('Model inputs'!B918="",0,1)),IF(IF('Model inputs'!B919="",0,1)="",0,IF('Model inputs'!B919="",0,1)))=0,"",SUM('Model inputs'!B915,'Model inputs'!B916,'Model inputs'!B917,'Model inputs'!B918,'Model inputs'!B919)) -> -1216.1 | Z29: =IF(SUM(IF(IF('Model inputs'!B920="",0,1)="",0,IF('Model inputs'!B920="",0,1)),IF(IF('Model inputs'!B921="",0,1)="",0,IF('Model inputs'!B921="",0,1)),IF(IF('Model inputs'!B922="",0,1)="",0,IF('Model inputs'!B922="",0,1)),IF(IF('Model inputs'!B923="",0,1)="",0,IF('Model inputs'!B923="",0,1)),IF(IF('Model inputs'!B924="",0,1)="",0,IF('Model inputs'!B924="",0,1)))=0,"",SUM('Model inputs'!B920,'Model inputs'!B921,'Model inputs'!B922,'Model inputs'!B923,'Model inputs'!B924)) -> -1216.1
A30: Audits delivered | C30: =SUM('Model inputs'!C31,'Model inputs'!C32,'Model inputs'!C33,'Model inputs'!C34,'Model inputs'!C35) -> 0 | D30: =SUM('Model inputs'!D31,'Model inputs'!D32,'Model inputs'!D33,'Model inputs'!D34,'Model inputs'!D35) -> 0 | E30: =SUM('Model inputs'!E31,'Model inputs'!E32,'Model inputs'!E33,'Model inputs'!E34,'Model inputs'!E35) -> 0 | F30: =SUM('Model inputs'!F31,'Model inputs'!F32,'Model inputs'!F33,'Model inputs'!F34,'Model inputs'!F35) -> 0 | G30: =SUM('Model inputs'!G31,'Model inputs'!G32,'Model inputs'!G33,'Model inputs'!G34,'Model inputs'!G35) -> 0 | H30: =SUM('Model inputs'!H31,'Model inputs'!H32,'Model inputs'!H33,'Model inputs'!H34,'Model inputs'!H35) -> 0 | I30: =SUM('Model inputs'!I31,'Model inputs'!I32,'Model inputs'!I33,'Model inputs'!I34,'Model inputs'!I35) -> 0 | J30: =SUM('Model inputs'!J31,'Model inputs'!J32,'Model inputs'!J33,'Model inputs'!J34,'Model inputs'!J35) -> 0 | K30: =SUM('Model inputs'!K31,'Model inputs'!K32,'Model inputs'!K33,'Model inputs'!K34,'Model inputs'!K35) -> 0 | L30: ="" | M30: ="" | N30: ="" | O30: ="" | P30: ="" | Q30: ="" | R30: ="" | S30: ="" | ... Z30: =""
A31: Audits delivered > Annual deal-team | C31: =0 -> 0 | D31: =0 -> 0 | E31: =0 -> 0 | F31: =0 -> 0 | G31: =0 -> 0 | H31: =0 -> 0 | I31: =0 -> 0 | J31: =0 -> 0 | K31: =0 -> 0 | L31: ='Model inputs'!L154*'Model inputs'!AA113 -> 5 | M31: ='Model inputs'!M154*'Model inputs'!AA113 -> 10 | N31: ='Model inputs'!N154*'Model inputs'!AA113 -> 15 | O31: ='Model inputs'!O154*'Model inputs'!AA113 -> 20 | P31: ='Model inputs'!P154*'Model inputs'!AA113 -> 25 | Q31: ='Model inputs'!Q154*'Model inputs'!AA113 -> 30 | R31: ='Model inputs'!R154*'Model inputs'!AA113 -> 35 | S31: ='Model inputs'!S154*'Model inputs'!AA113 -> 40 | T31: ='Model inputs'!T154*'Model inputs'!AA113 -> 45 | U31: ='Model inputs'!U154*'Model inputs'!AA113 -> 50 | V31: ='Model inputs'!V154*'Model inputs'!AA113 -> 55 | W31: ='Model inputs'!W154*'Model inputs'!AA113 -> 60 | X31: ='Model inputs'!X154*'Model inputs'!AA113 -> 60 | Y31: ='Model inputs'!Y154*'Model inputs'!AA113 -> 60 | Z31: ='Model inputs'!Z154*'Model inputs'!AA113 -> 60
A32: Audits delivered > Hybrid | C32: =0 -> 0 | D32: =0 -> 0 | E32: =0 -> 0 | F32: =0 -> 0 | G32: =0 -> 0 | H32: =0 -> 0 | I32: =0 -> 0 | J32: =0 -> 0 | K32: =0 -> 0 | L32: ='Model inputs'!L154*'Model inputs'!AA114 -> 5 | M32: ='Model inputs'!M154*'Model inputs'!AA114 -> 10 | N32: ='Model inputs'!N154*'Model inputs'!AA114 -> 15 | O32: ='Model inputs'!O154*'Model inputs'!AA114 -> 20 | P32: ='Model inputs'!P154*'Model inputs'!AA114 -> 25 | Q32: ='Model inputs'!Q154*'Model inputs'!AA114 -> 30 | R32: ='Model inputs'!R154*'Model inputs'!AA114 -> 35 | S32: ='Model inputs'!S154*'Model inputs'!AA114 -> 40 | T32: ='Model inputs'!T154*'Model inputs'!AA114 -> 45 | U32: ='Model inputs'!U154*'Model inputs'!AA114 -> 50 | V32: ='Model inputs'!V154*'Model inputs'!AA114 -> 55 | W32: ='Model inputs'!W154*'Model inputs'!AA114 -> 60 | X32: ='Model inputs'!X154*'Model inputs'!AA114 -> 60 | Y32: ='Model inputs'!Y154*'Model inputs'!AA114 -> 60 | Z32: ='Model inputs'!Z154*'Model inputs'!AA114 -> 60
A33: Audits delivered > Per audit — base | C33: =0 -> 0 | D33: =0 -> 0 | E33: =0 -> 0 | F33: =0 -> 0 | G33: =0 -> 0 | H33: =0 -> 0 | I33: =0 -> 0 | J33: =0 -> 0 | K33: =0 -> 0 | L33: ='Model inputs'!L154*'Model inputs'!AA115 -> 5 | M33: ='Model inputs'!M154*'Model inputs'!AA115 -> 10 | N33: ='Model inputs'!N154*'Model inputs'!AA115 -> 15 | O33: ='Model inputs'!O154*'Model inputs'!AA115 -> 20 | P33: ='Model inputs'!P154*'Model inputs'!AA115 -> 25 | Q33: ='Model inputs'!Q154*'Model inputs'!AA115 -> 30 | R33: ='Model inputs'!R154*'Model inputs'!AA115 -> 35 | S33: ='Model inputs'!S154*'Model inputs'!AA115 -> 40 | T33: ='Model inputs'!T154*'Model inputs'!AA115 -> 45 | U33: ='Model inputs'!U154*'Model inputs'!AA115 -> 50 | V33: ='Model inputs'!V154*'Model inputs'!AA115 -> 55 | W33: ='Model inputs'!W154*'Model inputs'!AA115 -> 60 | X33: ='Model inputs'!X154*'Model inputs'!AA115 -> 60 | Y33: ='Model inputs'!Y154*'Model inputs'!AA115 -> 60 | Z33: ='Model inputs'!Z154*'Model inputs'!AA115 -> 60
A34: Audits delivered > Per audit — high | C34: =0 -> 0 | D34: =0 -> 0 | E34: =0 -> 0 | F34: =0 -> 0 | G34: =0 -> 0 | H34: =0 -> 0 | I34: =0 -> 0 | J34: =0 -> 0 | K34: =0 -> 0 | L34: ='Model inputs'!L154*'Model inputs'!AA116 -> 5 | M34: ='Model inputs'!M154*'Model inputs'!AA116 -> 10 | N34: ='Model inputs'!N154*'Model inputs'!AA116 -> 15 | O34: ='Model inputs'!O154*'Model inputs'!AA116 -> 20 | P34: ='Model inputs'!P154*'Model inputs'!AA116 -> 25 | Q34: ='Model inputs'!Q154*'Model inputs'!AA116 -> 30 | R34: ='Model inputs'!R154*'Model inputs'!AA116 -> 35 | S34: ='Model inputs'!S154*'Model inputs'!AA116 -> 40 | T34: ='Model inputs'!T154*'Model inputs'!AA116 -> 45 | U34: ='Model inputs'!U154*'Model inputs'!AA116 -> 50 | V34: ='Model inputs'!V154*'Model inputs'!AA116 -> 55 | W34: ='Model inputs'!W154*'Model inputs'!AA116 -> 60 | X34: ='Model inputs'!X154*'Model inputs'!AA116 -> 60 | Y34: ='Model inputs'!Y154*'Model inputs'!AA116 -> 60 | Z34: ='Model inputs'!Z154*'Model inputs'!AA116 -> 60
A35: Audits delivered > Per audit — low | C35: =0 -> 0 | D35: =0 -> 0 | E35: =0 -> 0 | F35: =0 -> 0 | G35: =0 -> 0 | H35: =0 -> 0 | I35: =0 -> 0 | J35: =0 -> 0 | K35: =0 -> 0 | L35: ='Model inputs'!L154*'Model inputs'!AA117 -> 5 | M35: ='Model inputs'!M154*'Model inputs'!AA117 -> 10 | N35: ='Model inputs'!N154*'Model inputs'!AA117 -> 15 | O35: ='Model inputs'!O154*'Model inputs'!AA117 -> 20 | P35: ='Model inputs'!P154*'Model inputs'!AA117 -> 25 | Q35: ='Model inputs'!Q154*'Model inputs'!AA117 -> 30 | R35: ='Model inputs'!R154*'Model inputs'!AA117 -> 35 | S35: ='Model inputs'!S154*'Model inputs'!AA117 -> 40 | T35: ='Model inputs'!T154*'Model inputs'!AA117 -> 45 | U35: ='Model inputs'!U154*'Model inputs'!AA117 -> 50 | V35: ='Model inputs'!V154*'Model inputs'!AA117 -> 55 | W35: ='Model inputs'!W154*'Model inputs'!AA117 -> 60 | X35: ='Model inputs'!X154*'Model inputs'!AA117 -> 60 | Y35: ='Model inputs'!Y154*'Model inputs'!AA117 -> 60 | Z35: ='Model inputs'!Z154*'Model inputs'!AA117 -> 60
A36: Audits delivered | C36: =SUM('Model inputs'!C37,'Model inputs'!C38,'Model inputs'!C39,'Model inputs'!C40,'Model inputs'!C41) -> 0 | D36: =SUM('Model inputs'!D37,'Model inputs'!D38,'Model inputs'!D39,'Model inputs'!D40,'Model inputs'!D41) -> 0 | E36: =SUM('Model inputs'!E37,'Model inputs'!E38,'Model inputs'!E39,'Model inputs'!E40,'Model inputs'!E41) -> 0 | F36: =SUM('Model inputs'!F37,'Model inputs'!F38,'Model inputs'!F39,'Model inputs'!F40,'Model inputs'!F41) -> 0 | G36: =SUM('Model inputs'!G37,'Model inputs'!G38,'Model inputs'!G39,'Model inputs'!G40,'Model inputs'!G41) -> 0 | H36: =SUM('Model inputs'!H37,'Model inputs'!H38,'Model inputs'!H39,'Model inputs'!H40,'Model inputs'!H41) -> 0 | I36: =SUM('Model inputs'!I37,'Model inputs'!I38,'Model inputs'!I39,'Model inputs'!I40,'Model inputs'!I41) -> 0 | J36: =SUM('Model inputs'!J37,'Model inputs'!J38,'Model inputs'!J39,'Model inputs'!J40,'Model inputs'!J41) -> 0 | K36: =SUM('Model inputs'!K37,'Model inputs'!K38,'Model inputs'!K39,'Model inputs'!K40,'Model inputs'!K41) -> 0 | L36: ="" | M36: ="" | N36: ="" | O36: ="" | P36: ="" | Q36: ="" | R36: ="" | S36: ="" | ... Z36: =""
A37: Audits delivered > Annual deal-team | C37: =0 -> 0 | D37: =0 -> 0 | E37: =0 -> 0 | F37: =0 -> 0 | G37: =0 -> 0 | H37: =0 -> 0 | I37: =0 -> 0 | J37: =0 -> 0 | K37: =0 -> 0 | L37: ='Model inputs'!L155*'Model inputs'!AA119 -> 0 | M37: ='Model inputs'!M155*'Model inputs'!AA119 -> 0 | N37: ='Model inputs'!N155*'Model inputs'!AA119 -> 4 | O37: ='Model inputs'!O155*'Model inputs'!AA119 -> 4 | P37: ='Model inputs'!P155*'Model inputs'!AA119 -> 4 | Q37: ='Model inputs'!Q155*'Model inputs'!AA119 -> 4 | R37: ='Model inputs'!R155*'Model inputs'!AA119 -> 4 | S37: ='Model inputs'!S155*'Model inputs'!AA119 -> 4 | T37: ='Model inputs'!T155*'Model inputs'!AA119 -> 4 | U37: ='Model inputs'!U155*'Model inputs'!AA119 -> 4 | V37: ='Model inputs'!V155*'Model inputs'!AA119 -> 4 | W37: ='Model inputs'!W155*'Model inputs'!AA119 -> 4 | X37: ='Model inputs'!X155*'Model inputs'!AA119 -> 4 | Y37: ='Model inputs'!Y155*'Model inputs'!AA119 -> 4 | Z37: ='Model inputs'!Z155*'Model inputs'!AA119 -> 4
A38: Audits delivered > Hybrid | C38: =0 -> 0 | D38: =0 -> 0 | E38: =0 -> 0 | F38: =0 -> 0 | G38: =0 -> 0 | H38: =0 -> 0 | I38: =0 -> 0 | J38: =0 -> 0 | K38: =0 -> 0 | L38: ='Model inputs'!L155*'Model inputs'!AA120 -> 0 | M38: ='Model inputs'!M155*'Model inputs'!AA120 -> 0 | N38: ='Model inputs'!N155*'Model inputs'!AA120 -> 4 | O38: ='Model inputs'!O155*'Model inputs'!AA120 -> 4 | P38: ='Model inputs'!P155*'Model inputs'!AA120 -> 4 | Q38: ='Model inputs'!Q155*'Model inputs'!AA120 -> 4 | R38: ='Model inputs'!R155*'Model inputs'!AA120 -> 4 | S38: ='Model inputs'!S155*'Model inputs'!AA120 -> 4 | T38: ='Model inputs'!T155*'Model inputs'!AA120 -> 4 | U38: ='Model inputs'!U155*'Model inputs'!AA120 -> 4 | V38: ='Model inputs'!V155*'Model inputs'!AA120 -> 4 | W38: ='Model inputs'!W155*'Model inputs'!AA120 -> 4 | X38: ='Model inputs'!X155*'Model inputs'!AA120 -> 4 | Y38: ='Model inputs'!Y155*'Model inputs'!AA120 -> 4 | Z38: ='Model inputs'!Z155*'Model inputs'!AA120 -> 4
A39: Audits delivered > Per audit — base | C39: =0 -> 0 | D39: =0 -> 0 | E39: =0 -> 0 | F39: =0 -> 0 | G39: =0 -> 0 | H39: =0 -> 0 | I39: =0 -> 0 | J39: =0 -> 0 | K39: =0 -> 0 | L39: ='Model inputs'!L155*'Model inputs'!AA121 -> 0 | M39: ='Model inputs'!M155*'Model inputs'!AA121 -> 0 | N39: ='Model inputs'!N155*'Model inputs'!AA121 -> 4 | O39: ='Model inputs'!O155*'Model inputs'!AA121 -> 4 | P39: ='Model inputs'!P155*'Model inputs'!AA121 -> 4 | Q39: ='Model inputs'!Q155*'Model inputs'!AA121 -> 4 | R39: ='Model inputs'!R155*'Model inputs'!AA121 -> 4 | S39: ='Model inputs'!S155*'Model inputs'!AA121 -> 4 | T39: ='Model inputs'!T155*'Model inputs'!AA121 -> 4 | U39: ='Model inputs'!U155*'Model inputs'!AA121 -> 4 | V39: ='Model inputs'!V155*'Model inputs'!AA121 -> 4 | W39: ='Model inputs'!W155*'Model inputs'!AA121 -> 4 | X39: ='Model inputs'!X155*'Model inputs'!AA121 -> 4 | Y39: ='Model inputs'!Y155*'Model inputs'!AA121 -> 4 | Z39: ='Model inputs'!Z155*'Model inputs'!AA121 -> 4
A40: Audits delivered > Per audit — high | C40: =0 -> 0 | D40: =0 -> 0 | E40: =0 -> 0 | F40: =0 -> 0 | G40: =0 -> 0 | H40: =0 -> 0 | I40: =0 -> 0 | J40: =0 -> 0 | K40: =0 -> 0 | L40: ='Model inputs'!L155*'Model inputs'!AA122 -> 0 | M40: ='Model inputs'!M155*'Model inputs'!AA122 -> 0 | N40: ='Model inputs'!N155*'Model inputs'!AA122 -> 4 | O40: ='Model inputs'!O155*'Model inputs'!AA122 -> 4 | P40: ='Model inputs'!P155*'Model inputs'!AA122 -> 4 | Q40: ='Model inputs'!Q155*'Model inputs'!AA122 -> 4 | R40: ='Model inputs'!R155*'Model inputs'!AA122 -> 4 | S40: ='Model inputs'!S155*'Model inputs'!AA122 -> 4 | T40: ='Model inputs'!T155*'Model inputs'!AA122 -> 4 | U40: ='Model inputs'!U155*'Model inputs'!AA122 -> 4 | V40: ='Model inputs'!V155*'Model inputs'!AA122 -> 4 | W40: ='Model inputs'!W155*'Model inputs'!AA122 -> 4 | X40: ='Model inputs'!X155*'Model inputs'!AA122 -> 4 | Y40: ='Model inputs'!Y155*'Model inputs'!AA122 -> 4 | Z40: ='Model inputs'!Z155*'Model inputs'!AA122 -> 4
A41: Audits delivered > Per audit — low | C41: =0 -> 0 | D41: =0 -> 0 | E41: =0 -> 0 | F41: =0 -> 0 | G41: =0 -> 0 | H41: =0 -> 0 | I41: =0 -> 0 | J41: =0 -> 0 | K41: =0 -> 0 | L41: ='Model inputs'!L155*'Model inputs'!AA123 -> 0 | M41: ='Model inputs'!M155*'Model inputs'!AA123 -> 0 | N41: ='Model inputs'!N155*'Model inputs'!AA123 -> 4 | O41: ='Model inputs'!O155*'Model inputs'!AA123 -> 4 | P41: ='Model inputs'!P155*'Model inputs'!AA123 -> 4 | Q41: ='Model inputs'!Q155*'Model inputs'!AA123 -> 4 | R41: ='Model inputs'!R155*'Model inputs'!AA123 -> 4 | S41: ='Model inputs'!S155*'Model inputs'!AA123 -> 4 | T41: ='Model inputs'!T155*'Model inputs'!AA123 -> 4 | U41: ='Model inputs'!U155*'Model inputs'!AA123 -> 4 | V41: ='Model inputs'!V155*'Model inputs'!AA123 -> 4 | W41: ='Model inputs'!W155*'Model inputs'!AA123 -> 4 | X41: ='Model inputs'!X155*'Model inputs'!AA123 -> 4 | Y41: ='Model inputs'!Y155*'Model inputs'!AA123 -> 4 | Z41: ='Model inputs'!Z155*'Model inputs'!AA123 -> 4
A42: Cash collections | C42: =SUM('Model inputs'!C43,'Model inputs'!C44,'Model inputs'!C45,'Model inputs'!C46,'Model inputs'!C47) -> 0 | D42: =SUM('Model inputs'!D43,'Model inputs'!D44,'Model inputs'!D45,'Model inputs'!D46,'Model inputs'!D47) -> 0 | E42: =SUM('Model inputs'!E43,'Model inputs'!E44,'Model inputs'!E45,'Model inputs'!E46,'Model inputs'!E47) -> 0 | F42: =SUM('Model inputs'!F43,'Model inputs'!F44,'Model inputs'!F45,'Model inputs'!F46,'Model inputs'!F47) -> 0 | G42: =SUM('Model inputs'!G43,'Model inputs'!G44,'Model inputs'!G45,'Model inputs'!G46,'Model inputs'!G47) -> 0 | H42: =SUM('Model inputs'!H43,'Model inputs'!H44,'Model inputs'!H45,'Model inputs'!H46,'Model inputs'!H47) -> 0 | I42: =SUM('Model inputs'!I43,'Model inputs'!I44,'Model inputs'!I45,'Model inputs'!I46,'Model inputs'!I47) -> 0 | J42: =SUM('Model inputs'!J43,'Model inputs'!J44,'Model inputs'!J45,'Model inputs'!J46,'Model inputs'!J47) -> 0 | K42: =SUM('Model inputs'!K43,'Model inputs'!K44,'Model inputs'!K45,'Model inputs'!K46,'Model inputs'!K47) -> 0 | L42: ="" | M42: ="" | N42: ="" | O42: ="" | P42: ="" | Q42: ="" | R42: ="" | S42: ="" | ... Z42: =""
A43: Cash collections > Annual deal-team | C43: =0 -> 0 | D43: =0 -> 0 | E43: =0 -> 0 | F43: =0 -> 0 | G43: =0 -> 0 | H43: =0 -> 0 | I43: =0 -> 0 | J43: =0 -> 0 | K43: =0 -> 0 | L43: ='Model inputs'!L152*'Model inputs'!AA173*(1-'Model inputs'!AA170)+'Model inputs'!L57-'Model inputs'!L154*'Model inputs'!AA173/12*(1-'Model inputs'!AA170) -> 32500 | M43: ='Model inputs'!M152*'Model inputs'!AA173*(1-'Model inputs'!AA170)+'Model inputs'!M57-'Model inputs'!M154*'Model inputs'!AA173/12*(1-'Model inputs'!AA170) -> 35000 | N43: ='Model inputs'!N152*'Model inputs'!AA173*(1-'Model inputs'!AA170)+'Model inputs'!N57-'Model inputs'!N154*'Model inputs'!AA173/12*(1-'Model inputs'!AA170) -> 37500 | O43: ='Model inputs'!O152*'Model inputs'!AA173*(1-'Model inputs'!AA170)+'Model inputs'!O57-'Model inputs'!O154*'Model inputs'!AA173/12*(1-'Model inputs'!AA170) -> 40000 | P43: ='Model inputs'!P152*'Model inputs'!AA173*(1-'Model inputs'!AA170)+'Model inputs'!P57-'Model inputs'!P154*'Model inputs'!AA173/12*(1-'Model inputs'!AA170) -> 42500 | Q43: ='Model inputs'!Q152*'Model inputs'!AA173*(1-'Model inputs'!AA170)+'Model inputs'!Q57-'Model inputs'!Q154*'Model inputs'!AA173/12*(1-'Model inputs'!AA170) -> 45000 | R43: ='Model inputs'!R152*'Model inputs'!AA173*(1-'Model inputs'!AA170)+'Model inputs'!R57-'Model inputs'!R154*'Model inputs'!AA173/12*(1-'Model inputs'!AA170) -> 47500 | S43: ='Model inputs'!S152*'Model inputs'!AA173*(1-'Model inputs'!AA170)+'Model inputs'!S57-'Model inputs'!S154*'Model inputs'!AA173/12*(1-'Model inputs'!AA170) -> 50000 | T43: ='Model inputs'!T152*'Model inputs'!AA173*(1-'Model inputs'!AA170)+'Model inputs'!T57-'Model inputs'!T154*'Model inputs'!AA173/12*(1-'Model inputs'!AA170) -> 52500 | U43: ='Model inputs'!U152*'Model inputs'!AA173*(1-'Model inputs'!AA170)+'Model inputs'!U57-'Model inputs'!U154*'Model inputs'!AA173/12*(1-'Model inputs'!AA170) -> 55000 | V43: ='Model inputs'!V152*'Model inputs'!AA173*(1-'Model inputs'!AA170)+'Model inputs'!V57-'Model inputs'!V154*'Model inputs'!AA173/12*(1-'Model inputs'!AA170) -> 57500 | W43: ='Model inputs'!W152*'Model inputs'!AA173*(1-'Model inputs'!AA170)+'Model inputs'!W57-'Model inputs'!W154*'Model inputs'!AA173/12*(1-'Model inputs'!AA170) -> 60000 | X43: ='Model inputs'!X152*'Model inputs'!AA173*(1-'Model inputs'!AA170)+'Model inputs'!X57-'Model inputs'!X154*'Model inputs'!AA173/12*(1-'Model inputs'!AA170) -> 30000 | Y43: ='Model inputs'!Y152*'Model inputs'!AA173*(1-'Model inputs'!AA170)+'Model inputs'!Y57-'Model inputs'!Y154*'Model inputs'!AA173/12*(1-'Model inputs'!AA170) -> 30000 | Z43: ='Model inputs'!Z152*'Model inputs'!AA173*(1-'Model inputs'!AA170)+'Model inputs'!Z57-'Model inputs'!Z154*'Model inputs'!AA173/12*(1-'Model inputs'!AA170) -> 30000
A44: Cash collections > Hybrid | C44: =0 -> 0 | D44: =0 -> 0 | E44: =0 -> 0 | F44: =0 -> 0 | G44: =0 -> 0 | H44: =0 -> 0 | I44: =0 -> 0 | J44: =0 -> 0 | K44: =0 -> 0 | L44: ='Model inputs'!L152*'Model inputs'!AA174*(1-'Model inputs'!AA170)+'Model inputs'!L58-'Model inputs'!L154*'Model inputs'!AA174/12*(1-'Model inputs'!AA170) -> 12500 | M44: ='Model inputs'!M152*'Model inputs'!AA174*(1-'Model inputs'!AA170)+'Model inputs'!M58-'Model inputs'!M154*'Model inputs'!AA174/12*(1-'Model inputs'!AA170) -> 17500 | N44: ='Model inputs'!N152*'Model inputs'!AA174*(1-'Model inputs'!AA170)+'Model inputs'!N58-'Model inputs'!N154*'Model inputs'!AA174/12*(1-'Model inputs'!AA170) -> 22500 | O44: ='Model inputs'!O152*'Model inputs'!AA174*(1-'Model inputs'!AA170)+'Model inputs'!O58-'Model inputs'!O154*'Model inputs'!AA174/12*(1-'Model inputs'!AA170) -> 27500 | P44: ='Model inputs'!P152*'Model inputs'!AA174*(1-'Model inputs'!AA170)+'Model inputs'!P58-'Model inputs'!P154*'Model inputs'!AA174/12*(1-'Model inputs'!AA170) -> 32500 | Q44: ='Model inputs'!Q152*'Model inputs'!AA174*(1-'Model inputs'!AA170)+'Model inputs'!Q58-'Model inputs'!Q154*'Model inputs'!AA174/12*(1-'Model inputs'!AA170) -> 37500 | R44: ='Model inputs'!R152*'Model inputs'!AA174*(1-'Model inputs'!AA170)+'Model inputs'!R58-'Model inputs'!R154*'Model inputs'!AA174/12*(1-'Model inputs'!AA170) -> 42500 | S44: ='Model inputs'!S152*'Model inputs'!AA174*(1-'Model inputs'!AA170)+'Model inputs'!S58-'Model inputs'!S154*'Model inputs'!AA174/12*(1-'Model inputs'!AA170) -> 47500 | T44: ='Model inputs'!T152*'Model inputs'!AA174*(1-'Model inputs'!AA170)+'Model inputs'!T58-'Model inputs'!T154*'Model inputs'!AA174/12*(1-'Model inputs'!AA170) -> 52500 | U44: ='Model inputs'!U152*'Model inputs'!AA174*(1-'Model inputs'!AA170)+'Model inputs'!U58-'Model inputs'!U154*'Model inputs'!AA174/12*(1-'Model inputs'!AA170) -> 57500 | V44: ='Model inputs'!V152*'Model inputs'!AA174*(1-'Model inputs'!AA170)+'Model inputs'!V58-'Model inputs'!V154*'Model inputs'!AA174/12*(1-'Model inputs'!AA170) -> 62500 | W44: ='Model inputs'!W152*'Model inputs'!AA174*(1-'Model inputs'!AA170)+'Model inputs'!W58-'Model inputs'!W154*'Model inputs'!AA174/12*(1-'Model inputs'!AA170) -> 67500 | X44: ='Model inputs'!X152*'Model inputs'!AA174*(1-'Model inputs'!AA170)+'Model inputs'!X58-'Model inputs'!X154*'Model inputs'!AA174/12*(1-'Model inputs'!AA170) -> 60000 | Y44: ='Model inputs'!Y152*'Model inputs'!AA174*(1-'Model inputs'!AA170)+'Model inputs'!Y58-'Model inputs'!Y154*'Model inputs'!AA174/12*(1-'Model inputs'!AA170) -> 60000 | Z44: ='Model inputs'!Z152*'Model inputs'!AA174*(1-'Model inputs'!AA170)+'Model inputs'!Z58-'Model inputs'!Z154*'Model inputs'!AA174/12*(1-'Model inputs'!AA170) -> 60000
A45: Cash collections > Per audit — base | C45: =0 -> 0 | D45: =0 -> 0 | E45: =0 -> 0 | F45: =0 -> 0 | G45: =0 -> 0 | H45: =0 -> 0 | I45: =0 -> 0 | J45: =0 -> 0 | K45: =0 -> 0 | L45: ='Model inputs'!L152*'Model inputs'!AA175*(1-'Model inputs'!AA170)+'Model inputs'!L59-'Model inputs'!L154*'Model inputs'!AA175/12*(1-'Model inputs'!AA170) -> 7500 | M45: ='Model inputs'!M152*'Model inputs'!AA175*(1-'Model inputs'!AA170)+'Model inputs'!M59-'Model inputs'!M154*'Model inputs'!AA175/12*(1-'Model inputs'!AA170) -> 15000 | N45: ='Model inputs'!N152*'Model inputs'!AA175*(1-'Model inputs'!AA170)+'Model inputs'!N59-'Model inputs'!N154*'Model inputs'!AA175/12*(1-'Model inputs'!AA170) -> 22500 | O45: ='Model inputs'!O152*'Model inputs'!AA175*(1-'Model inputs'!AA170)+'Model inputs'!O59-'Model inputs'!O154*'Model inputs'!AA175/12*(1-'Model inputs'!AA170) -> 30000 | P45: ='Model inputs'!P152*'Model inputs'!AA175*(1-'Model inputs'!AA170)+'Model inputs'!P59-'Model inputs'!P154*'Model inputs'!AA175/12*(1-'Model inputs'!AA170) -> 37500 | Q45: ='Model inputs'!Q152*'Model inputs'!AA175*(1-'Model inputs'!AA170)+'Model inputs'!Q59-'Model inputs'!Q154*'Model inputs'!AA175/12*(1-'Model inputs'!AA170) -> 45000 | R45: ='Model inputs'!R152*'Model inputs'!AA175*(1-'Model inputs'!AA170)+'Model inputs'!R59-'Model inputs'!R154*'Model inputs'!AA175/12*(1-'Model inputs'!AA170) -> 52500 | S45: ='Model inputs'!S152*'Model inputs'!AA175*(1-'Model inputs'!AA170)+'Model inputs'!S59-'Model inputs'!S154*'Model inputs'!AA175/12*(1-'Model inputs'!AA170) -> 60000 | T45: ='Model inputs'!T152*'Model inputs'!AA175*(1-'Model inputs'!AA170)+'Model inputs'!T59-'Model inputs'!T154*'Model inputs'!AA175/12*(1-'Model inputs'!AA170) -> 67500 | U45: ='Model inputs'!U152*'Model inputs'!AA175*(1-'Model inputs'!AA170)+'Model inputs'!U59-'Model inputs'!U154*'Model inputs'!AA175/12*(1-'Model inputs'!AA170) -> 75000 | V45: ='Model inputs'!V152*'Model inputs'!AA175*(1-'Model inputs'!AA170)+'Model inputs'!V59-'Model inputs'!V154*'Model inputs'!AA175/12*(1-'Model inputs'!AA170) -> 82500 | W45: ='Model inputs'!W152*'Model inputs'!AA175*(1-'Model inputs'!AA170)+'Model inputs'!W59-'Model inputs'!W154*'Model inputs'!AA175/12*(1-'Model inputs'!AA170) -> 90000 | X45: ='Model inputs'!X152*'Model inputs'!AA175*(1-'Model inputs'!AA170)+'Model inputs'!X59-'Model inputs'!X154*'Model inputs'!AA175/12*(1-'Model inputs'!AA170) -> 90000 | Y45: ='Model inputs'!Y152*'Model inputs'!AA175*(1-'Model inputs'!AA170)+'Model inputs'!Y59-'Model inputs'!Y154*'Model inputs'!AA175/12*(1-'Model inputs'!AA170) -> 90000 | Z45: ='Model inputs'!Z152*'Model inputs'!AA175*(1-'Model inputs'!AA170)+'Model inputs'!Z59-'Model inputs'!Z154*'Model inputs'!AA175/12*(1-'Model inputs'!AA170) -> 90000
A46: Cash collections > Per audit — high | C46: =0 -> 0 | D46: =0 -> 0 | E46: =0 -> 0 | F46: =0 -> 0 | G46: =0 -> 0 | H46: =0 -> 0 | I46: =0 -> 0 | J46: =0 -> 0 | K46: =0 -> 0 | L46: ='Model inputs'!L152*'Model inputs'!AA176*(1-'Model inputs'!AA170)+'Model inputs'!L60-'Model inputs'!L154*'Model inputs'!AA176/12*(1-'Model inputs'!AA170) -> 15000 | M46: ='Model inputs'!M152*'Model inputs'!AA176*(1-'Model inputs'!AA170)+'Model inputs'!M60-'Model inputs'!M154*'Model inputs'!AA176/12*(1-'Model inputs'!AA170) -> 30000 | N46: ='Model inputs'!N152*'Model inputs'!AA176*(1-'Model inputs'!AA170)+'Model inputs'!N60-'Model inputs'!N154*'Model inputs'!AA176/12*(1-'Model inputs'!AA170) -> 45000 | O46: ='Model inputs'!O152*'Model inputs'!AA176*(1-'Model inputs'!AA170)+'Model inputs'!O60-'Model inputs'!O154*'Model inputs'!AA176/12*(1-'Model inputs'!AA170) -> 60000 | P46: ='Model inputs'!P152*'Model inputs'!AA176*(1-'Model inputs'!AA170)+'Model inputs'!P60-'Model inputs'!P154*'Model inputs'!AA176/12*(1-'Model inputs'!AA170) -> 75000 | Q46: ='Model inputs'!Q152*'Model inputs'!AA176*(1-'Model inputs'!AA170)+'Model inputs'!Q60-'Model inputs'!Q154*'Model inputs'!AA176/12*(1-'Model inputs'!AA170) -> 90000 | R46: ='Model inputs'!R152*'Model inputs'!AA176*(1-'Model inputs'!AA170)+'Model inputs'!R60-'Model inputs'!R154*'Model inputs'!AA176/12*(1-'Model inputs'!AA170) -> 105000 | S46: ='Model inputs'!S152*'Model inputs'!AA176*(1-'Model inputs'!AA170)+'Model inputs'!S60-'Model inputs'!S154*'Model inputs'!AA176/12*(1-'Model inputs'!AA170) -> 120000 | T46: ='Model inputs'!T152*'Model inputs'!AA176*(1-'Model inputs'!AA170)+'Model inputs'!T60-'Model inputs'!T154*'Model inputs'!AA176/12*(1-'Model inputs'!AA170) -> 135000 | U46: ='Model inputs'!U152*'Model inputs'!AA176*(1-'Model inputs'!AA170)+'Model inputs'!U60-'Model inputs'!U154*'Model inputs'!AA176/12*(1-'Model inputs'!AA170) -> 150000 | V46: ='Model inputs'!V152*'Model inputs'!AA176*(1-'Model inputs'!AA170)+'Model inputs'!V60-'Model inputs'!V154*'Model inputs'!AA176/12*(1-'Model inputs'!AA170) -> 165000 | W46: ='Model inputs'!W152*'Model inputs'!AA176*(1-'Model inputs'!AA170)+'Model inputs'!W60-'Model inputs'!W154*'Model inputs'!AA176/12*(1-'Model inputs'!AA170) -> 180000 | X46: ='Model inputs'!X152*'Model inputs'!AA176*(1-'Model inputs'!AA170)+'Model inputs'!X60-'Model inputs'!X154*'Model inputs'!AA176/12*(1-'Model inputs'!AA170) -> 180000 | Y46: ='Model inputs'!Y152*'Model inputs'!AA176*(1-'Model inputs'!AA170)+'Model inputs'!Y60-'Model inputs'!Y154*'Model inputs'!AA176/12*(1-'Model inputs'!AA170) -> 180000 | Z46: ='Model inputs'!Z152*'Model inputs'!AA176*(1-'Model inputs'!AA170)+'Model inputs'!Z60-'Model inputs'!Z154*'Model inputs'!AA176/12*(1-'Model inputs'!AA170) -> 180000
A47: Cash collections > Per audit — low | C47: =0 -> 0 | D47: =0 -> 0 | E47: =0 -> 0 | F47: =0 -> 0 | G47: =0 -> 0 | H47: =0 -> 0 | I47: =0 -> 0 | J47: =0 -> 0 | K47: =0 -> 0 | L47: ='Model inputs'!L152*'Model inputs'!AA177*(1-'Model inputs'!AA170)+'Model inputs'!L61-'Model inputs'!L154*'Model inputs'!AA177/12*(1-'Model inputs'!AA170) -> 3750 | M47: ='Model inputs'!M152*'Model inputs'!AA177*(1-'Model inputs'!AA170)+'Model inputs'!M61-'Model inputs'!M154*'Model inputs'!AA177/12*(1-'Model inputs'!AA170) -> 7500 | N47: ='Model inputs'!N152*'Model inputs'!AA177*(1-'Model inputs'!AA170)+'Model inputs'!N61-'Model inputs'!N154*'Model inputs'!AA177/12*(1-'Model inputs'!AA170) -> 11250 | O47: ='Model inputs'!O152*'Model inputs'!AA177*(1-'Model inputs'!AA170)+'Model inputs'!O61-'Model inputs'!O154*'Model inputs'!AA177/12*(1-'Model inputs'!AA170) -> 15000 | P47: ='Model inputs'!P152*'Model inputs'!AA177*(1-'Model inputs'!AA170)+'Model inputs'!P61-'Model inputs'!P154*'Model inputs'!AA177/12*(1-'Model inputs'!AA170) -> 18750 | Q47: ='Model inputs'!Q152*'Model inputs'!AA177*(1-'Model inputs'!AA170)+'Model inputs'!Q61-'Model inputs'!Q154*'Model inputs'!AA177/12*(1-'Model inputs'!AA170) -> 22500 | R47: ='Model inputs'!R152*'Model inputs'!AA177*(1-'Model inputs'!AA170)+'Model inputs'!R61-'Model inputs'!R154*'Model inputs'!AA177/12*(1-'Model inputs'!AA170) -> 26250 | S47: ='Model inputs'!S152*'Model inputs'!AA177*(1-'Model inputs'!AA170)+'Model inputs'!S61-'Model inputs'!S154*'Model inputs'!AA177/12*(1-'Model inputs'!AA170) -> 30000 | T47: ='Model inputs'!T152*'Model inputs'!AA177*(1-'Model inputs'!AA170)+'Model inputs'!T61-'Model inputs'!T154*'Model inputs'!AA177/12*(1-'Model inputs'!AA170) -> 33750 | U47: ='Model inputs'!U152*'Model inputs'!AA177*(1-'Model inputs'!AA170)+'Model inputs'!U61-'Model inputs'!U154*'Model inputs'!AA177/12*(1-'Model inputs'!AA170) -> 37500 | V47: ='Model inputs'!V152*'Model inputs'!AA177*(1-'Model inputs'!AA170)+'Model inputs'!V61-'Model inputs'!V154*'Model inputs'!AA177/12*(1-'Model inputs'!AA170) -> 41250 | W47: ='Model inputs'!W152*'Model inputs'!AA177*(1-'Model inputs'!AA170)+'Model inputs'!W61-'Model inputs'!W154*'Model inputs'!AA177/12*(1-'Model inputs'!AA170) -> 45000 | X47: ='Model inputs'!X152*'Model inputs'!AA177*(1-'Model inputs'!AA170)+'Model inputs'!X61-'Model inputs'!X154*'Model inputs'!AA177/12*(1-'Model inputs'!AA170) -> 45000 | Y47: ='Model inputs'!Y152*'Model inputs'!AA177*(1-'Model inputs'!AA170)+'Model inputs'!Y61-'Model inputs'!Y154*'Model inputs'!AA177/12*(1-'Model inputs'!AA170) -> 45000 | Z47: ='Model inputs'!Z152*'Model inputs'!AA177*(1-'Model inputs'!AA170)+'Model inputs'!Z61-'Model inputs'!Z154*'Model inputs'!AA177/12*(1-'Model inputs'!AA170) -> 45000
A48: Cash collections | C48: =SUM('Model inputs'!C49,'Model inputs'!C50,'Model inputs'!C51,'Model inputs'!C52,'Model inputs'!C53) -> 0 | D48: =SUM('Model inputs'!D49,'Model inputs'!D50,'Model inputs'!D51,'Model inputs'!D52,'Model inputs'!D53) -> 0 | E48: =SUM('Model inputs'!E49,'Model inputs'!E50,'Model inputs'!E51,'Model inputs'!E52,'Model inputs'!E53) -> 0 | F48: =SUM('Model inputs'!F49,'Model inputs'!F50,'Model inputs'!F51,'Model inputs'!F52,'Model inputs'!F53) -> 0 | G48: =SUM('Model inputs'!G49,'Model inputs'!G50,'Model inputs'!G51,'Model inputs'!G52,'Model inputs'!G53) -> 0 | H48: =SUM('Model inputs'!H49,'Model inputs'!H50,'Model inputs'!H51,'Model inputs'!H52,'Model inputs'!H53) -> 0 | I48: =SUM('Model inputs'!I49,'Model inputs'!I50,'Model inputs'!I51,'Model inputs'!I52,'Model inputs'!I53) -> 0 | J48: =SUM('Model inputs'!J49,'Model inputs'!J50,'Model inputs'!J51,'Model inputs'!J52,'Model inputs'!J53) -> 0 | K48: =SUM('Model inputs'!K49,'Model inputs'!K50,'Model inputs'!K51,'Model inputs'!K52,'Model inputs'!K53) -> 0 | L48: ="" | M48: ="" | N48: ="" | O48: ="" | P48: ="" | Q48: ="" | R48: ="" | S48: ="" | ... Z48: =""
A49: Cash collections > Annual deal-team | C49: =0 -> 0 | D49: =0 -> 0 | E49: =0 -> 0 | F49: =0 -> 0 | G49: =0 -> 0 | H49: =0 -> 0 | I49: =0 -> 0 | J49: =0 -> 0 | K49: =0 -> 0 | L49: ='Model inputs'!L153*'Model inputs'!AA179*(1-'Model inputs'!AA171)+'Model inputs'!L63-'Model inputs'!L155*'Model inputs'!AA179/12*(1-'Model inputs'!AA171) -> 0 | M49: ='Model inputs'!M153*'Model inputs'!AA179*(1-'Model inputs'!AA171)+'Model inputs'!M63-'Model inputs'!M155*'Model inputs'!AA179/12*(1-'Model inputs'!AA171) -> 0 | N49: ='Model inputs'!N153*'Model inputs'!AA179*(1-'Model inputs'!AA171)+'Model inputs'!N63-'Model inputs'!N155*'Model inputs'!AA179/12*(1-'Model inputs'!AA171) -> 48000 | O49: ='Model inputs'!O153*'Model inputs'!AA179*(1-'Model inputs'!AA171)+'Model inputs'!O63-'Model inputs'!O155*'Model inputs'!AA179/12*(1-'Model inputs'!AA171) -> 0 | P49: ='Model inputs'!P153*'Model inputs'!AA179*(1-'Model inputs'!AA171)+'Model inputs'!P63-'Model inputs'!P155*'Model inputs'!AA179/12*(1-'Model inputs'!AA171) -> 0 | Q49: ='Model inputs'!Q153*'Model inputs'!AA179*(1-'Model inputs'!AA171)+'Model inputs'!Q63-'Model inputs'!Q155*'Model inputs'!AA179/12*(1-'Model inputs'!AA171) -> 0 | R49: ='Model inputs'!R153*'Model inputs'!AA179*(1-'Model inputs'!AA171)+'Model inputs'!R63-'Model inputs'!R155*'Model inputs'!AA179/12*(1-'Model inputs'!AA171) -> 0 | S49: ='Model inputs'!S153*'Model inputs'!AA179*(1-'Model inputs'!AA171)+'Model inputs'!S63-'Model inputs'!S155*'Model inputs'!AA179/12*(1-'Model inputs'!AA171) -> 0 | T49: ='Model inputs'!T153*'Model inputs'!AA179*(1-'Model inputs'!AA171)+'Model inputs'!T63-'Model inputs'!T155*'Model inputs'!AA179/12*(1-'Model inputs'!AA171) -> 0 | U49: ='Model inputs'!U153*'Model inputs'!AA179*(1-'Model inputs'!AA171)+'Model inputs'!U63-'Model inputs'!U155*'Model inputs'!AA179/12*(1-'Model inputs'!AA171) -> 0 | V49: ='Model inputs'!V153*'Model inputs'!AA179*(1-'Model inputs'!AA171)+'Model inputs'!V63-'Model inputs'!V155*'Model inputs'!AA179/12*(1-'Model inputs'!AA171) -> 0 | W49: ='Model inputs'!W153*'Model inputs'!AA179*(1-'Model inputs'!AA171)+'Model inputs'!W63-'Model inputs'!W155*'Model inputs'!AA179/12*(1-'Model inputs'!AA171) -> 0 | X49: ='Model inputs'!X153*'Model inputs'!AA179*(1-'Model inputs'!AA171)+'Model inputs'!X63-'Model inputs'!X155*'Model inputs'!AA179/12*(1-'Model inputs'!AA171) -> 0 | Y49: ='Model inputs'!Y153*'Model inputs'!AA179*(1-'Model inputs'!AA171)+'Model inputs'!Y63-'Model inputs'!Y155*'Model inputs'!AA179/12*(1-'Model inputs'!AA171) -> 0 | Z49: ='Model inputs'!Z153*'Model inputs'!AA179*(1-'Model inputs'!AA171)+'Model inputs'!Z63-'Model inputs'!Z155*'Model inputs'!AA179/12*(1-'Model inputs'!AA171) -> 0
A50: Cash collections > Hybrid | C50: =0 -> 0 | D50: =0 -> 0 | E50: =0 -> 0 | F50: =0 -> 0 | G50: =0 -> 0 | H50: =0 -> 0 | I50: =0 -> 0 | J50: =0 -> 0 | K50: =0 -> 0 | L50: ='Model inputs'!L153*'Model inputs'!AA180*(1-'Model inputs'!AA171)+'Model inputs'!L64-'Model inputs'!L155*'Model inputs'!AA180/12*(1-'Model inputs'!AA171) -> 0 | M50: ='Model inputs'!M153*'Model inputs'!AA180*(1-'Model inputs'!AA171)+'Model inputs'!M64-'Model inputs'!M155*'Model inputs'!AA180/12*(1-'Model inputs'!AA171) -> 0 | N50: ='Model inputs'!N153*'Model inputs'!AA180*(1-'Model inputs'!AA171)+'Model inputs'!N64-'Model inputs'!N155*'Model inputs'!AA180/12*(1-'Model inputs'!AA171) -> 16000 | O50: ='Model inputs'!O153*'Model inputs'!AA180*(1-'Model inputs'!AA171)+'Model inputs'!O64-'Model inputs'!O155*'Model inputs'!AA180/12*(1-'Model inputs'!AA171) -> 4000 | P50: ='Model inputs'!P153*'Model inputs'!AA180*(1-'Model inputs'!AA171)+'Model inputs'!P64-'Model inputs'!P155*'Model inputs'!AA180/12*(1-'Model inputs'!AA171) -> 4000 | Q50: ='Model inputs'!Q153*'Model inputs'!AA180*(1-'Model inputs'!AA171)+'Model inputs'!Q64-'Model inputs'!Q155*'Model inputs'!AA180/12*(1-'Model inputs'!AA171) -> 4000 | R50: ='Model inputs'!R153*'Model inputs'!AA180*(1-'Model inputs'!AA171)+'Model inputs'!R64-'Model inputs'!R155*'Model inputs'!AA180/12*(1-'Model inputs'!AA171) -> 4000 | S50: ='Model inputs'!S153*'Model inputs'!AA180*(1-'Model inputs'!AA171)+'Model inputs'!S64-'Model inputs'!S155*'Model inputs'!AA180/12*(1-'Model inputs'!AA171) -> 4000 | T50: ='Model inputs'!T153*'Model inputs'!AA180*(1-'Model inputs'!AA171)+'Model inputs'!T64-'Model inputs'!T155*'Model inputs'!AA180/12*(1-'Model inputs'!AA171) -> 4000 | U50: ='Model inputs'!U153*'Model inputs'!AA180*(1-'Model inputs'!AA171)+'Model inputs'!U64-'Model inputs'!U155*'Model inputs'!AA180/12*(1-'Model inputs'!AA171) -> 4000 | V50: ='Model inputs'!V153*'Model inputs'!AA180*(1-'Model inputs'!AA171)+'Model inputs'!V64-'Model inputs'!V155*'Model inputs'!AA180/12*(1-'Model inputs'!AA171) -> 4000 | W50: ='Model inputs'!W153*'Model inputs'!AA180*(1-'Model inputs'!AA171)+'Model inputs'!W64-'Model inputs'!W155*'Model inputs'!AA180/12*(1-'Model inputs'!AA171) -> 4000 | X50: ='Model inputs'!X153*'Model inputs'!AA180*(1-'Model inputs'!AA171)+'Model inputs'!X64-'Model inputs'!X155*'Model inputs'!AA180/12*(1-'Model inputs'!AA171) -> 4000 | Y50: ='Model inputs'!Y153*'Model inputs'!AA180*(1-'Model inputs'!AA171)+'Model inputs'!Y64-'Model inputs'!Y155*'Model inputs'!AA180/12*(1-'Model inputs'!AA171) -> 4000 | Z50: ='Model inputs'!Z153*'Model inputs'!AA180*(1-'Model inputs'!AA171)+'Model inputs'!Z64-'Model inputs'!Z155*'Model inputs'!AA180/12*(1-'Model inputs'!AA171) -> 4000
A51: Cash collections > Per audit — base | C51: =0 -> 0 | D51: =0 -> 0 | E51: =0 -> 0 | F51: =0 -> 0 | G51: =0 -> 0 | H51: =0 -> 0 | I51: =0 -> 0 | J51: =0 -> 0 | K51: =0 -> 0 | L51: ='Model inputs'!L153*'Model inputs'!AA181*(1-'Model inputs'!AA171)+'Model inputs'!L65-'Model inputs'!L155*'Model inputs'!AA181/12*(1-'Model inputs'!AA171) -> 0 | M51: ='Model inputs'!M153*'Model inputs'!AA181*(1-'Model inputs'!AA171)+'Model inputs'!M65-'Model inputs'!M155*'Model inputs'!AA181/12*(1-'Model inputs'!AA171) -> 0 | N51: ='Model inputs'!N153*'Model inputs'!AA181*(1-'Model inputs'!AA171)+'Model inputs'!N65-'Model inputs'!N155*'Model inputs'!AA181/12*(1-'Model inputs'!AA171) -> 6000 | O51: ='Model inputs'!O153*'Model inputs'!AA181*(1-'Model inputs'!AA171)+'Model inputs'!O65-'Model inputs'!O155*'Model inputs'!AA181/12*(1-'Model inputs'!AA171) -> 6000 | P51: ='Model inputs'!P153*'Model inputs'!AA181*(1-'Model inputs'!AA171)+'Model inputs'!P65-'Model inputs'!P155*'Model inputs'!AA181/12*(1-'Model inputs'!AA171) -> 6000 | Q51: ='Model inputs'!Q153*'Model inputs'!AA181*(1-'Model inputs'!AA171)+'Model inputs'!Q65-'Model inputs'!Q155*'Model inputs'!AA181/12*(1-'Model inputs'!AA171) -> 6000 | R51: ='Model inputs'!R153*'Model inputs'!AA181*(1-'Model inputs'!AA171)+'Model inputs'!R65-'Model inputs'!R155*'Model inputs'!AA181/12*(1-'Model inputs'!AA171) -> 6000 | S51: ='Model inputs'!S153*'Model inputs'!AA181*(1-'Model inputs'!AA171)+'Model inputs'!S65-'Model inputs'!S155*'Model inputs'!AA181/12*(1-'Model inputs'!AA171) -> 6000 | T51: ='Model inputs'!T153*'Model inputs'!AA181*(1-'Model inputs'!AA171)+'Model inputs'!T65-'Model inputs'!T155*'Model inputs'!AA181/12*(1-'Model inputs'!AA171) -> 6000 | U51: ='Model inputs'!U153*'Model inputs'!AA181*(1-'Model inputs'!AA171)+'Model inputs'!U65-'Model inputs'!U155*'Model inputs'!AA181/12*(1-'Model inputs'!AA171) -> 6000 | V51: ='Model inputs'!V153*'Model inputs'!AA181*(1-'Model inputs'!AA171)+'Model inputs'!V65-'Model inputs'!V155*'Model inputs'!AA181/12*(1-'Model inputs'!AA171) -> 6000 | W51: ='Model inputs'!W153*'Model inputs'!AA181*(1-'Model inputs'!AA171)+'Model inputs'!W65-'Model inputs'!W155*'Model inputs'!AA181/12*(1-'Model inputs'!AA171) -> 6000 | X51: ='Model inputs'!X153*'Model inputs'!AA181*(1-'Model inputs'!AA171)+'Model inputs'!X65-'Model inputs'!X155*'Model inputs'!AA181/12*(1-'Model inputs'!AA171) -> 6000 | Y51: ='Model inputs'!Y153*'Model inputs'!AA181*(1-'Model inputs'!AA171)+'Model inputs'!Y65-'Model inputs'!Y155*'Model inputs'!AA181/12*(1-'Model inputs'!AA171) -> 6000 | Z51: ='Model inputs'!Z153*'Model inputs'!AA181*(1-'Model inputs'!AA171)+'Model inputs'!Z65-'Model inputs'!Z155*'Model inputs'!AA181/12*(1-'Model inputs'!AA171) -> 6000
A52: Cash collections > Per audit — high | C52: =0 -> 0 | D52: =0 -> 0 | E52: =0 -> 0 | F52: =0 -> 0 | G52: =0 -> 0 | H52: =0 -> 0 | I52: =0 -> 0 | J52: =0 -> 0 | K52: =0 -> 0 | L52: ='Model inputs'!L153*'Model inputs'!AA182*(1-'Model inputs'!AA171)+'Model inputs'!L66-'Model inputs'!L155*'Model inputs'!AA182/12*(1-'Model inputs'!AA171) -> 0 | M52: ='Model inputs'!M153*'Model inputs'!AA182*(1-'Model inputs'!AA171)+'Model inputs'!M66-'Model inputs'!M155*'Model inputs'!AA182/12*(1-'Model inputs'!AA171) -> 0 | N52: ='Model inputs'!N153*'Model inputs'!AA182*(1-'Model inputs'!AA171)+'Model inputs'!N66-'Model inputs'!N155*'Model inputs'!AA182/12*(1-'Model inputs'!AA171) -> 12000 | O52: ='Model inputs'!O153*'Model inputs'!AA182*(1-'Model inputs'!AA171)+'Model inputs'!O66-'Model inputs'!O155*'Model inputs'!AA182/12*(1-'Model inputs'!AA171) -> 12000 | P52: ='Model inputs'!P153*'Model inputs'!AA182*(1-'Model inputs'!AA171)+'Model inputs'!P66-'Model inputs'!P155*'Model inputs'!AA182/12*(1-'Model inputs'!AA171) -> 12000 | Q52: ='Model inputs'!Q153*'Model inputs'!AA182*(1-'Model inputs'!AA171)+'Model inputs'!Q66-'Model inputs'!Q155*'Model inputs'!AA182/12*(1-'Model inputs'!AA171) -> 12000 | R52: ='Model inputs'!R153*'Model inputs'!AA182*(1-'Model inputs'!AA171)+'Model inputs'!R66-'Model inputs'!R155*'Model inputs'!AA182/12*(1-'Model inputs'!AA171) -> 12000 | S52: ='Model inputs'!S153*'Model inputs'!AA182*(1-'Model inputs'!AA171)+'Model inputs'!S66-'Model inputs'!S155*'Model inputs'!AA182/12*(1-'Model inputs'!AA171) -> 12000 | T52: ='Model inputs'!T153*'Model inputs'!AA182*(1-'Model inputs'!AA171)+'Model inputs'!T66-'Model inputs'!T155*'Model inputs'!AA182/12*(1-'Model inputs'!AA171) -> 12000 | U52: ='Model inputs'!U153*'Model inputs'!AA182*(1-'Model inputs'!AA171)+'Model inputs'!U66-'Model inputs'!U155*'Model inputs'!AA182/12*(1-'Model inputs'!AA171) -> 12000 | V52: ='Model inputs'!V153*'Model inputs'!AA182*(1-'Model inputs'!AA171)+'Model inputs'!V66-'Model inputs'!V155*'Model inputs'!AA182/12*(1-'Model inputs'!AA171) -> 12000 | W52: ='Model inputs'!W153*'Model inputs'!AA182*(1-'Model inputs'!AA171)+'Model inputs'!W66-'Model inputs'!W155*'Model inputs'!AA182/12*(1-'Model inputs'!AA171) -> 12000 | X52: ='Model inputs'!X153*'Model inputs'!AA182*(1-'Model inputs'!AA171)+'Model inputs'!X66-'Model inputs'!X155*'Model inputs'!AA182/12*(1-'Model inputs'!AA171) -> 12000 | Y52: ='Model inputs'!Y153*'Model inputs'!AA182*(1-'Model inputs'!AA171)+'Model inputs'!Y66-'Model inputs'!Y155*'Model inputs'!AA182/12*(1-'Model inputs'!AA171) -> 12000 | Z52: ='Model inputs'!Z153*'Model inputs'!AA182*(1-'Model inputs'!AA171)+'Model inputs'!Z66-'Model inputs'!Z155*'Model inputs'!AA182/12*(1-'Model inputs'!AA171) -> 12000
A53: Cash collections > Per audit — low | C53: =0 -> 0 | D53: =0 -> 0 | E53: =0 -> 0 | F53: =0 -> 0 | G53: =0 -> 0 | H53: =0 -> 0 | I53: =0 -> 0 | J53: =0 -> 0 | K53: =0 -> 0 | L53: ='Model inputs'!L153*'Model inputs'!AA183*(1-'Model inputs'!AA171)+'Model inputs'!L67-'Model inputs'!L155*'Model inputs'!AA183/12*(1-'Model inputs'!AA171) -> 0 | M53: ='Model inputs'!M153*'Model inputs'!AA183*(1-'Model inputs'!AA171)+'Model inputs'!M67-'Model inputs'!M155*'Model inputs'!AA183/12*(1-'Model inputs'!AA171) -> 0 | N53: ='Model inputs'!N153*'Model inputs'!AA183*(1-'Model inputs'!AA171)+'Model inputs'!N67-'Model inputs'!N155*'Model inputs'!AA183/12*(1-'Model inputs'!AA171) -> 3000 | O53: ='Model inputs'!O153*'Model inputs'!AA183*(1-'Model inputs'!AA171)+'Model inputs'!O67-'Model inputs'!O155*'Model inputs'!AA183/12*(1-'Model inputs'!AA171) -> 3000 | P53: ='Model inputs'!P153*'Model inputs'!AA183*(1-'Model inputs'!AA171)+'Model inputs'!P67-'Model inputs'!P155*'Model inputs'!AA183/12*(1-'Model inputs'!AA171) -> 3000 | Q53: ='Model inputs'!Q153*'Model inputs'!AA183*(1-'Model inputs'!AA171)+'Model inputs'!Q67-'Model inputs'!Q155*'Model inputs'!AA183/12*(1-'Model inputs'!AA171) -> 3000 | R53: ='Model inputs'!R153*'Model inputs'!AA183*(1-'Model inputs'!AA171)+'Model inputs'!R67-'Model inputs'!R155*'Model inputs'!AA183/12*(1-'Model inputs'!AA171) -> 3000 | S53: ='Model inputs'!S153*'Model inputs'!AA183*(1-'Model inputs'!AA171)+'Model inputs'!S67-'Model inputs'!S155*'Model inputs'!AA183/12*(1-'Model inputs'!AA171) -> 3000 | T53: ='Model inputs'!T153*'Model inputs'!AA183*(1-'Model inputs'!AA171)+'Model inputs'!T67-'Model inputs'!T155*'Model inputs'!AA183/12*(1-'Model inputs'!AA171) -> 3000 | U53: ='Model inputs'!U153*'Model inputs'!AA183*(1-'Model inputs'!AA171)+'Model inputs'!U67-'Model inputs'!U155*'Model inputs'!AA183/12*(1-'Model inputs'!AA171) -> 3000 | V53: ='Model inputs'!V153*'Model inputs'!AA183*(1-'Model inputs'!AA171)+'Model inputs'!V67-'Model inputs'!V155*'Model inputs'!AA183/12*(1-'Model inputs'!AA171) -> 3000 | W53: ='Model inputs'!W153*'Model inputs'!AA183*(1-'Model inputs'!AA171)+'Model inputs'!W67-'Model inputs'!W155*'Model inputs'!AA183/12*(1-'Model inputs'!AA171) -> 3000 | X53: ='Model inputs'!X153*'Model inputs'!AA183*(1-'Model inputs'!AA171)+'Model inputs'!X67-'Model inputs'!X155*'Model inputs'!AA183/12*(1-'Model inputs'!AA171) -> 3000 | Y53: ='Model inputs'!Y153*'Model inputs'!AA183*(1-'Model inputs'!AA171)+'Model inputs'!Y67-'Model inputs'!Y155*'Model inputs'!AA183/12*(1-'Model inputs'!AA171) -> 3000 | Z53: ='Model inputs'!Z153*'Model inputs'!AA183*(1-'Model inputs'!AA171)+'Model inputs'!Z67-'Model inputs'!Z155*'Model inputs'!AA183/12*(1-'Model inputs'!AA171) -> 3000
A54: Cumulative net cash burn · Cumulative funding gap · Growth · Growth | C54: 0 | D54: 0 | E54: 0 | F54: 0 | G54: 0 | H54: 0 | I54: 0 | J54: 0 | K54: 0 | L54: =IF(IF(IF(IF(ISERROR('Model inputs'!L84=1),'Model inputs'!L84=1,IF('Model inputs'!L84="","",'Model inputs'!L84=1))="",FALSE,IF(ISERROR('Model inputs'!L84=1),'Model inputs'!L84=1,IF('Model inputs'!L84="","",'Model inputs'!L84=1))),0,IF('Model inputs'!K54="","",'Model inputs'!K54))="",0,IF(IF(IF(ISERROR('Model inputs'!L84=1),'Model inputs'!L84=1,IF('Model inputs'!L84="","",'Model inputs'!L84=1))="",FALSE,IF(ISERROR('Model inputs'!L84=1),'Model inputs'!L84=1,IF('Model inputs'!L84="","",'Model inputs'!L84=1))),0,IF('Model inputs'!K54="","",'Model inputs'!K54)))+'Model inputs'!L28 -> -30264.25 | M54: =IF(IF(IF(IF(ISERROR('Model inputs'!M84=1),'Model inputs'!M84=1,IF('Model inputs'!M84="","",'Model inputs'!M84=1))="",FALSE,IF(ISERROR('Model inputs'!M84=1),'Model inputs'!M84=1,IF('Model inputs'!M84="","",'Model inputs'!M84=1))),0,IF('Model inputs'!L54="","",'Model inputs'!L54))="",0,IF(IF(IF(ISERROR('Model inputs'!M84=1),'Model inputs'!M84=1,IF('Model inputs'!M84="","",'Model inputs'!M84=1))="",FALSE,IF(ISERROR('Model inputs'!M84=1),'Model inputs'!M84=1,IF('Model inputs'!M84="","",'Model inputs'!M84=1))),0,IF('Model inputs'!L54="","",'Model inputs'!L54)))+'Model inputs'!M28 -> -62442.75 | N54: =IF(IF(IF(IF(ISERROR('Model inputs'!N84=1),'Model inputs'!N84=1,IF('Model inputs'!N84="","",'Model inputs'!N84=1))="",FALSE,IF(ISERROR('Model inputs'!N84=1),'Model inputs'!N84=1,IF('Model inputs'!N84="","",'Model inputs'!N84=1))),0,IF('Model inputs'!M54="","",'Model inputs'!M54))="",0,IF(IF(IF(ISERROR('Model inputs'!N84=1),'Model inputs'!N84=1,IF('Model inputs'!N84="","",'Model inputs'!N84=1))="",FALSE,IF(ISERROR('Model inputs'!N84=1),'Model inputs'!N84=1,IF('Model inputs'!N84="","",'Model inputs'!N84=1))),0,IF('Model inputs'!M54="","",'Model inputs'!M54)))+'Model inputs'!N28 -> -96535.5 | O54: =IF(IF(IF(IF(ISERROR('Model inputs'!O84=1),'Model inputs'!O84=1,IF('Model inputs'!O84="","",'Model inputs'!O84=1))="",FALSE,IF(ISERROR('Model inputs'!O84=1),'Model inputs'!O84=1,IF('Model inputs'!O84="","",'Model inputs'!O84=1))),0,IF('Model inputs'!N54="","",'Model inputs'!N54))="",0,IF(IF(IF(ISERROR('Model inputs'!O84=1),'Model inputs'!O84=1,IF('Model inputs'!O84="","",'Model inputs'!O84=1))="",FALSE,IF(ISERROR('Model inputs'!O84=1),'Model inputs'!O84=1,IF('Model inputs'!O84="","",'Model inputs'!O84=1))),0,IF('Model inputs'!N54="","",'Model inputs'!N54)))+'Model inputs'!O28 -> -132542.5 | P54: =IF(IF(IF(IF(ISERROR('Model inputs'!P84=1),'Model inputs'!P84=1,IF('Model inputs'!P84="","",'Model inputs'!P84=1))="",FALSE,IF(ISERROR('Model inputs'!P84=1),'Model inputs'!P84=1,IF('Model inputs'!P84="","",'Model inputs'!P84=1))),0,IF('Model inputs'!O54="","",'Model inputs'!O54))="",0,IF(IF(IF(ISERROR('Model inputs'!P84=1),'Model inputs'!P84=1,IF('Model inputs'!P84="","",'Model inputs'!P84=1))="",FALSE,IF(ISERROR('Model inputs'!P84=1),'Model inputs'!P84=1,IF('Model inputs'!P84="","",'Model inputs'!P84=1))),0,IF('Model inputs'!O54="","",'Model inputs'!O54)))+'Model inputs'!P28 -> -170463.75 | Q54: =IF(IF(IF(IF(ISERROR('Model inputs'!Q84=1),'Model inputs'!Q84=1,IF('Model inputs'!Q84="","",'Model inputs'!Q84=1))="",FALSE,IF(ISERROR('Model inputs'!Q84=1),'Model inputs'!Q84=1,IF('Model inputs'!Q84="","",'Model inputs'!Q84=1))),0,IF('Model inputs'!P54="","",'Model inputs'!P54))="",0,IF(IF(IF(ISERROR('Model inputs'!Q84=1),'Model inputs'!Q84=1,IF('Model inputs'!Q84="","",'Model inputs'!Q84=1))="",FALSE,IF(ISERROR('Model inputs'!Q84=1),'Model inputs'!Q84=1,IF('Model inputs'!Q84="","",'Model inputs'!Q84=1))),0,IF('Model inputs'!P54="","",'Model inputs'!P54)))+'Model inputs'!Q28 -> -209799.25 | R54: =IF(IF(IF(IF(ISERROR('Model inputs'!R84=1),'Model inputs'!R84=1,IF('Model inputs'!R84="","",'Model inputs'!R84=1))="",FALSE,IF(ISERROR('Model inputs'!R84=1),'Model inputs'!R84=1,IF('Model inputs'!R84="","",'Model inputs'!R84=1))),0,IF('Model inputs'!Q54="","",'Model inputs'!Q54))="",0,IF(IF(IF(ISERROR('Model inputs'!R84=1),'Model inputs'!R84=1,IF('Model inputs'!R84="","",'Model inputs'!R84=1))="",FALSE,IF(ISERROR('Model inputs'!R84=1),'Model inputs'!R84=1,IF('Model inputs'!R84="","",'Model inputs'!R84=1))),0,IF('Model inputs'!Q54="","",'Model inputs'!Q54)))+'Model inputs'!R28 -> -251049 | S54: =IF(IF(IF(IF(ISERROR('Model inputs'!S84=1),'Model inputs'!S84=1,IF('Model inputs'!S84="","",'Model inputs'!S84=1))="",FALSE,IF(ISERROR('Model inputs'!S84=1),'Model inputs'!S84=1,IF('Model inputs'!S84="","",'Model inputs'!S84=1))),0,IF('Model inputs'!R54="","",'Model inputs'!R54))="",0,IF(IF(IF(ISERROR('Model inputs'!S84=1),'Model inputs'!S84=1,IF('Model inputs'!S84="","",'Model inputs'!S84=1))="",FALSE,IF(ISERROR('Model inputs'!S84=1),'Model inputs'!S84=1,IF('Model inputs'!S84="","",'Model inputs'!S84=1))),0,IF('Model inputs'!R54="","",'Model inputs'!R54)))+'Model inputs'!S28 -> -294213 | ... Z54: =IF(IF(IF(IF(ISERROR('Model inputs'!Z84=1),'Model inputs'!Z84=1,IF('Model inputs'!Z84="","",'Model inputs'!Z84=1))="",FALSE,IF(ISERROR('Model inputs'!Z84=1),'Model inputs'!Z84=1,IF('Model inputs'!Z84="","",'Model inputs'!Z84=1))),0,IF('Model inputs'!Y54="","",'Model inputs'!Y54))="",0,IF(IF(IF(ISERROR('Model inputs'!Z84=1),'Model inputs'!Z84=1,IF('Model inputs'!Z84="","",'Model inputs'!Z84=1))="",FALSE,IF(ISERROR('Model inputs'!Z84=1),'Model inputs'!Z84=1,IF('Model inputs'!Z84="","",'Model inputs'!Z84=1))),0,IF('Model inputs'!Y54="","",'Model inputs'!Y54)))+'Model inputs'!Z28 -> -551174.5
A55: Cumulative net cash burn · Cumulative funding gap · Conservative · Conservative | C55: 0 | D55: 0 | E55: 0 | F55: 0 | G55: 0 | H55: 0 | I55: 0 | J55: 0 | K55: 0 | L55: =IF(IF(IF(IF(ISERROR('Model inputs'!L85=1),'Model inputs'!L85=1,IF('Model inputs'!L85="","",'Model inputs'!L85=1))="",FALSE,IF(ISERROR('Model inputs'!L85=1),'Model inputs'!L85=1,IF('Model inputs'!L85="","",'Model inputs'!L85=1))),0,IF('Model inputs'!K55="","",'Model inputs'!K55))="",0,IF(IF(IF(ISERROR('Model inputs'!L85=1),'Model inputs'!L85=1,IF('Model inputs'!L85="","",'Model inputs'!L85=1))="",FALSE,IF(ISERROR('Model inputs'!L85=1),'Model inputs'!L85=1,IF('Model inputs'!L85="","",'Model inputs'!L85=1))),0,IF('Model inputs'!K55="","",'Model inputs'!K55)))+'Model inputs'!L29 -> 750 | M55: =IF(IF(IF(IF(ISERROR('Model inputs'!M85=1),'Model inputs'!M85=1,IF('Model inputs'!M85="","",'Model inputs'!M85=1))="",FALSE,IF(ISERROR('Model inputs'!M85=1),'Model inputs'!M85=1,IF('Model inputs'!M85="","",'Model inputs'!M85=1))),0,IF('Model inputs'!L55="","",'Model inputs'!L55))="",0,IF(IF(IF(ISERROR('Model inputs'!M85=1),'Model inputs'!M85=1,IF('Model inputs'!M85="","",'Model inputs'!M85=1))="",FALSE,IF(ISERROR('Model inputs'!M85=1),'Model inputs'!M85=1,IF('Model inputs'!M85="","",'Model inputs'!M85=1))),0,IF('Model inputs'!L55="","",'Model inputs'!L55)))+'Model inputs'!M29 -> 1500 | N55: =IF(IF(IF(IF(ISERROR('Model inputs'!N85=1),'Model inputs'!N85=1,IF('Model inputs'!N85="","",'Model inputs'!N85=1))="",FALSE,IF(ISERROR('Model inputs'!N85=1),'Model inputs'!N85=1,IF('Model inputs'!N85="","",'Model inputs'!N85=1))),0,IF('Model inputs'!M55="","",'Model inputs'!M55))="",0,IF(IF(IF(ISERROR('Model inputs'!N85=1),'Model inputs'!N85=1,IF('Model inputs'!N85="","",'Model inputs'!N85=1))="",FALSE,IF(ISERROR('Model inputs'!N85=1),'Model inputs'!N85=1,IF('Model inputs'!N85="","",'Model inputs'!N85=1))),0,IF('Model inputs'!M55="","",'Model inputs'!M55)))+'Model inputs'!N29 -> -216.1 | O55: =IF(IF(IF(IF(ISERROR('Model inputs'!O85=1),'Model inputs'!O85=1,IF('Model inputs'!O85="","",'Model inputs'!O85=1))="",FALSE,IF(ISERROR('Model inputs'!O85=1),'Model inputs'!O85=1,IF('Model inputs'!O85="","",'Model inputs'!O85=1))),0,IF('Model inputs'!N55="","",'Model inputs'!N55))="",0,IF(IF(IF(ISERROR('Model inputs'!O85=1),'Model inputs'!O85=1,IF('Model inputs'!O85="","",'Model inputs'!O85=1))="",FALSE,IF(ISERROR('Model inputs'!O85=1),'Model inputs'!O85=1,IF('Model inputs'!O85="","",'Model inputs'!O85=1))),0,IF('Model inputs'!N55="","",'Model inputs'!N55)))+'Model inputs'!O29 -> -1932.2 | P55: =IF(IF(IF(IF(ISERROR('Model inputs'!P85=1),'Model inputs'!P85=1,IF('Model inputs'!P85="","",'Model inputs'!P85=1))="",FALSE,IF(ISERROR('Model inputs'!P85=1),'Model inputs'!P85=1,IF('Model inputs'!P85="","",'Model inputs'!P85=1))),0,IF('Model inputs'!O55="","",'Model inputs'!O55))="",0,IF(IF(IF(ISERROR('Model inputs'!P85=1),'Model inputs'!P85=1,IF('Model inputs'!P85="","",'Model inputs'!P85=1))="",FALSE,IF(ISERROR('Model inputs'!P85=1),'Model inputs'!P85=1,IF('Model inputs'!P85="","",'Model inputs'!P85=1))),0,IF('Model inputs'!O55="","",'Model inputs'!O55)))+'Model inputs'!P29 -> -3648.3 | Q55: =IF(IF(IF(IF(ISERROR('Model inputs'!Q85=1),'Model inputs'!Q85=1,IF('Model inputs'!Q85="","",'Model inputs'!Q85=1))="",FALSE,IF(ISERROR('Model inputs'!Q85=1),'Model inputs'!Q85=1,IF('Model inputs'!Q85="","",'Model inputs'!Q85=1))),0,IF('Model inputs'!P55="","",'Model inputs'!P55))="",0,IF(IF(IF(ISERROR('Model inputs'!Q85=1),'Model inputs'!Q85=1,IF('Model inputs'!Q85="","",'Model inputs'!Q85=1))="",FALSE,IF(ISERROR('Model inputs'!Q85=1),'Model inputs'!Q85=1,IF('Model inputs'!Q85="","",'Model inputs'!Q85=1))),0,IF('Model inputs'!P55="","",'Model inputs'!P55)))+'Model inputs'!Q29 -> -4864.4 | R55: =IF(IF(IF(IF(ISERROR('Model inputs'!R85=1),'Model inputs'!R85=1,IF('Model inputs'!R85="","",'Model inputs'!R85=1))="",FALSE,IF(ISERROR('Model inputs'!R85=1),'Model inputs'!R85=1,IF('Model inputs'!R85="","",'Model inputs'!R85=1))),0,IF('Model inputs'!Q55="","",'Model inputs'!Q55))="",0,IF(IF(IF(ISERROR('Model inputs'!R85=1),'Model inputs'!R85=1,IF('Model inputs'!R85="","",'Model inputs'!R85=1))="",FALSE,IF(ISERROR('Model inputs'!R85=1),'Model inputs'!R85=1,IF('Model inputs'!R85="","",'Model inputs'!R85=1))),0,IF('Model inputs'!Q55="","",'Model inputs'!Q55)))+'Model inputs'!R29 -> -6080.5 | S55: =IF(IF(IF(IF(ISERROR('Model inputs'!S85=1),'Model inputs'!S85=1,IF('Model inputs'!S85="","",'Model inputs'!S85=1))="",FALSE,IF(ISERROR('Model inputs'!S85=1),'Model inputs'!S85=1,IF('Model inputs'!S85="","",'Model inputs'!S85=1))),0,IF('Model inputs'!R55="","",'Model inputs'!R55))="",0,IF(IF(IF(ISERROR('Model inputs'!S85=1),'Model inputs'!S85=1,IF('Model inputs'!S85="","",'Model inputs'!S85=1))="",FALSE,IF(ISERROR('Model inputs'!S85=1),'Model inputs'!S85=1,IF('Model inputs'!S85="","",'Model inputs'!S85=1))),0,IF('Model inputs'!R55="","",'Model inputs'!R55)))+'Model inputs'!S29 -> -7296.6 | ... Z55: =IF(IF(IF(IF(ISERROR('Model inputs'!Z85=1),'Model inputs'!Z85=1,IF('Model inputs'!Z85="","",'Model inputs'!Z85=1))="",FALSE,IF(ISERROR('Model inputs'!Z85=1),'Model inputs'!Z85=1,IF('Model inputs'!Z85="","",'Model inputs'!Z85=1))),0,IF('Model inputs'!Y55="","",'Model inputs'!Y55))="",0,IF(IF(IF(ISERROR('Model inputs'!Z85=1),'Model inputs'!Z85=1,IF('Model inputs'!Z85="","",'Model inputs'!Z85=1))="",FALSE,IF(ISERROR('Model inputs'!Z85=1),'Model inputs'!Z85=1,IF('Model inputs'!Z85="","",'Model inputs'!Z85=1))),0,IF('Model inputs'!Y55="","",'Model inputs'!Y55)))+'Model inputs'!Z29 -> -15809.3
A56: Earned revenue | C56: =SUM('Model inputs'!C57,'Model inputs'!C58,'Model inputs'!C59,'Model inputs'!C60,'Model inputs'!C61) -> 0 | D56: =SUM('Model inputs'!D57,'Model inputs'!D58,'Model inputs'!D59,'Model inputs'!D60,'Model inputs'!D61) -> 0 | E56: =SUM('Model inputs'!E57,'Model inputs'!E58,'Model inputs'!E59,'Model inputs'!E60,'Model inputs'!E61) -> 0 | F56: =SUM('Model inputs'!F57,'Model inputs'!F58,'Model inputs'!F59,'Model inputs'!F60,'Model inputs'!F61) -> 0 | G56: =SUM('Model inputs'!G57,'Model inputs'!G58,'Model inputs'!G59,'Model inputs'!G60,'Model inputs'!G61) -> 0 | H56: =SUM('Model inputs'!H57,'Model inputs'!H58,'Model inputs'!H59,'Model inputs'!H60,'Model inputs'!H61) -> 0 | I56: =SUM('Model inputs'!I57,'Model inputs'!I58,'Model inputs'!I59,'Model inputs'!I60,'Model inputs'!I61) -> 0 | J56: =SUM('Model inputs'!J57,'Model inputs'!J58,'Model inputs'!J59,'Model inputs'!J60,'Model inputs'!J61) -> 0 | K56: =SUM('Model inputs'!K57,'Model inputs'!K58,'Model inputs'!K59,'Model inputs'!K60,'Model inputs'!K61) -> 0 | L56: ="" | M56: ="" | N56: ="" | O56: ="" | P56: ="" | Q56: ="" | R56: ="" | S56: ="" | ... Z56: =""
A57: Earned revenue > Annual deal-team | C57: =0 -> 0 | D57: =0 -> 0 | E57: =0 -> 0 | F57: =0 -> 0 | G57: =0 -> 0 | H57: =0 -> 0 | I57: =0 -> 0 | J57: =0 -> 0 | K57: =0 -> 0 | L57: ='Model inputs'!L154*'Model inputs'!AA125 -> 5000 | M57: ='Model inputs'!M154*'Model inputs'!AA125 -> 10000 | N57: ='Model inputs'!N154*'Model inputs'!AA125 -> 15000 | O57: ='Model inputs'!O154*'Model inputs'!AA125 -> 20000 | P57: ='Model inputs'!P154*'Model inputs'!AA125 -> 25000 | Q57: ='Model inputs'!Q154*'Model inputs'!AA125 -> 30000 | R57: ='Model inputs'!R154*'Model inputs'!AA125 -> 35000 | S57: ='Model inputs'!S154*'Model inputs'!AA125 -> 40000 | T57: ='Model inputs'!T154*'Model inputs'!AA125 -> 45000 | U57: ='Model inputs'!U154*'Model inputs'!AA125 -> 50000 | V57: ='Model inputs'!V154*'Model inputs'!AA125 -> 55000 | W57: ='Model inputs'!W154*'Model inputs'!AA125 -> 60000 | X57: ='Model inputs'!X154*'Model inputs'!AA125 -> 60000 | Y57: ='Model inputs'!Y154*'Model inputs'!AA125 -> 60000 | Z57: ='Model inputs'!Z154*'Model inputs'!AA125 -> 60000
A58: Earned revenue > Hybrid | C58: =0 -> 0 | D58: =0 -> 0 | E58: =0 -> 0 | F58: =0 -> 0 | G58: =0 -> 0 | H58: =0 -> 0 | I58: =0 -> 0 | J58: =0 -> 0 | K58: =0 -> 0 | L58: ='Model inputs'!L154*'Model inputs'!AA126 -> 5625 | M58: ='Model inputs'!M154*'Model inputs'!AA126 -> 11250 | N58: ='Model inputs'!N154*'Model inputs'!AA126 -> 16875 | O58: ='Model inputs'!O154*'Model inputs'!AA126 -> 22500 | P58: ='Model inputs'!P154*'Model inputs'!AA126 -> 28125 | Q58: ='Model inputs'!Q154*'Model inputs'!AA126 -> 33750 | R58: ='Model inputs'!R154*'Model inputs'!AA126 -> 39375 | S58: ='Model inputs'!S154*'Model inputs'!AA126 -> 45000 | T58: ='Model inputs'!T154*'Model inputs'!AA126 -> 50625 | U58: ='Model inputs'!U154*'Model inputs'!AA126 -> 56250 | V58: ='Model inputs'!V154*'Model inputs'!AA126 -> 61875 | W58: ='Model inputs'!W154*'Model inputs'!AA126 -> 67500 | X58: ='Model inputs'!X154*'Model inputs'!AA126 -> 67500 | Y58: ='Model inputs'!Y154*'Model inputs'!AA126 -> 67500 | Z58: ='Model inputs'!Z154*'Model inputs'!AA126 -> 67500
A59: Earned revenue > Per audit — base | C59: =0 -> 0 | D59: =0 -> 0 | E59: =0 -> 0 | F59: =0 -> 0 | G59: =0 -> 0 | H59: =0 -> 0 | I59: =0 -> 0 | J59: =0 -> 0 | K59: =0 -> 0 | L59: ='Model inputs'!L154*'Model inputs'!AA127 -> 7500 | M59: ='Model inputs'!M154*'Model inputs'!AA127 -> 15000 | N59: ='Model inputs'!N154*'Model inputs'!AA127 -> 22500 | O59: ='Model inputs'!O154*'Model inputs'!AA127 -> 30000 | P59: ='Model inputs'!P154*'Model inputs'!AA127 -> 37500 | Q59: ='Model inputs'!Q154*'Model inputs'!AA127 -> 45000 | R59: ='Model inputs'!R154*'Model inputs'!AA127 -> 52500 | S59: ='Model inputs'!S154*'Model inputs'!AA127 -> 60000 | T59: ='Model inputs'!T154*'Model inputs'!AA127 -> 67500 | U59: ='Model inputs'!U154*'Model inputs'!AA127 -> 75000 | V59: ='Model inputs'!V154*'Model inputs'!AA127 -> 82500 | W59: ='Model inputs'!W154*'Model inputs'!AA127 -> 90000 | X59: ='Model inputs'!X154*'Model inputs'!AA127 -> 90000 | Y59: ='Model inputs'!Y154*'Model inputs'!AA127 -> 90000 | Z59: ='Model inputs'!Z154*'Model inputs'!AA127 -> 90000
A60: Earned revenue > Per audit — high | C60: =0 -> 0 | D60: =0 -> 0 | E60: =0 -> 0 | F60: =0 -> 0 | G60: =0 -> 0 | H60: =0 -> 0 | I60: =0 -> 0 | J60: =0 -> 0 | K60: =0 -> 0 | L60: ='Model inputs'!L154*'Model inputs'!AA128 -> 15000 | M60: ='Model inputs'!M154*'Model inputs'!AA128 -> 30000 | N60: ='Model inputs'!N154*'Model inputs'!AA128 -> 45000 | O60: ='Model inputs'!O154*'Model inputs'!AA128 -> 60000 | P60: ='Model inputs'!P154*'Model inputs'!AA128 -> 75000 | Q60: ='Model inputs'!Q154*'Model inputs'!AA128 -> 90000 | R60: ='Model inputs'!R154*'Model inputs'!AA128 -> 105000 | S60: ='Model inputs'!S154*'Model inputs'!AA128 -> 120000 | T60: ='Model inputs'!T154*'Model inputs'!AA128 -> 135000 | U60: ='Model inputs'!U154*'Model inputs'!AA128 -> 150000 | V60: ='Model inputs'!V154*'Model inputs'!AA128 -> 165000 | W60: ='Model inputs'!W154*'Model inputs'!AA128 -> 180000 | X60: ='Model inputs'!X154*'Model inputs'!AA128 -> 180000 | Y60: ='Model inputs'!Y154*'Model inputs'!AA128 -> 180000 | Z60: ='Model inputs'!Z154*'Model inputs'!AA128 -> 180000
A61: Earned revenue > Per audit — low | C61: =0 -> 0 | D61: =0 -> 0 | E61: =0 -> 0 | F61: =0 -> 0 | G61: =0 -> 0 | H61: =0 -> 0 | I61: =0 -> 0 | J61: =0 -> 0 | K61: =0 -> 0 | L61: ='Model inputs'!L154*'Model inputs'!AA129 -> 3750 | M61: ='Model inputs'!M154*'Model inputs'!AA129 -> 7500 | N61: ='Model inputs'!N154*'Model inputs'!AA129 -> 11250 | O61: ='Model inputs'!O154*'Model inputs'!AA129 -> 15000 | P61: ='Model inputs'!P154*'Model inputs'!AA129 -> 18750 | Q61: ='Model inputs'!Q154*'Model inputs'!AA129 -> 22500 | R61: ='Model inputs'!R154*'Model inputs'!AA129 -> 26250 | S61: ='Model inputs'!S154*'Model inputs'!AA129 -> 30000 | T61: ='Model inputs'!T154*'Model inputs'!AA129 -> 33750 | U61: ='Model inputs'!U154*'Model inputs'!AA129 -> 37500 | V61: ='Model inputs'!V154*'Model inputs'!AA129 -> 41250 | W61: ='Model inputs'!W154*'Model inputs'!AA129 -> 45000 | X61: ='Model inputs'!X154*'Model inputs'!AA129 -> 45000 | Y61: ='Model inputs'!Y154*'Model inputs'!AA129 -> 45000 | Z61: ='Model inputs'!Z154*'Model inputs'!AA129 -> 45000
A62: Earned revenue | C62: =SUM('Model inputs'!C63,'Model inputs'!C64,'Model inputs'!C65,'Model inputs'!C66,'Model inputs'!C67) -> 0 | D62: =SUM('Model inputs'!D63,'Model inputs'!D64,'Model inputs'!D65,'Model inputs'!D66,'Model inputs'!D67) -> 0 | E62: =SUM('Model inputs'!E63,'Model inputs'!E64,'Model inputs'!E65,'Model inputs'!E66,'Model inputs'!E67) -> 0 | F62: =SUM('Model inputs'!F63,'Model inputs'!F64,'Model inputs'!F65,'Model inputs'!F66,'Model inputs'!F67) -> 0 | G62: =SUM('Model inputs'!G63,'Model inputs'!G64,'Model inputs'!G65,'Model inputs'!G66,'Model inputs'!G67) -> 0 | H62: =SUM('Model inputs'!H63,'Model inputs'!H64,'Model inputs'!H65,'Model inputs'!H66,'Model inputs'!H67) -> 0 | I62: =SUM('Model inputs'!I63,'Model inputs'!I64,'Model inputs'!I65,'Model inputs'!I66,'Model inputs'!I67) -> 0 | J62: =SUM('Model inputs'!J63,'Model inputs'!J64,'Model inputs'!J65,'Model inputs'!J66,'Model inputs'!J67) -> 0 | K62: =SUM('Model inputs'!K63,'Model inputs'!K64,'Model inputs'!K65,'Model inputs'!K66,'Model inputs'!K67) -> 0 | L62: ="" | M62: ="" | N62: ="" | O62: ="" | P62: ="" | Q62: ="" | R62: ="" | S62: ="" | ... Z62: =""
A63: Earned revenue > Annual deal-team | C63: =0 -> 0 | D63: =0 -> 0 | E63: =0 -> 0 | F63: =0 -> 0 | G63: =0 -> 0 | H63: =0 -> 0 | I63: =0 -> 0 | J63: =0 -> 0 | K63: =0 -> 0 | L63: ='Model inputs'!L155*'Model inputs'!AA131 -> 0 | M63: ='Model inputs'!M155*'Model inputs'!AA131 -> 0 | N63: ='Model inputs'!N155*'Model inputs'!AA131 -> 4000 | O63: ='Model inputs'!O155*'Model inputs'!AA131 -> 4000 | P63: ='Model inputs'!P155*'Model inputs'!AA131 -> 4000 | Q63: ='Model inputs'!Q155*'Model inputs'!AA131 -> 4000 | R63: ='Model inputs'!R155*'Model inputs'!AA131 -> 4000 | S63: ='Model inputs'!S155*'Model inputs'!AA131 -> 4000 | T63: ='Model inputs'!T155*'Model inputs'!AA131 -> 4000 | U63: ='Model inputs'!U155*'Model inputs'!AA131 -> 4000 | V63: ='Model inputs'!V155*'Model inputs'!AA131 -> 4000 | W63: ='Model inputs'!W155*'Model inputs'!AA131 -> 4000 | X63: ='Model inputs'!X155*'Model inputs'!AA131 -> 4000 | Y63: ='Model inputs'!Y155*'Model inputs'!AA131 -> 4000 | Z63: ='Model inputs'!Z155*'Model inputs'!AA131 -> 4000
A64: Earned revenue > Hybrid | C64: =0 -> 0 | D64: =0 -> 0 | E64: =0 -> 0 | F64: =0 -> 0 | G64: =0 -> 0 | H64: =0 -> 0 | I64: =0 -> 0 | J64: =0 -> 0 | K64: =0 -> 0 | L64: ='Model inputs'!L155*'Model inputs'!AA132 -> 0 | M64: ='Model inputs'!M155*'Model inputs'!AA132 -> 0 | N64: ='Model inputs'!N155*'Model inputs'!AA132 -> 5000 | O64: ='Model inputs'!O155*'Model inputs'!AA132 -> 5000 | P64: ='Model inputs'!P155*'Model inputs'!AA132 -> 5000 | Q64: ='Model inputs'!Q155*'Model inputs'!AA132 -> 5000 | R64: ='Model inputs'!R155*'Model inputs'!AA132 -> 5000 | S64: ='Model inputs'!S155*'Model inputs'!AA132 -> 5000 | T64: ='Model inputs'!T155*'Model inputs'!AA132 -> 5000 | U64: ='Model inputs'!U155*'Model inputs'!AA132 -> 5000 | V64: ='Model inputs'!V155*'Model inputs'!AA132 -> 5000 | W64: ='Model inputs'!W155*'Model inputs'!AA132 -> 5000 | X64: ='Model inputs'!X155*'Model inputs'!AA132 -> 5000 | Y64: ='Model inputs'!Y155*'Model inputs'!AA132 -> 5000 | Z64: ='Model inputs'!Z155*'Model inputs'!AA132 -> 5000
A65: Earned revenue > Per audit — base | C65: =0 -> 0 | D65: =0 -> 0 | E65: =0 -> 0 | F65: =0 -> 0 | G65: =0 -> 0 | H65: =0 -> 0 | I65: =0 -> 0 | J65: =0 -> 0 | K65: =0 -> 0 | L65: ='Model inputs'!L155*'Model inputs'!AA133 -> 0 | M65: ='Model inputs'!M155*'Model inputs'!AA133 -> 0 | N65: ='Model inputs'!N155*'Model inputs'!AA133 -> 6000 | O65: ='Model inputs'!O155*'Model inputs'!AA133 -> 6000 | P65: ='Model inputs'!P155*'Model inputs'!AA133 -> 6000 | Q65: ='Model inputs'!Q155*'Model inputs'!AA133 -> 6000 | R65: ='Model inputs'!R155*'Model inputs'!AA133 -> 6000 | S65: ='Model inputs'!S155*'Model inputs'!AA133 -> 6000 | T65: ='Model inputs'!T155*'Model inputs'!AA133 -> 6000 | U65: ='Model inputs'!U155*'Model inputs'!AA133 -> 6000 | V65: ='Model inputs'!V155*'Model inputs'!AA133 -> 6000 | W65: ='Model inputs'!W155*'Model inputs'!AA133 -> 6000 | X65: ='Model inputs'!X155*'Model inputs'!AA133 -> 6000 | Y65: ='Model inputs'!Y155*'Model inputs'!AA133 -> 6000 | Z65: ='Model inputs'!Z155*'Model inputs'!AA133 -> 6000
A66: Earned revenue > Per audit — high | C66: =0 -> 0 | D66: =0 -> 0 | E66: =0 -> 0 | F66: =0 -> 0 | G66: =0 -> 0 | H66: =0 -> 0 | I66: =0 -> 0 | J66: =0 -> 0 | K66: =0 -> 0 | L66: ='Model inputs'!L155*'Model inputs'!AA134 -> 0 | M66: ='Model inputs'!M155*'Model inputs'!AA134 -> 0 | N66: ='Model inputs'!N155*'Model inputs'!AA134 -> 12000 | O66: ='Model inputs'!O155*'Model inputs'!AA134 -> 12000 | P66: ='Model inputs'!P155*'Model inputs'!AA134 -> 12000 | Q66: ='Model inputs'!Q155*'Model inputs'!AA134 -> 12000 | R66: ='Model inputs'!R155*'Model inputs'!AA134 -> 12000 | S66: ='Model inputs'!S155*'Model inputs'!AA134 -> 12000 | T66: ='Model inputs'!T155*'Model inputs'!AA134 -> 12000 | U66: ='Model inputs'!U155*'Model inputs'!AA134 -> 12000 | V66: ='Model inputs'!V155*'Model inputs'!AA134 -> 12000 | W66: ='Model inputs'!W155*'Model inputs'!AA134 -> 12000 | X66: ='Model inputs'!X155*'Model inputs'!AA134 -> 12000 | Y66: ='Model inputs'!Y155*'Model inputs'!AA134 -> 12000 | Z66: ='Model inputs'!Z155*'Model inputs'!AA134 -> 12000
A67: Earned revenue > Per audit — low | C67: =0 -> 0 | D67: =0 -> 0 | E67: =0 -> 0 | F67: =0 -> 0 | G67: =0 -> 0 | H67: =0 -> 0 | I67: =0 -> 0 | J67: =0 -> 0 | K67: =0 -> 0 | L67: ='Model inputs'!L155*'Model inputs'!AA135 -> 0 | M67: ='Model inputs'!M155*'Model inputs'!AA135 -> 0 | N67: ='Model inputs'!N155*'Model inputs'!AA135 -> 3000 | O67: ='Model inputs'!O155*'Model inputs'!AA135 -> 3000 | P67: ='Model inputs'!P155*'Model inputs'!AA135 -> 3000 | Q67: ='Model inputs'!Q155*'Model inputs'!AA135 -> 3000 | R67: ='Model inputs'!R155*'Model inputs'!AA135 -> 3000 | S67: ='Model inputs'!S155*'Model inputs'!AA135 -> 3000 | T67: ='Model inputs'!T155*'Model inputs'!AA135 -> 3000 | U67: ='Model inputs'!U155*'Model inputs'!AA135 -> 3000 | V67: ='Model inputs'!V155*'Model inputs'!AA135 -> 3000 | W67: ='Model inputs'!W155*'Model inputs'!AA135 -> 3000 | X67: ='Model inputs'!X155*'Model inputs'!AA135 -> 3000 | Y67: ='Model inputs'!Y155*'Model inputs'!AA135 -> 3000 | Z67: ='Model inputs'!Z155*'Model inputs'!AA135 -> 3000
A68: Forecast delivery cost · Growth | B68: =SUM('Model inputs'!B925,'Model inputs'!B926) -> 36913.5
A69: Forecast delivery cost · Conservative | B69: =SUM('Model inputs'!B927,'Model inputs'!B928) -> 3839
A70: Net cash burn | C70: =SUM('Model inputs'!C71,'Model inputs'!C72,'Model inputs'!C73,'Model inputs'!C74,'Model inputs'!C75) -> 0 | D70: =SUM('Model inputs'!D71,'Model inputs'!D72,'Model inputs'!D73,'Model inputs'!D74,'Model inputs'!D75) -> 0 | E70: =SUM('Model inputs'!E71,'Model inputs'!E72,'Model inputs'!E73,'Model inputs'!E74,'Model inputs'!E75) -> 0 | F70: =SUM('Model inputs'!F71,'Model inputs'!F72,'Model inputs'!F73,'Model inputs'!F74,'Model inputs'!F75) -> 0 | G70: =SUM('Model inputs'!G71,'Model inputs'!G72,'Model inputs'!G73,'Model inputs'!G74,'Model inputs'!G75) -> 0 | H70: =SUM('Model inputs'!H71,'Model inputs'!H72,'Model inputs'!H73,'Model inputs'!H74,'Model inputs'!H75) -> 0 | I70: =SUM('Model inputs'!I71,'Model inputs'!I72,'Model inputs'!I73,'Model inputs'!I74,'Model inputs'!I75) -> 0 | J70: =SUM('Model inputs'!J71,'Model inputs'!J72,'Model inputs'!J73,'Model inputs'!J74,'Model inputs'!J75) -> 0 | K70: =SUM('Model inputs'!K71,'Model inputs'!K72,'Model inputs'!K73,'Model inputs'!K74,'Model inputs'!K75) -> 0 | L70: ="" | M70: ="" | N70: ="" | O70: ="" | P70: ="" | Q70: ="" | R70: ="" | S70: ="" | ... Z70: =""
A71: Net cash burn > Annual deal-team | C71: =0 -> 0 | D71: =0 -> 0 | E71: =0 -> 0 | F71: =0 -> 0 | G71: =0 -> 0 | H71: =0 -> 0 | I71: =0 -> 0 | J71: =0 -> 0 | K71: =0 -> 0 | L71: ='Model inputs'!L137+'Model inputs'!L157+'Model inputs'!L89+'Model inputs'!L148-'Model inputs'!L43 -> -30264.25 | M71: ='Model inputs'!M137+'Model inputs'!M157+'Model inputs'!M89+'Model inputs'!M148-'Model inputs'!M43 -> -32178.5 | N71: ='Model inputs'!N137+'Model inputs'!N157+'Model inputs'!N89+'Model inputs'!N148-'Model inputs'!N43 -> -34092.75 | O71: ='Model inputs'!O137+'Model inputs'!O157+'Model inputs'!O89+'Model inputs'!O148-'Model inputs'!O43 -> -36007 | P71: ='Model inputs'!P137+'Model inputs'!P157+'Model inputs'!P89+'Model inputs'!P148-'Model inputs'!P43 -> -37921.25 | Q71: ='Model inputs'!Q137+'Model inputs'!Q157+'Model inputs'!Q89+'Model inputs'!Q148-'Model inputs'!Q43 -> -39335.5 | R71: ='Model inputs'!R137+'Model inputs'!R157+'Model inputs'!R89+'Model inputs'!R148-'Model inputs'!R43 -> -41249.75 | S71: ='Model inputs'!S137+'Model inputs'!S157+'Model inputs'!S89+'Model inputs'!S148-'Model inputs'!S43 -> -43164 | ... Z71: ='Model inputs'!Z137+'Model inputs'!Z157+'Model inputs'!Z89+'Model inputs'!Z148-'Model inputs'!Z43 -> -21721
A72: Net cash burn > Hybrid | C72: =0 -> 0 | D72: =0 -> 0 | E72: =0 -> 0 | F72: =0 -> 0 | G72: =0 -> 0 | H72: =0 -> 0 | I72: =0 -> 0 | J72: =0 -> 0 | K72: =0 -> 0 | L72: ='Model inputs'!L138+'Model inputs'!L158+'Model inputs'!L90+'Model inputs'!L148-'Model inputs'!L44 -> -10864.25 | M72: ='Model inputs'!M138+'Model inputs'!M158+'Model inputs'!M90+'Model inputs'!M148-'Model inputs'!M44 -> -15203.5 | N72: ='Model inputs'!N138+'Model inputs'!N158+'Model inputs'!N90+'Model inputs'!N148-'Model inputs'!N44 -> -19542.75 | O72: ='Model inputs'!O138+'Model inputs'!O158+'Model inputs'!O90+'Model inputs'!O148-'Model inputs'!O44 -> -23882 | P72: ='Model inputs'!P138+'Model inputs'!P158+'Model inputs'!P90+'Model inputs'!P148-'Model inputs'!P44 -> -28221.25 | Q72: ='Model inputs'!Q138+'Model inputs'!Q158+'Model inputs'!Q90+'Model inputs'!Q148-'Model inputs'!Q44 -> -32060.5 | R72: ='Model inputs'!R138+'Model inputs'!R158+'Model inputs'!R90+'Model inputs'!R148-'Model inputs'!R44 -> -36399.75 | S72: ='Model inputs'!S138+'Model inputs'!S158+'Model inputs'!S90+'Model inputs'!S148-'Model inputs'!S44 -> -40739 | ... Z72: ='Model inputs'!Z138+'Model inputs'!Z158+'Model inputs'!Z90+'Model inputs'!Z148-'Model inputs'!Z44 -> -50821
A73: Net cash burn > Per audit — base | C73: =0 -> 0 | D73: =0 -> 0 | E73: =0 -> 0 | F73: =0 -> 0 | G73: =0 -> 0 | H73: =0 -> 0 | I73: =0 -> 0 | J73: =0 -> 0 | K73: =0 -> 0 | L73: ='Model inputs'!L139+'Model inputs'!L159+'Model inputs'!L91+'Model inputs'!L148-'Model inputs'!L45 -> -6014.25 | M73: ='Model inputs'!M139+'Model inputs'!M159+'Model inputs'!M91+'Model inputs'!M148-'Model inputs'!M45 -> -12778.5 | N73: ='Model inputs'!N139+'Model inputs'!N159+'Model inputs'!N91+'Model inputs'!N148-'Model inputs'!N45 -> -19542.75 | O73: ='Model inputs'!O139+'Model inputs'!O159+'Model inputs'!O91+'Model inputs'!O148-'Model inputs'!O45 -> -26307 | P73: ='Model inputs'!P139+'Model inputs'!P159+'Model inputs'!P91+'Model inputs'!P148-'Model inputs'!P45 -> -33071.25 | Q73: ='Model inputs'!Q139+'Model inputs'!Q159+'Model inputs'!Q91+'Model inputs'!Q148-'Model inputs'!Q45 -> -39335.5 | R73: ='Model inputs'!R139+'Model inputs'!R159+'Model inputs'!R91+'Model inputs'!R148-'Model inputs'!R45 -> -46099.75 | S73: ='Model inputs'!S139+'Model inputs'!S159+'Model inputs'!S91+'Model inputs'!S148-'Model inputs'!S45 -> -52864 | ... Z73: ='Model inputs'!Z139+'Model inputs'!Z159+'Model inputs'!Z91+'Model inputs'!Z148-'Model inputs'!Z45 -> -79921
A74: Net cash burn > Per audit — high | C74: =0 -> 0 | D74: =0 -> 0 | E74: =0 -> 0 | F74: =0 -> 0 | G74: =0 -> 0 | H74: =0 -> 0 | I74: =0 -> 0 | J74: =0 -> 0 | K74: =0 -> 0 | L74: ='Model inputs'!L140+'Model inputs'!L160+'Model inputs'!L92+'Model inputs'!L148-'Model inputs'!L46 -> -13289.25 | M74: ='Model inputs'!M140+'Model inputs'!M160+'Model inputs'!M92+'Model inputs'!M148-'Model inputs'!M46 -> -27328.5 | N74: ='Model inputs'!N140+'Model inputs'!N160+'Model inputs'!N92+'Model inputs'!N148-'Model inputs'!N46 -> -41367.75 | O74: ='Model inputs'!O140+'Model inputs'!O160+'Model inputs'!O92+'Model inputs'!O148-'Model inputs'!O46 -> -55407 | P74: ='Model inputs'!P140+'Model inputs'!P160+'Model inputs'!P92+'Model inputs'!P148-'Model inputs'!P46 -> -69446.25 | Q74: ='Model inputs'!Q140+'Model inputs'!Q160+'Model inputs'!Q92+'Model inputs'!Q148-'Model inputs'!Q46 -> -82985.5 | R74: ='Model inputs'!R140+'Model inputs'!R160+'Model inputs'!R92+'Model inputs'!R148-'Model inputs'!R46 -> -97024.75 | S74: ='Model inputs'!S140+'Model inputs'!S160+'Model inputs'!S92+'Model inputs'!S148-'Model inputs'!S46 -> -111064 | ... Z74: ='Model inputs'!Z140+'Model inputs'!Z160+'Model inputs'!Z92+'Model inputs'!Z148-'Model inputs'!Z46 -> -167221
A75: Net cash burn > Per audit — low | C75: =0 -> 0 | D75: =0 -> 0 | E75: =0 -> 0 | F75: =0 -> 0 | G75: =0 -> 0 | H75: =0 -> 0 | I75: =0 -> 0 | J75: =0 -> 0 | K75: =0 -> 0 | L75: ='Model inputs'!L141+'Model inputs'!L161+'Model inputs'!L93+'Model inputs'!L148-'Model inputs'!L47 -> -2376.75 | M75: ='Model inputs'!M141+'Model inputs'!M161+'Model inputs'!M93+'Model inputs'!M148-'Model inputs'!M47 -> -5503.5 | N75: ='Model inputs'!N141+'Model inputs'!N161+'Model inputs'!N93+'Model inputs'!N148-'Model inputs'!N47 -> -8630.25 | O75: ='Model inputs'!O141+'Model inputs'!O161+'Model inputs'!O93+'Model inputs'!O148-'Model inputs'!O47 -> -11757 | P75: ='Model inputs'!P141+'Model inputs'!P161+'Model inputs'!P93+'Model inputs'!P148-'Model inputs'!P47 -> -14883.75 | Q75: ='Model inputs'!Q141+'Model inputs'!Q161+'Model inputs'!Q93+'Model inputs'!Q148-'Model inputs'!Q47 -> -17510.5 | R75: ='Model inputs'!R141+'Model inputs'!R161+'Model inputs'!R93+'Model inputs'!R148-'Model inputs'!R47 -> -20637.25 | S75: ='Model inputs'!S141+'Model inputs'!S161+'Model inputs'!S93+'Model inputs'!S148-'Model inputs'!S47 -> -23764 | ... Z75: ='Model inputs'!Z141+'Model inputs'!Z161+'Model inputs'!Z93+'Model inputs'!Z148-'Model inputs'!Z47 -> -36271
A76: Net cash burn | C76: =SUM('Model inputs'!C77,'Model inputs'!C78,'Model inputs'!C79,'Model inputs'!C80,'Model inputs'!C81) -> 0 | D76: =SUM('Model inputs'!D77,'Model inputs'!D78,'Model inputs'!D79,'Model inputs'!D80,'Model inputs'!D81) -> 0 | E76: =SUM('Model inputs'!E77,'Model inputs'!E78,'Model inputs'!E79,'Model inputs'!E80,'Model inputs'!E81) -> 0 | F76: =SUM('Model inputs'!F77,'Model inputs'!F78,'Model inputs'!F79,'Model inputs'!F80,'Model inputs'!F81) -> 0 | G76: =SUM('Model inputs'!G77,'Model inputs'!G78,'Model inputs'!G79,'Model inputs'!G80,'Model inputs'!G81) -> 0 | H76: =SUM('Model inputs'!H77,'Model inputs'!H78,'Model inputs'!H79,'Model inputs'!H80,'Model inputs'!H81) -> 0 | I76: =SUM('Model inputs'!I77,'Model inputs'!I78,'Model inputs'!I79,'Model inputs'!I80,'Model inputs'!I81) -> 0 | J76: =SUM('Model inputs'!J77,'Model inputs'!J78,'Model inputs'!J79,'Model inputs'!J80,'Model inputs'!J81) -> 0 | K76: =SUM('Model inputs'!K77,'Model inputs'!K78,'Model inputs'!K79,'Model inputs'!K80,'Model inputs'!K81) -> 0 | L76: ="" | M76: ="" | N76: ="" | O76: ="" | P76: ="" | Q76: ="" | R76: ="" | S76: ="" | ... Z76: =""
A77: Net cash burn > Annual deal-team | C77: =0 -> 0 | D77: =0 -> 0 | E77: =0 -> 0 | F77: =0 -> 0 | G77: =0 -> 0 | H77: =0 -> 0 | I77: =0 -> 0 | J77: =0 -> 0 | K77: =0 -> 0 | L77: ='Model inputs'!L143+'Model inputs'!L163+'Model inputs'!L95+'Model inputs'!L149-'Model inputs'!L49 -> 750 | M77: ='Model inputs'!M143+'Model inputs'!M163+'Model inputs'!M95+'Model inputs'!M149-'Model inputs'!M49 -> 750 | N77: ='Model inputs'!N143+'Model inputs'!N163+'Model inputs'!N95+'Model inputs'!N149-'Model inputs'!N49 -> -45366.1 | O77: ='Model inputs'!O143+'Model inputs'!O163+'Model inputs'!O95+'Model inputs'!O149-'Model inputs'!O49 -> 1193.9 | P77: ='Model inputs'!P143+'Model inputs'!P163+'Model inputs'!P95+'Model inputs'!P149-'Model inputs'!P49 -> 1193.9 | Q77: ='Model inputs'!Q143+'Model inputs'!Q163+'Model inputs'!Q95+'Model inputs'!Q149-'Model inputs'!Q49 -> 1693.9 | R77: ='Model inputs'!R143+'Model inputs'!R163+'Model inputs'!R95+'Model inputs'!R149-'Model inputs'!R49 -> 1693.9 | S77: ='Model inputs'!S143+'Model inputs'!S163+'Model inputs'!S95+'Model inputs'!S149-'Model inputs'!S49 -> 1693.9 | ... Z77: ='Model inputs'!Z143+'Model inputs'!Z163+'Model inputs'!Z95+'Model inputs'!Z149-'Model inputs'!Z49 -> 1693.9
A78: Net cash burn > Hybrid | C78: =0 -> 0 | D78: =0 -> 0 | E78: =0 -> 0 | F78: =0 -> 0 | G78: =0 -> 0 | H78: =0 -> 0 | I78: =0 -> 0 | J78: =0 -> 0 | K78: =0 -> 0 | L78: ='Model inputs'!L144+'Model inputs'!L164+'Model inputs'!L96+'Model inputs'!L149-'Model inputs'!L50 -> 750 | M78: ='Model inputs'!M144+'Model inputs'!M164+'Model inputs'!M96+'Model inputs'!M149-'Model inputs'!M50 -> 750 | N78: ='Model inputs'!N144+'Model inputs'!N164+'Model inputs'!N96+'Model inputs'!N149-'Model inputs'!N50 -> -14326.1 | O78: ='Model inputs'!O144+'Model inputs'!O164+'Model inputs'!O96+'Model inputs'!O149-'Model inputs'!O50 -> -2686.1 | P78: ='Model inputs'!P144+'Model inputs'!P164+'Model inputs'!P96+'Model inputs'!P149-'Model inputs'!P50 -> -2686.1 | Q78: ='Model inputs'!Q144+'Model inputs'!Q164+'Model inputs'!Q96+'Model inputs'!Q149-'Model inputs'!Q50 -> -2186.1 | R78: ='Model inputs'!R144+'Model inputs'!R164+'Model inputs'!R96+'Model inputs'!R149-'Model inputs'!R50 -> -2186.1 | S78: ='Model inputs'!S144+'Model inputs'!S164+'Model inputs'!S96+'Model inputs'!S149-'Model inputs'!S50 -> -2186.1 | ... Z78: ='Model inputs'!Z144+'Model inputs'!Z164+'Model inputs'!Z96+'Model inputs'!Z149-'Model inputs'!Z50 -> -2186.1
A79: Net cash burn > Per audit — base | C79: =0 -> 0 | D79: =0 -> 0 | E79: =0 -> 0 | F79: =0 -> 0 | G79: =0 -> 0 | H79: =0 -> 0 | I79: =0 -> 0 | J79: =0 -> 0 | K79: =0 -> 0 | L79: ='Model inputs'!L145+'Model inputs'!L165+'Model inputs'!L97+'Model inputs'!L149-'Model inputs'!L51 -> 750 | M79: ='Model inputs'!M145+'Model inputs'!M165+'Model inputs'!M97+'Model inputs'!M149-'Model inputs'!M51 -> 750 | N79: ='Model inputs'!N145+'Model inputs'!N165+'Model inputs'!N97+'Model inputs'!N149-'Model inputs'!N51 -> -4626.1 | O79: ='Model inputs'!O145+'Model inputs'!O165+'Model inputs'!O97+'Model inputs'!O149-'Model inputs'!O51 -> -4626.1 | P79: ='Model inputs'!P145+'Model inputs'!P165+'Model inputs'!P97+'Model inputs'!P149-'Model inputs'!P51 -> -4626.1 | Q79: ='Model inputs'!Q145+'Model inputs'!Q165+'Model inputs'!Q97+'Model inputs'!Q149-'Model inputs'!Q51 -> -4126.1 | R79: ='Model inputs'!R145+'Model inputs'!R165+'Model inputs'!R97+'Model inputs'!R149-'Model inputs'!R51 -> -4126.1 | S79: ='Model inputs'!S145+'Model inputs'!S165+'Model inputs'!S97+'Model inputs'!S149-'Model inputs'!S51 -> -4126.1 | ... Z79: ='Model inputs'!Z145+'Model inputs'!Z165+'Model inputs'!Z97+'Model inputs'!Z149-'Model inputs'!Z51 -> -4126.1
A80: Net cash burn > Per audit — high | C80: =0 -> 0 | D80: =0 -> 0 | E80: =0 -> 0 | F80: =0 -> 0 | G80: =0 -> 0 | H80: =0 -> 0 | I80: =0 -> 0 | J80: =0 -> 0 | K80: =0 -> 0 | L80: ='Model inputs'!L146+'Model inputs'!L166+'Model inputs'!L98+'Model inputs'!L149-'Model inputs'!L52 -> 750 | M80: ='Model inputs'!M146+'Model inputs'!M166+'Model inputs'!M98+'Model inputs'!M149-'Model inputs'!M52 -> 750 | N80: ='Model inputs'!N146+'Model inputs'!N166+'Model inputs'!N98+'Model inputs'!N149-'Model inputs'!N52 -> -10446.1 | O80: ='Model inputs'!O146+'Model inputs'!O166+'Model inputs'!O98+'Model inputs'!O149-'Model inputs'!O52 -> -10446.1 | P80: ='Model inputs'!P146+'Model inputs'!P166+'Model inputs'!P98+'Model inputs'!P149-'Model inputs'!P52 -> -10446.1 | Q80: ='Model inputs'!Q146+'Model inputs'!Q166+'Model inputs'!Q98+'Model inputs'!Q149-'Model inputs'!Q52 -> -9946.1 | R80: ='Model inputs'!R146+'Model inputs'!R166+'Model inputs'!R98+'Model inputs'!R149-'Model inputs'!R52 -> -9946.1 | S80: ='Model inputs'!S146+'Model inputs'!S166+'Model inputs'!S98+'Model inputs'!S149-'Model inputs'!S52 -> -9946.1 | ... Z80: ='Model inputs'!Z146+'Model inputs'!Z166+'Model inputs'!Z98+'Model inputs'!Z149-'Model inputs'!Z52 -> -9946.1
A81: Net cash burn > Per audit — low | C81: =0 -> 0 | D81: =0 -> 0 | E81: =0 -> 0 | F81: =0 -> 0 | G81: =0 -> 0 | H81: =0 -> 0 | I81: =0 -> 0 | J81: =0 -> 0 | K81: =0 -> 0 | L81: ='Model inputs'!L147+'Model inputs'!L167+'Model inputs'!L99+'Model inputs'!L149-'Model inputs'!L53 -> 750 | M81: ='Model inputs'!M147+'Model inputs'!M167+'Model inputs'!M99+'Model inputs'!M149-'Model inputs'!M53 -> 750 | N81: ='Model inputs'!N147+'Model inputs'!N167+'Model inputs'!N99+'Model inputs'!N149-'Model inputs'!N53 -> -1716.1 | O81: ='Model inputs'!O147+'Model inputs'!O167+'Model inputs'!O99+'Model inputs'!O149-'Model inputs'!O53 -> -1716.1 | P81: ='Model inputs'!P147+'Model inputs'!P167+'Model inputs'!P99+'Model inputs'!P149-'Model inputs'!P53 -> -1716.1 | Q81: ='Model inputs'!Q147+'Model inputs'!Q167+'Model inputs'!Q99+'Model inputs'!Q149-'Model inputs'!Q53 -> -1216.1 | R81: ='Model inputs'!R147+'Model inputs'!R167+'Model inputs'!R99+'Model inputs'!R149-'Model inputs'!R53 -> -1216.1 | S81: ='Model inputs'!S147+'Model inputs'!S167+'Model inputs'!S99+'Model inputs'!S149-'Model inputs'!S53 -> -1216.1 | ... Z81: ='Model inputs'!Z147+'Model inputs'!Z167+'Model inputs'!Z99+'Model inputs'!Z149-'Model inputs'!Z53 -> -1216.1
A82: Plan Contribution profit · Forecast contribution profit · Growth · Growth | C82: 0 | D82: 0 | E82: 0 | F82: 0 | G82: 0 | H82: 0 | I82: 0 | J82: 0 | K82: 0 | L82: =IF(SUM(IF(IF('Model inputs'!B929="",0,1)="",0,IF('Model inputs'!B929="",0,1)),IF(IF('Model inputs'!B930="",0,1)="",0,IF('Model inputs'!B930="",0,1)),IF(IF('Model inputs'!B931="",0,1)="",0,IF('Model inputs'!B931="",0,1)),IF(IF('Model inputs'!B932="",0,1)="",0,IF('Model inputs'!B932="",0,1)),IF(IF('Model inputs'!B933="",0,1)="",0,IF('Model inputs'!B933="",0,1)))=0,"",SUM('Model inputs'!B929,'Model inputs'!B930,'Model inputs'!B931,'Model inputs'!B932,'Model inputs'!B933)) -> 4339.25 | M82: =IF(SUM(IF(IF('Model inputs'!B934="",0,1)="",0,IF('Model inputs'!B934="",0,1)),IF(IF('Model inputs'!B935="",0,1)="",0,IF('Model inputs'!B935="",0,1)),IF(IF('Model inputs'!B936="",0,1)="",0,IF('Model inputs'!B936="",0,1)),IF(IF('Model inputs'!B937="",0,1)="",0,IF('Model inputs'!B937="",0,1)),IF(IF('Model inputs'!B938="",0,1)="",0,IF('Model inputs'!B938="",0,1)))=0,"",SUM('Model inputs'!B934,'Model inputs'!B935,'Model inputs'!B936,'Model inputs'!B937,'Model inputs'!B938)) -> 8678.5 | N82: =IF(SUM(IF(IF('Model inputs'!B939="",0,1)="",0,IF('Model inputs'!B939="",0,1)),IF(IF('Model inputs'!B940="",0,1)="",0,IF('Model inputs'!B940="",0,1)),IF(IF('Model inputs'!B941="",0,1)="",0,IF('Model inputs'!B941="",0,1)),IF(IF('Model inputs'!B942="",0,1)="",0,IF('Model inputs'!B942="",0,1)),IF(IF('Model inputs'!B943="",0,1)="",0,IF('Model inputs'!B943="",0,1)))=0,"",SUM('Model inputs'!B939,'Model inputs'!B940,'Model inputs'!B941,'Model inputs'!B942,'Model inputs'!B943)) -> 13017.75 | O82: =IF(SUM(IF(IF('Model inputs'!B944="",0,1)="",0,IF('Model inputs'!B944="",0,1)),IF(IF('Model inputs'!B945="",0,1)="",0,IF('Model inputs'!B945="",0,1)),IF(IF('Model inputs'!B946="",0,1)="",0,IF('Model inputs'!B946="",0,1)),IF(IF('Model inputs'!B947="",0,1)="",0,IF('Model inputs'!B947="",0,1)),IF(IF('Model inputs'!B948="",0,1)="",0,IF('Model inputs'!B948="",0,1)))=0,"",SUM('Model inputs'!B944,'Model inputs'!B945,'Model inputs'!B946,'Model inputs'!B947,'Model inputs'!B948)) -> 17357 | P82: =IF(SUM(IF(IF('Model inputs'!B949="",0,1)="",0,IF('Model inputs'!B949="",0,1)),IF(IF('Model inputs'!B950="",0,1)="",0,IF('Model inputs'!B950="",0,1)),IF(IF('Model inputs'!B951="",0,1)="",0,IF('Model inputs'!B951="",0,1)),IF(IF('Model inputs'!B952="",0,1)="",0,IF('Model inputs'!B952="",0,1)),IF(IF('Model inputs'!B953="",0,1)="",0,IF('Model inputs'!B953="",0,1)))=0,"",SUM('Model inputs'!B949,'Model inputs'!B950,'Model inputs'!B951,'Model inputs'!B952,'Model inputs'!B953)) -> 21696.25 | Q82: =IF(SUM(IF(IF('Model inputs'!B954="",0,1)="",0,IF('Model inputs'!B954="",0,1)),IF(IF('Model inputs'!B955="",0,1)="",0,IF('Model inputs'!B955="",0,1)),IF(IF('Model inputs'!B956="",0,1)="",0,IF('Model inputs'!B956="",0,1)),IF(IF('Model inputs'!B957="",0,1)="",0,IF('Model inputs'!B957="",0,1)),IF(IF('Model inputs'!B958="",0,1)="",0,IF('Model inputs'!B958="",0,1)))=0,"",SUM('Model inputs'!B954,'Model inputs'!B955,'Model inputs'!B956,'Model inputs'!B957,'Model inputs'!B958)) -> 26035.5 | R82: =IF(SUM(IF(IF('Model inputs'!B959="",0,1)="",0,IF('Model inputs'!B959="",0,1)),IF(IF('Model inputs'!B960="",0,1)="",0,IF('Model inputs'!B960="",0,1)),IF(IF('Model inputs'!B961="",0,1)="",0,IF('Model inputs'!B961="",0,1)),IF(IF('Model inputs'!B962="",0,1)="",0,IF('Model inputs'!B962="",0,1)),IF(IF('Model inputs'!B963="",0,1)="",0,IF('Model inputs'!B963="",0,1)))=0,"",SUM('Model inputs'!B959,'Model inputs'!B960,'Model inputs'!B961,'Model inputs'!B962,'Model inputs'!B963)) -> 30374.75 | S82: =IF(SUM(IF(IF('Model inputs'!B964="",0,1)="",0,IF('Model inputs'!B964="",0,1)),IF(IF('Model inputs'!B965="",0,1)="",0,IF('Model inputs'!B965="",0,1)),IF(IF('Model inputs'!B966="",0,1)="",0,IF('Model inputs'!B966="",0,1)),IF(IF('Model inputs'!B967="",0,1)="",0,IF('Model inputs'!B967="",0,1)),IF(IF('Model inputs'!B968="",0,1)="",0,IF('Model inputs'!B968="",0,1)))=0,"",SUM('Model inputs'!B964,'Model inputs'!B965,'Model inputs'!B966,'Model inputs'!B967,'Model inputs'!B968)) -> 34714 | T82: =IF(SUM(IF(IF('Model inputs'!B969="",0,1)="",0,IF('Model inputs'!B969="",0,1)),IF(IF('Model inputs'!B970="",0,1)="",0,IF('Model inputs'!B970="",0,1)),IF(IF('Model inputs'!B971="",0,1)="",0,IF('Model inputs'!B971="",0,1)),IF(IF('Model inputs'!B972="",0,1)="",0,IF('Model inputs'!B972="",0,1)),IF(IF('Model inputs'!B973="",0,1)="",0,IF('Model inputs'!B973="",0,1)))=0,"",SUM('Model inputs'!B969,'Model inputs'!B970,'Model inputs'!B971,'Model inputs'!B972,'Model inputs'!B973)) -> 39053.25 | U82: =IF(SUM(IF(IF('Model inputs'!B974="",0,1)="",0,IF('Model inputs'!B974="",0,1)),IF(IF('Model inputs'!B975="",0,1)="",0,IF('Model inputs'!B975="",0,1)),IF(IF('Model inputs'!B976="",0,1)="",0,IF('Model inputs'!B976="",0,1)),IF(IF('Model inputs'!B977="",0,1)="",0,IF('Model inputs'!B977="",0,1)),IF(IF('Model inputs'!B978="",0,1)="",0,IF('Model inputs'!B978="",0,1)))=0,"",SUM('Model inputs'!B974,'Model inputs'!B975,'Model inputs'!B976,'Model inputs'!B977,'Model inputs'!B978)) -> 43392.5 | V82: =IF(SUM(IF(IF('Model inputs'!B979="",0,1)="",0,IF('Model inputs'!B979="",0,1)),IF(IF('Model inputs'!B980="",0,1)="",0,IF('Model inputs'!B980="",0,1)),IF(IF('Model inputs'!B981="",0,1)="",0,IF('Model inputs'!B981="",0,1)),IF(IF('Model inputs'!B982="",0,1)="",0,IF('Model inputs'!B982="",0,1)),IF(IF('Model inputs'!B983="",0,1)="",0,IF('Model inputs'!B983="",0,1)))=0,"",SUM('Model inputs'!B979,'Model inputs'!B980,'Model inputs'!B981,'Model inputs'!B982,'Model inputs'!B983)) -> 47731.75 | W82: =IF(SUM(IF(IF('Model inputs'!B984="",0,1)="",0,IF('Model inputs'!B984="",0,1)),IF(IF('Model inputs'!B985="",0,1)="",0,IF('Model inputs'!B985="",0,1)),IF(IF('Model inputs'!B986="",0,1)="",0,IF('Model inputs'!B986="",0,1)),IF(IF('Model inputs'!B987="",0,1)="",0,IF('Model inputs'!B987="",0,1)),IF(IF('Model inputs'!B988="",0,1)="",0,IF('Model inputs'!B988="",0,1)))=0,"",SUM('Model inputs'!B984,'Model inputs'!B985,'Model inputs'!B986,'Model inputs'!B987,'Model inputs'!B988)) -> 52071 | X82: =IF(SUM(IF(IF('Model inputs'!B989="",0,1)="",0,IF('Model inputs'!B989="",0,1)),IF(IF('Model inputs'!B990="",0,1)="",0,IF('Model inputs'!B990="",0,1)),IF(IF('Model inputs'!B991="",0,1)="",0,IF('Model inputs'!B991="",0,1)),IF(IF('Model inputs'!B992="",0,1)="",0,IF('Model inputs'!B992="",0,1)),IF(IF('Model inputs'!B993="",0,1)="",0,IF('Model inputs'!B993="",0,1)))=0,"",SUM('Model inputs'!B989,'Model inputs'!B990,'Model inputs'!B991,'Model inputs'!B992,'Model inputs'!B993)) -> 52071 | Y82: =IF(SUM(IF(IF('Model inputs'!B994="",0,1)="",0,IF('Model inputs'!B994="",0,1)),IF(IF('Model inputs'!B995="",0,1)="",0,IF('Model inputs'!B995="",0,1)),IF(IF('Model inputs'!B996="",0,1)="",0,IF('Model inputs'!B996="",0,1)),IF(IF('Model inputs'!B997="",0,1)="",0,IF('Model inputs'!B997="",0,1)),IF(IF('Model inputs'!B998="",0,1)="",0,IF('Model inputs'!B998="",0,1)))=0,"",SUM('Model inputs'!B994,'Model inputs'!B995,'Model inputs'!B996,'Model inputs'!B997,'Model inputs'!B998)) -> 52071 | Z82: =IF(SUM(IF(IF('Model inputs'!B999="",0,1)="",0,IF('Model inputs'!B999="",0,1)),IF(IF('Model inputs'!B1000="",0,1)="",0,IF('Model inputs'!B1000="",0,1)),IF(IF('Model inputs'!B1001="",0,1)="",0,IF('Model inputs'!B1001="",0,1)),IF(IF('Model inputs'!B1002="",0,1)="",0,IF('Model inputs'!B1002="",0,1)),IF(IF('Model inputs'!B1003="",0,1)="",0,IF('Model inputs'!B1003="",0,1)))=0,"",SUM('Model inputs'!B999,'Model inputs'!B1000,'Model inputs'!B1001,'Model inputs'!B1002,'Model inputs'!B1003)) -> 52071
A83: Plan Contribution profit · Forecast contribution profit · Conservative · Conservative | C83: 0 | D83: 0 | E83: 0 | F83: 0 | G83: 0 | H83: 0 | I83: 0 | J83: 0 | K83: 0 | L83: =IF(SUM(IF(IF('Model inputs'!B1004="",0,1)="",0,IF('Model inputs'!B1004="",0,1)),IF(IF('Model inputs'!B1005="",0,1)="",0,IF('Model inputs'!B1005="",0,1)),IF(IF('Model inputs'!B1006="",0,1)="",0,IF('Model inputs'!B1006="",0,1)),IF(IF('Model inputs'!B1007="",0,1)="",0,IF('Model inputs'!B1007="",0,1)),IF(IF('Model inputs'!B1008="",0,1)="",0,IF('Model inputs'!B1008="",0,1)))=0,"",SUM('Model inputs'!B1004,'Model inputs'!B1005,'Model inputs'!B1006,'Model inputs'!B1007,'Model inputs'!B1008)) -> 0 | M83: =IF(SUM(IF(IF('Model inputs'!B1009="",0,1)="",0,IF('Model inputs'!B1009="",0,1)),IF(IF('Model inputs'!B1010="",0,1)="",0,IF('Model inputs'!B1010="",0,1)),IF(IF('Model inputs'!B1011="",0,1)="",0,IF('Model inputs'!B1011="",0,1)),IF(IF('Model inputs'!B1012="",0,1)="",0,IF('Model inputs'!B1012="",0,1)),IF(IF('Model inputs'!B1013="",0,1)="",0,IF('Model inputs'!B1013="",0,1)))=0,"",SUM('Model inputs'!B1009,'Model inputs'!B1010,'Model inputs'!B1011,'Model inputs'!B1012,'Model inputs'!B1013)) -> 0 | N83: =IF(SUM(IF(IF('Model inputs'!B1014="",0,1)="",0,IF('Model inputs'!B1014="",0,1)),IF(IF('Model inputs'!B1015="",0,1)="",0,IF('Model inputs'!B1015="",0,1)),IF(IF('Model inputs'!B1016="",0,1)="",0,IF('Model inputs'!B1016="",0,1)),IF(IF('Model inputs'!B1017="",0,1)="",0,IF('Model inputs'!B1017="",0,1)),IF(IF('Model inputs'!B1018="",0,1)="",0,IF('Model inputs'!B1018="",0,1)))=0,"",SUM('Model inputs'!B1014,'Model inputs'!B1015,'Model inputs'!B1016,'Model inputs'!B1017,'Model inputs'!B1018)) -> 2466.1 | O83: =IF(SUM(IF(IF('Model inputs'!B1019="",0,1)="",0,IF('Model inputs'!B1019="",0,1)),IF(IF('Model inputs'!B1020="",0,1)="",0,IF('Model inputs'!B1020="",0,1)),IF(IF('Model inputs'!B1021="",0,1)="",0,IF('Model inputs'!B1021="",0,1)),IF(IF('Model inputs'!B1022="",0,1)="",0,IF('Model inputs'!B1022="",0,1)),IF(IF('Model inputs'!B1023="",0,1)="",0,IF('Model inputs'!B1023="",0,1)))=0,"",SUM('Model inputs'!B1019,'Model inputs'!B1020,'Model inputs'!B1021,'Model inputs'!B1022,'Model inputs'!B1023)) -> 2466.1 | P83: =IF(SUM(IF(IF('Model inputs'!B1024="",0,1)="",0,IF('Model inputs'!B1024="",0,1)),IF(IF('Model inputs'!B1025="",0,1)="",0,IF('Model inputs'!B1025="",0,1)),IF(IF('Model inputs'!B1026="",0,1)="",0,IF('Model inputs'!B1026="",0,1)),IF(IF('Model inputs'!B1027="",0,1)="",0,IF('Model inputs'!B1027="",0,1)),IF(IF('Model inputs'!B1028="",0,1)="",0,IF('Model inputs'!B1028="",0,1)))=0,"",SUM('Model inputs'!B1024,'Model inputs'!B1025,'Model inputs'!B1026,'Model inputs'!B1027,'Model inputs'!B1028)) -> 2466.1 | Q83: =IF(SUM(IF(IF('Model inputs'!B1029="",0,1)="",0,IF('Model inputs'!B1029="",0,1)),IF(IF('Model inputs'!B1030="",0,1)="",0,IF('Model inputs'!B1030="",0,1)),IF(IF('Model inputs'!B1031="",0,1)="",0,IF('Model inputs'!B1031="",0,1)),IF(IF('Model inputs'!B1032="",0,1)="",0,IF('Model inputs'!B1032="",0,1)),IF(IF('Model inputs'!B1033="",0,1)="",0,IF('Model inputs'!B1033="",0,1)))=0,"",SUM('Model inputs'!B1029,'Model inputs'!B1030,'Model inputs'!B1031,'Model inputs'!B1032,'Model inputs'!B1033)) -> 2466.1 | R83: =IF(SUM(IF(IF('Model inputs'!B1034="",0,1)="",0,IF('Model inputs'!B1034="",0,1)),IF(IF('Model inputs'!B1035="",0,1)="",0,IF('Model inputs'!B1035="",0,1)),IF(IF('Model inputs'!B1036="",0,1)="",0,IF('Model inputs'!B1036="",0,1)),IF(IF('Model inputs'!B1037="",0,1)="",0,IF('Model inputs'!B1037="",0,1)),IF(IF('Model inputs'!B1038="",0,1)="",0,IF('Model inputs'!B1038="",0,1)))=0,"",SUM('Model inputs'!B1034,'Model inputs'!B1035,'Model inputs'!B1036,'Model inputs'!B1037,'Model inputs'!B1038)) -> 2466.1 | S83: =IF(SUM(IF(IF('Model inputs'!B1039="",0,1)="",0,IF('Model inputs'!B1039="",0,1)),IF(IF('Model inputs'!B1040="",0,1)="",0,IF('Model inputs'!B1040="",0,1)),IF(IF('Model inputs'!B1041="",0,1)="",0,IF('Model inputs'!B1041="",0,1)),IF(IF('Model inputs'!B1042="",0,1)="",0,IF('Model inputs'!B1042="",0,1)),IF(IF('Model inputs'!B1043="",0,1)="",0,IF('Model inputs'!B1043="",0,1)))=0,"",SUM('Model inputs'!B1039,'Model inputs'!B1040,'Model inputs'!B1041,'Model inputs'!B1042,'Model inputs'!B1043)) -> 2466.1 | T83: =IF(SUM(IF(IF('Model inputs'!B1044="",0,1)="",0,IF('Model inputs'!B1044="",0,1)),IF(IF('Model inputs'!B1045="",0,1)="",0,IF('Model inputs'!B1045="",0,1)),IF(IF('Model inputs'!B1046="",0,1)="",0,IF('Model inputs'!B1046="",0,1)),IF(IF('Model inputs'!B1047="",0,1)="",0,IF('Model inputs'!B1047="",0,1)),IF(IF('Model inputs'!B1048="",0,1)="",0,IF('Model inputs'!B1048="",0,1)))=0,"",SUM('Model inputs'!B1044,'Model inputs'!B1045,'Model inputs'!B1046,'Model inputs'!B1047,'Model inputs'!B1048)) -> 2466.1 | U83: =IF(SUM(IF(IF('Model inputs'!B1049="",0,1)="",0,IF('Model inputs'!B1049="",0,1)),IF(IF('Model inputs'!B1050="",0,1)="",0,IF('Model inputs'!B1050="",0,1)),IF(IF('Model inputs'!B1051="",0,1)="",0,IF('Model inputs'!B1051="",0,1)),IF(IF('Model inputs'!B1052="",0,1)="",0,IF('Model inputs'!B1052="",0,1)),IF(IF('Model inputs'!B1053="",0,1)="",0,IF('Model inputs'!B1053="",0,1)))=0,"",SUM('Model inputs'!B1049,'Model inputs'!B1050,'Model inputs'!B1051,'Model inputs'!B1052,'Model inputs'!B1053)) -> 2466.1 | V83: =IF(SUM(IF(IF('Model inputs'!B1054="",0,1)="",0,IF('Model inputs'!B1054="",0,1)),IF(IF('Model inputs'!B1055="",0,1)="",0,IF('Model inputs'!B1055="",0,1)),IF(IF('Model inputs'!B1056="",0,1)="",0,IF('Model inputs'!B1056="",0,1)),IF(IF('Model inputs'!B1057="",0,1)="",0,IF('Model inputs'!B1057="",0,1)),IF(IF('Model inputs'!B1058="",0,1)="",0,IF('Model inputs'!B1058="",0,1)))=0,"",SUM('Model inputs'!B1054,'Model inputs'!B1055,'Model inputs'!B1056,'Model inputs'!B1057,'Model inputs'!B1058)) -> 2466.1 | W83: =IF(SUM(IF(IF('Model inputs'!B1059="",0,1)="",0,IF('Model inputs'!B1059="",0,1)),IF(IF('Model inputs'!B1060="",0,1)="",0,IF('Model inputs'!B1060="",0,1)),IF(IF('Model inputs'!B1061="",0,1)="",0,IF('Model inputs'!B1061="",0,1)),IF(IF('Model inputs'!B1062="",0,1)="",0,IF('Model inputs'!B1062="",0,1)),IF(IF('Model inputs'!B1063="",0,1)="",0,IF('Model inputs'!B1063="",0,1)))=0,"",SUM('Model inputs'!B1059,'Model inputs'!B1060,'Model inputs'!B1061,'Model inputs'!B1062,'Model inputs'!B1063)) -> 2466.1 | X83: =IF(SUM(IF(IF('Model inputs'!B1064="",0,1)="",0,IF('Model inputs'!B1064="",0,1)),IF(IF('Model inputs'!B1065="",0,1)="",0,IF('Model inputs'!B1065="",0,1)),IF(IF('Model inputs'!B1066="",0,1)="",0,IF('Model inputs'!B1066="",0,1)),IF(IF('Model inputs'!B1067="",0,1)="",0,IF('Model inputs'!B1067="",0,1)),IF(IF('Model inputs'!B1068="",0,1)="",0,IF('Model inputs'!B1068="",0,1)))=0,"",SUM('Model inputs'!B1064,'Model inputs'!B1065,'Model inputs'!B1066,'Model inputs'!B1067,'Model inputs'!B1068)) -> 2466.1 | Y83: =IF(SUM(IF(IF('Model inputs'!B1069="",0,1)="",0,IF('Model inputs'!B1069="",0,1)),IF(IF('Model inputs'!B1070="",0,1)="",0,IF('Model inputs'!B1070="",0,1)),IF(IF('Model inputs'!B1071="",0,1)="",0,IF('Model inputs'!B1071="",0,1)),IF(IF('Model inputs'!B1072="",0,1)="",0,IF('Model inputs'!B1072="",0,1)),IF(IF('Model inputs'!B1073="",0,1)="",0,IF('Model inputs'!B1073="",0,1)))=0,"",SUM('Model inputs'!B1069,'Model inputs'!B1070,'Model inputs'!B1071,'Model inputs'!B1072,'Model inputs'!B1073)) -> 2466.1 | Z83: =IF(SUM(IF(IF('Model inputs'!B1074="",0,1)="",0,IF('Model inputs'!B1074="",0,1)),IF(IF('Model inputs'!B1075="",0,1)="",0,IF('Model inputs'!B1075="",0,1)),IF(IF('Model inputs'!B1076="",0,1)="",0,IF('Model inputs'!B1076="",0,1)),IF(IF('Model inputs'!B1077="",0,1)="",0,IF('Model inputs'!B1077="",0,1)),IF(IF('Model inputs'!B1078="",0,1)="",0,IF('Model inputs'!B1078="",0,1)))=0,"",SUM('Model inputs'!B1074,'Model inputs'!B1075,'Model inputs'!B1076,'Model inputs'!B1077,'Model inputs'!B1078)) -> 2466.1
A84: Projection month · Cumulative funding gap · Growth · Growth | C84: 0 | D84: 0 | E84: 0 | F84: 0 | G84: 0 | H84: 0 | I84: 0 | J84: 0 | K84: 0 | L84: =DATEDIF('Model inputs'!B20,DATE(2026,10,1),"M")+1 -> 1 | M84: =DATEDIF('Model inputs'!B20,DATE(2026,11,1),"M")+1 -> 2 | N84: =DATEDIF('Model inputs'!B20,DATE(2026,12,1),"M")+1 -> 3 | O84: =DATEDIF('Model inputs'!B20,DATE(2027,1,1),"M")+1 -> 4 | P84: =DATEDIF('Model inputs'!B20,DATE(2027,2,1),"M")+1 -> 5 | Q84: =DATEDIF('Model inputs'!B20,DATE(2027,3,1),"M")+1 -> 6 | R84: =DATEDIF('Model inputs'!B20,DATE(2027,4,1),"M")+1 -> 7 | S84: =DATEDIF('Model inputs'!B20,DATE(2027,5,1),"M")+1 -> 8 | T84: =DATEDIF('Model inputs'!B20,DATE(2027,6,1),"M")+1 -> 9 | U84: =DATEDIF('Model inputs'!B20,DATE(2027,7,1),"M")+1 -> 10 | V84: =DATEDIF('Model inputs'!B20,DATE(2027,8,1),"M")+1 -> 11 | W84: =DATEDIF('Model inputs'!B20,DATE(2027,9,1),"M")+1 -> 12 | X84: =DATEDIF('Model inputs'!B20,DATE(2027,10,1),"M")+1 -> 13 | Y84: =DATEDIF('Model inputs'!B20,DATE(2027,11,1),"M")+1 -> 14 | Z84: =DATEDIF('Model inputs'!B20,DATE(2027,12,1),"M")+1 -> 15
A85: Projection month · Cumulative funding gap · Conservative · Conservative | C85: 0 | D85: 0 | E85: 0 | F85: 0 | G85: 0 | H85: 0 | I85: 0 | J85: 0 | K85: 0 | L85: =DATEDIF('Model inputs'!B21,DATE(2026,10,1),"M")+1 -> 1 | M85: =DATEDIF('Model inputs'!B21,DATE(2026,11,1),"M")+1 -> 2 | N85: =DATEDIF('Model inputs'!B21,DATE(2026,12,1),"M")+1 -> 3 | O85: =DATEDIF('Model inputs'!B21,DATE(2027,1,1),"M")+1 -> 4 | P85: =DATEDIF('Model inputs'!B21,DATE(2027,2,1),"M")+1 -> 5 | Q85: =DATEDIF('Model inputs'!B21,DATE(2027,3,1),"M")+1 -> 6 | R85: =DATEDIF('Model inputs'!B21,DATE(2027,4,1),"M")+1 -> 7 | S85: =DATEDIF('Model inputs'!B21,DATE(2027,5,1),"M")+1 -> 8 | T85: =DATEDIF('Model inputs'!B21,DATE(2027,6,1),"M")+1 -> 9 | U85: =DATEDIF('Model inputs'!B21,DATE(2027,7,1),"M")+1 -> 10 | V85: =DATEDIF('Model inputs'!B21,DATE(2027,8,1),"M")+1 -> 11 | W85: =DATEDIF('Model inputs'!B21,DATE(2027,9,1),"M")+1 -> 12 | X85: =DATEDIF('Model inputs'!B21,DATE(2027,10,1),"M")+1 -> 13 | Y85: =DATEDIF('Model inputs'!B21,DATE(2027,11,1),"M")+1 -> 14 | Z85: =DATEDIF('Model inputs'!B21,DATE(2027,12,1),"M")+1 -> 15
A86: Selected pricing model · Plan Audits delivered · Growth · Growth | AA86: ="Annual deal-team" -> Annual deal-team
A87: Selected pricing model · Plan Audits delivered · Conservative · Conservative | AA87: ="Per audit — low" -> Per audit — low
A88: Account support cost | C88: =SUM('Model inputs'!C89,'Model inputs'!C90,'Model inputs'!C91,'Model inputs'!C92,'Model inputs'!C93) -> 0 | D88: =SUM('Model inputs'!D89,'Model inputs'!D90,'Model inputs'!D91,'Model inputs'!D92,'Model inputs'!D93) -> 0 | E88: =SUM('Model inputs'!E89,'Model inputs'!E90,'Model inputs'!E91,'Model inputs'!E92,'Model inputs'!E93) -> 0 | F88: =SUM('Model inputs'!F89,'Model inputs'!F90,'Model inputs'!F91,'Model inputs'!F92,'Model inputs'!F93) -> 0 | G88: =SUM('Model inputs'!G89,'Model inputs'!G90,'Model inputs'!G91,'Model inputs'!G92,'Model inputs'!G93) -> 0 | H88: =SUM('Model inputs'!H89,'Model inputs'!H90,'Model inputs'!H91,'Model inputs'!H92,'Model inputs'!H93) -> 0 | I88: =SUM('Model inputs'!I89,'Model inputs'!I90,'Model inputs'!I91,'Model inputs'!I92,'Model inputs'!I93) -> 0 | J88: =SUM('Model inputs'!J89,'Model inputs'!J90,'Model inputs'!J91,'Model inputs'!J92,'Model inputs'!J93) -> 0 | K88: =SUM('Model inputs'!K89,'Model inputs'!K90,'Model inputs'!K91,'Model inputs'!K92,'Model inputs'!K93) -> 0 | L88: ="" | M88: ="" | N88: ="" | O88: ="" | P88: ="" | Q88: ="" | R88: ="" | S88: ="" | ... Z88: =""
A89: Account support cost > Annual deal-team | C89: =0 -> 0 | D89: =0 -> 0 | E89: =0 -> 0 | F89: =0 -> 0 | G89: =0 -> 0 | H89: =0 -> 0 | I89: =0 -> 0 | J89: =0 -> 0 | K89: =0 -> 0 | L89: ='Model inputs'!L154*'Model inputs'!AA266*'Model inputs'!AA264 -> 37.5 | M89: ='Model inputs'!M154*'Model inputs'!AA266*'Model inputs'!AA264 -> 75 | N89: ='Model inputs'!N154*'Model inputs'!AA266*'Model inputs'!AA264 -> 112.5 | O89: ='Model inputs'!O154*'Model inputs'!AA266*'Model inputs'!AA264 -> 150 | P89: ='Model inputs'!P154*'Model inputs'!AA266*'Model inputs'!AA264 -> 187.5 | Q89: ='Model inputs'!Q154*'Model inputs'!AA266*'Model inputs'!AA264 -> 225 | R89: ='Model inputs'!R154*'Model inputs'!AA266*'Model inputs'!AA264 -> 262.5 | S89: ='Model inputs'!S154*'Model inputs'!AA266*'Model inputs'!AA264 -> 300 | T89: ='Model inputs'!T154*'Model inputs'!AA266*'Model inputs'!AA264 -> 337.5 | U89: ='Model inputs'!U154*'Model inputs'!AA266*'Model inputs'!AA264 -> 375 | V89: ='Model inputs'!V154*'Model inputs'!AA266*'Model inputs'!AA264 -> 412.5 | W89: ='Model inputs'!W154*'Model inputs'!AA266*'Model inputs'!AA264 -> 450 | X89: ='Model inputs'!X154*'Model inputs'!AA266*'Model inputs'!AA264 -> 450 | Y89: ='Model inputs'!Y154*'Model inputs'!AA266*'Model inputs'!AA264 -> 450 | Z89: ='Model inputs'!Z154*'Model inputs'!AA266*'Model inputs'!AA264 -> 450
A90: Account support cost > Hybrid | C90: =0 -> 0 | D90: =0 -> 0 | E90: =0 -> 0 | F90: =0 -> 0 | G90: =0 -> 0 | H90: =0 -> 0 | I90: =0 -> 0 | J90: =0 -> 0 | K90: =0 -> 0 | L90: ='Model inputs'!L154*'Model inputs'!AA266*'Model inputs'!AA264 -> 37.5 | M90: ='Model inputs'!M154*'Model inputs'!AA266*'Model inputs'!AA264 -> 75 | N90: ='Model inputs'!N154*'Model inputs'!AA266*'Model inputs'!AA264 -> 112.5 | O90: ='Model inputs'!O154*'Model inputs'!AA266*'Model inputs'!AA264 -> 150 | P90: ='Model inputs'!P154*'Model inputs'!AA266*'Model inputs'!AA264 -> 187.5 | Q90: ='Model inputs'!Q154*'Model inputs'!AA266*'Model inputs'!AA264 -> 225 | R90: ='Model inputs'!R154*'Model inputs'!AA266*'Model inputs'!AA264 -> 262.5 | S90: ='Model inputs'!S154*'Model inputs'!AA266*'Model inputs'!AA264 -> 300 | T90: ='Model inputs'!T154*'Model inputs'!AA266*'Model inputs'!AA264 -> 337.5 | U90: ='Model inputs'!U154*'Model inputs'!AA266*'Model inputs'!AA264 -> 375 | V90: ='Model inputs'!V154*'Model inputs'!AA266*'Model inputs'!AA264 -> 412.5 | W90: ='Model inputs'!W154*'Model inputs'!AA266*'Model inputs'!AA264 -> 450 | X90: ='Model inputs'!X154*'Model inputs'!AA266*'Model inputs'!AA264 -> 450 | Y90: ='Model inputs'!Y154*'Model inputs'!AA266*'Model inputs'!AA264 -> 450 | Z90: ='Model inputs'!Z154*'Model inputs'!AA266*'Model inputs'!AA264 -> 450
A91: Account support cost > Per audit — base | C91: =0 -> 0 | D91: =0 -> 0 | E91: =0 -> 0 | F91: =0 -> 0 | G91: =0 -> 0 | H91: =0 -> 0 | I91: =0 -> 0 | J91: =0 -> 0 | K91: =0 -> 0 | L91: ='Model inputs'!L154*'Model inputs'!AA266*'Model inputs'!AA264 -> 37.5 | M91: ='Model inputs'!M154*'Model inputs'!AA266*'Model inputs'!AA264 -> 75 | N91: ='Model inputs'!N154*'Model inputs'!AA266*'Model inputs'!AA264 -> 112.5 | O91: ='Model inputs'!O154*'Model inputs'!AA266*'Model inputs'!AA264 -> 150 | P91: ='Model inputs'!P154*'Model inputs'!AA266*'Model inputs'!AA264 -> 187.5 | Q91: ='Model inputs'!Q154*'Model inputs'!AA266*'Model inputs'!AA264 -> 225 | R91: ='Model inputs'!R154*'Model inputs'!AA266*'Model inputs'!AA264 -> 262.5 | S91: ='Model inputs'!S154*'Model inputs'!AA266*'Model inputs'!AA264 -> 300 | T91: ='Model inputs'!T154*'Model inputs'!AA266*'Model inputs'!AA264 -> 337.5 | U91: ='Model inputs'!U154*'Model inputs'!AA266*'Model inputs'!AA264 -> 375 | V91: ='Model inputs'!V154*'Model inputs'!AA266*'Model inputs'!AA264 -> 412.5 | W91: ='Model inputs'!W154*'Model inputs'!AA266*'Model inputs'!AA264 -> 450 | X91: ='Model inputs'!X154*'Model inputs'!AA266*'Model inputs'!AA264 -> 450 | Y91: ='Model inputs'!Y154*'Model inputs'!AA266*'Model inputs'!AA264 -> 450 | Z91: ='Model inputs'!Z154*'Model inputs'!AA266*'Model inputs'!AA264 -> 450
A92: Account support cost > Per audit — high | C92: =0 -> 0 | D92: =0 -> 0 | E92: =0 -> 0 | F92: =0 -> 0 | G92: =0 -> 0 | H92: =0 -> 0 | I92: =0 -> 0 | J92: =0 -> 0 | K92: =0 -> 0 | L92: ='Model inputs'!L154*'Model inputs'!AA266*'Model inputs'!AA264 -> 37.5 | M92: ='Model inputs'!M154*'Model inputs'!AA266*'Model inputs'!AA264 -> 75 | N92: ='Model inputs'!N154*'Model inputs'!AA266*'Model inputs'!AA264 -> 112.5 | O92: ='Model inputs'!O154*'Model inputs'!AA266*'Model inputs'!AA264 -> 150 | P92: ='Model inputs'!P154*'Model inputs'!AA266*'Model inputs'!AA264 -> 187.5 | Q92: ='Model inputs'!Q154*'Model inputs'!AA266*'Model inputs'!AA264 -> 225 | R92: ='Model inputs'!R154*'Model inputs'!AA266*'Model inputs'!AA264 -> 262.5 | S92: ='Model inputs'!S154*'Model inputs'!AA266*'Model inputs'!AA264 -> 300 | T92: ='Model inputs'!T154*'Model inputs'!AA266*'Model inputs'!AA264 -> 337.5 | U92: ='Model inputs'!U154*'Model inputs'!AA266*'Model inputs'!AA264 -> 375 | V92: ='Model inputs'!V154*'Model inputs'!AA266*'Model inputs'!AA264 -> 412.5 | W92: ='Model inputs'!W154*'Model inputs'!AA266*'Model inputs'!AA264 -> 450 | X92: ='Model inputs'!X154*'Model inputs'!AA266*'Model inputs'!AA264 -> 450 | Y92: ='Model inputs'!Y154*'Model inputs'!AA266*'Model inputs'!AA264 -> 450 | Z92: ='Model inputs'!Z154*'Model inputs'!AA266*'Model inputs'!AA264 -> 450
A93: Account support cost > Per audit — low | C93: =0 -> 0 | D93: =0 -> 0 | E93: =0 -> 0 | F93: =0 -> 0 | G93: =0 -> 0 | H93: =0 -> 0 | I93: =0 -> 0 | J93: =0 -> 0 | K93: =0 -> 0 | L93: ='Model inputs'!L154*'Model inputs'!AA266*'Model inputs'!AA264 -> 37.5 | M93: ='Model inputs'!M154*'Model inputs'!AA266*'Model inputs'!AA264 -> 75 | N93: ='Model inputs'!N154*'Model inputs'!AA266*'Model inputs'!AA264 -> 112.5 | O93: ='Model inputs'!O154*'Model inputs'!AA266*'Model inputs'!AA264 -> 150 | P93: ='Model inputs'!P154*'Model inputs'!AA266*'Model inputs'!AA264 -> 187.5 | Q93: ='Model inputs'!Q154*'Model inputs'!AA266*'Model inputs'!AA264 -> 225 | R93: ='Model inputs'!R154*'Model inputs'!AA266*'Model inputs'!AA264 -> 262.5 | S93: ='Model inputs'!S154*'Model inputs'!AA266*'Model inputs'!AA264 -> 300 | T93: ='Model inputs'!T154*'Model inputs'!AA266*'Model inputs'!AA264 -> 337.5 | U93: ='Model inputs'!U154*'Model inputs'!AA266*'Model inputs'!AA264 -> 375 | V93: ='Model inputs'!V154*'Model inputs'!AA266*'Model inputs'!AA264 -> 412.5 | W93: ='Model inputs'!W154*'Model inputs'!AA266*'Model inputs'!AA264 -> 450 | X93: ='Model inputs'!X154*'Model inputs'!AA266*'Model inputs'!AA264 -> 450 | Y93: ='Model inputs'!Y154*'Model inputs'!AA266*'Model inputs'!AA264 -> 450 | Z93: ='Model inputs'!Z154*'Model inputs'!AA266*'Model inputs'!AA264 -> 450
A94: Account support cost | C94: =SUM('Model inputs'!C95,'Model inputs'!C96,'Model inputs'!C97,'Model inputs'!C98,'Model inputs'!C99) -> 0 | D94: =SUM('Model inputs'!D95,'Model inputs'!D96,'Model inputs'!D97,'Model inputs'!D98,'Model inputs'!D99) -> 0 | E94: =SUM('Model inputs'!E95,'Model inputs'!E96,'Model inputs'!E97,'Model inputs'!E98,'Model inputs'!E99) -> 0 | F94: =SUM('Model inputs'!F95,'Model inputs'!F96,'Model inputs'!F97,'Model inputs'!F98,'Model inputs'!F99) -> 0 | G94: =SUM('Model inputs'!G95,'Model inputs'!G96,'Model inputs'!G97,'Model inputs'!G98,'Model inputs'!G99) -> 0 | H94: =SUM('Model inputs'!H95,'Model inputs'!H96,'Model inputs'!H97,'Model inputs'!H98,'Model inputs'!H99) -> 0 | I94: =SUM('Model inputs'!I95,'Model inputs'!I96,'Model inputs'!I97,'Model inputs'!I98,'Model inputs'!I99) -> 0 | J94: =SUM('Model inputs'!J95,'Model inputs'!J96,'Model inputs'!J97,'Model inputs'!J98,'Model inputs'!J99) -> 0 | K94: =SUM('Model inputs'!K95,'Model inputs'!K96,'Model inputs'!K97,'Model inputs'!K98,'Model inputs'!K99) -> 0 | L94: ="" | M94: ="" | N94: ="" | O94: ="" | P94: ="" | Q94: ="" | R94: ="" | S94: ="" | ... Z94: =""
A95: Account support cost > Annual deal-team | C95: =0 -> 0 | D95: =0 -> 0 | E95: =0 -> 0 | F95: =0 -> 0 | G95: =0 -> 0 | H95: =0 -> 0 | I95: =0 -> 0 | J95: =0 -> 0 | K95: =0 -> 0 | L95: ='Model inputs'!L155*'Model inputs'!AA267*'Model inputs'!AA265 -> 0 | M95: ='Model inputs'!M155*'Model inputs'!AA267*'Model inputs'!AA265 -> 0 | N95: ='Model inputs'!N155*'Model inputs'!AA267*'Model inputs'!AA265 -> 60 | O95: ='Model inputs'!O155*'Model inputs'!AA267*'Model inputs'!AA265 -> 60 | P95: ='Model inputs'!P155*'Model inputs'!AA267*'Model inputs'!AA265 -> 60 | Q95: ='Model inputs'!Q155*'Model inputs'!AA267*'Model inputs'!AA265 -> 60 | R95: ='Model inputs'!R155*'Model inputs'!AA267*'Model inputs'!AA265 -> 60 | S95: ='Model inputs'!S155*'Model inputs'!AA267*'Model inputs'!AA265 -> 60 | T95: ='Model inputs'!T155*'Model inputs'!AA267*'Model inputs'!AA265 -> 60 | U95: ='Model inputs'!U155*'Model inputs'!AA267*'Model inputs'!AA265 -> 60 | V95: ='Model inputs'!V155*'Model inputs'!AA267*'Model inputs'!AA265 -> 60 | W95: ='Model inputs'!W155*'Model inputs'!AA267*'Model inputs'!AA265 -> 60 | X95: ='Model inputs'!X155*'Model inputs'!AA267*'Model inputs'!AA265 -> 60 | Y95: ='Model inputs'!Y155*'Model inputs'!AA267*'Model inputs'!AA265 -> 60 | Z95: ='Model inputs'!Z155*'Model inputs'!AA267*'Model inputs'!AA265 -> 60
A96: Account support cost > Hybrid | C96: =0 -> 0 | D96: =0 -> 0 | E96: =0 -> 0 | F96: =0 -> 0 | G96: =0 -> 0 | H96: =0 -> 0 | I96: =0 -> 0 | J96: =0 -> 0 | K96: =0 -> 0 | L96: ='Model inputs'!L155*'Model inputs'!AA267*'Model inputs'!AA265 -> 0 | M96: ='Model inputs'!M155*'Model inputs'!AA267*'Model inputs'!AA265 -> 0 | N96: ='Model inputs'!N155*'Model inputs'!AA267*'Model inputs'!AA265 -> 60 | O96: ='Model inputs'!O155*'Model inputs'!AA267*'Model inputs'!AA265 -> 60 | P96: ='Model inputs'!P155*'Model inputs'!AA267*'Model inputs'!AA265 -> 60 | Q96: ='Model inputs'!Q155*'Model inputs'!AA267*'Model inputs'!AA265 -> 60 | R96: ='Model inputs'!R155*'Model inputs'!AA267*'Model inputs'!AA265 -> 60 | S96: ='Model inputs'!S155*'Model inputs'!AA267*'Model inputs'!AA265 -> 60 | T96: ='Model inputs'!T155*'Model inputs'!AA267*'Model inputs'!AA265 -> 60 | U96: ='Model inputs'!U155*'Model inputs'!AA267*'Model inputs'!AA265 -> 60 | V96: ='Model inputs'!V155*'Model inputs'!AA267*'Model inputs'!AA265 -> 60 | W96: ='Model inputs'!W155*'Model inputs'!AA267*'Model inputs'!AA265 -> 60 | X96: ='Model inputs'!X155*'Model inputs'!AA267*'Model inputs'!AA265 -> 60 | Y96: ='Model inputs'!Y155*'Model inputs'!AA267*'Model inputs'!AA265 -> 60 | Z96: ='Model inputs'!Z155*'Model inputs'!AA267*'Model inputs'!AA265 -> 60
A97: Account support cost > Per audit — base | C97: =0 -> 0 | D97: =0 -> 0 | E97: =0 -> 0 | F97: =0 -> 0 | G97: =0 -> 0 | H97: =0 -> 0 | I97: =0 -> 0 | J97: =0 -> 0 | K97: =0 -> 0 | L97: ='Model inputs'!L155*'Model inputs'!AA267*'Model inputs'!AA265 -> 0 | M97: ='Model inputs'!M155*'Model inputs'!AA267*'Model inputs'!AA265 -> 0 | N97: ='Model inputs'!N155*'Model inputs'!AA267*'Model inputs'!AA265 -> 60 | O97: ='Model inputs'!O155*'Model inputs'!AA267*'Model inputs'!AA265 -> 60 | P97: ='Model inputs'!P155*'Model inputs'!AA267*'Model inputs'!AA265 -> 60 | Q97: ='Model inputs'!Q155*'Model inputs'!AA267*'Model inputs'!AA265 -> 60 | R97: ='Model inputs'!R155*'Model inputs'!AA267*'Model inputs'!AA265 -> 60 | S97: ='Model inputs'!S155*'Model inputs'!AA267*'Model inputs'!AA265 -> 60 | T97: ='Model inputs'!T155*'Model inputs'!AA267*'Model inputs'!AA265 -> 60 | U97: ='Model inputs'!U155*'Model inputs'!AA267*'Model inputs'!AA265 -> 60 | V97: ='Model inputs'!V155*'Model inputs'!AA267*'Model inputs'!AA265 -> 60 | W97: ='Model inputs'!W155*'Model inputs'!AA267*'Model inputs'!AA265 -> 60 | X97: ='Model inputs'!X155*'Model inputs'!AA267*'Model inputs'!AA265 -> 60 | Y97: ='Model inputs'!Y155*'Model inputs'!AA267*'Model inputs'!AA265 -> 60 | Z97: ='Model inputs'!Z155*'Model inputs'!AA267*'Model inputs'!AA265 -> 60
