Workbook

Sheet DealScope monthly model and pri
A1: DealScope monthly model and pricing alternatives
A2: DealScope — Model formulas · Main Scenario
A4: Variable / dimension | B4: 2026-10 | C4: 2026-11 | D4: 2026-12 | E4: 2027-01 | F4: 2027-02 | G4: 2027-03 | H4: 2027-04 | I4: 2027-05 | J4: 2027-06 | K4: 2027-07 | L4: 2027-08 | M4: 2027-09
A5: Projection month | B5: =DATEDIF('Model inputs'!O58,DATE(2026,10,1),"M")+1 -> 1 | C5: =DATEDIF('Model inputs'!O58,DATE(2026,11,1),"M")+1 -> 2 | D5: =DATEDIF('Model inputs'!O58,DATE(2026,12,1),"M")+1 -> 3 | E5: =DATEDIF('Model inputs'!O58,DATE(2027,1,1),"M")+1 -> 4 | F5: =DATEDIF('Model inputs'!O58,DATE(2027,2,1),"M")+1 -> 5 | G5: =DATEDIF('Model inputs'!O58,DATE(2027,3,1),"M")+1 -> 6 | H5: =DATEDIF('Model inputs'!O58,DATE(2027,4,1),"M")+1 -> 7 | I5: =DATEDIF('Model inputs'!O58,DATE(2027,5,1),"M")+1 -> 8 | J5: =DATEDIF('Model inputs'!O58,DATE(2027,6,1),"M")+1 -> 9 | K5: =DATEDIF('Model inputs'!O58,DATE(2027,7,1),"M")+1 -> 10 | L5: =DATEDIF('Model inputs'!O58,DATE(2027,8,1),"M")+1 -> 11 | M5: =DATEDIF('Model inputs'!O58,DATE(2027,9,1),"M")+1 -> 12
A6: Paying customer equivalents | B6: =IF(IF(IF(ISERROR('Model inputs'!O94=1),'Model inputs'!O94=1,IF('Model inputs'!O94="","",'Model inputs'!O94=1))="",FALSE,IF(ISERROR('Model inputs'!O94=1),'Model inputs'!O94=1,IF('Model inputs'!O94="","",'Model inputs'!O94=1))),'Model inputs'!O96*MIN(MAX(('DealScope monthly model and pri'!B5-'Model inputs'!O95)/'Model inputs'!O93,0),1),IF(IF(IF(ISERROR('DealScope monthly model and pri'!B5>'Model inputs'!O95),'DealScope monthly model and pri'!B5>'Model inputs'!O95,IF(OR('DealScope monthly model and pri'!B5="",'Model inputs'!O95=""),"",'DealScope monthly model and pri'!B5>'Model inputs'!O95))="",FALSE,IF(ISERROR('DealScope monthly model and pri'!B5>'Model inputs'!O95),'DealScope monthly model and pri'!B5>'Model inputs'!O95,IF(OR('DealScope monthly model and pri'!B5="",'Model inputs'!O95=""),"",'DealScope monthly model and pri'!B5>'Model inputs'!O95))),IF('Model inputs'!O96="","",'Model inputs'!O96),0)) -> 5 | C6: =IF(IF(IF(ISERROR('Model inputs'!O94=1),'Model inputs'!O94=1,IF('Model inputs'!O94="","",'Model inputs'!O94=1))="",FALSE,IF(ISERROR('Model inputs'!O94=1),'Model inputs'!O94=1,IF('Model inputs'!O94="","",'Model inputs'!O94=1))),'Model inputs'!O96*MIN(MAX(('DealScope monthly model and pri'!C5-'Model inputs'!O95)/'Model inputs'!O93,0),1),IF(IF(IF(ISERROR('DealScope monthly model and pri'!C5>'Model inputs'!O95),'DealScope monthly model and pri'!C5>'Model inputs'!O95,IF(OR('DealScope monthly model and pri'!C5="",'Model inputs'!O95=""),"",'DealScope monthly model and pri'!C5>'Model inputs'!O95))="",FALSE,IF(ISERROR('DealScope monthly model and pri'!C5>'Model inputs'!O95),'DealScope monthly model and pri'!C5>'Model inputs'!O95,IF(OR('DealScope monthly model and pri'!C5="",'Model inputs'!O95=""),"",'DealScope monthly model and pri'!C5>'Model inputs'!O95))),IF('Model inputs'!O96="","",'Model inputs'!O96),0)) -> 5 | D6: =IF(IF(IF(ISERROR('Model inputs'!O94=1),'Model inputs'!O94=1,IF('Model inputs'!O94="","",'Model inputs'!O94=1))="",FALSE,IF(ISERROR('Model inputs'!O94=1),'Model inputs'!O94=1,IF('Model inputs'!O94="","",'Model inputs'!O94=1))),'Model inputs'!O96*MIN(MAX(('DealScope monthly model and pri'!D5-'Model inputs'!O95)/'Model inputs'!O93,0),1),IF(IF(IF(ISERROR('DealScope monthly model and pri'!D5>'Model inputs'!O95),'DealScope monthly model and pri'!D5>'Model inputs'!O95,IF(OR('DealScope monthly model and pri'!D5="",'Model inputs'!O95=""),"",'DealScope monthly model and pri'!D5>'Model inputs'!O95))="",FALSE,IF(ISERROR('DealScope monthly model and pri'!D5>'Model inputs'!O95),'DealScope monthly model and pri'!D5>'Model inputs'!O95,IF(OR('DealScope monthly model and pri'!D5="",'Model inputs'!O95=""),"",'DealScope monthly model and pri'!D5>'Model inputs'!O95))),IF('Model inputs'!O96="","",'Model inputs'!O96),0)) -> 5 | E6: =IF(IF(IF(ISERROR('Model inputs'!O94=1),'Model inputs'!O94=1,IF('Model inputs'!O94="","",'Model inputs'!O94=1))="",FALSE,IF(ISERROR('Model inputs'!O94=1),'Model inputs'!O94=1,IF('Model inputs'!O94="","",'Model inputs'!O94=1))),'Model inputs'!O96*MIN(MAX(('DealScope monthly model and pri'!E5-'Model inputs'!O95)/'Model inputs'!O93,0),1),IF(IF(IF(ISERROR('DealScope monthly model and pri'!E5>'Model inputs'!O95),'DealScope monthly model and pri'!E5>'Model inputs'!O95,IF(OR('DealScope monthly model and pri'!E5="",'Model inputs'!O95=""),"",'DealScope monthly model and pri'!E5>'Model inputs'!O95))="",FALSE,IF(ISERROR('DealScope monthly model and pri'!E5>'Model inputs'!O95),'DealScope monthly model and pri'!E5>'Model inputs'!O95,IF(OR('DealScope monthly model and pri'!E5="",'Model inputs'!O95=""),"",'DealScope monthly model and pri'!E5>'Model inputs'!O95))),IF('Model inputs'!O96="","",'Model inputs'!O96),0)) -> 5 | F6: =IF(IF(IF(ISERROR('Model inputs'!O94=1),'Model inputs'!O94=1,IF('Model inputs'!O94="","",'Model inputs'!O94=1))="",FALSE,IF(ISERROR('Model inputs'!O94=1),'Model inputs'!O94=1,IF('Model inputs'!O94="","",'Model inputs'!O94=1))),'Model inputs'!O96*MIN(MAX(('DealScope monthly model and pri'!F5-'Model inputs'!O95)/'Model inputs'!O93,0),1),IF(IF(IF(ISERROR('DealScope monthly model and pri'!F5>'Model inputs'!O95),'DealScope monthly model and pri'!F5>'Model inputs'!O95,IF(OR('DealScope monthly model and pri'!F5="",'Model inputs'!O95=""),"",'DealScope monthly model and pri'!F5>'Model inputs'!O95))="",FALSE,IF(ISERROR('DealScope monthly model and pri'!F5>'Model inputs'!O95),'DealScope monthly model and pri'!F5>'Model inputs'!O95,IF(OR('DealScope monthly model and pri'!F5="",'Model inputs'!O95=""),"",'DealScope monthly model and pri'!F5>'Model inputs'!O95))),IF('Model inputs'!O96="","",'Model inputs'!O96),0)) -> 5 | G6: =IF(IF(IF(ISERROR('Model inputs'!O94=1),'Model inputs'!O94=1,IF('Model inputs'!O94="","",'Model inputs'!O94=1))="",FALSE,IF(ISERROR('Model inputs'!O94=1),'Model inputs'!O94=1,IF('Model inputs'!O94="","",'Model inputs'!O94=1))),'Model inputs'!O96*MIN(MAX(('DealScope monthly model and pri'!G5-'Model inputs'!O95)/'Model inputs'!O93,0),1),IF(IF(IF(ISERROR('DealScope monthly model and pri'!G5>'Model inputs'!O95),'DealScope monthly model and pri'!G5>'Model inputs'!O95,IF(OR('DealScope monthly model and pri'!G5="",'Model inputs'!O95=""),"",'DealScope monthly model and pri'!G5>'Model inputs'!O95))="",FALSE,IF(ISERROR('DealScope monthly model and pri'!G5>'Model inputs'!O95),'DealScope monthly model and pri'!G5>'Model inputs'!O95,IF(OR('DealScope monthly model and pri'!G5="",'Model inputs'!O95=""),"",'DealScope monthly model and pri'!G5>'Model inputs'!O95))),IF('Model inputs'!O96="","",'Model inputs'!O96),0)) -> 5 | H6: =IF(IF(IF(ISERROR('Model inputs'!O94=1),'Model inputs'!O94=1,IF('Model inputs'!O94="","",'Model inputs'!O94=1))="",FALSE,IF(ISERROR('Model inputs'!O94=1),'Model inputs'!O94=1,IF('Model inputs'!O94="","",'Model inputs'!O94=1))),'Model inputs'!O96*MIN(MAX(('DealScope monthly model and pri'!H5-'Model inputs'!O95)/'Model inputs'!O93,0),1),IF(IF(IF(ISERROR('DealScope monthly model and pri'!H5>'Model inputs'!O95),'DealScope monthly model and pri'!H5>'Model inputs'!O95,IF(OR('DealScope monthly model and pri'!H5="",'Model inputs'!O95=""),"",'DealScope monthly model and pri'!H5>'Model inputs'!O95))="",FALSE,IF(ISERROR('DealScope monthly model and pri'!H5>'Model inputs'!O95),'DealScope monthly model and pri'!H5>'Model inputs'!O95,IF(OR('DealScope monthly model and pri'!H5="",'Model inputs'!O95=""),"",'DealScope monthly model and pri'!H5>'Model inputs'!O95))),IF('Model inputs'!O96="","",'Model inputs'!O96),0)) -> 5 | I6: =IF(IF(IF(ISERROR('Model inputs'!O94=1),'Model inputs'!O94=1,IF('Model inputs'!O94="","",'Model inputs'!O94=1))="",FALSE,IF(ISERROR('Model inputs'!O94=1),'Model inputs'!O94=1,IF('Model inputs'!O94="","",'Model inputs'!O94=1))),'Model inputs'!O96*MIN(MAX(('DealScope monthly model and pri'!I5-'Model inputs'!O95)/'Model inputs'!O93,0),1),IF(IF(IF(ISERROR('DealScope monthly model and pri'!I5>'Model inputs'!O95),'DealScope monthly model and pri'!I5>'Model inputs'!O95,IF(OR('DealScope monthly model and pri'!I5="",'Model inputs'!O95=""),"",'DealScope monthly model and pri'!I5>'Model inputs'!O95))="",FALSE,IF(ISERROR('DealScope monthly model and pri'!I5>'Model inputs'!O95),'DealScope monthly model and pri'!I5>'Model inputs'!O95,IF(OR('DealScope monthly model and pri'!I5="",'Model inputs'!O95=""),"",'DealScope monthly model and pri'!I5>'Model inputs'!O95))),IF('Model inputs'!O96="","",'Model inputs'!O96),0)) -> 5 | J6: =IF(IF(IF(ISERROR('Model inputs'!O94=1),'Model inputs'!O94=1,IF('Model inputs'!O94="","",'Model inputs'!O94=1))="",FALSE,IF(ISERROR('Model inputs'!O94=1),'Model inputs'!O94=1,IF('Model inputs'!O94="","",'Model inputs'!O94=1))),'Model inputs'!O96*MIN(MAX(('DealScope monthly model and pri'!J5-'Model inputs'!O95)/'Model inputs'!O93,0),1),IF(IF(IF(ISERROR('DealScope monthly model and pri'!J5>'Model inputs'!O95),'DealScope monthly model and pri'!J5>'Model inputs'!O95,IF(OR('DealScope monthly model and pri'!J5="",'Model inputs'!O95=""),"",'DealScope monthly model and pri'!J5>'Model inputs'!O95))="",FALSE,IF(ISERROR('DealScope monthly model and pri'!J5>'Model inputs'!O95),'DealScope monthly model and pri'!J5>'Model inputs'!O95,IF(OR('DealScope monthly model and pri'!J5="",'Model inputs'!O95=""),"",'DealScope monthly model and pri'!J5>'Model inputs'!O95))),IF('Model inputs'!O96="","",'Model inputs'!O96),0)) -> 5 | K6: =IF(IF(IF(ISERROR('Model inputs'!O94=1),'Model inputs'!O94=1,IF('Model inputs'!O94="","",'Model inputs'!O94=1))="",FALSE,IF(ISERROR('Model inputs'!O94=1),'Model inputs'!O94=1,IF('Model inputs'!O94="","",'Model inputs'!O94=1))),'Model inputs'!O96*MIN(MAX(('DealScope monthly model and pri'!K5-'Model inputs'!O95)/'Model inputs'!O93,0),1),IF(IF(IF(ISERROR('DealScope monthly model and pri'!K5>'Model inputs'!O95),'DealScope monthly model and pri'!K5>'Model inputs'!O95,IF(OR('DealScope monthly model and pri'!K5="",'Model inputs'!O95=""),"",'DealScope monthly model and pri'!K5>'Model inputs'!O95))="",FALSE,IF(ISERROR('DealScope monthly model and pri'!K5>'Model inputs'!O95),'DealScope monthly model and pri'!K5>'Model inputs'!O95,IF(OR('DealScope monthly model and pri'!K5="",'Model inputs'!O95=""),"",'DealScope monthly model and pri'!K5>'Model inputs'!O95))),IF('Model inputs'!O96="","",'Model inputs'!O96),0)) -> 5 | L6: =IF(IF(IF(ISERROR('Model inputs'!O94=1),'Model inputs'!O94=1,IF('Model inputs'!O94="","",'Model inputs'!O94=1))="",FALSE,IF(ISERROR('Model inputs'!O94=1),'Model inputs'!O94=1,IF('Model inputs'!O94="","",'Model inputs'!O94=1))),'Model inputs'!O96*MIN(MAX(('DealScope monthly model and pri'!L5-'Model inputs'!O95)/'Model inputs'!O93,0),1),IF(IF(IF(ISERROR('DealScope monthly model and pri'!L5>'Model inputs'!O95),'DealScope monthly model and pri'!L5>'Model inputs'!O95,IF(OR('DealScope monthly model and pri'!L5="",'Model inputs'!O95=""),"",'DealScope monthly model and pri'!L5>'Model inputs'!O95))="",FALSE,IF(ISERROR('DealScope monthly model and pri'!L5>'Model inputs'!O95),'DealScope monthly model and pri'!L5>'Model inputs'!O95,IF(OR('DealScope monthly model and pri'!L5="",'Model inputs'!O95=""),"",'DealScope monthly model and pri'!L5>'Model inputs'!O95))),IF('Model inputs'!O96="","",'Model inputs'!O96),0)) -> 5 | M6: =IF(IF(IF(ISERROR('Model inputs'!O94=1),'Model inputs'!O94=1,IF('Model inputs'!O94="","",'Model inputs'!O94=1))="",FALSE,IF(ISERROR('Model inputs'!O94=1),'Model inputs'!O94=1,IF('Model inputs'!O94="","",'Model inputs'!O94=1))),'Model inputs'!O96*MIN(MAX(('DealScope monthly model and pri'!M5-'Model inputs'!O95)/'Model inputs'!O93,0),1),IF(IF(IF(ISERROR('DealScope monthly model and pri'!M5>'Model inputs'!O95),'DealScope monthly model and pri'!M5>'Model inputs'!O95,IF(OR('DealScope monthly model and pri'!M5="",'Model inputs'!O95=""),"",'DealScope monthly model and pri'!M5>'Model inputs'!O95))="",FALSE,IF(ISERROR('DealScope monthly model and pri'!M5>'Model inputs'!O95),'DealScope monthly model and pri'!M5>'Model inputs'!O95,IF(OR('DealScope monthly model and pri'!M5="",'Model inputs'!O95=""),"",'DealScope monthly model and pri'!M5>'Model inputs'!O95))),IF('Model inputs'!O96="","",'Model inputs'!O96),0)) -> 5
A7: New customer equivalents | B7: =MAX('DealScope monthly model and pri'!B6-IF(IF(IF(IF(ISERROR('DealScope monthly model and pri'!B5=1),'DealScope monthly model and pri'!B5=1,IF('DealScope monthly model and pri'!B5="","",'DealScope monthly model and pri'!B5=1))="",FALSE,IF(ISERROR('DealScope monthly model and pri'!B5=1),'DealScope monthly model and pri'!B5=1,IF('DealScope monthly model and pri'!B5="","",'DealScope monthly model and pri'!B5=1))),0,IF('Model inputs'!B68="","",'Model inputs'!B68))="",0,IF(IF(IF(ISERROR('DealScope monthly model and pri'!B5=1),'DealScope monthly model and pri'!B5=1,IF('DealScope monthly model and pri'!B5="","",'DealScope monthly model and pri'!B5=1))="",FALSE,IF(ISERROR('DealScope monthly model and pri'!B5=1),'DealScope monthly model and pri'!B5=1,IF('DealScope monthly model and pri'!B5="","",'DealScope monthly model and pri'!B5=1))),0,IF('Model inputs'!B68="","",'Model inputs'!B68))),0) -> 5 | C7: =MAX('DealScope monthly model and pri'!C6-IF(IF(IF(IF(ISERROR('DealScope monthly model and pri'!C5=1),'DealScope monthly model and pri'!C5=1,IF('DealScope monthly model and pri'!C5="","",'DealScope monthly model and pri'!C5=1))="",FALSE,IF(ISERROR('DealScope monthly model and pri'!C5=1),'DealScope monthly model and pri'!C5=1,IF('DealScope monthly model and pri'!C5="","",'DealScope monthly model and pri'!C5=1))),0,IF('DealScope monthly model and pri'!B6="","",'DealScope monthly model and pri'!B6))="",0,IF(IF(IF(ISERROR('DealScope monthly model and pri'!C5=1),'DealScope monthly model and pri'!C5=1,IF('DealScope monthly model and pri'!C5="","",'DealScope monthly model and pri'!C5=1))="",FALSE,IF(ISERROR('DealScope monthly model and pri'!C5=1),'DealScope monthly model and pri'!C5=1,IF('DealScope monthly model and pri'!C5="","",'DealScope monthly model and pri'!C5=1))),0,IF('DealScope monthly model and pri'!B6="","",'DealScope monthly model and pri'!B6))),0) -> 0 | D7: =MAX('DealScope monthly model and pri'!D6-IF(IF(IF(IF(ISERROR('DealScope monthly model and pri'!D5=1),'DealScope monthly model and pri'!D5=1,IF('DealScope monthly model and pri'!D5="","",'DealScope monthly model and pri'!D5=1))="",FALSE,IF(ISERROR('DealScope monthly model and pri'!D5=1),'DealScope monthly model and pri'!D5=1,IF('DealScope monthly model and pri'!D5="","",'DealScope monthly model and pri'!D5=1))),0,IF('DealScope monthly model and pri'!C6="","",'DealScope monthly model and pri'!C6))="",0,IF(IF(IF(ISERROR('DealScope monthly model and pri'!D5=1),'DealScope monthly model and pri'!D5=1,IF('DealScope monthly model and pri'!D5="","",'DealScope monthly model and pri'!D5=1))="",FALSE,IF(ISERROR('DealScope monthly model and pri'!D5=1),'DealScope monthly model and pri'!D5=1,IF('DealScope monthly model and pri'!D5="","",'DealScope monthly model and pri'!D5=1))),0,IF('DealScope monthly model and pri'!C6="","",'DealScope monthly model and pri'!C6))),0) -> 0 | E7: =MAX('DealScope monthly model and pri'!E6-IF(IF(IF(IF(ISERROR('DealScope monthly model and pri'!E5=1),'DealScope monthly model and pri'!E5=1,IF('DealScope monthly model and pri'!E5="","",'DealScope monthly model and pri'!E5=1))="",FALSE,IF(ISERROR('DealScope monthly model and pri'!E5=1),'DealScope monthly model and pri'!E5=1,IF('DealScope monthly model and pri'!E5="","",'DealScope monthly model and pri'!E5=1))),0,IF('DealScope monthly model and pri'!D6="","",'DealScope monthly model and pri'!D6))="",0,IF(IF(IF(ISERROR('DealScope monthly model and pri'!E5=1),'DealScope monthly model and pri'!E5=1,IF('DealScope monthly model and pri'!E5="","",'DealScope monthly model and pri'!E5=1))="",FALSE,IF(ISERROR('DealScope monthly model and pri'!E5=1),'DealScope monthly model and pri'!E5=1,IF('DealScope monthly model and pri'!E5="","",'DealScope monthly model and pri'!E5=1))),0,IF('DealScope monthly model and pri'!D6="","",'DealScope monthly model and pri'!D6))),0) -> 0 | F7: =MAX('DealScope monthly model and pri'!F6-IF(IF(IF(IF(ISERROR('DealScope monthly model and pri'!F5=1),'DealScope monthly model and pri'!F5=1,IF('DealScope monthly model and pri'!F5="","",'DealScope monthly model and pri'!F5=1))="",FALSE,IF(ISERROR('DealScope monthly model and pri'!F5=1),'DealScope monthly model and pri'!F5=1,IF('DealScope monthly model and pri'!F5="","",'DealScope monthly model and pri'!F5=1))),0,IF('DealScope monthly model and pri'!E6="","",'DealScope monthly model and pri'!E6))="",0,IF(IF(IF(ISERROR('DealScope monthly model and pri'!F5=1),'DealScope monthly model and pri'!F5=1,IF('DealScope monthly model and pri'!F5="","",'DealScope monthly model and pri'!F5=1))="",FALSE,IF(ISERROR('DealScope monthly model and pri'!F5=1),'DealScope monthly model and pri'!F5=1,IF('DealScope monthly model and pri'!F5="","",'DealScope monthly model and pri'!F5=1))),0,IF('DealScope monthly model and pri'!E6="","",'DealScope monthly model and pri'!E6))),0) -> 0 | G7: =MAX('DealScope monthly model and pri'!G6-IF(IF(IF(IF(ISERROR('DealScope monthly model and pri'!G5=1),'DealScope monthly model and pri'!G5=1,IF('DealScope monthly model and pri'!G5="","",'DealScope monthly model and pri'!G5=1))="",FALSE,IF(ISERROR('DealScope monthly model and pri'!G5=1),'DealScope monthly model and pri'!G5=1,IF('DealScope monthly model and pri'!G5="","",'DealScope monthly model and pri'!G5=1))),0,IF('DealScope monthly model and pri'!F6="","",'DealScope monthly model and pri'!F6))="",0,IF(IF(IF(ISERROR('DealScope monthly model and pri'!G5=1),'DealScope monthly model and pri'!G5=1,IF('DealScope monthly model and pri'!G5="","",'DealScope monthly model and pri'!G5=1))="",FALSE,IF(ISERROR('DealScope monthly model and pri'!G5=1),'DealScope monthly model and pri'!G5=1,IF('DealScope monthly model and pri'!G5="","",'DealScope monthly model and pri'!G5=1))),0,IF('DealScope monthly model and pri'!F6="","",'DealScope monthly model and pri'!F6))),0) -> 0 | H7: =MAX('DealScope monthly model and pri'!H6-IF(IF(IF(IF(ISERROR('DealScope monthly model and pri'!H5=1),'DealScope monthly model and pri'!H5=1,IF('DealScope monthly model and pri'!H5="","",'DealScope monthly model and pri'!H5=1))="",FALSE,IF(ISERROR('DealScope monthly model and pri'!H5=1),'DealScope monthly model and pri'!H5=1,IF('DealScope monthly model and pri'!H5="","",'DealScope monthly model and pri'!H5=1))),0,IF('DealScope monthly model and pri'!G6="","",'DealScope monthly model and pri'!G6))="",0,IF(IF(IF(ISERROR('DealScope monthly model and pri'!H5=1),'DealScope monthly model and pri'!H5=1,IF('DealScope monthly model and pri'!H5="","",'DealScope monthly model and pri'!H5=1))="",FALSE,IF(ISERROR('DealScope monthly model and pri'!H5=1),'DealScope monthly model and pri'!H5=1,IF('DealScope monthly model and pri'!H5="","",'DealScope monthly model and pri'!H5=1))),0,IF('DealScope monthly model and pri'!G6="","",'DealScope monthly model and pri'!G6))),0) -> 0 | I7: =MAX('DealScope monthly model and pri'!I6-IF(IF(IF(IF(ISERROR('DealScope monthly model and pri'!I5=1),'DealScope monthly model and pri'!I5=1,IF('DealScope monthly model and pri'!I5="","",'DealScope monthly model and pri'!I5=1))="",FALSE,IF(ISERROR('DealScope monthly model and pri'!I5=1),'DealScope monthly model and pri'!I5=1,IF('DealScope monthly model and pri'!I5="","",'DealScope monthly model and pri'!I5=1))),0,IF('DealScope monthly model and pri'!H6="","",'DealScope monthly model and pri'!H6))="",0,IF(IF(IF(ISERROR('DealScope monthly model and pri'!I5=1),'DealScope monthly model and pri'!I5=1,IF('DealScope monthly model and pri'!I5="","",'DealScope monthly model and pri'!I5=1))="",FALSE,IF(ISERROR('DealScope monthly model and pri'!I5=1),'DealScope monthly model and pri'!I5=1,IF('DealScope monthly model and pri'!I5="","",'DealScope monthly model and pri'!I5=1))),0,IF('DealScope monthly model and pri'!H6="","",'DealScope monthly model and pri'!H6))),0) -> 0 | J7: =MAX('DealScope monthly model and pri'!J6-IF(IF(IF(IF(ISERROR('DealScope monthly model and pri'!J5=1),'DealScope monthly model and pri'!J5=1,IF('DealScope monthly model and pri'!J5="","",'DealScope monthly model and pri'!J5=1))="",FALSE,IF(ISERROR('DealScope monthly model and pri'!J5=1),'DealScope monthly model and pri'!J5=1,IF('DealScope monthly model and pri'!J5="","",'DealScope monthly model and pri'!J5=1))),0,IF('DealScope monthly model and pri'!I6="","",'DealScope monthly model and pri'!I6))="",0,IF(IF(IF(ISERROR('DealScope monthly model and pri'!J5=1),'DealScope monthly model and pri'!J5=1,IF('DealScope monthly model and pri'!J5="","",'DealScope monthly model and pri'!J5=1))="",FALSE,IF(ISERROR('DealScope monthly model and pri'!J5=1),'DealScope monthly model and pri'!J5=1,IF('DealScope monthly model and pri'!J5="","",'DealScope monthly model and pri'!J5=1))),0,IF('DealScope monthly model and pri'!I6="","",'DealScope monthly model and pri'!I6))),0) -> 0 | ... M7: =MAX('DealScope monthly model and pri'!M6-IF(IF(IF(IF(ISERROR('DealScope monthly model and pri'!M5=1),'DealScope monthly model and pri'!M5=1,IF('DealScope monthly model and pri'!M5="","",'DealScope monthly model and pri'!M5=1))="",FALSE,IF(ISERROR('DealScope monthly model and pri'!M5=1),'DealScope monthly model and pri'!M5=1,IF('DealScope monthly model and pri'!M5="","",'DealScope monthly model and pri'!M5=1))),0,IF('DealScope monthly model and pri'!L6="","",'DealScope monthly model and pri'!L6))="",0,IF(IF(IF(ISERROR('DealScope monthly model and pri'!M5=1),'DealScope monthly model and pri'!M5=1,IF('DealScope monthly model and pri'!M5="","",'DealScope monthly model and pri'!M5=1))="",FALSE,IF(ISERROR('DealScope monthly model and pri'!M5=1),'DealScope monthly model and pri'!M5=1,IF('DealScope monthly model and pri'!M5="","",'DealScope monthly model and pri'!M5=1))),0,IF('DealScope monthly model and pri'!L6="","",'DealScope monthly model and pri'!L6))),0) -> 0
A8: Fixed costs | B8: ='Model inputs'!O60+'Model inputs'!O84+'Model inputs'!O42+'Model inputs'!O59+'Model inputs'!O82+IF(IF(IF(IF(ISERROR('DealScope monthly model and pri'!B5>='Model inputs'!O27),'DealScope monthly model and pri'!B5>='Model inputs'!O27,IF(OR('DealScope monthly model and pri'!B5="",'Model inputs'!O27=""),"",'DealScope monthly model and pri'!B5>='Model inputs'!O27))="",FALSE,IF(ISERROR('DealScope monthly model and pri'!B5>='Model inputs'!O27),'DealScope monthly model and pri'!B5>='Model inputs'!O27,IF(OR('DealScope monthly model and pri'!B5="",'Model inputs'!O27=""),"",'DealScope monthly model and pri'!B5>='Model inputs'!O27))),IF('Model inputs'!O26="","",'Model inputs'!O26),0)="",0,IF(IF(IF(ISERROR('DealScope monthly model and pri'!B5>='Model inputs'!O27),'DealScope monthly model and pri'!B5>='Model inputs'!O27,IF(OR('DealScope monthly model and pri'!B5="",'Model inputs'!O27=""),"",'DealScope monthly model and pri'!B5>='Model inputs'!O27))="",FALSE,IF(ISERROR('DealScope monthly model and pri'!B5>='Model inputs'!O27),'DealScope monthly model and pri'!B5>='Model inputs'!O27,IF(OR('DealScope monthly model and pri'!B5="",'Model inputs'!O27=""),"",'DealScope monthly model and pri'!B5>='Model inputs'!O27))),IF('Model inputs'!O26="","",'Model inputs'!O26),0)) -> 750 | C8: ='Model inputs'!O60+'Model inputs'!O84+'Model inputs'!O42+'Model inputs'!O59+'Model inputs'!O82+IF(IF(IF(IF(ISERROR('DealScope monthly model and pri'!C5>='Model inputs'!O27),'DealScope monthly model and pri'!C5>='Model inputs'!O27,IF(OR('DealScope monthly model and pri'!C5="",'Model inputs'!O27=""),"",'DealScope monthly model and pri'!C5>='Model inputs'!O27))="",FALSE,IF(ISERROR('DealScope monthly model and pri'!C5>='Model inputs'!O27),'DealScope monthly model and pri'!C5>='Model inputs'!O27,IF(OR('DealScope monthly model and pri'!C5="",'Model inputs'!O27=""),"",'DealScope monthly model and pri'!C5>='Model inputs'!O27))),IF('Model inputs'!O26="","",'Model inputs'!O26),0)="",0,IF(IF(IF(ISERROR('DealScope monthly model and pri'!C5>='Model inputs'!O27),'DealScope monthly model and pri'!C5>='Model inputs'!O27,IF(OR('DealScope monthly model and pri'!C5="",'Model inputs'!O27=""),"",'DealScope monthly model and pri'!C5>='Model inputs'!O27))="",FALSE,IF(ISERROR('DealScope monthly model and pri'!C5>='Model inputs'!O27),'DealScope monthly model and pri'!C5>='Model inputs'!O27,IF(OR('DealScope monthly model and pri'!C5="",'Model inputs'!O27=""),"",'DealScope monthly model and pri'!C5>='Model inputs'!O27))),IF('Model inputs'!O26="","",'Model inputs'!O26),0)) -> 750 | D8: ='Model inputs'!O60+'Model inputs'!O84+'Model inputs'!O42+'Model inputs'!O59+'Model inputs'!O82+IF(IF(IF(IF(ISERROR('DealScope monthly model and pri'!D5>='Model inputs'!O27),'DealScope monthly model and pri'!D5>='Model inputs'!O27,IF(OR('DealScope monthly model and pri'!D5="",'Model inputs'!O27=""),"",'DealScope monthly model and pri'!D5>='Model inputs'!O27))="",FALSE,IF(ISERROR('DealScope monthly model and pri'!D5>='Model inputs'!O27),'DealScope monthly model and pri'!D5>='Model inputs'!O27,IF(OR('DealScope monthly model and pri'!D5="",'Model inputs'!O27=""),"",'DealScope monthly model and pri'!D5>='Model inputs'!O27))),IF('Model inputs'!O26="","",'Model inputs'!O26),0)="",0,IF(IF(IF(ISERROR('DealScope monthly model and pri'!D5>='Model inputs'!O27),'DealScope monthly model and pri'!D5>='Model inputs'!O27,IF(OR('DealScope monthly model and pri'!D5="",'Model inputs'!O27=""),"",'DealScope monthly model and pri'!D5>='Model inputs'!O27))="",FALSE,IF(ISERROR('DealScope monthly model and pri'!D5>='Model inputs'!O27),'DealScope monthly model and pri'!D5>='Model inputs'!O27,IF(OR('DealScope monthly model and pri'!D5="",'Model inputs'!O27=""),"",'DealScope monthly model and pri'!D5>='Model inputs'!O27))),IF('Model inputs'!O26="","",'Model inputs'!O26),0)) -> 750 | E8: ='Model inputs'!O60+'Model inputs'!O84+'Model inputs'!O42+'Model inputs'!O59+'Model inputs'!O82+IF(IF(IF(IF(ISERROR('DealScope monthly model and pri'!E5>='Model inputs'!O27),'DealScope monthly model and pri'!E5>='Model inputs'!O27,IF(OR('DealScope monthly model and pri'!E5="",'Model inputs'!O27=""),"",'DealScope monthly model and pri'!E5>='Model inputs'!O27))="",FALSE,IF(ISERROR('DealScope monthly model and pri'!E5>='Model inputs'!O27),'DealScope monthly model and pri'!E5>='Model inputs'!O27,IF(OR('DealScope monthly model and pri'!E5="",'Model inputs'!O27=""),"",'DealScope monthly model and pri'!E5>='Model inputs'!O27))),IF('Model inputs'!O26="","",'Model inputs'!O26),0)="",0,IF(IF(IF(ISERROR('DealScope monthly model and pri'!E5>='Model inputs'!O27),'DealScope monthly model and pri'!E5>='Model inputs'!O27,IF(OR('DealScope monthly model and pri'!E5="",'Model inputs'!O27=""),"",'DealScope monthly model and pri'!E5>='Model inputs'!O27))="",FALSE,IF(ISERROR('DealScope monthly model and pri'!E5>='Model inputs'!O27),'DealScope monthly model and pri'!E5>='Model inputs'!O27,IF(OR('DealScope monthly model and pri'!E5="",'Model inputs'!O27=""),"",'DealScope monthly model and pri'!E5>='Model inputs'!O27))),IF('Model inputs'!O26="","",'Model inputs'!O26),0)) -> 750 | F8: ='Model inputs'!O60+'Model inputs'!O84+'Model inputs'!O42+'Model inputs'!O59+'Model inputs'!O82+IF(IF(IF(IF(ISERROR('DealScope monthly model and pri'!F5>='Model inputs'!O27),'DealScope monthly model and pri'!F5>='Model inputs'!O27,IF(OR('DealScope monthly model and pri'!F5="",'Model inputs'!O27=""),"",'DealScope monthly model and pri'!F5>='Model inputs'!O27))="",FALSE,IF(ISERROR('DealScope monthly model and pri'!F5>='Model inputs'!O27),'DealScope monthly model and pri'!F5>='Model inputs'!O27,IF(OR('DealScope monthly model and pri'!F5="",'Model inputs'!O27=""),"",'DealScope monthly model and pri'!F5>='Model inputs'!O27))),IF('Model inputs'!O26="","",'Model inputs'!O26),0)="",0,IF(IF(IF(ISERROR('DealScope monthly model and pri'!F5>='Model inputs'!O27),'DealScope monthly model and pri'!F5>='Model inputs'!O27,IF(OR('DealScope monthly model and pri'!F5="",'Model inputs'!O27=""),"",'DealScope monthly model and pri'!F5>='Model inputs'!O27))="",FALSE,IF(ISERROR('DealScope monthly model and pri'!F5>='Model inputs'!O27),'DealScope monthly model and pri'!F5>='Model inputs'!O27,IF(OR('DealScope monthly model and pri'!F5="",'Model inputs'!O27=""),"",'DealScope monthly model and pri'!F5>='Model inputs'!O27))),IF('Model inputs'!O26="","",'Model inputs'!O26),0)) -> 750 | G8: ='Model inputs'!O60+'Model inputs'!O84+'Model inputs'!O42+'Model inputs'!O59+'Model inputs'!O82+IF(IF(IF(IF(ISERROR('DealScope monthly model and pri'!G5>='Model inputs'!O27),'DealScope monthly model and pri'!G5>='Model inputs'!O27,IF(OR('DealScope monthly model and pri'!G5="",'Model inputs'!O27=""),"",'DealScope monthly model and pri'!G5>='Model inputs'!O27))="",FALSE,IF(ISERROR('DealScope monthly model and pri'!G5>='Model inputs'!O27),'DealScope monthly model and pri'!G5>='Model inputs'!O27,IF(OR('DealScope monthly model and pri'!G5="",'Model inputs'!O27=""),"",'DealScope monthly model and pri'!G5>='Model inputs'!O27))),IF('Model inputs'!O26="","",'Model inputs'!O26),0)="",0,IF(IF(IF(ISERROR('DealScope monthly model and pri'!G5>='Model inputs'!O27),'DealScope monthly model and pri'!G5>='Model inputs'!O27,IF(OR('DealScope monthly model and pri'!G5="",'Model inputs'!O27=""),"",'DealScope monthly model and pri'!G5>='Model inputs'!O27))="",FALSE,IF(ISERROR('DealScope monthly model and pri'!G5>='Model inputs'!O27),'DealScope monthly model and pri'!G5>='Model inputs'!O27,IF(OR('DealScope monthly model and pri'!G5="",'Model inputs'!O27=""),"",'DealScope monthly model and pri'!G5>='Model inputs'!O27))),IF('Model inputs'!O26="","",'Model inputs'!O26),0)) -> 1250 | H8: ='Model inputs'!O60+'Model inputs'!O84+'Model inputs'!O42+'Model inputs'!O59+'Model inputs'!O82+IF(IF(IF(IF(ISERROR('DealScope monthly model and pri'!H5>='Model inputs'!O27),'DealScope monthly model and pri'!H5>='Model inputs'!O27,IF(OR('DealScope monthly model and pri'!H5="",'Model inputs'!O27=""),"",'DealScope monthly model and pri'!H5>='Model inputs'!O27))="",FALSE,IF(ISERROR('DealScope monthly model and pri'!H5>='Model inputs'!O27),'DealScope monthly model and pri'!H5>='Model inputs'!O27,IF(OR('DealScope monthly model and pri'!H5="",'Model inputs'!O27=""),"",'DealScope monthly model and pri'!H5>='Model inputs'!O27))),IF('Model inputs'!O26="","",'Model inputs'!O26),0)="",0,IF(IF(IF(ISERROR('DealScope monthly model and pri'!H5>='Model inputs'!O27),'DealScope monthly model and pri'!H5>='Model inputs'!O27,IF(OR('DealScope monthly model and pri'!H5="",'Model inputs'!O27=""),"",'DealScope monthly model and pri'!H5>='Model inputs'!O27))="",FALSE,IF(ISERROR('DealScope monthly model and pri'!H5>='Model inputs'!O27),'DealScope monthly model and pri'!H5>='Model inputs'!O27,IF(OR('DealScope monthly model and pri'!H5="",'Model inputs'!O27=""),"",'DealScope monthly model and pri'!H5>='Model inputs'!O27))),IF('Model inputs'!O26="","",'Model inputs'!O26),0)) -> 1250 | I8: ='Model inputs'!O60+'Model inputs'!O84+'Model inputs'!O42+'Model inputs'!O59+'Model inputs'!O82+IF(IF(IF(IF(ISERROR('DealScope monthly model and pri'!I5>='Model inputs'!O27),'DealScope monthly model and pri'!I5>='Model inputs'!O27,IF(OR('DealScope monthly model and pri'!I5="",'Model inputs'!O27=""),"",'DealScope monthly model and pri'!I5>='Model inputs'!O27))="",FALSE,IF(ISERROR('DealScope monthly model and pri'!I5>='Model inputs'!O27),'DealScope monthly model and pri'!I5>='Model inputs'!O27,IF(OR('DealScope monthly model and pri'!I5="",'Model inputs'!O27=""),"",'DealScope monthly model and pri'!I5>='Model inputs'!O27))),IF('Model inputs'!O26="","",'Model inputs'!O26),0)="",0,IF(IF(IF(ISERROR('DealScope monthly model and pri'!I5>='Model inputs'!O27),'DealScope monthly model and pri'!I5>='Model inputs'!O27,IF(OR('DealScope monthly model and pri'!I5="",'Model inputs'!O27=""),"",'DealScope monthly model and pri'!I5>='Model inputs'!O27))="",FALSE,IF(ISERROR('DealScope monthly model and pri'!I5>='Model inputs'!O27),'DealScope monthly model and pri'!I5>='Model inputs'!O27,IF(OR('DealScope monthly model and pri'!I5="",'Model inputs'!O27=""),"",'DealScope monthly model and pri'!I5>='Model inputs'!O27))),IF('Model inputs'!O26="","",'Model inputs'!O26),0)) -> 1250 | J8: ='Model inputs'!O60+'Model inputs'!O84+'Model inputs'!O42+'Model inputs'!O59+'Model inputs'!O82+IF(IF(IF(IF(ISERROR('DealScope monthly model and pri'!J5>='Model inputs'!O27),'DealScope monthly model and pri'!J5>='Model inputs'!O27,IF(OR('DealScope monthly model and pri'!J5="",'Model inputs'!O27=""),"",'DealScope monthly model and pri'!J5>='Model inputs'!O27))="",FALSE,IF(ISERROR('DealScope monthly model and pri'!J5>='Model inputs'!O27),'DealScope monthly model and pri'!J5>='Model inputs'!O27,IF(OR('DealScope monthly model and pri'!J5="",'Model inputs'!O27=""),"",'DealScope monthly model and pri'!J5>='Model inputs'!O27))),IF('Model inputs'!O26="","",'Model inputs'!O26),0)="",0,IF(IF(IF(ISERROR('DealScope monthly model and pri'!J5>='Model inputs'!O27),'DealScope monthly model and pri'!J5>='Model inputs'!O27,IF(OR('DealScope monthly model and pri'!J5="",'Model inputs'!O27=""),"",'DealScope monthly model and pri'!J5>='Model inputs'!O27))="",FALSE,IF(ISERROR('DealScope monthly model and pri'!J5>='Model inputs'!O27),'DealScope monthly model and pri'!J5>='Model inputs'!O27,IF(OR('DealScope monthly model and pri'!J5="",'Model inputs'!O27=""),"",'DealScope monthly model and pri'!J5>='Model inputs'!O27))),IF('Model inputs'!O26="","",'Model inputs'!O26),0)) -> 1250 | K8: ='Model inputs'!O60+'Model inputs'!O84+'Model inputs'!O42+'Model inputs'!O59+'Model inputs'!O82+IF(IF(IF(IF(ISERROR('DealScope monthly model and pri'!K5>='Model inputs'!O27),'DealScope monthly model and pri'!K5>='Model inputs'!O27,IF(OR('DealScope monthly model and pri'!K5="",'Model inputs'!O27=""),"",'DealScope monthly model and pri'!K5>='Model inputs'!O27))="",FALSE,IF(ISERROR('DealScope monthly model and pri'!K5>='Model inputs'!O27),'DealScope monthly model and pri'!K5>='Model inputs'!O27,IF(OR('DealScope monthly model and pri'!K5="",'Model inputs'!O27=""),"",'DealScope monthly model and pri'!K5>='Model inputs'!O27))),IF('Model inputs'!O26="","",'Model inputs'!O26),0)="",0,IF(IF(IF(ISERROR('DealScope monthly model and pri'!K5>='Model inputs'!O27),'DealScope monthly model and pri'!K5>='Model inputs'!O27,IF(OR('DealScope monthly model and pri'!K5="",'Model inputs'!O27=""),"",'DealScope monthly model and pri'!K5>='Model inputs'!O27))="",FALSE,IF(ISERROR('DealScope monthly model and pri'!K5>='Model inputs'!O27),'DealScope monthly model and pri'!K5>='Model inputs'!O27,IF(OR('DealScope monthly model and pri'!K5="",'Model inputs'!O27=""),"",'DealScope monthly model and pri'!K5>='Model inputs'!O27))),IF('Model inputs'!O26="","",'Model inputs'!O26),0)) -> 1250 | L8: ='Model inputs'!O60+'Model inputs'!O84+'Model inputs'!O42+'Model inputs'!O59+'Model inputs'!O82+IF(IF(IF(IF(ISERROR('DealScope monthly model and pri'!L5>='Model inputs'!O27),'DealScope monthly model and pri'!L5>='Model inputs'!O27,IF(OR('DealScope monthly model and pri'!L5="",'Model inputs'!O27=""),"",'DealScope monthly model and pri'!L5>='Model inputs'!O27))="",FALSE,IF(ISERROR('DealScope monthly model and pri'!L5>='Model inputs'!O27),'DealScope monthly model and pri'!L5>='Model inputs'!O27,IF(OR('DealScope monthly model and pri'!L5="",'Model inputs'!O27=""),"",'DealScope monthly model and pri'!L5>='Model inputs'!O27))),IF('Model inputs'!O26="","",'Model inputs'!O26),0)="",0,IF(IF(IF(ISERROR('DealScope monthly model and pri'!L5>='Model inputs'!O27),'DealScope monthly model and pri'!L5>='Model inputs'!O27,IF(OR('DealScope monthly model and pri'!L5="",'Model inputs'!O27=""),"",'DealScope monthly model and pri'!L5>='Model inputs'!O27))="",FALSE,IF(ISERROR('DealScope monthly model and pri'!L5>='Model inputs'!O27),'DealScope monthly model and pri'!L5>='Model inputs'!O27,IF(OR('DealScope monthly model and pri'!L5="",'Model inputs'!O27=""),"",'DealScope monthly model and pri'!L5>='Model inputs'!O27))),IF('Model inputs'!O26="","",'Model inputs'!O26),0)) -> 1250 | M8: ='Model inputs'!O60+'Model inputs'!O84+'Model inputs'!O42+'Model inputs'!O59+'Model inputs'!O82+IF(IF(IF(IF(ISERROR('DealScope monthly model and pri'!M5>='Model inputs'!O27),'DealScope monthly model and pri'!M5>='Model inputs'!O27,IF(OR('DealScope monthly model and pri'!M5="",'Model inputs'!O27=""),"",'DealScope monthly model and pri'!M5>='Model inputs'!O27))="",FALSE,IF(ISERROR('DealScope monthly model and pri'!M5>='Model inputs'!O27),'DealScope monthly model and pri'!M5>='Model inputs'!O27,IF(OR('DealScope monthly model and pri'!M5="",'Model inputs'!O27=""),"",'DealScope monthly model and pri'!M5>='Model inputs'!O27))),IF('Model inputs'!O26="","",'Model inputs'!O26),0)="",0,IF(IF(IF(ISERROR('DealScope monthly model and pri'!M5>='Model inputs'!O27),'DealScope monthly model and pri'!M5>='Model inputs'!O27,IF(OR('DealScope monthly model and pri'!M5="",'Model inputs'!O27=""),"",'DealScope monthly model and pri'!M5>='Model inputs'!O27))="",FALSE,IF(ISERROR('DealScope monthly model and pri'!M5>='Model inputs'!O27),'DealScope monthly model and pri'!M5>='Model inputs'!O27,IF(OR('DealScope monthly model and pri'!M5="",'Model inputs'!O27=""),"",'DealScope monthly model and pri'!M5>='Model inputs'!O27))),IF('Model inputs'!O26="","",'Model inputs'!O26),0)) -> 1250
A9: Audits delivered | B9: ="" | C9: ="" | D9: ="" | E9: ="" | F9: ="" | G9: ="" | H9: ="" | I9: ="" | ... M9: =""
A10: Annual deal-team | B10: ='DealScope monthly model and pri'!B6*'Model inputs'!O31 -> 15 | C10: ='DealScope monthly model and pri'!C6*'Model inputs'!O31 -> 15 | D10: ='DealScope monthly model and pri'!D6*'Model inputs'!O31 -> 15 | E10: ='DealScope monthly model and pri'!E6*'Model inputs'!O31 -> 15 | F10: ='DealScope monthly model and pri'!F6*'Model inputs'!O31 -> 15 | G10: ='DealScope monthly model and pri'!G6*'Model inputs'!O31 -> 15 | H10: ='DealScope monthly model and pri'!H6*'Model inputs'!O31 -> 15 | I10: ='DealScope monthly model and pri'!I6*'Model inputs'!O31 -> 15 | J10: ='DealScope monthly model and pri'!J6*'Model inputs'!O31 -> 15 | K10: ='DealScope monthly model and pri'!K6*'Model inputs'!O31 -> 15 | L10: ='DealScope monthly model and pri'!L6*'Model inputs'!O31 -> 15 | M10: ='DealScope monthly model and pri'!M6*'Model inputs'!O31 -> 15
A11: Hybrid | B11: ='DealScope monthly model and pri'!B6*'Model inputs'!O32 -> 15 | C11: ='DealScope monthly model and pri'!C6*'Model inputs'!O32 -> 15 | D11: ='DealScope monthly model and pri'!D6*'Model inputs'!O32 -> 15 | E11: ='DealScope monthly model and pri'!E6*'Model inputs'!O32 -> 15 | F11: ='DealScope monthly model and pri'!F6*'Model inputs'!O32 -> 15 | G11: ='DealScope monthly model and pri'!G6*'Model inputs'!O32 -> 15 | H11: ='DealScope monthly model and pri'!H6*'Model inputs'!O32 -> 15 | I11: ='DealScope monthly model and pri'!I6*'Model inputs'!O32 -> 15 | J11: ='DealScope monthly model and pri'!J6*'Model inputs'!O32 -> 15 | K11: ='DealScope monthly model and pri'!K6*'Model inputs'!O32 -> 15 | L11: ='DealScope monthly model and pri'!L6*'Model inputs'!O32 -> 15 | M11: ='DealScope monthly model and pri'!M6*'Model inputs'!O32 -> 15
A12: Per audit — base | B12: ='DealScope monthly model and pri'!B6*'Model inputs'!O33 -> 15 | C12: ='DealScope monthly model and pri'!C6*'Model inputs'!O33 -> 15 | D12: ='DealScope monthly model and pri'!D6*'Model inputs'!O33 -> 15 | E12: ='DealScope monthly model and pri'!E6*'Model inputs'!O33 -> 15 | F12: ='DealScope monthly model and pri'!F6*'Model inputs'!O33 -> 15 | G12: ='DealScope monthly model and pri'!G6*'Model inputs'!O33 -> 15 | H12: ='DealScope monthly model and pri'!H6*'Model inputs'!O33 -> 15 | I12: ='DealScope monthly model and pri'!I6*'Model inputs'!O33 -> 15 | J12: ='DealScope monthly model and pri'!J6*'Model inputs'!O33 -> 15 | K12: ='DealScope monthly model and pri'!K6*'Model inputs'!O33 -> 15 | L12: ='DealScope monthly model and pri'!L6*'Model inputs'!O33 -> 15 | M12: ='DealScope monthly model and pri'!M6*'Model inputs'!O33 -> 15
A13: Per audit — high | B13: ='DealScope monthly model and pri'!B6*'Model inputs'!O34 -> 15 | C13: ='DealScope monthly model and pri'!C6*'Model inputs'!O34 -> 15 | D13: ='DealScope monthly model and pri'!D6*'Model inputs'!O34 -> 15 | E13: ='DealScope monthly model and pri'!E6*'Model inputs'!O34 -> 15 | F13: ='DealScope monthly model and pri'!F6*'Model inputs'!O34 -> 15 | G13: ='DealScope monthly model and pri'!G6*'Model inputs'!O34 -> 15 | H13: ='DealScope monthly model and pri'!H6*'Model inputs'!O34 -> 15 | I13: ='DealScope monthly model and pri'!I6*'Model inputs'!O34 -> 15 | J13: ='DealScope monthly model and pri'!J6*'Model inputs'!O34 -> 15 | K13: ='DealScope monthly model and pri'!K6*'Model inputs'!O34 -> 15 | L13: ='DealScope monthly model and pri'!L6*'Model inputs'!O34 -> 15 | M13: ='DealScope monthly model and pri'!M6*'Model inputs'!O34 -> 15
A14: Per audit — low | B14: ='DealScope monthly model and pri'!B6*'Model inputs'!O35 -> 15 | C14: ='DealScope monthly model and pri'!C6*'Model inputs'!O35 -> 15 | D14: ='DealScope monthly model and pri'!D6*'Model inputs'!O35 -> 15 | E14: ='DealScope monthly model and pri'!E6*'Model inputs'!O35 -> 15 | F14: ='DealScope monthly model and pri'!F6*'Model inputs'!O35 -> 15 | G14: ='DealScope monthly model and pri'!G6*'Model inputs'!O35 -> 15 | H14: ='DealScope monthly model and pri'!H6*'Model inputs'!O35 -> 15 | I14: ='DealScope monthly model and pri'!I6*'Model inputs'!O35 -> 15 | J14: ='DealScope monthly model and pri'!J6*'Model inputs'!O35 -> 15 | K14: ='DealScope monthly model and pri'!K6*'Model inputs'!O35 -> 15 | L14: ='DealScope monthly model and pri'!L6*'Model inputs'!O35 -> 15 | M14: ='DealScope monthly model and pri'!M6*'Model inputs'!O35 -> 15
A15: Earned revenue | B15: ="" | C15: ="" | D15: ="" | E15: ="" | F15: ="" | G15: ="" | H15: ="" | I15: ="" | ... M15: =""
A16: Annual deal-team | B16: ='DealScope monthly model and pri'!B6*'Model inputs'!O37 -> 15000 | C16: ='DealScope monthly model and pri'!C6*'Model inputs'!O37 -> 15000 | D16: ='DealScope monthly model and pri'!D6*'Model inputs'!O37 -> 15000 | E16: ='DealScope monthly model and pri'!E6*'Model inputs'!O37 -> 15000 | F16: ='DealScope monthly model and pri'!F6*'Model inputs'!O37 -> 15000 | G16: ='DealScope monthly model and pri'!G6*'Model inputs'!O37 -> 15000 | H16: ='DealScope monthly model and pri'!H6*'Model inputs'!O37 -> 15000 | I16: ='DealScope monthly model and pri'!I6*'Model inputs'!O37 -> 15000 | J16: ='DealScope monthly model and pri'!J6*'Model inputs'!O37 -> 15000 | K16: ='DealScope monthly model and pri'!K6*'Model inputs'!O37 -> 15000 | L16: ='DealScope monthly model and pri'!L6*'Model inputs'!O37 -> 15000 | M16: ='DealScope monthly model and pri'!M6*'Model inputs'!O37 -> 15000
A17: Hybrid | B17: ='DealScope monthly model and pri'!B6*'Model inputs'!O38 -> 17500 | C17: ='DealScope monthly model and pri'!C6*'Model inputs'!O38 -> 17500 | D17: ='DealScope monthly model and pri'!D6*'Model inputs'!O38 -> 17500 | E17: ='DealScope monthly model and pri'!E6*'Model inputs'!O38 -> 17500 | F17: ='DealScope monthly model and pri'!F6*'Model inputs'!O38 -> 17500 | G17: ='DealScope monthly model and pri'!G6*'Model inputs'!O38 -> 17500 | H17: ='DealScope monthly model and pri'!H6*'Model inputs'!O38 -> 17500 | I17: ='DealScope monthly model and pri'!I6*'Model inputs'!O38 -> 17500 | J17: ='DealScope monthly model and pri'!J6*'Model inputs'!O38 -> 17500 | K17: ='DealScope monthly model and pri'!K6*'Model inputs'!O38 -> 17500 | L17: ='DealScope monthly model and pri'!L6*'Model inputs'!O38 -> 17500 | M17: ='DealScope monthly model and pri'!M6*'Model inputs'!O38 -> 17500
A18: Per audit — base | B18: ='DealScope monthly model and pri'!B6*'Model inputs'!O39 -> 22500 | C18: ='DealScope monthly model and pri'!C6*'Model inputs'!O39 -> 22500 | D18: ='DealScope monthly model and pri'!D6*'Model inputs'!O39 -> 22500 | E18: ='DealScope monthly model and pri'!E6*'Model inputs'!O39 -> 22500 | F18: ='DealScope monthly model and pri'!F6*'Model inputs'!O39 -> 22500 | G18: ='DealScope monthly model and pri'!G6*'Model inputs'!O39 -> 22500 | H18: ='DealScope monthly model and pri'!H6*'Model inputs'!O39 -> 22500 | I18: ='DealScope monthly model and pri'!I6*'Model inputs'!O39 -> 22500 | J18: ='DealScope monthly model and pri'!J6*'Model inputs'!O39 -> 22500 | K18: ='DealScope monthly model and pri'!K6*'Model inputs'!O39 -> 22500 | L18: ='DealScope monthly model and pri'!L6*'Model inputs'!O39 -> 22500 | M18: ='DealScope monthly model and pri'!M6*'Model inputs'!O39 -> 22500
A19: Per audit — high | B19: ='DealScope monthly model and pri'!B6*'Model inputs'!O40 -> 45000 | C19: ='DealScope monthly model and pri'!C6*'Model inputs'!O40 -> 45000 | D19: ='DealScope monthly model and pri'!D6*'Model inputs'!O40 -> 45000 | E19: ='DealScope monthly model and pri'!E6*'Model inputs'!O40 -> 45000 | F19: ='DealScope monthly model and pri'!F6*'Model inputs'!O40 -> 45000 | G19: ='DealScope monthly model and pri'!G6*'Model inputs'!O40 -> 45000 | H19: ='DealScope monthly model and pri'!H6*'Model inputs'!O40 -> 45000 | I19: ='DealScope monthly model and pri'!I6*'Model inputs'!O40 -> 45000 | J19: ='DealScope monthly model and pri'!J6*'Model inputs'!O40 -> 45000 | K19: ='DealScope monthly model and pri'!K6*'Model inputs'!O40 -> 45000 | L19: ='DealScope monthly model and pri'!L6*'Model inputs'!O40 -> 45000 | M19: ='DealScope monthly model and pri'!M6*'Model inputs'!O40 -> 45000
A20: Per audit — low | B20: ='DealScope monthly model and pri'!B6*'Model inputs'!O41 -> 11250 | C20: ='DealScope monthly model and pri'!C6*'Model inputs'!O41 -> 11250 | D20: ='DealScope monthly model and pri'!D6*'Model inputs'!O41 -> 11250 | E20: ='DealScope monthly model and pri'!E6*'Model inputs'!O41 -> 11250 | F20: ='DealScope monthly model and pri'!F6*'Model inputs'!O41 -> 11250 | G20: ='DealScope monthly model and pri'!G6*'Model inputs'!O41 -> 11250 | H20: ='DealScope monthly model and pri'!H6*'Model inputs'!O41 -> 11250 | I20: ='DealScope monthly model and pri'!I6*'Model inputs'!O41 -> 11250 | J20: ='DealScope monthly model and pri'!J6*'Model inputs'!O41 -> 11250 | K20: ='DealScope monthly model and pri'!K6*'Model inputs'!O41 -> 11250 | L20: ='DealScope monthly model and pri'!L6*'Model inputs'!O41 -> 11250 | M20: ='DealScope monthly model and pri'!M6*'Model inputs'!O41 -> 11250
A21: Cash collections | B21: ="" | C21: ="" | D21: ="" | E21: ="" | F21: ="" | G21: ="" | H21: ="" | I21: ="" | ... M21: =""
A22: Annual deal-team | B22: ='DealScope monthly model and pri'!B7*'Model inputs'!O88*(1-'Model inputs'!O78)+'DealScope monthly model and pri'!B16-'DealScope monthly model and pri'!B6*'Model inputs'!O88/12*(1-'Model inputs'!O78) -> 125000 | C22: ='DealScope monthly model and pri'!C7*'Model inputs'!O88*(1-'Model inputs'!O78)+'DealScope monthly model and pri'!C16-'DealScope monthly model and pri'!C6*'Model inputs'!O88/12*(1-'Model inputs'!O78) -> 5000 | D22: ='DealScope monthly model and pri'!D7*'Model inputs'!O88*(1-'Model inputs'!O78)+'DealScope monthly model and pri'!D16-'DealScope monthly model and pri'!D6*'Model inputs'!O88/12*(1-'Model inputs'!O78) -> 5000 | E22: ='DealScope monthly model and pri'!E7*'Model inputs'!O88*(1-'Model inputs'!O78)+'DealScope monthly model and pri'!E16-'DealScope monthly model and pri'!E6*'Model inputs'!O88/12*(1-'Model inputs'!O78) -> 5000 | F22: ='DealScope monthly model and pri'!F7*'Model inputs'!O88*(1-'Model inputs'!O78)+'DealScope monthly model and pri'!F16-'DealScope monthly model and pri'!F6*'Model inputs'!O88/12*(1-'Model inputs'!O78) -> 5000 | G22: ='DealScope monthly model and pri'!G7*'Model inputs'!O88*(1-'Model inputs'!O78)+'DealScope monthly model and pri'!G16-'DealScope monthly model and pri'!G6*'Model inputs'!O88/12*(1-'Model inputs'!O78) -> 5000 | H22: ='DealScope monthly model and pri'!H7*'Model inputs'!O88*(1-'Model inputs'!O78)+'DealScope monthly model and pri'!H16-'DealScope monthly model and pri'!H6*'Model inputs'!O88/12*(1-'Model inputs'!O78) -> 5000 | I22: ='DealScope monthly model and pri'!I7*'Model inputs'!O88*(1-'Model inputs'!O78)+'DealScope monthly model and pri'!I16-'DealScope monthly model and pri'!I6*'Model inputs'!O88/12*(1-'Model inputs'!O78) -> 5000 | J22: ='DealScope monthly model and pri'!J7*'Model inputs'!O88*(1-'Model inputs'!O78)+'DealScope monthly model and pri'!J16-'DealScope monthly model and pri'!J6*'Model inputs'!O88/12*(1-'Model inputs'!O78) -> 5000 | K22: ='DealScope monthly model and pri'!K7*'Model inputs'!O88*(1-'Model inputs'!O78)+'DealScope monthly model and pri'!K16-'DealScope monthly model and pri'!K6*'Model inputs'!O88/12*(1-'Model inputs'!O78) -> 5000 | L22: ='DealScope monthly model and pri'!L7*'Model inputs'!O88*(1-'Model inputs'!O78)+'DealScope monthly model and pri'!L16-'DealScope monthly model and pri'!L6*'Model inputs'!O88/12*(1-'Model inputs'!O78) -> 5000 | M22: ='DealScope monthly model and pri'!M7*'Model inputs'!O88*(1-'Model inputs'!O78)+'DealScope monthly model and pri'!M16-'DealScope monthly model and pri'!M6*'Model inputs'!O88/12*(1-'Model inputs'!O78) -> 5000
A23: Hybrid | B23: ='DealScope monthly model and pri'!B7*'Model inputs'!O89*(1-'Model inputs'!O78)+'DealScope monthly model and pri'!B17-'DealScope monthly model and pri'!B6*'Model inputs'!O89/12*(1-'Model inputs'!O78) -> 45000 | C23: ='DealScope monthly model and pri'!C7*'Model inputs'!O89*(1-'Model inputs'!O78)+'DealScope monthly model and pri'!C17-'DealScope monthly model and pri'!C6*'Model inputs'!O89/12*(1-'Model inputs'!O78) -> 15000 | D23: ='DealScope monthly model and pri'!D7*'Model inputs'!O89*(1-'Model inputs'!O78)+'DealScope monthly model and pri'!D17-'DealScope monthly model and pri'!D6*'Model inputs'!O89/12*(1-'Model inputs'!O78) -> 15000 | E23: ='DealScope monthly model and pri'!E7*'Model inputs'!O89*(1-'Model inputs'!O78)+'DealScope monthly model and pri'!E17-'DealScope monthly model and pri'!E6*'Model inputs'!O89/12*(1-'Model inputs'!O78) -> 15000 | F23: ='DealScope monthly model and pri'!F7*'Model inputs'!O89*(1-'Model inputs'!O78)+'DealScope monthly model and pri'!F17-'DealScope monthly model and pri'!F6*'Model inputs'!O89/12*(1-'Model inputs'!O78) -> 15000 | G23: ='DealScope monthly model and pri'!G7*'Model inputs'!O89*(1-'Model inputs'!O78)+'DealScope monthly model and pri'!G17-'DealScope monthly model and pri'!G6*'Model inputs'!O89/12*(1-'Model inputs'!O78) -> 15000 | H23: ='DealScope monthly model and pri'!H7*'Model inputs'!O89*(1-'Model inputs'!O78)+'DealScope monthly model and pri'!H17-'DealScope monthly model and pri'!H6*'Model inputs'!O89/12*(1-'Model inputs'!O78) -> 15000 | I23: ='DealScope monthly model and pri'!I7*'Model inputs'!O89*(1-'Model inputs'!O78)+'DealScope monthly model and pri'!I17-'DealScope monthly model and pri'!I6*'Model inputs'!O89/12*(1-'Model inputs'!O78) -> 15000 | J23: ='DealScope monthly model and pri'!J7*'Model inputs'!O89*(1-'Model inputs'!O78)+'DealScope monthly model and pri'!J17-'DealScope monthly model and pri'!J6*'Model inputs'!O89/12*(1-'Model inputs'!O78) -> 15000 | K23: ='DealScope monthly model and pri'!K7*'Model inputs'!O89*(1-'Model inputs'!O78)+'DealScope monthly model and pri'!K17-'DealScope monthly model and pri'!K6*'Model inputs'!O89/12*(1-'Model inputs'!O78) -> 15000 | L23: ='DealScope monthly model and pri'!L7*'Model inputs'!O89*(1-'Model inputs'!O78)+'DealScope monthly model and pri'!L17-'DealScope monthly model and pri'!L6*'Model inputs'!O89/12*(1-'Model inputs'!O78) -> 15000 | M23: ='DealScope monthly model and pri'!M7*'Model inputs'!O89*(1-'Model inputs'!O78)+'DealScope monthly model and pri'!M17-'DealScope monthly model and pri'!M6*'Model inputs'!O89/12*(1-'Model inputs'!O78) -> 15000
A24: Per audit — base | B24: ='DealScope monthly model and pri'!B7*'Model inputs'!O90*(1-'Model inputs'!O78)+'DealScope monthly model and pri'!B18-'DealScope monthly model and pri'!B6*'Model inputs'!O90/12*(1-'Model inputs'!O78) -> 22500 | C24: ='DealScope monthly model and pri'!C7*'Model inputs'!O90*(1-'Model inputs'!O78)+'DealScope monthly model and pri'!C18-'DealScope monthly model and pri'!C6*'Model inputs'!O90/12*(1-'Model inputs'!O78) -> 22500 | D24: ='DealScope monthly model and pri'!D7*'Model inputs'!O90*(1-'Model inputs'!O78)+'DealScope monthly model and pri'!D18-'DealScope monthly model and pri'!D6*'Model inputs'!O90/12*(1-'Model inputs'!O78) -> 22500 | E24: ='DealScope monthly model and pri'!E7*'Model inputs'!O90*(1-'Model inputs'!O78)+'DealScope monthly model and pri'!E18-'DealScope monthly model and pri'!E6*'Model inputs'!O90/12*(1-'Model inputs'!O78) -> 22500 | F24: ='DealScope monthly model and pri'!F7*'Model inputs'!O90*(1-'Model inputs'!O78)+'DealScope monthly model and pri'!F18-'DealScope monthly model and pri'!F6*'Model inputs'!O90/12*(1-'Model inputs'!O78) -> 22500 | G24: ='DealScope monthly model and pri'!G7*'Model inputs'!O90*(1-'Model inputs'!O78)+'DealScope monthly model and pri'!G18-'DealScope monthly model and pri'!G6*'Model inputs'!O90/12*(1-'Model inputs'!O78) -> 22500 | H24: ='DealScope monthly model and pri'!H7*'Model inputs'!O90*(1-'Model inputs'!O78)+'DealScope monthly model and pri'!H18-'DealScope monthly model and pri'!H6*'Model inputs'!O90/12*(1-'Model inputs'!O78) -> 22500 | I24: ='DealScope monthly model and pri'!I7*'Model inputs'!O90*(1-'Model inputs'!O78)+'DealScope monthly model and pri'!I18-'DealScope monthly model and pri'!I6*'Model inputs'!O90/12*(1-'Model inputs'!O78) -> 22500 | J24: ='DealScope monthly model and pri'!J7*'Model inputs'!O90*(1-'Model inputs'!O78)+'DealScope monthly model and pri'!J18-'DealScope monthly model and pri'!J6*'Model inputs'!O90/12*(1-'Model inputs'!O78) -> 22500 | K24: ='DealScope monthly model and pri'!K7*'Model inputs'!O90*(1-'Model inputs'!O78)+'DealScope monthly model and pri'!K18-'DealScope monthly model and pri'!K6*'Model inputs'!O90/12*(1-'Model inputs'!O78) -> 22500 | L24: ='DealScope monthly model and pri'!L7*'Model inputs'!O90*(1-'Model inputs'!O78)+'DealScope monthly model and pri'!L18-'DealScope monthly model and pri'!L6*'Model inputs'!O90/12*(1-'Model inputs'!O78) -> 22500 | M24: ='DealScope monthly model and pri'!M7*'Model inputs'!O90*(1-'Model inputs'!O78)+'DealScope monthly model and pri'!M18-'DealScope monthly model and pri'!M6*'Model inputs'!O90/12*(1-'Model inputs'!O78) -> 22500
A25: Per audit — high | B25: ='DealScope monthly model and pri'!B7*'Model inputs'!O91*(1-'Model inputs'!O78)+'DealScope monthly model and pri'!B19-'DealScope monthly model and pri'!B6*'Model inputs'!O91/12*(1-'Model inputs'!O78) -> 45000 | C25: ='DealScope monthly model and pri'!C7*'Model inputs'!O91*(1-'Model inputs'!O78)+'DealScope monthly model and pri'!C19-'DealScope monthly model and pri'!C6*'Model inputs'!O91/12*(1-'Model inputs'!O78) -> 45000 | D25: ='DealScope monthly model and pri'!D7*'Model inputs'!O91*(1-'Model inputs'!O78)+'DealScope monthly model and pri'!D19-'DealScope monthly model and pri'!D6*'Model inputs'!O91/12*(1-'Model inputs'!O78) -> 45000 | E25: ='DealScope monthly model and pri'!E7*'Model inputs'!O91*(1-'Model inputs'!O78)+'DealScope monthly model and pri'!E19-'DealScope monthly model and pri'!E6*'Model inputs'!O91/12*(1-'Model inputs'!O78) -> 45000 | F25: ='DealScope monthly model and pri'!F7*'Model inputs'!O91*(1-'Model inputs'!O78)+'DealScope monthly model and pri'!F19-'DealScope monthly model and pri'!F6*'Model inputs'!O91/12*(1-'Model inputs'!O78) -> 45000 | G25: ='DealScope monthly model and pri'!G7*'Model inputs'!O91*(1-'Model inputs'!O78)+'DealScope monthly model and pri'!G19-'DealScope monthly model and pri'!G6*'Model inputs'!O91/12*(1-'Model inputs'!O78) -> 45000 | H25: ='DealScope monthly model and pri'!H7*'Model inputs'!O91*(1-'Model inputs'!O78)+'DealScope monthly model and pri'!H19-'DealScope monthly model and pri'!H6*'Model inputs'!O91/12*(1-'Model inputs'!O78) -> 45000 | I25: ='DealScope monthly model and pri'!I7*'Model inputs'!O91*(1-'Model inputs'!O78)+'DealScope monthly model and pri'!I19-'DealScope monthly model and pri'!I6*'Model inputs'!O91/12*(1-'Model inputs'!O78) -> 45000 | J25: ='DealScope monthly model and pri'!J7*'Model inputs'!O91*(1-'Model inputs'!O78)+'DealScope monthly model and pri'!J19-'DealScope monthly model and pri'!J6*'Model inputs'!O91/12*(1-'Model inputs'!O78) -> 45000 | K25: ='DealScope monthly model and pri'!K7*'Model inputs'!O91*(1-'Model inputs'!O78)+'DealScope monthly model and pri'!K19-'DealScope monthly model and pri'!K6*'Model inputs'!O91/12*(1-'Model inputs'!O78) -> 45000 | L25: ='DealScope monthly model and pri'!L7*'Model inputs'!O91*(1-'Model inputs'!O78)+'DealScope monthly model and pri'!L19-'DealScope monthly model and pri'!L6*'Model inputs'!O91/12*(1-'Model inputs'!O78) -> 45000 | M25: ='DealScope monthly model and pri'!M7*'Model inputs'!O91*(1-'Model inputs'!O78)+'DealScope monthly model and pri'!M19-'DealScope monthly model and pri'!M6*'Model inputs'!O91/12*(1-'Model inputs'!O78) -> 45000
A26: Per audit — low | B26: ='DealScope monthly model and pri'!B7*'Model inputs'!O92*(1-'Model inputs'!O78)+'DealScope monthly model and pri'!B20-'DealScope monthly model and pri'!B6*'Model inputs'!O92/12*(1-'Model inputs'!O78) -> 11250 | C26: ='DealScope monthly model and pri'!C7*'Model inputs'!O92*(1-'Model inputs'!O78)+'DealScope monthly model and pri'!C20-'DealScope monthly model and pri'!C6*'Model inputs'!O92/12*(1-'Model inputs'!O78) -> 11250 | D26: ='DealScope monthly model and pri'!D7*'Model inputs'!O92*(1-'Model inputs'!O78)+'DealScope monthly model and pri'!D20-'DealScope monthly model and pri'!D6*'Model inputs'!O92/12*(1-'Model inputs'!O78) -> 11250 | E26: ='DealScope monthly model and pri'!E7*'Model inputs'!O92*(1-'Model inputs'!O78)+'DealScope monthly model and pri'!E20-'DealScope monthly model and pri'!E6*'Model inputs'!O92/12*(1-'Model inputs'!O78) -> 11250 | F26: ='DealScope monthly model and pri'!F7*'Model inputs'!O92*(1-'Model inputs'!O78)+'DealScope monthly model and pri'!F20-'DealScope monthly model and pri'!F6*'Model inputs'!O92/12*(1-'Model inputs'!O78) -> 11250 | G26: ='DealScope monthly model and pri'!G7*'Model inputs'!O92*(1-'Model inputs'!O78)+'DealScope monthly model and pri'!G20-'DealScope monthly model and pri'!G6*'Model inputs'!O92/12*(1-'Model inputs'!O78) -> 11250 | H26: ='DealScope monthly model and pri'!H7*'Model inputs'!O92*(1-'Model inputs'!O78)+'DealScope monthly model and pri'!H20-'DealScope monthly model and pri'!H6*'Model inputs'!O92/12*(1-'Model inputs'!O78) -> 11250 | I26: ='DealScope monthly model and pri'!I7*'Model inputs'!O92*(1-'Model inputs'!O78)+'DealScope monthly model and pri'!I20-'DealScope monthly model and pri'!I6*'Model inputs'!O92/12*(1-'Model inputs'!O78) -> 11250 | J26: ='DealScope monthly model and pri'!J7*'Model inputs'!O92*(1-'Model inputs'!O78)+'DealScope monthly model and pri'!J20-'DealScope monthly model and pri'!J6*'Model inputs'!O92/12*(1-'Model inputs'!O78) -> 11250 | K26: ='DealScope monthly model and pri'!K7*'Model inputs'!O92*(1-'Model inputs'!O78)+'DealScope monthly model and pri'!K20-'DealScope monthly model and pri'!K6*'Model inputs'!O92/12*(1-'Model inputs'!O78) -> 11250 | L26: ='DealScope monthly model and pri'!L7*'Model inputs'!O92*(1-'Model inputs'!O78)+'DealScope monthly model and pri'!L20-'DealScope monthly model and pri'!L6*'Model inputs'!O92/12*(1-'Model inputs'!O78) -> 11250 | M26: ='DealScope monthly model and pri'!M7*'Model inputs'!O92*(1-'Model inputs'!O78)+'DealScope monthly model and pri'!M20-'DealScope monthly model and pri'!M6*'Model inputs'!O92/12*(1-'Model inputs'!O78) -> 11250
A27: Delivery COGS | B27: ="" | C27: ="" | D27: ="" | E27: ="" | F27: ="" | G27: ="" | H27: ="" | I27: ="" | ... M27: =""
A28: Annual deal-team | B28: ='DealScope monthly model and pri'!B10*'Model inputs'!O50 -> 1419.75 | C28: ='DealScope monthly model and pri'!C10*'Model inputs'!O50 -> 1419.75 | D28: ='DealScope monthly model and pri'!D10*'Model inputs'!O50 -> 1419.75 | E28: ='DealScope monthly model and pri'!E10*'Model inputs'!O50 -> 1419.75 | F28: ='DealScope monthly model and pri'!F10*'Model inputs'!O50 -> 1419.75 | G28: ='DealScope monthly model and pri'!G10*'Model inputs'!O50 -> 1419.75 | H28: ='DealScope monthly model and pri'!H10*'Model inputs'!O50 -> 1419.75 | I28: ='DealScope monthly model and pri'!I10*'Model inputs'!O50 -> 1419.75 | J28: ='DealScope monthly model and pri'!J10*'Model inputs'!O50 -> 1419.75 | K28: ='DealScope monthly model and pri'!K10*'Model inputs'!O50 -> 1419.75 | L28: ='DealScope monthly model and pri'!L10*'Model inputs'!O50 -> 1419.75 | M28: ='DealScope monthly model and pri'!M10*'Model inputs'!O50 -> 1419.75
A29: Hybrid | B29: ='DealScope monthly model and pri'!B11*'Model inputs'!O50 -> 1419.75 | C29: ='DealScope monthly model and pri'!C11*'Model inputs'!O50 -> 1419.75 | D29: ='DealScope monthly model and pri'!D11*'Model inputs'!O50 -> 1419.75 | E29: ='DealScope monthly model and pri'!E11*'Model inputs'!O50 -> 1419.75 | F29: ='DealScope monthly model and pri'!F11*'Model inputs'!O50 -> 1419.75 | G29: ='DealScope monthly model and pri'!G11*'Model inputs'!O50 -> 1419.75 | H29: ='DealScope monthly model and pri'!H11*'Model inputs'!O50 -> 1419.75 | I29: ='DealScope monthly model and pri'!I11*'Model inputs'!O50 -> 1419.75 | J29: ='DealScope monthly model and pri'!J11*'Model inputs'!O50 -> 1419.75 | K29: ='DealScope monthly model and pri'!K11*'Model inputs'!O50 -> 1419.75 | L29: ='DealScope monthly model and pri'!L11*'Model inputs'!O50 -> 1419.75 | M29: ='DealScope monthly model and pri'!M11*'Model inputs'!O50 -> 1419.75
A30: Per audit — base | B30: ='DealScope monthly model and pri'!B12*'Model inputs'!O50 -> 1419.75 | C30: ='DealScope monthly model and pri'!C12*'Model inputs'!O50 -> 1419.75 | D30: ='DealScope monthly model and pri'!D12*'Model inputs'!O50 -> 1419.75 | E30: ='DealScope monthly model and pri'!E12*'Model inputs'!O50 -> 1419.75 | F30: ='DealScope monthly model and pri'!F12*'Model inputs'!O50 -> 1419.75 | G30: ='DealScope monthly model and pri'!G12*'Model inputs'!O50 -> 1419.75 | H30: ='DealScope monthly model and pri'!H12*'Model inputs'!O50 -> 1419.75 | I30: ='DealScope monthly model and pri'!I12*'Model inputs'!O50 -> 1419.75 | J30: ='DealScope monthly model and pri'!J12*'Model inputs'!O50 -> 1419.75 | K30: ='DealScope monthly model and pri'!K12*'Model inputs'!O50 -> 1419.75 | L30: ='DealScope monthly model and pri'!L12*'Model inputs'!O50 -> 1419.75 | M30: ='DealScope monthly model and pri'!M12*'Model inputs'!O50 -> 1419.75
A31: Per audit — high | B31: ='DealScope monthly model and pri'!B13*'Model inputs'!O50 -> 1419.75 | C31: ='DealScope monthly model and pri'!C13*'Model inputs'!O50 -> 1419.75 | D31: ='DealScope monthly model and pri'!D13*'Model inputs'!O50 -> 1419.75 | E31: ='DealScope monthly model and pri'!E13*'Model inputs'!O50 -> 1419.75 | F31: ='DealScope monthly model and pri'!F13*'Model inputs'!O50 -> 1419.75 | G31: ='DealScope monthly model and pri'!G13*'Model inputs'!O50 -> 1419.75 | H31: ='DealScope monthly model and pri'!H13*'Model inputs'!O50 -> 1419.75 | I31: ='DealScope monthly model and pri'!I13*'Model inputs'!O50 -> 1419.75 | J31: ='DealScope monthly model and pri'!J13*'Model inputs'!O50 -> 1419.75 | K31: ='DealScope monthly model and pri'!K13*'Model inputs'!O50 -> 1419.75 | L31: ='DealScope monthly model and pri'!L13*'Model inputs'!O50 -> 1419.75 | M31: ='DealScope monthly model and pri'!M13*'Model inputs'!O50 -> 1419.75
A32: Per audit — low | B32: ='DealScope monthly model and pri'!B14*'Model inputs'!O50 -> 1419.75 | C32: ='DealScope monthly model and pri'!C14*'Model inputs'!O50 -> 1419.75 | D32: ='DealScope monthly model and pri'!D14*'Model inputs'!O50 -> 1419.75 | E32: ='DealScope monthly model and pri'!E14*'Model inputs'!O50 -> 1419.75 | F32: ='DealScope monthly model and pri'!F14*'Model inputs'!O50 -> 1419.75 | G32: ='DealScope monthly model and pri'!G14*'Model inputs'!O50 -> 1419.75 | H32: ='DealScope monthly model and pri'!H14*'Model inputs'!O50 -> 1419.75 | I32: ='DealScope monthly model and pri'!I14*'Model inputs'!O50 -> 1419.75 | J32: ='DealScope monthly model and pri'!J14*'Model inputs'!O50 -> 1419.75 | K32: ='DealScope monthly model and pri'!K14*'Model inputs'!O50 -> 1419.75 | L32: ='DealScope monthly model and pri'!L14*'Model inputs'!O50 -> 1419.75 | M32: ='DealScope monthly model and pri'!M14*'Model inputs'!O50 -> 1419.75
A33: Gross profit | B33: ="" | C33: ="" | D33: ="" | E33: ="" | F33: ="" | G33: ="" | H33: ="" | I33: ="" | ... M33: =""
A34: Annual deal-team | B34: ='DealScope monthly model and pri'!B16-'DealScope monthly model and pri'!B28 -> 13580.25 | C34: ='DealScope monthly model and pri'!C16-'DealScope monthly model and pri'!C28 -> 13580.25 | D34: ='DealScope monthly model and pri'!D16-'DealScope monthly model and pri'!D28 -> 13580.25 | E34: ='DealScope monthly model and pri'!E16-'DealScope monthly model and pri'!E28 -> 13580.25 | F34: ='DealScope monthly model and pri'!F16-'DealScope monthly model and pri'!F28 -> 13580.25 | G34: ='DealScope monthly model and pri'!G16-'DealScope monthly model and pri'!G28 -> 13580.25 | H34: ='DealScope monthly model and pri'!H16-'DealScope monthly model and pri'!H28 -> 13580.25 | I34: ='DealScope monthly model and pri'!I16-'DealScope monthly model and pri'!I28 -> 13580.25 | ... M34: ='DealScope monthly model and pri'!M16-'DealScope monthly model and pri'!M28 -> 13580.25
A35: Hybrid | B35: ='DealScope monthly model and pri'!B17-'DealScope monthly model and pri'!B29 -> 16080.25 | C35: ='DealScope monthly model and pri'!C17-'DealScope monthly model and pri'!C29 -> 16080.25 | D35: ='DealScope monthly model and pri'!D17-'DealScope monthly model and pri'!D29 -> 16080.25 | E35: ='DealScope monthly model and pri'!E17-'DealScope monthly model and pri'!E29 -> 16080.25 | F35: ='DealScope monthly model and pri'!F17-'DealScope monthly model and pri'!F29 -> 16080.25 | G35: ='DealScope monthly model and pri'!G17-'DealScope monthly model and pri'!G29 -> 16080.25 | H35: ='DealScope monthly model and pri'!H17-'DealScope monthly model and pri'!H29 -> 16080.25 | I35: ='DealScope monthly model and pri'!I17-'DealScope monthly model and pri'!I29 -> 16080.25 | ... M35: ='DealScope monthly model and pri'!M17-'DealScope monthly model and pri'!M29 -> 16080.25
A36: Per audit — base | B36: ='DealScope monthly model and pri'!B18-'DealScope monthly model and pri'!B30 -> 21080.25 | C36: ='DealScope monthly model and pri'!C18-'DealScope monthly model and pri'!C30 -> 21080.25 | D36: ='DealScope monthly model and pri'!D18-'DealScope monthly model and pri'!D30 -> 21080.25 | E36: ='DealScope monthly model and pri'!E18-'DealScope monthly model and pri'!E30 -> 21080.25 | F36: ='DealScope monthly model and pri'!F18-'DealScope monthly model and pri'!F30 -> 21080.25 | G36: ='DealScope monthly model and pri'!G18-'DealScope monthly model and pri'!G30 -> 21080.25 | H36: ='DealScope monthly model and pri'!H18-'DealScope monthly model and pri'!H30 -> 21080.25 | I36: ='DealScope monthly model and pri'!I18-'DealScope monthly model and pri'!I30 -> 21080.25 | ... M36: ='DealScope monthly model and pri'!M18-'DealScope monthly model and pri'!M30 -> 21080.25
A37: Per audit — high | B37: ='DealScope monthly model and pri'!B19-'DealScope monthly model and pri'!B31 -> 43580.25 | C37: ='DealScope monthly model and pri'!C19-'DealScope monthly model and pri'!C31 -> 43580.25 | D37: ='DealScope monthly model and pri'!D19-'DealScope monthly model and pri'!D31 -> 43580.25 | E37: ='DealScope monthly model and pri'!E19-'DealScope monthly model and pri'!E31 -> 43580.25 | F37: ='DealScope monthly model and pri'!F19-'DealScope monthly model and pri'!F31 -> 43580.25 | G37: ='DealScope monthly model and pri'!G19-'DealScope monthly model and pri'!G31 -> 43580.25 | H37: ='DealScope monthly model and pri'!H19-'DealScope monthly model and pri'!H31 -> 43580.25 | I37: ='DealScope monthly model and pri'!I19-'DealScope monthly model and pri'!I31 -> 43580.25 | ... M37: ='DealScope monthly model and pri'!M19-'DealScope monthly model and pri'!M31 -> 43580.25
A38: Per audit — low | B38: ='DealScope monthly model and pri'!B20-'DealScope monthly model and pri'!B32 -> 9830.25 | C38: ='DealScope monthly model and pri'!C20-'DealScope monthly model and pri'!C32 -> 9830.25 | D38: ='DealScope monthly model and pri'!D20-'DealScope monthly model and pri'!D32 -> 9830.25 | E38: ='DealScope monthly model and pri'!E20-'DealScope monthly model and pri'!E32 -> 9830.25 | F38: ='DealScope monthly model and pri'!F20-'DealScope monthly model and pri'!F32 -> 9830.25 | G38: ='DealScope monthly model and pri'!G20-'DealScope monthly model and pri'!G32 -> 9830.25 | H38: ='DealScope monthly model and pri'!H20-'DealScope monthly model and pri'!H32 -> 9830.25 | I38: ='DealScope monthly model and pri'!I20-'DealScope monthly model and pri'!I32 -> 9830.25 | ... M38: ='DealScope monthly model and pri'!M20-'DealScope monthly model and pri'!M32 -> 9830.25
A39: Payment fees | B39: ="" | C39: ="" | D39: ="" | E39: ="" | F39: ="" | G39: ="" | H39: ="" | I39: ="" | ... M39: =""
A40: Annual deal-team | B40: ='DealScope monthly model and pri'!B22*'Model inputs'!O79 -> 3750 | C40: ='DealScope monthly model and pri'!C22*'Model inputs'!O79 -> 150 | D40: ='DealScope monthly model and pri'!D22*'Model inputs'!O79 -> 150 | E40: ='DealScope monthly model and pri'!E22*'Model inputs'!O79 -> 150 | F40: ='DealScope monthly model and pri'!F22*'Model inputs'!O79 -> 150 | G40: ='DealScope monthly model and pri'!G22*'Model inputs'!O79 -> 150 | H40: ='DealScope monthly model and pri'!H22*'Model inputs'!O79 -> 150 | I40: ='DealScope monthly model and pri'!I22*'Model inputs'!O79 -> 150 | J40: ='DealScope monthly model and pri'!J22*'Model inputs'!O79 -> 150 | K40: ='DealScope monthly model and pri'!K22*'Model inputs'!O79 -> 150 | L40: ='DealScope monthly model and pri'!L22*'Model inputs'!O79 -> 150 | M40: ='DealScope monthly model and pri'!M22*'Model inputs'!O79 -> 150
A41: Hybrid | B41: ='DealScope monthly model and pri'!B23*'Model inputs'!O79 -> 1350 | C41: ='DealScope monthly model and pri'!C23*'Model inputs'!O79 -> 450 | D41: ='DealScope monthly model and pri'!D23*'Model inputs'!O79 -> 450 | E41: ='DealScope monthly model and pri'!E23*'Model inputs'!O79 -> 450 | F41: ='DealScope monthly model and pri'!F23*'Model inputs'!O79 -> 450 | G41: ='DealScope monthly model and pri'!G23*'Model inputs'!O79 -> 450 | H41: ='DealScope monthly model and pri'!H23*'Model inputs'!O79 -> 450 | I41: ='DealScope monthly model and pri'!I23*'Model inputs'!O79 -> 450 | J41: ='DealScope monthly model and pri'!J23*'Model inputs'!O79 -> 450 | K41: ='DealScope monthly model and pri'!K23*'Model inputs'!O79 -> 450 | L41: ='DealScope monthly model and pri'!L23*'Model inputs'!O79 -> 450 | M41: ='DealScope monthly model and pri'!M23*'Model inputs'!O79 -> 450
A42: Per audit — base | B42: ='DealScope monthly model and pri'!B24*'Model inputs'!O79 -> 675 | C42: ='DealScope monthly model and pri'!C24*'Model inputs'!O79 -> 675 | D42: ='DealScope monthly model and pri'!D24*'Model inputs'!O79 -> 675 | E42: ='DealScope monthly model and pri'!E24*'Model inputs'!O79 -> 675 | F42: ='DealScope monthly model and pri'!F24*'Model inputs'!O79 -> 675 | G42: ='DealScope monthly model and pri'!G24*'Model inputs'!O79 -> 675 | H42: ='DealScope monthly model and pri'!H24*'Model inputs'!O79 -> 675 | I42: ='DealScope monthly model and pri'!I24*'Model inputs'!O79 -> 675 | J42: ='DealScope monthly model and pri'!J24*'Model inputs'!O79 -> 675 | K42: ='DealScope monthly model and pri'!K24*'Model inputs'!O79 -> 675 | L42: ='DealScope monthly model and pri'!L24*'Model inputs'!O79 -> 675 | M42: ='DealScope monthly model and pri'!M24*'Model inputs'!O79 -> 675
A43: Per audit — high | B43: ='DealScope monthly model and pri'!B25*'Model inputs'!O79 -> 1350 | C43: ='DealScope monthly model and pri'!C25*'Model inputs'!O79 -> 1350 | D43: ='DealScope monthly model and pri'!D25*'Model inputs'!O79 -> 1350 | E43: ='DealScope monthly model and pri'!E25*'Model inputs'!O79 -> 1350 | F43: ='DealScope monthly model and pri'!F25*'Model inputs'!O79 -> 1350 | G43: ='DealScope monthly model and pri'!G25*'Model inputs'!O79 -> 1350 | H43: ='DealScope monthly model and pri'!H25*'Model inputs'!O79 -> 1350 | I43: ='DealScope monthly model and pri'!I25*'Model inputs'!O79 -> 1350 | J43: ='DealScope monthly model and pri'!J25*'Model inputs'!O79 -> 1350 | K43: ='DealScope monthly model and pri'!K25*'Model inputs'!O79 -> 1350 | L43: ='DealScope monthly model and pri'!L25*'Model inputs'!O79 -> 1350 | M43: ='DealScope monthly model and pri'!M25*'Model inputs'!O79 -> 1350
A44: Per audit — low | B44: ='DealScope monthly model and pri'!B26*'Model inputs'!O79 -> 337.5 | C44: ='DealScope monthly model and pri'!C26*'Model inputs'!O79 -> 337.5 | D44: ='DealScope monthly model and pri'!D26*'Model inputs'!O79 -> 337.5 | E44: ='DealScope monthly model and pri'!E26*'Model inputs'!O79 -> 337.5 | F44: ='DealScope monthly model and pri'!F26*'Model inputs'!O79 -> 337.5 | G44: ='DealScope monthly model and pri'!G26*'Model inputs'!O79 -> 337.5 | H44: ='DealScope monthly model and pri'!H26*'Model inputs'!O79 -> 337.5 | I44: ='DealScope monthly model and pri'!I26*'Model inputs'!O79 -> 337.5 | J44: ='DealScope monthly model and pri'!J26*'Model inputs'!O79 -> 337.5 | K44: ='DealScope monthly model and pri'!K26*'Model inputs'!O79 -> 337.5 | L44: ='DealScope monthly model and pri'!L26*'Model inputs'!O79 -> 337.5 | M44: ='DealScope monthly model and pri'!M26*'Model inputs'!O79 -> 337.5
A45: Account support cost | B45: ="" | C45: ="" | D45: ="" | E45: ="" | F45: ="" | G45: ="" | H45: ="" | I45: ="" | ... M45: =""
A46: Annual deal-team | B46: ='DealScope monthly model and pri'!B6*'Model inputs'!O86*'Model inputs'!O85 -> 150 | C46: ='DealScope monthly model and pri'!C6*'Model inputs'!O86*'Model inputs'!O85 -> 150 | D46: ='DealScope monthly model and pri'!D6*'Model inputs'!O86*'Model inputs'!O85 -> 150 | E46: ='DealScope monthly model and pri'!E6*'Model inputs'!O86*'Model inputs'!O85 -> 150 | F46: ='DealScope monthly model and pri'!F6*'Model inputs'!O86*'Model inputs'!O85 -> 150 | G46: ='DealScope monthly model and pri'!G6*'Model inputs'!O86*'Model inputs'!O85 -> 150 | H46: ='DealScope monthly model and pri'!H6*'Model inputs'!O86*'Model inputs'!O85 -> 150 | I46: ='DealScope monthly model and pri'!I6*'Model inputs'!O86*'Model inputs'!O85 -> 150 | J46: ='DealScope monthly model and pri'!J6*'Model inputs'!O86*'Model inputs'!O85 -> 150 | K46: ='DealScope monthly model and pri'!K6*'Model inputs'!O86*'Model inputs'!O85 -> 150 | L46: ='DealScope monthly model and pri'!L6*'Model inputs'!O86*'Model inputs'!O85 -> 150 | M46: ='DealScope monthly model and pri'!M6*'Model inputs'!O86*'Model inputs'!O85 -> 150
A47: Hybrid | B47: ='DealScope monthly model and pri'!B6*'Model inputs'!O86*'Model inputs'!O85 -> 150 | C47: ='DealScope monthly model and pri'!C6*'Model inputs'!O86*'Model inputs'!O85 -> 150 | D47: ='DealScope monthly model and pri'!D6*'Model inputs'!O86*'Model inputs'!O85 -> 150 | E47: ='DealScope monthly model and pri'!E6*'Model inputs'!O86*'Model inputs'!O85 -> 150 | F47: ='DealScope monthly model and pri'!F6*'Model inputs'!O86*'Model inputs'!O85 -> 150 | G47: ='DealScope monthly model and pri'!G6*'Model inputs'!O86*'Model inputs'!O85 -> 150 | H47: ='DealScope monthly model and pri'!H6*'Model inputs'!O86*'Model inputs'!O85 -> 150 | I47: ='DealScope monthly model and pri'!I6*'Model inputs'!O86*'Model inputs'!O85 -> 150 | J47: ='DealScope monthly model and pri'!J6*'Model inputs'!O86*'Model inputs'!O85 -> 150 | K47: ='DealScope monthly model and pri'!K6*'Model inputs'!O86*'Model inputs'!O85 -> 150 | L47: ='DealScope monthly model and pri'!L6*'Model inputs'!O86*'Model inputs'!O85 -> 150 | M47: ='DealScope monthly model and pri'!M6*'Model inputs'!O86*'Model inputs'!O85 -> 150
A48: Per audit — base | B48: ='DealScope monthly model and pri'!B6*'Model inputs'!O86*'Model inputs'!O85 -> 150 | C48: ='DealScope monthly model and pri'!C6*'Model inputs'!O86*'Model inputs'!O85 -> 150 | D48: ='DealScope monthly model and pri'!D6*'Model inputs'!O86*'Model inputs'!O85 -> 150 | E48: ='DealScope monthly model and pri'!E6*'Model inputs'!O86*'Model inputs'!O85 -> 150 | F48: ='DealScope monthly model and pri'!F6*'Model inputs'!O86*'Model inputs'!O85 -> 150 | G48: ='DealScope monthly model and pri'!G6*'Model inputs'!O86*'Model inputs'!O85 -> 150 | H48: ='DealScope monthly model and pri'!H6*'Model inputs'!O86*'Model inputs'!O85 -> 150 | I48: ='DealScope monthly model and pri'!I6*'Model inputs'!O86*'Model inputs'!O85 -> 150 | J48: ='DealScope monthly model and pri'!J6*'Model inputs'!O86*'Model inputs'!O85 -> 150 | K48: ='DealScope monthly model and pri'!K6*'Model inputs'!O86*'Model inputs'!O85 -> 150 | L48: ='DealScope monthly model and pri'!L6*'Model inputs'!O86*'Model inputs'!O85 -> 150 | M48: ='DealScope monthly model and pri'!M6*'Model inputs'!O86*'Model inputs'!O85 -> 150
A49: Per audit — high | B49: ='DealScope monthly model and pri'!B6*'Model inputs'!O86*'Model inputs'!O85 -> 150 | C49: ='DealScope monthly model and pri'!C6*'Model inputs'!O86*'Model inputs'!O85 -> 150 | D49: ='DealScope monthly model and pri'!D6*'Model inputs'!O86*'Model inputs'!O85 -> 150 | E49: ='DealScope monthly model and pri'!E6*'Model inputs'!O86*'Model inputs'!O85 -> 150 | F49: ='DealScope monthly model and pri'!F6*'Model inputs'!O86*'Model inputs'!O85 -> 150 | G49: ='DealScope monthly model and pri'!G6*'Model inputs'!O86*'Model inputs'!O85 -> 150 | H49: ='DealScope monthly model and pri'!H6*'Model inputs'!O86*'Model inputs'!O85 -> 150 | I49: ='DealScope monthly model and pri'!I6*'Model inputs'!O86*'Model inputs'!O85 -> 150 | J49: ='DealScope monthly model and pri'!J6*'Model inputs'!O86*'Model inputs'!O85 -> 150 | K49: ='DealScope monthly model and pri'!K6*'Model inputs'!O86*'Model inputs'!O85 -> 150 | L49: ='DealScope monthly model and pri'!L6*'Model inputs'!O86*'Model inputs'!O85 -> 150 | M49: ='DealScope monthly model and pri'!M6*'Model inputs'!O86*'Model inputs'!O85 -> 150
A50: Per audit — low | B50: ='DealScope monthly model and pri'!B6*'Model inputs'!O86*'Model inputs'!O85 -> 150 | C50: ='DealScope monthly model and pri'!C6*'Model inputs'!O86*'Model inputs'!O85 -> 150 | D50: ='DealScope monthly model and pri'!D6*'Model inputs'!O86*'Model inputs'!O85 -> 150 | E50: ='DealScope monthly model and pri'!E6*'Model inputs'!O86*'Model inputs'!O85 -> 150 | F50: ='DealScope monthly model and pri'!F6*'Model inputs'!O86*'Model inputs'!O85 -> 150 | G50: ='DealScope monthly model and pri'!G6*'Model inputs'!O86*'Model inputs'!O85 -> 150 | H50: ='DealScope monthly model and pri'!H6*'Model inputs'!O86*'Model inputs'!O85 -> 150 | I50: ='DealScope monthly model and pri'!I6*'Model inputs'!O86*'Model inputs'!O85 -> 150 | J50: ='DealScope monthly model and pri'!J6*'Model inputs'!O86*'Model inputs'!O85 -> 150 | K50: ='DealScope monthly model and pri'!K6*'Model inputs'!O86*'Model inputs'!O85 -> 150 | L50: ='DealScope monthly model and pri'!L6*'Model inputs'!O86*'Model inputs'!O85 -> 150 | M50: ='DealScope monthly model and pri'!M6*'Model inputs'!O86*'Model inputs'!O85 -> 150
A51: Contribution profit | B51: ="" | C51: ="" | D51: ="" | E51: ="" | F51: ="" | G51: ="" | H51: ="" | I51: ="" | ... M51: =""
A52: Annual deal-team | B52: ='DealScope monthly model and pri'!B34-'DealScope monthly model and pri'!B16*'Model inputs'!O79-'DealScope monthly model and pri'!B46 -> 12980.25 | C52: ='DealScope monthly model and pri'!C34-'DealScope monthly model and pri'!C16*'Model inputs'!O79-'DealScope monthly model and pri'!C46 -> 12980.25 | D52: ='DealScope monthly model and pri'!D34-'DealScope monthly model and pri'!D16*'Model inputs'!O79-'DealScope monthly model and pri'!D46 -> 12980.25 | E52: ='DealScope monthly model and pri'!E34-'DealScope monthly model and pri'!E16*'Model inputs'!O79-'DealScope monthly model and pri'!E46 -> 12980.25 | F52: ='DealScope monthly model and pri'!F34-'DealScope monthly model and pri'!F16*'Model inputs'!O79-'DealScope monthly model and pri'!F46 -> 12980.25 | G52: ='DealScope monthly model and pri'!G34-'DealScope monthly model and pri'!G16*'Model inputs'!O79-'DealScope monthly model and pri'!G46 -> 12980.25 | H52: ='DealScope monthly model and pri'!H34-'DealScope monthly model and pri'!H16*'Model inputs'!O79-'DealScope monthly model and pri'!H46 -> 12980.25 | I52: ='DealScope monthly model and pri'!I34-'DealScope monthly model and pri'!I16*'Model inputs'!O79-'DealScope monthly model and pri'!I46 -> 12980.25 | J52: ='DealScope monthly model and pri'!J34-'DealScope monthly model and pri'!J16*'Model inputs'!O79-'DealScope monthly model and pri'!J46 -> 12980.25 | K52: ='DealScope monthly model and pri'!K34-'DealScope monthly model and pri'!K16*'Model inputs'!O79-'DealScope monthly model and pri'!K46 -> 12980.25 | L52: ='DealScope monthly model and pri'!L34-'DealScope monthly model and pri'!L16*'Model inputs'!O79-'DealScope monthly model and pri'!L46 -> 12980.25 | M52: ='DealScope monthly model and pri'!M34-'DealScope monthly model and pri'!M16*'Model inputs'!O79-'DealScope monthly model and pri'!M46 -> 12980.25
A53: Hybrid | B53: ='DealScope monthly model and pri'!B35-'DealScope monthly model and pri'!B17*'Model inputs'!O79-'DealScope monthly model and pri'!B47 -> 15405.25 | C53: ='DealScope monthly model and pri'!C35-'DealScope monthly model and pri'!C17*'Model inputs'!O79-'DealScope monthly model and pri'!C47 -> 15405.25 | D53: ='DealScope monthly model and pri'!D35-'DealScope monthly model and pri'!D17*'Model inputs'!O79-'DealScope monthly model and pri'!D47 -> 15405.25 | E53: ='DealScope monthly model and pri'!E35-'DealScope monthly model and pri'!E17*'Model inputs'!O79-'DealScope monthly model and pri'!E47 -> 15405.25 | F53: ='DealScope monthly model and pri'!F35-'DealScope monthly model and pri'!F17*'Model inputs'!O79-'DealScope monthly model and pri'!F47 -> 15405.25 | G53: ='DealScope monthly model and pri'!G35-'DealScope monthly model and pri'!G17*'Model inputs'!O79-'DealScope monthly model and pri'!G47 -> 15405.25 | H53: ='DealScope monthly model and pri'!H35-'DealScope monthly model and pri'!H17*'Model inputs'!O79-'DealScope monthly model and pri'!H47 -> 15405.25 | I53: ='DealScope monthly model and pri'!I35-'DealScope monthly model and pri'!I17*'Model inputs'!O79-'DealScope monthly model and pri'!I47 -> 15405.25 | J53: ='DealScope monthly model and pri'!J35-'DealScope monthly model and pri'!J17*'Model inputs'!O79-'DealScope monthly model and pri'!J47 -> 15405.25 | K53: ='DealScope monthly model and pri'!K35-'DealScope monthly model and pri'!K17*'Model inputs'!O79-'DealScope monthly model and pri'!K47 -> 15405.25 | L53: ='DealScope monthly model and pri'!L35-'DealScope monthly model and pri'!L17*'Model inputs'!O79-'DealScope monthly model and pri'!L47 -> 15405.25 | M53: ='DealScope monthly model and pri'!M35-'DealScope monthly model and pri'!M17*'Model inputs'!O79-'DealScope monthly model and pri'!M47 -> 15405.25
A54: Per audit — base | B54: ='DealScope monthly model and pri'!B36-'DealScope monthly model and pri'!B18*'Model inputs'!O79-'DealScope monthly model and pri'!B48 -> 20255.25 | C54: ='DealScope monthly model and pri'!C36-'DealScope monthly model and pri'!C18*'Model inputs'!O79-'DealScope monthly model and pri'!C48 -> 20255.25 | D54: ='DealScope monthly model and pri'!D36-'DealScope monthly model and pri'!D18*'Model inputs'!O79-'DealScope monthly model and pri'!D48 -> 20255.25 | E54: ='DealScope monthly model and pri'!E36-'DealScope monthly model and pri'!E18*'Model inputs'!O79-'DealScope monthly model and pri'!E48 -> 20255.25 | F54: ='DealScope monthly model and pri'!F36-'DealScope monthly model and pri'!F18*'Model inputs'!O79-'DealScope monthly model and pri'!F48 -> 20255.25 | G54: ='DealScope monthly model and pri'!G36-'DealScope monthly model and pri'!G18*'Model inputs'!O79-'DealScope monthly model and pri'!G48 -> 20255.25 | H54: ='DealScope monthly model and pri'!H36-'DealScope monthly model and pri'!H18*'Model inputs'!O79-'DealScope monthly model and pri'!H48 -> 20255.25 | I54: ='DealScope monthly model and pri'!I36-'DealScope monthly model and pri'!I18*'Model inputs'!O79-'DealScope monthly model and pri'!I48 -> 20255.25 | J54: ='DealScope monthly model and pri'!J36-'DealScope monthly model and pri'!J18*'Model inputs'!O79-'DealScope monthly model and pri'!J48 -> 20255.25 | K54: ='DealScope monthly model and pri'!K36-'DealScope monthly model and pri'!K18*'Model inputs'!O79-'DealScope monthly model and pri'!K48 -> 20255.25 | L54: ='DealScope monthly model and pri'!L36-'DealScope monthly model and pri'!L18*'Model inputs'!O79-'DealScope monthly model and pri'!L48 -> 20255.25 | M54: ='DealScope monthly model and pri'!M36-'DealScope monthly model and pri'!M18*'Model inputs'!O79-'DealScope monthly model and pri'!M48 -> 20255.25
A55: Per audit — high | B55: ='DealScope monthly model and pri'!B37-'DealScope monthly model and pri'!B19*'Model inputs'!O79-'DealScope monthly model and pri'!B49 -> 42080.25 | C55: ='DealScope monthly model and pri'!C37-'DealScope monthly model and pri'!C19*'Model inputs'!O79-'DealScope monthly model and pri'!C49 -> 42080.25 | D55: ='DealScope monthly model and pri'!D37-'DealScope monthly model and pri'!D19*'Model inputs'!O79-'DealScope monthly model and pri'!D49 -> 42080.25 | E55: ='DealScope monthly model and pri'!E37-'DealScope monthly model and pri'!E19*'Model inputs'!O79-'DealScope monthly model and pri'!E49 -> 42080.25 | F55: ='DealScope monthly model and pri'!F37-'DealScope monthly model and pri'!F19*'Model inputs'!O79-'DealScope monthly model and pri'!F49 -> 42080.25 | G55: ='DealScope monthly model and pri'!G37-'DealScope monthly model and pri'!G19*'Model inputs'!O79-'DealScope monthly model and pri'!G49 -> 42080.25 | H55: ='DealScope monthly model and pri'!H37-'DealScope monthly model and pri'!H19*'Model inputs'!O79-'DealScope monthly model and pri'!H49 -> 42080.25 | I55: ='DealScope monthly model and pri'!I37-'DealScope monthly model and pri'!I19*'Model inputs'!O79-'DealScope monthly model and pri'!I49 -> 42080.25 | J55: ='DealScope monthly model and pri'!J37-'DealScope monthly model and pri'!J19*'Model inputs'!O79-'DealScope monthly model and pri'!J49 -> 42080.25 | K55: ='DealScope monthly model and pri'!K37-'DealScope monthly model and pri'!K19*'Model inputs'!O79-'DealScope monthly model and pri'!K49 -> 42080.25 | L55: ='DealScope monthly model and pri'!L37-'DealScope monthly model and pri'!L19*'Model inputs'!O79-'DealScope monthly model and pri'!L49 -> 42080.25 | M55: ='DealScope monthly model and pri'!M37-'DealScope monthly model and pri'!M19*'Model inputs'!O79-'DealScope monthly model and pri'!M49 -> 42080.25
A56: Per audit — low | B56: ='DealScope monthly model and pri'!B38-'DealScope monthly model and pri'!B20*'Model inputs'!O79-'DealScope monthly model and pri'!B50 -> 9342.75 | C56: ='DealScope monthly model and pri'!C38-'DealScope monthly model and pri'!C20*'Model inputs'!O79-'DealScope monthly model and pri'!C50 -> 9342.75 | D56: ='DealScope monthly model and pri'!D38-'DealScope monthly model and pri'!D20*'Model inputs'!O79-'DealScope monthly model and pri'!D50 -> 9342.75 | E56: ='DealScope monthly model and pri'!E38-'DealScope monthly model and pri'!E20*'Model inputs'!O79-'DealScope monthly model and pri'!E50 -> 9342.75 | F56: ='DealScope monthly model and pri'!F38-'DealScope monthly model and pri'!F20*'Model inputs'!O79-'DealScope monthly model and pri'!F50 -> 9342.75 | G56: ='DealScope monthly model and pri'!G38-'DealScope monthly model and pri'!G20*'Model inputs'!O79-'DealScope monthly model and pri'!G50 -> 9342.75 | H56: ='DealScope monthly model and pri'!H38-'DealScope monthly model and pri'!H20*'Model inputs'!O79-'DealScope monthly model and pri'!H50 -> 9342.75 | I56: ='DealScope monthly model and pri'!I38-'DealScope monthly model and pri'!I20*'Model inputs'!O79-'DealScope monthly model and pri'!I50 -> 9342.75 | J56: ='DealScope monthly model and pri'!J38-'DealScope monthly model and pri'!J20*'Model inputs'!O79-'DealScope monthly model and pri'!J50 -> 9342.75 | K56: ='DealScope monthly model and pri'!K38-'DealScope monthly model and pri'!K20*'Model inputs'!O79-'DealScope monthly model and pri'!K50 -> 9342.75 | L56: ='DealScope monthly model and pri'!L38-'DealScope monthly model and pri'!L20*'Model inputs'!O79-'DealScope monthly model and pri'!L50 -> 9342.75 | M56: ='DealScope monthly model and pri'!M38-'DealScope monthly model and pri'!M20*'Model inputs'!O79-'DealScope monthly model and pri'!M50 -> 9342.75
A57: Operating profit | B57: ="" | C57: ="" | D57: ="" | E57: ="" | F57: ="" | G57: ="" | H57: ="" | I57: ="" | ... M57: =""
A58: Annual deal-team | B58: ='DealScope monthly model and pri'!B52-'DealScope monthly model and pri'!B8 -> 12230.25 | C58: ='DealScope monthly model and pri'!C52-'DealScope monthly model and pri'!C8 -> 12230.25 | D58: ='DealScope monthly model and pri'!D52-'DealScope monthly model and pri'!D8 -> 12230.25 | E58: ='DealScope monthly model and pri'!E52-'DealScope monthly model and pri'!E8 -> 12230.25 | F58: ='DealScope monthly model and pri'!F52-'DealScope monthly model and pri'!F8 -> 12230.25 | G58: ='DealScope monthly model and pri'!G52-'DealScope monthly model and pri'!G8 -> 11730.25 | H58: ='DealScope monthly model and pri'!H52-'DealScope monthly model and pri'!H8 -> 11730.25 | I58: ='DealScope monthly model and pri'!I52-'DealScope monthly model and pri'!I8 -> 11730.25 | ... M58: ='DealScope monthly model and pri'!M52-'DealScope monthly model and pri'!M8 -> 11730.25
A59: Hybrid | B59: ='DealScope monthly model and pri'!B53-'DealScope monthly model and pri'!B8 -> 14655.25 | C59: ='DealScope monthly model and pri'!C53-'DealScope monthly model and pri'!C8 -> 14655.25 | D59: ='DealScope monthly model and pri'!D53-'DealScope monthly model and pri'!D8 -> 14655.25 | E59: ='DealScope monthly model and pri'!E53-'DealScope monthly model and pri'!E8 -> 14655.25 | F59: ='DealScope monthly model and pri'!F53-'DealScope monthly model and pri'!F8 -> 14655.25 | G59: ='DealScope monthly model and pri'!G53-'DealScope monthly model and pri'!G8 -> 14155.25 | H59: ='DealScope monthly model and pri'!H53-'DealScope monthly model and pri'!H8 -> 14155.25 | I59: ='DealScope monthly model and pri'!I53-'DealScope monthly model and pri'!I8 -> 14155.25 | ... M59: ='DealScope monthly model and pri'!M53-'DealScope monthly model and pri'!M8 -> 14155.25
A60: Per audit — base | B60: ='DealScope monthly model and pri'!B54-'DealScope monthly model and pri'!B8 -> 19505.25 | C60: ='DealScope monthly model and pri'!C54-'DealScope monthly model and pri'!C8 -> 19505.25 | D60: ='DealScope monthly model and pri'!D54-'DealScope monthly model and pri'!D8 -> 19505.25 | E60: ='DealScope monthly model and pri'!E54-'DealScope monthly model and pri'!E8 -> 19505.25 | F60: ='DealScope monthly model and pri'!F54-'DealScope monthly model and pri'!F8 -> 19505.25 | G60: ='DealScope monthly model and pri'!G54-'DealScope monthly model and pri'!G8 -> 19005.25 | H60: ='DealScope monthly model and pri'!H54-'DealScope monthly model and pri'!H8 -> 19005.25 | I60: ='DealScope monthly model and pri'!I54-'DealScope monthly model and pri'!I8 -> 19005.25 | ... M60: ='DealScope monthly model and pri'!M54-'DealScope monthly model and pri'!M8 -> 19005.25
A61: Per audit — high | B61: ='DealScope monthly model and pri'!B55-'DealScope monthly model and pri'!B8 -> 41330.25 | C61: ='DealScope monthly model and pri'!C55-'DealScope monthly model and pri'!C8 -> 41330.25 | D61: ='DealScope monthly model and pri'!D55-'DealScope monthly model and pri'!D8 -> 41330.25 | E61: ='DealScope monthly model and pri'!E55-'DealScope monthly model and pri'!E8 -> 41330.25 | F61: ='DealScope monthly model and pri'!F55-'DealScope monthly model and pri'!F8 -> 41330.25 | G61: ='DealScope monthly model and pri'!G55-'DealScope monthly model and pri'!G8 -> 40830.25 | H61: ='DealScope monthly model and pri'!H55-'DealScope monthly model and pri'!H8 -> 40830.25 | I61: ='DealScope monthly model and pri'!I55-'DealScope monthly model and pri'!I8 -> 40830.25 | ... M61: ='DealScope monthly model and pri'!M55-'DealScope monthly model and pri'!M8 -> 40830.25
A62: Per audit — low | B62: ='DealScope monthly model and pri'!B56-'DealScope monthly model and pri'!B8 -> 8592.75 | C62: ='DealScope monthly model and pri'!C56-'DealScope monthly model and pri'!C8 -> 8592.75 | D62: ='DealScope monthly model and pri'!D56-'DealScope monthly model and pri'!D8 -> 8592.75 | E62: ='DealScope monthly model and pri'!E56-'DealScope monthly model and pri'!E8 -> 8592.75 | F62: ='DealScope monthly model and pri'!F56-'DealScope monthly model and pri'!F8 -> 8592.75 | G62: ='DealScope monthly model and pri'!G56-'DealScope monthly model and pri'!G8 -> 8092.75 | H62: ='DealScope monthly model and pri'!H56-'DealScope monthly model and pri'!H8 -> 8092.75 | I62: ='DealScope monthly model and pri'!I56-'DealScope monthly model and pri'!I8 -> 8092.75 | ... M62: ='DealScope monthly model and pri'!M56-'DealScope monthly model and pri'!M8 -> 8092.75
A63: Net cash burn | B63: ="" | C63: ="" | D63: ="" | E63: ="" | F63: ="" | G63: ="" | H63: ="" | I63: ="" | ... M63: =""
A64: Annual deal-team | B64: ='DealScope monthly model and pri'!B28+'DealScope monthly model and pri'!B40+'DealScope monthly model and pri'!B46+'DealScope monthly model and pri'!B8-'DealScope monthly model and pri'!B22 -> -118930.25 | C64: ='DealScope monthly model and pri'!C28+'DealScope monthly model and pri'!C40+'DealScope monthly model and pri'!C46+'DealScope monthly model and pri'!C8-'DealScope monthly model and pri'!C22 -> -2530.25 | D64: ='DealScope monthly model and pri'!D28+'DealScope monthly model and pri'!D40+'DealScope monthly model and pri'!D46+'DealScope monthly model and pri'!D8-'DealScope monthly model and pri'!D22 -> -2530.25 | E64: ='DealScope monthly model and pri'!E28+'DealScope monthly model and pri'!E40+'DealScope monthly model and pri'!E46+'DealScope monthly model and pri'!E8-'DealScope monthly model and pri'!E22 -> -2530.25 | F64: ='DealScope monthly model and pri'!F28+'DealScope monthly model and pri'!F40+'DealScope monthly model and pri'!F46+'DealScope monthly model and pri'!F8-'DealScope monthly model and pri'!F22 -> -2530.25 | G64: ='DealScope monthly model and pri'!G28+'DealScope monthly model and pri'!G40+'DealScope monthly model and pri'!G46+'DealScope monthly model and pri'!G8-'DealScope monthly model and pri'!G22 -> -2030.25 | H64: ='DealScope monthly model and pri'!H28+'DealScope monthly model and pri'!H40+'DealScope monthly model and pri'!H46+'DealScope monthly model and pri'!H8-'DealScope monthly model and pri'!H22 -> -2030.25 | I64: ='DealScope monthly model and pri'!I28+'DealScope monthly model and pri'!I40+'DealScope monthly model and pri'!I46+'DealScope monthly model and pri'!I8-'DealScope monthly model and pri'!I22 -> -2030.25 | ... M64: ='DealScope monthly model and pri'!M28+'DealScope monthly model and pri'!M40+'DealScope monthly model and pri'!M46+'DealScope monthly model and pri'!M8-'DealScope monthly model and pri'!M22 -> -2030.25
A65: Hybrid | B65: ='DealScope monthly model and pri'!B29+'DealScope monthly model and pri'!B41+'DealScope monthly model and pri'!B47+'DealScope monthly model and pri'!B8-'DealScope monthly model and pri'!B23 -> -41330.25 | C65: ='DealScope monthly model and pri'!C29+'DealScope monthly model and pri'!C41+'DealScope monthly model and pri'!C47+'DealScope monthly model and pri'!C8-'DealScope monthly model and pri'!C23 -> -12230.25 | D65: ='DealScope monthly model and pri'!D29+'DealScope monthly model and pri'!D41+'DealScope monthly model and pri'!D47+'DealScope monthly model and pri'!D8-'DealScope monthly model and pri'!D23 -> -12230.25 | E65: ='DealScope monthly model and pri'!E29+'DealScope monthly model and pri'!E41+'DealScope monthly model and pri'!E47+'DealScope monthly model and pri'!E8-'DealScope monthly model and pri'!E23 -> -12230.25 | F65: ='DealScope monthly model and pri'!F29+'DealScope monthly model and pri'!F41+'DealScope monthly model and pri'!F47+'DealScope monthly model and pri'!F8-'DealScope monthly model and pri'!F23 -> -12230.25 | G65: ='DealScope monthly model and pri'!G29+'DealScope monthly model and pri'!G41+'DealScope monthly model and pri'!G47+'DealScope monthly model and pri'!G8-'DealScope monthly model and pri'!G23 -> -11730.25 | H65: ='DealScope monthly model and pri'!H29+'DealScope monthly model and pri'!H41+'DealScope monthly model and pri'!H47+'DealScope monthly model and pri'!H8-'DealScope monthly model and pri'!H23 -> -11730.25 | I65: ='DealScope monthly model and pri'!I29+'DealScope monthly model and pri'!I41+'DealScope monthly model and pri'!I47+'DealScope monthly model and pri'!I8-'DealScope monthly model and pri'!I23 -> -11730.25 | ... M65: ='DealScope monthly model and pri'!M29+'DealScope monthly model and pri'!M41+'DealScope monthly model and pri'!M47+'DealScope monthly model and pri'!M8-'DealScope monthly model and pri'!M23 -> -11730.25
A66: Per audit — base | B66: ='DealScope monthly model and pri'!B30+'DealScope monthly model and pri'!B42+'DealScope monthly model and pri'!B48+'DealScope monthly model and pri'!B8-'DealScope monthly model and pri'!B24 -> -19505.25 | C66: ='DealScope monthly model and pri'!C30+'DealScope monthly model and pri'!C42+'DealScope monthly model and pri'!C48+'DealScope monthly model and pri'!C8-'DealScope monthly model and pri'!C24 -> -19505.25 | D66: ='DealScope monthly model and pri'!D30+'DealScope monthly model and pri'!D42+'DealScope monthly model and pri'!D48+'DealScope monthly model and pri'!D8-'DealScope monthly model and pri'!D24 -> -19505.25 | E66: ='DealScope monthly model and pri'!E30+'DealScope monthly model and pri'!E42+'DealScope monthly model and pri'!E48+'DealScope monthly model and pri'!E8-'DealScope monthly model and pri'!E24 -> -19505.25 | F66: ='DealScope monthly model and pri'!F30+'DealScope monthly model and pri'!F42+'DealScope monthly model and pri'!F48+'DealScope monthly model and pri'!F8-'DealScope monthly model and pri'!F24 -> -19505.25 | G66: ='DealScope monthly model and pri'!G30+'DealScope monthly model and pri'!G42+'DealScope monthly model and pri'!G48+'DealScope monthly model and pri'!G8-'DealScope monthly model and pri'!G24 -> -19005.25 | H66: ='DealScope monthly model and pri'!H30+'DealScope monthly model and pri'!H42+'DealScope monthly model and pri'!H48+'DealScope monthly model and pri'!H8-'DealScope monthly model and pri'!H24 -> -19005.25 | I66: ='DealScope monthly model and pri'!I30+'DealScope monthly model and pri'!I42+'DealScope monthly model and pri'!I48+'DealScope monthly model and pri'!I8-'DealScope monthly model and pri'!I24 -> -19005.25 | ... M66: ='DealScope monthly model and pri'!M30+'DealScope monthly model and pri'!M42+'DealScope monthly model and pri'!M48+'DealScope monthly model and pri'!M8-'DealScope monthly model and pri'!M24 -> -19005.25
A67: Per audit — high | B67: ='DealScope monthly model and pri'!B31+'DealScope monthly model and pri'!B43+'DealScope monthly model and pri'!B49+'DealScope monthly model and pri'!B8-'DealScope monthly model and pri'!B25 -> -41330.25 | C67: ='DealScope monthly model and pri'!C31+'DealScope monthly model and pri'!C43+'DealScope monthly model and pri'!C49+'DealScope monthly model and pri'!C8-'DealScope monthly model and pri'!C25 -> -41330.25 | D67: ='DealScope monthly model and pri'!D31+'DealScope monthly model and pri'!D43+'DealScope monthly model and pri'!D49+'DealScope monthly model and pri'!D8-'DealScope monthly model and pri'!D25 -> -41330.25 | E67: ='DealScope monthly model and pri'!E31+'DealScope monthly model and pri'!E43+'DealScope monthly model and pri'!E49+'DealScope monthly model and pri'!E8-'DealScope monthly model and pri'!E25 -> -41330.25 | F67: ='DealScope monthly model and pri'!F31+'DealScope monthly model and pri'!F43+'DealScope monthly model and pri'!F49+'DealScope monthly model and pri'!F8-'DealScope monthly model and pri'!F25 -> -41330.25 | G67: ='DealScope monthly model and pri'!G31+'DealScope monthly model and pri'!G43+'DealScope monthly model and pri'!G49+'DealScope monthly model and pri'!G8-'DealScope monthly model and pri'!G25 -> -40830.25 | H67: ='DealScope monthly model and pri'!H31+'DealScope monthly model and pri'!H43+'DealScope monthly model and pri'!H49+'DealScope monthly model and pri'!H8-'DealScope monthly model and pri'!H25 -> -40830.25 | I67: ='DealScope monthly model and pri'!I31+'DealScope monthly model and pri'!I43+'DealScope monthly model and pri'!I49+'DealScope monthly model and pri'!I8-'DealScope monthly model and pri'!I25 -> -40830.25 | ... M67: ='DealScope monthly model and pri'!M31+'DealScope monthly model and pri'!M43+'DealScope monthly model and pri'!M49+'DealScope monthly model and pri'!M8-'DealScope monthly model and pri'!M25 -> -40830.25
A68: Per audit — low | B68: ='DealScope monthly model and pri'!B32+'DealScope monthly model and pri'!B44+'DealScope monthly model and pri'!B50+'DealScope monthly model and pri'!B8-'DealScope monthly model and pri'!B26 -> -8592.75 | C68: ='DealScope monthly model and pri'!C32+'DealScope monthly model and pri'!C44+'DealScope monthly model and pri'!C50+'DealScope monthly model and pri'!C8-'DealScope monthly model and pri'!C26 -> -8592.75 | D68: ='DealScope monthly model and pri'!D32+'DealScope monthly model and pri'!D44+'DealScope monthly model and pri'!D50+'DealScope monthly model and pri'!D8-'DealScope monthly model and pri'!D26 -> -8592.75 | E68: ='DealScope monthly model and pri'!E32+'DealScope monthly model and pri'!E44+'DealScope monthly model and pri'!E50+'DealScope monthly model and pri'!E8-'DealScope monthly model and pri'!E26 -> -8592.75 | F68: ='DealScope monthly model and pri'!F32+'DealScope monthly model and pri'!F44+'DealScope monthly model and pri'!F50+'DealScope monthly model and pri'!F8-'DealScope monthly model and pri'!F26 -> -8592.75 | G68: ='DealScope monthly model and pri'!G32+'DealScope monthly model and pri'!G44+'DealScope monthly model and pri'!G50+'DealScope monthly model and pri'!G8-'DealScope monthly model and pri'!G26 -> -8092.75 | H68: ='DealScope monthly model and pri'!H32+'DealScope monthly model and pri'!H44+'DealScope monthly model and pri'!H50+'DealScope monthly model and pri'!H8-'DealScope monthly model and pri'!H26 -> -8092.75 | I68: ='DealScope monthly model and pri'!I32+'DealScope monthly model and pri'!I44+'DealScope monthly model and pri'!I50+'DealScope monthly model and pri'!I8-'DealScope monthly model and pri'!I26 -> -8092.75 | ... M68: ='DealScope monthly model and pri'!M32+'DealScope monthly model and pri'!M44+'DealScope monthly model and pri'!M50+'DealScope monthly model and pri'!M8-'DealScope monthly model and pri'!M26 -> -8092.75
A69: Gross margin by pricing | B69: =IFERROR(IF('DealScope monthly model and pri'!B33="",0,'DealScope monthly model and pri'!B33)/IF('DealScope monthly model and pri'!B15="",0,'DealScope monthly model and pri'!B15),"") | C69: =IFERROR(IF('DealScope monthly model and pri'!C33="",0,'DealScope monthly model and pri'!C33)/IF('DealScope monthly model and pri'!C15="",0,'DealScope monthly model and pri'!C15),"") | D69: =IFERROR(IF('DealScope monthly model and pri'!D33="",0,'DealScope monthly model and pri'!D33)/IF('DealScope monthly model and pri'!D15="",0,'DealScope monthly model and pri'!D15),"") | E69: =IFERROR(IF('DealScope monthly model and pri'!E33="",0,'DealScope monthly model and pri'!E33)/IF('DealScope monthly model and pri'!E15="",0,'DealScope monthly model and pri'!E15),"") | F69: =IFERROR(IF('DealScope monthly model and pri'!F33="",0,'DealScope monthly model and pri'!F33)/IF('DealScope monthly model and pri'!F15="",0,'DealScope monthly model and pri'!F15),"") | G69: =IFERROR(IF('DealScope monthly model and pri'!G33="",0,'DealScope monthly model and pri'!G33)/IF('DealScope monthly model and pri'!G15="",0,'DealScope monthly model and pri'!G15),"") | H69: =IFERROR(IF('DealScope monthly model and pri'!H33="",0,'DealScope monthly model and pri'!H33)/IF('DealScope monthly model and pri'!H15="",0,'DealScope monthly model and pri'!H15),"") | I69: =IFERROR(IF('DealScope monthly model and pri'!I33="",0,'DealScope monthly model and pri'!I33)/IF('DealScope monthly model and pri'!I15="",0,'DealScope monthly model and pri'!I15),"") | ... M69: =IFERROR(IF('DealScope monthly model and pri'!M33="",0,'DealScope monthly model and pri'!M33)/IF('DealScope monthly model and pri'!M15="",0,'DealScope monthly model and pri'!M15),"")
A70: Annual deal-team | B70: =IFERROR('DealScope monthly model and pri'!B34/'DealScope monthly model and pri'!B16,"") -> 0.90535 | C70: =IFERROR('DealScope monthly model and pri'!C34/'DealScope monthly model and pri'!C16,"") -> 0.90535 | D70: =IFERROR('DealScope monthly model and pri'!D34/'DealScope monthly model and pri'!D16,"") -> 0.90535 | E70: =IFERROR('DealScope monthly model and pri'!E34/'DealScope monthly model and pri'!E16,"") -> 0.90535 | F70: =IFERROR('DealScope monthly model and pri'!F34/'DealScope monthly model and pri'!F16,"") -> 0.90535 | G70: =IFERROR('DealScope monthly model and pri'!G34/'DealScope monthly model and pri'!G16,"") -> 0.90535 | H70: =IFERROR('DealScope monthly model and pri'!H34/'DealScope monthly model and pri'!H16,"") -> 0.90535 | I70: =IFERROR('DealScope monthly model and pri'!I34/'DealScope monthly model and pri'!I16,"") -> 0.90535 | ... M70: =IFERROR('DealScope monthly model and pri'!M34/'DealScope monthly model and pri'!M16,"") -> 0.90535
A71: Hybrid | B71: =IFERROR('DealScope monthly model and pri'!B35/'DealScope monthly model and pri'!B17,"") -> 0.91887143 | C71: =IFERROR('DealScope monthly model and pri'!C35/'DealScope monthly model and pri'!C17,"") -> 0.91887143 | D71: =IFERROR('DealScope monthly model and pri'!D35/'DealScope monthly model and pri'!D17,"") -> 0.91887143 | E71: =IFERROR('DealScope monthly model and pri'!E35/'DealScope monthly model and pri'!E17,"") -> 0.91887143 | F71: =IFERROR('DealScope monthly model and pri'!F35/'DealScope monthly model and pri'!F17,"") -> 0.91887143 | G71: =IFERROR('DealScope monthly model and pri'!G35/'DealScope monthly model and pri'!G17,"") -> 0.91887143 | H71: =IFERROR('DealScope monthly model and pri'!H35/'DealScope monthly model and pri'!H17,"") -> 0.91887143 | I71: =IFERROR('DealScope monthly model and pri'!I35/'DealScope monthly model and pri'!I17,"") -> 0.91887143 | ... M71: =IFERROR('DealScope monthly model and pri'!M35/'DealScope monthly model and pri'!M17,"") -> 0.91887143
A72: Per audit — base | B72: =IFERROR('DealScope monthly model and pri'!B36/'DealScope monthly model and pri'!B18,"") -> 0.9369 | C72: =IFERROR('DealScope monthly model and pri'!C36/'DealScope monthly model and pri'!C18,"") -> 0.9369 | D72: =IFERROR('DealScope monthly model and pri'!D36/'DealScope monthly model and pri'!D18,"") -> 0.9369 | E72: =IFERROR('DealScope monthly model and pri'!E36/'DealScope monthly model and pri'!E18,"") -> 0.9369 | F72: =IFERROR('DealScope monthly model and pri'!F36/'DealScope monthly model and pri'!F18,"") -> 0.9369 | G72: =IFERROR('DealScope monthly model and pri'!G36/'DealScope monthly model and pri'!G18,"") -> 0.9369 | H72: =IFERROR('DealScope monthly model and pri'!H36/'DealScope monthly model and pri'!H18,"") -> 0.9369 | I72: =IFERROR('DealScope monthly model and pri'!I36/'DealScope monthly model and pri'!I18,"") -> 0.9369 | ... M72: =IFERROR('DealScope monthly model and pri'!M36/'DealScope monthly model and pri'!M18,"") -> 0.9369
A73: Per audit — high | B73: =IFERROR('DealScope monthly model and pri'!B37/'DealScope monthly model and pri'!B19,"") -> 0.96845 | C73: =IFERROR('DealScope monthly model and pri'!C37/'DealScope monthly model and pri'!C19,"") -> 0.96845 | D73: =IFERROR('DealScope monthly model and pri'!D37/'DealScope monthly model and pri'!D19,"") -> 0.96845 | E73: =IFERROR('DealScope monthly model and pri'!E37/'DealScope monthly model and pri'!E19,"") -> 0.96845 | F73: =IFERROR('DealScope monthly model and pri'!F37/'DealScope monthly model and pri'!F19,"") -> 0.96845 | G73: =IFERROR('DealScope monthly model and pri'!G37/'DealScope monthly model and pri'!G19,"") -> 0.96845 | H73: =IFERROR('DealScope monthly model and pri'!H37/'DealScope monthly model and pri'!H19,"") -> 0.96845 | I73: =IFERROR('DealScope monthly model and pri'!I37/'DealScope monthly model and pri'!I19,"") -> 0.96845 | ... M73: =IFERROR('DealScope monthly model and pri'!M37/'DealScope monthly model and pri'!M19,"") -> 0.96845
A74: Per audit — low | B74: =IFERROR('DealScope monthly model and pri'!B38/'DealScope monthly model and pri'!B20,"") -> 0.8738 | C74: =IFERROR('DealScope monthly model and pri'!C38/'DealScope monthly model and pri'!C20,"") -> 0.8738 | D74: =IFERROR('DealScope monthly model and pri'!D38/'DealScope monthly model and pri'!D20,"") -> 0.8738 | E74: =IFERROR('DealScope monthly model and pri'!E38/'DealScope monthly model and pri'!E20,"") -> 0.8738 | F74: =IFERROR('DealScope monthly model and pri'!F38/'DealScope monthly model and pri'!F20,"") -> 0.8738 | G74: =IFERROR('DealScope monthly model and pri'!G38/'DealScope monthly model and pri'!G20,"") -> 0.8738 | H74: =IFERROR('DealScope monthly model and pri'!H38/'DealScope monthly model and pri'!H20,"") -> 0.8738 | I74: =IFERROR('DealScope monthly model and pri'!I38/'DealScope monthly model and pri'!I20,"") -> 0.8738 | ... M74: =IFERROR('DealScope monthly model and pri'!M38/'DealScope monthly model and pri'!M20,"") -> 0.8738
A75: Contribution margin by pricing | B75: =IFERROR(IF('DealScope monthly model and pri'!B51="",0,'DealScope monthly model and pri'!B51)/IF('DealScope monthly model and pri'!B15="",0,'DealScope monthly model and pri'!B15),"") | C75: =IFERROR(IF('DealScope monthly model and pri'!C51="",0,'DealScope monthly model and pri'!C51)/IF('DealScope monthly model and pri'!C15="",0,'DealScope monthly model and pri'!C15),"") | D75: =IFERROR(IF('DealScope monthly model and pri'!D51="",0,'DealScope monthly model and pri'!D51)/IF('DealScope monthly model and pri'!D15="",0,'DealScope monthly model and pri'!D15),"") | E75: =IFERROR(IF('DealScope monthly model and pri'!E51="",0,'DealScope monthly model and pri'!E51)/IF('DealScope monthly model and pri'!E15="",0,'DealScope monthly model and pri'!E15),"") | F75: =IFERROR(IF('DealScope monthly model and pri'!F51="",0,'DealScope monthly model and pri'!F51)/IF('DealScope monthly model and pri'!F15="",0,'DealScope monthly model and pri'!F15),"") | G75: =IFERROR(IF('DealScope monthly model and pri'!G51="",0,'DealScope monthly model and pri'!G51)/IF('DealScope monthly model and pri'!G15="",0,'DealScope monthly model and pri'!G15),"") | H75: =IFERROR(IF('DealScope monthly model and pri'!H51="",0,'DealScope monthly model and pri'!H51)/IF('DealScope monthly model and pri'!H15="",0,'DealScope monthly model and pri'!H15),"") | I75: =IFERROR(IF('DealScope monthly model and pri'!I51="",0,'DealScope monthly model and pri'!I51)/IF('DealScope monthly model and pri'!I15="",0,'DealScope monthly model and pri'!I15),"") | ... M75: =IFERROR(IF('DealScope monthly model and pri'!M51="",0,'DealScope monthly model and pri'!M51)/IF('DealScope monthly model and pri'!M15="",0,'DealScope monthly model and pri'!M15),"")
A76: Annual deal-team | B76: =IFERROR('DealScope monthly model and pri'!B52/'DealScope monthly model and pri'!B16,"") -> 0.86535 | C76: =IFERROR('DealScope monthly model and pri'!C52/'DealScope monthly model and pri'!C16,"") -> 0.86535 | D76: =IFERROR('DealScope monthly model and pri'!D52/'DealScope monthly model and pri'!D16,"") -> 0.86535 | E76: =IFERROR('DealScope monthly model and pri'!E52/'DealScope monthly model and pri'!E16,"") -> 0.86535 | F76: =IFERROR('DealScope monthly model and pri'!F52/'DealScope monthly model and pri'!F16,"") -> 0.86535 | G76: =IFERROR('DealScope monthly model and pri'!G52/'DealScope monthly model and pri'!G16,"") -> 0.86535 | H76: =IFERROR('DealScope monthly model and pri'!H52/'DealScope monthly model and pri'!H16,"") -> 0.86535 | I76: =IFERROR('DealScope monthly model and pri'!I52/'DealScope monthly model and pri'!I16,"") -> 0.86535 | ... M76: =IFERROR('DealScope monthly model and pri'!M52/'DealScope monthly model and pri'!M16,"") -> 0.86535
A77: Hybrid | B77: =IFERROR('DealScope monthly model and pri'!B53/'DealScope monthly model and pri'!B17,"") -> 0.8803 | C77: =IFERROR('DealScope monthly model and pri'!C53/'DealScope monthly model and pri'!C17,"") -> 0.8803 | D77: =IFERROR('DealScope monthly model and pri'!D53/'DealScope monthly model and pri'!D17,"") -> 0.8803 | E77: =IFERROR('DealScope monthly model and pri'!E53/'DealScope monthly model and pri'!E17,"") -> 0.8803 | F77: =IFERROR('DealScope monthly model and pri'!F53/'DealScope monthly model and pri'!F17,"") -> 0.8803 | G77: =IFERROR('DealScope monthly model and pri'!G53/'DealScope monthly model and pri'!G17,"") -> 0.8803 | H77: =IFERROR('DealScope monthly model and pri'!H53/'DealScope monthly model and pri'!H17,"") -> 0.8803 | I77: =IFERROR('DealScope monthly model and pri'!I53/'DealScope monthly model and pri'!I17,"") -> 0.8803 | ... M77: =IFERROR('DealScope monthly model and pri'!M53/'DealScope monthly model and pri'!M17,"") -> 0.8803
A78: Per audit — base | B78: =IFERROR('DealScope monthly model and pri'!B54/'DealScope monthly model and pri'!B18,"") -> 0.90023333 | C78: =IFERROR('DealScope monthly model and pri'!C54/'DealScope monthly model and pri'!C18,"") -> 0.90023333 | D78: =IFERROR('DealScope monthly model and pri'!D54/'DealScope monthly model and pri'!D18,"") -> 0.90023333 | E78: =IFERROR('DealScope monthly model and pri'!E54/'DealScope monthly model and pri'!E18,"") -> 0.90023333 | F78: =IFERROR('DealScope monthly model and pri'!F54/'DealScope monthly model and pri'!F18,"") -> 0.90023333 | G78: =IFERROR('DealScope monthly model and pri'!G54/'DealScope monthly model and pri'!G18,"") -> 0.90023333 | H78: =IFERROR('DealScope monthly model and pri'!H54/'DealScope monthly model and pri'!H18,"") -> 0.90023333 | I78: =IFERROR('DealScope monthly model and pri'!I54/'DealScope monthly model and pri'!I18,"") -> 0.90023333 | ... M78: =IFERROR('DealScope monthly model and pri'!M54/'DealScope monthly model and pri'!M18,"") -> 0.90023333
A79: Per audit — high | B79: =IFERROR('DealScope monthly model and pri'!B55/'DealScope monthly model and pri'!B19,"") -> 0.93511667 | C79: =IFERROR('DealScope monthly model and pri'!C55/'DealScope monthly model and pri'!C19,"") -> 0.93511667 | D79: =IFERROR('DealScope monthly model and pri'!D55/'DealScope monthly model and pri'!D19,"") -> 0.93511667 | E79: =IFERROR('DealScope monthly model and pri'!E55/'DealScope monthly model and pri'!E19,"") -> 0.93511667 | F79: =IFERROR('DealScope monthly model and pri'!F55/'DealScope monthly model and pri'!F19,"") -> 0.93511667 | G79: =IFERROR('DealScope monthly model and pri'!G55/'DealScope monthly model and pri'!G19,"") -> 0.93511667 | H79: =IFERROR('DealScope monthly model and pri'!H55/'DealScope monthly model and pri'!H19,"") -> 0.93511667 | I79: =IFERROR('DealScope monthly model and pri'!I55/'DealScope monthly model and pri'!I19,"") -> 0.93511667 | ... M79: =IFERROR('DealScope monthly model and pri'!M55/'DealScope monthly model and pri'!M19,"") -> 0.93511667
A80: Per audit — low | B80: =IFERROR('DealScope monthly model and pri'!B56/'DealScope monthly model and pri'!B20,"") -> 0.83046667 | C80: =IFERROR('DealScope monthly model and pri'!C56/'DealScope monthly model and pri'!C20,"") -> 0.83046667 | D80: =IFERROR('DealScope monthly model and pri'!D56/'DealScope monthly model and pri'!D20,"") -> 0.83046667 | E80: =IFERROR('DealScope monthly model and pri'!E56/'DealScope monthly model and pri'!E20,"") -> 0.83046667 | F80: =IFERROR('DealScope monthly model and pri'!F56/'DealScope monthly model and pri'!F20,"") -> 0.83046667 | G80: =IFERROR('DealScope monthly model and pri'!G56/'DealScope monthly model and pri'!G20,"") -> 0.83046667 | H80: =IFERROR('DealScope monthly model and pri'!H56/'DealScope monthly model and pri'!H20,"") -> 0.83046667 | I80: =IFERROR('DealScope monthly model and pri'!I56/'DealScope monthly model and pri'!I20,"") -> 0.83046667 | ... M80: =IFERROR('DealScope monthly model and pri'!M56/'DealScope monthly model and pri'!M20,"") -> 0.83046667
A81: Plan Audits delivered | B81: =IF(SUM(IF(IF('Model inputs'!B179="",0,1)="",0,IF('Model inputs'!B179="",0,1)),IF(IF('Model inputs'!B180="",0,1)="",0,IF('Model inputs'!B180="",0,1)),IF(IF('Model inputs'!B181="",0,1)="",0,IF('Model inputs'!B181="",0,1)),IF(IF('Model inputs'!B182="",0,1)="",0,IF('Model inputs'!B182="",0,1)),IF(IF('Model inputs'!B183="",0,1)="",0,IF('Model inputs'!B183="",0,1)))=0,"",SUM('Model inputs'!B179,'Model inputs'!B180,'Model inputs'!B181,'Model inputs'!B182,'Model inputs'!B183)) -> 15 | C81: =IF(SUM(IF(IF('Model inputs'!B184="",0,1)="",0,IF('Model inputs'!B184="",0,1)),IF(IF('Model inputs'!B185="",0,1)="",0,IF('Model inputs'!B185="",0,1)),IF(IF('Model inputs'!B186="",0,1)="",0,IF('Model inputs'!B186="",0,1)),IF(IF('Model inputs'!B187="",0,1)="",0,IF('Model inputs'!B187="",0,1)),IF(IF('Model inputs'!B188="",0,1)="",0,IF('Model inputs'!B188="",0,1)))=0,"",SUM('Model inputs'!B184,'Model inputs'!B185,'Model inputs'!B186,'Model inputs'!B187,'Model inputs'!B188)) -> 15 | D81: =IF(SUM(IF(IF('Model inputs'!B189="",0,1)="",0,IF('Model inputs'!B189="",0,1)),IF(IF('Model inputs'!B190="",0,1)="",0,IF('Model inputs'!B190="",0,1)),IF(IF('Model inputs'!B191="",0,1)="",0,IF('Model inputs'!B191="",0,1)),IF(IF('Model inputs'!B192="",0,1)="",0,IF('Model inputs'!B192="",0,1)),IF(IF('Model inputs'!B193="",0,1)="",0,IF('Model inputs'!B193="",0,1)))=0,"",SUM('Model inputs'!B189,'Model inputs'!B190,'Model inputs'!B191,'Model inputs'!B192,'Model inputs'!B193)) -> 15 | E81: =IF(SUM(IF(IF('Model inputs'!B194="",0,1)="",0,IF('Model inputs'!B194="",0,1)),IF(IF('Model inputs'!B195="",0,1)="",0,IF('Model inputs'!B195="",0,1)),IF(IF('Model inputs'!B196="",0,1)="",0,IF('Model inputs'!B196="",0,1)),IF(IF('Model inputs'!B197="",0,1)="",0,IF('Model inputs'!B197="",0,1)),IF(IF('Model inputs'!B198="",0,1)="",0,IF('Model inputs'!B198="",0,1)))=0,"",SUM('Model inputs'!B194,'Model inputs'!B195,'Model inputs'!B196,'Model inputs'!B197,'Model inputs'!B198)) -> 15 | F81: =IF(SUM(IF(IF('Model inputs'!B199="",0,1)="",0,IF('Model inputs'!B199="",0,1)),IF(IF('Model inputs'!B200="",0,1)="",0,IF('Model inputs'!B200="",0,1)),IF(IF('Model inputs'!B201="",0,1)="",0,IF('Model inputs'!B201="",0,1)),IF(IF('Model inputs'!B202="",0,1)="",0,IF('Model inputs'!B202="",0,1)),IF(IF('Model inputs'!B203="",0,1)="",0,IF('Model inputs'!B203="",0,1)))=0,"",SUM('Model inputs'!B199,'Model inputs'!B200,'Model inputs'!B201,'Model inputs'!B202,'Model inputs'!B203)) -> 15 | G81: =IF(SUM(IF(IF('Model inputs'!B204="",0,1)="",0,IF('Model inputs'!B204="",0,1)),IF(IF('Model inputs'!B205="",0,1)="",0,IF('Model inputs'!B205="",0,1)),IF(IF('Model inputs'!B206="",0,1)="",0,IF('Model inputs'!B206="",0,1)),IF(IF('Model inputs'!B207="",0,1)="",0,IF('Model inputs'!B207="",0,1)),IF(IF('Model inputs'!B208="",0,1)="",0,IF('Model inputs'!B208="",0,1)))=0,"",SUM('Model inputs'!B204,'Model inputs'!B205,'Model inputs'!B206,'Model inputs'!B207,'Model inputs'!B208)) -> 15 | H81: =IF(SUM(IF(IF('Model inputs'!B209="",0,1)="",0,IF('Model inputs'!B209="",0,1)),IF(IF('Model inputs'!B210="",0,1)="",0,IF('Model inputs'!B210="",0,1)),IF(IF('Model inputs'!B211="",0,1)="",0,IF('Model inputs'!B211="",0,1)),IF(IF('Model inputs'!B212="",0,1)="",0,IF('Model inputs'!B212="",0,1)),IF(IF('Model inputs'!B213="",0,1)="",0,IF('Model inputs'!B213="",0,1)))=0,"",SUM('Model inputs'!B209,'Model inputs'!B210,'Model inputs'!B211,'Model inputs'!B212,'Model inputs'!B213)) -> 15 | I81: =IF(SUM(IF(IF('Model inputs'!B214="",0,1)="",0,IF('Model inputs'!B214="",0,1)),IF(IF('Model inputs'!B215="",0,1)="",0,IF('Model inputs'!B215="",0,1)),IF(IF('Model inputs'!B216="",0,1)="",0,IF('Model inputs'!B216="",0,1)),IF(IF('Model inputs'!B217="",0,1)="",0,IF('Model inputs'!B217="",0,1)),IF(IF('Model inputs'!B218="",0,1)="",0,IF('Model inputs'!B218="",0,1)))=0,"",SUM('Model inputs'!B214,'Model inputs'!B215,'Model inputs'!B216,'Model inputs'!B217,'Model inputs'!B218)) -> 15 | J81: =IF(SUM(IF(IF('Model inputs'!B219="",0,1)="",0,IF('Model inputs'!B219="",0,1)),IF(IF('Model inputs'!B220="",0,1)="",0,IF('Model inputs'!B220="",0,1)),IF(IF('Model inputs'!B221="",0,1)="",0,IF('Model inputs'!B221="",0,1)),IF(IF('Model inputs'!B222="",0,1)="",0,IF('Model inputs'!B222="",0,1)),IF(IF('Model inputs'!B223="",0,1)="",0,IF('Model inputs'!B223="",0,1)))=0,"",SUM('Model inputs'!B219,'Model inputs'!B220,'Model inputs'!B221,'Model inputs'!B222,'Model inputs'!B223)) -> 15 | K81: =IF(SUM(IF(IF('Model inputs'!B224="",0,1)="",0,IF('Model inputs'!B224="",0,1)),IF(IF('Model inputs'!B225="",0,1)="",0,IF('Model inputs'!B225="",0,1)),IF(IF('Model inputs'!B226="",0,1)="",0,IF('Model inputs'!B226="",0,1)),IF(IF('Model inputs'!B227="",0,1)="",0,IF('Model inputs'!B227="",0,1)),IF(IF('Model inputs'!B228="",0,1)="",0,IF('Model inputs'!B228="",0,1)))=0,"",SUM('Model inputs'!B224,'Model inputs'!B225,'Model inputs'!B226,'Model inputs'!B227,'Model inputs'!B228)) -> 15 | L81: =IF(SUM(IF(IF('Model inputs'!B229="",0,1)="",0,IF('Model inputs'!B229="",0,1)),IF(IF('Model inputs'!B230="",0,1)="",0,IF('Model inputs'!B230="",0,1)),IF(IF('Model inputs'!B231="",0,1)="",0,IF('Model inputs'!B231="",0,1)),IF(IF('Model inputs'!B232="",0,1)="",0,IF('Model inputs'!B232="",0,1)),IF(IF('Model inputs'!B233="",0,1)="",0,IF('Model inputs'!B233="",0,1)))=0,"",SUM('Model inputs'!B229,'Model inputs'!B230,'Model inputs'!B231,'Model inputs'!B232,'Model inputs'!B233)) -> 15 | M81: =IF(SUM(IF(IF('Model inputs'!B234="",0,1)="",0,IF('Model inputs'!B234="",0,1)),IF(IF('Model inputs'!B235="",0,1)="",0,IF('Model inputs'!B235="",0,1)),IF(IF('Model inputs'!B236="",0,1)="",0,IF('Model inputs'!B236="",0,1)),IF(IF('Model inputs'!B237="",0,1)="",0,IF('Model inputs'!B237="",0,1)),IF(IF('Model inputs'!B238="",0,1)="",0,IF('Model inputs'!B238="",0,1)))=0,"",SUM('Model inputs'!B234,'Model inputs'!B235,'Model inputs'!B236,'Model inputs'!B237,'Model inputs'!B238)) -> 15
A82: Plan Earned revenue | B82: =IF(SUM(IF(IF('Model inputs'!B239="",0,1)="",0,IF('Model inputs'!B239="",0,1)),IF(IF('Model inputs'!B240="",0,1)="",0,IF('Model inputs'!B240="",0,1)),IF(IF('Model inputs'!B241="",0,1)="",0,IF('Model inputs'!B241="",0,1)),IF(IF('Model inputs'!B242="",0,1)="",0,IF('Model inputs'!B242="",0,1)),IF(IF('Model inputs'!B243="",0,1)="",0,IF('Model inputs'!B243="",0,1)))=0,"",SUM('Model inputs'!B239,'Model inputs'!B240,'Model inputs'!B241,'Model inputs'!B242,'Model inputs'!B243)) -> 22500 | C82: =IF(SUM(IF(IF('Model inputs'!B244="",0,1)="",0,IF('Model inputs'!B244="",0,1)),IF(IF('Model inputs'!B245="",0,1)="",0,IF('Model inputs'!B245="",0,1)),IF(IF('Model inputs'!B246="",0,1)="",0,IF('Model inputs'!B246="",0,1)),IF(IF('Model inputs'!B247="",0,1)="",0,IF('Model inputs'!B247="",0,1)),IF(IF('Model inputs'!B248="",0,1)="",0,IF('Model inputs'!B248="",0,1)))=0,"",SUM('Model inputs'!B244,'Model inputs'!B245,'Model inputs'!B246,'Model inputs'!B247,'Model inputs'!B248)) -> 22500 | D82: =IF(SUM(IF(IF('Model inputs'!B249="",0,1)="",0,IF('Model inputs'!B249="",0,1)),IF(IF('Model inputs'!B250="",0,1)="",0,IF('Model inputs'!B250="",0,1)),IF(IF('Model inputs'!B251="",0,1)="",0,IF('Model inputs'!B251="",0,1)),IF(IF('Model inputs'!B252="",0,1)="",0,IF('Model inputs'!B252="",0,1)),IF(IF('Model inputs'!B253="",0,1)="",0,IF('Model inputs'!B253="",0,1)))=0,"",SUM('Model inputs'!B249,'Model inputs'!B250,'Model inputs'!B251,'Model inputs'!B252,'Model inputs'!B253)) -> 22500 | E82: =IF(SUM(IF(IF('Model inputs'!B254="",0,1)="",0,IF('Model inputs'!B254="",0,1)),IF(IF('Model inputs'!B255="",0,1)="",0,IF('Model inputs'!B255="",0,1)),IF(IF('Model inputs'!B256="",0,1)="",0,IF('Model inputs'!B256="",0,1)),IF(IF('Model inputs'!B257="",0,1)="",0,IF('Model inputs'!B257="",0,1)),IF(IF('Model inputs'!B258="",0,1)="",0,IF('Model inputs'!B258="",0,1)))=0,"",SUM('Model inputs'!B254,'Model inputs'!B255,'Model inputs'!B256,'Model inputs'!B257,'Model inputs'!B258)) -> 22500 | F82: =IF(SUM(IF(IF('Model inputs'!B259="",0,1)="",0,IF('Model inputs'!B259="",0,1)),IF(IF('Model inputs'!B260="",0,1)="",0,IF('Model inputs'!B260="",0,1)),IF(IF('Model inputs'!B261="",0,1)="",0,IF('Model inputs'!B261="",0,1)),IF(IF('Model inputs'!B262="",0,1)="",0,IF('Model inputs'!B262="",0,1)),IF(IF('Model inputs'!B263="",0,1)="",0,IF('Model inputs'!B263="",0,1)))=0,"",SUM('Model inputs'!B259,'Model inputs'!B260,'Model inputs'!B261,'Model inputs'!B262,'Model inputs'!B263)) -> 22500 | G82: =IF(SUM(IF(IF('Model inputs'!B264="",0,1)="",0,IF('Model inputs'!B264="",0,1)),IF(IF('Model inputs'!B265="",0,1)="",0,IF('Model inputs'!B265="",0,1)),IF(IF('Model inputs'!B266="",0,1)="",0,IF('Model inputs'!B266="",0,1)),IF(IF('Model inputs'!B267="",0,1)="",0,IF('Model inputs'!B267="",0,1)),IF(IF('Model inputs'!B268="",0,1)="",0,IF('Model inputs'!B268="",0,1)))=0,"",SUM('Model inputs'!B264,'Model inputs'!B265,'Model inputs'!B266,'Model inputs'!B267,'Model inputs'!B268)) -> 22500 | H82: =IF(SUM(IF(IF('Model inputs'!B269="",0,1)="",0,IF('Model inputs'!B269="",0,1)),IF(IF('Model inputs'!B270="",0,1)="",0,IF('Model inputs'!B270="",0,1)),IF(IF('Model inputs'!B271="",0,1)="",0,IF('Model inputs'!B271="",0,1)),IF(IF('Model inputs'!B272="",0,1)="",0,IF('Model inputs'!B272="",0,1)),IF(IF('Model inputs'!B273="",0,1)="",0,IF('Model inputs'!B273="",0,1)))=0,"",SUM('Model inputs'!B269,'Model inputs'!B270,'Model inputs'!B271,'Model inputs'!B272,'Model inputs'!B273)) -> 22500 | I82: =IF(SUM(IF(IF('Model inputs'!B274="",0,1)="",0,IF('Model inputs'!B274="",0,1)),IF(IF('Model inputs'!B275="",0,1)="",0,IF('Model inputs'!B275="",0,1)),IF(IF('Model inputs'!B276="",0,1)="",0,IF('Model inputs'!B276="",0,1)),IF(IF('Model inputs'!B277="",0,1)="",0,IF('Model inputs'!B277="",0,1)),IF(IF('Model inputs'!B278="",0,1)="",0,IF('Model inputs'!B278="",0,1)))=0,"",SUM('Model inputs'!B274,'Model inputs'!B275,'Model inputs'!B276,'Model inputs'!B277,'Model inputs'!B278)) -> 22500 | J82: =IF(SUM(IF(IF('Model inputs'!B279="",0,1)="",0,IF('Model inputs'!B279="",0,1)),IF(IF('Model inputs'!B280="",0,1)="",0,IF('Model inputs'!B280="",0,1)),IF(IF('Model inputs'!B281="",0,1)="",0,IF('Model inputs'!B281="",0,1)),IF(IF('Model inputs'!B282="",0,1)="",0,IF('Model inputs'!B282="",0,1)),IF(IF('Model inputs'!B283="",0,1)="",0,IF('Model inputs'!B283="",0,1)))=0,"",SUM('Model inputs'!B279,'Model inputs'!B280,'Model inputs'!B281,'Model inputs'!B282,'Model inputs'!B283)) -> 22500 | K82: =IF(SUM(IF(IF('Model inputs'!B284="",0,1)="",0,IF('Model inputs'!B284="",0,1)),IF(IF('Model inputs'!B285="",0,1)="",0,IF('Model inputs'!B285="",0,1)),IF(IF('Model inputs'!B286="",0,1)="",0,IF('Model inputs'!B286="",0,1)),IF(IF('Model inputs'!B287="",0,1)="",0,IF('Model inputs'!B287="",0,1)),IF(IF('Model inputs'!B288="",0,1)="",0,IF('Model inputs'!B288="",0,1)))=0,"",SUM('Model inputs'!B284,'Model inputs'!B285,'Model inputs'!B286,'Model inputs'!B287,'Model inputs'!B288)) -> 22500 | L82: =IF(SUM(IF(IF('Model inputs'!B289="",0,1)="",0,IF('Model inputs'!B289="",0,1)),IF(IF('Model inputs'!B290="",0,1)="",0,IF('Model inputs'!B290="",0,1)),IF(IF('Model inputs'!B291="",0,1)="",0,IF('Model inputs'!B291="",0,1)),IF(IF('Model inputs'!B292="",0,1)="",0,IF('Model inputs'!B292="",0,1)),IF(IF('Model inputs'!B293="",0,1)="",0,IF('Model inputs'!B293="",0,1)))=0,"",SUM('Model inputs'!B289,'Model inputs'!B290,'Model inputs'!B291,'Model inputs'!B292,'Model inputs'!B293)) -> 22500 | M82: =IF(SUM(IF(IF('Model inputs'!B294="",0,1)="",0,IF('Model inputs'!B294="",0,1)),IF(IF('Model inputs'!B295="",0,1)="",0,IF('Model inputs'!B295="",0,1)),IF(IF('Model inputs'!B296="",0,1)="",0,IF('Model inputs'!B296="",0,1)),IF(IF('Model inputs'!B297="",0,1)="",0,IF('Model inputs'!B297="",0,1)),IF(IF('Model inputs'!B298="",0,1)="",0,IF('Model inputs'!B298="",0,1)))=0,"",SUM('Model inputs'!B294,'Model inputs'!B295,'Model inputs'!B296,'Model inputs'!B297,'Model inputs'!B298)) -> 22500
A83: Plan Cash collections | B83: =IF(SUM(IF(IF('Model inputs'!B299="",0,1)="",0,IF('Model inputs'!B299="",0,1)),IF(IF('Model inputs'!B300="",0,1)="",0,IF('Model inputs'!B300="",0,1)),IF(IF('Model inputs'!B301="",0,1)="",0,IF('Model inputs'!B301="",0,1)),IF(IF('Model inputs'!B302="",0,1)="",0,IF('Model inputs'!B302="",0,1)),IF(IF('Model inputs'!B303="",0,1)="",0,IF('Model inputs'!B303="",0,1)))=0,"",SUM('Model inputs'!B299,'Model inputs'!B300,'Model inputs'!B301,'Model inputs'!B302,'Model inputs'!B303)) -> 22500 | C83: =IF(SUM(IF(IF('Model inputs'!B304="",0,1)="",0,IF('Model inputs'!B304="",0,1)),IF(IF('Model inputs'!B305="",0,1)="",0,IF('Model inputs'!B305="",0,1)),IF(IF('Model inputs'!B306="",0,1)="",0,IF('Model inputs'!B306="",0,1)),IF(IF('Model inputs'!B307="",0,1)="",0,IF('Model inputs'!B307="",0,1)),IF(IF('Model inputs'!B308="",0,1)="",0,IF('Model inputs'!B308="",0,1)))=0,"",SUM('Model inputs'!B304,'Model inputs'!B305,'Model inputs'!B306,'Model inputs'!B307,'Model inputs'!B308)) -> 22500 | D83: =IF(SUM(IF(IF('Model inputs'!B309="",0,1)="",0,IF('Model inputs'!B309="",0,1)),IF(IF('Model inputs'!B310="",0,1)="",0,IF('Model inputs'!B310="",0,1)),IF(IF('Model inputs'!B311="",0,1)="",0,IF('Model inputs'!B311="",0,1)),IF(IF('Model inputs'!B312="",0,1)="",0,IF('Model inputs'!B312="",0,1)),IF(IF('Model inputs'!B313="",0,1)="",0,IF('Model inputs'!B313="",0,1)))=0,"",SUM('Model inputs'!B309,'Model inputs'!B310,'Model inputs'!B311,'Model inputs'!B312,'Model inputs'!B313)) -> 22500 | E83: =IF(SUM(IF(IF('Model inputs'!B314="",0,1)="",0,IF('Model inputs'!B314="",0,1)),IF(IF('Model inputs'!B315="",0,1)="",0,IF('Model inputs'!B315="",0,1)),IF(IF('Model inputs'!B316="",0,1)="",0,IF('Model inputs'!B316="",0,1)),IF(IF('Model inputs'!B317="",0,1)="",0,IF('Model inputs'!B317="",0,1)),IF(IF('Model inputs'!B318="",0,1)="",0,IF('Model inputs'!B318="",0,1)))=0,"",SUM('Model inputs'!B314,'Model inputs'!B315,'Model inputs'!B316,'Model inputs'!B317,'Model inputs'!B318)) -> 22500 | F83: =IF(SUM(IF(IF('Model inputs'!B319="",0,1)="",0,IF('Model inputs'!B319="",0,1)),IF(IF('Model inputs'!B320="",0,1)="",0,IF('Model inputs'!B320="",0,1)),IF(IF('Model inputs'!B321="",0,1)="",0,IF('Model inputs'!B321="",0,1)),IF(IF('Model inputs'!B322="",0,1)="",0,IF('Model inputs'!B322="",0,1)),IF(IF('Model inputs'!B323="",0,1)="",0,IF('Model inputs'!B323="",0,1)))=0,"",SUM('Model inputs'!B319,'Model inputs'!B320,'Model inputs'!B321,'Model inputs'!B322,'Model inputs'!B323)) -> 22500 | G83: =IF(SUM(IF(IF('Model inputs'!B324="",0,1)="",0,IF('Model inputs'!B324="",0,1)),IF(IF('Model inputs'!B325="",0,1)="",0,IF('Model inputs'!B325="",0,1)),IF(IF('Model inputs'!B326="",0,1)="",0,IF('Model inputs'!B326="",0,1)),IF(IF('Model inputs'!B327="",0,1)="",0,IF('Model inputs'!B327="",0,1)),IF(IF('Model inputs'!B328="",0,1)="",0,IF('Model inputs'!B328="",0,1)))=0,"",SUM('Model inputs'!B324,'Model inputs'!B325,'Model inputs'!B326,'Model inputs'!B327,'Model inputs'!B328)) -> 22500 | H83: =IF(SUM(IF(IF('Model inputs'!B329="",0,1)="",0,IF('Model inputs'!B329="",0,1)),IF(IF('Model inputs'!B330="",0,1)="",0,IF('Model inputs'!B330="",0,1)),IF(IF('Model inputs'!B331="",0,1)="",0,IF('Model inputs'!B331="",0,1)),IF(IF('Model inputs'!B332="",0,1)="",0,IF('Model inputs'!B332="",0,1)),IF(IF('Model inputs'!B333="",0,1)="",0,IF('Model inputs'!B333="",0,1)))=0,"",SUM('Model inputs'!B329,'Model inputs'!B330,'Model inputs'!B331,'Model inputs'!B332,'Model inputs'!B333)) -> 22500 | I83: =IF(SUM(IF(IF('Model inputs'!B334="",0,1)="",0,IF('Model inputs'!B334="",0,1)),IF(IF('Model inputs'!B335="",0,1)="",0,IF('Model inputs'!B335="",0,1)),IF(IF('Model inputs'!B336="",0,1)="",0,IF('Model inputs'!B336="",0,1)),IF(IF('Model inputs'!B337="",0,1)="",0,IF('Model inputs'!B337="",0,1)),IF(IF('Model inputs'!B338="",0,1)="",0,IF('Model inputs'!B338="",0,1)))=0,"",SUM('Model inputs'!B334,'Model inputs'!B335,'Model inputs'!B336,'Model inputs'!B337,'Model inputs'!B338)) -> 22500 | J83: =IF(SUM(IF(IF('Model inputs'!B339="",0,1)="",0,IF('Model inputs'!B339="",0,1)),IF(IF('Model inputs'!B340="",0,1)="",0,IF('Model inputs'!B340="",0,1)),IF(IF('Model inputs'!B341="",0,1)="",0,IF('Model inputs'!B341="",0,1)),IF(IF('Model inputs'!B342="",0,1)="",0,IF('Model inputs'!B342="",0,1)),IF(IF('Model inputs'!B343="",0,1)="",0,IF('Model inputs'!B343="",0,1)))=0,"",SUM('Model inputs'!B339,'Model inputs'!B340,'Model inputs'!B341,'Model inputs'!B342,'Model inputs'!B343)) -> 22500 | K83: =IF(SUM(IF(IF('Model inputs'!B344="",0,1)="",0,IF('Model inputs'!B344="",0,1)),IF(IF('Model inputs'!B345="",0,1)="",0,IF('Model inputs'!B345="",0,1)),IF(IF('Model inputs'!B346="",0,1)="",0,IF('Model inputs'!B346="",0,1)),IF(IF('Model inputs'!B347="",0,1)="",0,IF('Model inputs'!B347="",0,1)),IF(IF('Model inputs'!B348="",0,1)="",0,IF('Model inputs'!B348="",0,1)))=0,"",SUM('Model inputs'!B344,'Model inputs'!B345,'Model inputs'!B346,'Model inputs'!B347,'Model inputs'!B348)) -> 22500 | L83: =IF(SUM(IF(IF('Model inputs'!B349="",0,1)="",0,IF('Model inputs'!B349="",0,1)),IF(IF('Model inputs'!B350="",0,1)="",0,IF('Model inputs'!B350="",0,1)),IF(IF('Model inputs'!B351="",0,1)="",0,IF('Model inputs'!B351="",0,1)),IF(IF('Model inputs'!B352="",0,1)="",0,IF('Model inputs'!B352="",0,1)),IF(IF('Model inputs'!B353="",0,1)="",0,IF('Model inputs'!B353="",0,1)))=0,"",SUM('Model inputs'!B349,'Model inputs'!B350,'Model inputs'!B351,'Model inputs'!B352,'Model inputs'!B353)) -> 22500 | M83: =IF(SUM(IF(IF('Model inputs'!B354="",0,1)="",0,IF('Model inputs'!B354="",0,1)),IF(IF('Model inputs'!B355="",0,1)="",0,IF('Model inputs'!B355="",0,1)),IF(IF('Model inputs'!B356="",0,1)="",0,IF('Model inputs'!B356="",0,1)),IF(IF('Model inputs'!B357="",0,1)="",0,IF('Model inputs'!B357="",0,1)),IF(IF('Model inputs'!B358="",0,1)="",0,IF('Model inputs'!B358="",0,1)))=0,"",SUM('Model inputs'!B354,'Model inputs'!B355,'Model inputs'!B356,'Model inputs'!B357,'Model inputs'!B358)) -> 22500
A84: Plan Delivery COGS | B84: =IF(SUM(IF(IF('Model inputs'!B359="",0,1)="",0,IF('Model inputs'!B359="",0,1)),IF(IF('Model inputs'!B360="",0,1)="",0,IF('Model inputs'!B360="",0,1)),IF(IF('Model inputs'!B361="",0,1)="",0,IF('Model inputs'!B361="",0,1)),IF(IF('Model inputs'!B362="",0,1)="",0,IF('Model inputs'!B362="",0,1)),IF(IF('Model inputs'!B363="",0,1)="",0,IF('Model inputs'!B363="",0,1)))=0,"",SUM('Model inputs'!B359,'Model inputs'!B360,'Model inputs'!B361,'Model inputs'!B362,'Model inputs'!B363)) -> 1419.75 | C84: =IF(SUM(IF(IF('Model inputs'!B364="",0,1)="",0,IF('Model inputs'!B364="",0,1)),IF(IF('Model inputs'!B365="",0,1)="",0,IF('Model inputs'!B365="",0,1)),IF(IF('Model inputs'!B366="",0,1)="",0,IF('Model inputs'!B366="",0,1)),IF(IF('Model inputs'!B367="",0,1)="",0,IF('Model inputs'!B367="",0,1)),IF(IF('Model inputs'!B368="",0,1)="",0,IF('Model inputs'!B368="",0,1)))=0,"",SUM('Model inputs'!B364,'Model inputs'!B365,'Model inputs'!B366,'Model inputs'!B367,'Model inputs'!B368)) -> 1419.75 | D84: =IF(SUM(IF(IF('Model inputs'!B369="",0,1)="",0,IF('Model inputs'!B369="",0,1)),IF(IF('Model inputs'!B370="",0,1)="",0,IF('Model inputs'!B370="",0,1)),IF(IF('Model inputs'!B371="",0,1)="",0,IF('Model inputs'!B371="",0,1)),IF(IF('Model inputs'!B372="",0,1)="",0,IF('Model inputs'!B372="",0,1)),IF(IF('Model inputs'!B373="",0,1)="",0,IF('Model inputs'!B373="",0,1)))=0,"",SUM('Model inputs'!B369,'Model inputs'!B370,'Model inputs'!B371,'Model inputs'!B372,'Model inputs'!B373)) -> 1419.75 | E84: =IF(SUM(IF(IF('Model inputs'!B374="",0,1)="",0,IF('Model inputs'!B374="",0,1)),IF(IF('Model inputs'!B375="",0,1)="",0,IF('Model inputs'!B375="",0,1)),IF(IF('Model inputs'!B376="",0,1)="",0,IF('Model inputs'!B376="",0,1)),IF(IF('Model inputs'!B377="",0,1)="",0,IF('Model inputs'!B377="",0,1)),IF(IF('Model inputs'!B378="",0,1)="",0,IF('Model inputs'!B378="",0,1)))=0,"",SUM('Model inputs'!B374,'Model inputs'!B375,'Model inputs'!B376,'Model inputs'!B377,'Model inputs'!B378)) -> 1419.75 | F84: =IF(SUM(IF(IF('Model inputs'!B379="",0,1)="",0,IF('Model inputs'!B379="",0,1)),IF(IF('Model inputs'!B380="",0,1)="",0,IF('Model inputs'!B380="",0,1)),IF(IF('Model inputs'!B381="",0,1)="",0,IF('Model inputs'!B381="",0,1)),IF(IF('Model inputs'!B382="",0,1)="",0,IF('Model inputs'!B382="",0,1)),IF(IF('Model inputs'!B383="",0,1)="",0,IF('Model inputs'!B383="",0,1)))=0,"",SUM('Model inputs'!B379,'Model inputs'!B380,'Model inputs'!B381,'Model inputs'!B382,'Model inputs'!B383)) -> 1419.75 | G84: =IF(SUM(IF(IF('Model inputs'!B384="",0,1)="",0,IF('Model inputs'!B384="",0,1)),IF(IF('Model inputs'!B385="",0,1)="",0,IF('Model inputs'!B385="",0,1)),IF(IF('Model inputs'!B386="",0,1)="",0,IF('Model inputs'!B386="",0,1)),IF(IF('Model inputs'!B387="",0,1)="",0,IF('Model inputs'!B387="",0,1)),IF(IF('Model inputs'!B388="",0,1)="",0,IF('Model inputs'!B388="",0,1)))=0,"",SUM('Model inputs'!B384,'Model inputs'!B385,'Model inputs'!B386,'Model inputs'!B387,'Model inputs'!B388)) -> 1419.75 | H84: =IF(SUM(IF(IF('Model inputs'!B389="",0,1)="",0,IF('Model inputs'!B389="",0,1)),IF(IF('Model inputs'!B390="",0,1)="",0,IF('Model inputs'!B390="",0,1)),IF(IF('Model inputs'!B391="",0,1)="",0,IF('Model inputs'!B391="",0,1)),IF(IF('Model inputs'!B392="",0,1)="",0,IF('Model inputs'!B392="",0,1)),IF(IF('Model inputs'!B393="",0,1)="",0,IF('Model inputs'!B393="",0,1)))=0,"",SUM('Model inputs'!B389,'Model inputs'!B390,'Model inputs'!B391,'Model inputs'!B392,'Model inputs'!B393)) -> 1419.75 | I84: =IF(SUM(IF(IF('Model inputs'!B394="",0,1)="",0,IF('Model inputs'!B394="",0,1)),IF(IF('Model inputs'!B395="",0,1)="",0,IF('Model inputs'!B395="",0,1)),IF(IF('Model inputs'!B396="",0,1)="",0,IF('Model inputs'!B396="",0,1)),IF(IF('Model inputs'!B397="",0,1)="",0,IF('Model inputs'!B397="",0,1)),IF(IF('Model inputs'!B398="",0,1)="",0,IF('Model inputs'!B398="",0,1)))=0,"",SUM('Model inputs'!B394,'Model inputs'!B395,'Model inputs'!B396,'Model inputs'!B397,'Model inputs'!B398)) -> 1419.75 | J84: =IF(SUM(IF(IF('Model inputs'!B399="",0,1)="",0,IF('Model inputs'!B399="",0,1)),IF(IF('Model inputs'!B400="",0,1)="",0,IF('Model inputs'!B400="",0,1)),IF(IF('Model inputs'!B401="",0,1)="",0,IF('Model inputs'!B401="",0,1)),IF(IF('Model inputs'!B402="",0,1)="",0,IF('Model inputs'!B402="",0,1)),IF(IF('Model inputs'!B403="",0,1)="",0,IF('Model inputs'!B403="",0,1)))=0,"",SUM('Model inputs'!B399,'Model inputs'!B400,'Model inputs'!B401,'Model inputs'!B402,'Model inputs'!B403)) -> 1419.75 | K84: =IF(SUM(IF(IF('Model inputs'!B404="",0,1)="",0,IF('Model inputs'!B404="",0,1)),IF(IF('Model inputs'!B405="",0,1)="",0,IF('Model inputs'!B405="",0,1)),IF(IF('Model inputs'!B406="",0,1)="",0,IF('Model inputs'!B406="",0,1)),IF(IF('Model inputs'!B407="",0,1)="",0,IF('Model inputs'!B407="",0,1)),IF(IF('Model inputs'!B408="",0,1)="",0,IF('Model inputs'!B408="",0,1)))=0,"",SUM('Model inputs'!B404,'Model inputs'!B405,'Model inputs'!B406,'Model inputs'!B407,'Model inputs'!B408)) -> 1419.75 | L84: =IF(SUM(IF(IF('Model inputs'!B409="",0,1)="",0,IF('Model inputs'!B409="",0,1)),IF(IF('Model inputs'!B410="",0,1)="",0,IF('Model inputs'!B410="",0,1)),IF(IF('Model inputs'!B411="",0,1)="",0,IF('Model inputs'!B411="",0,1)),IF(IF('Model inputs'!B412="",0,1)="",0,IF('Model inputs'!B412="",0,1)),IF(IF('Model inputs'!B413="",0,1)="",0,IF('Model inputs'!B413="",0,1)))=0,"",SUM('Model inputs'!B409,'Model inputs'!B410,'Model inputs'!B411,'Model inputs'!B412,'Model inputs'!B413)) -> 1419.75 | M84: =IF(SUM(IF(IF('Model inputs'!B414="",0,1)="",0,IF('Model inputs'!B414="",0,1)),IF(IF('Model inputs'!B415="",0,1)="",0,IF('Model inputs'!B415="",0,1)),IF(IF('Model inputs'!B416="",0,1)="",0,IF('Model inputs'!B416="",0,1)),IF(IF('Model inputs'!B417="",0,1)="",0,IF('Model inputs'!B417="",0,1)),IF(IF('Model inputs'!B418="",0,1)="",0,IF('Model inputs'!B418="",0,1)))=0,"",SUM('Model inputs'!B414,'Model inputs'!B415,'Model inputs'!B416,'Model inputs'!B417,'Model inputs'!B418)) -> 1419.75
A85: Plan Gross profit | B85: =IF(SUM(IF(IF('Model inputs'!B419="",0,1)="",0,IF('Model inputs'!B419="",0,1)),IF(IF('Model inputs'!B420="",0,1)="",0,IF('Model inputs'!B420="",0,1)),IF(IF('Model inputs'!B421="",0,1)="",0,IF('Model inputs'!B421="",0,1)),IF(IF('Model inputs'!B422="",0,1)="",0,IF('Model inputs'!B422="",0,1)),IF(IF('Model inputs'!B423="",0,1)="",0,IF('Model inputs'!B423="",0,1)))=0,"",SUM('Model inputs'!B419,'Model inputs'!B420,'Model inputs'!B421,'Model inputs'!B422,'Model inputs'!B423)) -> 21080.25 | C85: =IF(SUM(IF(IF('Model inputs'!B424="",0,1)="",0,IF('Model inputs'!B424="",0,1)),IF(IF('Model inputs'!B425="",0,1)="",0,IF('Model inputs'!B425="",0,1)),IF(IF('Model inputs'!B426="",0,1)="",0,IF('Model inputs'!B426="",0,1)),IF(IF('Model inputs'!B427="",0,1)="",0,IF('Model inputs'!B427="",0,1)),IF(IF('Model inputs'!B428="",0,1)="",0,IF('Model inputs'!B428="",0,1)))=0,"",SUM('Model inputs'!B424,'Model inputs'!B425,'Model inputs'!B426,'Model inputs'!B427,'Model inputs'!B428)) -> 21080.25 | D85: =IF(SUM(IF(IF('Model inputs'!B429="",0,1)="",0,IF('Model inputs'!B429="",0,1)),IF(IF('Model inputs'!B430="",0,1)="",0,IF('Model inputs'!B430="",0,1)),IF(IF('Model inputs'!B431="",0,1)="",0,IF('Model inputs'!B431="",0,1)),IF(IF('Model inputs'!B432="",0,1)="",0,IF('Model inputs'!B432="",0,1)),IF(IF('Model inputs'!B433="",0,1)="",0,IF('Model inputs'!B433="",0,1)))=0,"",SUM('Model inputs'!B429,'Model inputs'!B430,'Model inputs'!B431,'Model inputs'!B432,'Model inputs'!B433)) -> 21080.25 | E85: =IF(SUM(IF(IF('Model inputs'!B434="",0,1)="",0,IF('Model inputs'!B434="",0,1)),IF(IF('Model inputs'!B435="",0,1)="",0,IF('Model inputs'!B435="",0,1)),IF(IF('Model inputs'!B436="",0,1)="",0,IF('Model inputs'!B436="",0,1)),IF(IF('Model inputs'!B437="",0,1)="",0,IF('Model inputs'!B437="",0,1)),IF(IF('Model inputs'!B438="",0,1)="",0,IF('Model inputs'!B438="",0,1)))=0,"",SUM('Model inputs'!B434,'Model inputs'!B435,'Model inputs'!B436,'Model inputs'!B437,'Model inputs'!B438)) -> 21080.25 | F85: =IF(SUM(IF(IF('Model inputs'!B439="",0,1)="",0,IF('Model inputs'!B439="",0,1)),IF(IF('Model inputs'!B440="",0,1)="",0,IF('Model inputs'!B440="",0,1)),IF(IF('Model inputs'!B441="",0,1)="",0,IF('Model inputs'!B441="",0,1)),IF(IF('Model inputs'!B442="",0,1)="",0,IF('Model inputs'!B442="",0,1)),IF(IF('Model inputs'!B443="",0,1)="",0,IF('Model inputs'!B443="",0,1)))=0,"",SUM('Model inputs'!B439,'Model inputs'!B440,'Model inputs'!B441,'Model inputs'!B442,'Model inputs'!B443)) -> 21080.25 | G85: =IF(SUM(IF(IF('Model inputs'!B444="",0,1)="",0,IF('Model inputs'!B444="",0,1)),IF(IF('Model inputs'!B445="",0,1)="",0,IF('Model inputs'!B445="",0,1)),IF(IF('Model inputs'!B446="",0,1)="",0,IF('Model inputs'!B446="",0,1)),IF(IF('Model inputs'!B447="",0,1)="",0,IF('Model inputs'!B447="",0,1)),IF(IF('Model inputs'!B448="",0,1)="",0,IF('Model inputs'!B448="",0,1)))=0,"",SUM('Model inputs'!B444,'Model inputs'!B445,'Model inputs'!B446,'Model inputs'!B447,'Model inputs'!B448)) -> 21080.25 | H85: =IF(SUM(IF(IF('Model inputs'!B449="",0,1)="",0,IF('Model inputs'!B449="",0,1)),IF(IF('Model inputs'!B450="",0,1)="",0,IF('Model inputs'!B450="",0,1)),IF(IF('Model inputs'!B451="",0,1)="",0,IF('Model inputs'!B451="",0,1)),IF(IF('Model inputs'!B452="",0,1)="",0,IF('Model inputs'!B452="",0,1)),IF(IF('Model inputs'!B453="",0,1)="",0,IF('Model inputs'!B453="",0,1)))=0,"",SUM('Model inputs'!B449,'Model inputs'!B450,'Model inputs'!B451,'Model inputs'!B452,'Model inputs'!B453)) -> 21080.25 | I85: =IF(SUM(IF(IF('Model inputs'!B454="",0,1)="",0,IF('Model inputs'!B454="",0,1)),IF(IF('Model inputs'!B455="",0,1)="",0,IF('Model inputs'!B455="",0,1)),IF(IF('Model inputs'!B456="",0,1)="",0,IF('Model inputs'!B456="",0,1)),IF(IF('Model inputs'!B457="",0,1)="",0,IF('Model inputs'!B457="",0,1)),IF(IF('Model inputs'!B458="",0,1)="",0,IF('Model inputs'!B458="",0,1)))=0,"",SUM('Model inputs'!B454,'Model inputs'!B455,'Model inputs'!B456,'Model inputs'!B457,'Model inputs'!B458)) -> 21080.25 | J85: =IF(SUM(IF(IF('Model inputs'!B459="",0,1)="",0,IF('Model inputs'!B459="",0,1)),IF(IF('Model inputs'!B460="",0,1)="",0,IF('Model inputs'!B460="",0,1)),IF(IF('Model inputs'!B461="",0,1)="",0,IF('Model inputs'!B461="",0,1)),IF(IF('Model inputs'!B462="",0,1)="",0,IF('Model inputs'!B462="",0,1)),IF(IF('Model inputs'!B463="",0,1)="",0,IF('Model inputs'!B463="",0,1)))=0,"",SUM('Model inputs'!B459,'Model inputs'!B460,'Model inputs'!B461,'Model inputs'!B462,'Model inputs'!B463)) -> 21080.25 | K85: =IF(SUM(IF(IF('Model inputs'!B464="",0,1)="",0,IF('Model inputs'!B464="",0,1)),IF(IF('Model inputs'!B465="",0,1)="",0,IF('Model inputs'!B465="",0,1)),IF(IF('Model inputs'!B466="",0,1)="",0,IF('Model inputs'!B466="",0,1)),IF(IF('Model inputs'!B467="",0,1)="",0,IF('Model inputs'!B467="",0,1)),IF(IF('Model inputs'!B468="",0,1)="",0,IF('Model inputs'!B468="",0,1)))=0,"",SUM('Model inputs'!B464,'Model inputs'!B465,'Model inputs'!B466,'Model inputs'!B467,'Model inputs'!B468)) -> 21080.25 | L85: =IF(SUM(IF(IF('Model inputs'!B469="",0,1)="",0,IF('Model inputs'!B469="",0,1)),IF(IF('Model inputs'!B470="",0,1)="",0,IF('Model inputs'!B470="",0,1)),IF(IF('Model inputs'!B471="",0,1)="",0,IF('Model inputs'!B471="",0,1)),IF(IF('Model inputs'!B472="",0,1)="",0,IF('Model inputs'!B472="",0,1)),IF(IF('Model inputs'!B473="",0,1)="",0,IF('Model inputs'!B473="",0,1)))=0,"",SUM('Model inputs'!B469,'Model inputs'!B470,'Model inputs'!B471,'Model inputs'!B472,'Model inputs'!B473)) -> 21080.25 | M85: =IF(SUM(IF(IF('Model inputs'!B474="",0,1)="",0,IF('Model inputs'!B474="",0,1)),IF(IF('Model inputs'!B475="",0,1)="",0,IF('Model inputs'!B475="",0,1)),IF(IF('Model inputs'!B476="",0,1)="",0,IF('Model inputs'!B476="",0,1)),IF(IF('Model inputs'!B477="",0,1)="",0,IF('Model inputs'!B477="",0,1)),IF(IF('Model inputs'!B478="",0,1)="",0,IF('Model inputs'!B478="",0,1)))=0,"",SUM('Model inputs'!B474,'Model inputs'!B475,'Model inputs'!B476,'Model inputs'!B477,'Model inputs'!B478)) -> 21080.25
A86: Plan Payment fees | B86: =IF(SUM(IF(IF('Model inputs'!B479="",0,1)="",0,IF('Model inputs'!B479="",0,1)),IF(IF('Model inputs'!B480="",0,1)="",0,IF('Model inputs'!B480="",0,1)),IF(IF('Model inputs'!B481="",0,1)="",0,IF('Model inputs'!B481="",0,1)),IF(IF('Model inputs'!B482="",0,1)="",0,IF('Model inputs'!B482="",0,1)),IF(IF('Model inputs'!B483="",0,1)="",0,IF('Model inputs'!B483="",0,1)))=0,"",SUM('Model inputs'!B479,'Model inputs'!B480,'Model inputs'!B481,'Model inputs'!B482,'Model inputs'!B483)) -> 675 | C86: =IF(SUM(IF(IF('Model inputs'!B484="",0,1)="",0,IF('Model inputs'!B484="",0,1)),IF(IF('Model inputs'!B485="",0,1)="",0,IF('Model inputs'!B485="",0,1)),IF(IF('Model inputs'!B486="",0,1)="",0,IF('Model inputs'!B486="",0,1)),IF(IF('Model inputs'!B487="",0,1)="",0,IF('Model inputs'!B487="",0,1)),IF(IF('Model inputs'!B488="",0,1)="",0,IF('Model inputs'!B488="",0,1)))=0,"",SUM('Model inputs'!B484,'Model inputs'!B485,'Model inputs'!B486,'Model inputs'!B487,'Model inputs'!B488)) -> 675 | D86: =IF(SUM(IF(IF('Model inputs'!B489="",0,1)="",0,IF('Model inputs'!B489="",0,1)),IF(IF('Model inputs'!B490="",0,1)="",0,IF('Model inputs'!B490="",0,1)),IF(IF('Model inputs'!B491="",0,1)="",0,IF('Model inputs'!B491="",0,1)),IF(IF('Model inputs'!B492="",0,1)="",0,IF('Model inputs'!B492="",0,1)),IF(IF('Model inputs'!B493="",0,1)="",0,IF('Model inputs'!B493="",0,1)))=0,"",SUM('Model inputs'!B489,'Model inputs'!B490,'Model inputs'!B491,'Model inputs'!B492,'Model inputs'!B493)) -> 675 | E86: =IF(SUM(IF(IF('Model inputs'!B494="",0,1)="",0,IF('Model inputs'!B494="",0,1)),IF(IF('Model inputs'!B495="",0,1)="",0,IF('Model inputs'!B495="",0,1)),IF(IF('Model inputs'!B496="",0,1)="",0,IF('Model inputs'!B496="",0,1)),IF(IF('Model inputs'!B497="",0,1)="",0,IF('Model inputs'!B497="",0,1)),IF(IF('Model inputs'!B498="",0,1)="",0,IF('Model inputs'!B498="",0,1)))=0,"",SUM('Model inputs'!B494,'Model inputs'!B495,'Model inputs'!B496,'Model inputs'!B497,'Model inputs'!B498)) -> 675 | F86: =IF(SUM(IF(IF('Model inputs'!B499="",0,1)="",0,IF('Model inputs'!B499="",0,1)),IF(IF('Model inputs'!B500="",0,1)="",0,IF('Model inputs'!B500="",0,1)),IF(IF('Model inputs'!B501="",0,1)="",0,IF('Model inputs'!B501="",0,1)),IF(IF('Model inputs'!B502="",0,1)="",0,IF('Model inputs'!B502="",0,1)),IF(IF('Model inputs'!B503="",0,1)="",0,IF('Model inputs'!B503="",0,1)))=0,"",SUM('Model inputs'!B499,'Model inputs'!B500,'Model inputs'!B501,'Model inputs'!B502,'Model inputs'!B503)) -> 675 | G86: =IF(SUM(IF(IF('Model inputs'!B504="",0,1)="",0,IF('Model inputs'!B504="",0,1)),IF(IF('Model inputs'!B505="",0,1)="",0,IF('Model inputs'!B505="",0,1)),IF(IF('Model inputs'!B506="",0,1)="",0,IF('Model inputs'!B506="",0,1)),IF(IF('Model inputs'!B507="",0,1)="",0,IF('Model inputs'!B507="",0,1)),IF(IF('Model inputs'!B508="",0,1)="",0,IF('Model inputs'!B508="",0,1)))=0,"",SUM('Model inputs'!B504,'Model inputs'!B505,'Model inputs'!B506,'Model inputs'!B507,'Model inputs'!B508)) -> 675 | H86: =IF(SUM(IF(IF('Model inputs'!B509="",0,1)="",0,IF('Model inputs'!B509="",0,1)),IF(IF('Model inputs'!B510="",0,1)="",0,IF('Model inputs'!B510="",0,1)),IF(IF('Model inputs'!B511="",0,1)="",0,IF('Model inputs'!B511="",0,1)),IF(IF('Model inputs'!B512="",0,1)="",0,IF('Model inputs'!B512="",0,1)),IF(IF('Model inputs'!B513="",0,1)="",0,IF('Model inputs'!B513="",0,1)))=0,"",SUM('Model inputs'!B509,'Model inputs'!B510,'Model inputs'!B511,'Model inputs'!B512,'Model inputs'!B513)) -> 675 | I86: =IF(SUM(IF(IF('Model inputs'!B514="",0,1)="",0,IF('Model inputs'!B514="",0,1)),IF(IF('Model inputs'!B515="",0,1)="",0,IF('Model inputs'!B515="",0,1)),IF(IF('Model inputs'!B516="",0,1)="",0,IF('Model inputs'!B516="",0,1)),IF(IF('Model inputs'!B517="",0,1)="",0,IF('Model inputs'!B517="",0,1)),IF(IF('Model inputs'!B518="",0,1)="",0,IF('Model inputs'!B518="",0,1)))=0,"",SUM('Model inputs'!B514,'Model inputs'!B515,'Model inputs'!B516,'Model inputs'!B517,'Model inputs'!B518)) -> 675 | J86: =IF(SUM(IF(IF('Model inputs'!B519="",0,1)="",0,IF('Model inputs'!B519="",0,1)),IF(IF('Model inputs'!B520="",0,1)="",0,IF('Model inputs'!B520="",0,1)),IF(IF('Model inputs'!B521="",0,1)="",0,IF('Model inputs'!B521="",0,1)),IF(IF('Model inputs'!B522="",0,1)="",0,IF('Model inputs'!B522="",0,1)),IF(IF('Model inputs'!B523="",0,1)="",0,IF('Model inputs'!B523="",0,1)))=0,"",SUM('Model inputs'!B519,'Model inputs'!B520,'Model inputs'!B521,'Model inputs'!B522,'Model inputs'!B523)) -> 675 | K86: =IF(SUM(IF(IF('Model inputs'!B524="",0,1)="",0,IF('Model inputs'!B524="",0,1)),IF(IF('Model inputs'!B525="",0,1)="",0,IF('Model inputs'!B525="",0,1)),IF(IF('Model inputs'!B526="",0,1)="",0,IF('Model inputs'!B526="",0,1)),IF(IF('Model inputs'!B527="",0,1)="",0,IF('Model inputs'!B527="",0,1)),IF(IF('Model inputs'!B528="",0,1)="",0,IF('Model inputs'!B528="",0,1)))=0,"",SUM('Model inputs'!B524,'Model inputs'!B525,'Model inputs'!B526,'Model inputs'!B527,'Model inputs'!B528)) -> 675 | L86: =IF(SUM(IF(IF('Model inputs'!B529="",0,1)="",0,IF('Model inputs'!B529="",0,1)),IF(IF('Model inputs'!B530="",0,1)="",0,IF('Model inputs'!B530="",0,1)),IF(IF('Model inputs'!B531="",0,1)="",0,IF('Model inputs'!B531="",0,1)),IF(IF('Model inputs'!B532="",0,1)="",0,IF('Model inputs'!B532="",0,1)),IF(IF('Model inputs'!B533="",0,1)="",0,IF('Model inputs'!B533="",0,1)))=0,"",SUM('Model inputs'!B529,'Model inputs'!B530,'Model inputs'!B531,'Model inputs'!B532,'Model inputs'!B533)) -> 675 | M86: =IF(SUM(IF(IF('Model inputs'!B534="",0,1)="",0,IF('Model inputs'!B534="",0,1)),IF(IF('Model inputs'!B535="",0,1)="",0,IF('Model inputs'!B535="",0,1)),IF(IF('Model inputs'!B536="",0,1)="",0,IF('Model inputs'!B536="",0,1)),IF(IF('Model inputs'!B537="",0,1)="",0,IF('Model inputs'!B537="",0,1)),IF(IF('Model inputs'!B538="",0,1)="",0,IF('Model inputs'!B538="",0,1)))=0,"",SUM('Model inputs'!B534,'Model inputs'!B535,'Model inputs'!B536,'Model inputs'!B537,'Model inputs'!B538)) -> 675
A87: Plan Account support cost | B87: =IF(SUM(IF(IF('Model inputs'!B539="",0,1)="",0,IF('Model inputs'!B539="",0,1)),IF(IF('Model inputs'!B540="",0,1)="",0,IF('Model inputs'!B540="",0,1)),IF(IF('Model inputs'!B541="",0,1)="",0,IF('Model inputs'!B541="",0,1)),IF(IF('Model inputs'!B542="",0,1)="",0,IF('Model inputs'!B542="",0,1)),IF(IF('Model inputs'!B543="",0,1)="",0,IF('Model inputs'!B543="",0,1)))=0,"",SUM('Model inputs'!B539,'Model inputs'!B540,'Model inputs'!B541,'Model inputs'!B542,'Model inputs'!B543)) -> 150 | C87: =IF(SUM(IF(IF('Model inputs'!B544="",0,1)="",0,IF('Model inputs'!B544="",0,1)),IF(IF('Model inputs'!B545="",0,1)="",0,IF('Model inputs'!B545="",0,1)),IF(IF('Model inputs'!B546="",0,1)="",0,IF('Model inputs'!B546="",0,1)),IF(IF('Model inputs'!B547="",0,1)="",0,IF('Model inputs'!B547="",0,1)),IF(IF('Model inputs'!B548="",0,1)="",0,IF('Model inputs'!B548="",0,1)))=0,"",SUM('Model inputs'!B544,'Model inputs'!B545,'Model inputs'!B546,'Model inputs'!B547,'Model inputs'!B548)) -> 150 | D87: =IF(SUM(IF(IF('Model inputs'!B549="",0,1)="",0,IF('Model inputs'!B549="",0,1)),IF(IF('Model inputs'!B550="",0,1)="",0,IF('Model inputs'!B550="",0,1)),IF(IF('Model inputs'!B551="",0,1)="",0,IF('Model inputs'!B551="",0,1)),IF(IF('Model inputs'!B552="",0,1)="",0,IF('Model inputs'!B552="",0,1)),IF(IF('Model inputs'!B553="",0,1)="",0,IF('Model inputs'!B553="",0,1)))=0,"",SUM('Model inputs'!B549,'Model inputs'!B550,'Model inputs'!B551,'Model inputs'!B552,'Model inputs'!B553)) -> 150 | E87: =IF(SUM(IF(IF('Model inputs'!B554="",0,1)="",0,IF('Model inputs'!B554="",0,1)),IF(IF('Model inputs'!B555="",0,1)="",0,IF('Model inputs'!B555="",0,1)),IF(IF('Model inputs'!B556="",0,1)="",0,IF('Model inputs'!B556="",0,1)),IF(IF('Model inputs'!B557="",0,1)="",0,IF('Model inputs'!B557="",0,1)),IF(IF('Model inputs'!B558="",0,1)="",0,IF('Model inputs'!B558="",0,1)))=0,"",SUM('Model inputs'!B554,'Model inputs'!B555,'Model inputs'!B556,'Model inputs'!B557,'Model inputs'!B558)) -> 150 | F87: =IF(SUM(IF(IF('Model inputs'!B559="",0,1)="",0,IF('Model inputs'!B559="",0,1)),IF(IF('Model inputs'!B560="",0,1)="",0,IF('Model inputs'!B560="",0,1)),IF(IF('Model inputs'!B561="",0,1)="",0,IF('Model inputs'!B561="",0,1)),IF(IF('Model inputs'!B562="",0,1)="",0,IF('Model inputs'!B562="",0,1)),IF(IF('Model inputs'!B563="",0,1)="",0,IF('Model inputs'!B563="",0,1)))=0,"",SUM('Model inputs'!B559,'Model inputs'!B560,'Model inputs'!B561,'Model inputs'!B562,'Model inputs'!B563)) -> 150 | G87: =IF(SUM(IF(IF('Model inputs'!B564="",0,1)="",0,IF('Model inputs'!B564="",0,1)),IF(IF('Model inputs'!B565="",0,1)="",0,IF('Model inputs'!B565="",0,1)),IF(IF('Model inputs'!B566="",0,1)="",0,IF('Model inputs'!B566="",0,1)),IF(IF('Model inputs'!B567="",0,1)="",0,IF('Model inputs'!B567="",0,1)),IF(IF('Model inputs'!B568="",0,1)="",0,IF('Model inputs'!B568="",0,1)))=0,"",SUM('Model inputs'!B564,'Model inputs'!B565,'Model inputs'!B566,'Model inputs'!B567,'Model inputs'!B568)) -> 150 | H87: =IF(SUM(IF(IF('Model inputs'!B569="",0,1)="",0,IF('Model inputs'!B569="",0,1)),IF(IF('Model inputs'!B570="",0,1)="",0,IF('Model inputs'!B570="",0,1)),IF(IF('Model inputs'!B571="",0,1)="",0,IF('Model inputs'!B571="",0,1)),IF(IF('Model inputs'!B572="",0,1)="",0,IF('Model inputs'!B572="",0,1)),IF(IF('Model inputs'!B573="",0,1)="",0,IF('Model inputs'!B573="",0,1)))=0,"",SUM('Model inputs'!B569,'Model inputs'!B570,'Model inputs'!B571,'Model inputs'!B572,'Model inputs'!B573)) -> 150 | I87: =IF(SUM(IF(IF('Model inputs'!B574="",0,1)="",0,IF('Model inputs'!B574="",0,1)),IF(IF('Model inputs'!B575="",0,1)="",0,IF('Model inputs'!B575="",0,1)),IF(IF('Model inputs'!B576="",0,1)="",0,IF('Model inputs'!B576="",0,1)),IF(IF('Model inputs'!B577="",0,1)="",0,IF('Model inputs'!B577="",0,1)),IF(IF('Model inputs'!B578="",0,1)="",0,IF('Model inputs'!B578="",0,1)))=0,"",SUM('Model inputs'!B574,'Model inputs'!B575,'Model inputs'!B576,'Model inputs'!B577,'Model inputs'!B578)) -> 150 | J87: =IF(SUM(IF(IF('Model inputs'!B579="",0,1)="",0,IF('Model inputs'!B579="",0,1)),IF(IF('Model inputs'!B580="",0,1)="",0,IF('Model inputs'!B580="",0,1)),IF(IF('Model inputs'!B581="",0,1)="",0,IF('Model inputs'!B581="",0,1)),IF(IF('Model inputs'!B582="",0,1)="",0,IF('Model inputs'!B582="",0,1)),IF(IF('Model inputs'!B583="",0,1)="",0,IF('Model inputs'!B583="",0,1)))=0,"",SUM('Model inputs'!B579,'Model inputs'!B580,'Model inputs'!B581,'Model inputs'!B582,'Model inputs'!B583)) -> 150 | K87: =IF(SUM(IF(IF('Model inputs'!B584="",0,1)="",0,IF('Model inputs'!B584="",0,1)),IF(IF('Model inputs'!B585="",0,1)="",0,IF('Model inputs'!B585="",0,1)),IF(IF('Model inputs'!B586="",0,1)="",0,IF('Model inputs'!B586="",0,1)),IF(IF('Model inputs'!B587="",0,1)="",0,IF('Model inputs'!B587="",0,1)),IF(IF('Model inputs'!B588="",0,1)="",0,IF('Model inputs'!B588="",0,1)))=0,"",SUM('Model inputs'!B584,'Model inputs'!B585,'Model inputs'!B586,'Model inputs'!B587,'Model inputs'!B588)) -> 150 | L87: =IF(SUM(IF(IF('Model inputs'!B589="",0,1)="",0,IF('Model inputs'!B589="",0,1)),IF(IF('Model inputs'!B590="",0,1)="",0,IF('Model inputs'!B590="",0,1)),IF(IF('Model inputs'!B591="",0,1)="",0,IF('Model inputs'!B591="",0,1)),IF(IF('Model inputs'!B592="",0,1)="",0,IF('Model inputs'!B592="",0,1)),IF(IF('Model inputs'!B593="",0,1)="",0,IF('Model inputs'!B593="",0,1)))=0,"",SUM('Model inputs'!B589,'Model inputs'!B590,'Model inputs'!B591,'Model inputs'!B592,'Model inputs'!B593)) -> 150 | M87: =IF(SUM(IF(IF('Model inputs'!B594="",0,1)="",0,IF('Model inputs'!B594="",0,1)),IF(IF('Model inputs'!B595="",0,1)="",0,IF('Model inputs'!B595="",0,1)),IF(IF('Model inputs'!B596="",0,1)="",0,IF('Model inputs'!B596="",0,1)),IF(IF('Model inputs'!B597="",0,1)="",0,IF('Model inputs'!B597="",0,1)),IF(IF('Model inputs'!B598="",0,1)="",0,IF('Model inputs'!B598="",0,1)))=0,"",SUM('Model inputs'!B594,'Model inputs'!B595,'Model inputs'!B596,'Model inputs'!B597,'Model inputs'!B598)) -> 150
A88: Plan Contribution profit | B88: =IF(SUM(IF(IF('Model inputs'!B599="",0,1)="",0,IF('Model inputs'!B599="",0,1)),IF(IF('Model inputs'!B600="",0,1)="",0,IF('Model inputs'!B600="",0,1)),IF(IF('Model inputs'!B601="",0,1)="",0,IF('Model inputs'!B601="",0,1)),IF(IF('Model inputs'!B602="",0,1)="",0,IF('Model inputs'!B602="",0,1)),IF(IF('Model inputs'!B603="",0,1)="",0,IF('Model inputs'!B603="",0,1)))=0,"",SUM('Model inputs'!B599,'Model inputs'!B600,'Model inputs'!B601,'Model inputs'!B602,'Model inputs'!B603)) -> 20255.25 | C88: =IF(SUM(IF(IF('Model inputs'!B604="",0,1)="",0,IF('Model inputs'!B604="",0,1)),IF(IF('Model inputs'!B605="",0,1)="",0,IF('Model inputs'!B605="",0,1)),IF(IF('Model inputs'!B606="",0,1)="",0,IF('Model inputs'!B606="",0,1)),IF(IF('Model inputs'!B607="",0,1)="",0,IF('Model inputs'!B607="",0,1)),IF(IF('Model inputs'!B608="",0,1)="",0,IF('Model inputs'!B608="",0,1)))=0,"",SUM('Model inputs'!B604,'Model inputs'!B605,'Model inputs'!B606,'Model inputs'!B607,'Model inputs'!B608)) -> 20255.25 | D88: =IF(SUM(IF(IF('Model inputs'!B609="",0,1)="",0,IF('Model inputs'!B609="",0,1)),IF(IF('Model inputs'!B610="",0,1)="",0,IF('Model inputs'!B610="",0,1)),IF(IF('Model inputs'!B611="",0,1)="",0,IF('Model inputs'!B611="",0,1)),IF(IF('Model inputs'!B612="",0,1)="",0,IF('Model inputs'!B612="",0,1)),IF(IF('Model inputs'!B613="",0,1)="",0,IF('Model inputs'!B613="",0,1)))=0,"",SUM('Model inputs'!B609,'Model inputs'!B610,'Model inputs'!B611,'Model inputs'!B612,'Model inputs'!B613)) -> 20255.25 | E88: =IF(SUM(IF(IF('Model inputs'!B614="",0,1)="",0,IF('Model inputs'!B614="",0,1)),IF(IF('Model inputs'!B615="",0,1)="",0,IF('Model inputs'!B615="",0,1)),IF(IF('Model inputs'!B616="",0,1)="",0,IF('Model inputs'!B616="",0,1)),IF(IF('Model inputs'!B617="",0,1)="",0,IF('Model inputs'!B617="",0,1)),IF(IF('Model inputs'!B618="",0,1)="",0,IF('Model inputs'!B618="",0,1)))=0,"",SUM('Model inputs'!B614,'Model inputs'!B615,'Model inputs'!B616,'Model inputs'!B617,'Model inputs'!B618)) -> 20255.25 | F88: =IF(SUM(IF(IF('Model inputs'!B619="",0,1)="",0,IF('Model inputs'!B619="",0,1)),IF(IF('Model inputs'!B620="",0,1)="",0,IF('Model inputs'!B620="",0,1)),IF(IF('Model inputs'!B621="",0,1)="",0,IF('Model inputs'!B621="",0,1)),IF(IF('Model inputs'!B622="",0,1)="",0,IF('Model inputs'!B622="",0,1)),IF(IF('Model inputs'!B623="",0,1)="",0,IF('Model inputs'!B623="",0,1)))=0,"",SUM('Model inputs'!B619,'Model inputs'!B620,'Model inputs'!B621,'Model inputs'!B622,'Model inputs'!B623)) -> 20255.25 | G88: =IF(SUM(IF(IF('Model inputs'!B624="",0,1)="",0,IF('Model inputs'!B624="",0,1)),IF(IF('Model inputs'!B625="",0,1)="",0,IF('Model inputs'!B625="",0,1)),IF(IF('Model inputs'!B626="",0,1)="",0,IF('Model inputs'!B626="",0,1)),IF(IF('Model inputs'!B627="",0,1)="",0,IF('Model inputs'!B627="",0,1)),IF(IF('Model inputs'!B628="",0,1)="",0,IF('Model inputs'!B628="",0,1)))=0,"",SUM('Model inputs'!B624,'Model inputs'!B625,'Model inputs'!B626,'Model inputs'!B627,'Model inputs'!B628)) -> 20255.25 | H88: =IF(SUM(IF(IF('Model inputs'!B629="",0,1)="",0,IF('Model inputs'!B629="",0,1)),IF(IF('Model inputs'!B630="",0,1)="",0,IF('Model inputs'!B630="",0,1)),IF(IF('Model inputs'!B631="",0,1)="",0,IF('Model inputs'!B631="",0,1)),IF(IF('Model inputs'!B632="",0,1)="",0,IF('Model inputs'!B632="",0,1)),IF(IF('Model inputs'!B633="",0,1)="",0,IF('Model inputs'!B633="",0,1)))=0,"",SUM('Model inputs'!B629,'Model inputs'!B630,'Model inputs'!B631,'Model inputs'!B632,'Model inputs'!B633)) -> 20255.25 | I88: =IF(SUM(IF(IF('Model inputs'!B634="",0,1)="",0,IF('Model inputs'!B634="",0,1)),IF(IF('Model inputs'!B635="",0,1)="",0,IF('Model inputs'!B635="",0,1)),IF(IF('Model inputs'!B636="",0,1)="",0,IF('Model inputs'!B636="",0,1)),IF(IF('Model inputs'!B637="",0,1)="",0,IF('Model inputs'!B637="",0,1)),IF(IF('Model inputs'!B638="",0,1)="",0,IF('Model inputs'!B638="",0,1)))=0,"",SUM('Model inputs'!B634,'Model inputs'!B635,'Model inputs'!B636,'Model inputs'!B637,'Model inputs'!B638)) -> 20255.25 | J88: =IF(SUM(IF(IF('Model inputs'!B639="",0,1)="",0,IF('Model inputs'!B639="",0,1)),IF(IF('Model inputs'!B640="",0,1)="",0,IF('Model inputs'!B640="",0,1)),IF(IF('Model inputs'!B641="",0,1)="",0,IF('Model inputs'!B641="",0,1)),IF(IF('Model inputs'!B642="",0,1)="",0,IF('Model inputs'!B642="",0,1)),IF(IF('Model inputs'!B643="",0,1)="",0,IF('Model inputs'!B643="",0,1)))=0,"",SUM('Model inputs'!B639,'Model inputs'!B640,'Model inputs'!B641,'Model inputs'!B642,'Model inputs'!B643)) -> 20255.25 | K88: =IF(SUM(IF(IF('Model inputs'!B644="",0,1)="",0,IF('Model inputs'!B644="",0,1)),IF(IF('Model inputs'!B645="",0,1)="",0,IF('Model inputs'!B645="",0,1)),IF(IF('Model inputs'!B646="",0,1)="",0,IF('Model inputs'!B646="",0,1)),IF(IF('Model inputs'!B647="",0,1)="",0,IF('Model inputs'!B647="",0,1)),IF(IF('Model inputs'!B648="",0,1)="",0,IF('Model inputs'!B648="",0,1)))=0,"",SUM('Model inputs'!B644,'Model inputs'!B645,'Model inputs'!B646,'Model inputs'!B647,'Model inputs'!B648)) -> 20255.25 | L88: =IF(SUM(IF(IF('Model inputs'!B649="",0,1)="",0,IF('Model inputs'!B649="",0,1)),IF(IF('Model inputs'!B650="",0,1)="",0,IF('Model inputs'!B650="",0,1)),IF(IF('Model inputs'!B651="",0,1)="",0,IF('Model inputs'!B651="",0,1)),IF(IF('Model inputs'!B652="",0,1)="",0,IF('Model inputs'!B652="",0,1)),IF(IF('Model inputs'!B653="",0,1)="",0,IF('Model inputs'!B653="",0,1)))=0,"",SUM('Model inputs'!B649,'Model inputs'!B650,'Model inputs'!B651,'Model inputs'!B652,'Model inputs'!B653)) -> 20255.25 | M88: =IF(SUM(IF(IF('Model inputs'!B654="",0,1)="",0,IF('Model inputs'!B654="",0,1)),IF(IF('Model inputs'!B655="",0,1)="",0,IF('Model inputs'!B655="",0,1)),IF(IF('Model inputs'!B656="",0,1)="",0,IF('Model inputs'!B656="",0,1)),IF(IF('Model inputs'!B657="",0,1)="",0,IF('Model inputs'!B657="",0,1)),IF(IF('Model inputs'!B658="",0,1)="",0,IF('Model inputs'!B658="",0,1)))=0,"",SUM('Model inputs'!B654,'Model inputs'!B655,'Model inputs'!B656,'Model inputs'!B657,'Model inputs'!B658)) -> 20255.25
A89: Plan Operating profit | B89: =IF(SUM(IF(IF('Model inputs'!B659="",0,1)="",0,IF('Model inputs'!B659="",0,1)),IF(IF('Model inputs'!B660="",0,1)="",0,IF('Model inputs'!B660="",0,1)),IF(IF('Model inputs'!B661="",0,1)="",0,IF('Model inputs'!B661="",0,1)),IF(IF('Model inputs'!B662="",0,1)="",0,IF('Model inputs'!B662="",0,1)),IF(IF('Model inputs'!B663="",0,1)="",0,IF('Model inputs'!B663="",0,1)))=0,"",SUM('Model inputs'!B659,'Model inputs'!B660,'Model inputs'!B661,'Model inputs'!B662,'Model inputs'!B663)) -> 19505.25 | C89: =IF(SUM(IF(IF('Model inputs'!B664="",0,1)="",0,IF('Model inputs'!B664="",0,1)),IF(IF('Model inputs'!B665="",0,1)="",0,IF('Model inputs'!B665="",0,1)),IF(IF('Model inputs'!B666="",0,1)="",0,IF('Model inputs'!B666="",0,1)),IF(IF('Model inputs'!B667="",0,1)="",0,IF('Model inputs'!B667="",0,1)),IF(IF('Model inputs'!B668="",0,1)="",0,IF('Model inputs'!B668="",0,1)))=0,"",SUM('Model inputs'!B664,'Model inputs'!B665,'Model inputs'!B666,'Model inputs'!B667,'Model inputs'!B668)) -> 19505.25 | D89: =IF(SUM(IF(IF('Model inputs'!B669="",0,1)="",0,IF('Model inputs'!B669="",0,1)),IF(IF('Model inputs'!B670="",0,1)="",0,IF('Model inputs'!B670="",0,1)),IF(IF('Model inputs'!B671="",0,1)="",0,IF('Model inputs'!B671="",0,1)),IF(IF('Model inputs'!B672="",0,1)="",0,IF('Model inputs'!B672="",0,1)),IF(IF('Model inputs'!B673="",0,1)="",0,IF('Model inputs'!B673="",0,1)))=0,"",SUM('Model inputs'!B669,'Model inputs'!B670,'Model inputs'!B671,'Model inputs'!B672,'Model inputs'!B673)) -> 19505.25 | E89: =IF(SUM(IF(IF('Model inputs'!B674="",0,1)="",0,IF('Model inputs'!B674="",0,1)),IF(IF('Model inputs'!B675="",0,1)="",0,IF('Model inputs'!B675="",0,1)),IF(IF('Model inputs'!B676="",0,1)="",0,IF('Model inputs'!B676="",0,1)),IF(IF('Model inputs'!B677="",0,1)="",0,IF('Model inputs'!B677="",0,1)),IF(IF('Model inputs'!B678="",0,1)="",0,IF('Model inputs'!B678="",0,1)))=0,"",SUM('Model inputs'!B674,'Model inputs'!B675,'Model inputs'!B676,'Model inputs'!B677,'Model inputs'!B678)) -> 19505.25 | F89: =IF(SUM(IF(IF('Model inputs'!B679="",0,1)="",0,IF('Model inputs'!B679="",0,1)),IF(IF('Model inputs'!B680="",0,1)="",0,IF('Model inputs'!B680="",0,1)),IF(IF('Model inputs'!B681="",0,1)="",0,IF('Model inputs'!B681="",0,1)),IF(IF('Model inputs'!B682="",0,1)="",0,IF('Model inputs'!B682="",0,1)),IF(IF('Model inputs'!B683="",0,1)="",0,IF('Model inputs'!B683="",0,1)))=0,"",SUM('Model inputs'!B679,'Model inputs'!B680,'Model inputs'!B681,'Model inputs'!B682,'Model inputs'!B683)) -> 19505.25 | G89: =IF(SUM(IF(IF('Model inputs'!B684="",0,1)="",0,IF('Model inputs'!B684="",0,1)),IF(IF('Model inputs'!B685="",0,1)="",0,IF('Model inputs'!B685="",0,1)),IF(IF('Model inputs'!B686="",0,1)="",0,IF('Model inputs'!B686="",0,1)),IF(IF('Model inputs'!B687="",0,1)="",0,IF('Model inputs'!B687="",0,1)),IF(IF('Model inputs'!B688="",0,1)="",0,IF('Model inputs'!B688="",0,1)))=0,"",SUM('Model inputs'!B684,'Model inputs'!B685,'Model inputs'!B686,'Model inputs'!B687,'Model inputs'!B688)) -> 19005.25 | H89: =IF(SUM(IF(IF('Model inputs'!B689="",0,1)="",0,IF('Model inputs'!B689="",0,1)),IF(IF('Model inputs'!B690="",0,1)="",0,IF('Model inputs'!B690="",0,1)),IF(IF('Model inputs'!B691="",0,1)="",0,IF('Model inputs'!B691="",0,1)),IF(IF('Model inputs'!B692="",0,1)="",0,IF('Model inputs'!B692="",0,1)),IF(IF('Model inputs'!B693="",0,1)="",0,IF('Model inputs'!B693="",0,1)))=0,"",SUM('Model inputs'!B689,'Model inputs'!B690,'Model inputs'!B691,'Model inputs'!B692,'Model inputs'!B693)) -> 19005.25 | I89: =IF(SUM(IF(IF('Model inputs'!B694="",0,1)="",0,IF('Model inputs'!B694="",0,1)),IF(IF('Model inputs'!B695="",0,1)="",0,IF('Model inputs'!B695="",0,1)),IF(IF('Model inputs'!B696="",0,1)="",0,IF('Model inputs'!B696="",0,1)),IF(IF('Model inputs'!B697="",0,1)="",0,IF('Model inputs'!B697="",0,1)),IF(IF('Model inputs'!B698="",0,1)="",0,IF('Model inputs'!B698="",0,1)))=0,"",SUM('Model inputs'!B694,'Model inputs'!B695,'Model inputs'!B696,'Model inputs'!B697,'Model inputs'!B698)) -> 19005.25 | J89: =IF(SUM(IF(IF('Model inputs'!B699="",0,1)="",0,IF('Model inputs'!B699="",0,1)),IF(IF('Model inputs'!B700="",0,1)="",0,IF('Model inputs'!B700="",0,1)),IF(IF('Model inputs'!B701="",0,1)="",0,IF('Model inputs'!B701="",0,1)),IF(IF('Model inputs'!B702="",0,1)="",0,IF('Model inputs'!B702="",0,1)),IF(IF('Model inputs'!B703="",0,1)="",0,IF('Model inputs'!B703="",0,1)))=0,"",SUM('Model inputs'!B699,'Model inputs'!B700,'Model inputs'!B701,'Model inputs'!B702,'Model inputs'!B703)) -> 19005.25 | K89: =IF(SUM(IF(IF('Model inputs'!B704="",0,1)="",0,IF('Model inputs'!B704="",0,1)),IF(IF('Model inputs'!B705="",0,1)="",0,IF('Model inputs'!B705="",0,1)),IF(IF('Model inputs'!B706="",0,1)="",0,IF('Model inputs'!B706="",0,1)),IF(IF('Model inputs'!B707="",0,1)="",0,IF('Model inputs'!B707="",0,1)),IF(IF('Model inputs'!B708="",0,1)="",0,IF('Model inputs'!B708="",0,1)))=0,"",SUM('Model inputs'!B704,'Model inputs'!B705,'Model inputs'!B706,'Model inputs'!B707,'Model inputs'!B708)) -> 19005.25 | L89: =IF(SUM(IF(IF('Model inputs'!B709="",0,1)="",0,IF('Model inputs'!B709="",0,1)),IF(IF('Model inputs'!B710="",0,1)="",0,IF('Model inputs'!B710="",0,1)),IF(IF('Model inputs'!B711="",0,1)="",0,IF('Model inputs'!B711="",0,1)),IF(IF('Model inputs'!B712="",0,1)="",0,IF('Model inputs'!B712="",0,1)),IF(IF('Model inputs'!B713="",0,1)="",0,IF('Model inputs'!B713="",0,1)))=0,"",SUM('Model inputs'!B709,'Model inputs'!B710,'Model inputs'!B711,'Model inputs'!B712,'Model inputs'!B713)) -> 19005.25 | M89: =IF(SUM(IF(IF('Model inputs'!B714="",0,1)="",0,IF('Model inputs'!B714="",0,1)),IF(IF('Model inputs'!B715="",0,1)="",0,IF('Model inputs'!B715="",0,1)),IF(IF('Model inputs'!B716="",0,1)="",0,IF('Model inputs'!B716="",0,1)),IF(IF('Model inputs'!B717="",0,1)="",0,IF('Model inputs'!B717="",0,1)),IF(IF('Model inputs'!B718="",0,1)="",0,IF('Model inputs'!B718="",0,1)))=0,"",SUM('Model inputs'!B714,'Model inputs'!B715,'Model inputs'!B716,'Model inputs'!B717,'Model inputs'!B718)) -> 19005.25
A90: Plan Net cash burn | B90: =IF(SUM(IF(IF('Model inputs'!B719="",0,1)="",0,IF('Model inputs'!B719="",0,1)),IF(IF('Model inputs'!B720="",0,1)="",0,IF('Model inputs'!B720="",0,1)),IF(IF('Model inputs'!B721="",0,1)="",0,IF('Model inputs'!B721="",0,1)),IF(IF('Model inputs'!B722="",0,1)="",0,IF('Model inputs'!B722="",0,1)),IF(IF('Model inputs'!B723="",0,1)="",0,IF('Model inputs'!B723="",0,1)))=0,"",SUM('Model inputs'!B719,'Model inputs'!B720,'Model inputs'!B721,'Model inputs'!B722,'Model inputs'!B723)) -> -19505.25 | C90: =IF(SUM(IF(IF('Model inputs'!B724="",0,1)="",0,IF('Model inputs'!B724="",0,1)),IF(IF('Model inputs'!B725="",0,1)="",0,IF('Model inputs'!B725="",0,1)),IF(IF('Model inputs'!B726="",0,1)="",0,IF('Model inputs'!B726="",0,1)),IF(IF('Model inputs'!B727="",0,1)="",0,IF('Model inputs'!B727="",0,1)),IF(IF('Model inputs'!B728="",0,1)="",0,IF('Model inputs'!B728="",0,1)))=0,"",SUM('Model inputs'!B724,'Model inputs'!B725,'Model inputs'!B726,'Model inputs'!B727,'Model inputs'!B728)) -> -19505.25 | D90: =IF(SUM(IF(IF('Model inputs'!B729="",0,1)="",0,IF('Model inputs'!B729="",0,1)),IF(IF('Model inputs'!B730="",0,1)="",0,IF('Model inputs'!B730="",0,1)),IF(IF('Model inputs'!B731="",0,1)="",0,IF('Model inputs'!B731="",0,1)),IF(IF('Model inputs'!B732="",0,1)="",0,IF('Model inputs'!B732="",0,1)),IF(IF('Model inputs'!B733="",0,1)="",0,IF('Model inputs'!B733="",0,1)))=0,"",SUM('Model inputs'!B729,'Model inputs'!B730,'Model inputs'!B731,'Model inputs'!B732,'Model inputs'!B733)) -> -19505.25 | E90: =IF(SUM(IF(IF('Model inputs'!B734="",0,1)="",0,IF('Model inputs'!B734="",0,1)),IF(IF('Model inputs'!B735="",0,1)="",0,IF('Model inputs'!B735="",0,1)),IF(IF('Model inputs'!B736="",0,1)="",0,IF('Model inputs'!B736="",0,1)),IF(IF('Model inputs'!B737="",0,1)="",0,IF('Model inputs'!B737="",0,1)),IF(IF('Model inputs'!B738="",0,1)="",0,IF('Model inputs'!B738="",0,1)))=0,"",SUM('Model inputs'!B734,'Model inputs'!B735,'Model inputs'!B736,'Model inputs'!B737,'Model inputs'!B738)) -> -19505.25 | F90: =IF(SUM(IF(IF('Model inputs'!B739="",0,1)="",0,IF('Model inputs'!B739="",0,1)),IF(IF('Model inputs'!B740="",0,1)="",0,IF('Model inputs'!B740="",0,1)),IF(IF('Model inputs'!B741="",0,1)="",0,IF('Model inputs'!B741="",0,1)),IF(IF('Model inputs'!B742="",0,1)="",0,IF('Model inputs'!B742="",0,1)),IF(IF('Model inputs'!B743="",0,1)="",0,IF('Model inputs'!B743="",0,1)))=0,"",SUM('Model inputs'!B739,'Model inputs'!B740,'Model inputs'!B741,'Model inputs'!B742,'Model inputs'!B743)) -> -19505.25 | G90: =IF(SUM(IF(IF('Model inputs'!B744="",0,1)="",0,IF('Model inputs'!B744="",0,1)),IF(IF('Model inputs'!B745="",0,1)="",0,IF('Model inputs'!B745="",0,1)),IF(IF('Model inputs'!B746="",0,1)="",0,IF('Model inputs'!B746="",0,1)),IF(IF('Model inputs'!B747="",0,1)="",0,IF('Model inputs'!B747="",0,1)),IF(IF('Model inputs'!B748="",0,1)="",0,IF('Model inputs'!B748="",0,1)))=0,"",SUM('Model inputs'!B744,'Model inputs'!B745,'Model inputs'!B746,'Model inputs'!B747,'Model inputs'!B748)) -> -19005.25 | H90: =IF(SUM(IF(IF('Model inputs'!B749="",0,1)="",0,IF('Model inputs'!B749="",0,1)),IF(IF('Model inputs'!B750="",0,1)="",0,IF('Model inputs'!B750="",0,1)),IF(IF('Model inputs'!B751="",0,1)="",0,IF('Model inputs'!B751="",0,1)),IF(IF('Model inputs'!B752="",0,1)="",0,IF('Model inputs'!B752="",0,1)),IF(IF('Model inputs'!B753="",0,1)="",0,IF('Model inputs'!B753="",0,1)))=0,"",SUM('Model inputs'!B749,'Model inputs'!B750,'Model inputs'!B751,'Model inputs'!B752,'Model inputs'!B753)) -> -19005.25 | I90: =IF(SUM(IF(IF('Model inputs'!B754="",0,1)="",0,IF('Model inputs'!B754="",0,1)),IF(IF('Model inputs'!B755="",0,1)="",0,IF('Model inputs'!B755="",0,1)),IF(IF('Model inputs'!B756="",0,1)="",0,IF('Model inputs'!B756="",0,1)),IF(IF('Model inputs'!B757="",0,1)="",0,IF('Model inputs'!B757="",0,1)),IF(IF('Model inputs'!B758="",0,1)="",0,IF('Model inputs'!B758="",0,1)))=0,"",SUM('Model inputs'!B754,'Model inputs'!B755,'Model inputs'!B756,'Model inputs'!B757,'Model inputs'!B758)) -> -19005.25 | J90: =IF(SUM(IF(IF('Model inputs'!B759="",0,1)="",0,IF('Model inputs'!B759="",0,1)),IF(IF('Model inputs'!B760="",0,1)="",0,IF('Model inputs'!B760="",0,1)),IF(IF('Model inputs'!B761="",0,1)="",0,IF('Model inputs'!B761="",0,1)),IF(IF('Model inputs'!B762="",0,1)="",0,IF('Model inputs'!B762="",0,1)),IF(IF('Model inputs'!B763="",0,1)="",0,IF('Model inputs'!B763="",0,1)))=0,"",SUM('Model inputs'!B759,'Model inputs'!B760,'Model inputs'!B761,'Model inputs'!B762,'Model inputs'!B763)) -> -19005.25 | K90: =IF(SUM(IF(IF('Model inputs'!B764="",0,1)="",0,IF('Model inputs'!B764="",0,1)),IF(IF('Model inputs'!B765="",0,1)="",0,IF('Model inputs'!B765="",0,1)),IF(IF('Model inputs'!B766="",0,1)="",0,IF('Model inputs'!B766="",0,1)),IF(IF('Model inputs'!B767="",0,1)="",0,IF('Model inputs'!B767="",0,1)),IF(IF('Model inputs'!B768="",0,1)="",0,IF('Model inputs'!B768="",0,1)))=0,"",SUM('Model inputs'!B764,'Model inputs'!B765,'Model inputs'!B766,'Model inputs'!B767,'Model inputs'!B768)) -> -19005.25 | L90: =IF(SUM(IF(IF('Model inputs'!B769="",0,1)="",0,IF('Model inputs'!B769="",0,1)),IF(IF('Model inputs'!B770="",0,1)="",0,IF('Model inputs'!B770="",0,1)),IF(IF('Model inputs'!B771="",0,1)="",0,IF('Model inputs'!B771="",0,1)),IF(IF('Model inputs'!B772="",0,1)="",0,IF('Model inputs'!B772="",0,1)),IF(IF('Model inputs'!B773="",0,1)="",0,IF('Model inputs'!B773="",0,1)))=0,"",SUM('Model inputs'!B769,'Model inputs'!B770,'Model inputs'!B771,'Model inputs'!B772,'Model inputs'!B773)) -> -19005.25 | M90: =IF(SUM(IF(IF('Model inputs'!B774="",0,1)="",0,IF('Model inputs'!B774="",0,1)),IF(IF('Model inputs'!B775="",0,1)="",0,IF('Model inputs'!B775="",0,1)),IF(IF('Model inputs'!B776="",0,1)="",0,IF('Model inputs'!B776="",0,1)),IF(IF('Model inputs'!B777="",0,1)="",0,IF('Model inputs'!B777="",0,1)),IF(IF('Model inputs'!B778="",0,1)="",0,IF('Model inputs'!B778="",0,1)))=0,"",SUM('Model inputs'!B774,'Model inputs'!B775,'Model inputs'!B776,'Model inputs'!B777,'Model inputs'!B778)) -> -19005.25
A91: Plan Gross margin by pricing | B91: =IF(SUM(IF(IF('Model inputs'!B779="",0,1)="",0,IF('Model inputs'!B779="",0,1)),IF(IF('Model inputs'!B780="",0,1)="",0,IF('Model inputs'!B780="",0,1)),IF(IF('Model inputs'!B781="",0,1)="",0,IF('Model inputs'!B781="",0,1)),IF(IF('Model inputs'!B782="",0,1)="",0,IF('Model inputs'!B782="",0,1)),IF(IF('Model inputs'!B783="",0,1)="",0,IF('Model inputs'!B783="",0,1)))=0,"",SUM('Model inputs'!B779,'Model inputs'!B780,'Model inputs'!B781,'Model inputs'!B782,'Model inputs'!B783)) -> 0.9369 | C91: =IF(SUM(IF(IF('Model inputs'!B784="",0,1)="",0,IF('Model inputs'!B784="",0,1)),IF(IF('Model inputs'!B785="",0,1)="",0,IF('Model inputs'!B785="",0,1)),IF(IF('Model inputs'!B786="",0,1)="",0,IF('Model inputs'!B786="",0,1)),IF(IF('Model inputs'!B787="",0,1)="",0,IF('Model inputs'!B787="",0,1)),IF(IF('Model inputs'!B788="",0,1)="",0,IF('Model inputs'!B788="",0,1)))=0,"",SUM('Model inputs'!B784,'Model inputs'!B785,'Model inputs'!B786,'Model inputs'!B787,'Model inputs'!B788)) -> 0.9369 | D91: =IF(SUM(IF(IF('Model inputs'!B789="",0,1)="",0,IF('Model inputs'!B789="",0,1)),IF(IF('Model inputs'!B790="",0,1)="",0,IF('Model inputs'!B790="",0,1)),IF(IF('Model inputs'!B791="",0,1)="",0,IF('Model inputs'!B791="",0,1)),IF(IF('Model inputs'!B792="",0,1)="",0,IF('Model inputs'!B792="",0,1)),IF(IF('Model inputs'!B793="",0,1)="",0,IF('Model inputs'!B793="",0,1)))=0,"",SUM('Model inputs'!B789,'Model inputs'!B790,'Model inputs'!B791,'Model inputs'!B792,'Model inputs'!B793)) -> 0.9369 | E91: =IF(SUM(IF(IF('Model inputs'!B794="",0,1)="",0,IF('Model inputs'!B794="",0,1)),IF(IF('Model inputs'!B795="",0,1)="",0,IF('Model inputs'!B795="",0,1)),IF(IF('Model inputs'!B796="",0,1)="",0,IF('Model inputs'!B796="",0,1)),IF(IF('Model inputs'!B797="",0,1)="",0,IF('Model inputs'!B797="",0,1)),IF(IF('Model inputs'!B798="",0,1)="",0,IF('Model inputs'!B798="",0,1)))=0,"",SUM('Model inputs'!B794,'Model inputs'!B795,'Model inputs'!B796,'Model inputs'!B797,'Model inputs'!B798)) -> 0.9369 | F91: =IF(SUM(IF(IF('Model inputs'!B799="",0,1)="",0,IF('Model inputs'!B799="",0,1)),IF(IF('Model inputs'!B800="",0,1)="",0,IF('Model inputs'!B800="",0,1)),IF(IF('Model inputs'!B801="",0,1)="",0,IF('Model inputs'!B801="",0,1)),IF(IF('Model inputs'!B802="",0,1)="",0,IF('Model inputs'!B802="",0,1)),IF(IF('Model inputs'!B803="",0,1)="",0,IF('Model inputs'!B803="",0,1)))=0,"",SUM('Model inputs'!B799,'Model inputs'!B800,'Model inputs'!B801,'Model inputs'!B802,'Model inputs'!B803)) -> 0.9369 | G91: =IF(SUM(IF(IF('Model inputs'!B804="",0,1)="",0,IF('Model inputs'!B804="",0,1)),IF(IF('Model inputs'!B805="",0,1)="",0,IF('Model inputs'!B805="",0,1)),IF(IF('Model inputs'!B806="",0,1)="",0,IF('Model inputs'!B806="",0,1)),IF(IF('Model inputs'!B807="",0,1)="",0,IF('Model inputs'!B807="",0,1)),IF(IF('Model inputs'!B808="",0,1)="",0,IF('Model inputs'!B808="",0,1)))=0,"",SUM('Model inputs'!B804,'Model inputs'!B805,'Model inputs'!B806,'Model inputs'!B807,'Model inputs'!B808)) -> 0.9369 | H91: =IF(SUM(IF(IF('Model inputs'!B809="",0,1)="",0,IF('Model inputs'!B809="",0,1)),IF(IF('Model inputs'!B810="",0,1)="",0,IF('Model inputs'!B810="",0,1)),IF(IF('Model inputs'!B811="",0,1)="",0,IF('Model inputs'!B811="",0,1)),IF(IF('Model inputs'!B812="",0,1)="",0,IF('Model inputs'!B812="",0,1)),IF(IF('Model inputs'!B813="",0,1)="",0,IF('Model inputs'!B813="",0,1)))=0,"",SUM('Model inputs'!B809,'Model inputs'!B810,'Model inputs'!B811,'Model inputs'!B812,'Model inputs'!B813)) -> 0.9369 | I91: =IF(SUM(IF(IF('Model inputs'!B814="",0,1)="",0,IF('Model inputs'!B814="",0,1)),IF(IF('Model inputs'!B815="",0,1)="",0,IF('Model inputs'!B815="",0,1)),IF(IF('Model inputs'!B816="",0,1)="",0,IF('Model inputs'!B816="",0,1)),IF(IF('Model inputs'!B817="",0,1)="",0,IF('Model inputs'!B817="",0,1)),IF(IF('Model inputs'!B818="",0,1)="",0,IF('Model inputs'!B818="",0,1)))=0,"",SUM('Model inputs'!B814,'Model inputs'!B815,'Model inputs'!B816,'Model inputs'!B817,'Model inputs'!B818)) -> 0.9369 | J91: =IF(SUM(IF(IF('Model inputs'!B819="",0,1)="",0,IF('Model inputs'!B819="",0,1)),IF(IF('Model inputs'!B820="",0,1)="",0,IF('Model inputs'!B820="",0,1)),IF(IF('Model inputs'!B821="",0,1)="",0,IF('Model inputs'!B821="",0,1)),IF(IF('Model inputs'!B822="",0,1)="",0,IF('Model inputs'!B822="",0,1)),IF(IF('Model inputs'!B823="",0,1)="",0,IF('Model inputs'!B823="",0,1)))=0,"",SUM('Model inputs'!B819,'Model inputs'!B820,'Model inputs'!B821,'Model inputs'!B822,'Model inputs'!B823)) -> 0.9369 | K91: =IF(SUM(IF(IF('Model inputs'!B824="",0,1)="",0,IF('Model inputs'!B824="",0,1)),IF(IF('Model inputs'!B825="",0,1)="",0,IF('Model inputs'!B825="",0,1)),IF(IF('Model inputs'!B826="",0,1)="",0,IF('Model inputs'!B826="",0,1)),IF(IF('Model inputs'!B827="",0,1)="",0,IF('Model inputs'!B827="",0,1)),IF(IF('Model inputs'!B828="",0,1)="",0,IF('Model inputs'!B828="",0,1)))=0,"",SUM('Model inputs'!B824,'Model inputs'!B825,'Model inputs'!B826,'Model inputs'!B827,'Model inputs'!B828)) -> 0.9369 | L91: =IF(SUM(IF(IF('Model inputs'!B829="",0,1)="",0,IF('Model inputs'!B829="",0,1)),IF(IF('Model inputs'!B830="",0,1)="",0,IF('Model inputs'!B830="",0,1)),IF(IF('Model inputs'!B831="",0,1)="",0,IF('Model inputs'!B831="",0,1)),IF(IF('Model inputs'!B832="",0,1)="",0,IF('Model inputs'!B832="",0,1)),IF(IF('Model inputs'!B833="",0,1)="",0,IF('Model inputs'!B833="",0,1)))=0,"",SUM('Model inputs'!B829,'Model inputs'!B830,'Model inputs'!B831,'Model inputs'!B832,'Model inputs'!B833)) -> 0.9369 | M91: =IF(SUM(IF(IF('Model inputs'!B834="",0,1)="",0,IF('Model inputs'!B834="",0,1)),IF(IF('Model inputs'!B835="",0,1)="",0,IF('Model inputs'!B835="",0,1)),IF(IF('Model inputs'!B836="",0,1)="",0,IF('Model inputs'!B836="",0,1)),IF(IF('Model inputs'!B837="",0,1)="",0,IF('Model inputs'!B837="",0,1)),IF(IF('Model inputs'!B838="",0,1)="",0,IF('Model inputs'!B838="",0,1)))=0,"",SUM('Model inputs'!B834,'Model inputs'!B835,'Model inputs'!B836,'Model inputs'!B837,'Model inputs'!B838)) -> 0.9369
A92: Plan Contribution margin by pricing | B92: =IF(SUM(IF(IF('Model inputs'!B839="",0,1)="",0,IF('Model inputs'!B839="",0,1)),IF(IF('Model inputs'!B840="",0,1)="",0,IF('Model inputs'!B840="",0,1)),IF(IF('Model inputs'!B841="",0,1)="",0,IF('Model inputs'!B841="",0,1)),IF(IF('Model inputs'!B842="",0,1)="",0,IF('Model inputs'!B842="",0,1)),IF(IF('Model inputs'!B843="",0,1)="",0,IF('Model inputs'!B843="",0,1)))=0,"",SUM('Model inputs'!B839,'Model inputs'!B840,'Model inputs'!B841,'Model inputs'!B842,'Model inputs'!B843)) -> 0.90023333 | C92: =IF(SUM(IF(IF('Model inputs'!B844="",0,1)="",0,IF('Model inputs'!B844="",0,1)),IF(IF('Model inputs'!B845="",0,1)="",0,IF('Model inputs'!B845="",0,1)),IF(IF('Model inputs'!B846="",0,1)="",0,IF('Model inputs'!B846="",0,1)),IF(IF('Model inputs'!B847="",0,1)="",0,IF('Model inputs'!B847="",0,1)),IF(IF('Model inputs'!B848="",0,1)="",0,IF('Model inputs'!B848="",0,1)))=0,"",SUM('Model inputs'!B844,'Model inputs'!B845,'Model inputs'!B846,'Model inputs'!B847,'Model inputs'!B848)) -> 0.90023333 | D92: =IF(SUM(IF(IF('Model inputs'!B849="",0,1)="",0,IF('Model inputs'!B849="",0,1)),IF(IF('Model inputs'!B850="",0,1)="",0,IF('Model inputs'!B850="",0,1)),IF(IF('Model inputs'!B851="",0,1)="",0,IF('Model inputs'!B851="",0,1)),IF(IF('Model inputs'!B852="",0,1)="",0,IF('Model inputs'!B852="",0,1)),IF(IF('Model inputs'!B853="",0,1)="",0,IF('Model inputs'!B853="",0,1)))=0,"",SUM('Model inputs'!B849,'Model inputs'!B850,'Model inputs'!B851,'Model inputs'!B852,'Model inputs'!B853)) -> 0.90023333 | E92: =IF(SUM(IF(IF('Model inputs'!B854="",0,1)="",0,IF('Model inputs'!B854="",0,1)),IF(IF('Model inputs'!B855="",0,1)="",0,IF('Model inputs'!B855="",0,1)),IF(IF('Model inputs'!B856="",0,1)="",0,IF('Model inputs'!B856="",0,1)),IF(IF('Model inputs'!B857="",0,1)="",0,IF('Model inputs'!B857="",0,1)),IF(IF('Model inputs'!B858="",0,1)="",0,IF('Model inputs'!B858="",0,1)))=0,"",SUM('Model inputs'!B854,'Model inputs'!B855,'Model inputs'!B856,'Model inputs'!B857,'Model inputs'!B858)) -> 0.90023333 | F92: =IF(SUM(IF(IF('Model inputs'!B859="",0,1)="",0,IF('Model inputs'!B859="",0,1)),IF(IF('Model inputs'!B860="",0,1)="",0,IF('Model inputs'!B860="",0,1)),IF(IF('Model inputs'!B861="",0,1)="",0,IF('Model inputs'!B861="",0,1)),IF(IF('Model inputs'!B862="",0,1)="",0,IF('Model inputs'!B862="",0,1)),IF(IF('Model inputs'!B863="",0,1)="",0,IF('Model inputs'!B863="",0,1)))=0,"",SUM('Model inputs'!B859,'Model inputs'!B860,'Model inputs'!B861,'Model inputs'!B862,'Model inputs'!B863)) -> 0.90023333 | G92: =IF(SUM(IF(IF('Model inputs'!B864="",0,1)="",0,IF('Model inputs'!B864="",0,1)),IF(IF('Model inputs'!B865="",0,1)="",0,IF('Model inputs'!B865="",0,1)),IF(IF('Model inputs'!B866="",0,1)="",0,IF('Model inputs'!B866="",0,1)),IF(IF('Model inputs'!B867="",0,1)="",0,IF('Model inputs'!B867="",0,1)),IF(IF('Model inputs'!B868="",0,1)="",0,IF('Model inputs'!B868="",0,1)))=0,"",SUM('Model inputs'!B864,'Model inputs'!B865,'Model inputs'!B866,'Model inputs'!B867,'Model inputs'!B868)) -> 0.90023333 | H92: =IF(SUM(IF(IF('Model inputs'!B869="",0,1)="",0,IF('Model inputs'!B869="",0,1)),IF(IF('Model inputs'!B870="",0,1)="",0,IF('Model inputs'!B870="",0,1)),IF(IF('Model inputs'!B871="",0,1)="",0,IF('Model inputs'!B871="",0,1)),IF(IF('Model inputs'!B872="",0,1)="",0,IF('Model inputs'!B872="",0,1)),IF(IF('Model inputs'!B873="",0,1)="",0,IF('Model inputs'!B873="",0,1)))=0,"",SUM('Model inputs'!B869,'Model inputs'!B870,'Model inputs'!B871,'Model inputs'!B872,'Model inputs'!B873)) -> 0.90023333 | I92: =IF(SUM(IF(IF('Model inputs'!B874="",0,1)="",0,IF('Model inputs'!B874="",0,1)),IF(IF('Model inputs'!B875="",0,1)="",0,IF('Model inputs'!B875="",0,1)),IF(IF('Model inputs'!B876="",0,1)="",0,IF('Model inputs'!B876="",0,1)),IF(IF('Model inputs'!B877="",0,1)="",0,IF('Model inputs'!B877="",0,1)),IF(IF('Model inputs'!B878="",0,1)="",0,IF('Model inputs'!B878="",0,1)))=0,"",SUM('Model inputs'!B874,'Model inputs'!B875,'Model inputs'!B876,'Model inputs'!B877,'Model inputs'!B878)) -> 0.90023333 | J92: =IF(SUM(IF(IF('Model inputs'!B879="",0,1)="",0,IF('Model inputs'!B879="",0,1)),IF(IF('Model inputs'!B880="",0,1)="",0,IF('Model inputs'!B880="",0,1)),IF(IF('Model inputs'!B881="",0,1)="",0,IF('Model inputs'!B881="",0,1)),IF(IF('Model inputs'!B882="",0,1)="",0,IF('Model inputs'!B882="",0,1)),IF(IF('Model inputs'!B883="",0,1)="",0,IF('Model inputs'!B883="",0,1)))=0,"",SUM('Model inputs'!B879,'Model inputs'!B880,'Model inputs'!B881,'Model inputs'!B882,'Model inputs'!B883)) -> 0.90023333 | K92: =IF(SUM(IF(IF('Model inputs'!B884="",0,1)="",0,IF('Model inputs'!B884="",0,1)),IF(IF('Model inputs'!B885="",0,1)="",0,IF('Model inputs'!B885="",0,1)),IF(IF('Model inputs'!B886="",0,1)="",0,IF('Model inputs'!B886="",0,1)),IF(IF('Model inputs'!B887="",0,1)="",0,IF('Model inputs'!B887="",0,1)),IF(IF('Model inputs'!B888="",0,1)="",0,IF('Model inputs'!B888="",0,1)))=0,"",SUM('Model inputs'!B884,'Model inputs'!B885,'Model inputs'!B886,'Model inputs'!B887,'Model inputs'!B888)) -> 0.90023333 | L92: =IF(SUM(IF(IF('Model inputs'!B889="",0,1)="",0,IF('Model inputs'!B889="",0,1)),IF(IF('Model inputs'!B890="",0,1)="",0,IF('Model inputs'!B890="",0,1)),IF(IF('Model inputs'!B891="",0,1)="",0,IF('Model inputs'!B891="",0,1)),IF(IF('Model inputs'!B892="",0,1)="",0,IF('Model inputs'!B892="",0,1)),IF(IF('Model inputs'!B893="",0,1)="",0,IF('Model inputs'!B893="",0,1)))=0,"",SUM('Model inputs'!B889,'Model inputs'!B890,'Model inputs'!B891,'Model inputs'!B892,'Model inputs'!B893)) -> 0.90023333 | M92: =IF(SUM(IF(IF('Model inputs'!B894="",0,1)="",0,IF('Model inputs'!B894="",0,1)),IF(IF('Model inputs'!B895="",0,1)="",0,IF('Model inputs'!B895="",0,1)),IF(IF('Model inputs'!B896="",0,1)="",0,IF('Model inputs'!B896="",0,1)),IF(IF('Model inputs'!B897="",0,1)="",0,IF('Model inputs'!B897="",0,1)),IF(IF('Model inputs'!B898="",0,1)="",0,IF('Model inputs'!B898="",0,1)))=0,"",SUM('Model inputs'!B894,'Model inputs'!B895,'Model inputs'!B896,'Model inputs'!B897,'Model inputs'!B898)) -> 0.90023333
A93: Monthly operating burn | B93: =-'DealScope monthly model and pri'!B89 -> -19505.25 | C93: =-'DealScope monthly model and pri'!C89 -> -19505.25 | D93: =-'DealScope monthly model and pri'!D89 -> -19505.25 | E93: =-'DealScope monthly model and pri'!E89 -> -19505.25 | F93: =-'DealScope monthly model and pri'!F89 -> -19505.25 | G93: =-'DealScope monthly model and pri'!G89 -> -19005.25 | H93: =-'DealScope monthly model and pri'!H89 -> -19005.25 | I93: =-'DealScope monthly model and pri'!I89 -> -19005.25 | ... M93: =-'DealScope monthly model and pri'!M89 -> -19005.25
A94: Cumulative funding gap | B94: =MAX(IF(IF(IF(IF(ISERROR('DealScope monthly model and pri'!B5=1),'DealScope monthly model and pri'!B5=1,IF('DealScope monthly model and pri'!B5="","",'DealScope monthly model and pri'!B5=1))="",FALSE,IF(ISERROR('DealScope monthly model and pri'!B5=1),'DealScope monthly model and pri'!B5=1,IF('DealScope monthly model and pri'!B5="","",'DealScope monthly model and pri'!B5=1))),0,IF('Model inputs'!B29="","",'Model inputs'!B29))="",0,IF(IF(IF(ISERROR('DealScope monthly model and pri'!B5=1),'DealScope monthly model and pri'!B5=1,IF('DealScope monthly model and pri'!B5="","",'DealScope monthly model and pri'!B5=1))="",FALSE,IF(ISERROR('DealScope monthly model and pri'!B5=1),'DealScope monthly model and pri'!B5=1,IF('DealScope monthly model and pri'!B5="","",'DealScope monthly model and pri'!B5=1))),0,IF('Model inputs'!B29="","",'Model inputs'!B29)))+'DealScope monthly model and pri'!B90,0) -> 0 | C94: =MAX(IF(IF(IF(IF(ISERROR('DealScope monthly model and pri'!C5=1),'DealScope monthly model and pri'!C5=1,IF('DealScope monthly model and pri'!C5="","",'DealScope monthly model and pri'!C5=1))="",FALSE,IF(ISERROR('DealScope monthly model and pri'!C5=1),'DealScope monthly model and pri'!C5=1,IF('DealScope monthly model and pri'!C5="","",'DealScope monthly model and pri'!C5=1))),0,IF('DealScope monthly model and pri'!B95="","",'DealScope monthly model and pri'!B95))="",0,IF(IF(IF(ISERROR('DealScope monthly model and pri'!C5=1),'DealScope monthly model and pri'!C5=1,IF('DealScope monthly model and pri'!C5="","",'DealScope monthly model and pri'!C5=1))="",FALSE,IF(ISERROR('DealScope monthly model and pri'!C5=1),'DealScope monthly model and pri'!C5=1,IF('DealScope monthly model and pri'!C5="","",'DealScope monthly model and pri'!C5=1))),0,IF('DealScope monthly model and pri'!B95="","",'DealScope monthly model and pri'!B95)))+'DealScope monthly model and pri'!C90,0) -> 0 | D94: =MAX(IF(IF(IF(IF(ISERROR('DealScope monthly model and pri'!D5=1),'DealScope monthly model and pri'!D5=1,IF('DealScope monthly model and pri'!D5="","",'DealScope monthly model and pri'!D5=1))="",FALSE,IF(ISERROR('DealScope monthly model and pri'!D5=1),'DealScope monthly model and pri'!D5=1,IF('DealScope monthly model and pri'!D5="","",'DealScope monthly model and pri'!D5=1))),0,IF('DealScope monthly model and pri'!C95="","",'DealScope monthly model and pri'!C95))="",0,IF(IF(IF(ISERROR('DealScope monthly model and pri'!D5=1),'DealScope monthly model and pri'!D5=1,IF('DealScope monthly model and pri'!D5="","",'DealScope monthly model and pri'!D5=1))="",FALSE,IF(ISERROR('DealScope monthly model and pri'!D5=1),'DealScope monthly model and pri'!D5=1,IF('DealScope monthly model and pri'!D5="","",'DealScope monthly model and pri'!D5=1))),0,IF('DealScope monthly model and pri'!C95="","",'DealScope monthly model and pri'!C95)))+'DealScope monthly model and pri'!D90,0) -> 0 | E94: =MAX(IF(IF(IF(IF(ISERROR('DealScope monthly model and pri'!E5=1),'DealScope monthly model and pri'!E5=1,IF('DealScope monthly model and pri'!E5="","",'DealScope monthly model and pri'!E5=1))="",FALSE,IF(ISERROR('DealScope monthly model and pri'!E5=1),'DealScope monthly model and pri'!E5=1,IF('DealScope monthly model and pri'!E5="","",'DealScope monthly model and pri'!E5=1))),0,IF('DealScope monthly model and pri'!D95="","",'DealScope monthly model and pri'!D95))="",0,IF(IF(IF(ISERROR('DealScope monthly model and pri'!E5=1),'DealScope monthly model and pri'!E5=1,IF('DealScope monthly model and pri'!E5="","",'DealScope monthly model and pri'!E5=1))="",FALSE,IF(ISERROR('DealScope monthly model and pri'!E5=1),'DealScope monthly model and pri'!E5=1,IF('DealScope monthly model and pri'!E5="","",'DealScope monthly model and pri'!E5=1))),0,IF('DealScope monthly model and pri'!D95="","",'DealScope monthly model and pri'!D95)))+'DealScope monthly model and pri'!E90,0) -> 0 | F94: =MAX(IF(IF(IF(IF(ISERROR('DealScope monthly model and pri'!F5=1),'DealScope monthly model and pri'!F5=1,IF('DealScope monthly model and pri'!F5="","",'DealScope monthly model and pri'!F5=1))="",FALSE,IF(ISERROR('DealScope monthly model and pri'!F5=1),'DealScope monthly model and pri'!F5=1,IF('DealScope monthly model and pri'!F5="","",'DealScope monthly model and pri'!F5=1))),0,IF('DealScope monthly model and pri'!E95="","",'DealScope monthly model and pri'!E95))="",0,IF(IF(IF(ISERROR('DealScope monthly model and pri'!F5=1),'DealScope monthly model and pri'!F5=1,IF('DealScope monthly model and pri'!F5="","",'DealScope monthly model and pri'!F5=1))="",FALSE,IF(ISERROR('DealScope monthly model and pri'!F5=1),'DealScope monthly model and pri'!F5=1,IF('DealScope monthly model and pri'!F5="","",'DealScope monthly model and pri'!F5=1))),0,IF('DealScope monthly model and pri'!E95="","",'DealScope monthly model and pri'!E95)))+'DealScope monthly model and pri'!F90,0) -> 0 | G94: =MAX(IF(IF(IF(IF(ISERROR('DealScope monthly model and pri'!G5=1),'DealScope monthly model and pri'!G5=1,IF('DealScope monthly model and pri'!G5="","",'DealScope monthly model and pri'!G5=1))="",FALSE,IF(ISERROR('DealScope monthly model and pri'!G5=1),'DealScope monthly model and pri'!G5=1,IF('DealScope monthly model and pri'!G5="","",'DealScope monthly model and pri'!G5=1))),0,IF('DealScope monthly model and pri'!F95="","",'DealScope monthly model and pri'!F95))="",0,IF(IF(IF(ISERROR('DealScope monthly model and pri'!G5=1),'DealScope monthly model and pri'!G5=1,IF('DealScope monthly model and pri'!G5="","",'DealScope monthly model and pri'!G5=1))="",FALSE,IF(ISERROR('DealScope monthly model and pri'!G5=1),'DealScope monthly model and pri'!G5=1,IF('DealScope monthly model and pri'!G5="","",'DealScope monthly model and pri'!G5=1))),0,IF('DealScope monthly model and pri'!F95="","",'DealScope monthly model and pri'!F95)))+'DealScope monthly model and pri'!G90,0) -> 0 | H94: =MAX(IF(IF(IF(IF(ISERROR('DealScope monthly model and pri'!H5=1),'DealScope monthly model and pri'!H5=1,IF('DealScope monthly model and pri'!H5="","",'DealScope monthly model and pri'!H5=1))="",FALSE,IF(ISERROR('DealScope monthly model and pri'!H5=1),'DealScope monthly model and pri'!H5=1,IF('DealScope monthly model and pri'!H5="","",'DealScope monthly model and pri'!H5=1))),0,IF('DealScope monthly model and pri'!G95="","",'DealScope monthly model and pri'!G95))="",0,IF(IF(IF(ISERROR('DealScope monthly model and pri'!H5=1),'DealScope monthly model and pri'!H5=1,IF('DealScope monthly model and pri'!H5="","",'DealScope monthly model and pri'!H5=1))="",FALSE,IF(ISERROR('DealScope monthly model and pri'!H5=1),'DealScope monthly model and pri'!H5=1,IF('DealScope monthly model and pri'!H5="","",'DealScope monthly model and pri'!H5=1))),0,IF('DealScope monthly model and pri'!G95="","",'DealScope monthly model and pri'!G95)))+'DealScope monthly model and pri'!H90,0) -> 0 | I94: =MAX(IF(IF(IF(IF(ISERROR('DealScope monthly model and pri'!I5=1),'DealScope monthly model and pri'!I5=1,IF('DealScope monthly model and pri'!I5="","",'DealScope monthly model and pri'!I5=1))="",FALSE,IF(ISERROR('DealScope monthly model and pri'!I5=1),'DealScope monthly model and pri'!I5=1,IF('DealScope monthly model and pri'!I5="","",'DealScope monthly model and pri'!I5=1))),0,IF('DealScope monthly model and pri'!H95="","",'DealScope monthly model and pri'!H95))="",0,IF(IF(IF(ISERROR('DealScope monthly model and pri'!I5=1),'DealScope monthly model and pri'!I5=1,IF('DealScope monthly model and pri'!I5="","",'DealScope monthly model and pri'!I5=1))="",FALSE,IF(ISERROR('DealScope monthly model and pri'!I5=1),'DealScope monthly model and pri'!I5=1,IF('DealScope monthly model and pri'!I5="","",'DealScope monthly model and pri'!I5=1))),0,IF('DealScope monthly model and pri'!H95="","",'DealScope monthly model and pri'!H95)))+'DealScope monthly model and pri'!I90,0) -> 0 | J94: =MAX(IF(IF(IF(IF(ISERROR('DealScope monthly model and pri'!J5=1),'DealScope monthly model and pri'!J5=1,IF('DealScope monthly model and pri'!J5="","",'DealScope monthly model and pri'!J5=1))="",FALSE,IF(ISERROR('DealScope monthly model and pri'!J5=1),'DealScope monthly model and pri'!J5=1,IF('DealScope monthly model and pri'!J5="","",'DealScope monthly model and pri'!J5=1))),0,IF('DealScope monthly model and pri'!I95="","",'DealScope monthly model and pri'!I95))="",0,IF(IF(IF(ISERROR('DealScope monthly model and pri'!J5=1),'DealScope monthly model and pri'!J5=1,IF('DealScope monthly model and pri'!J5="","",'DealScope monthly model and pri'!J5=1))="",FALSE,IF(ISERROR('DealScope monthly model and pri'!J5=1),'DealScope monthly model and pri'!J5=1,IF('DealScope monthly model and pri'!J5="","",'DealScope monthly model and pri'!J5=1))),0,IF('DealScope monthly model and pri'!I95="","",'DealScope monthly model and pri'!I95)))+'DealScope monthly model and pri'!J90,0) -> 0 | ... M94: =MAX(IF(IF(IF(IF(ISERROR('DealScope monthly model and pri'!M5=1),'DealScope monthly model and pri'!M5=1,IF('DealScope monthly model and pri'!M5="","",'DealScope monthly model and pri'!M5=1))="",FALSE,IF(ISERROR('DealScope monthly model and pri'!M5=1),'DealScope monthly model and pri'!M5=1,IF('DealScope monthly model and pri'!M5="","",'DealScope monthly model and pri'!M5=1))),0,IF('DealScope monthly model and pri'!L95="","",'DealScope monthly model and pri'!L95))="",0,IF(IF(IF(ISERROR('DealScope monthly model and pri'!M5=1),'DealScope monthly model and pri'!M5=1,IF('DealScope monthly model and pri'!M5="","",'DealScope monthly model and pri'!M5=1))="",FALSE,IF(ISERROR('DealScope monthly model and pri'!M5=1),'DealScope monthly model and pri'!M5=1,IF('DealScope monthly model and pri'!M5="","",'DealScope monthly model and pri'!M5=1))),0,IF('DealScope monthly model and pri'!L95="","",'DealScope monthly model and pri'!L95)))+'DealScope monthly model and pri'!M90,0) -> 0
